Workbook

Sheet Recommendations
B2: Recommendations: model-weighted long/short portfolio (100% gross)
B5: Summary | H5: How the weights are set
C6: Long book | F6: 0.6 | H6: Universe: the 168 models with a valuation (DCF or rNPV). Net-cash and no-data tickers are left out.
C7: Short book | F7: -0.4 | H7: Liquidity: price at least $5 and market cap at least $1B, so micro-caps and penny stocks can't drive the book.
C8: Gross exposure | F8: 1 | H8: Signal: long if upside is +15% or more, short if -15% or less; upside clipped to +100% / -60%.
C9: Net exposure | F9: 0.2 | H9: Score = upside × model confidence × size factor. Confidence: reviewed or full DCF 1.0, rNPV 0.7, basic DCF 0.5, basic DCF with an operating loss today 0.25.
C10: Long positions | F10: 16 | H10: Size factor rises from 0.25 at $1B to 1.0 at $100B+ (log scale).
C11: Short positions | F11: 28 | H11: Books: 60% long / 40% short. Caps: 8% for $50B+, 6% for $10–50B, 4% for $3–10B, 2% for $1–3B; positions under 0.5% are dropped.
C12: Weighted upside, longs | F12: 0.42585775 | H12: Basic DCFs use GAAP margins and no pipeline, so they lean negative for acquisitive big pharma; that's why they get half weight.
C13: Weighted upside, shorts | F13: -0.50604108
C14: Valuation models in universe | F14: 168
C15: Positions after filters | F15: 44
B17: # | C17: Ticker | D17: Company | E17: Side | F17: Weight | G17: Model | H17: Value / share | I17: Price | J17: Upside | K17: Mkt cap ($B) | L17: Confidence | M17: Size factor | N17: Cap | O17: Score | P17: Live upside | Q17: Event | R17: Note(s)
C18: Longs
B19: 1 | C19: SNY | D19: Sanofi SA | E19: Long | F19: 0.08 | G19: Reviewed DCF | H19: 66.822469 | I19: 41.4 | J19: 0.61406931 | K19: 100.96856 | L19: 1 | M19: 1 | N19: 0.08 | O19: 0.61406931 | P19: =IFERROR(INDEX(Pharma!$K$3:$K$677,MATCH($C19,Pharma!$B$3:$B$677,0)),"") | Q19: =IFERROR(IF(INDEX(Pharma!$M$3:$M$677,MATCH($C19,Pharma!$B$3:$B$677,0))="","",INDEX(Pharma!$M$3:$M$677,MATCH($C19,Pharma!$B$3:$B$677,0))),"") | R19: =IFERROR(T(INDEX(Pharma!$N$3:$N$677,MATCH($C19,Pharma!$B$3:$B$677,0))),"")
B20: 2 | C20: GSK | D20: GSK plc | E20: Long | F20: 0.08 | G20: Reviewed DCF | H20: 66.386169 | I20: 50.645 | J20: 0.31081388 | K20: 109.27786 | L20: 1 | M20: 1 | N20: 0.08 | O20: 0.31081388 | P20: =IFERROR(INDEX(Pharma!$K$3:$K$677,MATCH($C20,Pharma!$B$3:$B$677,0)),"") | Q20: =IFERROR(IF(INDEX(Pharma!$M$3:$M$677,MATCH($C20,Pharma!$B$3:$B$677,0))="","",INDEX(Pharma!$M$3:$M$677,MATCH($C20,Pharma!$B$3:$B$677,0))),"") | R20: =IFERROR(T(INDEX(Pharma!$N$3:$N$677,MATCH($C20,Pharma!$B$3:$B$677,0))),"")
B21: 3 | C21: ZTS | D21: Zoetis Inc | E21: Long | F21: 0.06 | G21: Reviewed DCF | H21: 103.19817 | I21: 80.04 | J21: 0.28933251 | K21: 33.074417 | L21: 1 | M21: 0.81980957 | N21: 0.06 | O21: 0.23719756 | P21: =IFERROR(INDEX(Pharma!$K$3:$K$677,MATCH($C21,Pharma!$B$3:$B$677,0)),"") | Q21: =IFERROR(IF(INDEX(Pharma!$M$3:$M$677,MATCH($C21,Pharma!$B$3:$B$677,0))="","",INDEX(Pharma!$M$3:$M$677,MATCH($C21,Pharma!$B$3:$B$677,0))),"") | R21: =IFERROR(T(INDEX(Pharma!$N$3:$N$677,MATCH($C21,Pharma!$B$3:$B$677,0))),"")
B22: 4 | C22: NBIX | D22: Neurocrine Biosciences, Inc. | E22: Long | F22: 0.06 | G22: Reviewed DCF | H22: 166.52692 | I22: 142 | J22: 0.1727248 | K22: 14.434184 | L22: 1 | M22: 0.68477209 | N22: 0.06 | O22: 0.11827712 | P22: =IFERROR(INDEX(Pharma!$K$3:$K$677,MATCH($C22,Pharma!$B$3:$B$677,0)),"") | Q22: =IFERROR(IF(INDEX(Pharma!$M$3:$M$677,MATCH($C22,Pharma!$B$3:$B$677,0))="","",INDEX(Pharma!$M$3:$M$677,MATCH($C22,Pharma!$B$3:$B$677,0))),"") | R22: =IFERROR(T(INDEX(Pharma!$N$3:$N$677,MATCH($C22,Pharma!$B$3:$B$677,0))),"")
B23: 5 | C23: ALNY | D23: Alnylam Pharmaceuticals, Inc. | E23: Long | F23: 0.059529503 | G23: Basic DCF | H23: 288.29954 | I23: 230.71 | J23: 0.24961874 | K23: 30.871102 | L23: 0.5 | M23: 0.80858205 | N23: 0.06 | O23: 0.10091861 | P23: =IFERROR(INDEX(Pharma!$K$3:$K$677,MATCH($C23,Pharma!$B$3:$B$677,0)),"") | Q23: =IFERROR(IF(INDEX(Pharma!$M$3:$M$677,MATCH($C23,Pharma!$B$3:$B$677,0))="","",INDEX(Pharma!$M$3:$M$677,MATCH($C23,Pharma!$B$3:$B$677,0))),"") | R23: =IFERROR(T(INDEX(Pharma!$N$3:$N$677,MATCH($C23,Pharma!$B$3:$B$677,0))),"")
B24: 6 | C24: BMY | D24: Bristol-Myers Squibb Company | E24: Long | F24: 0.046981691 | G24: Basic DCF | H24: 71.545789 | I24: 61.715 | J24: 0.15929336 | K24: 126.06613 | L24: 0.5 | M24: 1 | N24: 0.08 | O24: 0.079646678 | P24: =IFERROR(INDEX(Pharma!$K$3:$K$677,MATCH($C24,Pharma!$B$3:$B$677,0)),"") | Q24: =IFERROR(IF(INDEX(Pharma!$M$3:$M$677,MATCH($C24,Pharma!$B$3:$B$677,0))="","",INDEX(Pharma!$M$3:$M$677,MATCH($C24,Pharma!$B$3:$B$677,0))),"") | R24: =IFERROR(T(INDEX(Pharma!$N$3:$N$677,MATCH($C24,Pharma!$B$3:$B$677,0))),"")
B25: 7 | C25: NVS | D25: Novartis AG | E25: Long | F25: 0.045098416 | G25: Basic DCF | H25: 177.13279 | I25: 153.64 | J25: 0.15290803 | K25: 293.16842 | L25: 0.5 | M25: 1 | N25: 0.08 | O25: 0.076454017 | P25: =IFERROR(INDEX(Pharma!$K$3:$K$677,MATCH($C25,Pharma!$B$3:$B$677,0)),"") | Q25: =IFERROR(IF(INDEX(Pharma!$M$3:$M$677,MATCH($C25,Pharma!$B$3:$B$677,0))="","",INDEX(Pharma!$M$3:$M$677,MATCH($C25,Pharma!$B$3:$B$677,0))),"") | R25: =IFERROR(T(INDEX(Pharma!$N$3:$N$677,MATCH($C25,Pharma!$B$3:$B$677,0))),"")
B26: 8 | C26: LEGN | D26: Legend Biotech Corporation | E26: Long | F26: 0.020913628 | G26: Basic DCF | H26: 24.938304 | I26: 19.01 | J26: 0.31185188 | K26: 3.5157699 | L26: 0.25 | M26: 0.45475767 | N26: 0.04 | O26: 0.035454258 | P26: =IFERROR(INDEX(Pharma!$K$3:$K$677,MATCH($C26,Pharma!$B$3:$B$677,0)),"") | Q26: =IFERROR(IF(INDEX(Pharma!$M$3:$M$677,MATCH($C26,Pharma!$B$3:$B$677,0))="","",INDEX(Pharma!$M$3:$M$677,MATCH($C26,Pharma!$B$3:$B$677,0))),"") | R26: =IFERROR(T(INDEX(Pharma!$N$3:$N$677,MATCH($C26,Pharma!$B$3:$B$677,0))),"")
B27: 9 | C27: BHC | D27: Bausch Health Companies Inc. | E27: Long | F27: 0.02 | G27: Basic DCF | H27: 10.70824 | I27: 6.415 | J27: 0.66925014 | K27: 2.3991494 | L27: 0.5 | M27: 0.39252149 | N27: 0.02 | O27: 0.13134753 | P27: =IFERROR(INDEX(Pharma!$K$3:$K$677,MATCH($C27,Pharma!$B$3:$B$677,0)),"") | Q27: =IFERROR(IF(INDEX(Pharma!$M$3:$M$677,MATCH($C27,Pharma!$B$3:$B$677,0))="","",INDEX(Pharma!$M$3:$M$677,MATCH($C27,Pharma!$B$3:$B$677,0))),"") | R27: =IFERROR(T(INDEX(Pharma!$N$3:$N$677,MATCH($C27,Pharma!$B$3:$B$677,0))),"")
B28: 10 | C28: HRMY | D28: Harmony Biosciences Holdings, Inc. | E28: Long | F28: 0.02 | G28: Basic DCF | H28: 89.024702 | I28: 38.7 | J28: 1.3003799 | K28: 2.2537484 | L28: 0.5 | M28: 0.38233954 | N28: 0.02 | O28: 0.19116977 | P28: =IFERROR(INDEX(Pharma!$K$3:$K$677,MATCH($C28,Pharma!$B$3:$B$677,0)),"") | Q28: =IFERROR(IF(INDEX(Pharma!$M$3:$M$677,MATCH($C28,Pharma!$B$3:$B$677,0))="","",INDEX(Pharma!$M$3:$M$677,MATCH($C28,Pharma!$B$3:$B$677,0))),"") | R28: =IFERROR(T(INDEX(Pharma!$N$3:$N$677,MATCH($C28,Pharma!$B$3:$B$677,0))),"")
B29: 11 | C29: ANIP | D29: ANI Pharmaceuticals, Inc. | E29: Long | F29: 0.02 | G29: Basic DCF | H29: 158.06464 | I29: 72.67 | J29: 1.1751017 | K29: 1.6692555 | L29: 0.5 | M29: 0.33344605 | N29: 0.02 | O29: 0.16672303 | P29: =IFERROR(INDEX(Pharma!$K$3:$K$677,MATCH($C29,Pharma!$B$3:$B$677,0)),"") | Q29: =IFERROR(IF(INDEX(Pharma!$M$3:$M$677,MATCH($C29,Pharma!$B$3:$B$677,0))="","",INDEX(Pharma!$M$3:$M$677,MATCH($C29,Pharma!$B$3:$B$677,0))),"") | R29: =IFERROR(T(INDEX(Pharma!$N$3:$N$677,MATCH($C29,Pharma!$B$3:$B$677,0))),"")
B30: 12 | C30: PAHC | D30: Phibro Animal Health Corp | E30: Long | F30: 0.02 | G30: Basic DCF | H30: 90.16968 | I30: 38.8 | J30: 1.3239608 | K30: 1.5753422 | L30: 0.5 | M30: 0.32401559 | N30: 0.02 | O30: 0.16200779 | P30: =IFERROR(INDEX(Pharma!$K$3:$K$677,MATCH($C30,Pharma!$B$3:$B$677,0)),"") | Q30: =IFERROR(IF(INDEX(Pharma!$M$3:$M$677,MATCH($C30,Pharma!$B$3:$B$677,0))="","",INDEX(Pharma!$M$3:$M$677,MATCH($C30,Pharma!$B$3:$B$677,0))),"") | R30: =IFERROR(T(INDEX(Pharma!$N$3:$N$677,MATCH($C30,Pharma!$B$3:$B$677,0))),"")
... B34: 16 | C34: AMPH | D34: Amphastar Pharmaceuticals, Inc. | E34: Long | F34: 0.012004745 | G34: Basic DCF | H34: 29.90882 | I34: 25.94 | J34: 0.15300001 | K34: 1.1034343 | L34: 0.5 | M34: 0.26602993 | N34: 0.02 | O34: 0.02035129 | P34: =IFERROR(INDEX(Pharma!$K$3:$K$677,MATCH($C34,Pharma!$B$3:$B$677,0)),"") | Q34: =IFERROR(IF(INDEX(Pharma!$M$3:$M$677,MATCH($C34,Pharma!$B$3:$B$677,0))="","",INDEX(Pharma!$M$3:$M$677,MATCH($C34,Pharma!$B$3:$B$677,0))),"") | R34: =IFERROR(T(INDEX(Pharma!$N$3:$N$677,MATCH($C34,Pharma!$B$3:$B$677,0))),"")
D35: Total longs | F35: 0.6
C37: Shorts
B38: 1 | C38: LLY | D38: Eli Lilly and Company | E38: Short | F38: -0.032757191 | G38: Full DCF | H38: 734.21433 | I38: 1286.835 | J38: -0.42944175 | K38: 1147.0295 | L38: 1 | M38: 1 | N38: 0.08 | O38: 0.42944175 | P38: =IFERROR(INDEX(Pharma!$K$3:$K$677,MATCH($C38,Pharma!$B$3:$B$677,0)),"") | Q38: =IFERROR(IF(INDEX(Pharma!$M$3:$M$677,MATCH($C38,Pharma!$B$3:$B$677,0))="","",INDEX(Pharma!$M$3:$M$677,MATCH($C38,Pharma!$B$3:$B$677,0))),"") | R38: =IFERROR(T(INDEX(Pharma!$N$3:$N$677,MATCH($C38,Pharma!$B$3:$B$677,0))),"")
B39: 2 | C39: HALO | D39: Halozyme Therapeutics, Inc. | E39: Short | F39: -0.024971861 | G39: Reviewed DCF | H39: 64.593781 | I39: 124.37 | J39: -0.48063214 | K39: 14.115746 | L39: 1 | M39: 0.68113894 | N39: 0.06 | O39: 0.32737726 | P39: =IFERROR(INDEX(Pharma!$K$3:$K$677,MATCH($C39,Pharma!$B$3:$B$677,0)),"") | Q39: =IFERROR(IF(INDEX(Pharma!$M$3:$M$677,MATCH($C39,Pharma!$B$3:$B$677,0))="","",INDEX(Pharma!$M$3:$M$677,MATCH($C39,Pharma!$B$3:$B$677,0))),"") | R39: =IFERROR(T(INDEX(Pharma!$N$3:$N$677,MATCH($C39,Pharma!$B$3:$B$677,0))),"")
B40: 3 | C40: SMMT | D40: Summit Therapeutics Inc. | E40: Short | F40: -0.021993661 | G40: PDUFA rNPV | H40: 5.475264 | I40: 16.09 | J40: -0.65971013 | K40: 14.588893 | L40: 0.7 | M40: 0.68650838 | N40: 0.06 | O40: 0.28833352 | P40: =IFERROR(INDEX(Pharma!$K$3:$K$677,MATCH($C40,Pharma!$B$3:$B$677,0)),"") | Q40: =IFERROR(IF(INDEX(Pharma!$M$3:$M$677,MATCH($C40,Pharma!$B$3:$B$677,0))="","",INDEX(Pharma!$M$3:$M$677,MATCH($C40,Pharma!$B$3:$B$677,0))),"") | R40: =IFERROR(T(INDEX(Pharma!$N$3:$N$677,MATCH($C40,Pharma!$B$3:$B$677,0))),"")
B41: 4 | C41: ABBV | D41: AbbVie Inc. | E41: Short | F41: -0.020927843 | G41: Basic DCF | H41: 130.48714 | I41: 289.15 | J41: -0.54872163 | K41: 510.96196 | L41: 0.5 | M41: 1 | N41: 0.08 | O41: 0.27436081 | P41: =IFERROR(INDEX(Pharma!$K$3:$K$677,MATCH($C41,Pharma!$B$3:$B$677,0)),"") | Q41: =IFERROR(IF(INDEX(Pharma!$M$3:$M$677,MATCH($C41,Pharma!$B$3:$B$677,0))="","",INDEX(Pharma!$M$3:$M$677,MATCH($C41,Pharma!$B$3:$B$677,0))),"") | R41: =IFERROR(T(INDEX(Pharma!$N$3:$N$677,MATCH($C41,Pharma!$B$3:$B$677,0))),"")
B42: 5 | C42: GILD | D42: Gilead Sciences, Inc. | E42: Short | F42: -0.020712817 | G42: Basic DCF | H42: 71.511969 | I42: 156.51 | J42: -0.54308371 | K42: 194.06538 | L42: 0.5 | M42: 1 | N42: 0.08 | O42: 0.27154185 | P42: =IFERROR(INDEX(Pharma!$K$3:$K$677,MATCH($C42,Pharma!$B$3:$B$677,0)),"") | Q42: =IFERROR(IF(INDEX(Pharma!$M$3:$M$677,MATCH($C42,Pharma!$B$3:$B$677,0))="","",INDEX(Pharma!$M$3:$M$677,MATCH($C42,Pharma!$B$3:$B$677,0))),"") | R42: =IFERROR(T(INDEX(Pharma!$N$3:$N$677,MATCH($C42,Pharma!$B$3:$B$677,0))),"")
B43: 6 | C43: CORT | D43: Corcept Therapeutics Incorporated | E43: Short | F43: -0.018998549 | G43: PDUFA rNPV | H43: 53.906273 | I43: 116.45 | J43: -0.53708654 | K43: 12.588058 | L43: 0.7 | M43: 0.66248453 | N43: 0.06 | O43: 0.24906806 | P43: =IFERROR(INDEX(Pharma!$K$3:$K$677,MATCH($C43,Pharma!$B$3:$B$677,0)),"") | Q43: =IFERROR(IF(INDEX(Pharma!$M$3:$M$677,MATCH($C43,Pharma!$B$3:$B$677,0))="","",INDEX(Pharma!$M$3:$M$677,MATCH($C43,Pharma!$B$3:$B$677,0))),"") | R43: =IFERROR(T(INDEX(Pharma!$N$3:$N$677,MATCH($C43,Pharma!$B$3:$B$677,0))),"")
B44: 7 | C44: RPRX | D44: Royalty Pharma PLC | E44: Short | F44: -0.018673299 | G44: Basic DCF | H44: 25.647486 | I44: 62.25 | J44: -0.58799219 | K44: 35.793825 | L44: 0.5 | M44: 0.83267804 | N44: 0.06 | O44: 0.24480409 | P44: =IFERROR(INDEX(Pharma!$K$3:$K$677,MATCH($C44,Pharma!$B$3:$B$677,0)),"") | Q44: =IFERROR(IF(INDEX(Pharma!$M$3:$M$677,MATCH($C44,Pharma!$B$3:$B$677,0))="","",INDEX(Pharma!$M$3:$M$677,MATCH($C44,Pharma!$B$3:$B$677,0))),"") | R44: =IFERROR(T(INDEX(Pharma!$N$3:$N$677,MATCH($C44,Pharma!$B$3:$B$677,0))),"")
B45: 8 | C45: MRK | D45: Merck & Co Inc | E45: Short | F45: -0.016625809 | G45: Basic DCF | H45: 83.652529 | I45: 148.3 | J45: -0.43592361 | K45: 365.88155 | L45: 0.5 | M45: 1 | N45: 0.08 | O45: 0.21796181 | P45: =IFERROR(INDEX(Pharma!$K$3:$K$677,MATCH($C45,Pharma!$B$3:$B$677,0)),"") | Q45: =IFERROR(IF(INDEX(Pharma!$M$3:$M$677,MATCH($C45,Pharma!$B$3:$B$677,0))="","",INDEX(Pharma!$M$3:$M$677,MATCH($C45,Pharma!$B$3:$B$677,0))),"") | R45: =IFERROR(T(INDEX(Pharma!$N$3:$N$677,MATCH($C45,Pharma!$B$3:$B$677,0))),"")
B46: 9 | C46: AMGN | D46: Amgen Inc | E46: Short | F46: -0.014536795 | G46: Basic DCF | H46: 271.63789 | I46: 438.94 | J46: -0.3811503 | K46: 237.30501 | L46: 0.5 | M46: 1 | N46: 0.08 | O46: 0.19057515 | P46: =IFERROR(INDEX(Pharma!$K$3:$K$677,MATCH($C46,Pharma!$B$3:$B$677,0)),"") | Q46: =IFERROR(IF(INDEX(Pharma!$M$3:$M$677,MATCH($C46,Pharma!$B$3:$B$677,0))="","",INDEX(Pharma!$M$3:$M$677,MATCH($C46,Pharma!$B$3:$B$677,0))),"") | R46: =IFERROR(T(INDEX(Pharma!$N$3:$N$677,MATCH($C46,Pharma!$B$3:$B$677,0))),"")
B47: 10 | C47: KNSA | D47: Kiniksa Pharmaceuticals International, PLC | E47: Short | F47: -0.014448954 | G47: Basic DCF | H47: 35.801053 | I47: 83.17 | J47: -0.56954367 | K47: 12.79787 | L47: 0.5 | M47: 0.66517663 | N47: 0.06 | O47: 0.18942357 | P47: =IFERROR(INDEX(Pharma!$K$3:$K$677,MATCH($C47,Pharma!$B$3:$B$677,0)),"") | Q47: =IFERROR(IF(INDEX(Pharma!$M$3:$M$677,MATCH($C47,Pharma!$B$3:$B$677,0))="","",INDEX(Pharma!$M$3:$M$677,MATCH($C47,Pharma!$B$3:$B$677,0))),"") | R47: =IFERROR(T(INDEX(Pharma!$N$3:$N$677,MATCH($C47,Pharma!$B$3:$B$677,0))),"")
B48: 11 | C48: INCY | D48: Incyte Corp | E48: Short | F48: -0.013943314 | G48: Reviewed DCF | H48: 88.667654 | I48: 116.615 | J48: -0.23965482 | K48: 23.297596 | L48: 1 | M48: 0.76274167 | N48: 0.06 | O48: 0.18279471 | P48: =IFERROR(INDEX(Pharma!$K$3:$K$677,MATCH($C48,Pharma!$B$3:$B$677,0)),"") | Q48: =IFERROR(IF(INDEX(Pharma!$M$3:$M$677,MATCH($C48,Pharma!$B$3:$B$677,0))="","",INDEX(Pharma!$M$3:$M$677,MATCH($C48,Pharma!$B$3:$B$677,0))),"") | R48: =IFERROR(T(INDEX(Pharma!$N$3:$N$677,MATCH($C48,Pharma!$B$3:$B$677,0))),"")
B49: 12 | C49: HLN | D49: Haleon PLC | E49: Short | F49: -0.013720356 | G49: Basic DCF | H49: 5.973576 | I49: 10.17 | J49: -0.41262772 | K49: 45.522718 | L49: 0.5 | M49: 0.87183557 | N49: 0.06 | O49: 0.17987176 | P49: =IFERROR(INDEX(Pharma!$K$3:$K$677,MATCH($C49,Pharma!$B$3:$B$677,0)),"") | Q49: =IFERROR(IF(INDEX(Pharma!$M$3:$M$677,MATCH($C49,Pharma!$B$3:$B$677,0))="","",INDEX(Pharma!$M$3:$M$677,MATCH($C49,Pharma!$B$3:$B$677,0))),"") | R49: =IFERROR(T(INDEX(Pharma!$N$3:$N$677,MATCH($C49,Pharma!$B$3:$B$677,0))),"")
... B65: 28 | C65: VRTX | D65: Vertex Pharmaceuticals Incorporated | E65: Short | F65: -0.008314124 | G65: Basic DCF | H65: 402.4595 | I65: 514.65 | J65: -0.21799378 | K65: 130.44366 | L65: 0.5 | M65: 1 | N65: 0.08 | O65: 0.10899689 | P65: =IFERROR(INDEX(Pharma!$K$3:$K$677,MATCH($C65,Pharma!$B$3:$B$677,0)),"") | Q65: =IFERROR(IF(INDEX(Pharma!$M$3:$M$677,MATCH($C65,Pharma!$B$3:$B$677,0))="","",INDEX(Pharma!$M$3:$M$677,MATCH($C65,Pharma!$B$3:$B$677,0))),"") | R65: =IFERROR(T(INDEX(Pharma!$N$3:$N$677,MATCH($C65,Pharma!$B$3:$B$677,0))),"")
D66: Total shorts | F66: -0.4

Sheet Pharma
F1: Close 2026-10-20
B2: Ticker | C2: Name | D2: Industry | E2: Exchange | F2: Price | G2: Market Cap | H2: Enterprise V. | J2: NPV / Share | K2: Upside | L2: Model | M2: Event | N2: Note(s)
B3: LLY | C3: Eli Lilly and Company | D3: Pharmaceuticals | E3: NYSE | F3: 1286.835 | G3: =F3*[1]Main!$C$4 | H3: =G3-[1]Main!$C$7+[1]Main!$C$8 | J3: =[1]Main!$C$11 | K3: =IFERROR(J3/F3-1,"") | L3: ="rNPV ("&[1]Main!$C$14&")" | M3: 46324 | N3: Earnings Oct 29 (before open)
B4: JNJ | C4: Johnson & Johnson | D4: Pharmaceuticals | E4: NYSE | F4: 259.4 | G4: =F4*[2]Main!$C$4 | H4: =G4-[2]Main!$C$7+[2]Main!$C$8 | J4: =IF(ISNUMBER([2]Main!$C$11),[2]Main!$C$11,"") | K4: =IFERROR(J4/F4-1,"") | L4: =[2]Main!$C$15&" ("&[2]Main!$C$14&")"
B5: ABBV | C5: AbbVie Inc. | D5: Biotechnology | E5: NYSE | F5: 289.15 | G5: =F5*[3]Main!$C$4 | H5: =G5-[3]Main!$C$7+[3]Main!$C$8 | J5: =IF(ISNUMBER([3]Main!$C$11),[3]Main!$C$11,"") | K5: =IFERROR(J5/F5-1,"") | L5: =[3]Main!$C$15&" ("&[3]Main!$C$14&")" | M5: 46325 | N5: Earnings Oct 30 (before open)
B6: MRK | C6: Merck & Co Inc | D6: Pharmaceuticals | E6: NYSE | F6: 148.3 | G6: =F6*[4]Main!$C$4 | H6: =G6-[4]Main!$C$7+[4]Main!$C$8 | J6: =IF(ISNUMBER([4]Main!$C$11),[4]Main!$C$11,"") | K6: =IFERROR(J6/F6-1,"") | L6: =[4]Main!$C$15&" ("&[4]Main!$C$14&")" | M6: 46324 | N6: Earnings Oct 29 (before open)
B7: NVS | C7: Novartis AG | D7: Pharmaceuticals | E7: NYSE | F7: 153.64 | G7: =F7*[5]Main!$C$4 | H7: =G7-[5]Main!$C$7+[5]Main!$C$8 | J7: =IF(ISNUMBER([5]Main!$C$11),[5]Main!$C$11,"") | K7: =IFERROR(J7/F7-1,"") | L7: =[5]Main!$C$15&" ("&[5]Main!$C$14&")" | M7: 46322 | N7: Earnings Oct 27 (before open)
B8: AZN | C8: AstraZeneca PLC | D8: Pharmaceuticals | E8: NYSE | F8: 168.82 | G8: =F8*[6]Main!$C$4 | H8: =G8-[6]Main!$C$7+[6]Main!$C$8 | J8: =IF(ISNUMBER([6]Main!$C$11),[6]Main!$C$11,"") | K8: =IFERROR(J8/F8-1,"") | L8: =[6]Main!$C$15&" ("&[6]Main!$C$14&")" | M8: 46325 | N8: Earnings Oct 30 (before open)
B9: AMGN | C9: Amgen Inc | D9: Biotechnology | E9: NASDAQ | F9: 438.94 | G9: =F9*[7]Main!$C$4 | H9: =G9-[7]Main!$C$7+[7]Main!$C$8 | J9: =IF(ISNUMBER([7]Main!$C$11),[7]Main!$C$11,"") | K9: =IFERROR(J9/F9-1,"") | L9: =[7]Main!$C$15&" ("&[7]Main!$C$14&")" | M9: 46329 | N9: Earnings Nov 3 (after close)
B10: GILD | C10: Gilead Sciences, Inc. | D10: Biotechnology | E10: NASDAQ | F10: 156.51 | G10: =F10*[8]Main!$C$4 | H10: =G10-[8]Main!$C$7+[8]Main!$C$8 | J10: =IF(ISNUMBER([8]Main!$C$11),[8]Main!$C$11,"") | K10: =IFERROR(J10/F10-1,"") | L10: =[8]Main!$C$15&" ("&[8]Main!$C$14&")" | M10: 46324 | N10: Earnings Oct 29 (after close)
B11: NVO | C11: Novo Nordisk A/S | D11: Pharmaceuticals | E11: NYSE | F11: 39.345 | G11: =F11*[9]Main!$C$4 | H11: =G11-[9]Main!$C$7+[9]Main!$C$8 | J11: =IF(ISNUMBER([9]Main!$C$11),[9]Main!$C$11,"") | K11: =IFERROR(J11/F11-1,"") | L11: =[9]Main!$C$15&" ("&[9]Main!$C$14&")" | M11: 46330 | N11: Earnings Nov 4 (est.)
B12: PFE | C12: Pfizer Inc. | D12: Pharmaceuticals | E12: NYSE | F12: 30.13 | G12: =F12*[10]Main!$C$4 | H12: =G12-[10]Main!$C$7+[10]Main!$C$8 | J12: =IF(ISNUMBER([10]Main!$C$11),[10]Main!$C$11,"") | K12: =IFERROR(J12/F12-1,"") | L12: =[10]Main!$C$15&" ("&[10]Main!$C$14&")" | M12: 46329 | N12: Earnings Nov 3 (before open)
B13: VRTX | C13: Vertex Pharmaceuticals Incorporated | D13: Biotechnology | E13: NASDAQ | F13: 514.65 | G13: =F13*[11]Main!$C$4 | H13: =G13-[11]Main!$C$7+[11]Main!$C$8 | J13: =IF(ISNUMBER([11]Main!$C$11),[11]Main!$C$11,"") | K13: =IFERROR(J13/F13-1,"") | L13: =[11]Main!$C$15&" ("&[11]Main!$C$14&")" | M13: 46328 | N13: Earnings Nov 2 (after close)
B14: BMY | C14: Bristol-Myers Squibb Company | D14: Pharmaceuticals | E14: NYSE | F14: 61.715 | G14: =F14*[12]Main!$C$4 | H14: =G14-[12]Main!$C$7+[12]Main!$C$8 | J14: =IF(ISNUMBER([12]Main!$C$11),[12]Main!$C$11,"") | K14: =IFERROR(J14/F14-1,"") | L14: =[12]Main!$C$15&" ("&[12]Main!$C$14&")" | M14: 46324 | N14: Earnings Oct 29 (before open)
B15: GSK | C15: GSK plc | D15: Pharmaceuticals | E15: NYSE | F15: 50.645 | G15: =F15*[13]Main!$C$4 | H15: =G15-[13]Main!$C$7+[13]Main!$C$8 | J15: =IF(ISNUMBER([13]Main!$C$11),[13]Main!$C$11,"") | K15: =IFERROR(J15/F15-1,"") | L15: =[13]Main!$C$15&" ("&[13]Main!$C$14&")" | M15: 46323 | N15: Earnings Oct 28 (before open)
B16: SNY | C16: Sanofi SA | D16: Pharmaceuticals | E16: NASDAQ | F16: 41.4 | G16: =F16*[14]Main!$C$4 | H16: =G16-[14]Main!$C$7+[14]Main!$C$8 | J16: =IF(ISNUMBER([14]Main!$C$11),[14]Main!$C$11,"") | K16: =IFERROR(J16/F16-1,"") | L16: =[14]Main!$C$15&" ("&[14]Main!$C$14&")" | M16: 46325 | N16: Earnings Oct 30 (before open)
B17: MRNA | C17: Moderna, Inc. | D17: Biotechnology | E17: NASDAQ | F17: 242.08 | G17: =F17*[15]Main!$C$4 | H17: =G17-[15]Main!$C$7+[15]Main!$C$8 | J17: =IF(ISNUMBER([15]Main!$C$11),[15]Main!$C$11,"") | K17: =IFERROR(J17/F17-1,"") | L17: =[15]Main!$C$15&" ("&[15]Main!$C$14&")" | M17: 46332 | N17: Earnings Nov 6 (before open)
B18: REGN | C18: Regeneron Pharmaceuticals, Inc. | D18: Biotechnology | E18: NASDAQ | F18: 807.48 | G18: =F18*[16]Main!$C$4 | H18: =G18-[16]Main!$C$7+[16]Main!$C$8 | J18: =IF(ISNUMBER([16]Main!$C$11),[16]Main!$C$11,"") | K18: =IFERROR(J18/F18-1,"") | L18: =[16]Main!$C$15&" ("&[16]Main!$C$14&")" | M18: 46325 | N18: Earnings Oct 30 (before open)
B19: TAK | C19: Takeda Pharmaceutical Company Limited | D19: Pharmaceuticals | E19: NYSE | F19: 20.08 | G19: =F19*[17]Main!$C$4 | H19: =G19-[17]Main!$C$7+[17]Main!$C$8 | J19: =IF(ISNUMBER([17]Main!$C$11),[17]Main!$C$11,"") | K19: =IFERROR(J19/F19-1,"") | L19: =[17]Main!$C$15&" ("&[17]Main!$C$14&")" | M19: 46324 | N19: Earnings Oct 29 (before open)
B20: NTRA | C20: Natera, Inc. | D20: Biotechnology | E20: NASDAQ | F20: 405.92 | G20: =F20*[18]Main!$C$4 | H20: =G20-[18]Main!$C$7+[18]Main!$C$8 | J20: =IF(ISNUMBER([18]Main!$C$11),[18]Main!$C$11,"") | K20: =IFERROR(J20/F20-1,"") | L20: =[18]Main!$C$15&" ("&[18]Main!$C$14&")" | M20: 46331 | N20: Earnings Nov 5 (est.)
B21: ARGX | C21: argenx SE | D21: Biotechnology | E21: NASDAQ | F21: 869.72 | G21: =F21*[19]Main!$C$4 | H21: =G21-[19]Main!$C$7+[19]Main!$C$8 | J21: =IF(ISNUMBER([19]Main!$C$11),[19]Main!$C$11,"") | K21: =IFERROR(J21/F21-1,"") | L21: =[19]Main!$C$15&" ("&[19]Main!$C$14&")" | M21: 46317 | N21: Earnings Oct 22 (before open)
B22: TEVA | C22: Teva Pharmaceutical Industries Limited | D22: Pharmaceuticals | E22: NYSE | F22: 40.855 | G22: =F22*[20]Main!$C$4 | H22: =G22-[20]Main!$C$7+[20]Main!$C$8 | J22: =IF(ISNUMBER([20]Main!$C$11),[20]Main!$C$11,"") | K22: =IFERROR(J22/F22-1,"") | L22: =[20]Main!$C$15&" ("&[20]Main!$C$14&")" | M22: 46329 | N22: Earnings Nov 3 (before open)
B23: HLN | C23: Haleon PLC | D23: Pharmaceuticals | E23: NYSE | F23: 10.17 | G23: =F23*[21]Main!$C$4 | H23: =G23-[21]Main!$C$7+[21]Main!$C$8 | J23: =IF(ISNUMBER([21]Main!$C$11),[21]Main!$C$11,"") | K23: =IFERROR(J23/F23-1,"") | L23: =[21]Main!$C$15&" ("&[21]Main!$C$14&")" | M23: 46324 | N23: Earnings Oct 29 (before open)
B24: ONC | C24: BeOne Medicines AG | D24: Biotechnology | E24: NASDAQ | F24: 384.5 | G24: =F24*[22]Main!$C$4 | H24: =G24-[22]Main!$C$7+[22]Main!$C$8 | J24: =IF(ISNUMBER([22]Main!$C$11),[22]Main!$C$11,"") | K24: =IFERROR(J24/F24-1,"") | L24: =[22]Main!$C$15&" ("&[22]Main!$C$14&")" | M24: 46331 | N24: Earnings Nov 5 (est.)
B25: RVMD | C25: Revolution Medicines, Inc. | D25: Biotechnology | E25: NASDAQ | F25: 196.55 | G25: =F25*[23]Main!$C$4 | H25: =G25-[23]Main!$C$7+[23]Main!$C$8 | J25: =IF(ISNUMBER([23]Main!$C$11),[23]Main!$C$11,"") | K25: =IFERROR(J25/F25-1,"") | L25: =[23]Main!$C$15&" ("&[23]Main!$C$14&")" | M25: 46330 | N25: Earnings Nov 4 (est.) · Readout ~2026-12-31: Lung cancer, Phase 3
B26: RPRX | C26: Royalty Pharma PLC | D26: Pharmaceuticals | E26: NASDAQ | F26: 62.25 | G26: =F26*[24]Main!$C$4 | H26: =G26-[24]Main!$C$7+[24]Main!$C$8 | J26: =IF(ISNUMBER([24]Main!$C$11),[24]Main!$C$11,"") | K26: =IFERROR(J26/F26-1,"") | L26: =[24]Main!$C$15&" ("&[24]Main!$C$14&")" | M26: 46330 | N26: Earnings Nov 4 (before open)
B27: BIIB | C27: Biogen Inc. | D27: Biotechnology | E27: NASDAQ | F27: 243.1 | G27: =F27*[25]Main!$C$4 | H27: =G27-[25]Main!$C$7+[25]Main!$C$8 | J27: =IF(ISNUMBER([25]Main!$C$11),[25]Main!$C$11,"") | K27: =IFERROR(J27/F27-1,"") | L27: =[25]Main!$C$15&" ("&[25]Main!$C$14&")" | M27: 46323 | N27: Earnings Oct 28 (before open)
B28: ZTS | C28: Zoetis Inc | D28: Pharmaceuticals | E28: NYSE | F28: 80.04 | G28: =F28*[26]Main!$C$4 | H28: =G28-[26]Main!$C$7+[26]Main!$C$8 | J28: =IF(ISNUMBER([26]Main!$C$11),[26]Main!$C$11,"") | K28: =IFERROR(J28/F28-1,"") | L28: =[26]Main!$C$15&" ("&[26]Main!$C$14&")" | M28: 46331 | N28: Earnings Nov 5 (before open)
B29: ALNY | C29: Alnylam Pharmaceuticals, Inc. | D29: Biotechnology | E29: NASDAQ | F29: 230.71 | G29: =F29*[27]Main!$C$4 | H29: =G29-[27]Main!$C$7+[27]Main!$C$8 | J29: =IF(ISNUMBER([27]Main!$C$11),[27]Main!$C$11,"") | K29: =IFERROR(J29/F29-1,"") | L29: =[27]Main!$C$15&" ("&[27]Main!$C$14&")" | M29: 46324 | N29: Earnings Oct 29 (before open)
B30: ROIV | C30: Roivant Sciences Ltd | D30: Biotechnology | E30: NASDAQ | F30: 34.92 | G30: =F30*[28]Main!$C$4 | H30: =G30-[28]Main!$C$7+[28]Main!$C$8 | J30: =IF(ISNUMBER([28]Main!$C$11),[28]Main!$C$11,"") | K30: =IFERROR(J30/F30-1,"") | L30: =[28]Main!$C$15&" ("&[28]Main!$C$14&")" | M30: 46335 | N30: Earnings Nov 9 (est.) · Readout ~2026-12: Pulmonary hypertension, Phase 3
B31: GMAB | C31: Genmab A/S | D31: Biotechnology | E31: NASDAQ | F31: 39.07 | G31: =F31*[29]Main!$C$4 | H31: =G31-[29]Main!$C$7+[29]Main!$C$8 | J31: =IF(ISNUMBER([29]Main!$C$11),[29]Main!$C$11,"") | K31: =IFERROR(J31/F31-1,"") | L31: =[29]Main!$C$15&" ("&[29]Main!$C$14&")" | M31: 46331 | N31: Earnings Nov 5 (before open)
B32: UTHR | C32: United Therapeutics Corporation | D32: Biotechnology | E32: NASDAQ | F32: 553.88 | G32: =F32*[30]Main!$C$4 | H32: =G32-[30]Main!$C$7+[30]Main!$C$8 | J32: =IF(ISNUMBER([30]Main!$C$11),[30]Main!$C$11,"") | K32: =IFERROR(J32/F32-1,"") | L32: =[30]Main!$C$15&" ("&[30]Main!$C$14&")" | M32: 46330 | N32: Earnings Nov 4 (est.)
B33: INCY | C33: Incyte Corp | D33: Biotechnology | E33: NASDAQ | F33: 116.615 | G33: =F33*[31]Main!$C$4 | H33: =G33-[31]Main!$C$7+[31]Main!$C$8 | J33: =IF(ISNUMBER([31]Main!$C$11),[31]Main!$C$11,"") | K33: =IFERROR(J33/F33-1,"") | L33: =[31]Main!$C$15&" ("&[31]Main!$C$14&")" | M33: 46324 | N33: Earnings Oct 29 (before open)
B34: BNTX | C34: Biontech SE | D34: Biotechnology | E34: NASDAQ | F34: 91.17 | G34: =F34*[32]Main!$C$4 | H34: =G34-[32]Main!$C$7+[32]Main!$C$8 | J34: =IF(ISNUMBER([32]Main!$C$11),[32]Main!$C$11,"") | K34: =IFERROR(J34/F34-1,"") | L34: =[32]Main!$C$15&" ("&[32]Main!$C$14&")" | M34: 46329 | N34: Earnings Nov 3 (before open)
B35: VTRS | C35: Viatris Inc. | D35: Pharmaceuticals | E35: NASDAQ | F35: 18.65 | G35: =F35*[33]Main!$C$4 | H35: =G35-[33]Main!$C$7+[33]Main!$C$8 | J35: =IF(ISNUMBER([33]Main!$C$11),[33]Main!$C$11,"") | K35: =IFERROR(J35/F35-1,"") | L35: =[33]Main!$C$15&" ("&[33]Main!$C$14&")" | M35: 46331 | N35: Earnings Nov 5 (before open)
B36: INSM | C36: Insmed Incorporated | D36: Biotechnology | E36: NASDAQ | F36: 95.67 | G36: =F36*[34]Main!$C$4 | H36: =G36-[34]Main!$C$7+[34]Main!$C$8 | J36: =IF(ISNUMBER([34]Main!$C$11),[34]Main!$C$11,"") | K36: =IFERROR(J36/F36-1,"") | L36: =[34]Main!$C$15&" ("&[34]Main!$C$14&")" | M36: 46324 | N36: Earnings Oct 29 (before open)
B37: EXEL | C37: Exelixis Inc | D37: Biotechnology | E37: NASDAQ | F37: 64.39 | G37: =F37*[35]Main!$C$4 | H37: =G37-[35]Main!$C$7+[35]Main!$C$8 | J37: =IF(ISNUMBER([35]Main!$C$11),[35]Main!$C$11,"") | K37: =IFERROR(J37/F37-1,"") | L37: =[35]Main!$C$15&" ("&[35]Main!$C$14&")" | M37: 46324 | N37: Earnings Oct 29 (after close)
B38: ASND | C38: Ascendis Pharma A/S | D38: Biotechnology | E38: NASDAQ | F38: 234.33 | G38: =F38*[36]Main!$C$4 | H38: =G38-[36]Main!$C$7+[36]Main!$C$8 | J38: =IF(ISNUMBER([36]Main!$C$11),[36]Main!$C$11,"") | K38: =IFERROR(J38/F38-1,"") | L38: =[36]Main!$C$15&" ("&[36]Main!$C$14&")" | M38: 46337 | N38: Earnings Nov 11 (est.)
B39: HALO | C39: Halozyme Therapeutics, Inc. | D39: Biotechnology | E39: NASDAQ | F39: 124.37 | G39: =F39*[37]Main!$C$4 | H39: =G39-[37]Main!$C$7+[37]Main!$C$8 | J39: =IF(ISNUMBER([37]Main!$C$11),[37]Main!$C$11,"") | K39: =IFERROR(J39/F39-1,"") | L39: =[37]Main!$C$15&" ("&[37]Main!$C$14&")" | M39: 46328 | N39: Earnings Nov 2 (est.)
B40: NBIX | C40: Neurocrine Biosciences, Inc. | D40: Biotechnology | E40: NASDAQ | F40: 142 | G40: =F40*[38]Main!$C$4 | H40: =G40-[38]Main!$C$7+[38]Main!$C$8 | J40: =IF(ISNUMBER([38]Main!$C$11),[38]Main!$C$11,"") | K40: =IFERROR(J40/F40-1,"") | L40: =[38]Main!$C$15&" ("&[38]Main!$C$14&")" | M40: 46328 | N40: Earnings Nov 2 (after close)
B41: JAZZ | C41: Jazz Pharmaceuticals PLC | D41: Pharmaceuticals | E41: NASDAQ | F41: 213.76 | G41: =F41*[39]Main!$C$4 | H41: =G41-[39]Main!$C$7+[39]Main!$C$8 | J41: =IF(ISNUMBER([39]Main!$C$11),[39]Main!$C$11,"") | K41: =IFERROR(J41/F41-1,"") | L41: =[39]Main!$C$15&" ("&[39]Main!$C$14&")" | M41: 46330 | N41: Earnings Nov 4 (est.)
B42: SMMT | C42: Summit Therapeutics Inc. | D42: Biotechnology | E42: NASDAQ | F42: 16.09 | G42: =F42*[40]Main!$C$4 | H42: =G42-[40]Main!$C$7+[40]Main!$C$8 | J42: =[40]Main!$C$11 | K42: =IFERROR(J42/F42-1,"") | L42: ="rNPV ("&[40]Main!$C$14&")" | M42: 46340 | N42: PDUFA Nov 14: ivonescimab in EGFRm NSCLC
B43: BBIO | C43: BridgeBio Pharma, Inc. | D43: Biotechnology | E43: NASDAQ | F43: 67.55 | G43: =F43*[41]Main!$C$4 | H43: =G43-[41]Main!$C$7+[41]Main!$C$8 | J43: =[41]Main!$C$11 | K43: =IFERROR(J43/F43-1,"") | L43: ="rNPV ("&[41]Main!$C$14&")" | M43: 46353 | N43: PDUFA Nov 27: BBP-418 · Earnings Nov 4 (est.)
B44: KNSA | C44: Kiniksa Pharmaceuticals International, PLC | D44: Biotechnology | E44: NASDAQ | F44: 83.17 | G44: =F44*[42]Main!$C$4 | H44: =G44-[42]Main!$C$7+[42]Main!$C$8 | J44: =IF(ISNUMBER([42]Main!$C$11),[42]Main!$C$11,"") | K44: =IFERROR(J44/F44-1,"") | L44: =[42]Main!$C$15&" ("&[42]Main!$C$14&")" | M44: 46322 | N44: Earnings Oct 27 (est.)
B45: CORT | C45: Corcept Therapeutics Incorporated | D45: Pharmaceuticals | E45: NASDAQ | F45: 116.45 | G45: =F45*[43]Main!$C$4 | H45: =G45-[43]Main!$C$7+[43]Main!$C$8 | J45: =[43]Main!$C$11 | K45: =IFERROR(J45/F45-1,"") | L45: ="rNPV ("&[43]Main!$C$14&")" | M45: 46373 | N45: PDUFA Dec 17: relacorilant in hypercortisolism · Earnings Nov 3 (est.)
B46: ELAN | C46: Elanco Animal Health Incorporated | D46: Pharmaceuticals | E46: NYSE | F46: 22.7 | G46: =F46*[44]Main!$C$4 | H46: =G46-[44]Main!$C$7+[44]Main!$C$8 | J46: =IF(ISNUMBER([44]Main!$C$11),[44]Main!$C$11,"") | K46: =IFERROR(J46/F46-1,"") | L46: =[44]Main!$C$15&" ("&[44]Main!$C$14&")" | M46: 46332 | N46: Earnings Nov 6 (before open)
B47: RDY | C47: Dr. Reddy's Laboratories Limited | D47: Pharmaceuticals | E47: NYSE | F47: 13.26 | G47: =F47*[45]Main!$C$4 | H47: =G47-[45]Main!$C$7+[45]Main!$C$8 | J47: =IF(ISNUMBER([45]Main!$C$11),[45]Main!$C$11,"") | K47: =IFERROR(J47/F47-1,"") | L47: =[45]Main!$C$15&" ("&[45]Main!$C$14&")" | M47: 46318 | N47: Earnings Oct 23 (est.)
B48: BMRN | C48: BioMarin Pharmaceutical Inc. | D48: Biotechnology | E48: NASDAQ | F48: 56.44 | G48: =F48*[46]Main!$C$4 | H48: =G48-[46]Main!$C$7+[46]Main!$C$8 | J48: =IF(ISNUMBER([46]Main!$C$11),[46]Main!$C$11,"") | K48: =IFERROR(J48/F48-1,"") | L48: =[46]Main!$C$15&" ("&[46]Main!$C$14&")" | M48: 46321 | N48: Earnings Oct 26 (est.)
B49: MDGL | C49: Madrigal Pharmaceuticals, Inc. | D49: Biotechnology | E49: NASDAQ | F49: 467.54 | G49: =F49*[47]Main!$C$4 | H49: =G49-[47]Main!$C$7+[47]Main!$C$8 | J49: =IF(ISNUMBER([47]Main!$C$11),[47]Main!$C$11,"") | K49: =IFERROR(J49/F49-1,"") | L49: =[47]Main!$C$15&" ("&[47]Main!$C$14&")" | M49: 46329 | N49: Earnings Nov 3 (est.)
B50: IBRX | C50: ImmunityBio, Inc. | D50: Biotechnology | E50: NASDAQ | F50: 8.77 | G50: =F50*[48]Main!$C$4 | H50: =G50-[48]Main!$C$7+[48]Main!$C$8 | J50: =IF(ISNUMBER([48]Main!$C$11),[48]Main!$C$11,"") | K50: =IFERROR(J50/F50-1,"") | L50: =[48]Main!$C$15&" ("&[48]Main!$C$14&")" | M50: 46329 | N50: Earnings Nov 3 (est.)
B51: PCVX | C51: Vaxcyte, Inc. | D51: Biotechnology | E51: NASDAQ | F51: 66.23 | G51: =F51*[49]Main!$C$4 | H51: =G51-[49]Main!$C$7+[49]Main!$C$8 | J51: =IF(ISNUMBER([49]Main!$C$11),[49]Main!$C$11,"") | K51: =IFERROR(J51/F51-1,"") | L51: =[49]Main!$C$15&" ("&[49]Main!$C$14&")" | M51: 46329 | N51: Earnings Nov 3 (est.) · Readout ~2027-03: Pneumococcal vaccine, Phase 3
B52: KRYS | C52: Krystal Biotech, Inc. | D52: Biotechnology | E52: NASDAQ | F52: 325.42 | G52: =F52*[50]Main!$C$4 | H52: =G52-[50]Main!$C$7+[50]Main!$C$8 | J52: =IF(ISNUMBER([50]Main!$C$11),[50]Main!$C$11,"") | K52: =IFERROR(J52/F52-1,"") | L52: =[50]Main!$C$15&" ("&[50]Main!$C$14&")" | M52: 46328 | N52: Earnings Nov 2 (est.)
B53: KYMR | C53: Kymera Therapeutics, Inc. | D53: Biotechnology | E53: NASDAQ | F53: 113.46 | G53: =F53*[51]Main!$C$4 | H53: =G53-[51]Main!$C$7+[51]Main!$C$8 | J53: =IF(ISNUMBER([51]Main!$C$11),[51]Main!$C$11,"") | K53: =IFERROR(J53/F53-1,"") | L53: =[51]Main!$C$15&" ("&[51]Main!$C$14&")" | M53: 46329 | N53: Earnings Nov 3 (est.)
B54: CAI | C54: Caris Life Sciences, Inc. | D54: Biotechnology | E54: NASDAQ | F54: 31.11 | G54: =F54*[52]Main!$C$4 | H54: =G54-[52]Main!$C$7+[52]Main!$C$8 | J54: =IF(ISNUMBER([52]Main!$C$11),[52]Main!$C$11,"") | K54: =IFERROR(J54/F54-1,"") | L54: =[52]Main!$C$15&" ("&[52]Main!$C$14&")" | M54: 46330 | N54: Earnings Nov 4 (after close)
B55: CYTK | C55: Cytokinetics, Incorporated | D55: Biotechnology | E55: NASDAQ | F55: 63.95 | G55: =F55*[53]Main!$C$4 | H55: =G55-[53]Main!$C$7+[53]Main!$C$8 | J55: =[53]Main!$C$11 | K55: =IFERROR(J55/F55-1,"") | L55: ="rNPV ("&[53]Main!$C$14&")" | M55: 46340 | N55: PDUFA Nov 14: MAPLE-HCM label · Earnings Nov 4 (est.)
B56: AXSM | C56: Axsome Therapeutics, Inc. | D56: Pharmaceuticals | E56: NASDAQ | F56: 159.58 | G56: =F56*[54]Main!$C$4 | H56: =G56-[54]Main!$C$7+[54]Main!$C$8 | J56: =IF(ISNUMBER([54]Main!$C$11),[54]Main!$C$11,"") | K56: =IFERROR(J56/F56-1,"") | L56: =[54]Main!$C$15&" ("&[54]Main!$C$14&")" | M56: 46328 | N56: Earnings Nov 2 (before open)
B57: PTGX | C57: Protagonist Therapeutics, Inc. | D57: Biotechnology | E57: NASDAQ | F57: 137.99 | G57: =F57*[55]Main!$C$4 | H57: =G57-[55]Main!$C$7+[55]Main!$C$8 | J57: =IF(ISNUMBER([55]Main!$C$11),[55]Main!$C$11,"") | K57: =IFERROR(J57/F57-1,"") | L57: =[55]Main!$C$15&" ("&[55]Main!$C$14&")" | M57: 46331 | N57: Earnings Nov 5 (est.)
B58: TWST | C58: Twist Bioscience Corporation | D58: Biotechnology | E58: NASDAQ | F58: 142.7 | G58: =F58*[56]Main!$C$4 | H58: =G58-[56]Main!$C$7+[56]Main!$C$8 | J58: =IF(ISNUMBER([56]Main!$C$11),[56]Main!$C$11,"") | K58: =IFERROR(J58/F58-1,"") | L58: =[56]Main!$C$15&" ("&[56]Main!$C$14&")" | M58: 46339 | N58: Earnings Nov 13 (est.)
B59: TGTX | C59: TG Therapeutics, Inc. | D59: Biotechnology | E59: NASDAQ | F59: 54.53 | G59: =F59*[57]Main!$C$4 | H59: =G59-[57]Main!$C$7+[57]Main!$C$8 | J59: =IF(ISNUMBER([57]Main!$C$11),[57]Main!$C$11,"") | K59: =IFERROR(J59/F59-1,"") | L59: =[57]Main!$C$15&" ("&[57]Main!$C$14&")" | M59: 46328 | N59: Earnings Nov 2 (est.)
B60: ARWR | C60: Arrowhead Pharmaceuticals, Inc. | D60: Biotechnology | E60: NASDAQ | F60: 58.92 | G60: =F60*[58]Main!$C$4 | H60: =G60-[58]Main!$C$7+[58]Main!$C$8 | J60: =IF(ISNUMBER([58]Main!$C$11),[58]Main!$C$11,"") | K60: =IFERROR(J60/F60-1,"") | L60: =[58]Main!$C$15&" ("&[58]Main!$C$14&")" | M60: 46350 | N60: Earnings Nov 24 (est.)
B61: IONS | C61: Ionis Pharmaceuticals, Inc. | D61: Biotechnology | E61: NASDAQ | F61: 45.4 | G61: =F61*[59]Main!$C$4 | H61: =G61-[59]Main!$C$7+[59]Main!$C$8 | J61: =IF(ISNUMBER([59]Main!$C$11),[59]Main!$C$11,"") | K61: =IFERROR(J61/F61-1,"") | L61: =[59]Main!$C$15&" ("&[59]Main!$C$14&")" | M61: 46330 | N61: Earnings Nov 4 (est.)
B62: PRAX | C62: Praxis Precision Medicines, Inc. | D62: Biotechnology | E62: NASDAQ | F62: 264.49 | G62: =F62*[60]Main!$C$4 | H62: =G62-[60]Main!$C$7+[60]Main!$C$8 | J62: =[60]Main!$C$11 | K62: =IFERROR(J62/F62-1,"") | L62: ="rNPV ("&[60]Main!$C$14&")" | M62: 46383 | N62: PDUFA Dec 27: relutrigine · Earnings Nov 4 (est.)
B63: SYRE | C63: Spyre Therapeutics Inc | D63: Biotechnology | E63: NASDAQ | F63: 91.4 | G63: =F63*[61]Main!$C$4 | H63: =G63-[61]Main!$C$7+[61]Main!$C$8 | J63: =IF(ISNUMBER([61]Main!$C$11),[61]Main!$C$11,"") | K63: =IFERROR(J63/F63-1,"") | L63: =[61]Main!$C$15&" ("&[61]Main!$C$14&")" | M63: 46329 | N63: Earnings Nov 3 (est.) · Readout ~2026-10-31: Rheumatoid / spondyloarthritis, Phase 2
B64: ABVX | C64: Abivax SA | D64: Biotechnology | E64: NASDAQ | F64: 92.59 | G64: =F64*[62]Main!$C$4 | H64: =G64-[62]Main!$C$7+[62]Main!$C$8 | J64: =IF(ISNUMBER([62]Main!$C$11),[62]Main!$C$11,"") | K64: =IFERROR(J64/F64-1,"") | L64: =[62]Main!$C$15&" ("&[62]Main!$C$14&")" | N64: Readout ~2026-12: IBD (UC / Crohn's), Phase 3
B65: ALKS | C65: Alkermes Plc | D65: Biotechnology | E65: NASDAQ | F65: 44.11 | G65: =F65*[63]Main!$C$4 | H65: =G65-[63]Main!$C$7+[63]Main!$C$8 | J65: =IF(ISNUMBER([63]Main!$C$11),[63]Main!$C$11,"") | K65: =IFERROR(J65/F65-1,"") | L65: =[63]Main!$C$15&" ("&[63]Main!$C$14&")" | M65: 46322 | N65: Earnings Oct 27 (est.)
B66: IOVA | C66: Iovance Biotherapeutics Inc | D66: Biotechnology | E66: NASDAQ | F66: 14.86 | G66: =F66*[64]Main!$C$4 | H66: =G66-[64]Main!$C$7+[64]Main!$C$8 | J66: =IF(ISNUMBER([64]Main!$C$11),[64]Main!$C$11,"") | K66: =IFERROR(J66/F66-1,"") | L66: =[64]Main!$C$15&" ("&[64]Main!$C$14&")" | M66: 46331 | N66: Earnings Nov 5 (est.)
B67: AMRX | C67: Amneal Pharmaceuticals, Inc | D67: Pharmaceuticals | E67: NASDAQ | F67: 19.84 | G67: =F67*[65]Main!$C$4 | H67: =G67-[65]Main!$C$7+[65]Main!$C$8 | J67: =IF(ISNUMBER([65]Main!$C$11),[65]Main!$C$11,"") | K67: =IFERROR(J67/F67-1,"") | L67: =[65]Main!$C$15&" ("&[65]Main!$C$14&")" | M67: 46329 | N67: Earnings Nov 3 (before open)
B68: RYTM | C68: Rhythm Pharmaceuticals, Inc. | D68: Biotechnology | E68: NASDAQ | F68: 90.2 | G68: =F68*[66]Main!$C$4 | H68: =G68-[66]Main!$C$7+[66]Main!$C$8 | J68: =IF(ISNUMBER([66]Main!$C$11),[66]Main!$C$11,"") | K68: =IFERROR(J68/F68-1,"") | L68: =[66]Main!$C$15&" ("&[66]Main!$C$14&")" | M68: 46329 | N68: Earnings Nov 3 (est.)
B69: LGND | C69: Ligand Pharmaceuticals Incorporated | D69: Pharmaceuticals | E69: NASDAQ | F69: 306.4 | G69: =F69*[67]Main!$C$4 | H69: =G69-[67]Main!$C$7+[67]Main!$C$8 | J69: =IF(ISNUMBER([67]Main!$C$11),[67]Main!$C$11,"") | K69: =IFERROR(J69/F69-1,"") | L69: =[67]Main!$C$15&" ("&[67]Main!$C$14&")" | M69: 46324 | N69: Earnings Oct 29 (before open)
B70: BLTE | C70: Belite Bio, Inc | D70: Pharmaceuticals | E70: NASDAQ | F70: 154.45 | G70: =F70*[68]Main!$C$4 | H70: =G70-[68]Main!$C$7+[68]Main!$C$8 | J70: =IF(ISNUMBER([68]Main!$C$11),[68]Main!$C$11,"") | K70: =IFERROR(J70/F70-1,"") | L70: =[68]Main!$C$15&" ("&[68]Main!$C$14&")" | M70: 46335 | N70: Earnings Nov 9 (est.) · Readout ~2027-06-30: Geographic atrophy, Phase 3
B71: COGT | C71: Cogent Biosciences, Inc. | D71: Biotechnology | E71: NASDAQ | F71: 31.24 | G71: =F71*[69]Main!$C$4 | H71: =G71-[69]Main!$C$7+[69]Main!$C$8 | J71: =[69]Main!$C$11 | K71: =IFERROR(J71/F71-1,"") | L71: ="rNPV ("&[69]Main!$C$14&")" | M71: 46356 | N71: PDUFA Nov 30: bezuclastinib in GIST · Earnings Nov 6 (est.)
B72: IMVT | C72: Immunovant, Inc. | D72: Biotechnology | E72: NASDAQ | F72: 28.59 | G72: =F72*[70]Main!$C$4 | H72: =G72-[70]Main!$C$7+[70]Main!$C$8 | J72: =IF(ISNUMBER([70]Main!$C$11),[70]Main!$C$11,"") | K72: =IFERROR(J72/F72-1,"") | L72: =[70]Main!$C$15&" ("&[70]Main!$C$14&")" | M72: 46335 | N72: Earnings Nov 9 (est.) · Readout ~2026-10: Lupus / Sjogren's, Phase 2
B73: KOD | C73: Kodiak Sciences Inc. | D73: Biotechnology | E73: NASDAQ | F73: 92.97 | G73: =F73*[71]Main!$C$4 | H73: =G73-[71]Main!$C$7+[71]Main!$C$8 | J73: =IF(ISNUMBER([71]Main!$C$11),[71]Main!$C$11,"") | K73: =IFERROR(J73/F73-1,"") | L73: =[71]Main!$C$15&" ("&[71]Main!$C$14&")" | M73: 46338 | N73: Earnings Nov 12 (est.) · Readout ~2027-02: Retinal disease (AMD / DME), Phase 3
B74: CGON | C74: CG Oncology, Inc. | D74: Biotechnology | E74: NASDAQ | F74: 61.93 | G74: =F74*[72]Main!$C$4 | H74: =G74-[72]Main!$C$7+[72]Main!$C$8 | J74: =IF(ISNUMBER([72]Main!$C$11),[72]Main!$C$11,"") | K74: =IFERROR(J74/F74-1,"") | L74: =[72]Main!$C$15&" ("&[72]Main!$C$14&")" | M74: 46339 | N74: Earnings Nov 13 (est.) · Readout ~2026-11: Bladder / urothelial cancer, Phase 3
B75: GRAL | C75: Grail Inc | D75: Biotechnology | E75: NASDAQ | F75: 124.67 | G75: =F75*[73]Main!$C$4 | H75: =G75-[73]Main!$C$7+[73]Main!$C$8 | J75: =IF(ISNUMBER([73]Main!$C$11),[73]Main!$C$11,"") | K75: =IFERROR(J75/F75-1,"") | L75: =[73]Main!$C$15&" ("&[73]Main!$C$14&")" | M75: 46337 | N75: Earnings Nov 11 (est.)
B76: BLRX | C76: BioLine RX Ltd | D76: Biotechnology | E76: NASDAQ | F76: 2.2145 | G76: =F76*[74]Main!$C$4 | H76: =G76-[74]Main!$C$7+[74]Main!$C$8 | J76: =IF(ISNUMBER([74]Main!$C$11),[74]Main!$C$11,"") | K76: =IFERROR(J76/F76-1,"") | L76: =[74]Main!$C$15&" ("&[74]Main!$C$14&")" | M76: 46349 | N76: Earnings Nov 23 (est.)
B77: MIRM | C77: Mirum Pharmaceuticals, Inc. | D77: Biotechnology | E77: NASDAQ | F77: 85.07 | G77: =F77*[75]Main!$C$4 | H77: =G77-[75]Main!$C$7+[75]Main!$C$8 | J77: =IF(ISNUMBER([75]Main!$C$11),[75]Main!$C$11,"") | K77: =IFERROR(J77/F77-1,"") | L77: =[75]Main!$C$15&" ("&[75]Main!$C$14&")" | M77: 46329 | N77: Earnings Nov 3 (est.)
B78: PTCT | C78: PTC Therapeutics, Inc. | D78: Biotechnology | E78: NASDAQ | F78: 62.92 | G78: =F78*[76]Main!$C$4 | H78: =G78-[76]Main!$C$7+[76]Main!$C$8 | J78: =IF(ISNUMBER([76]Main!$C$11),[76]Main!$C$11,"") | K78: =IFERROR(J78/F78-1,"") | L78: =[76]Main!$C$15&" ("&[76]Main!$C$14&")" | M78: 46324 | N78: Earnings Oct 29 (after close)
B79: SRRK | C79: Scholar Rock Holding Corporation | D79: Biotechnology | E79: NASDAQ | F79: 41.36 | G79: =F79*[77]Main!$C$4 | H79: =G79-[77]Main!$C$7+[77]Main!$C$8 | J79: =IF(ISNUMBER([77]Main!$C$11),[77]Main!$C$11,"") | K79: =IFERROR(J79/F79-1,"") | L79: =[77]Main!$C$15&" ("&[77]Main!$C$14&")" | M79: 46339 | N79: Earnings Nov 13 (est.) · Readout ~2026-11-01: Muscular dystrophy / SMA, filed · PDUFA 2026-09-30: Muscular dystrophy / SMA
B80: ORKA | C80: Oruka Therapeutics Inc | D80: Biotechnology | E80: NASDAQ | F80: 79.09 | G80: =F80*[78]Main!$C$4 | H80: =G80-[78]Main!$C$7+[78]Main!$C$8 | J80: =IF(ISNUMBER([78]Main!$C$11),[78]Main!$C$11,"") | K80: =IFERROR(J80/F80-1,"") | L80: =[78]Main!$C$15&" ("&[78]Main!$C$14&")" | M80: 46337 | N80: Earnings Nov 11 (est.) · Readout ~2027-06: Psoriasis, Phase 2
B81: CRSP | C81: CRISPR Therapeutics AG | D81: Biotechnology | E81: NASDAQ | F81: 49.88 | G81: =F81*[79]Main!$C$4 | H81: =G81-[79]Main!$C$7+[79]Main!$C$8 | J81: =IF(ISNUMBER([79]Main!$C$11),[79]Main!$C$11,"") | K81: =IFERROR(J81/F81-1,"") | L81: =[79]Main!$C$15&" ("&[79]Main!$C$14&")" | M81: 46335 | N81: Earnings Nov 9 (est.) · Readout ~2027-06: Lipids / cardiometabolic, Phase 1
B82: RGC | C82: Regencell Bioscience Holdings Ltd | D82: Pharmaceuticals | E82: NASDAQ | F82: 10.45 | G82: =F82*[80]Main!$C$4 | H82: =G82-[80]Main!$C$7+[80]Main!$C$8 | J82: =IF(ISNUMBER([80]Main!$C$11),[80]Main!$C$11,"") | K82: =IFERROR(J82/F82-1,"") | L82: =[80]Main!$C$15&" ("&[80]Main!$C$14&")"
B83: ERAS | C83: Erasca, Inc. | D83: Biotechnology | E83: NASDAQ | F83: 14.62 | G83: =F83*[81]Main!$C$4 | H83: =G83-[81]Main!$C$7+[81]Main!$C$8 | J83: =IF(ISNUMBER([81]Main!$C$11),[81]Main!$C$11,"") | K83: =IFERROR(J83/F83-1,"") | L83: =[81]Main!$C$15&" ("&[81]Main!$C$14&")" | M83: 46337 | N83: Earnings Nov 11 (est.) · Readout ~2028-04: Melanoma, Phase 3
B84: TVTX | C84: Travere Therapeutics, Inc. | D84: Biotechnology | E84: NASDAQ | F84: 52.3 | G84: =F84*[82]Main!$C$4 | H84: =G84-[82]Main!$C$7+[82]Main!$C$8 | J84: =IF(ISNUMBER([82]Main!$C$11),[82]Main!$C$11,"") | K84: =IFERROR(J84/F84-1,"") | L84: =[82]Main!$C$15&" ("&[82]Main!$C$14&")" | M84: 46324 | N84: Earnings Oct 29 (est.)
B85: MANE | C85: Veradermics, Incorporated | D85: Pharmaceuticals | E85: NYSE | F85: 127.23 | G85: =F85*[83]Main!$C$4 | H85: =G85-[83]Main!$C$7+[83]Main!$C$8 | J85: =IF(ISNUMBER([83]Main!$C$11),[83]Main!$C$11,"") | K85: =IFERROR(J85/F85-1,"") | L85: =[83]Main!$C$15&" ("&[83]Main!$C$14&")" | M85: 46336 | N85: Earnings Nov 10 (est.) · Readout ~2026-12: Hidradenitis / alopecia / vitiligo, Phase 3
B86: DFTX | C86: Definium Therapeutics Inc | D86: Pharmaceuticals | E86: NASDAQ | F86: 35.09 | G86: =F86*[84]Main!$C$4 | H86: =G86-[84]Main!$C$7+[84]Main!$C$8 | J86: =IF(ISNUMBER([84]Main!$C$11),[84]Main!$C$11,"") | K86: =IFERROR(J86/F86-1,"") | L86: =[84]Main!$C$15&" ("&[84]Main!$C$14&")" | M86: 46331 | N86: Earnings Nov 5 (est.) · Readout ~2027-08: Anxiety / PTSD / addiction, Phase 3
B87: GOSS | C87: Gossamer Bio, Inc. | D87: Biotechnology | E87: NASDAQ | F87: 9.58 | G87: =F87*[85]Main!$C$4 | H87: =G87-[85]Main!$C$7+[85]Main!$C$8 | J87: =IF(ISNUMBER([85]Main!$C$11),[85]Main!$C$11,"") | K87: =IFERROR(J87/F87-1,"") | L87: =[85]Main!$C$15&" ("&[85]Main!$C$14&")" | M87: 46330 | N87: Earnings Nov 4 (est.)
B88: EWTX | C88: Edgewise Therapeutics, Inc. | D88: Pharmaceuticals | E88: NASDAQ | F88: 39.75 | G88: =F88*[86]Main!$C$4 | H88: =G88-[86]Main!$C$7+[86]Main!$C$8 | J88: =IF(ISNUMBER([86]Main!$C$11),[86]Main!$C$11,"") | K88: =IFERROR(J88/F88-1,"") | L88: =[86]Main!$C$15&" ("&[86]Main!$C$14&")" | M88: 46331 | N88: Earnings Nov 5 (est.) · Readout ~2027-01: Muscular dystrophy / SMA, Phase 2
B89: DNTH | C89: Dianthus Therapeutics Inc | D89: Biotechnology | E89: NASDAQ | F89: 78.75 | G89: =F89*[87]Main!$C$4 | H89: =G89-[87]Main!$C$7+[87]Main!$C$8 | J89: =IF(ISNUMBER([87]Main!$C$11),[87]Main!$C$11,"") | K89: =IFERROR(J89/F89-1,"") | L89: =[87]Main!$C$15&" ("&[87]Main!$C$14&")" | M89: 46330 | N89: Earnings Nov 4 (est.) · Readout ~2026-12: Migraine / pain, Phase 3
B90: INDV | C90: Indivior Pharmaceuticals Inc | D90: Pharmaceuticals | E90: NASDAQ | F90: 34.77 | G90: =F90*[88]Main!$C$4 | H90: =G90-[88]Main!$C$7+[88]Main!$C$8 | J90: =IF(ISNUMBER([88]Main!$C$11),[88]Main!$C$11,"") | K90: =IFERROR(J90/F90-1,"") | L90: =[88]Main!$C$15&" ("&[88]Main!$C$14&")" | M90: 46324 | N90: Earnings Oct 29 (est.)
B91: TNGX | C91: Tango Therapeutics, Inc. | D91: Biotechnology | E91: NASDAQ | F91: 25.255 | G91: =F91*[89]Main!$C$4 | H91: =G91-[89]Main!$C$7+[89]Main!$C$8 | J91: =IF(ISNUMBER([89]Main!$C$11),[89]Main!$C$11,"") | K91: =IFERROR(J91/F91-1,"") | L91: =[89]Main!$C$15&" ("&[89]Main!$C$14&")" | M91: 46329 | N91: Earnings Nov 3 (est.)
B92: ARQT | C92: Arcutis Biotherapeutics, Inc. | D92: Biotechnology | E92: NASDAQ | F92: 32.82 | G92: =F92*[90]Main!$C$4 | H92: =G92-[90]Main!$C$7+[90]Main!$C$8 | J92: =IF(ISNUMBER([90]Main!$C$11),[90]Main!$C$11,"") | K92: =IFERROR(J92/F92-1,"") | L92: =[90]Main!$C$15&" ("&[90]Main!$C$14&")" | M92: 46322 | N92: Earnings Oct 27 (est.)
B93: TLX | C93: Telix Pharmaceuticals Limited | D93: Biotechnology | E93: NASDAQ | F93: 11.16 | G93: =F93*[91]Main!$C$4 | H93: =G93-[91]Main!$C$7+[91]Main!$C$8 | J93: =IF(ISNUMBER([91]Main!$C$11),[91]Main!$C$11,"") | K93: =IFERROR(J93/F93-1,"") | L93: =[91]Main!$C$15&" ("&[91]Main!$C$14&")"
B94: OGN | C94: Organon & Co. | D94: Pharmaceuticals | E94: NYSE | F94: 13.755 | G94: =F94*[92]Main!$C$4 | H94: =G94-[92]Main!$C$7+[92]Main!$C$8 | J94: =IF(ISNUMBER([92]Main!$C$11),[92]Main!$C$11,"") | K94: =IFERROR(J94/F94-1,"") | L94: =[92]Main!$C$15&" ("&[92]Main!$C$14&")" | M94: 46335 | N94: Earnings Nov 9 (est.)
B95: RLAY | C95: Relay Therapeutics, Inc. | D95: Biotechnology | E95: NASDAQ | F95: 18.45 | G95: =F95*[93]Main!$C$4 | H95: =G95-[93]Main!$C$7+[93]Main!$C$8 | J95: =IF(ISNUMBER([93]Main!$C$11),[93]Main!$C$11,"") | K95: =IFERROR(J95/F95-1,"") | L95: =[93]Main!$C$15&" ("&[93]Main!$C$14&")" | M95: 46331 | N95: Earnings Nov 5 (est.) · Readout ~2027-04-30: Breast cancer, Phase 3
B96: VCYT | C96: Veracyte, Inc. | D96: Biotechnology | E96: NASDAQ | F96: 44.79 | G96: =F96*[94]Main!$C$4 | H96: =G96-[94]Main!$C$7+[94]Main!$C$8 | J96: =IF(ISNUMBER([94]Main!$C$11),[94]Main!$C$11,"") | K96: =IFERROR(J96/F96-1,"") | L96: =[94]Main!$C$15&" ("&[94]Main!$C$14&")" | M96: 46330 | N96: Earnings Nov 4 (after close)
B97: LEGN | C97: Legend Biotech Corporation | D97: Biotechnology | E97: NASDAQ | F97: 19.01 | G97: =F97*[95]Main!$C$4 | H97: =G97-[95]Main!$C$7+[95]Main!$C$8 | J97: =IF(ISNUMBER([95]Main!$C$11),[95]Main!$C$11,"") | K97: =IFERROR(J97/F97-1,"") | L97: =[95]Main!$C$15&" ("&[95]Main!$C$14&")" | M97: 46337 | N97: Earnings Nov 11 (est.)
B98: CDNA | C98: CareDx, Inc. | D98: Biotechnology | E98: NASDAQ | F98: 69.2 | G98: =F98*[96]Main!$C$4 | H98: =G98-[96]Main!$C$7+[96]Main!$C$8 | J98: =IF(ISNUMBER([96]Main!$C$11),[96]Main!$C$11,"") | K98: =IFERROR(J98/F98-1,"") | L98: =[96]Main!$C$15&" ("&[96]Main!$C$14&")" | M98: 46324 | N98: Earnings Oct 29 (after close)
B99: ACAD | C99: Acadia Pharmaceuticals Inc. | D99: Biotechnology | E99: NASDAQ | F99: 20.44 | G99: =F99*[97]Main!$C$4 | H99: =G99-[97]Main!$C$7+[97]Main!$C$8 | J99: =IF(ISNUMBER([97]Main!$C$11),[97]Main!$C$11,"") | K99: =IFERROR(J99/F99-1,"") | L99: =[97]Main!$C$15&" ("&[97]Main!$C$14&")" | M99: 46330 | N99: Earnings Nov 4 (est.)
B100: XENE | C100: Xenon Pharmaceuticals Inc. | D100: Biotechnology | E100: NASDAQ | F100: 36.27 | G100: =F100*[98]Main!$C$4 | H100: =G100-[98]Main!$C$7+[98]Main!$C$8 | J100: =IF(ISNUMBER([98]Main!$C$11),[98]Main!$C$11,"") | K100: =IFERROR(J100/F100-1,"") | L100: =[98]Main!$C$15&" ("&[98]Main!$C$14&")" | M100: 46328 | N100: Earnings Nov 2 (est.) · Readout ~2026-10: Depression / mood, Phase 3
...

Sheet Energy
B2: Ticker | C2: Name | D2: Industry | E2: Exchange | F2: Price | G2: Market Cap | H2: EV
