Workbook

Sheet Main
B2: Aurora Cannabis Inc.
B3: Price | C3: =INDEX([1]Pharma!$F$1:$F$1000,MATCH("ACB",[1]Pharma!$B$1:$B$1000,0)) -> 3.97
B4: Shares | C4: 56.234231
B5: Market Cap. | C5: =C3*C4 -> 223.2499
B7: Cash | C7: =(137.921+0.554)/1.4161 -> 97.786173
B8: Debt | C8: =(2.299+40.194)/1.4161 -> 30.007062
B9: Enterprise V. | C9: =C5-C7+C8 -> 155.47079
B11: NPV / Share | C11: =NPV!B28 -> 9.9086071
B12: Upside | C12: =IFERROR(C11/C3-1,"") -> 1.4958708
B13: Cash / Share | C13: =IFERROR((C7-C8)/C4,"") -> 1.2052999
B14: Scenario | C14: =Assumptions!C4 -> Base
B15: Model | C15: DCF

Sheet Yearly Model
B1: 2018 | C1: 2019 | D1: 2020 | E1: 2021 | F1: 2022 | G1: 2024 | H1: 2025 | I1: 2026 | J1: 2027 | K1: 2028 | L1: 2029 | M1: 2030 | N1: 2031 | O1: 2032 | P1: 2033 | Q1: 2034 | R1: 2035
A2: Revenue | B2: 38.977 | C2: 191.445 | D2: 221.028 | E2: 203.794 | F2: 177.676 | G2: 190.408 | H2: 242.421 | I2: =H2*(1+NPV!C5) -> 284.21438 | J2: =I2*(1+NPV!D5) -> 328.55814 | K2: =J2*(1+NPV!E5) -> 374.43946 | L2: =K2*(1+NPV!F5) -> 420.59536 | M2: =L2*(1+NPV!G5) -> 465.55233 | N2: =M2*(1+NPV!H5) -> 507.68999 | O2: =N2*(1+NPV!I5) -> 545.32674 | P2: =O2*(1+NPV!J5) -> 576.82239 | ... R2: =Q2*(1+NPV!L5) -> 615.70727
A3: Cost of Sales | B3: 0 | C3: 0 | D3: 0 | E3: 0 | F3: 0 | G3: 0 | H3: 0 | I3: =I2*(1-Assumptions!$B$19) -> 0 | J3: =J2*(1-Assumptions!$B$19) -> 0 | K3: =K2*(1-Assumptions!$B$19) -> 0 | L3: =L2*(1-Assumptions!$B$19) -> 0 | M3: =M2*(1-Assumptions!$B$19) -> 0 | N3: =N2*(1-Assumptions!$B$19) -> 0 | O3: =O2*(1-Assumptions!$B$19) -> 0 | P3: =P2*(1-Assumptions!$B$19) -> 0 | ... R3: =R2*(1-Assumptions!$B$19) -> 0
A4: Gross Margin | B4: =B2-B3 -> 38.977 | C4: =C2-C3 -> 191.445 | D4: =D2-D3 -> 221.028 | E4: =E2-E3 -> 203.794 | F4: =F2-F3 -> 177.676 | G4: =G2-G3 -> 190.408 | H4: =H2-H3 -> 242.421 | I4: =I2-I3 -> 284.21438 | ... R4: =R2-R3 -> 615.70727
A5: Research & Dev. | B5: 1.186 | C5: 10.436 | D5: 18.379 | E5: 8.083 | F5: 7.336 | G5: 2.522 | H5: 2.596 | I5: =I7*Assumptions!$B$20 -> 2.9958288 | J5: =J7*Assumptions!$B$20 -> 3.396776 | K5: =K7*Assumptions!$B$20 -> 3.7953663 | L5: =L7*Assumptions!$B$20 -> 4.1781203 | M5: =M7*Assumptions!$B$20 -> 4.5305318 | N5: =N7*Assumptions!$B$20 -> 4.8378876 | O5: =O7*Assumptions!$B$20 -> 5.0862146 | P5: =P7*Assumptions!$B$20 -> 5.2632782 | ... R5: =R7*Assumptions!$B$20 -> 5.3689674
A6: SG&A & Other | B6: 105.423 | C6: 405.766 | D6: 531.568 | E6: 395.426 | F6: 333.781 | G6: 219.734 | H6: 236.331 | I6: =I7-I5 -> 271.85085 | J6: =J7-J5 -> 308.23405 | K6: =K7-K5 -> 344.40337 | L6: =L7-L5 -> 379.13567 | M6: =M7-M5 -> 411.11459 | N6: =N7-N5 -> 439.00501 | O6: =O7-O5 -> 461.53897 | P6: =P7-P5 -> 477.60628 | ... R6: =R7-R5 -> 487.19685
A7: Operating Expense | B7: =SUM(B5:B6) -> 106.609 | C7: =SUM(C5:C6) -> 416.202 | D7: =SUM(D5:D6) -> 549.947 | E7: =SUM(E5:E6) -> 403.509 | F7: =SUM(F5:F6) -> 341.117 | G7: =SUM(G5:G6) -> 222.256 | H7: =SUM(H5:H6) -> 238.927 | I7: =I4-I2*NPV!C6 -> 274.84667 | J7: =J4-J2*NPV!D6 -> 311.63082 | K7: =K4-K2*NPV!E6 -> 348.19874 | L7: =L4-L2*NPV!F6 -> 383.31379 | M7: =M4-M2*NPV!G6 -> 415.64512 | N7: =N4-N2*NPV!H6 -> 443.8429 | O7: =O4-O2*NPV!I6 -> 466.62519 | P7: =P4-P2*NPV!J6 -> 482.86956 | ... R7: =R4-R2*NPV!L6 -> 492.56582
A8: Operating Income | B8: =B4-B7 -> -67.632 | C8: =C4-C7 -> -224.757 | D8: =D4-D7 -> -328.919 | E8: =E4-E7 -> -199.715 | F8: =F4-F7 -> -163.441 | G8: =G4-G7 -> -31.848 | H8: =H4-H7 -> 3.494 | I8: =I4-I7 -> 9.367706 | ... R8: =R4-R7 -> 123.14145
A9: Interest & Other | B9: 124.149 | C9: -3.63 | D9: -2047.276 | E9: -293.423 | F9: -1050.996 | G9: -17.498 | H9: 0.891 | I9: 0 | J9: 0 | K9: 0 | L9: 0 | M9: 0 | N9: 0 | O9: 0 | P9: 0 | Q9: 0 | R9: 0
A10: Pretax | B10: =B8+B9 -> 56.517 | C10: =C8+C9 -> -228.387 | D10: =D8+D9 -> -2376.195 | E10: =E8+E9 -> -493.138 | F10: =F8+F9 -> -1214.437 | G10: =G8+G9 -> -49.346 | H10: =H8+H9 -> 4.385 | I10: =I8+I9 -> 9.367706 | ... R10: =R8+R9 -> 123.14145
A11: Taxes | B11: 5.72 | C11: -21.121 | D11: -58.071 | E11: -4.464 | F11: -1.512 | G11: -0.391 | H11: 3.262 | I11: =MAX(0,I10)*Assumptions!$E$14 -> 1.59251 | J11: =MAX(0,J10)*Assumptions!$E$14 -> 2.8776436 | K11: =MAX(0,K10)*Assumptions!$E$14 -> 4.4609219 | L11: =MAX(0,L10)*Assumptions!$E$14 -> 6.3378674 | M11: =MAX(0,M10)*Assumptions!$E$14 -> 8.4842257 | N11: =MAX(0,N10)*Assumptions!$E$14 -> 10.854006 | O11: =MAX(0,O10)*Assumptions!$E$14 -> 13.379264 | P11: =MAX(0,P10)*Assumptions!$E$14 -> 15.971981 | ... R11: =MAX(0,R10)*Assumptions!$E$14 -> 20.934047
A12: Net Income | B12: 50.799 | C12: -207.266 | D12: -2318.123 | E12: -488.675 | F12: -1212.926 | G12: -48.956 | H12: 1.124 | I12: =I10-I11 -> 7.775196 | J12: =J10-J11 -> 14.049672 | K12: =K10-K11 -> 21.779795 | L12: =L10-L11 -> 30.943706 | M12: =M10-M11 -> 41.422984 | N12: =N10-N11 -> 52.993088 | O12: =O10-O11 -> 65.322291 | P12: =P10-P11 -> 77.98085 | ... R12: =R10-R11 -> 102.20741
A13: Earnings per Share | B13: =IFERROR(B12/B14,0) -> 0.53888423 | C13: =IFERROR(C12/C14,0) -> -1.0202609 | D13: =IFERROR(D12/D14,0) -> -119.79345 | E13: =IFERROR(E12/E14,0) -> -14.447582 | F13: =IFERROR(F12/F14,0) -> -28.218738 | G13: =IFERROR(G12/G14,0) -> -1.1326377 | H13: =IFERROR(H12/H14,0) -> 0.020207105 | I13: =IFERROR(I12/I14,0) -> 0.13826447 | ... R13: =IFERROR(R12/R14,0) -> 1.8175301
A14: Shares | B14: 94.267 | C14: 203.15 | D14: 19.351 | E14: 33.824 | F14: 42.983 | G14: 43.223 | H14: 55.624 | I14: =Main!$C$4 -> 56.234231 | J14: =Main!$C$4 -> 56.234231 | K14: =Main!$C$4 -> 56.234231 | L14: =Main!$C$4 -> 56.234231 | M14: =Main!$C$4 -> 56.234231 | N14: =Main!$C$4 -> 56.234231 | O14: =Main!$C$4 -> 56.234231 | P14: =Main!$C$4 -> 56.234231 | ... R14: =Main!$C$4 -> 56.234231
A16: Revenue Change | C16: =IFERROR(C2/B2-1,"") -> 3.9117428 | D16: =IFERROR(D2/C2-1,"") -> 0.1545248 | E16: =IFERROR(E2/D2-1,"") -> -0.077972022 | F16: =IFERROR(F2/E2-1,"") -> -0.12815883 | G16: =IFERROR(G2/F2-1,"") -> 0.071658525 | H16: =IFERROR(H2/G2-1,"") -> 0.27316604 | I16: =IFERROR(I2/H2-1,"") -> 0.1724 | J16: =IFERROR(J2/I2-1,"") -> 0.15602222 | ... R16: =IFERROR(R2/Q2-1,"") -> 0.025
A17: Gross Margin | B17: =IFERROR(B4/B2,"") -> 1 | C17: =IFERROR(C4/C2,"") -> 1 | D17: =IFERROR(D4/D2,"") -> 1 | E17: =IFERROR(E4/E2,"") -> 1 | F17: =IFERROR(F4/F2,"") -> 1 | G17: =IFERROR(G4/G2,"") -> 1 | H17: =IFERROR(H4/H2,"") -> 1 | I17: =IFERROR(I4/I2,"") -> 1 | ... R17: =IFERROR(R4/R2,"") -> 1
A18: Operating Margin | B18: =IFERROR(B8/B2,"") -> -1.7351772 | C18: =IFERROR(C8/C2,"") -> -1.174003 | D18: =IFERROR(D8/D2,"") -> -1.4881327 | E18: =IFERROR(E8/E2,"") -> -0.97998469 | F18: =IFERROR(F8/F2,"") -> -0.91988226 | G18: =IFERROR(G8/G2,"") -> -0.16726188 | H18: =IFERROR(H8/H2,"") -> 0.014412943 | I18: =IFERROR(I8/I2,"") -> 0.03296 | ... R18: =IFERROR(R8/R2,"") -> 0.2
A19: Actual / Estimate | B19: A | C19: A | D19: A | E19: A | F19: A | G19: A | H19: A | I19: E | J19: E | K19: E | L19: E | M19: E | N19: E | O19: E | P19: E | Q19: E | R19: E

Sheet Quarterly Model

Sheet Assumptions
A1: Aurora Cannabis Inc.: basic DCF assumptions
A2: Blue = input, black = formula, green = link. $mm unless noted.
A4: Scenario (1 Bear, 2 Base, 3 Bull) | B4: 2 | C4: =CHOOSE($B$4,"Bear","Base","Bull") -> Base
A6: Discount rate override (blank = scenario)
A7: Terminal growth override (blank = scenario)
A9: Parameter | B9: Bear | C9: Base | D9: Bull | E9: Live
A10: Discount rate | B10: 0.135 | C10: 0.125 | D10: 0.115 | E10: =IF(ISNUMBER($B$6),$B$6,CHOOSE($B$4,B10,C10,D10)) -> 0.125
A11: Terminal growth | B11: 0.02 | C11: 0.025 | D11: 0.03 | E11: =IF(ISNUMBER($B$7),$B$7,CHOOSE($B$4,B11,C11,D11)) -> 0.025
A12: Revenue growth, first forecast year | B12: 0.1224 | C12: 0.1724 | D12: 0.2224 | E12: =CHOOSE($B$4,B12,C12,D12) -> 0.1724
A13: Operating margin, year 10 | B13: 0.15 | C13: 0.2 | D13: 0.25 | E13: =CHOOSE($B$4,B13,C13,D13) -> 0.2
A14: Tax rate on operating income | B14: 0.17 | C14: 0.17 | D14: 0.17 | E14: =CHOOSE($B$4,B14,C14,D14) -> 0.17
A15: Reinvestment, % of revenue increase | B15: 0.25 | C15: 0.25 | D15: 0.25 | E15: =CHOOSE($B$4,B15,C15,D15) -> 0.25
A17: Single inputs
A18: Starting operating margin (TTM) | B18: 0.0144
A19: Gross margin (forecast) | B19: 1
A20: R&D share of operating expense (forecast) | B20: 0.0109
A21: Forecast years | B21: 10
A22: First forecast year, fraction after balance sheet date | B22: 1
A23: Balance sheet date | B23: 45747
A24: Reporting currency per USD (CAD) | B24: 1.4161
A25: Base revenue, FY2025 | B25: ='Yearly Model'!H2 -> 242.421
A27: Scenario summary
A28: Scenario | B28: Enterprise value | C28: Equity value | D28: NPV / share | E28: Upside
A29: Live | B29: =NPV!B23 -> 489.42379 | C29: =NPV!B26 -> 557.2029 | D29: =NPV!B28 -> 9.9086071 | E29: =NPV!B30 -> 1.4958708
A30: 1 | B30: 248.66918 | C30: 316.44829 | D30: 5.627325 | E30: 0.41746221
A31: 2 | B31: 489.42379 | C31: 557.2029 | D31: 9.9086071 | E31: 1.4958708
A32: 3 | B32: 929.87347 | C32: 997.65258 | D32: 17.741019 | E32: 3.4687706
A35: NPV / share: discount rate (rows) x terminal growth (columns)
A36: =NPV!B28 -> 9.9086071 | B36: 0.015 | C36: 0.02 | D36: 0.025 | E36: 0.03 | F36: 0.035
A37: 0.105 | B37: 11.803495 | C37: 12.397105 | D37: 13.065304 | E37: 13.823018 | F37: 14.689434
A38: 0.115 | B38: 10.339211 | C38: 10.792812 | D38: 11.297133 | E38: 11.86113 | F38: 12.495999
A39: 0.125 | B39: 9.1645841 | C39: 9.518753 | D39: 9.9086071 | E39: 10.339785 | F39: 10.819179
A40: 0.135 | B40: 8.2054402 | C40: 8.4869293 | D40: 8.7942359 | E40: 9.1310519 | F40: 9.5018076
A41: 0.145 | B41: 7.4105851 | C41: 7.6376664 | D41: 7.8838664 | E41: 8.1516819 | F41: 8.4440638

Sheet NPV
A1: Aurora Cannabis Inc.: free-cash-flow DCF ($mm)
A3: Fiscal year | B3: ='Yearly Model'!H1 -> 2025 | C3: ='Yearly Model'!I1 -> 2026 | D3: ='Yearly Model'!J1 -> 2027 | E3: ='Yearly Model'!K1 -> 2028 | F3: ='Yearly Model'!L1 -> 2029 | G3: ='Yearly Model'!M1 -> 2030 | H3: ='Yearly Model'!N1 -> 2031 | I3: ='Yearly Model'!O1 -> 2032 | ... L3: ='Yearly Model'!R1 -> 2035
A4: Period | B4: Actual | C4: 1 | D4: 2 | E4: 3 | F4: 4 | G4: 5 | H4: 6 | I4: 7 | J4: 8 | K4: 9 | L4: 10
A5: Revenue growth | C5: =Assumptions!$E$12+(Assumptions!$E$11-Assumptions!$E$12)*(C4-1)/(Assumptions!$B$21-1) -> 0.1724 | D5: =Assumptions!$E$12+(Assumptions!$E$11-Assumptions!$E$12)*(D4-1)/(Assumptions!$B$21-1) -> 0.15602222 | E5: =Assumptions!$E$12+(Assumptions!$E$11-Assumptions!$E$12)*(E4-1)/(Assumptions!$B$21-1) -> 0.13964444 | F5: =Assumptions!$E$12+(Assumptions!$E$11-Assumptions!$E$12)*(F4-1)/(Assumptions!$B$21-1) -> 0.12326667 | G5: =Assumptions!$E$12+(Assumptions!$E$11-Assumptions!$E$12)*(G4-1)/(Assumptions!$B$21-1) -> 0.10688889 | H5: =Assumptions!$E$12+(Assumptions!$E$11-Assumptions!$E$12)*(H4-1)/(Assumptions!$B$21-1) -> 0.090511111 | I5: =Assumptions!$E$12+(Assumptions!$E$11-Assumptions!$E$12)*(I4-1)/(Assumptions!$B$21-1) -> 0.074133333 | J5: =Assumptions!$E$12+(Assumptions!$E$11-Assumptions!$E$12)*(J4-1)/(Assumptions!$B$21-1) -> 0.057755556 | ... L5: =Assumptions!$E$12+(Assumptions!$E$11-Assumptions!$E$12)*(L4-1)/(Assumptions!$B$21-1) -> 0.025
A6: Operating margin | B6: =IFERROR(B8/B7,0) -> 0.014412943 | C6: =Assumptions!$B$18+(Assumptions!$E$13-Assumptions!$B$18)*C4/Assumptions!$B$21 -> 0.03296 | D6: =Assumptions!$B$18+(Assumptions!$E$13-Assumptions!$B$18)*D4/Assumptions!$B$21 -> 0.05152 | E6: =Assumptions!$B$18+(Assumptions!$E$13-Assumptions!$B$18)*E4/Assumptions!$B$21 -> 0.07008 | F6: =Assumptions!$B$18+(Assumptions!$E$13-Assumptions!$B$18)*F4/Assumptions!$B$21 -> 0.08864 | G6: =Assumptions!$B$18+(Assumptions!$E$13-Assumptions!$B$18)*G4/Assumptions!$B$21 -> 0.1072 | H6: =Assumptions!$B$18+(Assumptions!$E$13-Assumptions!$B$18)*H4/Assumptions!$B$21 -> 0.12576 | I6: =Assumptions!$B$18+(Assumptions!$E$13-Assumptions!$B$18)*I4/Assumptions!$B$21 -> 0.14432 | J6: =Assumptions!$B$18+(Assumptions!$E$13-Assumptions!$B$18)*J4/Assumptions!$B$21 -> 0.16288 | ... L6: =Assumptions!$B$18+(Assumptions!$E$13-Assumptions!$B$18)*L4/Assumptions!$B$21 -> 0.2
A7: Revenue | B7: ='Yearly Model'!H2 -> 242.421 | C7: ='Yearly Model'!I2 -> 284.21438 | D7: ='Yearly Model'!J2 -> 328.55814 | E7: ='Yearly Model'!K2 -> 374.43946 | F7: ='Yearly Model'!L2 -> 420.59536 | G7: ='Yearly Model'!M2 -> 465.55233 | H7: ='Yearly Model'!N2 -> 507.68999 | I7: ='Yearly Model'!O2 -> 545.32674 | ... L7: ='Yearly Model'!R2 -> 615.70727
A8: Operating income | B8: ='Yearly Model'!H8 -> 3.494 | C8: ='Yearly Model'!I8 -> 9.367706 | D8: ='Yearly Model'!J8 -> 16.927315 | E8: ='Yearly Model'!K8 -> 26.240717 | F8: ='Yearly Model'!L8 -> 37.281573 | G8: ='Yearly Model'!M8 -> 49.90721 | H8: ='Yearly Model'!N8 -> 63.847093 | I8: ='Yearly Model'!O8 -> 78.701556 | ... L8: ='Yearly Model'!R8 -> 123.14145
A9: Tax on operating income | C9: =MAX(0,C8)*Assumptions!$E$14 -> 1.59251 | D9: =MAX(0,D8)*Assumptions!$E$14 -> 2.8776436 | E9: =MAX(0,E8)*Assumptions!$E$14 -> 4.4609219 | F9: =MAX(0,F8)*Assumptions!$E$14 -> 6.3378674 | G9: =MAX(0,G8)*Assumptions!$E$14 -> 8.4842257 | H9: =MAX(0,H8)*Assumptions!$E$14 -> 10.854006 | I9: =MAX(0,I8)*Assumptions!$E$14 -> 13.379264 | J9: =MAX(0,J8)*Assumptions!$E$14 -> 15.971981 | ... L9: =MAX(0,L8)*Assumptions!$E$14 -> 20.934047
A10: NOPAT | C10: =C8-C9 -> 7.775196 | D10: =D8-D9 -> 14.049672 | E10: =E8-E9 -> 21.779795 | F10: =F8-F9 -> 30.943706 | G10: =G8-G9 -> 41.422984 | H10: =H8-H9 -> 52.993088 | I10: =I8-I9 -> 65.322291 | J10: =J8-J9 -> 77.98085 | ... L10: =L8-L9 -> 102.20741
A11: Reinvestment | C11: =(C7-B7)*Assumptions!$E$15 -> 10.448345 | D11: =(D7-C7)*Assumptions!$E$15 -> 11.08594 | E11: =(E7-D7)*Assumptions!$E$15 -> 11.47033 | F11: =(F7-E7)*Assumptions!$E$15 -> 11.538976 | G11: =(G7-F7)*Assumptions!$E$15 -> 11.239243 | H11: =(H7-G7)*Assumptions!$E$15 -> 10.534415 | I11: =(I7-H7)*Assumptions!$E$15 -> 9.4091879 | J11: =(J7-I7)*Assumptions!$E$15 -> 7.8739123 | ... L11: =(L7-K7)*Assumptions!$E$15 -> 3.7543126
A12: Free cash flow | C12: =C10-C11 -> -2.6731491 | D12: =D10-D11 -> 2.9637319 | E12: =E10-E11 -> 10.309466 | F12: =F10-F11 -> 19.40473 | G12: =G10-G11 -> 30.183742 | H12: =H10-H11 -> 42.458673 | I12: =I10-I11 -> 55.913103 | J12: =J10-J11 -> 70.106938 | ... L12: =L10-L11 -> 98.453095
A13: Year fraction | C13: =Assumptions!$B$22 -> 1 | D13: 1 | E13: 1 | F13: 1 | G13: 1 | H13: 1 | I13: 1 | J13: 1 | K13: 1 | L13: 1
A14: Discount time (mid-period) | C14: =C13/2 -> 0.5 | D14: =C14+C13/2+D13/2 -> 1.5 | E14: =D14+D13/2+E13/2 -> 2.5 | F14: =E14+E13/2+F13/2 -> 3.5 | G14: =F14+F13/2+G13/2 -> 4.5 | H14: =G14+G13/2+H13/2 -> 5.5 | I14: =H14+H13/2+I13/2 -> 6.5 | J14: =I14+I13/2+J13/2 -> 7.5 | K14: =J14+J13/2+K13/2 -> 8.5 | L14: =K14+K13/2+L13/2 -> 9.5
A15: Discount factor | C15: =1/(1+Assumptions!$E$10)^C14 -> 0.94280904 | D15: =1/(1+Assumptions!$E$10)^D14 -> 0.83805248 | E15: =1/(1+Assumptions!$E$10)^E14 -> 0.74493554 | F15: =1/(1+Assumptions!$E$10)^F14 -> 0.66216492 | G15: =1/(1+Assumptions!$E$10)^G14 -> 0.58859104 | H15: =1/(1+Assumptions!$E$10)^H14 -> 0.52319204 | I15: =1/(1+Assumptions!$E$10)^I14 -> 0.46505959 | J15: =1/(1+Assumptions!$E$10)^J14 -> 0.4133863 | ... L15: =1/(1+Assumptions!$E$10)^L14 -> 0.32662621
A16: PV of free cash flow | C16: =C12*C13*C15 -> -2.5202692 | D16: =D12*D13*D15 -> 2.4837629 | E16: =E12*E13*E15 -> 7.6798873 | F16: =F12*F13*F15 -> 12.849131 | G16: =G12*G13*G15 -> 17.76588 | H16: =H12*H13*H15 -> 22.21404 | I16: =I12*I13*I15 -> 26.002925 | J16: =J12*J13*J15 -> 28.981248 | ... L16: =L12*L13*L15 -> 32.157362
A19: PV of forecast free cash flow | B19: =SUM(C16:L16) -> 178.66171
A20: Terminal free cash flow (year 11) | B20: =L10*(1+Assumptions!$E$11)-L7*Assumptions!$E$11*Assumptions!$E$15 -> 100.91442
A21: Terminal value | B21: =B20/(Assumptions!$E$10-Assumptions!$E$11) -> 1009.1442
A22: PV of terminal value | B22: =B21/(1+Assumptions!$E$10)^(L14+0.5) -> 310.76207
A23: Enterprise value | B23: =B19+B22 -> 489.42379
A24: Cash & investments | B24: =Main!C7 -> 97.786173
A25: Debt | B25: =Main!C8 -> 30.007062
A26: Equity value | B26: =B23+B24-B25 -> 557.2029
A27: Shares (mm) | B27: =Main!C4 -> 56.234231
A28: NPV / share | B28: =B26/B27 -> 9.9086071
A29: Price | B29: =Main!C3 -> 3.97
A30: Upside | B30: =B28/B29-1 -> 1.4958708
A31: Terminal value, % of EV | B31: =IFERROR(B22/B23,0) -> 0.63495499
