Workbook

Sheet Main
B2: Amphastar Pharmaceuticals, Inc.
B3: Price | C3: =INDEX([1]Pharma!$F$1:$F$1000,MATCH("AMPH",[1]Pharma!$B$1:$B$1000,0)) -> 25.94
B4: Shares | C4: 42.537944
B5: Market Cap. | C5: =C3*C4 -> 1103.4343
B7: Cash | C7: =223.614+66.509 -> 290.123
B8: Debt | C8: =2.488+609.564 -> 612.052
B9: Enterprise V. | C9: =C5-C7+C8 -> 1425.3633
B11: NPV / Share | C11: =NPV!B28 -> 29.90882
B12: Upside | C12: =IFERROR(C11/C3-1,"") -> 0.15300001
B13: Cash / Share | C13: =IFERROR((C7-C8)/C4,"") -> -7.5680433
B14: Scenario | C14: =Assumptions!C4 -> Base
B15: Model | C15: DCF

Sheet Yearly Model
B1: 2012 | C1: 2013 | D1: 2014 | E1: 2015 | F1: 2016 | G1: 2017 | H1: 2018 | I1: 2019 | J1: 2020 | K1: 2021 | L1: 2022 | M1: 2023 | N1: 2024 | O1: 2025 | P1: 2026 | Q1: 2027 | R1: 2028 | S1: 2029 | T1: 2030 | U1: 2031 | V1: 2032 | W1: 2033 | X1: 2034 | Y1: 2035
A2: Revenue | B2: 204.323 | C2: 229.681 | D2: 210.461 | E2: 251.519 | F2: 255.165 | G2: 240.175 | H2: 294.666 | I2: 322.357 | J2: 349.846 | K2: 437.768 | L2: 498.987 | M2: 644.395 | N2: 731.967 | O2: 719.887 | P2: =O2*(1+NPV!C5) -> 741.05168 | Q2: =P2*(1+NPV!D5) -> 762.47631 | R2: =Q2*(1+NPV!E5) -> 784.14758 | S2: =R2*(1+NPV!F5) -> 806.05143 | T2: =S2*(1+NPV!G5) -> 828.17307 | U2: =T2*(1+NPV!H5) -> 850.49693 | V2: =U2*(1+NPV!I5) -> 873.00675 | W2: =V2*(1+NPV!J5) -> 895.68552 | ... Y2: =X2*(1+NPV!L5) -> 941.47844
A3: Cost of Sales | B3: 114.02 | C3: 142.725 | D3: 159.205 | E3: 174.172 | F3: 150.969 | G3: 149.666 | H3: 187.681 | I3: 190.434 | J3: 206.506 | K3: 238.029 | L3: 250.127 | M3: 293.274 | N3: 358.112 | O3: 363.83 | P3: =P2*(1-Assumptions!$B$19) -> 374.52752 | Q3: =Q2*(1-Assumptions!$B$19) -> 385.35552 | R3: =R2*(1-Assumptions!$B$19) -> 396.30819 | S3: =S2*(1-Assumptions!$B$19) -> 407.37839 | T3: =T2*(1-Assumptions!$B$19) -> 418.55867 | U3: =U2*(1-Assumptions!$B$19) -> 429.84115 | V3: =V2*(1-Assumptions!$B$19) -> 441.21761 | W3: =W2*(1-Assumptions!$B$19) -> 452.67946 | ... Y3: =Y2*(1-Assumptions!$B$19) -> 475.8232
A4: Gross Margin | B4: =B2-B3 -> 90.303 | C4: =C2-C3 -> 86.956 | D4: =D2-D3 -> 51.256 | E4: =E2-E3 -> 77.347 | F4: =F2-F3 -> 104.196 | G4: =G2-G3 -> 90.509 | H4: =H2-H3 -> 106.985 | I4: =I2-I3 -> 131.923 | ... Y4: =Y2-Y3 -> 465.65524
A5: Research & Dev. | B5: 31.163 | C5: 33.019 | D5: 28.866 | E5: 37.271 | F5: 41.522 | G5: 43.503 | H5: 57.564 | I5: 68.853 | J5: 67.229 | K5: 60.932 | L5: 74.771 | M5: 73.741 | N5: 73.914 | O5: 85.844 | P5: =P7*Assumptions!$B$20 -> 97.318781 | Q5: =Q7*Assumptions!$B$20 -> 97.667615 | R5: =R7*Assumptions!$B$20 -> 97.908732 | S5: =S7*Assumptions!$B$20 -> 98.03803 | T5: =T7*Assumptions!$B$20 -> 98.0515 | U5: =U7*Assumptions!$B$20 -> 97.945241 | V5: =V7*Assumptions!$B$20 -> 97.715467 | W5: =W7*Assumptions!$B$20 -> 97.35853 | ... Y5: =Y7*Assumptions!$B$20 -> 96.249299
A6: SG&A & Other | B6: 33.743 | C6: 36.447 | D6: 40.373 | E6: 46.974 | F6: 47.298 | G6: 48.275 | H6: 58.044 | I6: 63.109 | J6: 65.157 | K6: 68.92 | L6: 66.592 | M6: 80.393 | N6: 94.522 | O6: 129.81 | P6: =P7-P5 -> 147.13935 | Q6: =Q7-Q5 -> 147.66676 | R6: =R7-R5 -> 148.03131 | S6: =S7-S5 -> 148.2268 | T6: =T7-T5 -> 148.24717 | U6: =U7-U5 -> 148.08651 | V6: =V7-V5 -> 147.73911 | W6: =W7-W5 -> 147.19945 | ... Y6: =Y7-Y5 -> 145.52236
A7: Operating Expense | B7: =SUM(B5:B6) -> 64.906 | C7: =SUM(C5:C6) -> 69.466 | D7: =SUM(D5:D6) -> 69.239 | E7: =SUM(E5:E6) -> 84.245 | F7: =SUM(F5:F6) -> 88.82 | G7: =SUM(G5:G6) -> 91.778 | H7: =SUM(H5:H6) -> 115.608 | I7: =SUM(I5:I6) -> 131.962 | ... O7: =SUM(O5:O6) -> 215.654 | P7: =P4-P2*NPV!C6 -> 244.45813 | Q7: =Q4-Q2*NPV!D6 -> 245.33438 | R7: =R4-R2*NPV!E6 -> 245.94005 | S7: =S4-S2*NPV!F6 -> 246.26483 | T7: =T4-T2*NPV!G6 -> 246.29867 | U7: =U4-U2*NPV!H6 -> 246.03175 | V7: =V4-V2*NPV!I6 -> 245.45458 | W7: =W4-W2*NPV!J6 -> 244.55798 | ... Y7: =Y4-Y2*NPV!L6 -> 241.77166
A8: Operating Income | B8: =B4-B7 -> 25.397 | C8: =C4-C7 -> 17.49 | D8: =D4-D7 -> -17.983 | E8: =E4-E7 -> -6.898 | F8: =F4-F7 -> 15.376 | G8: =G4-G7 -> -1.269 | H8: =H4-H7 -> -8.623 | I8: =I4-I7 -> -0.039 | ... Y8: =Y4-Y7 -> 223.88357
A9: Interest & Other | B9: 0.481 | C9: -0.263 | D9: -0.165 | E9: -3.466 | F9: -0.746 | G9: 2.518 | H9: -0.381 | I9: 62.701 | J9: -6.011 | K9: 12.859 | L9: 7.366 | M9: -27.609 | N9: -16.228 | O9: -16.779 | P9: 0 | Q9: 0 | R9: 0 | S9: 0 | T9: 0 | U9: 0 | V9: 0 | W9: 0 | X9: 0 | Y9: 0
A10: Pretax | B10: =B8+B9 -> 25.878 | C10: =C8+C9 -> 17.227 | D10: =D8+D9 -> -18.148 | E10: =E8+E9 -> -10.364 | F10: =F8+F9 -> 14.63 | G10: =G8+G9 -> 1.249 | H10: =H8+H9 -> -9.004 | I10: =I8+I9 -> 62.662 | ... Y10: =Y8+Y9 -> 223.88357
A11: Taxes | B11: 7.784 | C11: 5.365 | D11: -7.449 | E11: -7.577 | F11: 4.81 | G11: -2.398 | H11: -3.266 | I11: 13.723 | J11: 3.54 | K11: 20.63 | L11: 23.477 | M11: 31.833 | N11: 29.672 | O11: 25.53 | P11: =MAX(0,P10)*Assumptions!$E$14 -> 20.751226 | Q11: =MAX(0,Q10)*Assumptions!$E$14 -> 22.403689 | R11: =MAX(0,R10)*Assumptions!$E$14 -> 24.122889 | S11: =MAX(0,S10)*Assumptions!$E$14 -> 25.909395 | T11: =MAX(0,T10)*Assumptions!$E$14 -> 27.763674 | U11: =MAX(0,U10)*Assumptions!$E$14 -> 29.686085 | V11: =MAX(0,V10)*Assumptions!$E$14 -> 31.676875 | W11: =MAX(0,W10)*Assumptions!$E$14 -> 33.736174 | ... Y11: =MAX(0,Y10)*Assumptions!$E$14 -> 38.060208
A12: Net Income | B12: 18.094 | C12: 11.862 | D12: -10.699 | E12: -2.787 | F12: 9.82 | G12: 3.647 | H12: -5.738 | I12: 48.939 | J12: 1.403 | K12: 62.116 | L12: 91.386 | M12: 137.545 | N12: 159.519 | O12: 98.094 | P12: =P10-P11 -> 101.31481 | Q12: =Q10-Q11 -> 109.38272 | R12: =R10-R11 -> 117.77646 | S12: =S10-S11 -> 126.49881 | T12: =T10-T11 -> 135.55205 | U12: =U10-U11 -> 144.93794 | V12: =V10-V11 -> 154.65769 | W12: =W10-W11 -> 164.71191 | ... Y12: =Y10-Y11 -> 185.82337
A13: Earnings per Share | B13: =IFERROR(B12/B14,0) -> 0.46466359 | C13: =IFERROR(C12/C14,0) -> 0.30506905 | D13: =IFERROR(D12/D14,0) -> -0.25499917 | E13: =IFERROR(E12/E14,0) -> -0.061987055 | F13: =IFERROR(F12/F14,0) -> 0.20671943 | G13: =IFERROR(G12/G14,0) -> 0.075402651 | H13: =IFERROR(H12/H14,0) -> -0.12367712 | I13: =IFERROR(I12/I14,0) -> 0.98060392 | ... Y13: =IFERROR(Y12/Y14,0) -> 4.3684144
A14: Shares | B14: 38.94 | C14: 38.883 | D14: 41.957 | E14: 44.961 | F14: 47.504 | G14: 48.367 | H14: 46.395 | I14: 49.907 | J14: 49.124 | K14: 49.784 | L14: 52.427 | M14: 53.001 | N14: 52.058 | O14: 48.215 | P14: =Main!$C$4 -> 42.537944 | Q14: =Main!$C$4 -> 42.537944 | R14: =Main!$C$4 -> 42.537944 | S14: =Main!$C$4 -> 42.537944 | T14: =Main!$C$4 -> 42.537944 | U14: =Main!$C$4 -> 42.537944 | V14: =Main!$C$4 -> 42.537944 | W14: =Main!$C$4 -> 42.537944 | ... Y14: =Main!$C$4 -> 42.537944
A16: Revenue Change | C16: =IFERROR(C2/B2-1,"") -> 0.12410742 | D16: =IFERROR(D2/C2-1,"") -> -0.08368128 | E16: =IFERROR(E2/D2-1,"") -> 0.19508603 | F16: =IFERROR(F2/E2-1,"") -> 0.014495923 | G16: =IFERROR(G2/F2-1,"") -> -0.058746301 | H16: =IFERROR(H2/G2-1,"") -> 0.2268804 | I16: =IFERROR(I2/H2-1,"") -> 0.093974195 | J16: =IFERROR(J2/I2-1,"") -> 0.085275021 | ... Y16: =IFERROR(Y2/X2-1,"") -> 0.025
A17: Gross Margin | B17: =IFERROR(B4/B2,"") -> 0.44196199 | C17: =IFERROR(C4/C2,"") -> 0.37859466 | D17: =IFERROR(D4/D2,"") -> 0.24354156 | E17: =IFERROR(E4/E2,"") -> 0.30751951 | F17: =IFERROR(F4/F2,"") -> 0.40834754 | G17: =IFERROR(G4/G2,"") -> 0.37684605 | H17: =IFERROR(H4/H2,"") -> 0.36307209 | I17: =IFERROR(I4/I2,"") -> 0.40924503 | ... Y17: =IFERROR(Y4/Y2,"") -> 0.4946
A18: Operating Margin | B18: =IFERROR(B8/B2,"") -> 0.12429829 | C18: =IFERROR(C8/C2,"") -> 0.076149094 | D18: =IFERROR(D8/D2,"") -> -0.08544576 | E18: =IFERROR(E8/E2,"") -> -0.027425363 | F18: =IFERROR(F8/F2,"") -> 0.060259048 | G18: =IFERROR(G8/G2,"") -> -0.0052836473 | H18: =IFERROR(H8/H2,"") -> -0.029263641 | I18: =IFERROR(I8/I2,"") -> -0.00012098388 | ... Y18: =IFERROR(Y8/Y2,"") -> 0.2378
A19: Actual / Estimate | B19: A | C19: A | D19: A | E19: A | F19: A | G19: A | H19: A | I19: A | J19: A | K19: A | L19: A | M19: A | N19: A | O19: A | P19: E | Q19: E | R19: E | S19: E | T19: E | U19: E | V19: E | W19: E | X19: E | Y19: E

Sheet Quarterly Model

Sheet Assumptions
A1: Amphastar Pharmaceuticals, Inc.: basic DCF assumptions
A2: Blue = input, black = formula, green = link. $mm unless noted.
A4: Scenario (1 Bear, 2 Base, 3 Bull) | B4: 2 | C4: =CHOOSE($B$4,"Bear","Base","Bull") -> Base
A6: Discount rate override (blank = scenario)
A7: Terminal growth override (blank = scenario)
A9: Parameter | B9: Bear | C9: Base | D9: Bull | E9: Live
A10: Discount rate | B10: 0.12 | C10: 0.11 | D10: 0.1 | E10: =IF(ISNUMBER($B$6),$B$6,CHOOSE($B$4,B10,C10,D10)) -> 0.11
A11: Terminal growth | B11: 0.02 | C11: 0.025 | D11: 0.03 | E11: =IF(ISNUMBER($B$7),$B$7,CHOOSE($B$4,B11,C11,D11)) -> 0.025
A12: Revenue growth, first forecast year | B12: -0.0206 | C12: 0.0294 | D12: 0.0794 | E12: =CHOOSE($B$4,B12,C12,D12) -> 0.0294
A13: Operating margin, year 10 | B13: 0.1878 | C13: 0.2378 | D13: 0.2878 | E13: =CHOOSE($B$4,B13,C13,D13) -> 0.2378
A14: Tax rate on operating income | B14: 0.17 | C14: 0.17 | D14: 0.17 | E14: =CHOOSE($B$4,B14,C14,D14) -> 0.17
A15: Reinvestment, % of revenue increase | B15: 0.25 | C15: 0.25 | D15: 0.25 | E15: =CHOOSE($B$4,B15,C15,D15) -> 0.25
A17: Single inputs
A18: Starting operating margin (TTM) | B18: 0.1566
A19: Gross margin (forecast) | B19: 0.4946
A20: R&D share of operating expense (forecast) | B20: 0.3981
A21: Forecast years | B21: 10
A22: First forecast year, fraction after balance sheet date | B22: 0.5041
A23: Balance sheet date | B23: 46203
A24: Reporting currency per USD (USD) | B24: 1
A25: Base revenue, FY2025 | B25: ='Yearly Model'!O2 -> 719.887
A27: Scenario summary
A28: Scenario | B28: Enterprise value | C28: Equity value | D28: NPV / share | E28: Upside
A29: Live | B29: =NPV!B23 -> 1594.1887 | C29: =NPV!B26 -> 1272.2597 | D29: =NPV!B28 -> 29.90882 | E29: =NPV!B30 -> 0.15300001
A30: 1 | B30: 952.10053 | C30: 630.17153 | D30: 14.814339 | E30: -0.4288998
A31: 2 | B31: 1594.1887 | C31: 1272.2597 | D31: 29.90882 | E31: 0.15300001
A32: 3 | B32: 2778.9832 | C32: 2457.0542 | D32: 57.76147 | E32: 1.2267336
A35: NPV / share: discount rate (rows) x terminal growth (columns)
A36: =NPV!B28 -> 29.90882 | B36: 0.015 | C36: 0.02 | D36: 0.025 | E36: 0.03 | F36: 0.035
A37: 0.09 | B37: 36.715311 | C37: 39.174732 | D37: 42.009679 | E37: 45.314011 | F37: 49.215713
A38: 0.1 | B38: 31.249615 | C38: 33.072822 | D38: 35.136749 | E38: 37.492958 | F38: 40.20888
A39: 0.11 | B39: 26.960066 | C39: 28.353484 | D39: 29.90882 | E39: 31.656416 | F39: 33.634705
A40: 0.12 | B40: 23.508286 | C40: 24.59949 | D40: 25.803826 | E40: 27.140134 | F40: 28.631689
A41: 0.13 | B41: 20.673837 | C41: 21.545586 | D41: 22.498854 | E41: 23.545855 | F41: 24.701377

Sheet NPV
A1: Amphastar Pharmaceuticals, Inc.: free-cash-flow DCF ($mm)
A3: Fiscal year | B3: ='Yearly Model'!O1 -> 2025 | C3: ='Yearly Model'!P1 -> 2026 | D3: ='Yearly Model'!Q1 -> 2027 | E3: ='Yearly Model'!R1 -> 2028 | F3: ='Yearly Model'!S1 -> 2029 | G3: ='Yearly Model'!T1 -> 2030 | H3: ='Yearly Model'!U1 -> 2031 | I3: ='Yearly Model'!V1 -> 2032 | ... L3: ='Yearly Model'!Y1 -> 2035
A4: Period | B4: Actual | C4: 1 | D4: 2 | E4: 3 | F4: 4 | G4: 5 | H4: 6 | I4: 7 | J4: 8 | K4: 9 | L4: 10
A5: Revenue growth | C5: =Assumptions!$E$12+(Assumptions!$E$11-Assumptions!$E$12)*(C4-1)/(Assumptions!$B$21-1) -> 0.0294 | D5: =Assumptions!$E$12+(Assumptions!$E$11-Assumptions!$E$12)*(D4-1)/(Assumptions!$B$21-1) -> 0.028911111 | E5: =Assumptions!$E$12+(Assumptions!$E$11-Assumptions!$E$12)*(E4-1)/(Assumptions!$B$21-1) -> 0.028422222 | F5: =Assumptions!$E$12+(Assumptions!$E$11-Assumptions!$E$12)*(F4-1)/(Assumptions!$B$21-1) -> 0.027933333 | G5: =Assumptions!$E$12+(Assumptions!$E$11-Assumptions!$E$12)*(G4-1)/(Assumptions!$B$21-1) -> 0.027444444 | H5: =Assumptions!$E$12+(Assumptions!$E$11-Assumptions!$E$12)*(H4-1)/(Assumptions!$B$21-1) -> 0.026955556 | I5: =Assumptions!$E$12+(Assumptions!$E$11-Assumptions!$E$12)*(I4-1)/(Assumptions!$B$21-1) -> 0.026466667 | J5: =Assumptions!$E$12+(Assumptions!$E$11-Assumptions!$E$12)*(J4-1)/(Assumptions!$B$21-1) -> 0.025977778 | ... L5: =Assumptions!$E$12+(Assumptions!$E$11-Assumptions!$E$12)*(L4-1)/(Assumptions!$B$21-1) -> 0.025
A6: Operating margin | B6: =IFERROR(B8/B7,0) -> 0.19503478 | C6: =Assumptions!$B$18+(Assumptions!$E$13-Assumptions!$B$18)*C4/Assumptions!$B$21 -> 0.16472 | D6: =Assumptions!$B$18+(Assumptions!$E$13-Assumptions!$B$18)*D4/Assumptions!$B$21 -> 0.17284 | E6: =Assumptions!$B$18+(Assumptions!$E$13-Assumptions!$B$18)*E4/Assumptions!$B$21 -> 0.18096 | F6: =Assumptions!$B$18+(Assumptions!$E$13-Assumptions!$B$18)*F4/Assumptions!$B$21 -> 0.18908 | G6: =Assumptions!$B$18+(Assumptions!$E$13-Assumptions!$B$18)*G4/Assumptions!$B$21 -> 0.1972 | H6: =Assumptions!$B$18+(Assumptions!$E$13-Assumptions!$B$18)*H4/Assumptions!$B$21 -> 0.20532 | I6: =Assumptions!$B$18+(Assumptions!$E$13-Assumptions!$B$18)*I4/Assumptions!$B$21 -> 0.21344 | J6: =Assumptions!$B$18+(Assumptions!$E$13-Assumptions!$B$18)*J4/Assumptions!$B$21 -> 0.22156 | ... L6: =Assumptions!$B$18+(Assumptions!$E$13-Assumptions!$B$18)*L4/Assumptions!$B$21 -> 0.2378
A7: Revenue | B7: ='Yearly Model'!O2 -> 719.887 | C7: ='Yearly Model'!P2 -> 741.05168 | D7: ='Yearly Model'!Q2 -> 762.47631 | E7: ='Yearly Model'!R2 -> 784.14758 | F7: ='Yearly Model'!S2 -> 806.05143 | G7: ='Yearly Model'!T2 -> 828.17307 | H7: ='Yearly Model'!U2 -> 850.49693 | I7: ='Yearly Model'!V2 -> 873.00675 | ... L7: ='Yearly Model'!Y2 -> 941.47844
A8: Operating income | B8: ='Yearly Model'!O8 -> 140.403 | C8: ='Yearly Model'!P8 -> 122.06603 | D8: ='Yearly Model'!Q8 -> 131.7864 | E8: ='Yearly Model'!R8 -> 141.89935 | F8: ='Yearly Model'!S8 -> 152.4082 | G8: ='Yearly Model'!T8 -> 163.31573 | H8: ='Yearly Model'!U8 -> 174.62403 | I8: ='Yearly Model'!V8 -> 186.33456 | ... L8: ='Yearly Model'!Y8 -> 223.88357
A9: Tax on operating income | C9: =MAX(0,C8)*Assumptions!$E$14 -> 20.751226 | D9: =MAX(0,D8)*Assumptions!$E$14 -> 22.403689 | E9: =MAX(0,E8)*Assumptions!$E$14 -> 24.122889 | F9: =MAX(0,F8)*Assumptions!$E$14 -> 25.909395 | G9: =MAX(0,G8)*Assumptions!$E$14 -> 27.763674 | H9: =MAX(0,H8)*Assumptions!$E$14 -> 29.686085 | I9: =MAX(0,I8)*Assumptions!$E$14 -> 31.676875 | J9: =MAX(0,J8)*Assumptions!$E$14 -> 33.736174 | ... L9: =MAX(0,L8)*Assumptions!$E$14 -> 38.060208
A10: NOPAT | C10: =C8-C9 -> 101.31481 | D10: =D8-D9 -> 109.38272 | E10: =E8-E9 -> 117.77646 | F10: =F8-F9 -> 126.49881 | G10: =G8-G9 -> 135.55205 | H10: =H8-H9 -> 144.93794 | I10: =I8-I9 -> 154.65769 | J10: =J8-J9 -> 164.71191 | ... L10: =L8-L9 -> 185.82337
A11: Reinvestment | C11: =(C7-B7)*Assumptions!$E$15 -> 5.2911695 | D11: =(D7-C7)*Assumptions!$E$15 -> 5.3561568 | E11: =(E7-D7)*Assumptions!$E$15 -> 5.4178177 | F11: =(F7-E7)*Assumptions!$E$15 -> 5.4759639 | G11: =(G7-F7)*Assumptions!$E$15 -> 5.5304084 | H11: =(H7-G7)*Assumptions!$E$15 -> 5.5809663 | I11: =(I7-H7)*Assumptions!$E$15 -> 5.6274547 | J11: =(J7-I7)*Assumptions!$E$15 -> 5.6696938 | ... L11: =(L7-K7)*Assumptions!$E$15 -> 5.7407222
A12: Free cash flow | C12: =C10-C11 -> 96.023637 | D12: =D10-D11 -> 104.02656 | E12: =E10-E11 -> 112.35864 | F12: =F10-F11 -> 121.02285 | G12: =G10-G11 -> 130.02165 | H12: =H10-H11 -> 139.35698 | I12: =I10-I11 -> 149.03023 | J12: =J10-J11 -> 159.04222 | ... L12: =L10-L11 -> 180.08264
A13: Year fraction | C13: =Assumptions!$B$22 -> 0.5041 | D13: 1 | E13: 1 | F13: 1 | G13: 1 | H13: 1 | I13: 1 | J13: 1 | K13: 1 | L13: 1
A14: Discount time (mid-period) | C14: =C13/2 -> 0.25205 | D14: =C14+C13/2+D13/2 -> 1.0041 | E14: =D14+D13/2+E13/2 -> 2.0041 | F14: =E14+E13/2+F13/2 -> 3.0041 | G14: =F14+F13/2+G13/2 -> 4.0041 | H14: =G14+G13/2+H13/2 -> 5.0041 | I14: =H14+H13/2+I13/2 -> 6.0041 | J14: =I14+I13/2+J13/2 -> 7.0041 | K14: =J14+J13/2+K13/2 -> 8.0041 | L14: =K14+K13/2+L13/2 -> 9.0041
A15: Discount factor | C15: =1/(1+Assumptions!$E$10)^C14 -> 0.97403899 | D15: =1/(1+Assumptions!$E$10)^D14 -> 0.90051551 | E15: =1/(1+Assumptions!$E$10)^E14 -> 0.81127523 | F15: =1/(1+Assumptions!$E$10)^F14 -> 0.73087859 | G15: =1/(1+Assumptions!$E$10)^G14 -> 0.65844918 | H15: =1/(1+Assumptions!$E$10)^H14 -> 0.59319746 | I15: =1/(1+Assumptions!$E$10)^I14 -> 0.53441213 | J15: =1/(1+Assumptions!$E$10)^J14 -> 0.48145236 | ... L15: =1/(1+Assumptions!$E$10)^L14 -> 0.39075754
A16: PV of free cash flow | C16: =C12*C13*C15 -> 47.14886 | D16: =D12*D13*D15 -> 93.67753 | E16: =E12*E13*E15 -> 91.153781 | F16: =F12*F13*F15 -> 88.453007 | G16: =G12*G13*G15 -> 85.612646 | H16: =H12*H13*H15 -> 82.666205 | I16: =I12*I13*I15 -> 79.643562 | J16: =J12*J13*J15 -> 76.571251 | ... L16: =L12*L13*L15 -> 70.368651
A19: PV of forecast free cash flow | B19: =SUM(C16:L16) -> 788.76823
A20: Terminal free cash flow (year 11) | B20: =L10*(1+Assumptions!$E$11)-L7*Assumptions!$E$11*Assumptions!$E$15 -> 184.58471
A21: Terminal value | B21: =B20/(Assumptions!$E$10-Assumptions!$E$11) -> 2171.5848
A22: PV of terminal value | B22: =B21/(1+Assumptions!$E$10)^(L14+0.5) -> 805.42049
A23: Enterprise value | B23: =B19+B22 -> 1594.1887
A24: Cash & investments | B24: =Main!C7 -> 290.123
A25: Debt | B25: =Main!C8 -> 612.052
A26: Equity value | B26: =B23+B24-B25 -> 1272.2597
A27: Shares (mm) | B27: =Main!C4 -> 42.537944
A28: NPV / share | B28: =B26/B27 -> 29.90882
A29: Price | B29: =Main!C3 -> 25.94
A30: Upside | B30: =B28/B29-1 -> 0.15300001
A31: Terminal value, % of EV | B31: =IFERROR(B22/B23,0) -> 0.5052228
