Workbook

Sheet Main
B2: Aquestive Therapeutics, Inc.
B3: Price | C3: =INDEX([1]Pharma!$F$1:$F$1000,MATCH("AQST",[1]Pharma!$B$1:$B$1000,0)) -> 4.05
B4: Shares | C4: 125.51165
B5: Market Cap. | C5: =C3*C4 -> 508.32217
B7: Cash | C7: 98.49
B8: Debt | C8: =0.032+50.654 -> 50.686
B9: Enterprise V. | C9: =C5-C7+C8 -> 460.51817
B11: NPV / Share | C11: =NPV!B28 -> 0.24887018
B12: Upside | C12: =IFERROR(C11/C3-1,"") -> -0.93855057
B13: Cash / Share | C13: =IFERROR((C7-C8)/C4,"") -> 0.38087302
B14: Scenario | C14: =Assumptions!C4 -> Base
B15: Model | C15: DCF

Sheet Yearly Model
B1: 2017 | C1: 2018 | D1: 2019 | E1: 2020 | F1: 2021 | G1: 2022 | H1: 2023 | I1: 2024 | J1: 2025 | K1: 2026 | L1: 2027 | M1: 2028 | N1: 2029 | O1: 2030 | P1: 2031 | Q1: 2032 | R1: 2033 | S1: 2034 | T1: 2035
A2: Revenue | B2: 66.918 | C2: 67.43 | D2: 52.609 | E2: 45.849 | F2: 50.832 | G2: 47.68 | H2: 50.583 | I2: 57.561 | J2: 44.545 | K2: =J2*(1+NPV!C5) -> 50.69221 | L2: =K2*(1+NPV!D5) -> 57.051266 | M2: =L2*(1+NPV!E5) -> 63.49172 | N2: =M2*(1+NPV!F5) -> 69.862056 | O2: =N2*(1+NPV!G5) -> 75.994392 | P2: =O2*(1+NPV!H5) -> 81.710859 | Q2: =P2*(1+NPV!I5) -> 86.831406 | R2: =Q2*(1+NPV!J5) -> 91.182625 | ... T2: =S2*(1+NPV!L5) -> 96.972215
A3: Cost of Sales | B3: 0 | C3: 0 | D3: 20.361 | E3: 12.964 | F3: 0 | G3: 19.386 | H3: 20.831 | I3: 17.872 | J3: 18.555 | K3: =K2*(1-Assumptions!$B$19) -> 21.113305 | L3: =L2*(1-Assumptions!$B$19) -> 23.761852 | M3: =M2*(1-Assumptions!$B$19) -> 26.444301 | N3: =N2*(1-Assumptions!$B$19) -> 29.097546 | O3: =O2*(1-Assumptions!$B$19) -> 31.651664 | P3: =P2*(1-Assumptions!$B$19) -> 34.032573 | Q3: =Q2*(1-Assumptions!$B$19) -> 36.165281 | R3: =R2*(1-Assumptions!$B$19) -> 37.977563 | ... T3: =T2*(1-Assumptions!$B$19) -> 40.388927
A4: Gross Margin | B4: =B2-B3 -> 66.918 | C4: =C2-C3 -> 67.43 | D4: =D2-D3 -> 32.248 | E4: =E2-E3 -> 32.885 | F4: =F2-F3 -> 50.832 | G4: =G2-G3 -> 28.294 | H4: =H2-H3 -> 29.752 | I4: =I2-I3 -> 39.689 | ... T4: =T2-T3 -> 56.583287
A5: Research & Dev. | B5: 22.133 | C5: 23.112 | D5: 20.574 | E5: 19.886 | F5: 17.047 | G5: 17.481 | H5: 13.104 | I5: 20.28 | J5: 17.192 | K5: =K7*Assumptions!$B$20 -> 9.3836455 | L5: =L7*Assumptions!$B$20 -> 9.818129 | M5: =M7*Assumptions!$B$20 -> 10.100008 | N5: =N7*Assumptions!$B$20 -> 10.203973 | O5: =O7*Assumptions!$B$20 -> 10.110428 | P5: =P7*Assumptions!$B$20 -> 9.8073171 | Q5: =Q7*Assumptions!$B$20 -> 9.2916148 | R5: =R7*Assumptions!$B$20 -> 8.5702935 | ... T5: =T7*Assumptions!$B$20 -> 6.5898632
A6: SG&A & Other | B6: 44.898 | C6: 93.252 | D6: 64.342 | E6: 55.892 | F6: 68.464 | G6: 52.879 | H6: 31.75 | I6: 50.18 | J6: 79.849 | K6: =K7-K5 -> 43.571465 | L6: =L7-L5 -> 45.58892 | M6: =M7-M5 -> 46.897779 | N6: =N7-N5 -> 47.380525 | O6: =O7-O5 -> 46.946162 | P6: =P7-P5 -> 45.538716 | Q6: =Q7-Q5 -> 43.144135 | R6: =R7-R5 -> 39.794794 | ... T6: =T7-T5 -> 30.598981
A7: Operating Expense | B7: =SUM(B5:B6) -> 67.031 | C7: =SUM(C5:C6) -> 116.364 | D7: =SUM(D5:D6) -> 84.916 | E7: =SUM(E5:E6) -> 75.778 | F7: =SUM(F5:F6) -> 85.511 | G7: =SUM(G5:G6) -> 70.36 | H7: =SUM(H5:H6) -> 44.854 | I7: =SUM(I5:I6) -> 70.46 | J7: =SUM(J5:J6) -> 97.041 | K7: =K4-K2*NPV!C6 -> 52.95511 | L7: =L4-L2*NPV!D6 -> 55.407049 | M7: =M4-M2*NPV!E6 -> 56.997787 | N7: =N4-N2*NPV!F6 -> 57.584498 | O7: =O4-O2*NPV!G6 -> 57.05659 | P7: =P4-P2*NPV!H6 -> 55.346033 | Q7: =Q4-Q2*NPV!I6 -> 52.43575 | R7: =R4-R2*NPV!J6 -> 48.365088 | ... T7: =T4-T2*NPV!L6 -> 37.188844
A8: Operating Income | B8: =B4-B7 -> -0.113 | C8: =C4-C7 -> -48.934 | D8: =D4-D7 -> -52.668 | E8: =E4-E7 -> -42.893 | F8: =F4-F7 -> -34.679 | G8: =G4-G7 -> -42.066 | H8: =H4-H7 -> -15.102 | I8: =I4-I7 -> -30.771 | ... T8: =T4-T7 -> 19.394443
A9: Interest & Other | B9: -8.83 | C9: -12.442 | D9: -13.578 | E9: -12.89 | F9: -35.86 | G9: -12.344 | H9: 7.477 | I9: -13.38 | J9: -12.733 | K9: 0 | L9: 0 | M9: 0 | N9: 0 | O9: 0 | P9: 0 | Q9: 0 | R9: 0 | S9: 0 | T9: 0
A10: Pretax | B10: =B8+B9 -> -8.943 | C10: =C8+C9 -> -61.376 | D10: =D8+D9 -> -66.246 | E10: =E8+E9 -> -55.783 | F10: =F8+F9 -> -70.539 | G10: =G8+G9 -> -54.41 | H10: =H8+H9 -> -7.625 | I10: =I8+I9 -> -44.151 | ... T10: =T8+T9 -> 19.394443
A11: Taxes | B11: 0 | C11: 0 | D11: 0 | E11: 0 | F11: 0 | G11: 0 | H11: 0.245 | I11: -0.014 | J11: 0 | K11: =MAX(0,K10)*Assumptions!$E$14 -> 0 | L11: =MAX(0,L10)*Assumptions!$E$14 -> 0 | M11: =MAX(0,M10)*Assumptions!$E$14 -> 0 | N11: =MAX(0,N10)*Assumptions!$E$14 -> 0 | O11: =MAX(0,O10)*Assumptions!$E$14 -> 0 | P11: =MAX(0,P10)*Assumptions!$E$14 -> 0 | Q11: =MAX(0,Q10)*Assumptions!$E$14 -> 0 | R11: =MAX(0,R10)*Assumptions!$E$14 -> 0.82279553 | ... T11: =MAX(0,T10)*Assumptions!$E$14 -> 3.2970553
A12: Net Income | B12: -8.943 | C12: -61.376 | D12: -66.246 | E12: -55.783 | F12: -70.539 | G12: -54.41 | H12: -7.87 | I12: -44.137 | J12: -83.784 | K12: =K10-K11 -> -23.376206 | L12: =L10-L11 -> -22.117635 | M12: =M10-M11 -> -19.950368 | N12: =N10-N11 -> -16.819989 | O12: =O10-O11 -> -12.713862 | P12: =P10-P11 -> -7.667747 | Q12: =Q10-Q11 -> -1.7696241 | R12: =R10-R11 -> 4.0171782 | ... T12: =T10-T11 -> 16.097388
A13: Earnings per Share | B13: =IFERROR(B12/B14,0) -> 0 | C13: =IFERROR(C12/C14,0) -> -2.9613046 | D13: =IFERROR(D12/D14,0) -> -2.6126361 | E13: =IFERROR(E12/E14,0) -> -1.6576922 | F13: =IFERROR(F12/F14,0) -> -1.852487 | G13: =IFERROR(G12/G14,0) -> -1.116469 | H13: =IFERROR(H12/H14,0) -> -0.12847721 | I13: =IFERROR(I12/I14,0) -> -0.50892466 | ... T13: =IFERROR(T12/T14,0) -> 0.12825413
A14: Shares | C14: 20.726 | D14: 25.356 | E14: 33.651 | F14: 38.078 | G14: 48.734 | H14: 61.256 | I14: 86.726 | J14: 106.927 | K14: =Main!$C$4 -> 125.51165 | L14: =Main!$C$4 -> 125.51165 | M14: =Main!$C$4 -> 125.51165 | N14: =Main!$C$4 -> 125.51165 | O14: =Main!$C$4 -> 125.51165 | P14: =Main!$C$4 -> 125.51165 | Q14: =Main!$C$4 -> 125.51165 | R14: =Main!$C$4 -> 125.51165 | ... T14: =Main!$C$4 -> 125.51165
A16: Revenue Change | C16: =IFERROR(C2/B2-1,"") -> 0.0076511551 | D16: =IFERROR(D2/C2-1,"") -> -0.21979831 | E16: =IFERROR(E2/D2-1,"") -> -0.12849512 | F16: =IFERROR(F2/E2-1,"") -> 0.10868285 | G16: =IFERROR(G2/F2-1,"") -> -0.062008184 | H16: =IFERROR(H2/G2-1,"") -> 0.060885067 | I16: =IFERROR(I2/H2-1,"") -> 0.13795149 | J16: =IFERROR(J2/I2-1,"") -> -0.22612533 | ... T16: =IFERROR(T2/S2-1,"") -> 0.025
A17: Gross Margin | B17: =IFERROR(B4/B2,"") -> 1 | C17: =IFERROR(C4/C2,"") -> 1 | D17: =IFERROR(D4/D2,"") -> 0.61297497 | E17: =IFERROR(E4/E2,"") -> 0.71724574 | F17: =IFERROR(F4/F2,"") -> 1 | G17: =IFERROR(G4/G2,"") -> 0.59341443 | H17: =IFERROR(H4/H2,"") -> 0.5881818 | I17: =IFERROR(I4/I2,"") -> 0.689512 | ... T17: =IFERROR(T4/T2,"") -> 0.5835
A18: Operating Margin | B18: =IFERROR(B8/B2,"") -> -0.0016886339 | C18: =IFERROR(C8/C2,"") -> -0.72570073 | D18: =IFERROR(D8/D2,"") -> -1.0011215 | E18: =IFERROR(E8/E2,"") -> -0.93552749 | F18: =IFERROR(F8/F2,"") -> -0.68222773 | G18: =IFERROR(G8/G2,"") -> -0.88225671 | H18: =IFERROR(H8/H2,"") -> -0.2985588 | I18: =IFERROR(I8/I2,"") -> -0.53458071 | ... T18: =IFERROR(T8/T2,"") -> 0.2
A19: Actual / Estimate | B19: A | C19: A | D19: A | E19: A | F19: A | G19: A | H19: A | I19: A | J19: A | K19: E | L19: E | M19: E | N19: E | O19: E | P19: E | Q19: E | R19: E | S19: E | T19: E

Sheet Quarterly Model

Sheet Assumptions
A1: Aquestive Therapeutics, Inc.: basic DCF assumptions
A2: Blue = input, black = formula, green = link. $mm unless noted.
A4: Scenario (1 Bear, 2 Base, 3 Bull) | B4: 2 | C4: =CHOOSE($B$4,"Bear","Base","Bull") -> Base
A6: Discount rate override (blank = scenario)
A7: Terminal growth override (blank = scenario)
A9: Parameter | B9: Bear | C9: Base | D9: Bull | E9: Live
A10: Discount rate | B10: 0.135 | C10: 0.125 | D10: 0.115 | E10: =IF(ISNUMBER($B$6),$B$6,CHOOSE($B$4,B10,C10,D10)) -> 0.125
A11: Terminal growth | B11: 0.02 | C11: 0.025 | D11: 0.03 | E11: =IF(ISNUMBER($B$7),$B$7,CHOOSE($B$4,B11,C11,D11)) -> 0.025
A12: Revenue growth, first forecast year | B12: 0.088 | C12: 0.138 | D12: 0.188 | E12: =CHOOSE($B$4,B12,C12,D12) -> 0.138
A13: Operating margin, year 10 | B13: 0.15 | C13: 0.2 | D13: 0.25 | E13: =CHOOSE($B$4,B13,C13,D13) -> 0.2
A14: Tax rate on operating income | B14: 0.17 | C14: 0.17 | D14: 0.17 | E14: =CHOOSE($B$4,B14,C14,D14) -> 0.17
A15: Reinvestment, % of revenue increase | B15: 0.25 | C15: 0.25 | D15: 0.25 | E15: =CHOOSE($B$4,B15,C15,D15) -> 0.25
A17: Single inputs
A18: Starting operating margin (TTM) | B18: -0.5346
A19: Gross margin (forecast) | B19: 0.5835
A20: R&D share of operating expense (forecast) | B20: 0.1772
A21: Forecast years | B21: 10
A22: First forecast year, fraction after balance sheet date | B22: 0.5041
A23: Balance sheet date | B23: 46203
A24: Reporting currency per USD (USD) | B24: 1
A25: Base revenue, FY2025 | B25: ='Yearly Model'!J2 -> 44.545
A27: Scenario summary
A28: Scenario | B28: Enterprise value | C28: Equity value | D28: NPV / share | E28: Upside
A29: Live | B29: =NPV!B23 -> -16.567894 | C29: =NPV!B26 -> 31.236106 | D29: =NPV!B28 -> 0.24887018 | E29: =NPV!B30 -> -0.93855057
A30: 1 | B30: -43.33774 | C30: 4.4662596 | D30: 0.035584423 | E30: -0.99121372
A31: 2 | B31: -16.567894 | C31: 31.236106 | D31: 0.24887018 | E31: -0.93855057
A32: 3 | B32: 41.340095 | C32: 89.144095 | D32: 0.7102456 | E32: -0.82463072
A35: NPV / share: discount rate (rows) x terminal growth (columns)
A36: =NPV!B28 -> 0.24887018 | B36: 0.015 | C36: 0.02 | D36: 0.025 | E36: 0.03 | F36: 0.035
A37: 0.105 | B37: 0.34934439 | C37: 0.39037192 | D37: 0.43692728 | E37: 0.49012059 | F37: 0.55137919
A38: 0.115 | B38: 0.2641618 | C38: 0.29507578 | D38: 0.32976145 | E38: 0.36888815 | F38: 0.41329263
A39: 0.125 | B39: 0.19873166 | C39: 0.22247008 | D39: 0.24887018 | E39: 0.27835539 | F39: 0.31144328
A40: 0.135 | B40: 0.14783079 | C40: 0.16633316 | D40: 0.18676627 | E40: 0.20940865 | F40: 0.23459454
A41: 0.145 | B41: 0.10786575 | C41: 0.12245821 | D41: 0.13848361 | E41: 0.15613116 | F41: 0.17562451

Sheet NPV
A1: Aquestive Therapeutics, Inc.: free-cash-flow DCF ($mm)
A3: Fiscal year | B3: ='Yearly Model'!J1 -> 2025 | C3: ='Yearly Model'!K1 -> 2026 | D3: ='Yearly Model'!L1 -> 2027 | E3: ='Yearly Model'!M1 -> 2028 | F3: ='Yearly Model'!N1 -> 2029 | G3: ='Yearly Model'!O1 -> 2030 | H3: ='Yearly Model'!P1 -> 2031 | I3: ='Yearly Model'!Q1 -> 2032 | ... L3: ='Yearly Model'!T1 -> 2035
A4: Period | B4: Actual | C4: 1 | D4: 2 | E4: 3 | F4: 4 | G4: 5 | H4: 6 | I4: 7 | J4: 8 | K4: 9 | L4: 10
A5: Revenue growth | C5: =Assumptions!$E$12+(Assumptions!$E$11-Assumptions!$E$12)*(C4-1)/(Assumptions!$B$21-1) -> 0.138 | D5: =Assumptions!$E$12+(Assumptions!$E$11-Assumptions!$E$12)*(D4-1)/(Assumptions!$B$21-1) -> 0.12544444 | E5: =Assumptions!$E$12+(Assumptions!$E$11-Assumptions!$E$12)*(E4-1)/(Assumptions!$B$21-1) -> 0.11288889 | F5: =Assumptions!$E$12+(Assumptions!$E$11-Assumptions!$E$12)*(F4-1)/(Assumptions!$B$21-1) -> 0.10033333 | G5: =Assumptions!$E$12+(Assumptions!$E$11-Assumptions!$E$12)*(G4-1)/(Assumptions!$B$21-1) -> 0.087777778 | H5: =Assumptions!$E$12+(Assumptions!$E$11-Assumptions!$E$12)*(H4-1)/(Assumptions!$B$21-1) -> 0.075222222 | I5: =Assumptions!$E$12+(Assumptions!$E$11-Assumptions!$E$12)*(I4-1)/(Assumptions!$B$21-1) -> 0.062666667 | J5: =Assumptions!$E$12+(Assumptions!$E$11-Assumptions!$E$12)*(J4-1)/(Assumptions!$B$21-1) -> 0.050111111 | ... L5: =Assumptions!$E$12+(Assumptions!$E$11-Assumptions!$E$12)*(L4-1)/(Assumptions!$B$21-1) -> 0.025
A6: Operating margin | B6: =IFERROR(B8/B7,0) -> -1.5950387 | C6: =Assumptions!$B$18+(Assumptions!$E$13-Assumptions!$B$18)*C4/Assumptions!$B$21 -> -0.46114 | D6: =Assumptions!$B$18+(Assumptions!$E$13-Assumptions!$B$18)*D4/Assumptions!$B$21 -> -0.38768 | E6: =Assumptions!$B$18+(Assumptions!$E$13-Assumptions!$B$18)*E4/Assumptions!$B$21 -> -0.31422 | F6: =Assumptions!$B$18+(Assumptions!$E$13-Assumptions!$B$18)*F4/Assumptions!$B$21 -> -0.24076 | G6: =Assumptions!$B$18+(Assumptions!$E$13-Assumptions!$B$18)*G4/Assumptions!$B$21 -> -0.1673 | H6: =Assumptions!$B$18+(Assumptions!$E$13-Assumptions!$B$18)*H4/Assumptions!$B$21 -> -0.09384 | I6: =Assumptions!$B$18+(Assumptions!$E$13-Assumptions!$B$18)*I4/Assumptions!$B$21 -> -0.02038 | J6: =Assumptions!$B$18+(Assumptions!$E$13-Assumptions!$B$18)*J4/Assumptions!$B$21 -> 0.05308 | ... L6: =Assumptions!$B$18+(Assumptions!$E$13-Assumptions!$B$18)*L4/Assumptions!$B$21 -> 0.2
A7: Revenue | B7: ='Yearly Model'!J2 -> 44.545 | C7: ='Yearly Model'!K2 -> 50.69221 | D7: ='Yearly Model'!L2 -> 57.051266 | E7: ='Yearly Model'!M2 -> 63.49172 | F7: ='Yearly Model'!N2 -> 69.862056 | G7: ='Yearly Model'!O2 -> 75.994392 | H7: ='Yearly Model'!P2 -> 81.710859 | I7: ='Yearly Model'!Q2 -> 86.831406 | ... L7: ='Yearly Model'!T2 -> 96.972215
A8: Operating income | B8: ='Yearly Model'!J8 -> -71.051 | C8: ='Yearly Model'!K8 -> -23.376206 | D8: ='Yearly Model'!L8 -> -22.117635 | E8: ='Yearly Model'!M8 -> -19.950368 | F8: ='Yearly Model'!N8 -> -16.819989 | G8: ='Yearly Model'!O8 -> -12.713862 | H8: ='Yearly Model'!P8 -> -7.667747 | I8: ='Yearly Model'!Q8 -> -1.7696241 | ... L8: ='Yearly Model'!T8 -> 19.394443
A9: Tax on operating income | C9: =MAX(0,C8)*Assumptions!$E$14 -> 0 | D9: =MAX(0,D8)*Assumptions!$E$14 -> 0 | E9: =MAX(0,E8)*Assumptions!$E$14 -> 0 | F9: =MAX(0,F8)*Assumptions!$E$14 -> 0 | G9: =MAX(0,G8)*Assumptions!$E$14 -> 0 | H9: =MAX(0,H8)*Assumptions!$E$14 -> 0 | I9: =MAX(0,I8)*Assumptions!$E$14 -> 0 | J9: =MAX(0,J8)*Assumptions!$E$14 -> 0.82279553 | ... L9: =MAX(0,L8)*Assumptions!$E$14 -> 3.2970553
A10: NOPAT | C10: =C8-C9 -> -23.376206 | D10: =D8-D9 -> -22.117635 | E10: =E8-E9 -> -19.950368 | F10: =F8-F9 -> -16.819989 | G10: =G8-G9 -> -12.713862 | H10: =H8-H9 -> -7.667747 | I10: =I8-I9 -> -1.7696241 | J10: =J8-J9 -> 4.0171782 | ... L10: =L8-L9 -> 16.097388
A11: Reinvestment | C11: =(C7-B7)*Assumptions!$E$15 -> 1.5368025 | D11: =(D7-C7)*Assumptions!$E$15 -> 1.589764 | E11: =(E7-D7)*Assumptions!$E$15 -> 1.6101135 | F11: =(F7-E7)*Assumptions!$E$15 -> 1.592584 | G11: =(G7-F7)*Assumptions!$E$15 -> 1.533084 | H11: =(H7-G7)*Assumptions!$E$15 -> 1.4291168 | I11: =(I7-H7)*Assumptions!$E$15 -> 1.2801368 | J11: =(J7-I7)*Assumptions!$E$15 -> 1.0878046 | ... L11: =(L7-K7)*Assumptions!$E$15 -> 0.59129399
A12: Free cash flow | C12: =C10-C11 -> -24.913008 | D12: =D10-D11 -> -23.707399 | E12: =E10-E11 -> -21.560482 | F12: =F10-F11 -> -18.412573 | G12: =G10-G11 -> -14.246946 | H12: =H10-H11 -> -9.0968638 | I12: =I10-I11 -> -3.0497609 | J12: =J10-J11 -> 2.9293736 | ... L12: =L10-L11 -> 15.506094
A13: Year fraction | C13: =Assumptions!$B$22 -> 0.5041 | D13: 1 | E13: 1 | F13: 1 | G13: 1 | H13: 1 | I13: 1 | J13: 1 | K13: 1 | L13: 1
A14: Discount time (mid-period) | C14: =C13/2 -> 0.25205 | D14: =C14+C13/2+D13/2 -> 1.0041 | E14: =D14+D13/2+E13/2 -> 2.0041 | F14: =E14+E13/2+F13/2 -> 3.0041 | G14: =F14+F13/2+G13/2 -> 4.0041 | H14: =G14+G13/2+H13/2 -> 5.0041 | I14: =H14+H13/2+I13/2 -> 6.0041 | J14: =I14+I13/2+J13/2 -> 7.0041 | K14: =J14+J13/2+K13/2 -> 8.0041 | L14: =K14+K13/2+L13/2 -> 9.0041
A15: Discount factor | C15: =1/(1+Assumptions!$E$10)^C14 -> 0.97074912 | D15: =1/(1+Assumptions!$E$10)^D14 -> 0.88845974 | E15: =1/(1+Assumptions!$E$10)^E14 -> 0.78974199 | F15: =1/(1+Assumptions!$E$10)^F14 -> 0.70199288 | G15: =1/(1+Assumptions!$E$10)^G14 -> 0.62399367 | H15: =1/(1+Assumptions!$E$10)^H14 -> 0.55466104 | I15: =1/(1+Assumptions!$E$10)^I14 -> 0.49303204 | J15: =1/(1+Assumptions!$E$10)^J14 -> 0.4382507 | ... L15: =1/(1+Assumptions!$E$10)^L14 -> 0.34627216
A16: PV of free cash flow | C16: =C12*C13*C15 -> -12.191296 | D16: =D12*D13*D15 -> -21.063069 | E16: =E12*E13*E15 -> -17.027218 | F16: =F12*F13*F15 -> -12.925495 | G16: =G12*G13*G15 -> -8.890004 | H16: =H12*H13*H15 -> -5.0456759 | I16: =I12*I13*I15 -> -1.5036298 | J16: =J12*J13*J15 -> 1.2838 | ... L16: =L12*L13*L15 -> 5.3693285
A19: PV of forecast free cash flow | B19: =SUM(C16:L16) -> -68.455971
A20: Terminal free cash flow (year 11) | B20: =L10*(1+Assumptions!$E$11)-L7*Assumptions!$E$11*Assumptions!$E$15 -> 15.893746
A21: Terminal value | B21: =B20/(Assumptions!$E$10-Assumptions!$E$11) -> 158.93746
A22: PV of terminal value | B22: =B21/(1+Assumptions!$E$10)^(L14+0.5) -> 51.888077
A23: Enterprise value | B23: =B19+B22 -> -16.567894
A24: Cash & investments | B24: =Main!C7 -> 98.49
A25: Debt | B25: =Main!C8 -> 50.686
A26: Equity value | B26: =B23+B24-B25 -> 31.236106
A27: Shares (mm) | B27: =Main!C4 -> 125.51165
A28: NPV / share | B28: =B26/B27 -> 0.24887018
A29: Price | B29: =Main!C3 -> 4.05
A30: Upside | B30: =B28/B29-1 -> -0.93855057
A31: Terminal value, % of EV | B31: =IFERROR(B22/B23,0) -> -3.1318452
