Workbook

Sheet Main
B2: Aytu Biopharma Inc
B3: Price | C3: =INDEX([1]Pharma!$F$1:$F$1000,MATCH("AYTU",[1]Pharma!$B$1:$B$1000,0)) -> 2.01
B4: Shares | C4: 10.866708
B5: Market Cap. | C5: =C3*C4 -> 21.842083
B7: Cash | C7: 26.308
B8: Debt | C8: =1.857+6.074+9.101 -> 17.032
B9: Enterprise V. | C9: =C5-C7+C8 -> 12.566083
B11: NPV / Share | C11: =NPV!B28 -> 2.8977372
B12: Upside | C12: =IFERROR(C11/C3-1,"") -> 0.44166028
B13: Cash / Share | C13: =IFERROR((C7-C8)/C4,"") -> 0.85361639
B14: Scenario | C14: =Assumptions!C4 -> Base
B15: Model | C15: DCF

Sheet Yearly Model
B1: 2006 | C1: 2007 | D1: 2008 | E1: 2009 | F1: 2010 | G1: 2011 | H1: 2012 | I1: 2013 | J1: 2014 | K1: 2015 | L1: 2016 | M1: 2017 | N1: 2018 | O1: 2019 | P1: 2020 | Q1: 2021 | R1: 2022 | S1: 2023 | T1: 2024 | U1: 2025 | V1: 2026 | W1: 2027 | X1: 2028 | Y1: 2029 | Z1: 2030 | AA1: 2031 | AB1: 2032 | AC1: 2033 | AD1: 2034 | AE1: 2035 | AF1: 2036
A2: Revenue | B2: 0 | C2: 0 | D2: 0 | E2: 0 | F2: 0 | G2: 0 | H2: 0 | I2: 0 | J2: 0.059 | K2: 0.262 | L2: 2.562 | M2: 3.222 | N2: 3.66 | O2: 7.32 | P2: 27.632 | Q2: 65.632 | R2: 96.669 | S2: 107.399 | T2: 65.183 | U2: 66.382 | V2: 57.57 | W2: =V2*(1+NPV!C5) -> 51.813 | X2: =W2*(1+NPV!D5) -> 47.351325 | Y2: =X2*(1+NPV!E5) -> 43.931507 | Z2: =Y2*(1+NPV!F5) -> 41.368836 | AA2: =Z2*(1+NPV!G5) -> 39.530221 | AB2: =AA2*(1+NPV!H5) -> 38.322353 | AC2: =AB2*(1+NPV!I5) -> 37.683647 | AD2: =AC2*(1+NPV!J5) -> 37.57897 | ... AF2: =AE2*(1+NPV!L5) -> 38.946427
A3: Cost of Sales | B3: 0 | C3: 0 | D3: 0 | E3: 0 | F3: 0 | G3: 0 | H3: 0 | I3: 0 | J3: 0 | K3: 0.088 | L3: 0.957 | M3: 1.417 | N3: 2.051 | O3: 2.202 | P3: 8.281 | Q3: 36.432 | R3: 44.386 | S3: 40.767 | T3: 16.129 | U3: 20.551 | V3: 20.752 | W3: =W2*(1-Assumptions!$B$19) -> 18.678587 | X3: =X2*(1-Assumptions!$B$19) -> 17.070153 | Y3: =Y2*(1-Assumptions!$B$19) -> 15.837308 | Z3: =Z2*(1-Assumptions!$B$19) -> 14.913465 | AA3: =AA2*(1-Assumptions!$B$19) -> 14.250645 | AB3: =AB2*(1-Assumptions!$B$19) -> 13.815208 | AC3: =AC2*(1-Assumptions!$B$19) -> 13.584955 | AD3: =AD2*(1-Assumptions!$B$19) -> 13.547219 | ... AF3: =AF2*(1-Assumptions!$B$19) -> 14.040187
A4: Gross Margin | B4: =B2-B3 -> 0 | C4: =C2-C3 -> 0 | D4: =D2-D3 -> 0 | E4: =E2-E3 -> 0 | F4: =F2-F3 -> 0 | G4: =G2-G3 -> 0 | H4: =H2-H3 -> 0 | I4: =I2-I3 -> 0 | ... AF4: =AF2-AF3 -> 24.90624
A5: Research & Dev. | B5: 0 | C5: 0 | D5: 0 | E5: 0 | F5: 0 | G5: 0 | H5: 0 | I5: 0 | J5: 3.934 | K5: 3.219 | L5: 6.128 | M5: 0.96 | N5: 0.168 | O5: 0.589 | P5: 1.722 | Q5: 5.623 | R5: 12.662 | S5: 4.095 | T5: 2.769 | U5: 1.326 | V5: 0 | W5: =W7*Assumptions!$B$20 -> 0 | X5: =X7*Assumptions!$B$20 -> 0 | Y5: =Y7*Assumptions!$B$20 -> 0 | Z5: =Z7*Assumptions!$B$20 -> 0 | AA5: =AA7*Assumptions!$B$20 -> 0 | AB5: =AB7*Assumptions!$B$20 -> 0 | AC5: =AC7*Assumptions!$B$20 -> 0 | AD5: =AD7*Assumptions!$B$20 -> 0 | ... AF5: =AF7*Assumptions!$B$20 -> 0
A6: SG&A & Other | B6: 0.07 | C6: 0.049 | D6: 0.057 | E6: 0.059 | F6: 0.06 | G6: 0.134 | H6: 0.056 | I6: 0.052 | J6: 2.472 | K6: 4.587 | L6: 17.182 | M6: 20.97 | N6: 21.142 | O6: 21.376 | P6: 38.76 | Q6: 82.447 | R6: 149.527 | S6: 79.602 | T6: 47.876 | U6: 52.332 | V6: 45.133 | W6: =W7-W5 -> 38.831771 | X6: =X7-X5 -> 33.857144 | Y6: =Y7-Y5 -> 29.898905 | Z6: =Z7-Z5 -> 26.73006 | AA6: =AA7-AA5 -> 24.180636 | AB6: =AB7-AB5 -> 22.121962 | AC6: =AC7-AC5 -> 20.455437 | AD6: =AD7-AD5 -> 19.104397 | ... AF6: =AF7-AF5 -> 17.116955
A7: Operating Expense | B7: =SUM(B5:B6) -> 0.07 | C7: =SUM(C5:C6) -> 0.049 | D7: =SUM(D5:D6) -> 0.057 | E7: =SUM(E5:E6) -> 0.059 | F7: =SUM(F5:F6) -> 0.06 | G7: =SUM(G5:G6) -> 0.134 | H7: =SUM(H5:H6) -> 0.056 | I7: =SUM(I5:I6) -> 0.052 | ... V7: =SUM(V5:V6) -> 45.133 | W7: =W4-W2*NPV!C6 -> 38.831771 | X7: =X4-X2*NPV!D6 -> 33.857144 | Y7: =Y4-Y2*NPV!E6 -> 29.898905 | Z7: =Z4-Z2*NPV!F6 -> 26.73006 | AA7: =AA4-AA2*NPV!G6 -> 24.180636 | AB7: =AB4-AB2*NPV!H6 -> 22.121962 | AC7: =AC4-AC2*NPV!I6 -> 20.455437 | AD7: =AD4-AD2*NPV!J6 -> 19.104397 | ... AF7: =AF4-AF2*NPV!L6 -> 17.116955
A8: Operating Income | B8: =B4-B7 -> -0.07 | C8: =C4-C7 -> -0.049 | D8: =D4-D7 -> -0.057 | E8: =E4-E7 -> -0.059 | F8: =F4-F7 -> -0.06 | G8: =G4-G7 -> -0.134 | H8: =H4-H7 -> -0.056 | I8: =I4-I7 -> -0.052 | ... AF8: =AF4-AF7 -> 7.7892855
A9: Interest & Other | B9: 0 | C9: 0 | D9: 0 | E9: 0 | F9: 0 | G9: -0.003 | H9: -0.003 | I9: -0.005 | J9: 5.471 | K9: -0.115 | L9: -6.476 | M9: -2.383 | N9: 9.512 | O9: -10.285 | P9: 7.51 | Q9: 0.84 | R9: 1.017 | S9: 0.014 | T9: -12.111 | U9: -5.298 | V9: -5.916 | W9: 0 | X9: 0 | Y9: 0 | Z9: 0 | AA9: 0 | AB9: 0 | AC9: 0 | AD9: 0 | AE9: 0 | AF9: 0
A10: Pretax | B10: =B8+B9 -> -0.07 | C10: =C8+C9 -> -0.049 | D10: =D8+D9 -> -0.057 | E10: =E8+E9 -> -0.059 | F10: =F8+F9 -> -0.06 | G10: =G8+G9 -> -0.137 | H10: =H8+H9 -> -0.059 | I10: =I8+I9 -> -0.057 | ... AF10: =AF8+AF9 -> 7.7892855
A11: Taxes | B11: 0 | C11: 0 | D11: 0 | E11: 0 | F11: 0 | G11: 0 | H11: 0 | I11: 0 | J11: -0.814 | K11: -0.024 | L11: 0 | M11: 0 | N11: 0 | O11: 0 | P11: 0 | Q11: 0.259 | R11: -0.11 | S11: 0 | T11: 2.142 | U11: 0.437 | V11: 0.021 | W11: =MAX(0,W10)*Assumptions!$E$14 -> 0 | X11: =MAX(0,X10)*Assumptions!$E$14 -> 0 | Y11: =MAX(0,Y10)*Assumptions!$E$14 -> 0 | Z11: =MAX(0,Z10)*Assumptions!$E$14 -> 0 | AA11: =MAX(0,AA10)*Assumptions!$E$14 -> 0.18681982 | AB11: =MAX(0,AB10)*Assumptions!$E$14 -> 0.40548115 | AC11: =MAX(0,AC10)*Assumptions!$E$14 -> 0.61935335 | AD11: =MAX(0,AD10)*Assumptions!$E$14 -> 0.83765028 | ... AF11: =MAX(0,AF10)*Assumptions!$E$14 -> 1.3241785
A12: Net Income | B12: -0.07 | C12: -0.049 | D12: -0.057 | E12: -0.059 | F12: -0.06 | G12: -0.137 | H12: -0.06 | I12: -0.057 | J12: -0.062 | K12: -7.723 | L12: -28.18 | M12: -22.508 | N12: -10.188 | O12: -27.132 | P12: -13.621 | Q12: -58.289 | R12: -108.779 | S12: -17.051 | T12: -15.844 | U12: -13.562 | V12: -14.252 | W12: =W10-W11 -> -5.6973575 | X12: =X10-X11 -> -3.5759721 | Y12: =Y10-Y11 -> -1.8047063 | Z12: =Z10-Z11 -> -0.27468907 | AA12: =AA10-AA11 -> 0.91212032 | AB12: =AB10-AB11 -> 1.9797021 | AC12: =AC10-AC11 -> 3.0239017 | AD12: =AD10-AD11 -> 4.0897043 | ... AF12: =AF10-AF11 -> 6.4651069
A13: Earnings per Share | B13: =IFERROR(B12/B14,0) -> 0 | C13: =IFERROR(C12/C14,0) -> 0 | D13: =IFERROR(D12/D14,0) -> 0 | E13: =IFERROR(E12/E14,0) -> 0 | F13: =IFERROR(F12/F14,0) -> 0 | G13: =IFERROR(G12/G14,0) -> 0 | H13: =IFERROR(H12/H14,0) -> -0.056127222 | I13: =IFERROR(I12/I14,0) -> -0.052534562 | ... AF13: =IFERROR(AF12/AF14,0) -> 0.59494623
A14: Shares | H14: 1.069 | I14: 1.085 | J14: 1.544 | K14: 1.535 | L14: 0.174 | M14: 0.932 | N14: 1.331 | O14: 15.589 | P14: 9.038 | Q14: 33.493 | R14: 2.94 | S14: 6.68 | T14: 11.076 | U14: 12.559 | V14: 12.319 | W14: =Main!$C$4 -> 10.866708 | X14: =Main!$C$4 -> 10.866708 | Y14: =Main!$C$4 -> 10.866708 | Z14: =Main!$C$4 -> 10.866708 | AA14: =Main!$C$4 -> 10.866708 | AB14: =Main!$C$4 -> 10.866708 | AC14: =Main!$C$4 -> 10.866708 | AD14: =Main!$C$4 -> 10.866708 | ... AF14: =Main!$C$4 -> 10.866708
A16: Revenue Change | C16: =IFERROR(C2/B2-1,"") | D16: =IFERROR(D2/C2-1,"") | E16: =IFERROR(E2/D2-1,"") | F16: =IFERROR(F2/E2-1,"") | G16: =IFERROR(G2/F2-1,"") | H16: =IFERROR(H2/G2-1,"") | I16: =IFERROR(I2/H2-1,"") | J16: =IFERROR(J2/I2-1,"") | ... AF16: =IFERROR(AF2/AE2-1,"") -> 0.025
A17: Gross Margin | B17: =IFERROR(B4/B2,"") | C17: =IFERROR(C4/C2,"") | D17: =IFERROR(D4/D2,"") | E17: =IFERROR(E4/E2,"") | F17: =IFERROR(F4/F2,"") | G17: =IFERROR(G4/G2,"") | H17: =IFERROR(H4/H2,"") | I17: =IFERROR(I4/I2,"") | ... AF17: =IFERROR(AF4/AF2,"") -> 0.6395
A18: Operating Margin | B18: =IFERROR(B8/B2,"") | C18: =IFERROR(C8/C2,"") | D18: =IFERROR(D8/D2,"") | E18: =IFERROR(E8/E2,"") | F18: =IFERROR(F8/F2,"") | G18: =IFERROR(G8/G2,"") | H18: =IFERROR(H8/H2,"") | I18: =IFERROR(I8/I2,"") | ... AF18: =IFERROR(AF8/AF2,"") -> 0.2
A19: Actual / Estimate | B19: A | C19: A | D19: A | E19: A | F19: A | G19: A | H19: A | I19: A | J19: A | K19: A | L19: A | M19: A | N19: A | O19: A | P19: A | Q19: A | R19: A | S19: A | T19: A | U19: A | V19: A | W19: E | X19: E | Y19: E | Z19: E | AA19: E | AB19: E | AC19: E | AD19: E | AE19: E | AF19: E

Sheet Quarterly Model

Sheet Assumptions
A1: Aytu Biopharma Inc: basic DCF assumptions
A2: Blue = input, black = formula, green = link. $mm unless noted.
A4: Scenario (1 Bear, 2 Base, 3 Bull) | B4: 2 | C4: =CHOOSE($B$4,"Bear","Base","Bull") -> Base
A6: Discount rate override (blank = scenario)
A7: Terminal growth override (blank = scenario)
A9: Parameter | B9: Bear | C9: Base | D9: Bull | E9: Live
A10: Discount rate | B10: 0.135 | C10: 0.125 | D10: 0.115 | E10: =IF(ISNUMBER($B$6),$B$6,CHOOSE($B$4,B10,C10,D10)) -> 0.125
A11: Terminal growth | B11: 0.02 | C11: 0.025 | D11: 0.03 | E11: =IF(ISNUMBER($B$7),$B$7,CHOOSE($B$4,B11,C11,D11)) -> 0.025
A12: Revenue growth, first forecast year | B12: -0.15 | C12: -0.1 | D12: -0.05 | E12: =CHOOSE($B$4,B12,C12,D12) -> -0.1
A13: Operating margin, year 10 | B13: 0.15 | C13: 0.2 | D13: 0.25 | E13: =CHOOSE($B$4,B13,C13,D13) -> 0.2
A14: Tax rate on operating income | B14: 0.17 | C14: 0.17 | D14: 0.17 | E14: =CHOOSE($B$4,B14,C14,D14) -> 0.17
A15: Reinvestment, % of revenue increase | B15: 0.25 | C15: 0.25 | D15: 0.25 | E15: =CHOOSE($B$4,B15,C15,D15) -> 0.25
A17: Single inputs
A18: Starting operating margin (TTM) | B18: -0.1444
A19: Gross margin (forecast) | B19: 0.6395
A20: R&D share of operating expense (forecast) | B20: 0
A21: Forecast years | B21: 10
A22: First forecast year, fraction after balance sheet date | B22: 1
A23: Balance sheet date | B23: 46203
A24: Reporting currency per USD (USD) | B24: 1
A25: Base revenue, FY2026 | B25: ='Yearly Model'!V2 -> 57.57
A27: Scenario summary
A28: Scenario | B28: Enterprise value | C28: Equity value | D28: NPV / share | E28: Upside
A29: Live | B29: =NPV!B23 -> 22.212864 | C29: =NPV!B26 -> 31.488864 | D29: =NPV!B28 -> 2.8977372 | E29: =NPV!B30 -> 0.44166028
A30: 1 | B30: 7.6828433 | C30: 16.958843 | D30: 1.5606238 | E30: -0.22357024
A31: 2 | B31: 22.212864 | C31: 31.488864 | D31: 2.8977372 | E31: 0.44166028
A32: 3 | B32: 51.307956 | C32: 60.583956 | D32: 5.5751895 | E32: 1.7737261
A35: NPV / share: discount rate (rows) x terminal growth (columns)
A36: =NPV!B28 -> 2.8977372 | B36: 0.015 | C36: 0.02 | D36: 0.025 | E36: 0.03 | F36: 0.035
A37: 0.105 | B37: 3.4892733 | C37: 3.6843287 | D37: 3.9044917 | E37: 4.1547931 | F37: 4.4417014
A38: 0.115 | B38: 3.0248984 | C38: 3.17351 | D38: 3.3392453 | E38: 3.5251336 | F38: 3.734962
A39: 0.125 | B39: 2.6544663 | C39: 2.770061 | D39: 2.8977372 | E39: 3.0394087 | F39: 3.1974152
A40: 0.135 | B40: 2.3538189 | C40: 2.445261 | D40: 2.5454669 | E40: 2.655694 | F40: 2.7774512
A41: 0.145 | B41: 2.1062897 | C41: 2.1796416 | D41: 2.2594994 | E41: 2.3467163 | F41: 2.4423007

Sheet NPV
A1: Aytu Biopharma Inc: free-cash-flow DCF ($mm)
A3: Fiscal year | B3: ='Yearly Model'!V1 -> 2026 | C3: ='Yearly Model'!W1 -> 2027 | D3: ='Yearly Model'!X1 -> 2028 | E3: ='Yearly Model'!Y1 -> 2029 | F3: ='Yearly Model'!Z1 -> 2030 | G3: ='Yearly Model'!AA1 -> 2031 | H3: ='Yearly Model'!AB1 -> 2032 | I3: ='Yearly Model'!AC1 -> 2033 | ... L3: ='Yearly Model'!AF1 -> 2036
A4: Period | B4: Actual | C4: 1 | D4: 2 | E4: 3 | F4: 4 | G4: 5 | H4: 6 | I4: 7 | J4: 8 | K4: 9 | L4: 10
A5: Revenue growth | C5: =Assumptions!$E$12+(Assumptions!$E$11-Assumptions!$E$12)*(C4-1)/(Assumptions!$B$21-1) -> -0.1 | D5: =Assumptions!$E$12+(Assumptions!$E$11-Assumptions!$E$12)*(D4-1)/(Assumptions!$B$21-1) -> -0.086111111 | E5: =Assumptions!$E$12+(Assumptions!$E$11-Assumptions!$E$12)*(E4-1)/(Assumptions!$B$21-1) -> -0.072222222 | F5: =Assumptions!$E$12+(Assumptions!$E$11-Assumptions!$E$12)*(F4-1)/(Assumptions!$B$21-1) -> -0.058333333 | G5: =Assumptions!$E$12+(Assumptions!$E$11-Assumptions!$E$12)*(G4-1)/(Assumptions!$B$21-1) -> -0.044444444 | H5: =Assumptions!$E$12+(Assumptions!$E$11-Assumptions!$E$12)*(H4-1)/(Assumptions!$B$21-1) -> -0.030555556 | I5: =Assumptions!$E$12+(Assumptions!$E$11-Assumptions!$E$12)*(I4-1)/(Assumptions!$B$21-1) -> -0.016666667 | J5: =Assumptions!$E$12+(Assumptions!$E$11-Assumptions!$E$12)*(J4-1)/(Assumptions!$B$21-1) -> -0.0027777778 | ... L5: =Assumptions!$E$12+(Assumptions!$E$11-Assumptions!$E$12)*(L4-1)/(Assumptions!$B$21-1) -> 0.025
A6: Operating margin | B6: =IFERROR(B8/B7,0) -> -0.14443286 | C6: =Assumptions!$B$18+(Assumptions!$E$13-Assumptions!$B$18)*C4/Assumptions!$B$21 -> -0.10996 | D6: =Assumptions!$B$18+(Assumptions!$E$13-Assumptions!$B$18)*D4/Assumptions!$B$21 -> -0.07552 | E6: =Assumptions!$B$18+(Assumptions!$E$13-Assumptions!$B$18)*E4/Assumptions!$B$21 -> -0.04108 | F6: =Assumptions!$B$18+(Assumptions!$E$13-Assumptions!$B$18)*F4/Assumptions!$B$21 -> -0.00664 | G6: =Assumptions!$B$18+(Assumptions!$E$13-Assumptions!$B$18)*G4/Assumptions!$B$21 -> 0.0278 | H6: =Assumptions!$B$18+(Assumptions!$E$13-Assumptions!$B$18)*H4/Assumptions!$B$21 -> 0.06224 | I6: =Assumptions!$B$18+(Assumptions!$E$13-Assumptions!$B$18)*I4/Assumptions!$B$21 -> 0.09668 | J6: =Assumptions!$B$18+(Assumptions!$E$13-Assumptions!$B$18)*J4/Assumptions!$B$21 -> 0.13112 | ... L6: =Assumptions!$B$18+(Assumptions!$E$13-Assumptions!$B$18)*L4/Assumptions!$B$21 -> 0.2
A7: Revenue | B7: ='Yearly Model'!V2 -> 57.57 | C7: ='Yearly Model'!W2 -> 51.813 | D7: ='Yearly Model'!X2 -> 47.351325 | E7: ='Yearly Model'!Y2 -> 43.931507 | F7: ='Yearly Model'!Z2 -> 41.368836 | G7: ='Yearly Model'!AA2 -> 39.530221 | H7: ='Yearly Model'!AB2 -> 38.322353 | I7: ='Yearly Model'!AC2 -> 37.683647 | ... L7: ='Yearly Model'!AF2 -> 38.946427
A8: Operating income | B8: ='Yearly Model'!V8 -> -8.315 | C8: ='Yearly Model'!W8 -> -5.6973575 | D8: ='Yearly Model'!X8 -> -3.5759721 | E8: ='Yearly Model'!Y8 -> -1.8047063 | F8: ='Yearly Model'!Z8 -> -0.27468907 | G8: ='Yearly Model'!AA8 -> 1.0989401 | H8: ='Yearly Model'!AB8 -> 2.3851833 | I8: ='Yearly Model'!AC8 -> 3.643255 | ... L8: ='Yearly Model'!AF8 -> 7.7892855
A9: Tax on operating income | C9: =MAX(0,C8)*Assumptions!$E$14 -> 0 | D9: =MAX(0,D8)*Assumptions!$E$14 -> 0 | E9: =MAX(0,E8)*Assumptions!$E$14 -> 0 | F9: =MAX(0,F8)*Assumptions!$E$14 -> 0 | G9: =MAX(0,G8)*Assumptions!$E$14 -> 0.18681982 | H9: =MAX(0,H8)*Assumptions!$E$14 -> 0.40548115 | I9: =MAX(0,I8)*Assumptions!$E$14 -> 0.61935335 | J9: =MAX(0,J8)*Assumptions!$E$14 -> 0.83765028 | ... L9: =MAX(0,L8)*Assumptions!$E$14 -> 1.3241785
A10: NOPAT | C10: =C8-C9 -> -5.6973575 | D10: =D8-D9 -> -3.5759721 | E10: =E8-E9 -> -1.8047063 | F10: =F8-F9 -> -0.27468907 | G10: =G8-G9 -> 0.91212032 | H10: =H8-H9 -> 1.9797021 | I10: =I8-I9 -> 3.0239017 | J10: =J8-J9 -> 4.0897043 | ... L10: =L8-L9 -> 6.4651069
A11: Reinvestment | C11: =(C7-B7)*Assumptions!$E$15 -> -1.43925 | D11: =(D7-C7)*Assumptions!$E$15 -> -1.1154187 | E11: =(E7-D7)*Assumptions!$E$15 -> -0.85495448 | F11: =(F7-E7)*Assumptions!$E$15 -> -0.64066781 | G11: =(G7-F7)*Assumptions!$E$15 -> -0.45965373 | H11: =(H7-G7)*Assumptions!$E$15 -> -0.30196697 | I11: =(I7-H7)*Assumptions!$E$15 -> -0.15967647 | J11: =(J7-I7)*Assumptions!$E$15 -> -0.026169199 | ... L11: =(L7-K7)*Assumptions!$E$15 -> 0.23747822
A12: Free cash flow | C12: =C10-C11 -> -4.2581075 | D12: =D10-D11 -> -2.4605533 | E12: =E10-E11 -> -0.94975183 | F12: =F10-F11 -> 0.36597874 | G12: =G10-G11 -> 1.371774 | H12: =H10-H11 -> 2.2816691 | I12: =I10-I11 -> 3.1835781 | J12: =J10-J11 -> 4.1158735 | ... L12: =L10-L11 -> 6.2276287
A13: Year fraction | C13: =Assumptions!$B$22 -> 1 | D13: 1 | E13: 1 | F13: 1 | G13: 1 | H13: 1 | I13: 1 | J13: 1 | K13: 1 | L13: 1
A14: Discount time (mid-period) | C14: =C13/2 -> 0.5 | D14: =C14+C13/2+D13/2 -> 1.5 | E14: =D14+D13/2+E13/2 -> 2.5 | F14: =E14+E13/2+F13/2 -> 3.5 | G14: =F14+F13/2+G13/2 -> 4.5 | H14: =G14+G13/2+H13/2 -> 5.5 | I14: =H14+H13/2+I13/2 -> 6.5 | J14: =I14+I13/2+J13/2 -> 7.5 | K14: =J14+J13/2+K13/2 -> 8.5 | L14: =K14+K13/2+L13/2 -> 9.5
A15: Discount factor | C15: =1/(1+Assumptions!$E$10)^C14 -> 0.94280904 | D15: =1/(1+Assumptions!$E$10)^D14 -> 0.83805248 | E15: =1/(1+Assumptions!$E$10)^E14 -> 0.74493554 | F15: =1/(1+Assumptions!$E$10)^F14 -> 0.66216492 | G15: =1/(1+Assumptions!$E$10)^G14 -> 0.58859104 | H15: =1/(1+Assumptions!$E$10)^H14 -> 0.52319204 | I15: =1/(1+Assumptions!$E$10)^I14 -> 0.46505959 | J15: =1/(1+Assumptions!$E$10)^J14 -> 0.4133863 | ... L15: =1/(1+Assumptions!$E$10)^L14 -> 0.32662621
A16: PV of free cash flow | C16: =C12*C13*C15 -> -4.0145822 | D16: =D12*D13*D15 -> -2.0620728 | E16: =E12*E13*E15 -> -0.70750389 | F16: =F12*F13*F15 -> 0.24233829 | G16: =G12*G13*G15 -> 0.80741392 | H16: =H12*H13*H15 -> 1.1937511 | I16: =I12*I13*I15 -> 1.4805535 | J16: =J12*J13*J15 -> 1.7014457 | ... L16: =L12*L13*L15 -> 2.0341068
A19: PV of forecast free cash flow | B19: =SUM(C16:L16) -> 2.5556773
A20: Terminal free cash flow (year 11) | B20: =L10*(1+Assumptions!$E$11)-L7*Assumptions!$E$11*Assumptions!$E$15 -> 6.3833194
A21: Terminal value | B21: =B20/(Assumptions!$E$10-Assumptions!$E$11) -> 63.833194
A22: PV of terminal value | B22: =B21/(1+Assumptions!$E$10)^(L14+0.5) -> 19.657186
A23: Enterprise value | B23: =B19+B22 -> 22.212864
A24: Cash & investments | B24: =Main!C7 -> 26.308
A25: Debt | B25: =Main!C8 -> 17.032
A26: Equity value | B26: =B23+B24-B25 -> 31.488864
A27: Shares (mm) | B27: =Main!C4 -> 10.866708
A28: NPV / share | B28: =B26/B27 -> 2.8977372
A29: Price | B29: =Main!C3 -> 2.01
A30: Upside | B30: =B28/B29-1 -> 0.44166028
A31: Terminal value, % of EV | B31: =IFERROR(B22/B23,0) -> 0.88494607
