Workbook

Sheet Main
B2: BridgeBio Pharma, Inc.
B3: Price | C3: =INDEX([1]Pharma!$F$1:$F$1000,MATCH("BBIO",[1]Pharma!$B$1:$B$1000,0)) -> 67.55
B4: Shares | C4: =195.487474 -> 195.48747
B5: Market Cap. | C5: =C3*C4 -> 13205.179
B7: Cash | C7: =677.911+42.249+1000 -> 1720.16
B8: Debt | C8: =550+747.5+575+632.5+1000 -> 3505
B9: Enterprise V. | C9: =C5-C7+C8 -> 14990.019
B11: rNPV / Share | C11: =NPV!C43 -> 54.634524
B12: Upside | C12: =C11/C3-1 -> -0.19119876
B13: Cash / Share | C13: =(C7-C8)/C4 -> -9.1302014
B14: Scenario | C14: =Assumptions!$C$4 -> Base
B16: PDUFA Date | C16: =Assumptions!$B$30 -> 46353
B17: P(Approval) | C17: =Assumptions!$B$32 -> 0.88
B18: If Approved | C18: =Assumptions!$D$168 -> 55.02037
B19: If CRL | C19: =Assumptions!$D$167 -> 51.790583

Sheet Yearly Model
B1: 2021 | C1: 2022 | D1: 2023 | E1: 2024 | F1: 2025 | G1: 2026 | H1: 2027 | I1: 2028 | J1: 2029 | K1: 2030 | L1: 2031 | M1: 2032 | N1: 2033 | O1: 2034 | P1: 2035 | Q1: 2036 | R1: 2037 | S1: 2038 | T1: 2039 | U1: 2040 | V1: 2041 | W1: 2042 | X1: 2043 | Y1: 2044 | Z1: 2045 | AA1: 2046 | AB1: 2047 | AC1: 2048 | AD1: 2049 | AE1: 2050
A2: Revenue | B2: 69.716 | C2: 77.648 | D2: 9.303 | E2: 221.902 | F2: 502.076 | G2: =SUM('Quarterly Model'!F2:I2) -> 1027.19 | H2: =Pipeline!C75 -> 1910.676 | I2: =Pipeline!D75 -> 2676.932 | J2: =Pipeline!E75 -> 3752.158 | K2: =Pipeline!F75 -> 4849.674 | L2: =Pipeline!G75 -> 5904.91 | M2: =Pipeline!H75 -> 6373.68 | N2: =Pipeline!I75 -> 6625.02 | O2: =Pipeline!J75 -> 6736.65 | ... AE2: =Pipeline!Z75 -> 0.83034636
A3: Cost of Sales | B3: 3.114 | C3: 3.434 | D3: 2.446 | E3: 3.878 | F3: 20.962 | G3: =SUM('Quarterly Model'!F3:I3) -> 61.503 | H3: =Pipeline!C76 -> 198.45732 | I3: =Pipeline!D76 -> 292.21474 | J3: =Pipeline!E76 -> 401.48426 | K3: =Pipeline!F76 -> 515.24598 | L3: =Pipeline!G76 -> 623.8604 | M3: =Pipeline!H76 -> 666.7143 | N3: =Pipeline!I76 -> 690.5736 | O3: =Pipeline!J76 -> 700.395 | ... AE3: =Pipeline!Z76 -> 0.078250928
A4: Gross Margin | B4: =B2-B3 -> 66.602 | C4: =C2-C3 -> 74.214 | D4: =D2-D3 -> 6.857 | E4: =E2-E3 -> 218.024 | F4: =F2-F3 -> 481.114 | G4: =G2-G3 -> 965.687 | H4: =H2-H3 -> 1712.2187 | I4: =I2-I3 -> 2384.7173 | ... AE4: =AE2-AE3 -> 0.75209544
A5: Research & Dev. | B5: 451.024 | C5: 399.462 | D5: 455.711 | E5: 506.461 | F5: 451.953 | G5: =SUM('Quarterly Model'!F5:I5) -> 581.084 | H5: =Pipeline!C79 -> 485 | I5: =Pipeline!D79 -> 424.9 | J5: =Pipeline!E79 -> 455.25896 | K5: =Pipeline!F79 -> 581.96088 | L5: =Pipeline!G79 -> 708.5892 | M5: =Pipeline!H79 -> 764.8416 | N5: =Pipeline!I79 -> 795.0024 | O5: =Pipeline!J79 -> 808.398 | ... AE5: =Pipeline!Z79 -> 0.099641564
A6: General & Admin | B6: 192.21 | C6: 186.954 | D6: 158.516 | E6: 304.536 | F6: 552.572 | G6: =SUM('Quarterly Model'!F6:I6) -> 740.157 | H6: =Pipeline!C82 -> 1002.5628 | I6: =Pipeline!D82 -> 1205.0914 | J6: =Pipeline!E82 -> 1479.2695 | K6: =Pipeline!F82 -> 1702.5987 | L6: =Pipeline!G82 -> 1962.8173 | M6: =Pipeline!H82 -> 2024.1071 | N6: =Pipeline!I82 -> 2082.827 | O6: =Pipeline!J82 -> 2080.673 | ... AE6: =Pipeline!Z82 -> 0.26175246
A7: Operating Expense | B7: =SUM(B5:B6) -> 643.234 | C7: =SUM(C5:C6) -> 586.416 | D7: =SUM(D5:D6) -> 614.227 | E7: =SUM(E5:E6) -> 810.997 | F7: =SUM(F5:F6) -> 1004.525 | G7: =SUM(G5:G6) -> 1321.241 | H7: =SUM(H5:H6) -> 1487.5628 | I7: =SUM(I5:I6) -> 1629.9914 | ... AE7: =SUM(AE5:AE6) -> 0.36139403
A8: Operating Income | B8: =B4-B7 -> -576.632 | C8: =C4-C7 -> -512.202 | D8: =D4-D7 -> -607.37 | E8: =E4-E7 -> -592.973 | F8: =F4-F7 -> -523.411 | G8: =G4-G7 -> -355.554 | H8: =H4-H7 -> 224.65588 | I8: =I4-I7 -> 754.72584 | ... AE8: =AE4-AE7 -> 0.39070141
A9: Interest & Other | B9: -9.822 | C9: 27.577 | D9: -45.881 | E9: 50.779 | F9: -209.092 | G9: =SUM('Quarterly Model'!F9:I9) -> -189.411 | H9: =Assumptions!$B$16*MAX(0,G20)-Assumptions!$B$17*Main!$C$8 -> -31.463425 | I9: =Assumptions!$B$16*MAX(0,H20)-Assumptions!$B$17*Main!$C$8 -> -24.218708 | J9: =Assumptions!$B$16*MAX(0,I20)-Assumptions!$B$17*Main!$C$8 -> 3.1753095 | K9: =Assumptions!$B$16*MAX(0,J20)-Assumptions!$B$17*Main!$C$8 -> 56.39983 | L9: =Assumptions!$B$16*MAX(0,K20)-Assumptions!$B$17*Main!$C$8 -> 128.26334 | M9: =Assumptions!$B$16*MAX(0,L20)-Assumptions!$B$17*Main!$C$8 -> 209.37382 | N9: =Assumptions!$B$16*MAX(0,M20)-Assumptions!$B$17*Main!$C$8 -> 302.02278 | O9: =Assumptions!$B$16*MAX(0,N20)-Assumptions!$B$17*Main!$C$8 -> 401.52248 | ... AE9: =Assumptions!$B$16*MAX(0,AD20)-Assumptions!$B$17*Main!$C$8 -> 1526.7357
A10: Pretax | B10: =B8+B9 -> -586.454 | C10: =C8+C9 -> -484.625 | D10: =D8+D9 -> -653.251 | E10: =E8+E9 -> -542.194 | F10: =F8+F9 -> -732.503 | G10: =G8+G9 -> -544.965 | H10: =H8+H9 -> 193.19245 | I10: =I8+I9 -> 730.50713 | ... AE10: =AE8+AE9 -> 1527.1264
A11: Taxes | B11: 0 | C11: 0 | D11: 0 | E11: 1.153 | F11: 0.435 | G11: =SUM('Quarterly Model'!F11:I11) -> 0 | H11: =MAX(0,H10-G21)*Assumptions!$B$15 -> 0 | I11: =MAX(0,I10-H21)*Assumptions!$B$15 -> 0 | J11: =MAX(0,J10-I21)*Assumptions!$B$15 -> 0 | K11: =MAX(0,K10-J21)*Assumptions!$B$15 -> 189.90792 | L11: =MAX(0,L10-K21)*Assumptions!$B$15 -> 574.96035 | M11: =MAX(0,M10-L21)*Assumptions!$B$15 -> 656.75207 | N11: =MAX(0,N10-M21)*Assumptions!$B$15 -> 705.31435 | O11: =MAX(0,O10-N21)*Assumptions!$B$15 -> 745.22836 | ... AE11: =MAX(0,AE10-AD21)*Assumptions!$B$15 -> 320.69655
A12: Net Income | B12: -586.454 | C12: -484.625 | D12: -653.251 | E12: -543.347 | F12: -732.938 | G12: =G10-G11 -> -544.965 | H12: =H10-H11 -> 193.19245 | I12: =I10-I11 -> 730.50713 | J12: =J10-J11 -> 1419.3205 | K12: =K10-K11 -> 1916.3604 | L12: =L10-L11 -> 2162.9461 | M12: =M10-M11 -> 2470.6387 | N12: =N10-N11 -> 2653.3254 | ... AE12: =AE10-AE11 -> 1206.4299
A13: Earnings per Share | B13: =IFERROR(B12/B14,0) -> -4.0625255 | C13: =IFERROR(C12/C14,0) -> -3.2861948 | D13: =IFERROR(D12/D14,0) -> -4.0127955 | E13: =IFERROR(E12/E14,0) -> -2.9200273 | F13: =IFERROR(F12/F14,0) -> -3.8268129 | G13: =IFERROR(G12/G14,0) -> -2.7851371 | H13: =IFERROR(H12/H14,0) -> 0.98826002 | I13: =IFERROR(I12/I14,0) -> 3.7368488 | ... AE13: =IFERROR(AE12/AE14,0) -> 6.1713923
A14: Shares | B14: 144.357 | C14: 147.473 | D14: 162.792 | E14: 186.076 | F14: 191.527 | G14: =AVERAGE('Quarterly Model'!F14:I14) -> 195.669 | H14: =Main!$C$4*(1+Assumptions!$B$26)^(H1-2026) -> 195.48747 | I14: =Main!$C$4*(1+Assumptions!$B$26)^(I1-2026) -> 195.48747 | J14: =Main!$C$4*(1+Assumptions!$B$26)^(J1-2026) -> 195.48747 | K14: =Main!$C$4*(1+Assumptions!$B$26)^(K1-2026) -> 195.48747 | L14: =Main!$C$4*(1+Assumptions!$B$26)^(L1-2026) -> 195.48747 | M14: =Main!$C$4*(1+Assumptions!$B$26)^(M1-2026) -> 195.48747 | N14: =Main!$C$4*(1+Assumptions!$B$26)^(N1-2026) -> 195.48747 | O14: =Main!$C$4*(1+Assumptions!$B$26)^(O1-2026) -> 195.48747 | ... AE14: =Main!$C$4*(1+Assumptions!$B$26)^(AE1-2026) -> 195.48747
A16: Revenue Change | C16: =IFERROR(C2/B2-1,"") -> 0.11377589 | D16: =IFERROR(D2/C2-1,"") -> -0.88019009 | E16: =IFERROR(E2/D2-1,"") -> 22.852736 | F16: =IFERROR(F2/E2-1,"") -> 1.2626024 | G16: =IFERROR(G2/F2-1,"") -> 1.0458855 | H16: =IFERROR(H2/G2-1,"") -> 0.86009988 | I16: =IFERROR(I2/H2-1,"") -> 0.40103921 | J16: =IFERROR(J2/I2-1,"") -> 0.40166355 | ... AE16: =IFERROR(AE2/AD2-1,"") -> -0.6
A17: Gross Margin | B17: =IFERROR(B4/B2,"") -> 0.95533307 | C17: =IFERROR(C4/C2,"") -> 0.95577478 | D17: =IFERROR(D4/D2,"") -> 0.73707406 | E17: =IFERROR(E4/E2,"") -> 0.98252382 | F17: =IFERROR(F4/F2,"") -> 0.95824935 | G17: =IFERROR(G4/G2,"") -> 0.940125 | H17: =IFERROR(H4/H2,"") -> 0.89613241 | I17: =IFERROR(I4/I2,"") -> 0.89083969 | ... AE17: =IFERROR(AE4/AE2,"") -> 0.9057611
A19: Actual / Estimate | B19: A | C19: A | D19: A | E19: A | F19: A | G19: A+E | H19: E | I19: E | J19: E | K19: E | L19: E | M19: E | N19: E | O19: E | P19: E | Q19: E | R19: E | S19: E | T19: E | U19: E | V19: E | W19: E | X19: E | Y19: E | Z19: E | AA19: E | AB19: E | AC19: E | AD19: E | AE19: E
A20: Cash & Investments | G20: ='Quarterly Model'!I20 -> 1497.642 | H20: =G20+H12 -> 1690.8345 | I20: =H20+I12 -> 2421.3416 | J20: =I20+J12 -> 3840.6621 | K20: =J20+K12 -> 5757.0225 | L20: =K20+L12 -> 7919.9686 | M20: =L20+M12 -> 10390.607 | N20: =M20+N12 -> 13043.933 | O20: =N20+O12 -> 15847.411 | ... AE20: =AD20+AE12 -> 44256.05
A21: Tax-Loss Pool | F21: =Assumptions!$B$18 -> 3000 | G21: =F21-MIN(F21,MAX(0,G10))+MAX(0,-G10) -> 3544.965 | H21: =G21-MIN(G21,MAX(0,H10))+MAX(0,-H10) -> 3351.7725 | I21: =H21-MIN(H21,MAX(0,I10))+MAX(0,-I10) -> 2621.2654 | J21: =I21-MIN(I21,MAX(0,J10))+MAX(0,-J10) -> 1201.9449 | K21: =J21-MIN(J21,MAX(0,K10))+MAX(0,-K10) -> 0 | L21: =K21-MIN(K21,MAX(0,L10))+MAX(0,-L10) -> 0 | M21: =L21-MIN(L21,MAX(0,M10))+MAX(0,-M10) -> 0 | N21: =M21-MIN(M21,MAX(0,N10))+MAX(0,-N10) -> 0 | ... AE21: =AD21-MIN(AD21,MAX(0,AE10))+MAX(0,-AE10) -> 0

Sheet Quarterly Model
B1: Q1 2025 | C1: Q2 2025 | D1: Q3 2025 | E1: Q4 2025 | F1: Q1 2026 | G1: Q2 2026 | H1: Q3 2026 | I1: Q4 2026
A2: Revenue | B2: =SUM(B24:B26) -> 116.63 | C2: =SUM(C24:C26) -> 110.56 | D2: =SUM(D24:D26) -> 120.7 | E2: =SUM(E24:E26) -> 154.18 | F2: =SUM(F24:F26) -> 194.52 | G2: =SUM(G24:G26) -> 243.67 | H2: =SUM(H24:H26) -> 278 | I2: =SUM(I24:I26) -> 311
A3: Cost of Sales | B3: 2.639 | C3: 3.653 | D3: 6.563 | E3: 8.107 | F3: 9.939 | G3: 15.046 | H3: =H2*0.062 -> 17.236 | I3: =I2*0.062 -> 19.282
A4: Gross Margin | B4: =B2-B3 -> 113.991 | C4: =C2-C3 -> 106.907 | D4: =D2-D3 -> 114.137 | E4: =E2-E3 -> 146.073 | F4: =F2-F3 -> 184.581 | G4: =G2-G3 -> 228.624 | H4: =H2-H3 -> 260.764 | I4: =I2-I3 -> 291.718
A5: Research & Dev. | B5: 111.431 | C5: 111.231 | D5: 112.874 | E5: 116.417 | F5: 126.636 | G5: 149.448 | H5: 150 | I5: 155
A6: General & Admin | B6: 106.935 | C6: 129.959 | D6: 146.462 | E6: 169.216 | F6: 163.896 | G6: 186.261 | H6: 190 | I6: 200
A7: Operating Expense | B7: =SUM(B5:B6) -> 218.366 | C7: =SUM(C5:C6) -> 241.19 | D7: =SUM(D5:D6) -> 259.336 | E7: =SUM(E5:E6) -> 285.633 | F7: =SUM(F5:F6) -> 290.532 | G7: =SUM(G5:G6) -> 335.709 | H7: =SUM(H5:H6) -> 340 | I7: =SUM(I5:I6) -> 355
A8: Operating Income | B8: =B4-B7 -> -104.375 | C8: =C4-C7 -> -134.283 | D8: =D4-D7 -> -145.199 | E8: =E4-E7 -> -139.56 | F8: =F4-F7 -> -105.951 | G8: =G4-G7 -> -107.085 | H8: =H4-H7 -> -79.236 | I8: =I4-I7 -> -63.282
A9: Interest & Other | B9: -65.236 | C9: -47.38 | D9: -41.283 | E9: -55.193 | F9: -60.599 | G9: -48.812 | H9: -40 | I9: -40
A10: Pretax | B10: =B8+B9 -> -169.611 | C10: =C8+C9 -> -181.663 | D10: =D8+D9 -> -186.482 | E10: =E8+E9 -> -194.753 | F10: =F8+F9 -> -166.55 | G10: =G8+G9 -> -155.897 | H10: =H8+H9 -> -119.236 | I10: =I8+I9 -> -103.282
A11: Taxes | B11: 0 | C11: 2.1 | D11: -1.545 | E11: -0.12 | F11: 0 | G11: 0 | H11: 0 | I11: 0
A12: Net Income | B12: =B10-B11 -> -169.611 | C12: =C10-C11 -> -183.763 | D12: =D10-D11 -> -184.937 | E12: =E10-E11 -> -194.633 | F12: =F10-F11 -> -166.55 | G12: =G10-G11 -> -155.897 | H12: =H10-H11 -> -119.236 | I12: =I10-I11 -> -103.282
A13: Earnings per Share | B13: =IFERROR(B12/B14,0) -> -0.89200873 | C13: =IFERROR(C12/C14,0) -> -0.9645491 | D13: =IFERROR(D12/D14,0) -> -0.96394654 | E13: =IFERROR(E12/E14,0) -> -1.0053721 | F13: =IFERROR(F12/F14,0) -> -0.85502336 | G13: =IFERROR(G12/G14,0) -> -0.79626225 | H13: =IFERROR(H12/H14,0) -> -0.60865748 | I13: =IFERROR(I12/I14,0) -> -0.52641182
A14: Shares | B14: 190.145 | C14: 190.517 | D14: 191.854 | E14: 193.593 | F14: 194.79 | G14: 195.786 | H14: 195.9 | I14: 196.2
A16: Revenue Change (YoY) | F16: =IFERROR(F2/B2-1,"") -> 0.66783846 | G16: =IFERROR(G2/C2-1,"") -> 1.2039616 | H16: =IFERROR(H2/D2-1,"") -> 1.3032312 | I16: =IFERROR(I2/E2-1,"") -> 1.0171228
A17: Gross Margin | B17: =IFERROR(B4/B2,"") -> 0.97737289 | C17: =IFERROR(C4/C2,"") -> 0.96695912 | D17: =IFERROR(D4/D2,"") -> 0.94562552 | E17: =IFERROR(E4/E2,"") -> 0.9474186 | F17: =IFERROR(F4/F2,"") -> 0.948905 | G17: =IFERROR(G4/G2,"") -> 0.93825255 | H17: =IFERROR(H4/H2,"") -> 0.938 | I17: =IFERROR(I4/I2,"") -> 0.938
A19: Actual / Estimate | B19: A | C19: A | D19: A | E19: A | F19: A | G19: A | H19: E | I19: E
A20: Cash & Investments | G20: 720.16 | H20: =G20+H12+H21 -> 1600.924 | I20: =H20+I12+I21 -> 1497.642
A21: Other Cash Flows (est.) | H21: 1000 | I21: 0
A23: Revenue by Product
A24: Attruby (U.S.) | B24: 36.74 | C24: 71.5 | D24: 110.03 | E24: 144.1 | F24: 180.6 | G24: 222.44 | H24: 255 | I24: 285
A25: Royalties | B25: 0.2 | C25: 1.62 | D25: 4.27 | E25: 5.29 | F25: 9.5 | G25: 15.43 | H25: 18 | I25: 21
A26: License & services | B26: 79.69 | C26: 37.44 | D26: 6.4 | E26: 4.79 | F26: 4.42 | G26: 5.8 | H26: 5 | I26: 5

Sheet Assumptions
A1: BBIO — rNPV assumptions ($mm unless noted)
A4: Scenario (1 = Bear, 2 = Base, 3 = Bull) | B4: 2 | C4: =CHOOSE($B$4,"Bear","Base","Bull") -> Base
A5: Overrides (blank = scenario value; the sensitivity tables drive these)
A6: Discount rate override
A7: PDUFA approval probability override
A8: PDUFA program peak sales override ($mm)
A10: Parameter | B10: Active | C10: Bear | D10: Base | E10: Bull
A12: Valuation & corporate
A13: Valuation date | B13: =DATE(2026,10,16) -> 46311
A14: Discount rate (cost of equity) | B14: =IF(ISNUMBER($B$6),$B$6,CHOOSE($B$4,C14,D14,E14)) -> 0.095 | C14: 0.11 | D14: 0.095 | E14: 0.085
A15: Tax rate | B15: =CHOOSE($B$4,C15,D15,E15) -> 0.21 | C15: 0.21 | D15: 0.21 | E15: 0.21
A16: Interest yield on cash | B16: =CHOOSE($B$4,C16,D16,E16) -> 0.0375 | C16: 0.0375 | D16: 0.0375 | E16: 0.0375
A17: Average cash cost of debt (P&L display only) | B17: =CHOOSE($B$4,C17,D17,E17) -> 0.025 | C17: 0.025 | D17: 0.025 | E17: 0.025
A18: Tax-loss pool at 12/31/2025 | B18: =CHOOSE($B$4,C18,D18,E18) -> 3000 | C18: 3000 | D18: 3000 | E18: 3000
A19: Corporate G&A, 2027 | B19: =CHOOSE($B$4,C19,D19,E19) -> 170 | C19: 170 | D19: 170 | E19: 170
A20: Platform / unallocated R&D, 2027 | B20: =CHOOSE($B$4,C20,D20,E20) -> 330 | C20: 330 | D20: 330 | E20: 330
A21: Cost inflation | B21: =CHOOSE($B$4,C21,D21,E21) -> 0.03 | C21: 0.03 | D21: 0.03 | E21: 0.03
A22: Corporate G&A floor, % of revenue | B22: =CHOOSE($B$4,C22,D22,E22) -> 0.07 | C22: 0.07 | D22: 0.07 | E22: 0.07
A23: Platform R&D floor, % of revenue | B23: =CHOOSE($B$4,C23,D23,E23) -> 0.12 | C23: 0.12 | D23: 0.12 | E23: 0.12
A24: Corporate cost cut after a CRL (2027+) | B24: =CHOOSE($B$4,C24,D24,E24) -> 0 | C24: 0 | D24: 0 | E24: 0
A25: Last year of base-level corporate costs (then % of revenue only) | B25: =CHOOSE($B$4,C25,D25,E25) -> 2038 | C25: 2038 | D25: 2038 | E25: 2038
A26: Annual share count growth (EPS display only) | B26: =CHOOSE($B$4,C26,D26,E26) -> 0 | C26: 0 | D26: 0 | E26: 0
A27: Wind-down cost for liquidation value | B27: =CHOOSE($B$4,C27,D27,E27) -> 150 | C27: 150 | D27: 150 | E27: 150
A29: PDUFA event
A30: PDUFA target action date | B30: =DATE(2026,11,27) -> 46353
A31: Application | B31: BBP-418 NDA, LGMD2I/R9 (priority; PRV-eligible)
A32: Probability of approval at this PDUFA | B32: =IF(ISNUMBER($B$7),$B$7,CHOOSE($B$4,C32,D32,E32)) -> 0.88 | C32: 0.82 | D32: 0.88 | E32: 0.93
A33: Probability of approval later, after a CRL | B33: =CHOOSE($B$4,C33,D33,E33) -> 0.8 | C33: 0.75 | D33: 0.8 | E33: 0.85
A34: Launch delay after a CRL (years) | B34: =CHOOSE($B$4,C34,D34,E34) -> 2 | C34: 2 | D34: 2 | E34: 1
A35: Probability of approval, scenario value (before override) | B35: =CHOOSE($B$4,C32,D32,E32) -> 0.88
A36: Read-through: relative cut to other programs' PoS after a CRL | B36: =CHOOSE($B$4,C36,D36,E36) -> 0 | C36: 0 | D36: 0 | E36: 0
A37: Read-through multiplier on other programs' PoS (1 = none) | B37: =1+$B$36*($B$32-$B$35)/$B$35 -> 1
A38: Expected corporate cost multiplier (2027+) | B38: =$B$32+(1-$B$32)*(1-$B$24) -> 1
A40: Commercial curves (by year since launch)
A41: Year since launch | B41: 1 | C41: 2 | D41: 3 | E41: 4 | F41: 5 | G41: 6 | H41: 7
A42: Ramp 1 — standard launch, % of peak | B42: 0.1 | C42: 0.25 | D42: 0.45 | E42: 0.65 | F42: 0.82 | G42: 0.93 | H42: 1
A43: Ramp 2 — orphan-disease launch, % of peak | B43: 0.15 | C43: 0.35 | D43: 0.55 | E43: 0.75 | F43: 0.9 | G43: 1 | H43: 1
A44: Commercial SG&A, % of sales (years 1–5; floor = program maturity %) | B44: 0.9 | C44: 0.55 | D44: 0.4 | E44: 0.32 | F44: 0.28
A46: Attruby (acoramidis) — ATTR-CM, U.S. (marketed)
A47: Launch year (first commercial year) | B47: 2025
A48: Peak net sales, unrisked | B48: =CHOOSE($B$4,C48,D48,E48) -> 3000 | C48: 2000 | D48: 3000 | E48: 4000
A49: Year peak is reached | B49: =CHOOSE($B$4,C49,D49,E49) -> 2031 | C49: 2031 | D49: 2031 | E49: 2031
A50: Path to peak (1 = straight line, >1 = slower start) | B50: 1
A51: Company revenue, % of product net sales | B51: 1
A52: Cost of goods, % of product sales | B52: 0.05
A53: Royalties owed, % of product sales | B53: 0.06
A54: Commercial SG&A at maturity, % of sales | B54: 0.25
A55: Loss of exclusivity (year) | B55: =CHOOSE($B$4,C55,D55,E55) -> 2037 | C55: 2036 | D55: 2037 | E55: 2038
A56: Post-LOE annual sales erosion | B56: 0.6
A57: 2026E net sales (Quarterly Model) | B57: =SUM('Quarterly Model'!F24:I24) -> 943.04
A59: Acoramidis — ex-U.S. royalties (Bayer, Alexion) (marketed)
A60: Launch year (first commercial year) | B60: 2025
A61: Peak net sales, unrisked | B61: =CHOOSE($B$4,C61,D61,E61) -> 250 | C61: 150 | D61: 250 | E61: 350
A62: Year peak is reached | B62: =CHOOSE($B$4,C62,D62,E62) -> 2031 | C62: 2031 | D62: 2031 | E62: 2031
A63: Path to peak (1 = straight line, >1 = slower start) | B63: 1
A64: Company revenue, % of product net sales | B64: 1
A65: Cost of goods, % of product sales | B65: 0.2
A66: Royalties owed, % of product sales | B66: 0
A67: Commercial SG&A at maturity, % of sales | B67: 0
A68: Loss of exclusivity (year) | B68: =CHOOSE($B$4,C68,D68,E68) -> 2037 | C68: 2036 | D68: 2037 | E68: 2038
A69: Post-LOE annual sales erosion | B69: 0.6
A70: 2026E net sales (Quarterly Model) | B70: =SUM('Quarterly Model'!F25:I25) -> 63.93
A72: BBP-418 — LGMD2I/R9 (PDUFA)
A73: Launch year (first full year of sales) | B73: =CHOOSE($B$4,C73,D73,E73) -> 2027 | C73: 2027 | D73: 2027 | E73: 2027
A74: Peak net sales, unrisked | B74: =IF(ISNUMBER($B$8),$B$8,CHOOSE($B$4,C74,D74,E74)) -> 800 | C74: 500 | D74: 800 | E74: 1200
A75: Probability of approval (PDUFA event above) | B75: =$B$32 -> 0.88
A76: Company revenue, % of product net sales | B76: 1
A77: Cost of goods, % of product sales | B77: 0.05
A78: Royalties owed, % of product sales | B78: 0.03
A79: Commercial SG&A at maturity, % of sales | B79: 0.25
A80: Pre-launch commercial spend, year before launch | B80: 30
A81: Launch ramp (1 = standard, 2 = orphan) | B81: 2
A82: Loss of exclusivity (year) | B82: =CHOOSE($B$4,C82,D82,E82) -> 2040 | C82: 2040 | D82: 2040 | E82: 2040
A83: Post-LOE annual sales erosion | B83: 0.6
A84: Development spend, unrisked ($mm) by year | B84: 2027 | C84: 2028 | D84: 2029 | E84: 2030 | F84: 2031 | G84: 2032 | H84: 2033 | I84: 2034
A85: Cost | B85: 20 | C85: 15 | D85: 0 | E85: 0 | F85: 0 | G85: 0 | H85: 0 | I85: 0
A86: Probability the cost is incurred | B86: 1 | C86: 1 | D86: 1 | E86: 1 | F86: 1 | G86: 1 | H86: 1 | I86: 1
A87: Milestones / PRV received, by year relative to launch (on-time path) | B87: 0 | C87: 1 | D87: 2 | E87: 3 | F87: 4 | G87: 5 | H87: 6 | I87: 7 | J87: 8 | K87: 9
A88: Amount ($mm, unrisked) | B88: 150 | C88: 0 | D88: 0 | E88: 0 | F88: 0 | G88: 0 | H88: 0 | I88: 0 | J88: 0 | K88: 0
A90: Encaleret — ADH1 (PDUFA May 8, 2027) (pipeline)
A91: Launch year (first full year of sales) | B91: =CHOOSE($B$4,C91,D91,E91) -> 2027 | C91: 2027 | D91: 2027 | E91: 2027
A92: Peak net sales, unrisked | B92: =CHOOSE($B$4,C92,D92,E92) -> 800 | C92: 500 | D92: 800 | E92: 1200
A93: Probability of reaching market | B93: =CHOOSE($B$4,C93,D93,E93) -> 0.87 | C93: 0.8 | D93: 0.87 | E93: 0.92
A94: Company revenue, % of product net sales | B94: 1
A95: Cost of goods, % of product sales | B95: 0.05
A96: Royalties owed, % of product sales | B96: 0.03
A97: Commercial SG&A at maturity, % of sales | B97: 0.25
A98: Pre-launch commercial spend, year before launch | B98: 25
A99: Launch ramp (1 = standard, 2 = orphan) | B99: 2
A100: Loss of exclusivity (year) | B100: =CHOOSE($B$4,C100,D100,E100) -> 2041 | C100: 2041 | D100: 2041 | E100: 2041
A101: Post-LOE annual sales erosion | B101: 0.6
A102: Development spend, unrisked ($mm) by year | B102: 2027 | C102: 2028 | D102: 2029 | E102: 2030 | F102: 2031 | G102: 2032 | H102: 2033 | I102: 2034
A103: Cost | B103: 10 | C103: 0 | D103: 0 | E103: 0 | F103: 0 | G103: 0 | H103: 0 | I103: 0
A104: Probability the cost is incurred | B104: 1 | C104: 1 | D104: 1 | E104: 1 | F104: 1 | G104: 1 | H104: 1 | I104: 1
A106: Infigratinib — achondroplasia (PDUFA Feb 4, 2027) (pipeline)
A107: Launch year (first full year of sales) | B107: =CHOOSE($B$4,C107,D107,E107) -> 2027 | C107: 2027 | D107: 2027 | E107: 2027
A108: Peak net sales, unrisked | B108: =CHOOSE($B$4,C108,D108,E108) -> 1300 | C108: 800 | D108: 1300 | E108: 2000
A109: Probability of reaching market | B109: =CHOOSE($B$4,C109,D109,E109) -> 0.87 | C109: 0.8 | D109: 0.87 | E109: 0.92
A110: Company revenue, % of product net sales | B110: 1
A111: Cost of goods, % of product sales | B111: 0.05
...

Sheet Pipeline
A1: BBIO — risk-adjusted program build ($mm)
A2: Year | C2: 2027 | D2: 2028 | E2: 2029 | F2: 2030 | G2: 2031 | H2: 2032 | I2: 2033 | J2: 2034 | K2: 2035 | L2: 2036 | M2: 2037 | N2: 2038 | O2: 2039 | P2: 2040 | Q2: 2041 | R2: 2042 | S2: 2043 | T2: 2044 | U2: 2045 | V2: 2046 | W2: 2047 | X2: 2048 | Y2: 2049 | Z2: 2050
A4: Attruby (acoramidis) — ATTR-CM, U.S.
A5: Years since launch | C5: =C$2-Assumptions!$B$47+1 -> 3 | D5: =D$2-Assumptions!$B$47+1 -> 4 | E5: =E$2-Assumptions!$B$47+1 -> 5 | F5: =F$2-Assumptions!$B$47+1 -> 6 | G5: =G$2-Assumptions!$B$47+1 -> 7 | H5: =H$2-Assumptions!$B$47+1 -> 8 | I5: =I$2-Assumptions!$B$47+1 -> 9 | J5: =J$2-Assumptions!$B$47+1 -> 10 | ... Z5: =Z$2-Assumptions!$B$47+1 -> 26
A6: Net sales | C6: =IF(C$2>Assumptions!$B$55,Assumptions!$B$57*(1-Assumptions!$B$56),IF(C$2<Assumptions!$B$49,Assumptions!$B$57+(Assumptions!$B$48-Assumptions!$B$57)*((C$2-2026)/(Assumptions!$B$49-2026))^Assumptions!$B$50,Assumptions!$B$48)) -> 1354.432 | D6: =IF(D$2>Assumptions!$B$55,C6*(1-Assumptions!$B$56),IF(D$2<Assumptions!$B$49,Assumptions!$B$57+(Assumptions!$B$48-Assumptions!$B$57)*((D$2-2026)/(Assumptions!$B$49-2026))^Assumptions!$B$50,Assumptions!$B$48)) -> 1765.824 | E6: =IF(E$2>Assumptions!$B$55,D6*(1-Assumptions!$B$56),IF(E$2<Assumptions!$B$49,Assumptions!$B$57+(Assumptions!$B$48-Assumptions!$B$57)*((E$2-2026)/(Assumptions!$B$49-2026))^Assumptions!$B$50,Assumptions!$B$48)) -> 2177.216 | F6: =IF(F$2>Assumptions!$B$55,E6*(1-Assumptions!$B$56),IF(F$2<Assumptions!$B$49,Assumptions!$B$57+(Assumptions!$B$48-Assumptions!$B$57)*((F$2-2026)/(Assumptions!$B$49-2026))^Assumptions!$B$50,Assumptions!$B$48)) -> 2588.608 | G6: =IF(G$2>Assumptions!$B$55,F6*(1-Assumptions!$B$56),IF(G$2<Assumptions!$B$49,Assumptions!$B$57+(Assumptions!$B$48-Assumptions!$B$57)*((G$2-2026)/(Assumptions!$B$49-2026))^Assumptions!$B$50,Assumptions!$B$48)) -> 3000 | H6: =IF(H$2>Assumptions!$B$55,G6*(1-Assumptions!$B$56),IF(H$2<Assumptions!$B$49,Assumptions!$B$57+(Assumptions!$B$48-Assumptions!$B$57)*((H$2-2026)/(Assumptions!$B$49-2026))^Assumptions!$B$50,Assumptions!$B$48)) -> 3000 | I6: =IF(I$2>Assumptions!$B$55,H6*(1-Assumptions!$B$56),IF(I$2<Assumptions!$B$49,Assumptions!$B$57+(Assumptions!$B$48-Assumptions!$B$57)*((I$2-2026)/(Assumptions!$B$49-2026))^Assumptions!$B$50,Assumptions!$B$48)) -> 3000 | J6: =IF(J$2>Assumptions!$B$55,I6*(1-Assumptions!$B$56),IF(J$2<Assumptions!$B$49,Assumptions!$B$57+(Assumptions!$B$48-Assumptions!$B$57)*((J$2-2026)/(Assumptions!$B$49-2026))^Assumptions!$B$50,Assumptions!$B$48)) -> 3000 | K6: =IF(K$2>Assumptions!$B$55,J6*(1-Assumptions!$B$56),IF(K$2<Assumptions!$B$49,Assumptions!$B$57+(Assumptions!$B$48-Assumptions!$B$57)*((K$2-2026)/(Assumptions!$B$49-2026))^Assumptions!$B$50,Assumptions!$B$48)) -> 3000 | ... Z6: =IF(Z$2>Assumptions!$B$55,Y6*(1-Assumptions!$B$56),IF(Z$2<Assumptions!$B$49,Assumptions!$B$57+(Assumptions!$B$48-Assumptions!$B$57)*((Z$2-2026)/(Assumptions!$B$49-2026))^Assumptions!$B$50,Assumptions!$B$48)) -> 0.020132659
A7: Company revenue | C7: =C6*Assumptions!$B$51 -> 1354.432 | D7: =D6*Assumptions!$B$51 -> 1765.824 | E7: =E6*Assumptions!$B$51 -> 2177.216 | F7: =F6*Assumptions!$B$51 -> 2588.608 | G7: =G6*Assumptions!$B$51 -> 3000 | H7: =H6*Assumptions!$B$51 -> 3000 | I7: =I6*Assumptions!$B$51 -> 3000 | J7: =J6*Assumptions!$B$51 -> 3000 | ... Z7: =Z6*Assumptions!$B$51 -> 0.020132659
A8: COGS + royalties | C8: =C6*(Assumptions!$B$52+Assumptions!$B$53) -> 148.98752 | D8: =D6*(Assumptions!$B$52+Assumptions!$B$53) -> 194.24064 | E8: =E6*(Assumptions!$B$52+Assumptions!$B$53) -> 239.49376 | F8: =F6*(Assumptions!$B$52+Assumptions!$B$53) -> 284.74688 | G8: =G6*(Assumptions!$B$52+Assumptions!$B$53) -> 330 | H8: =H6*(Assumptions!$B$52+Assumptions!$B$53) -> 330 | I8: =I6*(Assumptions!$B$52+Assumptions!$B$53) -> 330 | J8: =J6*(Assumptions!$B$52+Assumptions!$B$53) -> 330 | ... Z8: =Z6*(Assumptions!$B$52+Assumptions!$B$53) -> 0.0022145925
A9: Commercial SG&A | C9: =IF(Assumptions!$B$54=0,0,IF(FALSE,0,IF(C5>=1,C6*IF(OR(Assumptions!$B$51<1,C5>5),Assumptions!$B$54,MAX(Assumptions!$B$54,INDEX(Assumptions!$B$44:$F$44,C5))),0))) -> 541.7728 | D9: =IF(Assumptions!$B$54=0,0,IF(FALSE,0,IF(D5>=1,D6*IF(OR(Assumptions!$B$51<1,D5>5),Assumptions!$B$54,MAX(Assumptions!$B$54,INDEX(Assumptions!$B$44:$F$44,D5))),0))) -> 565.06368 | E9: =IF(Assumptions!$B$54=0,0,IF(FALSE,0,IF(E5>=1,E6*IF(OR(Assumptions!$B$51<1,E5>5),Assumptions!$B$54,MAX(Assumptions!$B$54,INDEX(Assumptions!$B$44:$F$44,E5))),0))) -> 609.62048 | F9: =IF(Assumptions!$B$54=0,0,IF(FALSE,0,IF(F5>=1,F6*IF(OR(Assumptions!$B$51<1,F5>5),Assumptions!$B$54,MAX(Assumptions!$B$54,INDEX(Assumptions!$B$44:$F$44,F5))),0))) -> 647.152 | G9: =IF(Assumptions!$B$54=0,0,IF(FALSE,0,IF(G5>=1,G6*IF(OR(Assumptions!$B$51<1,G5>5),Assumptions!$B$54,MAX(Assumptions!$B$54,INDEX(Assumptions!$B$44:$F$44,G5))),0))) -> 750 | H9: =IF(Assumptions!$B$54=0,0,IF(FALSE,0,IF(H5>=1,H6*IF(OR(Assumptions!$B$51<1,H5>5),Assumptions!$B$54,MAX(Assumptions!$B$54,INDEX(Assumptions!$B$44:$F$44,H5))),0))) -> 750 | I9: =IF(Assumptions!$B$54=0,0,IF(FALSE,0,IF(I5>=1,I6*IF(OR(Assumptions!$B$51<1,I5>5),Assumptions!$B$54,MAX(Assumptions!$B$54,INDEX(Assumptions!$B$44:$F$44,I5))),0))) -> 750 | J9: =IF(Assumptions!$B$54=0,0,IF(FALSE,0,IF(J5>=1,J6*IF(OR(Assumptions!$B$51<1,J5>5),Assumptions!$B$54,MAX(Assumptions!$B$54,INDEX(Assumptions!$B$44:$F$44,J5))),0))) -> 750 | ... Z9: =IF(Assumptions!$B$54=0,0,IF(FALSE,0,IF(Z5>=1,Z6*IF(OR(Assumptions!$B$51<1,Z5>5),Assumptions!$B$54,MAX(Assumptions!$B$54,INDEX(Assumptions!$B$44:$F$44,Z5))),0))) -> 0.0050331648
A10: Development R&D | C10: =0 -> 0 | D10: =0 -> 0 | E10: =0 -> 0 | F10: =0 -> 0 | G10: =0 -> 0 | H10: =0 -> 0 | I10: =0 -> 0 | J10: =0 -> 0 | ... Z10: =0 -> 0
A11: Program contribution (pre-tax) | C11: =C7-C8-C9-C10 -> 663.67168 | D11: =D7-D8-D9-D10 -> 1006.5197 | E11: =E7-E8-E9-E10 -> 1328.1018 | F11: =F7-F8-F9-F10 -> 1656.7091 | G11: =G7-G8-G9-G10 -> 1920 | H11: =H7-H8-H9-H10 -> 1920 | I11: =I7-I8-I9-I10 -> 1920 | J11: =J7-J8-J9-J10 -> 1920 | ... Z11: =Z7-Z8-Z9-Z10 -> 0.012884902
A13: Acoramidis — ex-U.S. royalties (Bayer, Alexion)
A14: Years since launch | C14: =C$2-Assumptions!$B$60+1 -> 3 | D14: =D$2-Assumptions!$B$60+1 -> 4 | E14: =E$2-Assumptions!$B$60+1 -> 5 | F14: =F$2-Assumptions!$B$60+1 -> 6 | G14: =G$2-Assumptions!$B$60+1 -> 7 | H14: =H$2-Assumptions!$B$60+1 -> 8 | I14: =I$2-Assumptions!$B$60+1 -> 9 | J14: =J$2-Assumptions!$B$60+1 -> 10 | ... Z14: =Z$2-Assumptions!$B$60+1 -> 26
A15: Net sales | C15: =IF(C$2>Assumptions!$B$68,Assumptions!$B$70*(1-Assumptions!$B$69),IF(C$2<Assumptions!$B$62,Assumptions!$B$70+(Assumptions!$B$61-Assumptions!$B$70)*((C$2-2026)/(Assumptions!$B$62-2026))^Assumptions!$B$63,Assumptions!$B$61)) -> 101.144 | D15: =IF(D$2>Assumptions!$B$68,C15*(1-Assumptions!$B$69),IF(D$2<Assumptions!$B$62,Assumptions!$B$70+(Assumptions!$B$61-Assumptions!$B$70)*((D$2-2026)/(Assumptions!$B$62-2026))^Assumptions!$B$63,Assumptions!$B$61)) -> 138.358 | E15: =IF(E$2>Assumptions!$B$68,D15*(1-Assumptions!$B$69),IF(E$2<Assumptions!$B$62,Assumptions!$B$70+(Assumptions!$B$61-Assumptions!$B$70)*((E$2-2026)/(Assumptions!$B$62-2026))^Assumptions!$B$63,Assumptions!$B$61)) -> 175.572 | F15: =IF(F$2>Assumptions!$B$68,E15*(1-Assumptions!$B$69),IF(F$2<Assumptions!$B$62,Assumptions!$B$70+(Assumptions!$B$61-Assumptions!$B$70)*((F$2-2026)/(Assumptions!$B$62-2026))^Assumptions!$B$63,Assumptions!$B$61)) -> 212.786 | G15: =IF(G$2>Assumptions!$B$68,F15*(1-Assumptions!$B$69),IF(G$2<Assumptions!$B$62,Assumptions!$B$70+(Assumptions!$B$61-Assumptions!$B$70)*((G$2-2026)/(Assumptions!$B$62-2026))^Assumptions!$B$63,Assumptions!$B$61)) -> 250 | H15: =IF(H$2>Assumptions!$B$68,G15*(1-Assumptions!$B$69),IF(H$2<Assumptions!$B$62,Assumptions!$B$70+(Assumptions!$B$61-Assumptions!$B$70)*((H$2-2026)/(Assumptions!$B$62-2026))^Assumptions!$B$63,Assumptions!$B$61)) -> 250 | I15: =IF(I$2>Assumptions!$B$68,H15*(1-Assumptions!$B$69),IF(I$2<Assumptions!$B$62,Assumptions!$B$70+(Assumptions!$B$61-Assumptions!$B$70)*((I$2-2026)/(Assumptions!$B$62-2026))^Assumptions!$B$63,Assumptions!$B$61)) -> 250 | J15: =IF(J$2>Assumptions!$B$68,I15*(1-Assumptions!$B$69),IF(J$2<Assumptions!$B$62,Assumptions!$B$70+(Assumptions!$B$61-Assumptions!$B$70)*((J$2-2026)/(Assumptions!$B$62-2026))^Assumptions!$B$63,Assumptions!$B$61)) -> 250 | K15: =IF(K$2>Assumptions!$B$68,J15*(1-Assumptions!$B$69),IF(K$2<Assumptions!$B$62,Assumptions!$B$70+(Assumptions!$B$61-Assumptions!$B$70)*((K$2-2026)/(Assumptions!$B$62-2026))^Assumptions!$B$63,Assumptions!$B$61)) -> 250 | ... Z15: =IF(Z$2>Assumptions!$B$68,Y15*(1-Assumptions!$B$69),IF(Z$2<Assumptions!$B$62,Assumptions!$B$70+(Assumptions!$B$61-Assumptions!$B$70)*((Z$2-2026)/(Assumptions!$B$62-2026))^Assumptions!$B$63,Assumptions!$B$61)) -> 0.0016777216
A16: Company revenue | C16: =C15*Assumptions!$B$64 -> 101.144 | D16: =D15*Assumptions!$B$64 -> 138.358 | E16: =E15*Assumptions!$B$64 -> 175.572 | F16: =F15*Assumptions!$B$64 -> 212.786 | G16: =G15*Assumptions!$B$64 -> 250 | H16: =H15*Assumptions!$B$64 -> 250 | I16: =I15*Assumptions!$B$64 -> 250 | J16: =J15*Assumptions!$B$64 -> 250 | ... Z16: =Z15*Assumptions!$B$64 -> 0.0016777216
A17: COGS + royalties | C17: =C15*(Assumptions!$B$65+Assumptions!$B$66) -> 20.2288 | D17: =D15*(Assumptions!$B$65+Assumptions!$B$66) -> 27.6716 | E17: =E15*(Assumptions!$B$65+Assumptions!$B$66) -> 35.1144 | F17: =F15*(Assumptions!$B$65+Assumptions!$B$66) -> 42.5572 | G17: =G15*(Assumptions!$B$65+Assumptions!$B$66) -> 50 | H17: =H15*(Assumptions!$B$65+Assumptions!$B$66) -> 50 | I17: =I15*(Assumptions!$B$65+Assumptions!$B$66) -> 50 | J17: =J15*(Assumptions!$B$65+Assumptions!$B$66) -> 50 | ... Z17: =Z15*(Assumptions!$B$65+Assumptions!$B$66) -> 0.00033554432
A18: Commercial SG&A | C18: =IF(Assumptions!$B$67=0,0,IF(FALSE,0,IF(C14>=1,C15*IF(OR(Assumptions!$B$64<1,C14>5),Assumptions!$B$67,MAX(Assumptions!$B$67,INDEX(Assumptions!$B$44:$F$44,C14))),0))) -> 0 | D18: =IF(Assumptions!$B$67=0,0,IF(FALSE,0,IF(D14>=1,D15*IF(OR(Assumptions!$B$64<1,D14>5),Assumptions!$B$67,MAX(Assumptions!$B$67,INDEX(Assumptions!$B$44:$F$44,D14))),0))) -> 0 | E18: =IF(Assumptions!$B$67=0,0,IF(FALSE,0,IF(E14>=1,E15*IF(OR(Assumptions!$B$64<1,E14>5),Assumptions!$B$67,MAX(Assumptions!$B$67,INDEX(Assumptions!$B$44:$F$44,E14))),0))) -> 0 | F18: =IF(Assumptions!$B$67=0,0,IF(FALSE,0,IF(F14>=1,F15*IF(OR(Assumptions!$B$64<1,F14>5),Assumptions!$B$67,MAX(Assumptions!$B$67,INDEX(Assumptions!$B$44:$F$44,F14))),0))) -> 0 | G18: =IF(Assumptions!$B$67=0,0,IF(FALSE,0,IF(G14>=1,G15*IF(OR(Assumptions!$B$64<1,G14>5),Assumptions!$B$67,MAX(Assumptions!$B$67,INDEX(Assumptions!$B$44:$F$44,G14))),0))) -> 0 | H18: =IF(Assumptions!$B$67=0,0,IF(FALSE,0,IF(H14>=1,H15*IF(OR(Assumptions!$B$64<1,H14>5),Assumptions!$B$67,MAX(Assumptions!$B$67,INDEX(Assumptions!$B$44:$F$44,H14))),0))) -> 0 | I18: =IF(Assumptions!$B$67=0,0,IF(FALSE,0,IF(I14>=1,I15*IF(OR(Assumptions!$B$64<1,I14>5),Assumptions!$B$67,MAX(Assumptions!$B$67,INDEX(Assumptions!$B$44:$F$44,I14))),0))) -> 0 | J18: =IF(Assumptions!$B$67=0,0,IF(FALSE,0,IF(J14>=1,J15*IF(OR(Assumptions!$B$64<1,J14>5),Assumptions!$B$67,MAX(Assumptions!$B$67,INDEX(Assumptions!$B$44:$F$44,J14))),0))) -> 0 | ... Z18: =IF(Assumptions!$B$67=0,0,IF(FALSE,0,IF(Z14>=1,Z15*IF(OR(Assumptions!$B$64<1,Z14>5),Assumptions!$B$67,MAX(Assumptions!$B$67,INDEX(Assumptions!$B$44:$F$44,Z14))),0))) -> 0
A19: Development R&D | C19: =0 -> 0 | D19: =0 -> 0 | E19: =0 -> 0 | F19: =0 -> 0 | G19: =0 -> 0 | H19: =0 -> 0 | I19: =0 -> 0 | J19: =0 -> 0 | ... Z19: =0 -> 0
A20: Program contribution (pre-tax) | C20: =C16-C17-C18-C19 -> 80.9152 | D20: =D16-D17-D18-D19 -> 110.6864 | E20: =E16-E17-E18-E19 -> 140.4576 | F20: =F16-F17-F18-F19 -> 170.2288 | G20: =G16-G17-G18-G19 -> 200 | H20: =H16-H17-H18-H19 -> 200 | I20: =I16-I17-I18-I19 -> 200 | J20: =J16-J17-J18-J19 -> 200 | ... Z20: =Z16-Z17-Z18-Z19 -> 0.0013421773
A22: BBP-418 — LGMD2I/R9
A23: Years since launch (approved on time) | C23: =C$2-Assumptions!$B$73+1 -> 1 | D23: =D$2-Assumptions!$B$73+1 -> 2 | E23: =E$2-Assumptions!$B$73+1 -> 3 | F23: =F$2-Assumptions!$B$73+1 -> 4 | G23: =G$2-Assumptions!$B$73+1 -> 5 | H23: =H$2-Assumptions!$B$73+1 -> 6 | I23: =I$2-Assumptions!$B$73+1 -> 7 | J23: =J$2-Assumptions!$B$73+1 -> 8 | ... Z23: =Z$2-Assumptions!$B$73+1 -> 24
A24: Net sales, unrisked (approved on time) | C24: =IF(C$2>Assumptions!$B$82,0*(1-Assumptions!$B$83),IF(C23>=1,Assumptions!$B$74*CHOOSE(Assumptions!$B$81,INDEX(Assumptions!$B$42:$H$42,MIN(C23,7)),INDEX(Assumptions!$B$43:$H$43,MIN(C23,7))),0)) -> 120 | D24: =IF(D$2>Assumptions!$B$82,C24*(1-Assumptions!$B$83),IF(D23>=1,Assumptions!$B$74*CHOOSE(Assumptions!$B$81,INDEX(Assumptions!$B$42:$H$42,MIN(D23,7)),INDEX(Assumptions!$B$43:$H$43,MIN(D23,7))),0)) -> 280 | E24: =IF(E$2>Assumptions!$B$82,D24*(1-Assumptions!$B$83),IF(E23>=1,Assumptions!$B$74*CHOOSE(Assumptions!$B$81,INDEX(Assumptions!$B$42:$H$42,MIN(E23,7)),INDEX(Assumptions!$B$43:$H$43,MIN(E23,7))),0)) -> 440 | F24: =IF(F$2>Assumptions!$B$82,E24*(1-Assumptions!$B$83),IF(F23>=1,Assumptions!$B$74*CHOOSE(Assumptions!$B$81,INDEX(Assumptions!$B$42:$H$42,MIN(F23,7)),INDEX(Assumptions!$B$43:$H$43,MIN(F23,7))),0)) -> 600 | G24: =IF(G$2>Assumptions!$B$82,F24*(1-Assumptions!$B$83),IF(G23>=1,Assumptions!$B$74*CHOOSE(Assumptions!$B$81,INDEX(Assumptions!$B$42:$H$42,MIN(G23,7)),INDEX(Assumptions!$B$43:$H$43,MIN(G23,7))),0)) -> 720 | H24: =IF(H$2>Assumptions!$B$82,G24*(1-Assumptions!$B$83),IF(H23>=1,Assumptions!$B$74*CHOOSE(Assumptions!$B$81,INDEX(Assumptions!$B$42:$H$42,MIN(H23,7)),INDEX(Assumptions!$B$43:$H$43,MIN(H23,7))),0)) -> 800 | I24: =IF(I$2>Assumptions!$B$82,H24*(1-Assumptions!$B$83),IF(I23>=1,Assumptions!$B$74*CHOOSE(Assumptions!$B$81,INDEX(Assumptions!$B$42:$H$42,MIN(I23,7)),INDEX(Assumptions!$B$43:$H$43,MIN(I23,7))),0)) -> 800 | J24: =IF(J$2>Assumptions!$B$82,I24*(1-Assumptions!$B$83),IF(J23>=1,Assumptions!$B$74*CHOOSE(Assumptions!$B$81,INDEX(Assumptions!$B$42:$H$42,MIN(J23,7)),INDEX(Assumptions!$B$43:$H$43,MIN(J23,7))),0)) -> 800 | K24: =IF(K$2>Assumptions!$B$82,J24*(1-Assumptions!$B$83),IF(K23>=1,Assumptions!$B$74*CHOOSE(Assumptions!$B$81,INDEX(Assumptions!$B$42:$H$42,MIN(K23,7)),INDEX(Assumptions!$B$43:$H$43,MIN(K23,7))),0)) -> 800 | ... Z24: =IF(Z$2>Assumptions!$B$82,Y24*(1-Assumptions!$B$83),IF(Z23>=1,Assumptions!$B$74*CHOOSE(Assumptions!$B$81,INDEX(Assumptions!$B$42:$H$42,MIN(Z23,7)),INDEX(Assumptions!$B$43:$H$43,MIN(Z23,7))),0)) -> 0.08388608
A25: Years since launch (approved after a CRL) | C25: =C$2-(Assumptions!$B$73+Assumptions!$B$34)+1 -> -1 | D25: =D$2-(Assumptions!$B$73+Assumptions!$B$34)+1 -> 0 | E25: =E$2-(Assumptions!$B$73+Assumptions!$B$34)+1 -> 1 | F25: =F$2-(Assumptions!$B$73+Assumptions!$B$34)+1 -> 2 | G25: =G$2-(Assumptions!$B$73+Assumptions!$B$34)+1 -> 3 | H25: =H$2-(Assumptions!$B$73+Assumptions!$B$34)+1 -> 4 | I25: =I$2-(Assumptions!$B$73+Assumptions!$B$34)+1 -> 5 | J25: =J$2-(Assumptions!$B$73+Assumptions!$B$34)+1 -> 6 | ... Z25: =Z$2-(Assumptions!$B$73+Assumptions!$B$34)+1 -> 22
A26: Net sales, unrisked (approved after a CRL) | C26: =IF(C$2>Assumptions!$B$82,0*(1-Assumptions!$B$83),IF(C25>=1,Assumptions!$B$74*CHOOSE(Assumptions!$B$81,INDEX(Assumptions!$B$42:$H$42,MIN(C25,7)),INDEX(Assumptions!$B$43:$H$43,MIN(C25,7))),0)) -> 0 | D26: =IF(D$2>Assumptions!$B$82,C26*(1-Assumptions!$B$83),IF(D25>=1,Assumptions!$B$74*CHOOSE(Assumptions!$B$81,INDEX(Assumptions!$B$42:$H$42,MIN(D25,7)),INDEX(Assumptions!$B$43:$H$43,MIN(D25,7))),0)) -> 0 | E26: =IF(E$2>Assumptions!$B$82,D26*(1-Assumptions!$B$83),IF(E25>=1,Assumptions!$B$74*CHOOSE(Assumptions!$B$81,INDEX(Assumptions!$B$42:$H$42,MIN(E25,7)),INDEX(Assumptions!$B$43:$H$43,MIN(E25,7))),0)) -> 120 | F26: =IF(F$2>Assumptions!$B$82,E26*(1-Assumptions!$B$83),IF(F25>=1,Assumptions!$B$74*CHOOSE(Assumptions!$B$81,INDEX(Assumptions!$B$42:$H$42,MIN(F25,7)),INDEX(Assumptions!$B$43:$H$43,MIN(F25,7))),0)) -> 280 | G26: =IF(G$2>Assumptions!$B$82,F26*(1-Assumptions!$B$83),IF(G25>=1,Assumptions!$B$74*CHOOSE(Assumptions!$B$81,INDEX(Assumptions!$B$42:$H$42,MIN(G25,7)),INDEX(Assumptions!$B$43:$H$43,MIN(G25,7))),0)) -> 440 | H26: =IF(H$2>Assumptions!$B$82,G26*(1-Assumptions!$B$83),IF(H25>=1,Assumptions!$B$74*CHOOSE(Assumptions!$B$81,INDEX(Assumptions!$B$42:$H$42,MIN(H25,7)),INDEX(Assumptions!$B$43:$H$43,MIN(H25,7))),0)) -> 600 | I26: =IF(I$2>Assumptions!$B$82,H26*(1-Assumptions!$B$83),IF(I25>=1,Assumptions!$B$74*CHOOSE(Assumptions!$B$81,INDEX(Assumptions!$B$42:$H$42,MIN(I25,7)),INDEX(Assumptions!$B$43:$H$43,MIN(I25,7))),0)) -> 720 | J26: =IF(J$2>Assumptions!$B$82,I26*(1-Assumptions!$B$83),IF(J25>=1,Assumptions!$B$74*CHOOSE(Assumptions!$B$81,INDEX(Assumptions!$B$42:$H$42,MIN(J25,7)),INDEX(Assumptions!$B$43:$H$43,MIN(J25,7))),0)) -> 800 | K26: =IF(K$2>Assumptions!$B$82,J26*(1-Assumptions!$B$83),IF(K25>=1,Assumptions!$B$74*CHOOSE(Assumptions!$B$81,INDEX(Assumptions!$B$42:$H$42,MIN(K25,7)),INDEX(Assumptions!$B$43:$H$43,MIN(K25,7))),0)) -> 800 | ... Z26: =IF(Z$2>Assumptions!$B$82,Y26*(1-Assumptions!$B$83),IF(Z25>=1,Assumptions!$B$74*CHOOSE(Assumptions!$B$81,INDEX(Assumptions!$B$42:$H$42,MIN(Z25,7)),INDEX(Assumptions!$B$43:$H$43,MIN(Z25,7))),0)) -> 0.08388608
A27: Product net sales, risk-adjusted | C27: =Assumptions!$B$32*C24+(1-Assumptions!$B$32)*Assumptions!$B$33*C26 -> 105.6 | D27: =Assumptions!$B$32*D24+(1-Assumptions!$B$32)*Assumptions!$B$33*D26 -> 246.4 | E27: =Assumptions!$B$32*E24+(1-Assumptions!$B$32)*Assumptions!$B$33*E26 -> 398.72 | F27: =Assumptions!$B$32*F24+(1-Assumptions!$B$32)*Assumptions!$B$33*F26 -> 554.88 | G27: =Assumptions!$B$32*G24+(1-Assumptions!$B$32)*Assumptions!$B$33*G26 -> 675.84 | H27: =Assumptions!$B$32*H24+(1-Assumptions!$B$32)*Assumptions!$B$33*H26 -> 761.6 | I27: =Assumptions!$B$32*I24+(1-Assumptions!$B$32)*Assumptions!$B$33*I26 -> 773.12 | J27: =Assumptions!$B$32*J24+(1-Assumptions!$B$32)*Assumptions!$B$33*J26 -> 780.8 | ... Z27: =Assumptions!$B$32*Z24+(1-Assumptions!$B$32)*Assumptions!$B$33*Z26 -> 0.081872814
A28: Company revenue, risk-adjusted (incl. milestones) | C28: =C27*Assumptions!$B$76+Assumptions!$B$32*IFERROR(INDEX(Assumptions!$B$88:$K$88,MATCH(C$2-Assumptions!$B$73,Assumptions!$B$87:$K$87,0)),0)+(1-Assumptions!$B$32)*Assumptions!$B$33*IFERROR(INDEX(Assumptions!$B$88:$K$88,MATCH(C$2-Assumptions!$B$73-Assumptions!$B$34,Assumptions!$B$87:$K$87,0)),0) -> 237.6 | D28: =D27*Assumptions!$B$76+Assumptions!$B$32*IFERROR(INDEX(Assumptions!$B$88:$K$88,MATCH(D$2-Assumptions!$B$73,Assumptions!$B$87:$K$87,0)),0)+(1-Assumptions!$B$32)*Assumptions!$B$33*IFERROR(INDEX(Assumptions!$B$88:$K$88,MATCH(D$2-Assumptions!$B$73-Assumptions!$B$34,Assumptions!$B$87:$K$87,0)),0) -> 246.4 | E28: =E27*Assumptions!$B$76+Assumptions!$B$32*IFERROR(INDEX(Assumptions!$B$88:$K$88,MATCH(E$2-Assumptions!$B$73,Assumptions!$B$87:$K$87,0)),0)+(1-Assumptions!$B$32)*Assumptions!$B$33*IFERROR(INDEX(Assumptions!$B$88:$K$88,MATCH(E$2-Assumptions!$B$73-Assumptions!$B$34,Assumptions!$B$87:$K$87,0)),0) -> 413.12 | F28: =F27*Assumptions!$B$76+Assumptions!$B$32*IFERROR(INDEX(Assumptions!$B$88:$K$88,MATCH(F$2-Assumptions!$B$73,Assumptions!$B$87:$K$87,0)),0)+(1-Assumptions!$B$32)*Assumptions!$B$33*IFERROR(INDEX(Assumptions!$B$88:$K$88,MATCH(F$2-Assumptions!$B$73-Assumptions!$B$34,Assumptions!$B$87:$K$87,0)),0) -> 554.88 | G28: =G27*Assumptions!$B$76+Assumptions!$B$32*IFERROR(INDEX(Assumptions!$B$88:$K$88,MATCH(G$2-Assumptions!$B$73,Assumptions!$B$87:$K$87,0)),0)+(1-Assumptions!$B$32)*Assumptions!$B$33*IFERROR(INDEX(Assumptions!$B$88:$K$88,MATCH(G$2-Assumptions!$B$73-Assumptions!$B$34,Assumptions!$B$87:$K$87,0)),0) -> 675.84 | H28: =H27*Assumptions!$B$76+Assumptions!$B$32*IFERROR(INDEX(Assumptions!$B$88:$K$88,MATCH(H$2-Assumptions!$B$73,Assumptions!$B$87:$K$87,0)),0)+(1-Assumptions!$B$32)*Assumptions!$B$33*IFERROR(INDEX(Assumptions!$B$88:$K$88,MATCH(H$2-Assumptions!$B$73-Assumptions!$B$34,Assumptions!$B$87:$K$87,0)),0) -> 761.6 | I28: =I27*Assumptions!$B$76+Assumptions!$B$32*IFERROR(INDEX(Assumptions!$B$88:$K$88,MATCH(I$2-Assumptions!$B$73,Assumptions!$B$87:$K$87,0)),0)+(1-Assumptions!$B$32)*Assumptions!$B$33*IFERROR(INDEX(Assumptions!$B$88:$K$88,MATCH(I$2-Assumptions!$B$73-Assumptions!$B$34,Assumptions!$B$87:$K$87,0)),0) -> 773.12 | J28: =J27*Assumptions!$B$76+Assumptions!$B$32*IFERROR(INDEX(Assumptions!$B$88:$K$88,MATCH(J$2-Assumptions!$B$73,Assumptions!$B$87:$K$87,0)),0)+(1-Assumptions!$B$32)*Assumptions!$B$33*IFERROR(INDEX(Assumptions!$B$88:$K$88,MATCH(J$2-Assumptions!$B$73-Assumptions!$B$34,Assumptions!$B$87:$K$87,0)),0) -> 780.8 | ... Z28: =Z27*Assumptions!$B$76+Assumptions!$B$32*IFERROR(INDEX(Assumptions!$B$88:$K$88,MATCH(Z$2-Assumptions!$B$73,Assumptions!$B$87:$K$87,0)),0)+(1-Assumptions!$B$32)*Assumptions!$B$33*IFERROR(INDEX(Assumptions!$B$88:$K$88,MATCH(Z$2-Assumptions!$B$73-Assumptions!$B$34,Assumptions!$B$87:$K$87,0)),0) -> 0.081872814
A29: COGS + royalties, risk-adjusted | C29: =C27*(Assumptions!$B$77+Assumptions!$B$78) -> 8.448 | D29: =D27*(Assumptions!$B$77+Assumptions!$B$78) -> 19.712 | E29: =E27*(Assumptions!$B$77+Assumptions!$B$78) -> 31.8976 | F29: =F27*(Assumptions!$B$77+Assumptions!$B$78) -> 44.3904 | G29: =G27*(Assumptions!$B$77+Assumptions!$B$78) -> 54.0672 | H29: =H27*(Assumptions!$B$77+Assumptions!$B$78) -> 60.928 | I29: =I27*(Assumptions!$B$77+Assumptions!$B$78) -> 61.8496 | J29: =J27*(Assumptions!$B$77+Assumptions!$B$78) -> 62.464 | ... Z29: =Z27*(Assumptions!$B$77+Assumptions!$B$78) -> 0.0065498251
A30: Commercial SG&A, risk-adjusted | C30: =Assumptions!$B$32*IF(Assumptions!$B$79=0,0,IF(C23=0,Assumptions!$B$80,IF(C23>=1,C24*IF(OR(Assumptions!$B$76<1,C23>5),Assumptions!$B$79,MAX(Assumptions!$B$79,INDEX(Assumptions!$B$44:$F$44,C23))),0)))+(1-Assumptions!$B$32)*Assumptions!$B$33*IF(Assumptions!$B$79=0,0,IF(C25=0,Assumptions!$B$80,IF(C25>=1,C26*IF(OR(Assumptions!$B$76<1,C25>5),Assumptions!$B$79,MAX(Assumptions!$B$79,INDEX(Assumptions!$B$44:$F$44,C25))),0))) -> 95.04 | D30: =Assumptions!$B$32*IF(Assumptions!$B$79=0,0,IF(D23=0,Assumptions!$B$80,IF(D23>=1,D24*IF(OR(Assumptions!$B$76<1,D23>5),Assumptions!$B$79,MAX(Assumptions!$B$79,INDEX(Assumptions!$B$44:$F$44,D23))),0)))+(1-Assumptions!$B$32)*Assumptions!$B$33*IF(Assumptions!$B$79=0,0,IF(D25=0,Assumptions!$B$80,IF(D25>=1,D26*IF(OR(Assumptions!$B$76<1,D25>5),Assumptions!$B$79,MAX(Assumptions!$B$79,INDEX(Assumptions!$B$44:$F$44,D25))),0))) -> 138.4 | E30: =Assumptions!$B$32*IF(Assumptions!$B$79=0,0,IF(E23=0,Assumptions!$B$80,IF(E23>=1,E24*IF(OR(Assumptions!$B$76<1,E23>5),Assumptions!$B$79,MAX(Assumptions!$B$79,INDEX(Assumptions!$B$44:$F$44,E23))),0)))+(1-Assumptions!$B$32)*Assumptions!$B$33*IF(Assumptions!$B$79=0,0,IF(E25=0,Assumptions!$B$80,IF(E25>=1,E26*IF(OR(Assumptions!$B$76<1,E25>5),Assumptions!$B$79,MAX(Assumptions!$B$79,INDEX(Assumptions!$B$44:$F$44,E25))),0))) -> 165.248 | F30: =Assumptions!$B$32*IF(Assumptions!$B$79=0,0,IF(F23=0,Assumptions!$B$80,IF(F23>=1,F24*IF(OR(Assumptions!$B$76<1,F23>5),Assumptions!$B$79,MAX(Assumptions!$B$79,INDEX(Assumptions!$B$44:$F$44,F23))),0)))+(1-Assumptions!$B$32)*Assumptions!$B$33*IF(Assumptions!$B$79=0,0,IF(F25=0,Assumptions!$B$80,IF(F25>=1,F26*IF(OR(Assumptions!$B$76<1,F25>5),Assumptions!$B$79,MAX(Assumptions!$B$79,INDEX(Assumptions!$B$44:$F$44,F25))),0))) -> 183.744 | G30: =Assumptions!$B$32*IF(Assumptions!$B$79=0,0,IF(G23=0,Assumptions!$B$80,IF(G23>=1,G24*IF(OR(Assumptions!$B$76<1,G23>5),Assumptions!$B$79,MAX(Assumptions!$B$79,INDEX(Assumptions!$B$44:$F$44,G23))),0)))+(1-Assumptions!$B$32)*Assumptions!$B$33*IF(Assumptions!$B$79=0,0,IF(G25=0,Assumptions!$B$80,IF(G25>=1,G26*IF(OR(Assumptions!$B$76<1,G25>5),Assumptions!$B$79,MAX(Assumptions!$B$79,INDEX(Assumptions!$B$44:$F$44,G25))),0))) -> 194.304 | H30: =Assumptions!$B$32*IF(Assumptions!$B$79=0,0,IF(H23=0,Assumptions!$B$80,IF(H23>=1,H24*IF(OR(Assumptions!$B$76<1,H23>5),Assumptions!$B$79,MAX(Assumptions!$B$79,INDEX(Assumptions!$B$44:$F$44,H23))),0)))+(1-Assumptions!$B$32)*Assumptions!$B$33*IF(Assumptions!$B$79=0,0,IF(H25=0,Assumptions!$B$80,IF(H25>=1,H26*IF(OR(Assumptions!$B$76<1,H25>5),Assumptions!$B$79,MAX(Assumptions!$B$79,INDEX(Assumptions!$B$44:$F$44,H25))),0))) -> 194.432 | I30: =Assumptions!$B$32*IF(Assumptions!$B$79=0,0,IF(I23=0,Assumptions!$B$80,IF(I23>=1,I24*IF(OR(Assumptions!$B$76<1,I23>5),Assumptions!$B$79,MAX(Assumptions!$B$79,INDEX(Assumptions!$B$44:$F$44,I23))),0)))+(1-Assumptions!$B$32)*Assumptions!$B$33*IF(Assumptions!$B$79=0,0,IF(I25=0,Assumptions!$B$80,IF(I25>=1,I26*IF(OR(Assumptions!$B$76<1,I25>5),Assumptions!$B$79,MAX(Assumptions!$B$79,INDEX(Assumptions!$B$44:$F$44,I25))),0))) -> 195.3536 | J30: =Assumptions!$B$32*IF(Assumptions!$B$79=0,0,IF(J23=0,Assumptions!$B$80,IF(J23>=1,J24*IF(OR(Assumptions!$B$76<1,J23>5),Assumptions!$B$79,MAX(Assumptions!$B$79,INDEX(Assumptions!$B$44:$F$44,J23))),0)))+(1-Assumptions!$B$32)*Assumptions!$B$33*IF(Assumptions!$B$79=0,0,IF(J25=0,Assumptions!$B$80,IF(J25>=1,J26*IF(OR(Assumptions!$B$76<1,J25>5),Assumptions!$B$79,MAX(Assumptions!$B$79,INDEX(Assumptions!$B$44:$F$44,J25))),0))) -> 195.2 | ... Z30: =Assumptions!$B$32*IF(Assumptions!$B$79=0,0,IF(Z23=0,Assumptions!$B$80,IF(Z23>=1,Z24*IF(OR(Assumptions!$B$76<1,Z23>5),Assumptions!$B$79,MAX(Assumptions!$B$79,INDEX(Assumptions!$B$44:$F$44,Z23))),0)))+(1-Assumptions!$B$32)*Assumptions!$B$33*IF(Assumptions!$B$79=0,0,IF(Z25=0,Assumptions!$B$80,IF(Z25>=1,Z26*IF(OR(Assumptions!$B$76<1,Z25>5),Assumptions!$B$79,MAX(Assumptions!$B$79,INDEX(Assumptions!$B$44:$F$44,Z25))),0))) -> 0.020468204
A31: Development R&D, risk-adjusted | C31: =IFERROR(INDEX(Assumptions!$B$85:$I$85,MATCH(C$2,Assumptions!$B$84:$I$84,0))*INDEX(Assumptions!$B$86:$I$86,MATCH(C$2,Assumptions!$B$84:$I$84,0)),0) -> 20 | D31: =IFERROR(INDEX(Assumptions!$B$85:$I$85,MATCH(D$2,Assumptions!$B$84:$I$84,0))*INDEX(Assumptions!$B$86:$I$86,MATCH(D$2,Assumptions!$B$84:$I$84,0)),0) -> 15 | E31: =IFERROR(INDEX(Assumptions!$B$85:$I$85,MATCH(E$2,Assumptions!$B$84:$I$84,0))*INDEX(Assumptions!$B$86:$I$86,MATCH(E$2,Assumptions!$B$84:$I$84,0)),0) -> 0 | F31: =IFERROR(INDEX(Assumptions!$B$85:$I$85,MATCH(F$2,Assumptions!$B$84:$I$84,0))*INDEX(Assumptions!$B$86:$I$86,MATCH(F$2,Assumptions!$B$84:$I$84,0)),0) -> 0 | G31: =IFERROR(INDEX(Assumptions!$B$85:$I$85,MATCH(G$2,Assumptions!$B$84:$I$84,0))*INDEX(Assumptions!$B$86:$I$86,MATCH(G$2,Assumptions!$B$84:$I$84,0)),0) -> 0 | H31: =IFERROR(INDEX(Assumptions!$B$85:$I$85,MATCH(H$2,Assumptions!$B$84:$I$84,0))*INDEX(Assumptions!$B$86:$I$86,MATCH(H$2,Assumptions!$B$84:$I$84,0)),0) -> 0 | I31: =IFERROR(INDEX(Assumptions!$B$85:$I$85,MATCH(I$2,Assumptions!$B$84:$I$84,0))*INDEX(Assumptions!$B$86:$I$86,MATCH(I$2,Assumptions!$B$84:$I$84,0)),0) -> 0 | J31: =IFERROR(INDEX(Assumptions!$B$85:$I$85,MATCH(J$2,Assumptions!$B$84:$I$84,0))*INDEX(Assumptions!$B$86:$I$86,MATCH(J$2,Assumptions!$B$84:$I$84,0)),0) -> 0 | ... Z31: =IFERROR(INDEX(Assumptions!$B$85:$I$85,MATCH(Z$2,Assumptions!$B$84:$I$84,0))*INDEX(Assumptions!$B$86:$I$86,MATCH(Z$2,Assumptions!$B$84:$I$84,0)),0) -> 0
A32: Program contribution (pre-tax) | C32: =C28-C29-C30-C31 -> 114.112 | D32: =D28-D29-D30-D31 -> 73.288 | E32: =E28-E29-E30-E31 -> 215.9744 | F32: =F28-F29-F30-F31 -> 326.7456 | G32: =G28-G29-G30-G31 -> 427.4688 | H32: =H28-H29-H30-H31 -> 506.24 | I32: =I28-I29-I30-I31 -> 515.9168 | J32: =J28-J29-J30-J31 -> 523.136 | ... Z32: =Z28-Z29-Z30-Z31 -> 0.054854785
A34: Encaleret — ADH1 (PDUFA May 8, 2027)
A35: Years since launch | C35: =C$2-Assumptions!$B$91+1 -> 1 | D35: =D$2-Assumptions!$B$91+1 -> 2 | E35: =E$2-Assumptions!$B$91+1 -> 3 | F35: =F$2-Assumptions!$B$91+1 -> 4 | G35: =G$2-Assumptions!$B$91+1 -> 5 | H35: =H$2-Assumptions!$B$91+1 -> 6 | I35: =I$2-Assumptions!$B$91+1 -> 7 | J35: =J$2-Assumptions!$B$91+1 -> 8 | ... Z35: =Z$2-Assumptions!$B$91+1 -> 24
A36: Net sales, unrisked | C36: =IF(C$2>Assumptions!$B$100,0*(1-Assumptions!$B$101),IF(C35>=1,Assumptions!$B$92*CHOOSE(Assumptions!$B$99,INDEX(Assumptions!$B$42:$H$42,MIN(C35,7)),INDEX(Assumptions!$B$43:$H$43,MIN(C35,7))),0)) -> 120 | D36: =IF(D$2>Assumptions!$B$100,C36*(1-Assumptions!$B$101),IF(D35>=1,Assumptions!$B$92*CHOOSE(Assumptions!$B$99,INDEX(Assumptions!$B$42:$H$42,MIN(D35,7)),INDEX(Assumptions!$B$43:$H$43,MIN(D35,7))),0)) -> 280 | E36: =IF(E$2>Assumptions!$B$100,D36*(1-Assumptions!$B$101),IF(E35>=1,Assumptions!$B$92*CHOOSE(Assumptions!$B$99,INDEX(Assumptions!$B$42:$H$42,MIN(E35,7)),INDEX(Assumptions!$B$43:$H$43,MIN(E35,7))),0)) -> 440 | F36: =IF(F$2>Assumptions!$B$100,E36*(1-Assumptions!$B$101),IF(F35>=1,Assumptions!$B$92*CHOOSE(Assumptions!$B$99,INDEX(Assumptions!$B$42:$H$42,MIN(F35,7)),INDEX(Assumptions!$B$43:$H$43,MIN(F35,7))),0)) -> 600 | G36: =IF(G$2>Assumptions!$B$100,F36*(1-Assumptions!$B$101),IF(G35>=1,Assumptions!$B$92*CHOOSE(Assumptions!$B$99,INDEX(Assumptions!$B$42:$H$42,MIN(G35,7)),INDEX(Assumptions!$B$43:$H$43,MIN(G35,7))),0)) -> 720 | H36: =IF(H$2>Assumptions!$B$100,G36*(1-Assumptions!$B$101),IF(H35>=1,Assumptions!$B$92*CHOOSE(Assumptions!$B$99,INDEX(Assumptions!$B$42:$H$42,MIN(H35,7)),INDEX(Assumptions!$B$43:$H$43,MIN(H35,7))),0)) -> 800 | I36: =IF(I$2>Assumptions!$B$100,H36*(1-Assumptions!$B$101),IF(I35>=1,Assumptions!$B$92*CHOOSE(Assumptions!$B$99,INDEX(Assumptions!$B$42:$H$42,MIN(I35,7)),INDEX(Assumptions!$B$43:$H$43,MIN(I35,7))),0)) -> 800 | J36: =IF(J$2>Assumptions!$B$100,I36*(1-Assumptions!$B$101),IF(J35>=1,Assumptions!$B$92*CHOOSE(Assumptions!$B$99,INDEX(Assumptions!$B$42:$H$42,MIN(J35,7)),INDEX(Assumptions!$B$43:$H$43,MIN(J35,7))),0)) -> 800 | K36: =IF(K$2>Assumptions!$B$100,J36*(1-Assumptions!$B$101),IF(K35>=1,Assumptions!$B$92*CHOOSE(Assumptions!$B$99,INDEX(Assumptions!$B$42:$H$42,MIN(K35,7)),INDEX(Assumptions!$B$43:$H$43,MIN(K35,7))),0)) -> 800 | ... Z36: =IF(Z$2>Assumptions!$B$100,Y36*(1-Assumptions!$B$101),IF(Z35>=1,Assumptions!$B$92*CHOOSE(Assumptions!$B$99,INDEX(Assumptions!$B$42:$H$42,MIN(Z35,7)),INDEX(Assumptions!$B$43:$H$43,MIN(Z35,7))),0)) -> 0.2097152
A37: Product net sales, risk-adjusted | C37: =C36*MIN(1,Assumptions!$B$93*Assumptions!$B$37) -> 104.4 | D37: =D36*MIN(1,Assumptions!$B$93*Assumptions!$B$37) -> 243.6 | E37: =E36*MIN(1,Assumptions!$B$93*Assumptions!$B$37) -> 382.8 | F37: =F36*MIN(1,Assumptions!$B$93*Assumptions!$B$37) -> 522 | G37: =G36*MIN(1,Assumptions!$B$93*Assumptions!$B$37) -> 626.4 | H37: =H36*MIN(1,Assumptions!$B$93*Assumptions!$B$37) -> 696 | I37: =I36*MIN(1,Assumptions!$B$93*Assumptions!$B$37) -> 696 | J37: =J36*MIN(1,Assumptions!$B$93*Assumptions!$B$37) -> 696 | ... Z37: =Z36*MIN(1,Assumptions!$B$93*Assumptions!$B$37) -> 0.18245222
A38: Company revenue, risk-adjusted (incl. milestones) | C38: =C37*Assumptions!$B$94 -> 104.4 | D38: =D37*Assumptions!$B$94 -> 243.6 | E38: =E37*Assumptions!$B$94 -> 382.8 | F38: =F37*Assumptions!$B$94 -> 522 | G38: =G37*Assumptions!$B$94 -> 626.4 | H38: =H37*Assumptions!$B$94 -> 696 | I38: =I37*Assumptions!$B$94 -> 696 | J38: =J37*Assumptions!$B$94 -> 696 | ... Z38: =Z37*Assumptions!$B$94 -> 0.18245222
A39: COGS + royalties, risk-adjusted | C39: =C37*(Assumptions!$B$95+Assumptions!$B$96) -> 8.352 | D39: =D37*(Assumptions!$B$95+Assumptions!$B$96) -> 19.488 | E39: =E37*(Assumptions!$B$95+Assumptions!$B$96) -> 30.624 | F39: =F37*(Assumptions!$B$95+Assumptions!$B$96) -> 41.76 | G39: =G37*(Assumptions!$B$95+Assumptions!$B$96) -> 50.112 | H39: =H37*(Assumptions!$B$95+Assumptions!$B$96) -> 55.68 | I39: =I37*(Assumptions!$B$95+Assumptions!$B$96) -> 55.68 | J39: =J37*(Assumptions!$B$95+Assumptions!$B$96) -> 55.68 | ... Z39: =Z37*(Assumptions!$B$95+Assumptions!$B$96) -> 0.014596178
A40: Commercial SG&A, risk-adjusted | C40: =MIN(1,Assumptions!$B$93*Assumptions!$B$37)*IF(Assumptions!$B$97=0,0,IF(C35=0,Assumptions!$B$98,IF(C35>=1,C36*IF(OR(Assumptions!$B$94<1,C35>5),Assumptions!$B$97,MAX(Assumptions!$B$97,INDEX(Assumptions!$B$44:$F$44,C35))),0))) -> 93.96 | D40: =MIN(1,Assumptions!$B$93*Assumptions!$B$37)*IF(Assumptions!$B$97=0,0,IF(D35=0,Assumptions!$B$98,IF(D35>=1,D36*IF(OR(Assumptions!$B$94<1,D35>5),Assumptions!$B$97,MAX(Assumptions!$B$97,INDEX(Assumptions!$B$44:$F$44,D35))),0))) -> 133.98 | E40: =MIN(1,Assumptions!$B$93*Assumptions!$B$37)*IF(Assumptions!$B$97=0,0,IF(E35=0,Assumptions!$B$98,IF(E35>=1,E36*IF(OR(Assumptions!$B$94<1,E35>5),Assumptions!$B$97,MAX(Assumptions!$B$97,INDEX(Assumptions!$B$44:$F$44,E35))),0))) -> 153.12 | F40: =MIN(1,Assumptions!$B$93*Assumptions!$B$37)*IF(Assumptions!$B$97=0,0,IF(F35=0,Assumptions!$B$98,IF(F35>=1,F36*IF(OR(Assumptions!$B$94<1,F35>5),Assumptions!$B$97,MAX(Assumptions!$B$97,INDEX(Assumptions!$B$44:$F$44,F35))),0))) -> 167.04 | G40: =MIN(1,Assumptions!$B$93*Assumptions!$B$37)*IF(Assumptions!$B$97=0,0,IF(G35=0,Assumptions!$B$98,IF(G35>=1,G36*IF(OR(Assumptions!$B$94<1,G35>5),Assumptions!$B$97,MAX(Assumptions!$B$97,INDEX(Assumptions!$B$44:$F$44,G35))),0))) -> 175.392 | H40: =MIN(1,Assumptions!$B$93*Assumptions!$B$37)*IF(Assumptions!$B$97=0,0,IF(H35=0,Assumptions!$B$98,IF(H35>=1,H36*IF(OR(Assumptions!$B$94<1,H35>5),Assumptions!$B$97,MAX(Assumptions!$B$97,INDEX(Assumptions!$B$44:$F$44,H35))),0))) -> 174 | I40: =MIN(1,Assumptions!$B$93*Assumptions!$B$37)*IF(Assumptions!$B$97=0,0,IF(I35=0,Assumptions!$B$98,IF(I35>=1,I36*IF(OR(Assumptions!$B$94<1,I35>5),Assumptions!$B$97,MAX(Assumptions!$B$97,INDEX(Assumptions!$B$44:$F$44,I35))),0))) -> 174 | J40: =MIN(1,Assumptions!$B$93*Assumptions!$B$37)*IF(Assumptions!$B$97=0,0,IF(J35=0,Assumptions!$B$98,IF(J35>=1,J36*IF(OR(Assumptions!$B$94<1,J35>5),Assumptions!$B$97,MAX(Assumptions!$B$97,INDEX(Assumptions!$B$44:$F$44,J35))),0))) -> 174 | ... Z40: =MIN(1,Assumptions!$B$93*Assumptions!$B$37)*IF(Assumptions!$B$97=0,0,IF(Z35=0,Assumptions!$B$98,IF(Z35>=1,Z36*IF(OR(Assumptions!$B$94<1,Z35>5),Assumptions!$B$97,MAX(Assumptions!$B$97,INDEX(Assumptions!$B$44:$F$44,Z35))),0))) -> 0.045613056
A41: Development R&D, risk-adjusted | C41: =IFERROR(INDEX(Assumptions!$B$103:$I$103,MATCH(C$2,Assumptions!$B$102:$I$102,0))*INDEX(Assumptions!$B$104:$I$104,MATCH(C$2,Assumptions!$B$102:$I$102,0)),0) -> 10 | D41: =IFERROR(INDEX(Assumptions!$B$103:$I$103,MATCH(D$2,Assumptions!$B$102:$I$102,0))*INDEX(Assumptions!$B$104:$I$104,MATCH(D$2,Assumptions!$B$102:$I$102,0)),0) -> 0 | E41: =IFERROR(INDEX(Assumptions!$B$103:$I$103,MATCH(E$2,Assumptions!$B$102:$I$102,0))*INDEX(Assumptions!$B$104:$I$104,MATCH(E$2,Assumptions!$B$102:$I$102,0)),0) -> 0 | F41: =IFERROR(INDEX(Assumptions!$B$103:$I$103,MATCH(F$2,Assumptions!$B$102:$I$102,0))*INDEX(Assumptions!$B$104:$I$104,MATCH(F$2,Assumptions!$B$102:$I$102,0)),0) -> 0 | G41: =IFERROR(INDEX(Assumptions!$B$103:$I$103,MATCH(G$2,Assumptions!$B$102:$I$102,0))*INDEX(Assumptions!$B$104:$I$104,MATCH(G$2,Assumptions!$B$102:$I$102,0)),0) -> 0 | H41: =IFERROR(INDEX(Assumptions!$B$103:$I$103,MATCH(H$2,Assumptions!$B$102:$I$102,0))*INDEX(Assumptions!$B$104:$I$104,MATCH(H$2,Assumptions!$B$102:$I$102,0)),0) -> 0 | I41: =IFERROR(INDEX(Assumptions!$B$103:$I$103,MATCH(I$2,Assumptions!$B$102:$I$102,0))*INDEX(Assumptions!$B$104:$I$104,MATCH(I$2,Assumptions!$B$102:$I$102,0)),0) -> 0 | J41: =IFERROR(INDEX(Assumptions!$B$103:$I$103,MATCH(J$2,Assumptions!$B$102:$I$102,0))*INDEX(Assumptions!$B$104:$I$104,MATCH(J$2,Assumptions!$B$102:$I$102,0)),0) -> 0 | ... Z41: =IFERROR(INDEX(Assumptions!$B$103:$I$103,MATCH(Z$2,Assumptions!$B$102:$I$102,0))*INDEX(Assumptions!$B$104:$I$104,MATCH(Z$2,Assumptions!$B$102:$I$102,0)),0) -> 0
A42: Program contribution (pre-tax) | C42: =C38-C39-C40-C41 -> -7.912 | D42: =D38-D39-D40-D41 -> 90.132 | E42: =E38-E39-E40-E41 -> 199.056 | F42: =F38-F39-F40-F41 -> 313.2 | G42: =G38-G39-G40-G41 -> 400.896 | H42: =H38-H39-H40-H41 -> 466.32 | I42: =I38-I39-I40-I41 -> 466.32 | J42: =J38-J39-J40-J41 -> 466.32 | ... Z42: =Z38-Z39-Z40-Z41 -> 0.12224299
A44: Infigratinib — achondroplasia (PDUFA Feb 4, 2027)
A45: Years since launch | C45: =C$2-Assumptions!$B$107+1 -> 1 | D45: =D$2-Assumptions!$B$107+1 -> 2 | E45: =E$2-Assumptions!$B$107+1 -> 3 | F45: =F$2-Assumptions!$B$107+1 -> 4 | G45: =G$2-Assumptions!$B$107+1 -> 5 | H45: =H$2-Assumptions!$B$107+1 -> 6 | I45: =I$2-Assumptions!$B$107+1 -> 7 | J45: =J$2-Assumptions!$B$107+1 -> 8 | ... Z45: =Z$2-Assumptions!$B$107+1 -> 24
A46: Net sales, unrisked | C46: =IF(C$2>Assumptions!$B$116,0*(1-Assumptions!$B$117),IF(C45>=1,Assumptions!$B$108*CHOOSE(Assumptions!$B$115,INDEX(Assumptions!$B$42:$H$42,MIN(C45,7)),INDEX(Assumptions!$B$43:$H$43,MIN(C45,7))),0)) -> 130 | D46: =IF(D$2>Assumptions!$B$116,C46*(1-Assumptions!$B$117),IF(D45>=1,Assumptions!$B$108*CHOOSE(Assumptions!$B$115,INDEX(Assumptions!$B$42:$H$42,MIN(D45,7)),INDEX(Assumptions!$B$43:$H$43,MIN(D45,7))),0)) -> 325 | E46: =IF(E$2>Assumptions!$B$116,D46*(1-Assumptions!$B$117),IF(E45>=1,Assumptions!$B$108*CHOOSE(Assumptions!$B$115,INDEX(Assumptions!$B$42:$H$42,MIN(E45,7)),INDEX(Assumptions!$B$43:$H$43,MIN(E45,7))),0)) -> 585 | F46: =IF(F$2>Assumptions!$B$116,E46*(1-Assumptions!$B$117),IF(F45>=1,Assumptions!$B$108*CHOOSE(Assumptions!$B$115,INDEX(Assumptions!$B$42:$H$42,MIN(F45,7)),INDEX(Assumptions!$B$43:$H$43,MIN(F45,7))),0)) -> 845 | G46: =IF(G$2>Assumptions!$B$116,F46*(1-Assumptions!$B$117),IF(G45>=1,Assumptions!$B$108*CHOOSE(Assumptions!$B$115,INDEX(Assumptions!$B$42:$H$42,MIN(G45,7)),INDEX(Assumptions!$B$43:$H$43,MIN(G45,7))),0)) -> 1066 | H46: =IF(H$2>Assumptions!$B$116,G46*(1-Assumptions!$B$117),IF(H45>=1,Assumptions!$B$108*CHOOSE(Assumptions!$B$115,INDEX(Assumptions!$B$42:$H$42,MIN(H45,7)),INDEX(Assumptions!$B$43:$H$43,MIN(H45,7))),0)) -> 1209 | I46: =IF(I$2>Assumptions!$B$116,H46*(1-Assumptions!$B$117),IF(I45>=1,Assumptions!$B$108*CHOOSE(Assumptions!$B$115,INDEX(Assumptions!$B$42:$H$42,MIN(I45,7)),INDEX(Assumptions!$B$43:$H$43,MIN(I45,7))),0)) -> 1300 | J46: =IF(J$2>Assumptions!$B$116,I46*(1-Assumptions!$B$117),IF(J45>=1,Assumptions!$B$108*CHOOSE(Assumptions!$B$115,INDEX(Assumptions!$B$42:$H$42,MIN(J45,7)),INDEX(Assumptions!$B$43:$H$43,MIN(J45,7))),0)) -> 1300 | K46: =IF(K$2>Assumptions!$B$116,J46*(1-Assumptions!$B$117),IF(K45>=1,Assumptions!$B$108*CHOOSE(Assumptions!$B$115,INDEX(Assumptions!$B$42:$H$42,MIN(K45,7)),INDEX(Assumptions!$B$43:$H$43,MIN(K45,7))),0)) -> 1300 | ... Z46: =IF(Z$2>Assumptions!$B$116,Y46*(1-Assumptions!$B$117),IF(Z45>=1,Assumptions!$B$108*CHOOSE(Assumptions!$B$115,INDEX(Assumptions!$B$42:$H$42,MIN(Z45,7)),INDEX(Assumptions!$B$43:$H$43,MIN(Z45,7))),0)) -> 0.3407872
A47: Product net sales, risk-adjusted | C47: =C46*MIN(1,Assumptions!$B$109*Assumptions!$B$37) -> 113.1 | D47: =D46*MIN(1,Assumptions!$B$109*Assumptions!$B$37) -> 282.75 | E47: =E46*MIN(1,Assumptions!$B$109*Assumptions!$B$37) -> 508.95 | F47: =F46*MIN(1,Assumptions!$B$109*Assumptions!$B$37) -> 735.15 | G47: =G46*MIN(1,Assumptions!$B$109*Assumptions!$B$37) -> 927.42 | H47: =H46*MIN(1,Assumptions!$B$109*Assumptions!$B$37) -> 1051.83 | I47: =I46*MIN(1,Assumptions!$B$109*Assumptions!$B$37) -> 1131 | J47: =J46*MIN(1,Assumptions!$B$109*Assumptions!$B$37) -> 1131 | ... Z47: =Z46*MIN(1,Assumptions!$B$109*Assumptions!$B$37) -> 0.29648486
A48: Company revenue, risk-adjusted (incl. milestones) | C48: =C47*Assumptions!$B$110 -> 113.1 | D48: =D47*Assumptions!$B$110 -> 282.75 | E48: =E47*Assumptions!$B$110 -> 508.95 | F48: =F47*Assumptions!$B$110 -> 735.15 | G48: =G47*Assumptions!$B$110 -> 927.42 | H48: =H47*Assumptions!$B$110 -> 1051.83 | I48: =I47*Assumptions!$B$110 -> 1131 | J48: =J47*Assumptions!$B$110 -> 1131 | ... Z48: =Z47*Assumptions!$B$110 -> 0.29648486
A49: COGS + royalties, risk-adjusted | C49: =C47*(Assumptions!$B$111+Assumptions!$B$112) -> 12.441 | D49: =D47*(Assumptions!$B$111+Assumptions!$B$112) -> 31.1025 | E49: =E47*(Assumptions!$B$111+Assumptions!$B$112) -> 55.9845 | F49: =F47*(Assumptions!$B$111+Assumptions!$B$112) -> 80.8665 | G49: =G47*(Assumptions!$B$111+Assumptions!$B$112) -> 102.0162 | H49: =H47*(Assumptions!$B$111+Assumptions!$B$112) -> 115.7013 | I49: =I47*(Assumptions!$B$111+Assumptions!$B$112) -> 124.41 | J49: =J47*(Assumptions!$B$111+Assumptions!$B$112) -> 124.41 | ... Z49: =Z47*(Assumptions!$B$111+Assumptions!$B$112) -> 0.032613335
A50: Commercial SG&A, risk-adjusted | C50: =MIN(1,Assumptions!$B$109*Assumptions!$B$37)*IF(Assumptions!$B$113=0,0,IF(C45=0,Assumptions!$B$114,IF(C45>=1,C46*IF(OR(Assumptions!$B$110<1,C45>5),Assumptions!$B$113,MAX(Assumptions!$B$113,INDEX(Assumptions!$B$44:$F$44,C45))),0))) -> 101.79 | D50: =MIN(1,Assumptions!$B$109*Assumptions!$B$37)*IF(Assumptions!$B$113=0,0,IF(D45=0,Assumptions!$B$114,IF(D45>=1,D46*IF(OR(Assumptions!$B$110<1,D45>5),Assumptions!$B$113,MAX(Assumptions!$B$113,INDEX(Assumptions!$B$44:$F$44,D45))),0))) -> 155.5125 | E50: =MIN(1,Assumptions!$B$109*Assumptions!$B$37)*IF(Assumptions!$B$113=0,0,IF(E45=0,Assumptions!$B$114,IF(E45>=1,E46*IF(OR(Assumptions!$B$110<1,E45>5),Assumptions!$B$113,MAX(Assumptions!$B$113,INDEX(Assumptions!$B$44:$F$44,E45))),0))) -> 203.58 | F50: =MIN(1,Assumptions!$B$109*Assumptions!$B$37)*IF(Assumptions!$B$113=0,0,IF(F45=0,Assumptions!$B$114,IF(F45>=1,F46*IF(OR(Assumptions!$B$110<1,F45>5),Assumptions!$B$113,MAX(Assumptions!$B$113,INDEX(Assumptions!$B$44:$F$44,F45))),0))) -> 235.248 | G50: =MIN(1,Assumptions!$B$109*Assumptions!$B$37)*IF(Assumptions!$B$113=0,0,IF(G45=0,Assumptions!$B$114,IF(G45>=1,G46*IF(OR(Assumptions!$B$110<1,G45>5),Assumptions!$B$113,MAX(Assumptions!$B$113,INDEX(Assumptions!$B$44:$F$44,G45))),0))) -> 259.6776 | H50: =MIN(1,Assumptions!$B$109*Assumptions!$B$37)*IF(Assumptions!$B$113=0,0,IF(H45=0,Assumptions!$B$114,IF(H45>=1,H46*IF(OR(Assumptions!$B$110<1,H45>5),Assumptions!$B$113,MAX(Assumptions!$B$113,INDEX(Assumptions!$B$44:$F$44,H45))),0))) -> 262.9575 | I50: =MIN(1,Assumptions!$B$109*Assumptions!$B$37)*IF(Assumptions!$B$113=0,0,IF(I45=0,Assumptions!$B$114,IF(I45>=1,I46*IF(OR(Assumptions!$B$110<1,I45>5),Assumptions!$B$113,MAX(Assumptions!$B$113,INDEX(Assumptions!$B$44:$F$44,I45))),0))) -> 282.75 | J50: =MIN(1,Assumptions!$B$109*Assumptions!$B$37)*IF(Assumptions!$B$113=0,0,IF(J45=0,Assumptions!$B$114,IF(J45>=1,J46*IF(OR(Assumptions!$B$110<1,J45>5),Assumptions!$B$113,MAX(Assumptions!$B$113,INDEX(Assumptions!$B$44:$F$44,J45))),0))) -> 282.75 | ... Z50: =MIN(1,Assumptions!$B$109*Assumptions!$B$37)*IF(Assumptions!$B$113=0,0,IF(Z45=0,Assumptions!$B$114,IF(Z45>=1,Z46*IF(OR(Assumptions!$B$110<1,Z45>5),Assumptions!$B$113,MAX(Assumptions!$B$113,INDEX(Assumptions!$B$44:$F$44,Z45))),0))) -> 0.074121216
A51: Development R&D, risk-adjusted | C51: =IFERROR(INDEX(Assumptions!$B$119:$I$119,MATCH(C$2,Assumptions!$B$118:$I$118,0))*INDEX(Assumptions!$B$120:$I$120,MATCH(C$2,Assumptions!$B$118:$I$118,0)),0) -> 15 | D51: =IFERROR(INDEX(Assumptions!$B$119:$I$119,MATCH(D$2,Assumptions!$B$118:$I$118,0))*INDEX(Assumptions!$B$120:$I$120,MATCH(D$2,Assumptions!$B$118:$I$118,0)),0) -> 0 | E51: =IFERROR(INDEX(Assumptions!$B$119:$I$119,MATCH(E$2,Assumptions!$B$118:$I$118,0))*INDEX(Assumptions!$B$120:$I$120,MATCH(E$2,Assumptions!$B$118:$I$118,0)),0) -> 0 | F51: =IFERROR(INDEX(Assumptions!$B$119:$I$119,MATCH(F$2,Assumptions!$B$118:$I$118,0))*INDEX(Assumptions!$B$120:$I$120,MATCH(F$2,Assumptions!$B$118:$I$118,0)),0) -> 0 | G51: =IFERROR(INDEX(Assumptions!$B$119:$I$119,MATCH(G$2,Assumptions!$B$118:$I$118,0))*INDEX(Assumptions!$B$120:$I$120,MATCH(G$2,Assumptions!$B$118:$I$118,0)),0) -> 0 | H51: =IFERROR(INDEX(Assumptions!$B$119:$I$119,MATCH(H$2,Assumptions!$B$118:$I$118,0))*INDEX(Assumptions!$B$120:$I$120,MATCH(H$2,Assumptions!$B$118:$I$118,0)),0) -> 0 | I51: =IFERROR(INDEX(Assumptions!$B$119:$I$119,MATCH(I$2,Assumptions!$B$118:$I$118,0))*INDEX(Assumptions!$B$120:$I$120,MATCH(I$2,Assumptions!$B$118:$I$118,0)),0) -> 0 | J51: =IFERROR(INDEX(Assumptions!$B$119:$I$119,MATCH(J$2,Assumptions!$B$118:$I$118,0))*INDEX(Assumptions!$B$120:$I$120,MATCH(J$2,Assumptions!$B$118:$I$118,0)),0) -> 0 | ... Z51: =IFERROR(INDEX(Assumptions!$B$119:$I$119,MATCH(Z$2,Assumptions!$B$118:$I$118,0))*INDEX(Assumptions!$B$120:$I$120,MATCH(Z$2,Assumptions!$B$118:$I$118,0)),0) -> 0
A52: Program contribution (pre-tax) | C52: =C48-C49-C50-C51 -> -16.131 | D52: =D48-D49-D50-D51 -> 96.135 | E52: =E48-E49-E50-E51 -> 249.3855 | F52: =F48-F49-F50-F51 -> 419.0355 | G52: =G48-G49-G50-G51 -> 565.7262 | H52: =H48-H49-H50-H51 -> 673.1712 | I52: =I48-I49-I50-I51 -> 723.84 | J52: =J48-J49-J50-J51 -> 723.84 | ... Z52: =Z48-Z49-Z50-Z51 -> 0.18975031
A54: Encaleret — chronic hypoparathyroidism (Phase 3)
A55: Years since launch | C55: =C$2-Assumptions!$B$123+1 -> -1 | D55: =D$2-Assumptions!$B$123+1 -> 0 | E55: =E$2-Assumptions!$B$123+1 -> 1 | F55: =F$2-Assumptions!$B$123+1 -> 2 | G55: =G$2-Assumptions!$B$123+1 -> 3 | H55: =H$2-Assumptions!$B$123+1 -> 4 | I55: =I$2-Assumptions!$B$123+1 -> 5 | J55: =J$2-Assumptions!$B$123+1 -> 6 | ... Z55: =Z$2-Assumptions!$B$123+1 -> 22
A56: Net sales, unrisked | C56: =IF(C$2>Assumptions!$B$132,0*(1-Assumptions!$B$133),IF(C55>=1,Assumptions!$B$124*CHOOSE(Assumptions!$B$131,INDEX(Assumptions!$B$42:$H$42,MIN(C55,7)),INDEX(Assumptions!$B$43:$H$43,MIN(C55,7))),0)) -> 0 | D56: =IF(D$2>Assumptions!$B$132,C56*(1-Assumptions!$B$133),IF(D55>=1,Assumptions!$B$124*CHOOSE(Assumptions!$B$131,INDEX(Assumptions!$B$42:$H$42,MIN(D55,7)),INDEX(Assumptions!$B$43:$H$43,MIN(D55,7))),0)) -> 0 | E56: =IF(E$2>Assumptions!$B$132,D56*(1-Assumptions!$B$133),IF(E55>=1,Assumptions!$B$124*CHOOSE(Assumptions!$B$131,INDEX(Assumptions!$B$42:$H$42,MIN(E55,7)),INDEX(Assumptions!$B$43:$H$43,MIN(E55,7))),0)) -> 150 | F56: =IF(F$2>Assumptions!$B$132,E56*(1-Assumptions!$B$133),IF(F55>=1,Assumptions!$B$124*CHOOSE(Assumptions!$B$131,INDEX(Assumptions!$B$42:$H$42,MIN(F55,7)),INDEX(Assumptions!$B$43:$H$43,MIN(F55,7))),0)) -> 375 | G56: =IF(G$2>Assumptions!$B$132,F56*(1-Assumptions!$B$133),IF(G55>=1,Assumptions!$B$124*CHOOSE(Assumptions!$B$131,INDEX(Assumptions!$B$42:$H$42,MIN(G55,7)),INDEX(Assumptions!$B$43:$H$43,MIN(G55,7))),0)) -> 675 | H56: =IF(H$2>Assumptions!$B$132,G56*(1-Assumptions!$B$133),IF(H55>=1,Assumptions!$B$124*CHOOSE(Assumptions!$B$131,INDEX(Assumptions!$B$42:$H$42,MIN(H55,7)),INDEX(Assumptions!$B$43:$H$43,MIN(H55,7))),0)) -> 975 | I56: =IF(I$2>Assumptions!$B$132,H56*(1-Assumptions!$B$133),IF(I55>=1,Assumptions!$B$124*CHOOSE(Assumptions!$B$131,INDEX(Assumptions!$B$42:$H$42,MIN(I55,7)),INDEX(Assumptions!$B$43:$H$43,MIN(I55,7))),0)) -> 1230 | J56: =IF(J$2>Assumptions!$B$132,I56*(1-Assumptions!$B$133),IF(J55>=1,Assumptions!$B$124*CHOOSE(Assumptions!$B$131,INDEX(Assumptions!$B$42:$H$42,MIN(J55,7)),INDEX(Assumptions!$B$43:$H$43,MIN(J55,7))),0)) -> 1395 | K56: =IF(K$2>Assumptions!$B$132,J56*(1-Assumptions!$B$133),IF(K55>=1,Assumptions!$B$124*CHOOSE(Assumptions!$B$131,INDEX(Assumptions!$B$42:$H$42,MIN(K55,7)),INDEX(Assumptions!$B$43:$H$43,MIN(K55,7))),0)) -> 1500 | ... Z56: =IF(Z$2>Assumptions!$B$132,Y56*(1-Assumptions!$B$133),IF(Z55>=1,Assumptions!$B$124*CHOOSE(Assumptions!$B$131,INDEX(Assumptions!$B$42:$H$42,MIN(Z55,7)),INDEX(Assumptions!$B$43:$H$43,MIN(Z55,7))),0)) -> 0.393216
A57: Product net sales, risk-adjusted | C57: =C56*MIN(1,Assumptions!$B$125*Assumptions!$B$37) -> 0 | D57: =D56*MIN(1,Assumptions!$B$125*Assumptions!$B$37) -> 0 | E57: =E56*MIN(1,Assumptions!$B$125*Assumptions!$B$37) -> 67.5 | F57: =F56*MIN(1,Assumptions!$B$125*Assumptions!$B$37) -> 168.75 | G57: =G56*MIN(1,Assumptions!$B$125*Assumptions!$B$37) -> 303.75 | H57: =H56*MIN(1,Assumptions!$B$125*Assumptions!$B$37) -> 438.75 | I57: =I56*MIN(1,Assumptions!$B$125*Assumptions!$B$37) -> 553.5 | J57: =J56*MIN(1,Assumptions!$B$125*Assumptions!$B$37) -> 627.75 | ... Z57: =Z56*MIN(1,Assumptions!$B$125*Assumptions!$B$37) -> 0.1769472
A58: Company revenue, risk-adjusted (incl. milestones) | C58: =C57*Assumptions!$B$126 -> 0 | D58: =D57*Assumptions!$B$126 -> 0 | E58: =E57*Assumptions!$B$126 -> 67.5 | F58: =F57*Assumptions!$B$126 -> 168.75 | G58: =G57*Assumptions!$B$126 -> 303.75 | H58: =H57*Assumptions!$B$126 -> 438.75 | I58: =I57*Assumptions!$B$126 -> 553.5 | J58: =J57*Assumptions!$B$126 -> 627.75 | ... Z58: =Z57*Assumptions!$B$126 -> 0.1769472
A59: COGS + royalties, risk-adjusted | C59: =C57*(Assumptions!$B$127+Assumptions!$B$128) -> 0 | D59: =D57*(Assumptions!$B$127+Assumptions!$B$128) -> 0 | E59: =E57*(Assumptions!$B$127+Assumptions!$B$128) -> 5.4 | F59: =F57*(Assumptions!$B$127+Assumptions!$B$128) -> 13.5 | G59: =G57*(Assumptions!$B$127+Assumptions!$B$128) -> 24.3 | H59: =H57*(Assumptions!$B$127+Assumptions!$B$128) -> 35.1 | I59: =I57*(Assumptions!$B$127+Assumptions!$B$128) -> 44.28 | J59: =J57*(Assumptions!$B$127+Assumptions!$B$128) -> 50.22 | ... Z59: =Z57*(Assumptions!$B$127+Assumptions!$B$128) -> 0.014155776
A60: Commercial SG&A, risk-adjusted | C60: =MIN(1,Assumptions!$B$125*Assumptions!$B$37)*IF(Assumptions!$B$129=0,0,IF(C55=0,Assumptions!$B$130,IF(C55>=1,C56*IF(OR(Assumptions!$B$126<1,C55>5),Assumptions!$B$129,MAX(Assumptions!$B$129,INDEX(Assumptions!$B$44:$F$44,C55))),0))) -> 0 | D60: =MIN(1,Assumptions!$B$125*Assumptions!$B$37)*IF(Assumptions!$B$129=0,0,IF(D55=0,Assumptions!$B$130,IF(D55>=1,D56*IF(OR(Assumptions!$B$126<1,D55>5),Assumptions!$B$129,MAX(Assumptions!$B$129,INDEX(Assumptions!$B$44:$F$44,D55))),0))) -> 18 | E60: =MIN(1,Assumptions!$B$125*Assumptions!$B$37)*IF(Assumptions!$B$129=0,0,IF(E55=0,Assumptions!$B$130,IF(E55>=1,E56*IF(OR(Assumptions!$B$126<1,E55>5),Assumptions!$B$129,MAX(Assumptions!$B$129,INDEX(Assumptions!$B$44:$F$44,E55))),0))) -> 60.75 | F60: =MIN(1,Assumptions!$B$125*Assumptions!$B$37)*IF(Assumptions!$B$129=0,0,IF(F55=0,Assumptions!$B$130,IF(F55>=1,F56*IF(OR(Assumptions!$B$126<1,F55>5),Assumptions!$B$129,MAX(Assumptions!$B$129,INDEX(Assumptions!$B$44:$F$44,F55))),0))) -> 92.8125 | G60: =MIN(1,Assumptions!$B$125*Assumptions!$B$37)*IF(Assumptions!$B$129=0,0,IF(G55=0,Assumptions!$B$130,IF(G55>=1,G56*IF(OR(Assumptions!$B$126<1,G55>5),Assumptions!$B$129,MAX(Assumptions!$B$129,INDEX(Assumptions!$B$44:$F$44,G55))),0))) -> 121.5 | H60: =MIN(1,Assumptions!$B$125*Assumptions!$B$37)*IF(Assumptions!$B$129=0,0,IF(H55=0,Assumptions!$B$130,IF(H55>=1,H56*IF(OR(Assumptions!$B$126<1,H55>5),Assumptions!$B$129,MAX(Assumptions!$B$129,INDEX(Assumptions!$B$44:$F$44,H55))),0))) -> 140.4 | I60: =MIN(1,Assumptions!$B$125*Assumptions!$B$37)*IF(Assumptions!$B$129=0,0,IF(I55=0,Assumptions!$B$130,IF(I55>=1,I56*IF(OR(Assumptions!$B$126<1,I55>5),Assumptions!$B$129,MAX(Assumptions!$B$129,INDEX(Assumptions!$B$44:$F$44,I55))),0))) -> 154.98 | J60: =MIN(1,Assumptions!$B$125*Assumptions!$B$37)*IF(Assumptions!$B$129=0,0,IF(J55=0,Assumptions!$B$130,IF(J55>=1,J56*IF(OR(Assumptions!$B$126<1,J55>5),Assumptions!$B$129,MAX(Assumptions!$B$129,INDEX(Assumptions!$B$44:$F$44,J55))),0))) -> 156.9375 | ... Z60: =MIN(1,Assumptions!$B$125*Assumptions!$B$37)*IF(Assumptions!$B$129=0,0,IF(Z55=0,Assumptions!$B$130,IF(Z55>=1,Z56*IF(OR(Assumptions!$B$126<1,Z55>5),Assumptions!$B$129,MAX(Assumptions!$B$129,INDEX(Assumptions!$B$44:$F$44,Z55))),0))) -> 0.0442368
A61: Development R&D, risk-adjusted | C61: =IFERROR(INDEX(Assumptions!$B$135:$I$135,MATCH(C$2,Assumptions!$B$134:$I$134,0))*INDEX(Assumptions!$B$136:$I$136,MATCH(C$2,Assumptions!$B$134:$I$134,0)),0) -> 70 | D61: =IFERROR(INDEX(Assumptions!$B$135:$I$135,MATCH(D$2,Assumptions!$B$134:$I$134,0))*INDEX(Assumptions!$B$136:$I$136,MATCH(D$2,Assumptions!$B$134:$I$134,0)),0) -> 50 | E61: =IFERROR(INDEX(Assumptions!$B$135:$I$135,MATCH(E$2,Assumptions!$B$134:$I$134,0))*INDEX(Assumptions!$B$136:$I$136,MATCH(E$2,Assumptions!$B$134:$I$134,0)),0) -> 5 | F61: =IFERROR(INDEX(Assumptions!$B$135:$I$135,MATCH(F$2,Assumptions!$B$134:$I$134,0))*INDEX(Assumptions!$B$136:$I$136,MATCH(F$2,Assumptions!$B$134:$I$134,0)),0) -> 0 | G61: =IFERROR(INDEX(Assumptions!$B$135:$I$135,MATCH(G$2,Assumptions!$B$134:$I$134,0))*INDEX(Assumptions!$B$136:$I$136,MATCH(G$2,Assumptions!$B$134:$I$134,0)),0) -> 0 | H61: =IFERROR(INDEX(Assumptions!$B$135:$I$135,MATCH(H$2,Assumptions!$B$134:$I$134,0))*INDEX(Assumptions!$B$136:$I$136,MATCH(H$2,Assumptions!$B$134:$I$134,0)),0) -> 0 | I61: =IFERROR(INDEX(Assumptions!$B$135:$I$135,MATCH(I$2,Assumptions!$B$134:$I$134,0))*INDEX(Assumptions!$B$136:$I$136,MATCH(I$2,Assumptions!$B$134:$I$134,0)),0) -> 0 | J61: =IFERROR(INDEX(Assumptions!$B$135:$I$135,MATCH(J$2,Assumptions!$B$134:$I$134,0))*INDEX(Assumptions!$B$136:$I$136,MATCH(J$2,Assumptions!$B$134:$I$134,0)),0) -> 0 | ... Z61: =IFERROR(INDEX(Assumptions!$B$135:$I$135,MATCH(Z$2,Assumptions!$B$134:$I$134,0))*INDEX(Assumptions!$B$136:$I$136,MATCH(Z$2,Assumptions!$B$134:$I$134,0)),0) -> 0
A62: Program contribution (pre-tax) | C62: =C58-C59-C60-C61 -> -70 | D62: =D58-D59-D60-D61 -> -68 | E62: =E58-E59-E60-E61 -> -3.65 | F62: =F58-F59-F60-F61 -> 62.4375 | G62: =G58-G59-G60-G61 -> 157.95 | H62: =H58-H59-H60-H61 -> 263.25 | I62: =I58-I59-I60-I61 -> 354.24 | J62: =J58-J59-J60-J61 -> 420.5925 | ... Z62: =Z58-Z59-Z60-Z61 -> 0.11855462
A64: Infigratinib — hypochondroplasia (Phase 3)
A65: Years since launch | C65: =C$2-Assumptions!$B$139+1 -> -1 | D65: =D$2-Assumptions!$B$139+1 -> 0 | E65: =E$2-Assumptions!$B$139+1 -> 1 | F65: =F$2-Assumptions!$B$139+1 -> 2 | G65: =G$2-Assumptions!$B$139+1 -> 3 | H65: =H$2-Assumptions!$B$139+1 -> 4 | I65: =I$2-Assumptions!$B$139+1 -> 5 | J65: =J$2-Assumptions!$B$139+1 -> 6 | ... Z65: =Z$2-Assumptions!$B$139+1 -> 22
A66: Net sales, unrisked | C66: =IF(C$2>Assumptions!$B$148,0*(1-Assumptions!$B$149),IF(C65>=1,Assumptions!$B$140*CHOOSE(Assumptions!$B$147,INDEX(Assumptions!$B$42:$H$42,MIN(C65,7)),INDEX(Assumptions!$B$43:$H$43,MIN(C65,7))),0)) -> 0 | D66: =IF(D$2>Assumptions!$B$148,C66*(1-Assumptions!$B$149),IF(D65>=1,Assumptions!$B$140*CHOOSE(Assumptions!$B$147,INDEX(Assumptions!$B$42:$H$42,MIN(D65,7)),INDEX(Assumptions!$B$43:$H$43,MIN(D65,7))),0)) -> 0 | E66: =IF(E$2>Assumptions!$B$148,D66*(1-Assumptions!$B$149),IF(E65>=1,Assumptions!$B$140*CHOOSE(Assumptions!$B$147,INDEX(Assumptions!$B$42:$H$42,MIN(E65,7)),INDEX(Assumptions!$B$43:$H$43,MIN(E65,7))),0)) -> 60 | F66: =IF(F$2>Assumptions!$B$148,E66*(1-Assumptions!$B$149),IF(F65>=1,Assumptions!$B$140*CHOOSE(Assumptions!$B$147,INDEX(Assumptions!$B$42:$H$42,MIN(F65,7)),INDEX(Assumptions!$B$43:$H$43,MIN(F65,7))),0)) -> 150 | G66: =IF(G$2>Assumptions!$B$148,F66*(1-Assumptions!$B$149),IF(G65>=1,Assumptions!$B$140*CHOOSE(Assumptions!$B$147,INDEX(Assumptions!$B$42:$H$42,MIN(G65,7)),INDEX(Assumptions!$B$43:$H$43,MIN(G65,7))),0)) -> 270 | H66: =IF(H$2>Assumptions!$B$148,G66*(1-Assumptions!$B$149),IF(H65>=1,Assumptions!$B$140*CHOOSE(Assumptions!$B$147,INDEX(Assumptions!$B$42:$H$42,MIN(H65,7)),INDEX(Assumptions!$B$43:$H$43,MIN(H65,7))),0)) -> 390 | I66: =IF(I$2>Assumptions!$B$148,H66*(1-Assumptions!$B$149),IF(I65>=1,Assumptions!$B$140*CHOOSE(Assumptions!$B$147,INDEX(Assumptions!$B$42:$H$42,MIN(I65,7)),INDEX(Assumptions!$B$43:$H$43,MIN(I65,7))),0)) -> 492 | J66: =IF(J$2>Assumptions!$B$148,I66*(1-Assumptions!$B$149),IF(J65>=1,Assumptions!$B$140*CHOOSE(Assumptions!$B$147,INDEX(Assumptions!$B$42:$H$42,MIN(J65,7)),INDEX(Assumptions!$B$43:$H$43,MIN(J65,7))),0)) -> 558 | K66: =IF(K$2>Assumptions!$B$148,J66*(1-Assumptions!$B$149),IF(K65>=1,Assumptions!$B$140*CHOOSE(Assumptions!$B$147,INDEX(Assumptions!$B$42:$H$42,MIN(K65,7)),INDEX(Assumptions!$B$43:$H$43,MIN(K65,7))),0)) -> 600 | ... Z66: =IF(Z$2>Assumptions!$B$148,Y66*(1-Assumptions!$B$149),IF(Z65>=1,Assumptions!$B$140*CHOOSE(Assumptions!$B$147,INDEX(Assumptions!$B$42:$H$42,MIN(Z65,7)),INDEX(Assumptions!$B$43:$H$43,MIN(Z65,7))),0)) -> 0.1572864
A67: Product net sales, risk-adjusted | C67: =C66*MIN(1,Assumptions!$B$141*Assumptions!$B$37) -> 0 | D67: =D66*MIN(1,Assumptions!$B$141*Assumptions!$B$37) -> 0 | E67: =E66*MIN(1,Assumptions!$B$141*Assumptions!$B$37) -> 27 | F67: =F66*MIN(1,Assumptions!$B$141*Assumptions!$B$37) -> 67.5 | G67: =G66*MIN(1,Assumptions!$B$141*Assumptions!$B$37) -> 121.5 | H67: =H66*MIN(1,Assumptions!$B$141*Assumptions!$B$37) -> 175.5 | I67: =I66*MIN(1,Assumptions!$B$141*Assumptions!$B$37) -> 221.4 | J67: =J66*MIN(1,Assumptions!$B$141*Assumptions!$B$37) -> 251.1 | ... Z67: =Z66*MIN(1,Assumptions!$B$141*Assumptions!$B$37) -> 0.07077888
A68: Company revenue, risk-adjusted (incl. milestones) | C68: =C67*Assumptions!$B$142 -> 0 | D68: =D67*Assumptions!$B$142 -> 0 | E68: =E67*Assumptions!$B$142 -> 27 | F68: =F67*Assumptions!$B$142 -> 67.5 | G68: =G67*Assumptions!$B$142 -> 121.5 | H68: =H67*Assumptions!$B$142 -> 175.5 | I68: =I67*Assumptions!$B$142 -> 221.4 | J68: =J67*Assumptions!$B$142 -> 251.1 | ... Z68: =Z67*Assumptions!$B$142 -> 0.07077888
A69: COGS + royalties, risk-adjusted | C69: =C67*(Assumptions!$B$143+Assumptions!$B$144) -> 0 | D69: =D67*(Assumptions!$B$143+Assumptions!$B$144) -> 0 | E69: =E67*(Assumptions!$B$143+Assumptions!$B$144) -> 2.97 | F69: =F67*(Assumptions!$B$143+Assumptions!$B$144) -> 7.425 | G69: =G67*(Assumptions!$B$143+Assumptions!$B$144) -> 13.365 | H69: =H67*(Assumptions!$B$143+Assumptions!$B$144) -> 19.305 | I69: =I67*(Assumptions!$B$143+Assumptions!$B$144) -> 24.354 | J69: =J67*(Assumptions!$B$143+Assumptions!$B$144) -> 27.621 | ... Z69: =Z67*(Assumptions!$B$143+Assumptions!$B$144) -> 0.0077856768
A70: Commercial SG&A, risk-adjusted | C70: =MIN(1,Assumptions!$B$141*Assumptions!$B$37)*IF(Assumptions!$B$145=0,0,IF(C65=0,Assumptions!$B$146,IF(C65>=1,C66*IF(OR(Assumptions!$B$142<1,C65>5),Assumptions!$B$145,MAX(Assumptions!$B$145,INDEX(Assumptions!$B$44:$F$44,C65))),0))) -> 0 | D70: =MIN(1,Assumptions!$B$141*Assumptions!$B$37)*IF(Assumptions!$B$145=0,0,IF(D65=0,Assumptions!$B$146,IF(D65>=1,D66*IF(OR(Assumptions!$B$142<1,D65>5),Assumptions!$B$145,MAX(Assumptions!$B$145,INDEX(Assumptions!$B$44:$F$44,D65))),0))) -> 6.75 | E70: =MIN(1,Assumptions!$B$141*Assumptions!$B$37)*IF(Assumptions!$B$145=0,0,IF(E65=0,Assumptions!$B$146,IF(E65>=1,E66*IF(OR(Assumptions!$B$142<1,E65>5),Assumptions!$B$145,MAX(Assumptions!$B$145,INDEX(Assumptions!$B$44:$F$44,E65))),0))) -> 24.3 | F70: =MIN(1,Assumptions!$B$141*Assumptions!$B$37)*IF(Assumptions!$B$145=0,0,IF(F65=0,Assumptions!$B$146,IF(F65>=1,F66*IF(OR(Assumptions!$B$142<1,F65>5),Assumptions!$B$145,MAX(Assumptions!$B$145,INDEX(Assumptions!$B$44:$F$44,F65))),0))) -> 37.125 | G70: =MIN(1,Assumptions!$B$141*Assumptions!$B$37)*IF(Assumptions!$B$145=0,0,IF(G65=0,Assumptions!$B$146,IF(G65>=1,G66*IF(OR(Assumptions!$B$142<1,G65>5),Assumptions!$B$145,MAX(Assumptions!$B$145,INDEX(Assumptions!$B$44:$F$44,G65))),0))) -> 48.6 | H70: =MIN(1,Assumptions!$B$141*Assumptions!$B$37)*IF(Assumptions!$B$145=0,0,IF(H65=0,Assumptions!$B$146,IF(H65>=1,H66*IF(OR(Assumptions!$B$142<1,H65>5),Assumptions!$B$145,MAX(Assumptions!$B$145,INDEX(Assumptions!$B$44:$F$44,H65))),0))) -> 56.16 | I70: =MIN(1,Assumptions!$B$141*Assumptions!$B$37)*IF(Assumptions!$B$145=0,0,IF(I65=0,Assumptions!$B$146,IF(I65>=1,I66*IF(OR(Assumptions!$B$142<1,I65>5),Assumptions!$B$145,MAX(Assumptions!$B$145,INDEX(Assumptions!$B$44:$F$44,I65))),0))) -> 61.992 | J70: =MIN(1,Assumptions!$B$141*Assumptions!$B$37)*IF(Assumptions!$B$145=0,0,IF(J65=0,Assumptions!$B$146,IF(J65>=1,J66*IF(OR(Assumptions!$B$142<1,J65>5),Assumptions!$B$145,MAX(Assumptions!$B$145,INDEX(Assumptions!$B$44:$F$44,J65))),0))) -> 50.22 | ... Z70: =MIN(1,Assumptions!$B$141*Assumptions!$B$37)*IF(Assumptions!$B$145=0,0,IF(Z65=0,Assumptions!$B$146,IF(Z65>=1,Z66*IF(OR(Assumptions!$B$142<1,Z65>5),Assumptions!$B$145,MAX(Assumptions!$B$145,INDEX(Assumptions!$B$44:$F$44,Z65))),0))) -> 0.014155776
A71: Development R&D, risk-adjusted | C71: =IFERROR(INDEX(Assumptions!$B$151:$I$151,MATCH(C$2,Assumptions!$B$150:$I$150,0))*INDEX(Assumptions!$B$152:$I$152,MATCH(C$2,Assumptions!$B$150:$I$150,0)),0) -> 40 | D71: =IFERROR(INDEX(Assumptions!$B$151:$I$151,MATCH(D$2,Assumptions!$B$150:$I$150,0))*INDEX(Assumptions!$B$152:$I$152,MATCH(D$2,Assumptions!$B$150:$I$150,0)),0) -> 20 | E71: =IFERROR(INDEX(Assumptions!$B$151:$I$151,MATCH(E$2,Assumptions!$B$150:$I$150,0))*INDEX(Assumptions!$B$152:$I$152,MATCH(E$2,Assumptions!$B$150:$I$150,0)),0) -> 0 | F71: =IFERROR(INDEX(Assumptions!$B$151:$I$151,MATCH(F$2,Assumptions!$B$150:$I$150,0))*INDEX(Assumptions!$B$152:$I$152,MATCH(F$2,Assumptions!$B$150:$I$150,0)),0) -> 0 | G71: =IFERROR(INDEX(Assumptions!$B$151:$I$151,MATCH(G$2,Assumptions!$B$150:$I$150,0))*INDEX(Assumptions!$B$152:$I$152,MATCH(G$2,Assumptions!$B$150:$I$150,0)),0) -> 0 | H71: =IFERROR(INDEX(Assumptions!$B$151:$I$151,MATCH(H$2,Assumptions!$B$150:$I$150,0))*INDEX(Assumptions!$B$152:$I$152,MATCH(H$2,Assumptions!$B$150:$I$150,0)),0) -> 0 | I71: =IFERROR(INDEX(Assumptions!$B$151:$I$151,MATCH(I$2,Assumptions!$B$150:$I$150,0))*INDEX(Assumptions!$B$152:$I$152,MATCH(I$2,Assumptions!$B$150:$I$150,0)),0) -> 0 | J71: =IFERROR(INDEX(Assumptions!$B$151:$I$151,MATCH(J$2,Assumptions!$B$150:$I$150,0))*INDEX(Assumptions!$B$152:$I$152,MATCH(J$2,Assumptions!$B$150:$I$150,0)),0) -> 0 | ... Z71: =IFERROR(INDEX(Assumptions!$B$151:$I$151,MATCH(Z$2,Assumptions!$B$150:$I$150,0))*INDEX(Assumptions!$B$152:$I$152,MATCH(Z$2,Assumptions!$B$150:$I$150,0)),0) -> 0
A72: Program contribution (pre-tax) | C72: =C68-C69-C70-C71 -> -40 | D72: =D68-D69-D70-D71 -> -26.75 | E72: =E68-E69-E70-E71 -> -0.27 | F72: =F68-F69-F70-F71 -> 22.95 | G72: =G68-G69-G70-G71 -> 59.535 | H72: =H68-H69-H70-H71 -> 100.035 | I72: =I68-I69-I70-I71 -> 135.054 | J72: =J68-J69-J70-J71 -> 173.259 | ... Z72: =Z68-Z69-Z70-Z71 -> 0.048837427
A74: Company totals (risk-adjusted)
A75: Revenue | C75: =C7+C16+C28+C38+C48+C58+C68 -> 1910.676 | D75: =D7+D16+D28+D38+D48+D58+D68 -> 2676.932 | E75: =E7+E16+E28+E38+E48+E58+E68 -> 3752.158 | F75: =F7+F16+F28+F38+F48+F58+F68 -> 4849.674 | G75: =G7+G16+G28+G38+G48+G58+G68 -> 5904.91 | H75: =H7+H16+H28+H38+H48+H58+H68 -> 6373.68 | I75: =I7+I16+I28+I38+I48+I58+I68 -> 6625.02 | J75: =J7+J16+J28+J38+J48+J58+J68 -> 6736.65 | ... Z75: =Z7+Z16+Z28+Z38+Z48+Z58+Z68 -> 0.83034636
A76: Cost of sales (COGS + royalties) | C76: =C8+C17+C29+C39+C49+C59+C69 -> 198.45732 | D76: =D8+D17+D29+D39+D49+D59+D69 -> 292.21474 | E76: =E8+E17+E29+E39+E49+E59+E69 -> 401.48426 | F76: =F8+F17+F29+F39+F49+F59+F69 -> 515.24598 | G76: =G8+G17+G29+G39+G49+G59+G69 -> 623.8604 | H76: =H8+H17+H29+H39+H49+H59+H69 -> 666.7143 | I76: =I8+I17+I29+I39+I49+I59+I69 -> 690.5736 | J76: =J8+J17+J29+J39+J49+J59+J69 -> 700.395 | ... Z76: =Z8+Z17+Z29+Z39+Z49+Z59+Z69 -> 0.078250928
A77: Program development R&D | C77: =C10+C19+C31+C41+C51+C61+C71 -> 155 | D77: =D10+D19+D31+D41+D51+D61+D71 -> 85 | E77: =E10+E19+E31+E41+E51+E61+E71 -> 5 | F77: =F10+F19+F31+F41+F51+F61+F71 -> 0 | G77: =G10+G19+G31+G41+G51+G61+G71 -> 0 | H77: =H10+H19+H31+H41+H51+H61+H71 -> 0 | I77: =I10+I19+I31+I41+I51+I61+I71 -> 0 | J77: =J10+J19+J31+J41+J51+J61+J71 -> 0 | ... Z77: =Z10+Z19+Z31+Z41+Z51+Z61+Z71 -> 0
A78: Platform / unallocated R&D | C78: =IF(C$2>Assumptions!$B$25,Assumptions!$B$23*C75,MAX(Assumptions!$B$20*(1+Assumptions!$B$21)^(C$2-2027)*Assumptions!$B$38,Assumptions!$B$23*C75)) -> 330 | D78: =IF(D$2>Assumptions!$B$25,Assumptions!$B$23*D75,MAX(Assumptions!$B$20*(1+Assumptions!$B$21)^(D$2-2027)*Assumptions!$B$38,Assumptions!$B$23*D75)) -> 339.9 | E78: =IF(E$2>Assumptions!$B$25,Assumptions!$B$23*E75,MAX(Assumptions!$B$20*(1+Assumptions!$B$21)^(E$2-2027)*Assumptions!$B$38,Assumptions!$B$23*E75)) -> 450.25896 | F78: =IF(F$2>Assumptions!$B$25,Assumptions!$B$23*F75,MAX(Assumptions!$B$20*(1+Assumptions!$B$21)^(F$2-2027)*Assumptions!$B$38,Assumptions!$B$23*F75)) -> 581.96088 | G78: =IF(G$2>Assumptions!$B$25,Assumptions!$B$23*G75,MAX(Assumptions!$B$20*(1+Assumptions!$B$21)^(G$2-2027)*Assumptions!$B$38,Assumptions!$B$23*G75)) -> 708.5892 | H78: =IF(H$2>Assumptions!$B$25,Assumptions!$B$23*H75,MAX(Assumptions!$B$20*(1+Assumptions!$B$21)^(H$2-2027)*Assumptions!$B$38,Assumptions!$B$23*H75)) -> 764.8416 | I78: =IF(I$2>Assumptions!$B$25,Assumptions!$B$23*I75,MAX(Assumptions!$B$20*(1+Assumptions!$B$21)^(I$2-2027)*Assumptions!$B$38,Assumptions!$B$23*I75)) -> 795.0024 | J78: =IF(J$2>Assumptions!$B$25,Assumptions!$B$23*J75,MAX(Assumptions!$B$20*(1+Assumptions!$B$21)^(J$2-2027)*Assumptions!$B$38,Assumptions!$B$23*J75)) -> 808.398 | ... Z78: =IF(Z$2>Assumptions!$B$25,Assumptions!$B$23*Z75,MAX(Assumptions!$B$20*(1+Assumptions!$B$21)^(Z$2-2027)*Assumptions!$B$38,Assumptions!$B$23*Z75)) -> 0.099641564
A79: Total R&D | C79: =C77+C78 -> 485 | D79: =D77+D78 -> 424.9 | E79: =E77+E78 -> 455.25896 | F79: =F77+F78 -> 581.96088 | G79: =G77+G78 -> 708.5892 | H79: =H77+H78 -> 764.8416 | I79: =I77+I78 -> 795.0024 | J79: =J77+J78 -> 808.398 | ... Z79: =Z77+Z78 -> 0.099641564
A80: Commercial SG&A | C80: =C9+C18+C30+C40+C50+C60+C70 -> 832.5628 | D80: =D9+D18+D30+D40+D50+D60+D70 -> 1017.7062 | E80: =E9+E18+E30+E40+E50+E60+E70 -> 1216.6185 | F80: =F9+F18+F30+F40+F50+F60+F70 -> 1363.1215 | G80: =G9+G18+G30+G40+G50+G60+G70 -> 1549.4736 | H80: =H9+H18+H30+H40+H50+H60+H70 -> 1577.9495 | I80: =I9+I18+I30+I40+I50+I60+I70 -> 1619.0756 | J80: =J9+J18+J30+J40+J50+J60+J70 -> 1609.1075 | ... Z80: =Z9+Z18+Z30+Z40+Z50+Z60+Z70 -> 0.20362822
A81: Corporate G&A | C81: =IF(C$2>Assumptions!$B$25,Assumptions!$B$22*C75,MAX(Assumptions!$B$19*(1+Assumptions!$B$21)^(C$2-2027)*Assumptions!$B$38,Assumptions!$B$22*C75)) -> 170 | D81: =IF(D$2>Assumptions!$B$25,Assumptions!$B$22*D75,MAX(Assumptions!$B$19*(1+Assumptions!$B$21)^(D$2-2027)*Assumptions!$B$38,Assumptions!$B$22*D75)) -> 187.38524 | E81: =IF(E$2>Assumptions!$B$25,Assumptions!$B$22*E75,MAX(Assumptions!$B$19*(1+Assumptions!$B$21)^(E$2-2027)*Assumptions!$B$38,Assumptions!$B$22*E75)) -> 262.65106 | F81: =IF(F$2>Assumptions!$B$25,Assumptions!$B$22*F75,MAX(Assumptions!$B$19*(1+Assumptions!$B$21)^(F$2-2027)*Assumptions!$B$38,Assumptions!$B$22*F75)) -> 339.47718 | G81: =IF(G$2>Assumptions!$B$25,Assumptions!$B$22*G75,MAX(Assumptions!$B$19*(1+Assumptions!$B$21)^(G$2-2027)*Assumptions!$B$38,Assumptions!$B$22*G75)) -> 413.3437 | H81: =IF(H$2>Assumptions!$B$25,Assumptions!$B$22*H75,MAX(Assumptions!$B$19*(1+Assumptions!$B$21)^(H$2-2027)*Assumptions!$B$38,Assumptions!$B$22*H75)) -> 446.1576 | I81: =IF(I$2>Assumptions!$B$25,Assumptions!$B$22*I75,MAX(Assumptions!$B$19*(1+Assumptions!$B$21)^(I$2-2027)*Assumptions!$B$38,Assumptions!$B$22*I75)) -> 463.7514 | J81: =IF(J$2>Assumptions!$B$25,Assumptions!$B$22*J75,MAX(Assumptions!$B$19*(1+Assumptions!$B$21)^(J$2-2027)*Assumptions!$B$38,Assumptions!$B$22*J75)) -> 471.5655 | ... Z81: =IF(Z$2>Assumptions!$B$25,Assumptions!$B$22*Z75,MAX(Assumptions!$B$19*(1+Assumptions!$B$21)^(Z$2-2027)*Assumptions!$B$38,Assumptions!$B$22*Z75)) -> 0.058124245
A82: Total G&A incl. SG&A | C82: =C80+C81 -> 1002.5628 | D82: =D80+D81 -> 1205.0914 | E82: =E80+E81 -> 1479.2695 | F82: =F80+F81 -> 1702.5987 | G82: =G80+G81 -> 1962.8173 | H82: =H80+H81 -> 2024.1071 | I82: =I80+I81 -> 2082.827 | J82: =J80+J81 -> 2080.673 | ... Z82: =Z80+Z81 -> 0.26175246
A83: Operating income (EBIT) | C83: =C75-C76-C79-C82 -> 224.65588 | D83: =D75-D76-D79-D82 -> 754.72584 | E83: =E75-E76-E79-E82 -> 1416.1452 | F83: =F75-F76-F79-F82 -> 2049.8685 | G83: =G75-G76-G79-G82 -> 2609.6431 | H83: =H75-H76-H79-H82 -> 2918.017 | I83: =I75-I76-I79-I82 -> 3056.617 | J83: =J75-J76-J79-J82 -> 3147.184 | ... Z83: =Z75-Z76-Z79-Z82 -> 0.39070141

Sheet NPV
A1: BBIO — risk-adjusted NPV (rNPV), $mm except per share
A3: Scenario | B3: =Assumptions!$C$4 -> Base
A4: Valuation date | B4: =Assumptions!$B$13 -> 46311
A5: Discount rate | B5: =Assumptions!$B$14 -> 0.095
A7: Period | C7: 2H 2026 | D7: 2027 | E7: 2028 | F7: 2029 | G7: 2030 | H7: 2031 | I7: 2032 | J7: 2033 | K7: 2034 | L7: 2035 | M7: 2036 | N7: 2037 | O7: 2038 | P7: 2039 | Q7: 2040 | R7: 2041 | S7: 2042 | T7: 2043 | U7: 2044 | V7: 2045 | W7: 2046 | X7: 2047 | Y7: 2048 | Z7: 2049 | AA7: 2050
A8: Revenue, risk-adjusted | C8: =SUM('Quarterly Model'!H2:I2) -> 589 | D8: ='Yearly Model'!H2 -> 1910.676 | E8: ='Yearly Model'!I2 -> 2676.932 | F8: ='Yearly Model'!J2 -> 3752.158 | G8: ='Yearly Model'!K2 -> 4849.674 | H8: ='Yearly Model'!L2 -> 5904.91 | I8: ='Yearly Model'!M2 -> 6373.68 | J8: ='Yearly Model'!N2 -> 6625.02 | K8: ='Yearly Model'!O2 -> 6736.65 | ... AA8: ='Yearly Model'!AE2 -> 0.83034636
A9: Operating income (EBIT) | C9: =SUM('Quarterly Model'!H8:I8) -> -142.518 | D9: ='Yearly Model'!H8 -> 224.65588 | E9: ='Yearly Model'!I8 -> 754.72584 | F9: ='Yearly Model'!J8 -> 1416.1452 | G9: ='Yearly Model'!K8 -> 2049.8685 | H9: ='Yearly Model'!L8 -> 2609.6431 | I9: ='Yearly Model'!M8 -> 2918.017 | J9: ='Yearly Model'!N8 -> 3056.617 | K9: ='Yearly Model'!O8 -> 3147.184 | ... AA9: ='Yearly Model'!AE8 -> 0.39070141
A10: Taxes on EBIT (after tax-loss pool) | C10: 0 | D10: =IF(D9>0,MAX(0,D9-'Yearly Model'!G21)*Assumptions!$B$15,0) -> 0 | E10: =IF(E9>0,MAX(0,E9-'Yearly Model'!H21)*Assumptions!$B$15,0) -> 0 | F10: =IF(F9>0,MAX(0,F9-'Yearly Model'!I21)*Assumptions!$B$15,0) -> 0 | G10: =IF(G9>0,MAX(0,G9-'Yearly Model'!J21)*Assumptions!$B$15,0) -> 178.06396 | H10: =IF(H9>0,MAX(0,H9-'Yearly Model'!K21)*Assumptions!$B$15,0) -> 548.02505 | I10: =IF(I9>0,MAX(0,I9-'Yearly Model'!L21)*Assumptions!$B$15,0) -> 612.78357 | J10: =IF(J9>0,MAX(0,J9-'Yearly Model'!M21)*Assumptions!$B$15,0) -> 641.88957 | K10: =IF(K9>0,MAX(0,K9-'Yearly Model'!N21)*Assumptions!$B$15,0) -> 660.90864 | ... AA10: =IF(AA9>0,MAX(0,AA9-'Yearly Model'!AD21)*Assumptions!$B$15,0) -> 0.082047296
A11: Unlevered free cash flow | C11: =C9-C10 -> -142.518 | D11: =D9-D10 -> 224.65588 | E11: =E9-E10 -> 754.72584 | F11: =F9-F10 -> 1416.1452 | G11: =G9-G10 -> 1871.8045 | H11: =H9-H10 -> 2061.618 | I11: =I9-I10 -> 2305.2334 | J11: =J9-J10 -> 2414.7274 | ... AA11: =AA9-AA10 -> 0.30865411
A12: Cash-flow date (mid-period) | C12: =DATE(2026,10,1) -> 46296 | D12: =DATE(D7,7,1) -> 46569 | E12: =DATE(E7,7,1) -> 46935 | F12: =DATE(F7,7,1) -> 47300 | G12: =DATE(G7,7,1) -> 47665 | H12: =DATE(H7,7,1) -> 48030 | I12: =DATE(I7,7,1) -> 48396 | J12: =DATE(J7,7,1) -> 48761 | K12: =DATE(K7,7,1) -> 49126 | ... AA12: =DATE(AA7,7,1) -> 54970
A13: Years from valuation date | C13: =MAX(0,(C12-$B$4)/365.25) -> 0 | D13: =MAX(0,(D12-$B$4)/365.25) -> 0.7063655 | E13: =MAX(0,(E12-$B$4)/365.25) -> 1.7084189 | F13: =MAX(0,(F12-$B$4)/365.25) -> 2.7077344 | G13: =MAX(0,(G12-$B$4)/365.25) -> 3.70705 | H13: =MAX(0,(H12-$B$4)/365.25) -> 4.7063655 | I13: =MAX(0,(I12-$B$4)/365.25) -> 5.7084189 | J13: =MAX(0,(J12-$B$4)/365.25) -> 6.7077344 | ... AA13: =MAX(0,(AA12-$B$4)/365.25) -> 23.70705
A14: Discount factor | C14: =1/(1+$B$5)^C13 -> 1 | D14: =1/(1+$B$5)^D13 -> 0.93790581 | E14: =1/(1+$B$5)^E13 -> 0.85637538 | F14: =1/(1+$B$5)^F13 -> 0.78212656 | G14: =1/(1+$B$5)^G13 -> 0.7143152 | H14: =1/(1+$B$5)^H13 -> 0.65238317 | I14: =1/(1+$B$5)^I13 -> 0.5956727 | J14: =1/(1+$B$5)^J13 -> 0.54402713 | ... AA14: =1/(1+$B$5)^AA13 -> 0.11630744
A15: PV of free cash flow | C15: =C11*C14 -> -142.518 | D15: =D11*D14 -> 210.70605 | E15: =E11*E14 -> 646.32863 | F15: =F11*F14 -> 1107.6048 | G15: =G11*G14 -> 1337.0584 | H15: =H11*H14 -> 1344.9649 | I15: =I11*I14 -> 1373.1646 | J15: =J11*J14 -> 1313.6772 | ... AA15: =AA11*AA14 -> 0.035898771
A17: Valuation summary
A18: PV of risk-adjusted free cash flows | C18: =SUM(C15:AA15) -> 13549.072
A19: Cash & investments (Main; incl. post-quarter financing) | C19: =Main!C7 -> 1720.16
A20: Debt, convertibles & preferred at face (Main) | C20: =Main!C8 -> 3505
A21: Equity value, all claims treated as debt | C21: =C18+C19-C20 -> 11764.232
A22: Basic shares incl. pre-funded / as-converted (Main) | C22: =Main!C4 -> 195.48747
A23: Value / share before conversions | C23: =C21/C22 -> 60.178954
A25: Convertible instruments (converted if value / share before conversions > conversion price) | B25: Face ($mm) | C25: Shares (mm) | D25: Conv. price | E25: Converted?
A26: 2027 notes | B26: 550 | C26: 12.878305 | D26: 42.71 | E26: =IF(AND(C26>0,$C$23>D26),1,0) -> 1
A27: 2029 notes | B27: 747.5 | C27: 7.702988 | D27: 97.04 | E27: =IF(AND(C27>0,$C$23>D27),1,0) -> 0
A28: 2031 notes | B28: 575 | C28: 11.544448 | D28: 49.81 | E28: =IF(AND(C28>0,$C$23>D28),1,0) -> 1
A29: 2033 notes | B29: 632.5 | C29: 5.720014 | D29: 110.58 | E29: =IF(AND(C29>0,$C$23>D29),1,0) -> 0
A30: Series A preferred (7% PIK) | B30: 1000 | C30: 7.257421 | D30: 137.79 | E30: =IF(AND(C30>0,$C$23>D30),1,0) -> 0
A31: Equity value (rNPV) after conversions | C31: =C21+SUMPRODUCT(B26:B30,E26:E30) -> 12889.232
A32: Shares after conversions (mm) | C32: =C22+SUMPRODUCT(C26:C30,E26:E30) -> 219.91023
A33: Value / share before options & warrants | C33: =C31/C32 -> 58.611334
A35: Options, warrants & RSUs (treasury-stock method) | B35: Count (mm) | C35: Strike | D35: Dilution (mm)
A36: Options | B36: 10.041746 | C36: 25.76 | D36: =IF(AND(B36>0,$C$33>C36),B36*(1-C36/$C$33),0) -> 5.628344
A37: RSUs / PSUs | B37: 9.476 | C37: 0 | D37: =IF(AND(B37>0,$C$33>C37),B37*(1-C37/$C$33),0) -> 9.476
A38: Milestone awards | B38: 0.902775 | C38: 0 | D38: =IF(AND(B38>0,$C$33>C38),B38*(1-C38/$C$33),0) -> 0.902775
A39: — | B39: 0 | C39: 0 | D39: =IF(AND(B39>0,$C$33>C39),B39*(1-C39/$C$33),0) -> 0
A40: — | B40: 0 | C40: 0 | D40: =IF(AND(B40>0,$C$33>C40),B40*(1-C40/$C$33),0) -> 0
A41: — | B41: 0 | C41: 0 | D41: =IF(AND(B41>0,$C$33>C41),B41*(1-C41/$C$33),0) -> 0
A42: Diluted shares (mm) | C42: =C32+SUM(D36:D41) -> 235.91735
A43: rNPV / share, diluted | C43: =C31/C42 -> 54.634524
A44: Current price (Main) | C44: =Main!C3 -> 67.55
A45: Upside / (downside) to rNPV | C45: =C43/C44-1 -> -0.19119876
A46: Net cash / share | C46: =(C19-C20)/C22 -> -9.1302014
A47: Est. cash & investments at 12/31/2026 | C47: ='Quarterly Model'!I20 -> 1497.642
A48: Liquidation value / share (12/31/2026E cash − debt − wind-down) | C48: =MAX(0,C47-C20-Assumptions!$B$27)/C22 -> 0
A49: Market-implied value of pipeline (market cap − net cash) | C49: =Main!C5-(C19-C20) -> 14990.019
A51: Sum of the parts (PV) | B51: $mm | C51: $ / share
A52: Attruby (acoramidis) — ATTR-CM, U.S. | B52: =SUMPRODUCT(Pipeline!C11:Z11,$D$14:$AA$14) -> 10912.861 | C52: =B52/$C$42 -> 46.257138
A53: Acoramidis — ex-U.S. royalties (Bayer, Alexion) | B53: =SUMPRODUCT(Pipeline!C20:Z20,$D$14:$AA$14) -> 1152.7872 | C53: =B53/$C$42 -> 4.8864031
A54: BBP-418 — LGMD2I/R9 | B54: =SUMPRODUCT(Pipeline!C32:Z32,$D$14:$AA$14) -> 2928.6983 | C54: =B54/$C$42 -> 12.414086
A55: Encaleret — ADH1 (PDUFA May 8, 2027) | B55: =SUMPRODUCT(Pipeline!C42:Z42,$D$14:$AA$14) -> 2691.2791 | C55: =B55/$C$42 -> 11.40772
A56: Infigratinib — achondroplasia (PDUFA Feb 4, 2027) | B56: =SUMPRODUCT(Pipeline!C52:Z52,$D$14:$AA$14) -> 3974.7704 | C56: =B56/$C$42 -> 16.848148
A57: Encaleret — chronic hypoparathyroidism (Phase 3) | B57: =SUMPRODUCT(Pipeline!C62:Z62,$D$14:$AA$14) -> 1760.077 | C57: =B57/$C$42 -> 7.4605664
A58: Infigratinib — hypochondroplasia (Phase 3) | B58: =SUMPRODUCT(Pipeline!C72:Z72,$D$14:$AA$14) -> 700.11078 | C58: =B58/$C$42 -> 2.9676104
A59: Corporate G&A + platform R&D (2027+) | B59: =-SUMPRODUCT(Pipeline!C78:Z78,$D$14:$AA$14)-SUMPRODUCT(Pipeline!C81:Z81,$D$14:$AA$14) -> -7539.9305 | C59: =B59/$C$42 -> -31.960051
A60: 2H 2026 operating result | B60: =C11*C14 -> -142.518 | C60: =B60/$C$42 -> -0.6041014
A61: Taxes | B61: =-SUMPRODUCT(D10:AA10,D14:AA14) -> -2889.0638 | C61: =B61/$C$42 -> -12.246085
A62: Net cash (cash − all claims at face) | B62: =C19-C20 -> -1784.84 | C62: =B62/$C$42 -> -7.565531
A63: Add back converted claims | B63: =SUMPRODUCT(B26:B30,E26:E30) -> 1125 | C63: =B63/$C$42 -> 4.7686193
A64: Equity value | B64: =SUM(B52:B63) -> 12889.232 | C64: =B64/$C$42 -> 54.634524
A65: Check vs. equity value above (should be 0) | B65: =ROUND(B64-C31,6) -> 0

Sheet Options
A1: BBIO — PDUFA options analysis (per contract = 100 shares)
A3: Inputs
A4: Spot price (close 10/16/2026) | B4: 66.39
A5: Pricing date | B5: =DATE(2026,10,16) -> 46311
A6: PDUFA date | B6: =Assumptions!$B$30 -> 46353
A7: Expiry (first monthly after the PDUFA date) | B7: =DATE(2026,12,18) -> 46374
A8: Years to expiry (T) | B8: =(B7-B5)/365 -> 0.17260274
A9: Risk-free rate | B9: 0.04
A10: Reference IV for wide quotes (theo prices) | B10: 0.533
A11: Contract multiplier | B11: 100
A13: Event model (two outcomes at the PDUFA)
A14: Model value / share, probability-weighted | B14: =NPV!C43 -> 54.634524
A15: Model value / share if approved | B15: =Assumptions!$D$168 -> 55.02037
A16: Model value / share if CRL | B16: =Assumptions!$D$167 -> 51.790583
A17: Model probability of approval | B17: =Assumptions!$B$32 -> 0.88
A18: Event-move scale (share of model jump priced at expiry) | B18: 1
A19: Floor after a CRL, % of est. 12/31/2026 net cash / share | B19: 0.5
A20: Floor price after a CRL | B20: =MAX(0,B19*(NPV!C47-NPV!C20)/NPV!C22) -> 0
A21: Price if approved (center of outcome) | B21: =IF(B14>0,B4*(1+B18*(B15/B14-1)),B4+B18*(B15-B14)) -> 66.858867
A22: Price if CRL (center of outcome) | B22: =MAX(B20,IF(B14>0,B4*(1+B18*(B16/B14-1)),B4+B18*(B16-B14))) -> 62.934141
A23: Model expected price after the decision | B23: =B17*B21+(1-B17)*B22 -> 66.3879
A24: Non-event volatility (6-month realized, 3 largest days removed) | B24: 0.321
A25: Model fair ATM straddle, % of spot (jump + non-event volatility) | B25: =(B17*((B21*NORMSDIST(((LN(B21/67.5)+$B$24^2*$B$8/2)/($B$24*SQRT($B$8))))-67.5*NORMSDIST((((LN(B21/67.5)+$B$24^2*$B$8/2)/($B$24*SQRT($B$8)))-$B$24*SQRT($B$8))))+(67.5*NORMSDIST(-(((LN(B21/67.5)+$B$24^2*$B$8/2)/($B$24*SQRT($B$8)))-$B$24*SQRT($B$8)))-B21*NORMSDIST(-((LN(B21/67.5)+$B$24^2*$B$8/2)/($B$24*SQRT($B$8))))))+(1-B17)*((B22*NORMSDIST(((LN(B22/67.5)+$B$24^2*$B$8/2)/($B$24*SQRT($B$8))))-67.5*NORMSDIST((((LN(B22/67.5)+$B$24^2*$B$8/2)/($B$24*SQRT($B$8)))-$B$24*SQRT($B$8))))+(67.5*NORMSDIST(-(((LN(B22/67.5)+$B$24^2*$B$8/2)/($B$24*SQRT($B$8)))-$B$24*SQRT($B$8)))-B22*NORMSDIST(-((LN(B22/67.5)+$B$24^2*$B$8/2)/($B$24*SQRT($B$8)))))))/B4 -> 0.10914356
A26: Market ATM straddle, % of spot | B26: =($G$43+$G$44)/B4 -> 0.17734694
A27: Options richness (market straddle ÷ model straddle) | B27: =B26/B25 -> 1.6248961
A28: Market snapshot — 12/18/2026 expiry (Cboe delayed quotes, 10/16/2026 close)
A29: Strike | B29: Call bid | C29: Call ask | D29: Call mid | E29: Call IV | F29: Put bid | G29: Put ask | H29: Put mid | I29: Put IV | J29: Call OI | K29: Put OI
A30: 55 | B30: 11.5 | C30: 15.1 | D30: =(B30+C30)/2 -> 13.3 | E30: 0.5629 | F30: 0 | G30: 3.7 | H30: =(F30+G30)/2 -> 1.85 | I30: 0.5975 | J30: 0 | K30: 0
A31: 57.5 | B31: 9.7 | C31: 13.5 | D31: =(B31+C31)/2 -> 11.6 | E31: 0.5766 | F31: 0.2 | G31: 4 | H31: =(F31+G31)/2 -> 2.1 | I31: 0.5419 | J31: 0 | K31: 0
A32: 60 | B32: 8.6 | C32: 10.8 | D32: =(B32+C32)/2 -> 9.7 | E32: 0.5485 | F32: 1 | G32: 4.9 | H32: =(F32+G32)/2 -> 2.95 | I32: 0.5463 | J32: 3 | K32: 0
A33: 62.5 | B33: 6.5 | C33: 9.6 | D33: =(B33+C33)/2 -> 8.05 | E33: 0.5337 | F33: 3.2 | G33: 4.4 | H33: =(F33+G33)/2 -> 3.8 | I33: 0.533 | J33: 0 | K33: 0
A34: 65 | B34: 5 | C34: 8.2 | D34: =(B34+C34)/2 -> 6.6 | E34: 0.5233 | F34: 3.2 | G34: 6.7 | H34: =(F34+G34)/2 -> 4.95 | I34: 0.5331 | J34: 2 | K34: 0
A35: 67.5 | B35: 3.2 | C35: 7.4 | D35: =(B35+C35)/2 -> 5.3 | E35: 0.5114 | F35: 4 | G35: 8 | H35: =(F35+G35)/2 -> 6 | I35: 0.5082 | J35: 0 | K35: 0
A36: 70 | B36: 2.25 | C36: 6.4 | D36: =(B36+C36)/2 -> 4.325 | E36: 0.5141 | F36: 5.5 | G36: 9.4 | H36: =(F36+G36)/2 -> 7.45 | I36: 0.5045 | J36: 0 | K36: 0
A37: 72.5 | B37: 1.4 | C37: 5.2 | D37: =(B37+C37)/2 -> 3.3 | E37: 0.4973 | F37: 7.4 | G37: 11.1 | H37: =(F37+G37)/2 -> 9.25 | I37: 0.5186 | J37: 0 | K37: 0
A38: 75 | B38: 2.15 | C38: 4.4 | D38: =(B38+C38)/2 -> 3.275 | E38: 0.5639 | F38: 9.4 | G38: 12.7 | H38: =(F38+G38)/2 -> 11.05 | I38: 0.5196 | J38: 300 | K38: 300
A39: 80 | B39: 0 | C39: 3.4 | D39: =(B39+C39)/2 -> 1.7 | E39: 0.5121 | F39: 13.4 | G39: 16.5 | H39: =(F39+G39)/2 -> 14.95 | I39: 0.514 | J39: 0 | K39: 0
A41: Legs (premium = mid when the market is tight, else Black-Scholes at the reference IV)
A42: Leg | B42: Type | C42: Strike | D42: Mid | E42: Spread % of mid | F42: BS value | G42: Premium used | H42: Source | I42: d1 | J42: Delta | K42: E[payoff] if approved | L42: E[payoff] if CRL
A43: Dec-26 $67.50 call | B43: C | C43: =A35 -> 67.5 | D43: =(B35+C35)/2 -> 5.3 | E43: =IF(B35>0,(C35-B35)/D43,9.99) -> 0.79245283 | F43: =IF(B43="C",$B$4*NORMSDIST((LN($B$4/C43)+($B$9+$B$10^2/2)*$B$8)/($B$10*SQRT($B$8)))-C43*EXP(-$B$9*$B$8)*NORMSDIST((LN($B$4/C43)+($B$9+$B$10^2/2)*$B$8)/($B$10*SQRT($B$8))-$B$10*SQRT($B$8)),C43*EXP(-$B$9*$B$8)*NORMSDIST(-((LN($B$4/C43)+($B$9+$B$10^2/2)*$B$8)/($B$10*SQRT($B$8))-$B$10*SQRT($B$8)))-$B$4*NORMSDIST(-(LN($B$4/C43)+($B$9+$B$10^2/2)*$B$8)/($B$10*SQRT($B$8)))) -> 5.5642429 | G43: =IF(AND(B35>0,E43<=0.6),D43,F43) -> 5.5642429 | H43: =IF(AND(B35>0,E43<=0.6),"market","theo") -> theo | I43: =(LN($B$4/C43)+($B$9+$B$10^2/2)*$B$8)/($B$10*SQRT($B$8)) -> 0.067017684 | J43: =IF(B43="C",NORMSDIST(I43),NORMSDIST(I43)-1) -> 0.52671619 | K43: =IF(B43="C",($B$21*NORMSDIST(((LN($B$21/C43)+$B$24^2*$B$8/2)/($B$24*SQRT($B$8))))-C43*NORMSDIST((((LN($B$21/C43)+$B$24^2*$B$8/2)/($B$24*SQRT($B$8)))-$B$24*SQRT($B$8)))),(C43*NORMSDIST(-(((LN($B$21/C43)+$B$24^2*$B$8/2)/($B$24*SQRT($B$8)))-$B$24*SQRT($B$8)))-$B$21*NORMSDIST(-((LN($B$21/C43)+$B$24^2*$B$8/2)/($B$24*SQRT($B$8)))))) -> 3.2600851 | L43: =IF(B43="C",($B$22*NORMSDIST(((LN($B$22/C43)+$B$24^2*$B$8/2)/($B$24*SQRT($B$8))))-C43*NORMSDIST((((LN($B$22/C43)+$B$24^2*$B$8/2)/($B$24*SQRT($B$8)))-$B$24*SQRT($B$8)))),(C43*NORMSDIST(-(((LN($B$22/C43)+$B$24^2*$B$8/2)/($B$24*SQRT($B$8)))-$B$24*SQRT($B$8)))-$B$22*NORMSDIST(-((LN($B$22/C43)+$B$24^2*$B$8/2)/($B$24*SQRT($B$8)))))) -> 1.650797
A44: Dec-26 $67.50 put | B44: P | C44: =A35 -> 67.5 | D44: =(F35+G35)/2 -> 6 | E44: =IF(F35>0,(G35-F35)/D44,9.99) -> 0.66666667 | F44: =IF(B44="C",$B$4*NORMSDIST((LN($B$4/C44)+($B$9+$B$10^2/2)*$B$8)/($B$10*SQRT($B$8)))-C44*EXP(-$B$9*$B$8)*NORMSDIST((LN($B$4/C44)+($B$9+$B$10^2/2)*$B$8)/($B$10*SQRT($B$8))-$B$10*SQRT($B$8)),C44*EXP(-$B$9*$B$8)*NORMSDIST(-((LN($B$4/C44)+($B$9+$B$10^2/2)*$B$8)/($B$10*SQRT($B$8))-$B$10*SQRT($B$8)))-$B$4*NORMSDIST(-(LN($B$4/C44)+($B$9+$B$10^2/2)*$B$8)/($B$10*SQRT($B$8)))) -> 6.2098205 | G44: =IF(AND(F35>0,E44<=0.6),D44,F44) -> 6.2098205 | H44: =IF(AND(F35>0,E44<=0.6),"market","theo") -> theo | I44: =(LN($B$4/C44)+($B$9+$B$10^2/2)*$B$8)/($B$10*SQRT($B$8)) -> 0.067017684 | J44: =IF(B44="C",NORMSDIST(I44),NORMSDIST(I44)-1) -> -0.47328381 | K44: =IF(B44="C",($B$21*NORMSDIST(((LN($B$21/C44)+$B$24^2*$B$8/2)/($B$24*SQRT($B$8))))-C44*NORMSDIST((((LN($B$21/C44)+$B$24^2*$B$8/2)/($B$24*SQRT($B$8)))-$B$24*SQRT($B$8)))),(C44*NORMSDIST(-(((LN($B$21/C44)+$B$24^2*$B$8/2)/($B$24*SQRT($B$8)))-$B$24*SQRT($B$8)))-$B$21*NORMSDIST(-((LN($B$21/C44)+$B$24^2*$B$8/2)/($B$24*SQRT($B$8)))))) -> 3.9012179 | L44: =IF(B44="C",($B$22*NORMSDIST(((LN($B$22/C44)+$B$24^2*$B$8/2)/($B$24*SQRT($B$8))))-C44*NORMSDIST((((LN($B$22/C44)+$B$24^2*$B$8/2)/($B$24*SQRT($B$8)))-$B$24*SQRT($B$8)))),(C44*NORMSDIST(-(((LN($B$22/C44)+$B$24^2*$B$8/2)/($B$24*SQRT($B$8)))-$B$24*SQRT($B$8)))-$B$22*NORMSDIST(-((LN($B$22/C44)+$B$24^2*$B$8/2)/($B$24*SQRT($B$8)))))) -> 6.2166562
A45: Dec-26 $80 call | B45: C | C45: =A39 -> 80 | D45: =(B39+C39)/2 -> 1.7 | E45: =IF(B39>0,(C39-B39)/D45,9.99) -> 9.99 | F45: =IF(B45="C",$B$4*NORMSDIST((LN($B$4/C45)+($B$9+$B$10^2/2)*$B$8)/($B$10*SQRT($B$8)))-C45*EXP(-$B$9*$B$8)*NORMSDIST((LN($B$4/C45)+($B$9+$B$10^2/2)*$B$8)/($B$10*SQRT($B$8))-$B$10*SQRT($B$8)),C45*EXP(-$B$9*$B$8)*NORMSDIST(-((LN($B$4/C45)+($B$9+$B$10^2/2)*$B$8)/($B$10*SQRT($B$8))-$B$10*SQRT($B$8)))-$B$4*NORMSDIST(-(LN($B$4/C45)+($B$9+$B$10^2/2)*$B$8)/($B$10*SQRT($B$8)))) -> 1.8892856 | G45: =IF(AND(B39>0,E45<=0.6),D45,F45) -> 1.8892856 | H45: =IF(AND(B39>0,E45<=0.6),"market","theo") -> theo | I45: =(LN($B$4/C45)+($B$9+$B$10^2/2)*$B$8)/($B$10*SQRT($B$8)) -> -0.70023756 | J45: =IF(B45="C",NORMSDIST(I45),NORMSDIST(I45)-1) -> 0.24188948 | K45: =IF(B45="C",($B$21*NORMSDIST(((LN($B$21/C45)+$B$24^2*$B$8/2)/($B$24*SQRT($B$8))))-C45*NORMSDIST((((LN($B$21/C45)+$B$24^2*$B$8/2)/($B$24*SQRT($B$8)))-$B$24*SQRT($B$8)))),(C45*NORMSDIST(-(((LN($B$21/C45)+$B$24^2*$B$8/2)/($B$24*SQRT($B$8)))-$B$24*SQRT($B$8)))-$B$21*NORMSDIST(-((LN($B$21/C45)+$B$24^2*$B$8/2)/($B$24*SQRT($B$8)))))) -> 0.40212718 | L45: =IF(B45="C",($B$22*NORMSDIST(((LN($B$22/C45)+$B$24^2*$B$8/2)/($B$24*SQRT($B$8))))-C45*NORMSDIST((((LN($B$22/C45)+$B$24^2*$B$8/2)/($B$24*SQRT($B$8)))-$B$24*SQRT($B$8)))),(C45*NORMSDIST(-(((LN($B$22/C45)+$B$24^2*$B$8/2)/($B$24*SQRT($B$8)))-$B$24*SQRT($B$8)))-$B$22*NORMSDIST(-((LN($B$22/C45)+$B$24^2*$B$8/2)/($B$24*SQRT($B$8)))))) -> 0.13514239
A46: Dec-26 $55 put | B46: P | C46: =A30 -> 55 | D46: =(F30+G30)/2 -> 1.85 | E46: =IF(F30>0,(G30-F30)/D46,9.99) -> 9.99 | F46: =IF(B46="C",$B$4*NORMSDIST((LN($B$4/C46)+($B$9+$B$10^2/2)*$B$8)/($B$10*SQRT($B$8)))-C46*EXP(-$B$9*$B$8)*NORMSDIST((LN($B$4/C46)+($B$9+$B$10^2/2)*$B$8)/($B$10*SQRT($B$8))-$B$10*SQRT($B$8)),C46*EXP(-$B$9*$B$8)*NORMSDIST(-((LN($B$4/C46)+($B$9+$B$10^2/2)*$B$8)/($B$10*SQRT($B$8))-$B$10*SQRT($B$8)))-$B$4*NORMSDIST(-(LN($B$4/C46)+($B$9+$B$10^2/2)*$B$8)/($B$10*SQRT($B$8)))) -> 1.3809855 | G46: =IF(AND(F30>0,E46<=0.6),D46,F46) -> 1.3809855 | H46: =IF(AND(F30>0,E46<=0.6),"market","theo") -> theo | I46: =(LN($B$4/C46)+($B$9+$B$10^2/2)*$B$8)/($B$10*SQRT($B$8)) -> 0.99185864 | J46: =IF(B46="C",NORMSDIST(I46),NORMSDIST(I46)-1) -> -0.16063324 | K46: =IF(B46="C",($B$21*NORMSDIST(((LN($B$21/C46)+$B$24^2*$B$8/2)/($B$24*SQRT($B$8))))-C46*NORMSDIST((((LN($B$21/C46)+$B$24^2*$B$8/2)/($B$24*SQRT($B$8)))-$B$24*SQRT($B$8)))),(C46*NORMSDIST(-(((LN($B$21/C46)+$B$24^2*$B$8/2)/($B$24*SQRT($B$8)))-$B$24*SQRT($B$8)))-$B$21*NORMSDIST(-((LN($B$21/C46)+$B$24^2*$B$8/2)/($B$24*SQRT($B$8)))))) -> 0.25669182 | L46: =IF(B46="C",($B$22*NORMSDIST(((LN($B$22/C46)+$B$24^2*$B$8/2)/($B$24*SQRT($B$8))))-C46*NORMSDIST((((LN($B$22/C46)+$B$24^2*$B$8/2)/($B$24*SQRT($B$8)))-$B$24*SQRT($B$8)))),(C46*NORMSDIST(-(((LN($B$22/C46)+$B$24^2*$B$8/2)/($B$24*SQRT($B$8)))-$B$24*SQRT($B$8)))-$B$22*NORMSDIST(-((LN($B$22/C46)+$B$24^2*$B$8/2)/($B$24*SQRT($B$8)))))) -> 0.6398801
A48: Strategies (+ = credit received, − = debit paid; per share unless noted)
A49: Metric | B49: Long straddle | C49: Bull call spread | D49: Bear put spread | E49: Iron butterfly
A50: Structure | B50: Buy $67.50 call + $67.50 put | C50: Buy $67.50 / sell $80 call | D50: Buy $67.50 / sell $55 put | E50: Sell $67.50 straddle, buy $55 put + $80 call
A51: Net premium | B51: =-$G$43-$G$44 -> -11.774063 | C51: =-$G$43+$G$45 -> -3.6749573 | D51: =-$G$44+$G$46 -> -4.828835 | E51: =$G$43+$G$44-$G$45-$G$46 -> 8.5037923
A52: Net premium / contract | B52: =B51*$B$11 -> -1177.4063 | C52: =C51*$B$11 -> -367.49573 | D52: =D51*$B$11 -> -482.8835 | E52: =E51*$B$11 -> 850.37923
A53: Max profit / contract | B53: ="Unlimited" -> Unlimited | C53: =(80.0-67.5+C51)*$B$11 -> 882.50427 | D53: =(67.5-55.0+D51)*$B$11 -> 767.1165 | E53: =E51*$B$11 -> 850.37923
A54: Max loss / contract | B54: =B51*$B$11 -> -1177.4063 | C54: =C51*$B$11 -> -367.49573 | D54: =D51*$B$11 -> -482.8835 | E54: =-(MAX(80.0-67.5,67.5-55.0)-E51)*$B$11 -> -399.62077
A55: Breakeven (low) | B55: =67.5+B51 -> 55.725937 | C55: ="—" -> — | D55: =67.5+D51 -> 62.671165 | E55: =67.5-E51 -> 58.996208
A56: Breakeven (high) | B56: =67.5-B51 -> 79.274063 | C56: =67.5-C51 -> 71.174957 | D56: ="—" -> — | E56: =67.5+E51 -> 76.003792
A57: Prob. of profit (market-implied, lognormal) | B57: =(1-NORMSDIST((LN($B$4/B55)+($B$9-IF((($E$35+$I$35)/2)>0,(($E$35+$I$35)/2),$B$10)^2/2)*$B$8)/(IF((($E$35+$I$35)/2)>0,(($E$35+$I$35)/2),$B$10)*SQRT($B$8))))+NORMSDIST((LN($B$4/B56)+($B$9-IF((($E$35+$I$35)/2)>0,(($E$35+$I$35)/2),$B$10)^2/2)*$B$8)/(IF((($E$35+$I$35)/2)>0,(($E$35+$I$35)/2),$B$10)*SQRT($B$8))) -> 0.40681702 | C57: =NORMSDIST((LN($B$4/C56)+($B$9-IF((($E$35+$I$35)/2)>0,(($E$35+$I$35)/2),$B$10)^2/2)*$B$8)/(IF((($E$35+$I$35)/2)>0,(($E$35+$I$35)/2),$B$10)*SQRT($B$8))) -> 0.34388247 | D57: =1-NORMSDIST((LN($B$4/D55)+($B$9-IF((($E$35+$I$35)/2)>0,(($E$35+$I$35)/2),$B$10)^2/2)*$B$8)/(IF((($E$35+$I$35)/2)>0,(($E$35+$I$35)/2),$B$10)*SQRT($B$8))) -> 0.42118357 | E57: =MAX(0,NORMSDIST((LN($B$4/E55)+($B$9-IF((($E$35+$I$35)/2)>0,(($E$35+$I$35)/2),$B$10)^2/2)*$B$8)/(IF((($E$35+$I$35)/2)>0,(($E$35+$I$35)/2),$B$10)*SQRT($B$8)))-NORMSDIST((LN($B$4/E56)+($B$9-IF((($E$35+$I$35)/2)>0,(($E$35+$I$35)/2),$B$10)^2/2)*$B$8)/(IF((($E$35+$I$35)/2)>0,(($E$35+$I$35)/2),$B$10)*SQRT($B$8)))) -> 0.4475806
A58: Expected P/L if approved | B58: =((1)*$K$43+(1)*$K$44+B51)*$B$11 -> -461.27605 | C58: =((1)*$K$43+(-1)*$K$45+C51)*$B$11 -> -81.699939 | D58: =((1)*$K$44+(-1)*$K$46+D51)*$B$11 -> -118.4309 | E58: =((-1)*$K$43+(-1)*$K$44+(1)*$K$45+(1)*$K$46+E51)*$B$11 -> 200.13084
A59: Expected P/L if CRL | B59: =((1)*$L$43+(1)*$L$44+B51)*$B$11 -> -390.66102 | C59: =((1)*$L$43+(-1)*$L$45+C51)*$B$11 -> -215.93026 | D59: =((1)*$L$44+(-1)*$L$46+D51)*$B$11 -> 74.79411 | E59: =((-1)*$L$43+(-1)*$L$44+(1)*$L$45+(1)*$L$46+E51)*$B$11 -> 141.13616
A60: Model expected P/L | B60: =$B$17*B58+(1-$B$17)*B59 -> -452.80224 | C60: =$B$17*C58+(1-$B$17)*C59 -> -97.807578 | D60: =$B$17*D58+(1-$B$17)*D59 -> -95.243898 | E60: =$B$17*E58+(1-$B$17)*E59 -> 193.05148
A61: Expected P/L ÷ max loss | B61: =B60/-B54 -> -0.38457602 | C61: =C60/-C54 -> -0.26614616 | D61: =D60/-D54 -> -0.19723991 | E61: =E60/-E54 -> 0.48308669
A63: Payoff at expiry per contract ($)
A64: Price at expiry | B64: Long straddle | C64: Bull call spread | D64: Bear put spread | E64: Iron butterfly
A65: 31.1 | B65: =(MAX($A65-67.5,0)+MAX(67.5-$A65,0)-$G$43-$G$44)*$B$11 -> 2462.5937 | C65: =(MAX($A65-67.5,0)-MAX($A65-80.0,0)-$G$43+$G$45)*$B$11 -> -367.49573 | D65: =(MAX(67.5-$A65,0)-MAX(55.0-$A65,0)-$G$44+$G$46)*$B$11 -> 767.1165 | E65: =($G$43+$G$44-$G$45-$G$46-MAX($A65-67.5,0)-MAX(67.5-$A65,0)+MAX($A65-80.0,0)+MAX(55.0-$A65,0))*$B$11 -> -399.62077
A66: 33.4 | B66: =(MAX($A66-67.5,0)+MAX(67.5-$A66,0)-$G$43-$G$44)*$B$11 -> 2232.5937 | C66: =(MAX($A66-67.5,0)-MAX($A66-80.0,0)-$G$43+$G$45)*$B$11 -> -367.49573 | D66: =(MAX(67.5-$A66,0)-MAX(55.0-$A66,0)-$G$44+$G$46)*$B$11 -> 767.1165 | E66: =($G$43+$G$44-$G$45-$G$46-MAX($A66-67.5,0)-MAX(67.5-$A66,0)+MAX($A66-80.0,0)+MAX(55.0-$A66,0))*$B$11 -> -399.62077
A67: 35.8 | B67: =(MAX($A67-67.5,0)+MAX(67.5-$A67,0)-$G$43-$G$44)*$B$11 -> 1992.5937 | C67: =(MAX($A67-67.5,0)-MAX($A67-80.0,0)-$G$43+$G$45)*$B$11 -> -367.49573 | D67: =(MAX(67.5-$A67,0)-MAX(55.0-$A67,0)-$G$44+$G$46)*$B$11 -> 767.1165 | E67: =($G$43+$G$44-$G$45-$G$46-MAX($A67-67.5,0)-MAX(67.5-$A67,0)+MAX($A67-80.0,0)+MAX(55.0-$A67,0))*$B$11 -> -399.62077
A68: 38.1 | B68: =(MAX($A68-67.5,0)+MAX(67.5-$A68,0)-$G$43-$G$44)*$B$11 -> 1762.5937 | C68: =(MAX($A68-67.5,0)-MAX($A68-80.0,0)-$G$43+$G$45)*$B$11 -> -367.49573 | D68: =(MAX(67.5-$A68,0)-MAX(55.0-$A68,0)-$G$44+$G$46)*$B$11 -> 767.1165 | E68: =($G$43+$G$44-$G$45-$G$46-MAX($A68-67.5,0)-MAX(67.5-$A68,0)+MAX($A68-80.0,0)+MAX(55.0-$A68,0))*$B$11 -> -399.62077
A69: 40.5 | B69: =(MAX($A69-67.5,0)+MAX(67.5-$A69,0)-$G$43-$G$44)*$B$11 -> 1522.5937 | C69: =(MAX($A69-67.5,0)-MAX($A69-80.0,0)-$G$43+$G$45)*$B$11 -> -367.49573 | D69: =(MAX(67.5-$A69,0)-MAX(55.0-$A69,0)-$G$44+$G$46)*$B$11 -> 767.1165 | E69: =($G$43+$G$44-$G$45-$G$46-MAX($A69-67.5,0)-MAX(67.5-$A69,0)+MAX($A69-80.0,0)+MAX(55.0-$A69,0))*$B$11 -> -399.62077
A70: 42.8 | B70: =(MAX($A70-67.5,0)+MAX(67.5-$A70,0)-$G$43-$G$44)*$B$11 -> 1292.5937 | C70: =(MAX($A70-67.5,0)-MAX($A70-80.0,0)-$G$43+$G$45)*$B$11 -> -367.49573 | D70: =(MAX(67.5-$A70,0)-MAX(55.0-$A70,0)-$G$44+$G$46)*$B$11 -> 767.1165 | E70: =($G$43+$G$44-$G$45-$G$46-MAX($A70-67.5,0)-MAX(67.5-$A70,0)+MAX($A70-80.0,0)+MAX(55.0-$A70,0))*$B$11 -> -399.62077
A71: 45.2 | B71: =(MAX($A71-67.5,0)+MAX(67.5-$A71,0)-$G$43-$G$44)*$B$11 -> 1052.5937 | C71: =(MAX($A71-67.5,0)-MAX($A71-80.0,0)-$G$43+$G$45)*$B$11 -> -367.49573 | D71: =(MAX(67.5-$A71,0)-MAX(55.0-$A71,0)-$G$44+$G$46)*$B$11 -> 767.1165 | E71: =($G$43+$G$44-$G$45-$G$46-MAX($A71-67.5,0)-MAX(67.5-$A71,0)+MAX($A71-80.0,0)+MAX(55.0-$A71,0))*$B$11 -> -399.62077
A72: 47.6 | B72: =(MAX($A72-67.5,0)+MAX(67.5-$A72,0)-$G$43-$G$44)*$B$11 -> 812.59366 | C72: =(MAX($A72-67.5,0)-MAX($A72-80.0,0)-$G$43+$G$45)*$B$11 -> -367.49573 | D72: =(MAX(67.5-$A72,0)-MAX(55.0-$A72,0)-$G$44+$G$46)*$B$11 -> 767.1165 | E72: =($G$43+$G$44-$G$45-$G$46-MAX($A72-67.5,0)-MAX(67.5-$A72,0)+MAX($A72-80.0,0)+MAX(55.0-$A72,0))*$B$11 -> -399.62077
A73: 49.9 | B73: =(MAX($A73-67.5,0)+MAX(67.5-$A73,0)-$G$43-$G$44)*$B$11 -> 582.59366 | C73: =(MAX($A73-67.5,0)-MAX($A73-80.0,0)-$G$43+$G$45)*$B$11 -> -367.49573 | D73: =(MAX(67.5-$A73,0)-MAX(55.0-$A73,0)-$G$44+$G$46)*$B$11 -> 767.1165 | E73: =($G$43+$G$44-$G$45-$G$46-MAX($A73-67.5,0)-MAX(67.5-$A73,0)+MAX($A73-80.0,0)+MAX(55.0-$A73,0))*$B$11 -> -399.62077
A74: 52.3 | B74: =(MAX($A74-67.5,0)+MAX(67.5-$A74,0)-$G$43-$G$44)*$B$11 -> 342.59366 | C74: =(MAX($A74-67.5,0)-MAX($A74-80.0,0)-$G$43+$G$45)*$B$11 -> -367.49573 | D74: =(MAX(67.5-$A74,0)-MAX(55.0-$A74,0)-$G$44+$G$46)*$B$11 -> 767.1165 | E74: =($G$43+$G$44-$G$45-$G$46-MAX($A74-67.5,0)-MAX(67.5-$A74,0)+MAX($A74-80.0,0)+MAX(55.0-$A74,0))*$B$11 -> -399.62077
A75: 54.6 | B75: =(MAX($A75-67.5,0)+MAX(67.5-$A75,0)-$G$43-$G$44)*$B$11 -> 112.59366 | C75: =(MAX($A75-67.5,0)-MAX($A75-80.0,0)-$G$43+$G$45)*$B$11 -> -367.49573 | D75: =(MAX(67.5-$A75,0)-MAX(55.0-$A75,0)-$G$44+$G$46)*$B$11 -> 767.1165 | E75: =($G$43+$G$44-$G$45-$G$46-MAX($A75-67.5,0)-MAX(67.5-$A75,0)+MAX($A75-80.0,0)+MAX(55.0-$A75,0))*$B$11 -> -399.62077
A76: 57 | B76: =(MAX($A76-67.5,0)+MAX(67.5-$A76,0)-$G$43-$G$44)*$B$11 -> -127.40634 | C76: =(MAX($A76-67.5,0)-MAX($A76-80.0,0)-$G$43+$G$45)*$B$11 -> -367.49573 | D76: =(MAX(67.5-$A76,0)-MAX(55.0-$A76,0)-$G$44+$G$46)*$B$11 -> 567.1165 | E76: =($G$43+$G$44-$G$45-$G$46-MAX($A76-67.5,0)-MAX(67.5-$A76,0)+MAX($A76-80.0,0)+MAX(55.0-$A76,0))*$B$11 -> -199.62077
... A95: 101.7 | B95: =(MAX($A95-67.5,0)+MAX(67.5-$A95,0)-$G$43-$G$44)*$B$11 -> 2242.5937 | C95: =(MAX($A95-67.5,0)-MAX($A95-80.0,0)-$G$43+$G$45)*$B$11 -> 882.50427 | D95: =(MAX(67.5-$A95,0)-MAX(55.0-$A95,0)-$G$44+$G$46)*$B$11 -> -482.8835 | E95: =($G$43+$G$44-$G$45-$G$46-MAX($A95-67.5,0)-MAX(67.5-$A95,0)+MAX($A95-80.0,0)+MAX(55.0-$A95,0))*$B$11 -> -399.62077
