Workbook

Sheet Main
B2: Caris Life Sciences, Inc.
B3: Price | C3: =INDEX([1]Pharma!$F$1:$F$1000,MATCH("CAI",[1]Pharma!$B$1:$B$1000,0)) -> 31.11
B4: Shares | C4: 282.59519
B5: Market Cap. | C5: =C3*C4 -> 8791.5362
B7: Cash | C7: 102.2
B8: Debt | C8: =0.178+392.973 -> 393.151
B9: Enterprise V. | C9: =C5-C7+C8 -> 9082.4872
B11: NPV / Share | C11: =NPV!B28 -> 21.409855
B12: Upside | C12: =IFERROR(C11/C3-1,"") -> -0.31180152
B13: Cash / Share | C13: =IFERROR((C7-C8)/C4,"") -> -1.0295681
B14: Scenario | C14: =Assumptions!C4 -> Base
B15: Model | C15: DCF

Sheet Yearly Model
B1: 2023 | C1: 2024 | D1: 2025 | E1: 2026 | F1: 2027 | G1: 2028 | H1: 2029 | I1: 2030 | J1: 2031 | K1: 2032 | L1: 2033 | M1: 2034 | N1: 2035
A2: Revenue | B2: 306.128 | C2: 412.26 | D2: 812.033 | E2: =D2*(1+NPV!C5) -> 1096.2446 | F2: =E2*(1+NPV!D5) -> 1440.3435 | G2: =F2*(1+NPV!E5) -> 1840.439 | H2: =G2*(1+NPV!F5) -> 2285.2117 | I2: =H2*(1+NPV!G5) -> 2754.9497 | J2: =I2*(1+NPV!H5) -> 3221.7606 | K2: =J2*(1+NPV!I5) -> 3651.3287 | L2: =K2*(1+NPV!J5) -> 4006.319 | ... N2: =M2*(1+NPV!L5) -> 4357.4283
A3: Cost of Sales | B3: 0 | C3: 0 | D3: 0 | E3: =E2*(1-Assumptions!$B$19) -> 0 | F3: =F2*(1-Assumptions!$B$19) -> 0 | G3: =G2*(1-Assumptions!$B$19) -> 0 | H3: =H2*(1-Assumptions!$B$19) -> 0 | I3: =I2*(1-Assumptions!$B$19) -> 0 | J3: =J2*(1-Assumptions!$B$19) -> 0 | K3: =K2*(1-Assumptions!$B$19) -> 0 | L3: =L2*(1-Assumptions!$B$19) -> 0 | ... N3: =N2*(1-Assumptions!$B$19) -> 0
A4: Gross Margin | B4: =B2-B3 -> 306.128 | C4: =C2-C3 -> 412.26 | D4: =D2-D3 -> 812.033 | E4: =E2-E3 -> 1096.2446 | F4: =F2-F3 -> 1440.3435 | G4: =G2-G3 -> 1840.439 | H4: =H2-H3 -> 2285.2117 | I4: =I2-I3 -> 2754.9497 | ... N4: =N2-N3 -> 4357.4283
A5: Research & Dev. | B5: 116.883 | C5: 113.916 | D5: 101.584 | E5: =E7*Assumptions!$B$20 -> 122.09772 | F5: =F7*Assumptions!$B$20 -> 159.56212 | G5: =G7*Assumptions!$B$20 -> 202.78513 | H5: =H7*Assumptions!$B$20 -> 250.42595 | I5: =I7*Assumptions!$B$20 -> 300.25611 | J5: =J7*Assumptions!$B$20 -> 349.2076 | K5: =K7*Assumptions!$B$20 -> 393.58667 | L5: =L7*Assumptions!$B$20 -> 429.45796 | ... N5: =N7*Assumptions!$B$20 -> 461.8874
A6: SG&A & Other | B6: 508.796 | C6: 555.466 | D6: 665.336 | E6: =E7-E5 -> 799.39449 | F6: =F7-F5 -> 1044.6803 | G6: =G7-G5 -> 1327.6687 | H6: =H7-H5 -> 1639.5812 | I6: =I7-I5 -> 1965.8277 | J6: =J7-J5 -> 2286.3214 | K6: =K7-K5 -> 2576.8787 | L6: =L7-L5 -> 2811.7342 | ... N6: =N7-N5 -> 3024.0552
A7: Operating Expense | B7: =SUM(B5:B6) -> 625.679 | C7: =SUM(C5:C6) -> 669.382 | D7: =SUM(D5:D6) -> 766.92 | E7: =E4-E2*NPV!C6 -> 921.49221 | F7: =F4-F2*NPV!D6 -> 1204.2424 | G7: =G4-G2*NPV!E6 -> 1530.4538 | H7: =H4-H2*NPV!F6 -> 1890.0072 | I7: =I4-I2*NPV!G6 -> 2266.0839 | J7: =J4-J2*NPV!H6 -> 2635.529 | K7: =K4-K2*NPV!I6 -> 2970.4654 | L7: =L4-L2*NPV!J6 -> 3241.1922 | ... N7: =N4-N2*NPV!L6 -> 3485.9426
A8: Operating Income | B8: =B4-B7 -> -319.551 | C8: =C4-C7 -> -257.122 | D8: =D4-D7 -> 45.113 | E8: =E4-E7 -> 174.75234 | F8: =F4-F7 -> 236.10111 | G8: =G4-G7 -> 309.98513 | H8: =H4-H7 -> 395.20451 | I8: =I4-I7 -> 488.86582 | ... N8: =N4-N7 -> 871.48566
A9: Interest & Other | B9: -21.864 | C9: -24.768 | D9: -113.201 | E9: 0 | F9: 0 | G9: 0 | H9: 0 | I9: 0 | J9: 0 | K9: 0 | L9: 0 | M9: 0 | N9: 0
A10: Pretax | B10: =B8+B9 -> -341.415 | C10: =C8+C9 -> -281.89 | D10: =D8+D9 -> -68.088 | E10: =E8+E9 -> 174.75234 | F10: =F8+F9 -> 236.10111 | G10: =G8+G9 -> 309.98513 | H10: =H8+H9 -> 395.20451 | I10: =I8+I9 -> 488.86582 | ... N10: =N8+N9 -> 871.48566
A11: Taxes | B11: 0 | C11: 0 | D11: 0 | E11: =MAX(0,E10)*Assumptions!$E$14 -> 29.707898 | F11: =MAX(0,F10)*Assumptions!$E$14 -> 40.137189 | G11: =MAX(0,G10)*Assumptions!$E$14 -> 52.697473 | H11: =MAX(0,H10)*Assumptions!$E$14 -> 67.184767 | I11: =MAX(0,I10)*Assumptions!$E$14 -> 83.107189 | J11: =MAX(0,J10)*Assumptions!$E$14 -> 99.659365 | K11: =MAX(0,K10)*Assumptions!$E$14 -> 115.74675 | L11: =MAX(0,L10)*Assumptions!$E$14 -> 130.07155 | ... N11: =MAX(0,N10)*Assumptions!$E$14 -> 148.15256
A12: Net Income | B12: -341.415 | C12: -281.89 | D12: -68.088 | E12: =E10-E11 -> 145.04445 | F12: =F10-F11 -> 195.96392 | G12: =G10-G11 -> 257.28766 | H12: =H10-H11 -> 328.01975 | I12: =I10-I11 -> 405.75863 | J12: =J10-J11 -> 486.57219 | K12: =K10-K11 -> 565.1165 | L12: =L10-L11 -> 635.05524 | ... N12: =N10-N11 -> 723.3331
A13: Earnings per Share | B13: =IFERROR(B12/B14,0) -> -9.7706264 | C13: =IFERROR(C12/C14,0) -> -7.9412345 | D13: =IFERROR(D12/D14,0) -> -0.40721027 | E13: =IFERROR(E12/E14,0) -> 0.51325873 | F13: =IFERROR(F12/F14,0) -> 0.69344395 | G13: =IFERROR(G12/G14,0) -> 0.91044602 | H13: =IFERROR(H12/H14,0) -> 1.1607407 | I13: =IFERROR(I12/I14,0) -> 1.4358299 | ... N13: =IFERROR(N12/N14,0) -> 2.5596087
A14: Shares | B14: 34.943 | C14: 35.497 | D14: 167.206 | E14: =Main!$C$4 -> 282.59519 | F14: =Main!$C$4 -> 282.59519 | G14: =Main!$C$4 -> 282.59519 | H14: =Main!$C$4 -> 282.59519 | I14: =Main!$C$4 -> 282.59519 | J14: =Main!$C$4 -> 282.59519 | K14: =Main!$C$4 -> 282.59519 | L14: =Main!$C$4 -> 282.59519 | ... N14: =Main!$C$4 -> 282.59519
A16: Revenue Change | C16: =IFERROR(C2/B2-1,"") -> 0.34669158 | D16: =IFERROR(D2/C2-1,"") -> 0.96971086 | E16: =IFERROR(E2/D2-1,"") -> 0.35 | F16: =IFERROR(F2/E2-1,"") -> 0.31388889 | G16: =IFERROR(G2/F2-1,"") -> 0.27777778 | H16: =IFERROR(H2/G2-1,"") -> 0.24166667 | I16: =IFERROR(I2/H2-1,"") -> 0.20555556 | J16: =IFERROR(J2/I2-1,"") -> 0.16944444 | ... N16: =IFERROR(N2/M2-1,"") -> 0.025
A17: Gross Margin | B17: =IFERROR(B4/B2,"") -> 1 | C17: =IFERROR(C4/C2,"") -> 1 | D17: =IFERROR(D4/D2,"") -> 1 | E17: =IFERROR(E4/E2,"") -> 1 | F17: =IFERROR(F4/F2,"") -> 1 | G17: =IFERROR(G4/G2,"") -> 1 | H17: =IFERROR(H4/H2,"") -> 1 | I17: =IFERROR(I4/I2,"") -> 1 | ... N17: =IFERROR(N4/N2,"") -> 1
A18: Operating Margin | B18: =IFERROR(B8/B2,"") -> -1.0438477 | C18: =IFERROR(C8/C2,"") -> -0.62368893 | D18: =IFERROR(D8/D2,"") -> 0.055555624 | E18: =IFERROR(E8/E2,"") -> 0.15941 | F18: =IFERROR(F8/F2,"") -> 0.16392 | G18: =IFERROR(G8/G2,"") -> 0.16843 | H18: =IFERROR(H8/H2,"") -> 0.17294 | I18: =IFERROR(I8/I2,"") -> 0.17745 | ... N18: =IFERROR(N8/N2,"") -> 0.2
A19: Actual / Estimate | B19: A | C19: A | D19: A | E19: E | F19: E | G19: E | H19: E | I19: E | J19: E | K19: E | L19: E | M19: E | N19: E

Sheet Quarterly Model

Sheet Assumptions
A1: Caris Life Sciences, Inc.: basic DCF assumptions
A2: Blue = input, black = formula, green = link. $mm unless noted.
A4: Scenario (1 Bear, 2 Base, 3 Bull) | B4: 2 | C4: =CHOOSE($B$4,"Bear","Base","Bull") -> Base
A6: Discount rate override (blank = scenario)
A7: Terminal growth override (blank = scenario)
A9: Parameter | B9: Bear | C9: Base | D9: Bull | E9: Live
A10: Discount rate | B10: 0.105 | C10: 0.095 | D10: 0.085 | E10: =IF(ISNUMBER($B$6),$B$6,CHOOSE($B$4,B10,C10,D10)) -> 0.095
A11: Terminal growth | B11: 0.02 | C11: 0.025 | D11: 0.03 | E11: =IF(ISNUMBER($B$7),$B$7,CHOOSE($B$4,B11,C11,D11)) -> 0.025
A12: Revenue growth, first forecast year | B12: 0.3 | C12: 0.35 | D12: 0.4 | E12: =CHOOSE($B$4,B12,C12,D12) -> 0.35
A13: Operating margin, year 10 | B13: 0.15 | C13: 0.2 | D13: 0.25 | E13: =CHOOSE($B$4,B13,C13,D13) -> 0.2
A14: Tax rate on operating income | B14: 0.17 | C14: 0.17 | D14: 0.17 | E14: =CHOOSE($B$4,B14,C14,D14) -> 0.17
A15: Reinvestment, % of revenue increase | B15: 0.25 | C15: 0.25 | D15: 0.25 | E15: =CHOOSE($B$4,B15,C15,D15) -> 0.25
A17: Single inputs
A18: Starting operating margin (TTM) | B18: 0.1549
A19: Gross margin (forecast) | B19: 1
A20: R&D share of operating expense (forecast) | B20: 0.1325
A21: Forecast years | B21: 10
A22: First forecast year, fraction after balance sheet date | B22: 0.5041
A23: Balance sheet date | B23: 46203
A24: Reporting currency per USD (USD) | B24: 1
A25: Base revenue, FY2025 | B25: ='Yearly Model'!D2 -> 812.033
A27: Scenario summary
A28: Scenario | B28: Enterprise value | C28: Equity value | D28: NPV / share | E28: Upside
A29: Live | B29: =NPV!B23 -> 6341.2729 | C29: =NPV!B26 -> 6050.3219 | D29: =NPV!B28 -> 21.409855 | E29: =NPV!B30 -> -0.31180152
A30: 1 | B30: 3264.9269 | C30: 2973.9759 | D30: 10.523803 | E30: -0.66172284
A31: 2 | B31: 6341.2729 | C31: 6050.3219 | D31: 21.409855 | E31: -0.31180152
A32: 3 | B32: 12413.825 | C32: 12122.874 | D32: 42.898373 | E32: 0.37892552
A35: NPV / share: discount rate (rows) x terminal growth (columns)
A36: =NPV!B28 -> 21.409855 | B36: 0.015 | C36: 0.02 | D36: 0.025 | E36: 0.03 | F36: 0.035
A37: 0.075 | B37: 27.241545 | C37: 29.587714 | D37: 32.40174 | E37: 35.839563 | F37: 40.135091
A38: 0.085 | B38: 22.45036 | C38: 24.070902 | D38: 25.96043 | E38: 28.192293 | F38: 30.86918
A39: 0.095 | B39: 18.901028 | C39: 20.072239 | D39: 21.409855 | E39: 22.952268 | F39: 24.750669
A40: 0.105 | B40: 16.176264 | C40: 17.05236 | D40: 18.037202 | E40: 19.152532 | F40: 20.426305
A41: 0.115 | B41: 14.026 | C41: 14.699324 | D41: 15.446809 | E41: 16.281535 | F41: 17.219854

Sheet NPV
A1: Caris Life Sciences, Inc.: free-cash-flow DCF ($mm)
A3: Fiscal year | B3: ='Yearly Model'!D1 -> 2025 | C3: ='Yearly Model'!E1 -> 2026 | D3: ='Yearly Model'!F1 -> 2027 | E3: ='Yearly Model'!G1 -> 2028 | F3: ='Yearly Model'!H1 -> 2029 | G3: ='Yearly Model'!I1 -> 2030 | H3: ='Yearly Model'!J1 -> 2031 | I3: ='Yearly Model'!K1 -> 2032 | ... L3: ='Yearly Model'!N1 -> 2035
A4: Period | B4: Actual | C4: 1 | D4: 2 | E4: 3 | F4: 4 | G4: 5 | H4: 6 | I4: 7 | J4: 8 | K4: 9 | L4: 10
A5: Revenue growth | C5: =Assumptions!$E$12+(Assumptions!$E$11-Assumptions!$E$12)*(C4-1)/(Assumptions!$B$21-1) -> 0.35 | D5: =Assumptions!$E$12+(Assumptions!$E$11-Assumptions!$E$12)*(D4-1)/(Assumptions!$B$21-1) -> 0.31388889 | E5: =Assumptions!$E$12+(Assumptions!$E$11-Assumptions!$E$12)*(E4-1)/(Assumptions!$B$21-1) -> 0.27777778 | F5: =Assumptions!$E$12+(Assumptions!$E$11-Assumptions!$E$12)*(F4-1)/(Assumptions!$B$21-1) -> 0.24166667 | G5: =Assumptions!$E$12+(Assumptions!$E$11-Assumptions!$E$12)*(G4-1)/(Assumptions!$B$21-1) -> 0.20555556 | H5: =Assumptions!$E$12+(Assumptions!$E$11-Assumptions!$E$12)*(H4-1)/(Assumptions!$B$21-1) -> 0.16944444 | I5: =Assumptions!$E$12+(Assumptions!$E$11-Assumptions!$E$12)*(I4-1)/(Assumptions!$B$21-1) -> 0.13333333 | J5: =Assumptions!$E$12+(Assumptions!$E$11-Assumptions!$E$12)*(J4-1)/(Assumptions!$B$21-1) -> 0.097222222 | ... L5: =Assumptions!$E$12+(Assumptions!$E$11-Assumptions!$E$12)*(L4-1)/(Assumptions!$B$21-1) -> 0.025
A6: Operating margin | B6: =IFERROR(B8/B7,0) -> 0.055555624 | C6: =Assumptions!$B$18+(Assumptions!$E$13-Assumptions!$B$18)*C4/Assumptions!$B$21 -> 0.15941 | D6: =Assumptions!$B$18+(Assumptions!$E$13-Assumptions!$B$18)*D4/Assumptions!$B$21 -> 0.16392 | E6: =Assumptions!$B$18+(Assumptions!$E$13-Assumptions!$B$18)*E4/Assumptions!$B$21 -> 0.16843 | F6: =Assumptions!$B$18+(Assumptions!$E$13-Assumptions!$B$18)*F4/Assumptions!$B$21 -> 0.17294 | G6: =Assumptions!$B$18+(Assumptions!$E$13-Assumptions!$B$18)*G4/Assumptions!$B$21 -> 0.17745 | H6: =Assumptions!$B$18+(Assumptions!$E$13-Assumptions!$B$18)*H4/Assumptions!$B$21 -> 0.18196 | I6: =Assumptions!$B$18+(Assumptions!$E$13-Assumptions!$B$18)*I4/Assumptions!$B$21 -> 0.18647 | J6: =Assumptions!$B$18+(Assumptions!$E$13-Assumptions!$B$18)*J4/Assumptions!$B$21 -> 0.19098 | ... L6: =Assumptions!$B$18+(Assumptions!$E$13-Assumptions!$B$18)*L4/Assumptions!$B$21 -> 0.2
A7: Revenue | B7: ='Yearly Model'!D2 -> 812.033 | C7: ='Yearly Model'!E2 -> 1096.2446 | D7: ='Yearly Model'!F2 -> 1440.3435 | E7: ='Yearly Model'!G2 -> 1840.439 | F7: ='Yearly Model'!H2 -> 2285.2117 | G7: ='Yearly Model'!I2 -> 2754.9497 | H7: ='Yearly Model'!J2 -> 3221.7606 | I7: ='Yearly Model'!K2 -> 3651.3287 | ... L7: ='Yearly Model'!N2 -> 4357.4283
A8: Operating income | B8: ='Yearly Model'!D8 -> 45.113 | C8: ='Yearly Model'!E8 -> 174.75234 | D8: ='Yearly Model'!F8 -> 236.10111 | E8: ='Yearly Model'!G8 -> 309.98513 | F8: ='Yearly Model'!H8 -> 395.20451 | G8: ='Yearly Model'!I8 -> 488.86582 | H8: ='Yearly Model'!J8 -> 586.23156 | I8: ='Yearly Model'!K8 -> 680.86326 | ... L8: ='Yearly Model'!N8 -> 871.48566
A9: Tax on operating income | C9: =MAX(0,C8)*Assumptions!$E$14 -> 29.707898 | D9: =MAX(0,D8)*Assumptions!$E$14 -> 40.137189 | E9: =MAX(0,E8)*Assumptions!$E$14 -> 52.697473 | F9: =MAX(0,F8)*Assumptions!$E$14 -> 67.184767 | G9: =MAX(0,G8)*Assumptions!$E$14 -> 83.107189 | H9: =MAX(0,H8)*Assumptions!$E$14 -> 99.659365 | I9: =MAX(0,I8)*Assumptions!$E$14 -> 115.74675 | J9: =MAX(0,J8)*Assumptions!$E$14 -> 130.07155 | ... L9: =MAX(0,L8)*Assumptions!$E$14 -> 148.15256
A10: NOPAT | C10: =C8-C9 -> 145.04445 | D10: =D8-D9 -> 195.96392 | E10: =E8-E9 -> 257.28766 | F10: =F8-F9 -> 328.01975 | G10: =G8-G9 -> 405.75863 | H10: =H8-H9 -> 486.57219 | I10: =I8-I9 -> 565.1165 | J10: =J8-J9 -> 635.05524 | ... L10: =L8-L9 -> 723.3331
A11: Reinvestment | C11: =(C7-B7)*Assumptions!$E$15 -> 71.052888 | D11: =(D7-C7)*Assumptions!$E$15 -> 86.024746 | E11: =(E7-D7)*Assumptions!$E$15 -> 100.02386 | F11: =(F7-E7)*Assumptions!$E$15 -> 111.19319 | G11: =(G7-F7)*Assumptions!$E$15 -> 117.43449 | H11: =(H7-G7)*Assumptions!$E$15 -> 116.70273 | I11: =(I7-H7)*Assumptions!$E$15 -> 107.39202 | J11: =(J7-I7)*Assumptions!$E$15 -> 88.747572 | ... L11: =(L7-K7)*Assumptions!$E$15 -> 26.569685
A12: Free cash flow | C12: =C10-C11 -> 73.991558 | D12: =D10-D11 -> 109.93918 | E12: =E10-E11 -> 157.2638 | F12: =F10-F11 -> 216.82656 | G12: =G10-G11 -> 288.32414 | H12: =H10-H11 -> 369.86946 | I12: =I10-I11 -> 457.72448 | J12: =J10-J11 -> 546.30767 | ... L12: =L10-L11 -> 696.76341
A13: Year fraction | C13: =Assumptions!$B$22 -> 0.5041 | D13: 1 | E13: 1 | F13: 1 | G13: 1 | H13: 1 | I13: 1 | J13: 1 | K13: 1 | L13: 1
A14: Discount time (mid-period) | C14: =C13/2 -> 0.25205 | D14: =C14+C13/2+D13/2 -> 1.0041 | E14: =D14+D13/2+E13/2 -> 2.0041 | F14: =E14+E13/2+F13/2 -> 3.0041 | G14: =F14+F13/2+G13/2 -> 4.0041 | H14: =G14+G13/2+H13/2 -> 5.0041 | I14: =H14+H13/2+I13/2 -> 6.0041 | J14: =I14+I13/2+J13/2 -> 7.0041 | K14: =J14+J13/2+K13/2 -> 8.0041 | L14: =K14+K13/2+L13/2 -> 9.0041
A15: Discount factor | C15: =1/(1+Assumptions!$E$10)^C14 -> 0.977385 | D15: =1/(1+Assumptions!$E$10)^D14 -> 0.91290226 | E15: =1/(1+Assumptions!$E$10)^E14 -> 0.8337007 | F15: =1/(1+Assumptions!$E$10)^F14 -> 0.7613705 | G15: =1/(1+Assumptions!$E$10)^G14 -> 0.69531552 | H15: =1/(1+Assumptions!$E$10)^H14 -> 0.63499135 | I15: =1/(1+Assumptions!$E$10)^I14 -> 0.57990077 | J15: =1/(1+Assumptions!$E$10)^J14 -> 0.52958975 | ... L15: =1/(1+Assumptions!$E$10)^L14 -> 0.44168366
A16: PV of free cash flow | C16: =C12*C13*C15 -> 36.455624 | D16: =D12*D13*D15 -> 100.36372 | E16: =E12*E13*E15 -> 131.11094 | F16: =F12*F13*F15 -> 165.08534 | G16: =G12*G13*G15 -> 200.47625 | H16: =H12*H13*H15 -> 234.86391 | I16: =I12*I13*I15 -> 265.43478 | J16: =J12*J13*J15 -> 289.31894 | ... L16: =L12*L13*L15 -> 307.74901
A19: PV of forecast free cash flow | B19: =SUM(C16:L16) -> 2034.8623
A20: Terminal free cash flow (year 11) | B20: =L10*(1+Assumptions!$E$11)-L7*Assumptions!$E$11*Assumptions!$E$15 -> 714.1825
A21: Terminal value | B21: =B20/(Assumptions!$E$10-Assumptions!$E$11) -> 10202.607
A22: PV of terminal value | B22: =B21/(1+Assumptions!$E$10)^(L14+0.5) -> 4306.4106
A23: Enterprise value | B23: =B19+B22 -> 6341.2729
A24: Cash & investments | B24: =Main!C7 -> 102.2
A25: Debt | B25: =Main!C8 -> 393.151
A26: Equity value | B26: =B23+B24-B25 -> 6050.3219
A27: Shares (mm) | B27: =Main!C4 -> 282.59519
A28: NPV / share | B28: =B26/B27 -> 21.409855
A29: Price | B29: =Main!C3 -> 31.11
A30: Upside | B30: =B28/B29-1 -> -0.31180152
A31: Terminal value, % of EV | B31: =IFERROR(B22/B23,0) -> 0.67910822
