Workbook

Sheet Main
B2: Cronos Group Inc.
B3: Price | C3: =INDEX([1]Pharma!$F$1:$F$1000,MATCH("CRON",[1]Pharma!$B$1:$B$1000,0)) -> 3.28
B4: Shares | C4: 368.41286
B5: Market Cap. | C5: =C3*C4 -> 1208.3942
B7: Cash | C7: =467.019+330 -> 797.019
B8: Debt | C8: 0
B9: Enterprise V. | C9: =C5-C7+C8 -> 411.37519
B11: NPV / Share | C11: =NPV!B28 -> 4.7836435
B12: Upside | C12: =IFERROR(C11/C3-1,"") -> 0.45842788
B13: Cash / Share | C13: =IFERROR((C7-C8)/C4,"") -> 2.1633854
B14: Scenario | C14: =Assumptions!C4 -> Base
B15: Model | C15: DCF

Sheet Yearly Model
B1: 2016 | C1: 2017 | D1: 2018 | E1: 2019 | F1: 2020 | G1: 2021 | H1: 2022 | I1: 2023 | J1: 2024 | K1: 2025 | L1: 2026 | M1: 2027 | N1: 2028 | O1: 2029 | P1: 2030 | Q1: 2031 | R1: 2032 | S1: 2033 | T1: 2034 | U1: 2035
A2: Revenue | B2: 0.391 | C2: 3.147 | D2: 13.234 | E2: 25.639 | F2: 54.353 | G2: 79.612 | H2: 109.301 | I2: 120.27 | J2: 161.821 | K2: 193.363 | L2: =K2*(1+NPV!C5) -> 260.16992 | M2: =L2*(1+NPV!D5) -> 340.79368 | N2: =M2*(1+NPV!E5) -> 434.26582 | O2: =N2*(1+NPV!F5) -> 537.91059 | P2: =O2*(1+NPV!G5) -> 647.13633 | Q2: =P2*(1+NPV!H5) -> 755.49571 | R2: =Q2*(1+NPV!I5) -> 855.09523 | S2: =R2*(1+NPV!J5) -> 937.37439 | ... U2: =T2*(1+NPV!L5) -> 1019.0444
A3: Cost of Sales | B3: 0 | C3: 0 | D3: 0 | E3: 0 | F3: 0 | G3: 0 | H3: 0 | I3: 0 | J3: 0 | K3: 0 | L3: =L2*(1-Assumptions!$B$19) -> 0 | M3: =M2*(1-Assumptions!$B$19) -> 0 | N3: =N2*(1-Assumptions!$B$19) -> 0 | O3: =O2*(1-Assumptions!$B$19) -> 0 | P3: =P2*(1-Assumptions!$B$19) -> 0 | Q3: =Q2*(1-Assumptions!$B$19) -> 0 | R3: =R2*(1-Assumptions!$B$19) -> 0 | S3: =S2*(1-Assumptions!$B$19) -> 0 | ... U3: =U2*(1-Assumptions!$B$19) -> 0
A4: Gross Margin | B4: =B2-B3 -> 0.391 | C4: =C2-C3 -> 3.147 | D4: =D2-D3 -> 13.234 | E4: =E2-E3 -> 25.639 | F4: =F2-F3 -> 54.353 | G4: =G2-G3 -> 79.612 | H4: =H2-H3 -> 109.301 | I4: =I2-I3 -> 120.27 | ... U4: =U2-U3 -> 1019.0444
A5: Research & Dev. | B5: 0 | C5: 0 | D5: 1.814 | E5: 12.155 | F5: 20.366 | G5: 21.841 | H5: 13.131 | I5: 5.843 | J5: 4.229 | K5: 4.449 | L5: =L7*Assumptions!$B$20 -> 5.430682 | M5: =M7*Assumptions!$B$20 -> 6.9623686 | N5: =N7*Assumptions!$B$20 -> 8.6792935 | O5: =O7*Assumptions!$B$20 -> 10.512063 | P5: =P7*Assumptions!$B$20 -> 12.35944 | Q5: =Q7*Assumptions!$B$20 -> 14.093721 | R5: =R7*Assumptions!$B$20 -> 15.572309 | S5: =S7*Assumptions!$B$20 -> 16.654768 | ... U5: =U7*Assumptions!$B$20 -> 17.20147
A6: SG&A & Other | B6: 1.896 | C6: 9.268 | D6: 31.865 | E6: 166.8 | F6: 253.374 | G6: 349.74 | H6: 207.598 | I6: 199.227 | J6: 234.121 | K6: 206.309 | L6: =L7-L5 -> 251.94761 | M6: =M7-M5 -> 323.00771 | N6: =N7-N5 -> 402.66163 | O6: =O7-O5 -> 487.68997 | P6: =P7-P5 -> 573.39601 | Q6: =Q7-Q5 -> 653.85514 | R6: =R7-R5 -> 722.45183 | S6: =S7-S5 -> 772.67071 | ... U6: =U7-U5 -> 798.03408
A7: Operating Expense | B7: =SUM(B5:B6) -> 1.896 | C7: =SUM(C5:C6) -> 9.268 | D7: =SUM(D5:D6) -> 33.679 | E7: =SUM(E5:E6) -> 178.955 | F7: =SUM(F5:F6) -> 273.74 | G7: =SUM(G5:G6) -> 371.581 | H7: =SUM(H5:H6) -> 220.729 | I7: =SUM(I5:I6) -> 205.07 | ... K7: =SUM(K5:K6) -> 210.758 | L7: =L4-L2*NPV!C6 -> 257.37829 | M7: =M4-M2*NPV!D6 -> 329.97008 | N7: =N4-N2*NPV!E6 -> 411.34092 | O7: =O4-O2*NPV!F6 -> 498.20203 | P7: =P4-P2*NPV!G6 -> 585.75545 | Q7: =Q4-Q2*NPV!H6 -> 667.94887 | R7: =R4-R2*NPV!I6 -> 738.02414 | S7: =S4-S2*NPV!J6 -> 789.32548 | ... U7: =U4-U2*NPV!L6 -> 815.23555
A8: Operating Income | B8: =B4-B7 -> -1.505 | C8: =C4-C7 -> -6.121 | D8: =D4-D7 -> -20.445 | E8: =E4-E7 -> -153.316 | F8: =F4-F7 -> -219.387 | G8: =G4-G7 -> -291.969 | H8: =H4-H7 -> -111.428 | I8: =I4-I7 -> -84.8 | ... U8: =U4-U7 -> 203.80889
A9: Interest & Other | B9: 0.263 | C9: 3.776 | D9: -1.191 | E9: 1319.822 | F9: 147.597 | G9: -104.562 | H9: -23.097 | I9: 7.67 | J9: 113.093 | K9: 0.304 | L9: 0 | M9: 0 | N9: 0 | O9: 0 | P9: 0 | Q9: 0 | R9: 0 | S9: 0 | T9: 0 | U9: 0
A10: Pretax | B10: =B8+B9 -> -1.242 | C10: =C8+C9 -> -2.345 | D10: =D8+D9 -> -21.636 | E10: =E8+E9 -> 1166.506 | F10: =F8+F9 -> -71.79 | G10: =G8+G9 -> -396.531 | H10: =H8+H9 -> -134.525 | I10: =I8+I9 -> -77.13 | ... U10: =U8+U9 -> 203.80889
A11: Taxes | B11: -0.401 | C11: -0.862 | D11: 0 | E11: 0 | F11: 1.347 | G11: -0.431 | H11: 34.175 | I11: -3.23 | J11: -3.436 | K11: -14.191 | L11: =MAX(0,L10)*Assumptions!$E$14 -> 0.47457594 | M11: =MAX(0,M10)*Assumptions!$E$14 -> 1.8400133 | N11: =MAX(0,N10)*Assumptions!$E$14 -> 3.8972317 | O11: =MAX(0,O10)*Assumptions!$E$14 -> 6.7504552 | P11: =MAX(0,P10)*Assumptions!$E$14 -> 10.43475 | Q11: =MAX(0,Q10)*Assumptions!$E$14 -> 14.882963 | R11: =MAX(0,R10)*Assumptions!$E$14 -> 19.902085 | S11: =MAX(0,S10)*Assumptions!$E$14 -> 25.168315 | ... U11: =MAX(0,U10)*Assumptions!$E$14 -> 34.647511
A12: Net Income | B12: -0.84 | C12: -1.483 | D12: -21.636 | E12: 1166.506 | F12: -73.137 | G12: -396.1 | H12: -168.7 | I12: -73.9 | J12: 40 | K12: -2.9 | L12: =L10-L11 -> 2.3170473 | M12: =M10-M11 -> 8.9835941 | N12: =N10-N11 -> 19.027661 | O12: =O10-O11 -> 32.958105 | P12: =P10-P11 -> 50.946131 | Q12: =Q10-Q11 -> 72.663879 | R12: =R10-R11 -> 97.169003 | S12: =S10-S11 -> 122.8806 | ... U12: =U10-U11 -> 169.16138
A13: Earnings per Share | B13: =IFERROR(B12/B14,0) -> -0.0053675493 | C13: =IFERROR(C12/C14,0) -> -0.0041942655 | D13: =IFERROR(D12/D14,0) -> -0.062797137 | E13: =IFERROR(E12/E14,0) -> 3.4027572 | F13: =IFERROR(F12/F14,0) -> -0.20802555 | G13: =IFERROR(G12/G14,0) -> -1.0694104 | H13: =IFERROR(H12/H14,0) -> -0.44752521 | I13: =IFERROR(I12/I14,0) -> -0.19398107 | ... U13: =IFERROR(U12/U14,0) -> 0.45916251
A14: Shares | B14: 156.496 | C14: 353.578 | D14: 344.538 | E14: 342.812 | F14: 351.577 | G14: 370.391 | H14: 376.962 | I14: 380.965 | J14: 385.557 | K14: 383.469 | L14: =Main!$C$4 -> 368.41286 | M14: =Main!$C$4 -> 368.41286 | N14: =Main!$C$4 -> 368.41286 | O14: =Main!$C$4 -> 368.41286 | P14: =Main!$C$4 -> 368.41286 | Q14: =Main!$C$4 -> 368.41286 | R14: =Main!$C$4 -> 368.41286 | S14: =Main!$C$4 -> 368.41286 | ... U14: =Main!$C$4 -> 368.41286
A16: Revenue Change | C16: =IFERROR(C2/B2-1,"") -> 7.0485934 | D16: =IFERROR(D2/C2-1,"") -> 3.2052749 | E16: =IFERROR(E2/D2-1,"") -> 0.93735832 | F16: =IFERROR(F2/E2-1,"") -> 1.1199345 | G16: =IFERROR(G2/F2-1,"") -> 0.46472136 | H16: =IFERROR(H2/G2-1,"") -> 0.37292117 | I16: =IFERROR(I2/H2-1,"") -> 0.1003559 | J16: =IFERROR(J2/I2-1,"") -> 0.345481 | ... U16: =IFERROR(U2/T2-1,"") -> 0.025
A17: Gross Margin | B17: =IFERROR(B4/B2,"") -> 1 | C17: =IFERROR(C4/C2,"") -> 1 | D17: =IFERROR(D4/D2,"") -> 1 | E17: =IFERROR(E4/E2,"") -> 1 | F17: =IFERROR(F4/F2,"") -> 1 | G17: =IFERROR(G4/G2,"") -> 1 | H17: =IFERROR(H4/H2,"") -> 1 | I17: =IFERROR(I4/I2,"") -> 1 | ... U17: =IFERROR(U4/U2,"") -> 1
A18: Operating Margin | B18: =IFERROR(B8/B2,"") -> -3.8491049 | C18: =IFERROR(C8/C2,"") -> -1.945027 | D18: =IFERROR(D8/D2,"") -> -1.5448844 | E18: =IFERROR(E8/E2,"") -> -5.9797964 | F18: =IFERROR(F8/F2,"") -> -4.0363365 | G18: =IFERROR(G8/G2,"") -> -3.6673994 | H18: =IFERROR(H8/H2,"") -> -1.01946 | I18: =IFERROR(I8/I2,"") -> -0.70508024 | ... U18: =IFERROR(U8/U2,"") -> 0.2
A19: Actual / Estimate | B19: A | C19: A | D19: A | E19: A | F19: A | G19: A | H19: A | I19: A | J19: A | K19: A | L19: E | M19: E | N19: E | O19: E | P19: E | Q19: E | R19: E | S19: E | T19: E | U19: E

Sheet Quarterly Model

Sheet Assumptions
A1: Cronos Group Inc.: basic DCF assumptions
A2: Blue = input, black = formula, green = link. $mm unless noted.
A4: Scenario (1 Bear, 2 Base, 3 Bull) | B4: 2 | C4: =CHOOSE($B$4,"Bear","Base","Bull") -> Base
A6: Discount rate override (blank = scenario)
A7: Terminal growth override (blank = scenario)
A9: Parameter | B9: Bear | C9: Base | D9: Bull | E9: Live
A10: Discount rate | B10: 0.12 | C10: 0.11 | D10: 0.1 | E10: =IF(ISNUMBER($B$6),$B$6,CHOOSE($B$4,B10,C10,D10)) -> 0.11
A11: Terminal growth | B11: 0.02 | C11: 0.025 | D11: 0.03 | E11: =IF(ISNUMBER($B$7),$B$7,CHOOSE($B$4,B11,C11,D11)) -> 0.025
A12: Revenue growth, first forecast year | B12: 0.2955 | C12: 0.3455 | D12: 0.3955 | E12: =CHOOSE($B$4,B12,C12,D12) -> 0.3455
A13: Operating margin, year 10 | B13: 0.15 | C13: 0.2 | D13: 0.25 | E13: =CHOOSE($B$4,B13,C13,D13) -> 0.2
A14: Tax rate on operating income | B14: 0.17 | C14: 0.17 | D14: 0.17 | E14: =CHOOSE($B$4,B14,C14,D14) -> 0.17
A15: Reinvestment, % of revenue increase | B15: 0.25 | C15: 0.25 | D15: 0.25 | E15: =CHOOSE($B$4,B15,C15,D15) -> 0.25
A17: Single inputs
A18: Starting operating margin (TTM) | B18: -0.0103
A19: Gross margin (forecast) | B19: 1
A20: R&D share of operating expense (forecast) | B20: 0.0211
A21: Forecast years | B21: 10
A22: First forecast year, fraction after balance sheet date | B22: 0.5041
A23: Balance sheet date | B23: 46203
A24: Reporting currency per USD (USD) | B24: 1
A25: Base revenue, FY2025 | B25: ='Yearly Model'!K2 -> 193.363
A27: Scenario summary
A28: Scenario | B28: Enterprise value | C28: Equity value | D28: NPV / share | E28: Upside
A29: Live | B29: =NPV!B23 -> 965.33679 | C29: =NPV!B26 -> 1762.3558 | D29: =NPV!B28 -> 4.7836435 | E29: =NPV!B30 -> 0.45842788
A30: 1 | B30: 454.24817 | C30: 1251.2672 | D30: 3.3963721 | E30: 0.035479293
A31: 2 | B31: 965.33679 | C31: 1762.3558 | D31: 4.7836435 | E31: 0.45842788
A32: 3 | B32: 1927.8808 | C32: 2724.8998 | D32: 7.3963209 | E32: 1.2549759
A35: NPV / share: discount rate (rows) x terminal growth (columns)
A36: =NPV!B28 -> 4.7836435 | B36: 0.015 | C36: 0.02 | D36: 0.025 | E36: 0.03 | F36: 0.035
A37: 0.09 | B37: 5.4515386 | C37: 5.6949023 | D37: 5.9759156 | E37: 6.3039938 | F37: 6.6919761
A38: 0.1 | B38: 4.9136027 | C38: 5.0921735 | D38: 5.2947223 | E38: 5.5263898 | F38: 5.7938982
A39: 0.11 | B39: 4.4975871 | C39: 4.6326037 | D39: 4.7836435 | E39: 4.9537127 | F39: 5.1466194
A40: 0.12 | B40: 4.1680223 | C40: 4.272572 | D40: 4.3882431 | E40: 4.5168908 | F40: 4.6608067
A41: 0.13 | B41: 3.9018311 | C41: 3.9843777 | D41: 4.0748844 | E41: 4.1745465 | F41: 4.284811

Sheet NPV
A1: Cronos Group Inc.: free-cash-flow DCF ($mm)
A3: Fiscal year | B3: ='Yearly Model'!K1 -> 2025 | C3: ='Yearly Model'!L1 -> 2026 | D3: ='Yearly Model'!M1 -> 2027 | E3: ='Yearly Model'!N1 -> 2028 | F3: ='Yearly Model'!O1 -> 2029 | G3: ='Yearly Model'!P1 -> 2030 | H3: ='Yearly Model'!Q1 -> 2031 | I3: ='Yearly Model'!R1 -> 2032 | ... L3: ='Yearly Model'!U1 -> 2035
A4: Period | B4: Actual | C4: 1 | D4: 2 | E4: 3 | F4: 4 | G4: 5 | H4: 6 | I4: 7 | J4: 8 | K4: 9 | L4: 10
A5: Revenue growth | C5: =Assumptions!$E$12+(Assumptions!$E$11-Assumptions!$E$12)*(C4-1)/(Assumptions!$B$21-1) -> 0.3455 | D5: =Assumptions!$E$12+(Assumptions!$E$11-Assumptions!$E$12)*(D4-1)/(Assumptions!$B$21-1) -> 0.30988889 | E5: =Assumptions!$E$12+(Assumptions!$E$11-Assumptions!$E$12)*(E4-1)/(Assumptions!$B$21-1) -> 0.27427778 | F5: =Assumptions!$E$12+(Assumptions!$E$11-Assumptions!$E$12)*(F4-1)/(Assumptions!$B$21-1) -> 0.23866667 | G5: =Assumptions!$E$12+(Assumptions!$E$11-Assumptions!$E$12)*(G4-1)/(Assumptions!$B$21-1) -> 0.20305556 | H5: =Assumptions!$E$12+(Assumptions!$E$11-Assumptions!$E$12)*(H4-1)/(Assumptions!$B$21-1) -> 0.16744444 | I5: =Assumptions!$E$12+(Assumptions!$E$11-Assumptions!$E$12)*(I4-1)/(Assumptions!$B$21-1) -> 0.13183333 | J5: =Assumptions!$E$12+(Assumptions!$E$11-Assumptions!$E$12)*(J4-1)/(Assumptions!$B$21-1) -> 0.096222222 | ... L5: =Assumptions!$E$12+(Assumptions!$E$11-Assumptions!$E$12)*(L4-1)/(Assumptions!$B$21-1) -> 0.025
A6: Operating margin | B6: =IFERROR(B8/B7,0) -> -0.089960334 | C6: =Assumptions!$B$18+(Assumptions!$E$13-Assumptions!$B$18)*C4/Assumptions!$B$21 -> 0.01073 | D6: =Assumptions!$B$18+(Assumptions!$E$13-Assumptions!$B$18)*D4/Assumptions!$B$21 -> 0.03176 | E6: =Assumptions!$B$18+(Assumptions!$E$13-Assumptions!$B$18)*E4/Assumptions!$B$21 -> 0.05279 | F6: =Assumptions!$B$18+(Assumptions!$E$13-Assumptions!$B$18)*F4/Assumptions!$B$21 -> 0.07382 | G6: =Assumptions!$B$18+(Assumptions!$E$13-Assumptions!$B$18)*G4/Assumptions!$B$21 -> 0.09485 | H6: =Assumptions!$B$18+(Assumptions!$E$13-Assumptions!$B$18)*H4/Assumptions!$B$21 -> 0.11588 | I6: =Assumptions!$B$18+(Assumptions!$E$13-Assumptions!$B$18)*I4/Assumptions!$B$21 -> 0.13691 | J6: =Assumptions!$B$18+(Assumptions!$E$13-Assumptions!$B$18)*J4/Assumptions!$B$21 -> 0.15794 | ... L6: =Assumptions!$B$18+(Assumptions!$E$13-Assumptions!$B$18)*L4/Assumptions!$B$21 -> 0.2
A7: Revenue | B7: ='Yearly Model'!K2 -> 193.363 | C7: ='Yearly Model'!L2 -> 260.16992 | D7: ='Yearly Model'!M2 -> 340.79368 | E7: ='Yearly Model'!N2 -> 434.26582 | F7: ='Yearly Model'!O2 -> 537.91059 | G7: ='Yearly Model'!P2 -> 647.13633 | H7: ='Yearly Model'!Q2 -> 755.49571 | I7: ='Yearly Model'!R2 -> 855.09523 | ... L7: ='Yearly Model'!U2 -> 1019.0444
A8: Operating income | B8: ='Yearly Model'!K8 -> -17.395 | C8: ='Yearly Model'!L8 -> 2.7916232 | D8: ='Yearly Model'!M8 -> 10.823607 | E8: ='Yearly Model'!N8 -> 22.924892 | F8: ='Yearly Model'!O8 -> 39.70856 | G8: ='Yearly Model'!P8 -> 61.380881 | H8: ='Yearly Model'!Q8 -> 87.546843 | I8: ='Yearly Model'!R8 -> 117.07109 | ... L8: ='Yearly Model'!U8 -> 203.80889
A9: Tax on operating income | C9: =MAX(0,C8)*Assumptions!$E$14 -> 0.47457594 | D9: =MAX(0,D8)*Assumptions!$E$14 -> 1.8400133 | E9: =MAX(0,E8)*Assumptions!$E$14 -> 3.8972317 | F9: =MAX(0,F8)*Assumptions!$E$14 -> 6.7504552 | G9: =MAX(0,G8)*Assumptions!$E$14 -> 10.43475 | H9: =MAX(0,H8)*Assumptions!$E$14 -> 14.882963 | I9: =MAX(0,I8)*Assumptions!$E$14 -> 19.902085 | J9: =MAX(0,J8)*Assumptions!$E$14 -> 25.168315 | ... L9: =MAX(0,L8)*Assumptions!$E$14 -> 34.647511
A10: NOPAT | C10: =C8-C9 -> 2.3170473 | D10: =D8-D9 -> 8.9835941 | E10: =E8-E9 -> 19.027661 | F10: =F8-F9 -> 32.958105 | G10: =G8-G9 -> 50.946131 | H10: =H8-H9 -> 72.663879 | I10: =I8-I9 -> 97.169003 | J10: =J8-J9 -> 122.8806 | ... L10: =L8-L9 -> 169.16138
A11: Reinvestment | C11: =(C7-B7)*Assumptions!$E$15 -> 16.701729 | D11: =(D7-C7)*Assumptions!$E$15 -> 20.155942 | E11: =(E7-D7)*Assumptions!$E$15 -> 23.368034 | F11: =(F7-E7)*Assumptions!$E$15 -> 25.911194 | G11: =(G7-F7)*Assumptions!$E$15 -> 27.306434 | H11: =(H7-G7)*Assumptions!$E$15 -> 27.089846 | I11: =(I7-H7)*Assumptions!$E$15 -> 24.899879 | J11: =(J7-I7)*Assumptions!$E$15 -> 20.569791 | ... L11: =(L7-K7)*Assumptions!$E$15 -> 6.2136856
A12: Free cash flow | C12: =C10-C11 -> -14.384682 | D12: =D10-D11 -> -11.172347 | E12: =E10-E11 -> -4.3403728 | F12: =F10-F11 -> 7.046911 | G12: =G10-G11 -> 23.639697 | H12: =H10-H11 -> 45.574034 | I12: =I10-I11 -> 72.269123 | J12: =J10-J11 -> 102.31081 | ... L12: =L10-L11 -> 162.94769
A13: Year fraction | C13: =Assumptions!$B$22 -> 0.5041 | D13: 1 | E13: 1 | F13: 1 | G13: 1 | H13: 1 | I13: 1 | J13: 1 | K13: 1 | L13: 1
A14: Discount time (mid-period) | C14: =C13/2 -> 0.25205 | D14: =C14+C13/2+D13/2 -> 1.0041 | E14: =D14+D13/2+E13/2 -> 2.0041 | F14: =E14+E13/2+F13/2 -> 3.0041 | G14: =F14+F13/2+G13/2 -> 4.0041 | H14: =G14+G13/2+H13/2 -> 5.0041 | I14: =H14+H13/2+I13/2 -> 6.0041 | J14: =I14+I13/2+J13/2 -> 7.0041 | K14: =J14+J13/2+K13/2 -> 8.0041 | L14: =K14+K13/2+L13/2 -> 9.0041
A15: Discount factor | C15: =1/(1+Assumptions!$E$10)^C14 -> 0.97403899 | D15: =1/(1+Assumptions!$E$10)^D14 -> 0.90051551 | E15: =1/(1+Assumptions!$E$10)^E14 -> 0.81127523 | F15: =1/(1+Assumptions!$E$10)^F14 -> 0.73087859 | G15: =1/(1+Assumptions!$E$10)^G14 -> 0.65844918 | H15: =1/(1+Assumptions!$E$10)^H14 -> 0.59319746 | I15: =1/(1+Assumptions!$E$10)^I14 -> 0.53441213 | J15: =1/(1+Assumptions!$E$10)^J14 -> 0.48145236 | ... L15: =1/(1+Assumptions!$E$10)^L14 -> 0.39075754
A16: PV of free cash flow | C16: =C12*C13*C15 -> -7.0630666 | D16: =D12*D13*D15 -> -10.060872 | E16: =E12*E13*E15 -> -3.5212369 | F16: =F12*F13*F15 -> 5.1504363 | G16: =G12*G13*G15 -> 15.565539 | H16: =H12*H13*H15 -> 27.034401 | I16: =I12*I13*I15 -> 38.621496 | J16: =J12*J13*J15 -> 49.257779 | ... L16: =L12*L13*L15 -> 63.673039
A19: PV of forecast free cash flow | B19: =SUM(C16:L16) -> 236.55246
A20: Terminal free cash flow (year 11) | B20: =L10*(1+Assumptions!$E$11)-L7*Assumptions!$E$11*Assumptions!$E$15 -> 167.02138
A21: Terminal value | B21: =B20/(Assumptions!$E$10-Assumptions!$E$11) -> 1964.9574
A22: PV of terminal value | B22: =B21/(1+Assumptions!$E$10)^(L14+0.5) -> 728.78433
A23: Enterprise value | B23: =B19+B22 -> 965.33679
A24: Cash & investments | B24: =Main!C7 -> 797.019
A25: Debt | B25: =Main!C8 -> 0
A26: Equity value | B26: =B23+B24-B25 -> 1762.3558
A27: Shares (mm) | B27: =Main!C4 -> 368.41286
A28: NPV / share | B28: =B26/B27 -> 4.7836435
A29: Price | B29: =Main!C3 -> 3.28
A30: Upside | B30: =B28/B29-1 -> 0.45842788
A31: Terminal value, % of EV | B31: =IFERROR(B22/B23,0) -> 0.75495344
