Workbook

Sheet Main
B2: CytomX Therapeutics, Inc.
B3: Price | C3: =INDEX([1]Pharma!$F$1:$F$1000,MATCH("CTMX",[1]Pharma!$B$1:$B$1000,0)) -> 2.51
B4: Shares | C4: 217.89928
B5: Market Cap. | C5: =C3*C4 -> 546.9272
B7: Cash | C7: =17.224+313.056 -> 330.28
B8: Debt | C8: 0
B9: Enterprise V. | C9: =C5-C7+C8 -> 216.6472
B11: rNPV / Share | C11: =NPV!B27 -> 0.83580153
B12: Upside | C12: =IFERROR(C11/C3-1,"") -> -0.66701134
B13: Cash / Share | C13: =IFERROR((C7-C8)/C4,"") -> 1.5157461
B14: Scenario | C14: =Assumptions!C4 -> Base
B15: Model | C15: Pipeline rNPV
B17: TTM Operating Cash Flow | C17: -82.408
B18: Runway (years) | C18: =IF(AND(ISNUMBER(C17),C17<0),IF(C7>C8,(C7-C8)/-C17,"net debt"),"n/a") -> 4.0078633
B19: Implied Pipeline Value | C19: =C9 -> 216.6472

Sheet Yearly Model
B1: 2013 | C1: 2014 | D1: 2015 | E1: 2016 | F1: 2017 | G1: 2018 | H1: 2019 | I1: 2020 | J1: 2021 | K1: 2022 | L1: 2023 | M1: 2024 | N1: 2025
A2: Revenue | B2: 0.888 | C2: 5.077 | D2: 7.712 | E2: 15.043 | F2: 71.623 | G2: 59.502 | H2: 26.902 | I2: 68.427 | J2: 37.312 | K2: 53.163 | L2: 101.214 | M2: 138.103 | N2: 76.201
A3: Cost of Sales | B3: 0 | C3: 0 | D3: 0 | E3: 0 | F3: 0 | G3: 0 | H3: 0 | I3: 0 | J3: 0 | K3: 0 | L3: 0 | M3: 0 | N3: 0
A4: Gross Margin | B4: =B2-B3 -> 0.888 | C4: =C2-C3 -> 5.077 | D4: =D2-D3 -> 7.712 | E4: =E2-E3 -> 15.043 | F4: =F2-F3 -> 71.623 | G4: =G2-G3 -> 59.502 | H4: =H2-H3 -> 26.902 | I4: =I2-I3 -> 68.427 | ... N4: =N2-N3 -> 76.201
A5: Research & Dev. | B5: 10.89 | C5: 28.302 | D5: 28.357 | E5: 54.755 | F5: 92.277 | G5: 103.866 | H5: 131.619 | I5: 112.936 | J5: 114.194 | K5: 111.649 | L5: 77.68 | M5: 83.382 | N5: 68.728
A6: SG&A & Other | B6: 4.954 | C6: 6.54 | D6: 12.558 | E6: 19.874 | F6: 25.605 | G6: 33.51 | H6: 36.765 | I6: 36.031 | J6: 39.16 | K6: 42.849 | L6: 30.018 | M6: 29.726 | N6: 29.837
A7: Operating Expense | B7: =SUM(B5:B6) -> 15.844 | C7: =SUM(C5:C6) -> 34.842 | D7: =SUM(D5:D6) -> 40.915 | E7: =SUM(E5:E6) -> 74.629 | F7: =SUM(F5:F6) -> 117.882 | G7: =SUM(G5:G6) -> 137.376 | H7: =SUM(H5:H6) -> 168.384 | I7: =SUM(I5:I6) -> 148.967 | ... N7: =SUM(N5:N6) -> 98.565
A8: Operating Income | B8: =B4-B7 -> -14.956 | C8: =C4-C7 -> -29.765 | D8: =D4-D7 -> -33.203 | E8: =E4-E7 -> -59.586 | F8: =F4-F7 -> -46.259 | G8: =G4-G7 -> -77.874 | H8: =H4-H7 -> -141.482 | I8: =I4-I7 -> -80.54 | ... N8: =N4-N7 -> -22.364
A9: Interest & Other | B9: -0.177 | C9: -0.535 | D9: -2.161 | E9: 0.667 | F9: 2.647 | G9: 7.573 | H9: 8.23 | I9: 1.809 | J9: 0.172 | K9: 2.018 | L9: 9.807 | M9: 7.098 | N9: 5.234
A10: Pretax | B10: =B8+B9 -> -15.133 | C10: =C8+C9 -> -30.3 | D10: =D8+D9 -> -35.364 | E10: =E8+E9 -> -58.919 | F10: =F8+F9 -> -43.612 | G10: =G8+G9 -> -70.301 | H10: =H8+H9 -> -133.252 | I10: =I8+I9 -> -78.731 | ... N10: =N8+N9 -> -17.13
A11: Taxes | B11: 0.01 | C11: 0.01 | D11: 0.01 | E11: -0.019 | F11: -0.513 | G11: 14.303 | H11: -0.427 | I11: -13.911 | J11: 0 | K11: 0 | L11: 3.892 | M11: 0.224 | N11: 0.238
A12: Net Income | B12: -15.143 | C12: -30.31 | D12: -35.374 | E12: -58.9 | F12: -43.099 | G12: -84.604 | H12: -132.825 | I12: -64.82 | J12: -115.87 | K12: -99.317 | L12: -0.569 | M12: 31.869 | N12: -17.368
A13: Earnings per Share | B13: =IFERROR(B12/B14,0) -> -19.615285 | C13: =IFERROR(C12/C14,0) -> -30.647118 | D13: =IFERROR(D12/D14,0) -> -4.1156486 | E13: =IFERROR(E12/E14,0) -> -1.6255002 | F13: =IFERROR(F12/F14,0) -> -1.1596039 | G13: =IFERROR(G12/G14,0) -> -2.030626 | H13: =IFERROR(H12/H14,0) -> -2.9297909 | I13: =IFERROR(I12/I14,0) -> -1.4046721 | ... N13: =IFERROR(N12/N14,0) -> -0.12591347
A14: Shares | B14: 0.772 | C14: 0.989 | D14: 8.595 | E14: 36.235 | F14: 37.167 | G14: 41.664 | H14: 45.336 | I14: 46.146 | J14: 64.147 | K14: 65.74 | L14: 73.808 | M14: 84.745 | N14: 137.936
A16: Revenue Change | C16: =IFERROR(C2/B2-1,"") -> 4.7173423 | D16: =IFERROR(D2/C2-1,"") -> 0.51900729 | E16: =IFERROR(E2/D2-1,"") -> 0.95059647 | F16: =IFERROR(F2/E2-1,"") -> 3.7612178 | G16: =IFERROR(G2/F2-1,"") -> -0.16923335 | H16: =IFERROR(H2/G2-1,"") -> -0.54788074 | I16: =IFERROR(I2/H2-1,"") -> 1.5435655 | J16: =IFERROR(J2/I2-1,"") -> -0.45471817 | ... N16: =IFERROR(N2/M2-1,"") -> -0.44823067
A17: Gross Margin | B17: =IFERROR(B4/B2,"") -> 1 | C17: =IFERROR(C4/C2,"") -> 1 | D17: =IFERROR(D4/D2,"") -> 1 | E17: =IFERROR(E4/E2,"") -> 1 | F17: =IFERROR(F4/F2,"") -> 1 | G17: =IFERROR(G4/G2,"") -> 1 | H17: =IFERROR(H4/H2,"") -> 1 | I17: =IFERROR(I4/I2,"") -> 1 | ... N17: =IFERROR(N4/N2,"") -> 1
A18: Operating Margin | B18: =IFERROR(B8/B2,"") -> -16.842342 | C18: =IFERROR(C8/C2,"") -> -5.8627142 | D18: =IFERROR(D8/D2,"") -> -4.3053683 | E18: =IFERROR(E8/E2,"") -> -3.961045 | F18: =IFERROR(F8/F2,"") -> -0.64586795 | G18: =IFERROR(G8/G2,"") -> -1.3087627 | H18: =IFERROR(H8/H2,"") -> -5.2591629 | I18: =IFERROR(I8/I2,"") -> -1.1770208 | ... N18: =IFERROR(N8/N2,"") -> -0.29348696
A19: Actual / Estimate | B19: A | C19: A | D19: A | E19: A | F19: A | G19: A | H19: A | I19: A | J19: A | K19: A | L19: A | M19: A | N19: A

Sheet Quarterly Model

Sheet Assumptions
A1: CytomX Therapeutics, Inc.: pipeline rNPV assumptions
A2: Blue = input, black = formula, green = link. $mm unless noted.
A4: Scenario (1 Bear, 2 Base, 3 Bull) | B4: 2 | C4: =CHOOSE($B$4,"Bear","Base","Bull") -> Base
A6: Discount rate override (blank = scenario)
A7: Approval-odds multiplier override
A8: Peak-sales multiplier override
A9: Parameter | B9: Bear | C9: Base | D9: Bull | E9: Live
A10: Discount rate | B10: 0.14 | C10: 0.12 | D10: 0.1 | E10: =IF(ISNUMBER($B$6),$B$6,CHOOSE($B$4,B10,C10,D10)) -> 0.12
A11: Peak-sales multiplier (× indication table) | B11: 0.6 | C11: 1 | D11: 1.4 | E11: =IF(ISNUMBER($B$8),$B$8,CHOOSE($B$4,B11,C11,D11)) -> 1
A12: Approval-odds multiplier (× BIO rates) | B12: 0.8 | C12: 1 | D12: 1.15 | E12: =IF(ISNUMBER($B$7),$B$7,CHOOSE($B$4,B12,C12,D12)) -> 1
A13: Net margin on owned product sales at peak | B13: 0.4 | C13: 0.4 | D13: 0.4 | E13: =CHOOSE($B$4,B13,C13,D13) -> 0.4
A14: Royalty / economics on partnered sales | B14: 0.12 | C14: 0.12 | D14: 0.12 | E14: =CHOOSE($B$4,B14,C14,D14) -> 0.12
A15: Tax rate | B15: 0.21 | C15: 0.21 | D15: 0.21 | E15: =CHOOSE($B$4,B15,C15,D15) -> 0.21
A16: Probability at least one owned program is approved | B16: =1-PRODUCT(Pipeline!AG4:AG4) -> 0.0754
A17: Company costs and timing
A18: Net operating burn, TTM (operating loss) | B18: 87.153
A19: Years of full burn (until the first launch, max 4) | B19: =MIN(4,MAX(1,MIN(Pipeline!I4:I4)-2026)) -> 4
A20: Burn after that, % of TTM (platform R&D and G&A), if a product is approved | B20: 0.3
A21: Tax-loss carryforward at start | B21: 698.2
A22: First year, fraction after the balance sheet date | B22: 0.5041
A23: Balance sheet date | B23: 46203
A24: Launch ramp, share of peak in years 1-6 | B24: 0.1 | C24: 0.25 | D24: 0.45 | E24: 0.65 | F24: 0.85 | G24: 1
A25: Patent / exclusivity life after launch (years) | B25: 12
A26: Sales erosion per year after exclusivity | B26: 0.5
A27: Scenario summary
A28: Scenario | B28: Pipeline rNPV (ops) | C28: Equity value | D28: rNPV / share | E28: Upside
A29: Live | B29: =NPV!B22 -> -148.15945 | C29: =NPV!B25 -> 182.12055 | D29: =NPV!B27 -> 0.83580153 | E29: =NPV!B29 -> -0.66701134
A30: 1 | B30: -207.4476 | C30: 122.8324 | D30: 0.56371182 | E30: -0.77541362
A31: 2 | B31: -148.15945 | C31: 182.12055 | D31: 0.83580153 | E31: -0.66701134
A32: 3 | B32: -44.491675 | C32: 285.78833 | D32: 1.3115616 | E32: -0.47746551
A35: rNPV / share: approval-odds multiplier (rows) x peak-sales multiplier (columns)
A36: =NPV!B27 -> 0.83580153 | B36: 0.5 | C36: 0.75 | D36: 1 | E36: 1.5 | F36: 2
A37: 0.6 | B37: 0.4889847 | C37: 0.56715026 | D37: 0.64531582 | E37: 0.80164694 | F37: 0.95797806
A38: 0.8 | B38: 0.53211718 | C38: 0.63633793 | D38: 0.74055867 | E38: 0.94900016 | F38: 1.1574417
A39: 1 | B39: 0.57524966 | C39: 0.7055256 | D39: 0.83580153 | E39: 1.0963534 | F39: 1.3569053
A40: 1.2 | B40: 0.61838215 | C40: 0.77471326 | D40: 0.93104438 | E40: 1.2437066 | F40: 1.5460475
A41: 1.4 | B41: 0.66151463 | C41: 0.84390093 | D41: 1.0262872 | E41: 1.3910598 | F41: 1.7205437

Sheet Pipeline
A1: CytomX Therapeutics, Inc.: pipeline (risked revenue, $mm)
A2: Programs from ClinicalTrials.gov (company as lead sponsor, or partner of an industry sponsor), one row per indication; approval odds from BIO 2011-2020 phase-transition rates.
A3: No. | B3: Program (indication) | C3: Drug(s) | D3: Stage | E3: Area / rate class | F3: Economics | G3: Peak | H3: PoS | I3: Launch | J3: LOE | K3: Share | L3: Risked PV | M3: 2026 | N3: 2027 | O3: 2028 | P3: 2029 | Q3: 2030 | R3: 2031 | S3: 2032 | T3: 2033 | U3: 2034 | V3: 2035 | W3: 2036 | X3: 2037 | Y3: 2038 | Z3: 2039 | AA3: 2040 | AB3: 2041 | AC3: 2042 | AD3: 2043 | AE3: 2044 | AF3: 2045 | AG3: 1 - PoS (owned)
A4: 1 | B4: Solid tumors (basket) | C4: CX-2029, CX-2051 | D4: Phase 1/2 | E4: Oncology / area | F4: Owned | G4: 1500 | H4: 0.0754 | I4: 2032 | J4: =I4+Assumptions!$B$25 -> 2044 | K4: =Assumptions!$E$13 -> 0.4 | L4: =K4*SUMPRODUCT(M4:AF4,NPV!$C$15:$V$15) -> 113.54813 | M4: =IF(M$3<$I4,0,$G4*Assumptions!$E$11*INDEX(Assumptions!$B$24:$G$24,MIN(6,M$3-$I4+1))*IF(M$3>$J4,(1-Assumptions!$B$26)^(M$3-$J4),1)*IF($H4>=1,1,MIN(0.97,$H4*Assumptions!$E$12))) -> 0 | N4: =IF(N$3<$I4,0,$G4*Assumptions!$E$11*INDEX(Assumptions!$B$24:$G$24,MIN(6,N$3-$I4+1))*IF(N$3>$J4,(1-Assumptions!$B$26)^(N$3-$J4),1)*IF($H4>=1,1,MIN(0.97,$H4*Assumptions!$E$12))) -> 0 | O4: =IF(O$3<$I4,0,$G4*Assumptions!$E$11*INDEX(Assumptions!$B$24:$G$24,MIN(6,O$3-$I4+1))*IF(O$3>$J4,(1-Assumptions!$B$26)^(O$3-$J4),1)*IF($H4>=1,1,MIN(0.97,$H4*Assumptions!$E$12))) -> 0 | P4: =IF(P$3<$I4,0,$G4*Assumptions!$E$11*INDEX(Assumptions!$B$24:$G$24,MIN(6,P$3-$I4+1))*IF(P$3>$J4,(1-Assumptions!$B$26)^(P$3-$J4),1)*IF($H4>=1,1,MIN(0.97,$H4*Assumptions!$E$12))) -> 0 | Q4: =IF(Q$3<$I4,0,$G4*Assumptions!$E$11*INDEX(Assumptions!$B$24:$G$24,MIN(6,Q$3-$I4+1))*IF(Q$3>$J4,(1-Assumptions!$B$26)^(Q$3-$J4),1)*IF($H4>=1,1,MIN(0.97,$H4*Assumptions!$E$12))) -> 0 | R4: =IF(R$3<$I4,0,$G4*Assumptions!$E$11*INDEX(Assumptions!$B$24:$G$24,MIN(6,R$3-$I4+1))*IF(R$3>$J4,(1-Assumptions!$B$26)^(R$3-$J4),1)*IF($H4>=1,1,MIN(0.97,$H4*Assumptions!$E$12))) -> 0 | S4: =IF(S$3<$I4,0,$G4*Assumptions!$E$11*INDEX(Assumptions!$B$24:$G$24,MIN(6,S$3-$I4+1))*IF(S$3>$J4,(1-Assumptions!$B$26)^(S$3-$J4),1)*IF($H4>=1,1,MIN(0.97,$H4*Assumptions!$E$12))) -> 11.31 | T4: =IF(T$3<$I4,0,$G4*Assumptions!$E$11*INDEX(Assumptions!$B$24:$G$24,MIN(6,T$3-$I4+1))*IF(T$3>$J4,(1-Assumptions!$B$26)^(T$3-$J4),1)*IF($H4>=1,1,MIN(0.97,$H4*Assumptions!$E$12))) -> 28.275 | ... AF4: =IF(AF$3<$I4,0,$G4*Assumptions!$E$11*INDEX(Assumptions!$B$24:$G$24,MIN(6,AF$3-$I4+1))*IF(AF$3>$J4,(1-Assumptions!$B$26)^(AF$3-$J4),1)*IF($H4>=1,1,MIN(0.97,$H4*Assumptions!$E$12))) -> 56.55 | AG4: =IF(F4="Owned",1-IF(H4>=1,1,MIN(0.97,H4*Assumptions!$E$12)),1) -> 0.9246
B5: Risked revenue | L5: =SUM(L4:L4) -> 113.54813 | M5: =SUM(M4:M4) -> 0 | N5: =SUM(N4:N4) -> 0 | O5: =SUM(O4:O4) -> 0 | P5: =SUM(P4:P4) -> 0 | Q5: =SUM(Q4:Q4) -> 0 | R5: =SUM(R4:R4) -> 0 | S5: =SUM(S4:S4) -> 11.31 | ... AF5: =SUM(AF4:AF4) -> 56.55
B6: Risked contribution (revenue x share) | M6: =SUMPRODUCT(M4:M4,$K$4:$K$4) -> 0 | N6: =SUMPRODUCT(N4:N4,$K$4:$K$4) -> 0 | O6: =SUMPRODUCT(O4:O4,$K$4:$K$4) -> 0 | P6: =SUMPRODUCT(P4:P4,$K$4:$K$4) -> 0 | Q6: =SUMPRODUCT(Q4:Q4,$K$4:$K$4) -> 0 | R6: =SUMPRODUCT(R4:R4,$K$4:$K$4) -> 0 | S6: =SUMPRODUCT(S4:S4,$K$4:$K$4) -> 4.524 | T6: =SUMPRODUCT(T4:T4,$K$4:$K$4) -> 11.31 | ... AF6: =SUMPRODUCT(AF4:AF4,$K$4:$K$4) -> 22.62

Sheet NPV
A1: CytomX Therapeutics, Inc.: risk-adjusted NPV ($mm)
A3: Year | C3: 2026 | D3: 2027 | E3: 2028 | F3: 2029 | G3: 2030 | H3: 2031 | I3: 2032 | J3: 2033 | K3: 2034 | L3: 2035 | M3: 2036 | N3: 2037 | O3: 2038 | P3: 2039 | Q3: 2040 | R3: 2041 | S3: 2042 | T3: 2043 | U3: 2044 | V3: 2045
A4: Risked pipeline revenue | C4: =Pipeline!M5 -> 0 | D4: =Pipeline!N5 -> 0 | E4: =Pipeline!O5 -> 0 | F4: =Pipeline!P5 -> 0 | G4: =Pipeline!Q5 -> 0 | H4: =Pipeline!R5 -> 0 | I4: =Pipeline!S5 -> 11.31 | J4: =Pipeline!T5 -> 28.275 | ... V4: =Pipeline!AF5 -> 56.55
A5: Risked contribution | C5: =Pipeline!M6 -> 0 | D5: =Pipeline!N6 -> 0 | E5: =Pipeline!O6 -> 0 | F5: =Pipeline!P6 -> 0 | G5: =Pipeline!Q6 -> 0 | H5: =Pipeline!R6 -> 0 | I5: =Pipeline!S6 -> 4.524 | J5: =Pipeline!T6 -> 11.31 | ... V5: =Pipeline!AF6 -> 22.62
A6: Corporate burn | C6: =-IF(C3-2026<Assumptions!$B$19,Assumptions!$B$18,Assumptions!$B$18*Assumptions!$B$20*Assumptions!$B$16) -> -87.153 | D6: =-IF(D3-2026<Assumptions!$B$19,Assumptions!$B$18,Assumptions!$B$18*Assumptions!$B$20*Assumptions!$B$16) -> -87.153 | E6: =-IF(E3-2026<Assumptions!$B$19,Assumptions!$B$18,Assumptions!$B$18*Assumptions!$B$20*Assumptions!$B$16) -> -87.153 | F6: =-IF(F3-2026<Assumptions!$B$19,Assumptions!$B$18,Assumptions!$B$18*Assumptions!$B$20*Assumptions!$B$16) -> -87.153 | G6: =-IF(G3-2026<Assumptions!$B$19,Assumptions!$B$18,Assumptions!$B$18*Assumptions!$B$20*Assumptions!$B$16) -> -1.9714009 | H6: =-IF(H3-2026<Assumptions!$B$19,Assumptions!$B$18,Assumptions!$B$18*Assumptions!$B$20*Assumptions!$B$16) -> -1.9714009 | I6: =-IF(I3-2026<Assumptions!$B$19,Assumptions!$B$18,Assumptions!$B$18*Assumptions!$B$20*Assumptions!$B$16) -> -1.9714009 | J6: =-IF(J3-2026<Assumptions!$B$19,Assumptions!$B$18,Assumptions!$B$18*Assumptions!$B$20*Assumptions!$B$16) -> -1.9714009 | ... V6: =-IF(V3-2026<Assumptions!$B$19,Assumptions!$B$18,Assumptions!$B$18*Assumptions!$B$20*Assumptions!$B$16) -> -1.9714009
A7: Pre-tax cash flow | C7: =C5+C6 -> -87.153 | D7: =D5+D6 -> -87.153 | E7: =E5+E6 -> -87.153 | F7: =F5+F6 -> -87.153 | G7: =G5+G6 -> -1.9714009 | H7: =H5+H6 -> -1.9714009 | I7: =I5+I6 -> 2.5525991 | J7: =J5+J6 -> 9.3385991 | ... V7: =V5+V6 -> 20.648599
A8: Tax-loss carryforward used | C8: =MIN(Assumptions!$B$21,MAX(0,C7)) -> 0 | D8: =MIN(C17,MAX(0,D7)) -> 0 | E8: =MIN(D17,MAX(0,E7)) -> 0 | F8: =MIN(E17,MAX(0,F7)) -> 0 | G8: =MIN(F17,MAX(0,G7)) -> 0 | H8: =MIN(G17,MAX(0,H7)) -> 0 | I8: =MIN(H17,MAX(0,I7)) -> 2.5525991 | J8: =MIN(I17,MAX(0,J7)) -> 9.3385991 | K8: =MIN(J17,MAX(0,K7)) -> 18.386599 | ... V8: =MIN(U17,MAX(0,V7)) -> 20.648599
A9: Taxable income | C9: =MAX(0,C7)-C8 -> 0 | D9: =MAX(0,D7)-D8 -> 0 | E9: =MAX(0,E7)-E8 -> 0 | F9: =MAX(0,F7)-F8 -> 0 | G9: =MAX(0,G7)-G8 -> 0 | H9: =MAX(0,H7)-H8 -> 0 | I9: =MAX(0,I7)-I8 -> 0 | J9: =MAX(0,J7)-J8 -> 0 | ... V9: =MAX(0,V7)-V8 -> 0
A10: Tax | C10: =C9*Assumptions!$E$15 -> 0 | D10: =D9*Assumptions!$E$15 -> 0 | E10: =E9*Assumptions!$E$15 -> 0 | F10: =F9*Assumptions!$E$15 -> 0 | G10: =G9*Assumptions!$E$15 -> 0 | H10: =H9*Assumptions!$E$15 -> 0 | I10: =I9*Assumptions!$E$15 -> 0 | J10: =J9*Assumptions!$E$15 -> 0 | ... V10: =V9*Assumptions!$E$15 -> 0
A11: Free cash flow | C11: =C7-C10 -> -87.153 | D11: =D7-D10 -> -87.153 | E11: =E7-E10 -> -87.153 | F11: =F7-F10 -> -87.153 | G11: =G7-G10 -> -1.9714009 | H11: =H7-H10 -> -1.9714009 | I11: =I7-I10 -> 2.5525991 | J11: =J7-J10 -> 9.3385991 | ... V11: =V7-V10 -> 20.648599
A12: Year fraction | C12: =Assumptions!$B$22 -> 0.5041 | D12: 1 | E12: 1 | F12: 1 | G12: 1 | H12: 1 | I12: 1 | J12: 1 | K12: 1 | L12: 1 | M12: 1 | N12: 1 | O12: 1 | P12: 1 | Q12: 1 | R12: 1 | S12: 1 | T12: 1 | U12: 1 | V12: 1
A13: Discount time (mid-year) | C13: =C12/2 -> 0.25205 | D13: =C13+C12/2+D12/2 -> 1.0041 | E13: =D13+D12/2+E12/2 -> 2.0041 | F13: =E13+E12/2+F12/2 -> 3.0041 | G13: =F13+F12/2+G12/2 -> 4.0041 | H13: =G13+G12/2+H12/2 -> 5.0041 | I13: =H13+H12/2+I12/2 -> 6.0041 | J13: =I13+I12/2+J12/2 -> 7.0041 | K13: =J13+J12/2+K12/2 -> 8.0041 | ... V13: =U13+U12/2+V12/2 -> 19.0041
A14: Discount factor | C14: =1/(1+Assumptions!$E$10)^C13 -> 0.97183961 | D14: =1/(1+Assumptions!$E$10)^D13 -> 0.89244238 | E14: =1/(1+Assumptions!$E$10)^E13 -> 0.79682355 | F14: =1/(1+Assumptions!$E$10)^F13 -> 0.7114496 | G14: =1/(1+Assumptions!$E$10)^G13 -> 0.63522286 | H14: =1/(1+Assumptions!$E$10)^H13 -> 0.56716326 | I14: =1/(1+Assumptions!$E$10)^I13 -> 0.50639577 | J14: =1/(1+Assumptions!$E$10)^J13 -> 0.45213908 | ... V14: =1/(1+Assumptions!$E$10)^V13 -> 0.11605284
A15: PV factor | C15: =C12*C14 -> 0.48990435 | D15: =D12*D14 -> 0.89244238 | E15: =E12*E14 -> 0.79682355 | F15: =F12*F14 -> 0.7114496 | G15: =G12*G14 -> 0.63522286 | H15: =H12*H14 -> 0.56716326 | I15: =I12*I14 -> 0.50639577 | J15: =J12*J14 -> 0.45213908 | ... V15: =V12*V14 -> 0.11605284
A16: PV of free cash flow | C16: =C11*C15 -> -42.696634 | D16: =D11*D15 -> -77.77903 | E16: =E11*E15 -> -69.445563 | F16: =F11*F15 -> -62.004967 | G16: =G11*G15 -> -1.2522789 | H16: =H11*H15 -> -1.1181061 | I16: =I11*I15 -> 1.2926254 | J16: =J11*J15 -> 4.2223456 | ... V16: =V11*V15 -> 2.3963286
A17: Tax-loss carryforward, end of year | C17: =Assumptions!$B$21-C8+MAX(0,-C7) -> 785.353 | D17: =C17-D8+MAX(0,-D7) -> 872.506 | E17: =D17-E8+MAX(0,-E7) -> 959.659 | F17: =E17-F8+MAX(0,-F7) -> 1046.812 | G17: =F17-G8+MAX(0,-G7) -> 1048.7834 | H17: =G17-H8+MAX(0,-H7) -> 1050.7548 | I17: =H17-I8+MAX(0,-I7) -> 1048.2022 | J17: =I17-J8+MAX(0,-J7) -> 1038.8636 | K17: =J17-K8+MAX(0,-K7) -> 1020.477 | ... V17: =U17-V8+MAX(0,-V7) -> 589.76241
A19: PV of risked pipeline contribution | B19: =SUMPRODUCT(C5:V5,C15:V15) -> 113.54813
A20: PV of corporate burn | B20: =SUMPRODUCT(C6:V6,C15:V15) -> -261.70757
A21: PV of taxes | B21: =-SUMPRODUCT(C10:V10,C15:V15) -> 0
A22: Pipeline rNPV (operations) | B22: =SUM(C16:V16) -> -148.15945
A23: Cash & investments | B23: =Main!C7 -> 330.28
A24: Debt | B24: =Main!C8 -> 0
A25: Equity value | B25: =B22+B23-B24 -> 182.12055
A26: Shares (mm) | B26: =Main!C4 -> 217.89928
A27: rNPV / share | B27: =B25/B26 -> 0.83580153
A28: Price | B28: =Main!C3 -> 2.51
A29: Upside | B29: =B27/B28-1 -> -0.66701134
