Workbook

Sheet Main
B2: Evommune, Inc.
B3: Price | C3: =INDEX([1]Pharma!$F$1:$F$1000,MATCH("EVMN",[1]Pharma!$B$1:$B$1000,0)) -> 5.35
B4: Shares | C4: 36.292113
B5: Market Cap. | C5: =C3*C4 -> 194.1628
B7: Cash | C7: =60.034+140.759+87.214 -> 288.007
B8: Debt | C8: 0
B9: Enterprise V. | C9: =C5-C7+C8 -> -93.844195
B11: rNPV / Share | C11: =NPV!C27 -> 6.7806114
B12: Upside | C12: =C11/C3-1 -> 0.26740399
B13: Cash / Share | C13: =(C7-C8)/C4 -> 7.9358014
B14: Scenario | C14: =Assumptions!$C$4 -> Base

Sheet Yearly Model
B1: 2023 | C1: 2024 | D1: 2025 | E1: 2026 | F1: 2027 | G1: 2028 | H1: 2029 | I1: 2030 | J1: 2031 | K1: 2032 | L1: 2033 | M1: 2034 | N1: 2035 | O1: 2036 | P1: 2037 | Q1: 2038 | R1: 2039 | S1: 2040 | T1: 2041 | U1: 2042 | V1: 2043 | W1: 2044 | X1: 2045 | Y1: 2046 | Z1: 2047 | AA1: 2048 | AB1: 2049 | AC1: 2050
A2: Revenue | B2: 5 | C2: 7 | D2: 13 | E2: =SUM('Quarterly Model'!F2:I2) -> 0 | F2: =Pipeline!C35 -> 0 | G2: =Pipeline!D35 -> 0 | H2: =Pipeline!E35 -> 0 | I2: =Pipeline!F35 -> 0 | J2: =Pipeline!G35 -> 0 | K2: =Pipeline!H35 -> 7.92 | L2: =Pipeline!I35 -> 66.6 | M2: =Pipeline!J35 -> 154.62 | ... AC2: =Pipeline!Z35 -> 119.52512
A3: Cost of Sales | B3: 0 | C3: 0 | D3: 0 | E3: =SUM('Quarterly Model'!F3:I3) -> 0 | F3: =Pipeline!C36 -> 0 | G3: =Pipeline!D36 -> 0 | H3: =Pipeline!E36 -> 0 | I3: =Pipeline!F36 -> 0 | J3: =Pipeline!G36 -> 0 | K3: =Pipeline!H36 -> 0.6336 | L3: =Pipeline!I36 -> 11.88 | M3: =Pipeline!J36 -> 28.7496 | ... AC3: =Pipeline!Z36 -> 26.238755
A4: Gross Margin | B4: =B2-B3 -> 5 | C4: =C2-C3 -> 7 | D4: =D2-D3 -> 13 | E4: =E2-E3 -> 0 | F4: =F2-F3 -> 0 | G4: =G2-G3 -> 0 | H4: =H2-H3 -> 0 | I4: =I2-I3 -> 0 | ... AC4: =AC2-AC3 -> 93.286361
A5: Research & Dev. | B5: 31.997 | C5: 64.244 | D5: 74.042 | E5: =SUM('Quarterly Model'!F5:I5) -> 88.731 | F5: =Pipeline!C39 -> 71 | G5: =Pipeline!D39 -> 85.48 | H5: =Pipeline!E39 -> 116.4744 | I5: =Pipeline!F39 -> 117.48363 | J5: =Pipeline!G39 -> 90.758141 | K5: =Pipeline!H39 -> 54.312774 | L5: =Pipeline!I39 -> 42.633407 | M5: =Pipeline!J39 -> 12.81141 | ... AC5: =Pipeline!Z39 -> 13.939137
A6: General & Admin | B6: 10.853 | C6: 12.769 | D6: 20.029 | E6: =SUM('Quarterly Model'!F6:I6) -> 32.118 | F6: =Pipeline!C42 -> 34 | G6: =Pipeline!D42 -> 35.02 | H6: =Pipeline!E42 -> 36.0706 | I6: =Pipeline!F42 -> 37.152718 | J6: =Pipeline!G42 -> 43.7673 | K6: =Pipeline!H42 -> 44.02702 | L6: =Pipeline!I42 -> 70.930991 | M6: =Pipeline!J42 -> 97.85662 | ... AC6: =Pipeline!Z42 -> 58.482288
A7: Operating Expense | B7: =SUM(B5:B6) -> 42.85 | C7: =SUM(C5:C6) -> 77.013 | D7: =SUM(D5:D6) -> 94.071 | E7: =SUM(E5:E6) -> 120.849 | F7: =SUM(F5:F6) -> 105 | G7: =SUM(G5:G6) -> 120.5 | H7: =SUM(H5:H6) -> 152.545 | I7: =SUM(I5:I6) -> 154.63635 | ... AC7: =SUM(AC5:AC6) -> 72.421425
A8: Operating Income | B8: =B4-B7 -> -37.85 | C8: =C4-C7 -> -70.013 | D8: =D4-D7 -> -81.071 | E8: =E4-E7 -> -120.849 | F8: =F4-F7 -> -105 | G8: =G4-G7 -> -120.5 | H8: =H4-H7 -> -152.545 | I8: =I4-I7 -> -154.63635 | ... AC8: =AC4-AC7 -> 20.864936
A9: Interest | B9: 3.797 | C9: 3.205 | D9: 12.201 | E9: =SUM('Quarterly Model'!F9:I9) -> 10.091944 | F9: =Assumptions!$B$16*MAX(0,E20) -> 9.0063729 | G9: =Assumptions!$B$16*MAX(0,F20) -> 5.4066119 | H9: =Assumptions!$B$16*MAX(0,G20) -> 1.0906098 | I9: =Assumptions!$B$16*MAX(0,H20) -> 0 | J9: =Assumptions!$B$16*MAX(0,I20) -> 0 | K9: =Assumptions!$B$16*MAX(0,J20) -> 0 | L9: =Assumptions!$B$16*MAX(0,K20) -> 0 | M9: =Assumptions!$B$16*MAX(0,L20) -> 0 | ... AC9: =Assumptions!$B$16*MAX(0,AB20) -> 111.48637
A10: Pretax | B10: =B8+B9 -> -34.053 | C10: =C8+C9 -> -66.808 | D10: =D8+D9 -> -68.87 | E10: =E8+E9 -> -110.75706 | F10: =F8+F9 -> -95.993627 | G10: =G8+G9 -> -115.09339 | H10: =H8+H9 -> -151.45439 | I10: =I8+I9 -> -154.63635 | ... AC10: =AC8+AC9 -> 132.35131
A11: Taxes | B11: 0 | C11: 0 | D11: 0 | E11: =SUM('Quarterly Model'!F11:I11) -> 0 | F11: =MAX(0,F10-E21)*Assumptions!$B$15 -> 0 | G11: =MAX(0,G10-F21)*Assumptions!$B$15 -> 0 | H11: =MAX(0,H10-G21)*Assumptions!$B$15 -> 0 | I11: =MAX(0,I10-H21)*Assumptions!$B$15 -> 0 | J11: =MAX(0,J10-I21)*Assumptions!$B$15 -> 0 | K11: =MAX(0,K10-J21)*Assumptions!$B$15 -> 0 | L11: =MAX(0,L10-K21)*Assumptions!$B$15 -> 0 | M11: =MAX(0,M10-L21)*Assumptions!$B$15 -> 0 | ... AC11: =MAX(0,AC10-AB21)*Assumptions!$B$15 -> 27.793774
A12: Net Income | B12: =B10-B11 -> -34.053 | C12: =C10-C11 -> -66.808 | D12: =D10-D11 -> -68.87 | E12: =E10-E11 -> -110.75706 | F12: =F10-F11 -> -95.993627 | G12: =G10-G11 -> -115.09339 | H12: =H10-H11 -> -151.45439 | I12: =I10-I11 -> -154.63635 | ... AC12: =AC10-AC11 -> 104.55753
A13: Earnings per Share | B13: =B12/B14 -> -27.171667 | C13: =C12/C14 -> -44.294045 | D13: =D12/D14 -> -11.222761 | E13: =E12/E14 -> -3.1113714 | F13: =F12/F14 -> -2.6966392 | G13: =G12/G14 -> -3.233187 | H13: =H12/H14 -> -4.254635 | I13: =I12/I14 -> -4.3440222 | ... AC13: =AC12/AC14 -> 2.9372152
A14: Shares | B14: 1.253254 | C14: 1.508284 | D14: 6.136636 | E14: =AVERAGE('Quarterly Model'!F14:I14) -> 35.597504 | F14: =E14*(1+Assumptions!$B$23) -> 35.597504 | G14: =F14*(1+Assumptions!$B$23) -> 35.597504 | H14: =G14*(1+Assumptions!$B$23) -> 35.597504 | I14: =H14*(1+Assumptions!$B$23) -> 35.597504 | J14: =I14*(1+Assumptions!$B$23) -> 35.597504 | K14: =J14*(1+Assumptions!$B$23) -> 35.597504 | L14: =K14*(1+Assumptions!$B$23) -> 35.597504 | M14: =L14*(1+Assumptions!$B$23) -> 35.597504 | ... AC14: =AB14*(1+Assumptions!$B$23) -> 35.597504
A16: Revenue Change | C16: =IFERROR(C2/B2-1,"") -> 0.4 | D16: =IFERROR(D2/C2-1,"") -> 0.85714286 | E16: =IFERROR(E2/D2-1,"") -> -1 | F16: =IFERROR(F2/E2-1,"") | G16: =IFERROR(G2/F2-1,"") | H16: =IFERROR(H2/G2-1,"") | I16: =IFERROR(I2/H2-1,"") | J16: =IFERROR(J2/I2-1,"") | ... AC16: =IFERROR(AC2/AB2-1,"") -> -0.30177661
A17: Gross Margin | B17: =IFERROR(B4/B2,"") -> 1 | C17: =IFERROR(C4/C2,"") -> 1 | D17: =IFERROR(D4/D2,"") -> 1 | E17: =IFERROR(E4/E2,"") | F17: =IFERROR(F4/F2,"") | G17: =IFERROR(G4/G2,"") | H17: =IFERROR(H4/H2,"") | I17: =IFERROR(I4/I2,"") | ... AC17: =IFERROR(AC4/AC2,"") -> 0.78047497
A19: Actual / Estimate | B19: A | C19: A | D19: A | E19: A+E | F19: E | G19: E | H19: E | I19: E | J19: E | K19: E | L19: E | M19: E | N19: E | O19: E | P19: E | Q19: E | R19: E | S19: E | T19: E | U19: E | V19: E | W19: E | X19: E | Y19: E | Z19: E | AA19: E | AB19: E | AC19: E
A20: Cash & Investments | C20: =16.255+55.785 -> 72.04 | D20: =44.063+105.137+67.489 -> 216.689 | E20: ='Quarterly Model'!I20 -> 240.16994 | F20: =E20+F12 -> 144.17632 | G20: =F20+G12 -> 29.082929 | H20: =G20+H12 -> -122.37146 | I20: =H20+I12 -> -277.00781 | J20: =I20+J12 -> -411.53325 | K20: =J20+K12 -> -502.58665 | L20: =K20+L12 -> -561.43104 | M20: =L20+M12 -> -546.22867 | ... AC20: =AB20+AC12 -> 3077.5274
A21: Tax-Loss Pool | D21: =Assumptions!$B$17 -> 250 | E21: =D21-MIN(D21,MAX(0,E10))+MAX(0,-E10) -> 360.75706 | F21: =E21-MIN(E21,MAX(0,F10))+MAX(0,-F10) -> 456.75068 | G21: =F21-MIN(F21,MAX(0,G10))+MAX(0,-G10) -> 571.84407 | H21: =G21-MIN(G21,MAX(0,H10))+MAX(0,-H10) -> 723.29846 | I21: =H21-MIN(H21,MAX(0,I10))+MAX(0,-I10) -> 877.93481 | J21: =I21-MIN(I21,MAX(0,J10))+MAX(0,-J10) -> 1012.4603 | K21: =J21-MIN(J21,MAX(0,K10))+MAX(0,-K10) -> 1103.5136 | L21: =K21-MIN(K21,MAX(0,L10))+MAX(0,-L10) -> 1162.358 | ... AC21: =AB21-MIN(AB21,MAX(0,AC10))+MAX(0,-AC10) -> 0
A23: 2027+ projections are risk-adjusted (probability-weighted) and come from the Pipeline sheet. G&A includes commercial SG&A. Cash is before any new financing; stock comp is not added back.

Sheet Quarterly Model
B1: Q1 2025 | C1: Q2 2025 | D1: Q3 2025 | E1: Q4 2025 | F1: Q1 2026 | G1: Q2 2026 | H1: Q3 2026 | I1: Q4 2026
A2: Revenue | B2: 3 | C2: 0 | D2: 10 | E2: 0 | F2: 0 | G2: 0 | H2: 0 | I2: 0
A3: Cost of Sales | B3: 0 | C3: 0 | D3: 0 | E3: 0 | F3: 0 | G3: 0 | H3: 0 | I3: 0
A4: Gross Margin | B4: =B2-B3 -> 3 | C4: =C2-C3 -> 0 | D4: =D2-D3 -> 10 | E4: =E2-E3 -> 0 | F4: =F2-F3 -> 0 | G4: =G2-G3 -> 0 | H4: =H2-H3 -> 0 | I4: =I2-I3 -> 0
A5: Research & Dev. | B5: 14.362 | C5: 19.638 | D5: 19.639 | E5: =74.042-53.639 -> 20.403 | F5: 17.319 | G5: 26.412 | H5: 24 | I5: 21
A6: General & Admin | B6: 3.67 | C6: 3.356 | D6: 3.689 | E6: =20.029-10.716 -> 9.313 | F6: 6.635 | G6: 8.483 | H6: 8.5 | I6: 8.5
A7: Operating Expense | B7: =SUM(B5:B6) -> 18.032 | C7: =SUM(C5:C6) -> 22.994 | D7: =SUM(D5:D6) -> 23.328 | E7: =SUM(E5:E6) -> 29.716 | F7: =SUM(F5:F6) -> 23.954 | G7: =SUM(G5:G6) -> 34.895 | H7: =SUM(H5:H6) -> 32.5 | I7: =SUM(I5:I6) -> 29.5
A8: Operating Income | B8: =B4-B7 -> -15.032 | C8: =C4-C7 -> -22.994 | D8: =D4-D7 -> -13.328 | E8: =E4-E7 -> -29.716 | F8: =F4-F7 -> -23.954 | G8: =G4-G7 -> -34.895 | H8: =H4-H7 -> -32.5 | I8: =I4-I7 -> -29.5
A9: Interest | B9: 0.475 | C9: 9.429 | D9: 0.853 | E9: =12.201-10.758 -> 1.443 | F9: 2.28 | G9: 2.649 | H9: =Assumptions!$B$16*G20/4 -> 2.7000656 | I9: =Assumptions!$B$16*H20/4 -> 2.4628787
A10: Pretax | B10: =B8+B9 -> -14.557 | C10: =C8+C9 -> -13.565 | D10: =D8+D9 -> -12.475 | E10: =E8+E9 -> -28.273 | F10: =F8+F9 -> -21.674 | G10: =G8+G9 -> -32.246 | H10: =H8+H9 -> -29.799934 | I10: =I8+I9 -> -27.037121
A11: Taxes | B11: 0 | C11: 0 | D11: 0 | E11: 0 | F11: 0 | G11: 0 | H11: 0 | I11: 0
A12: Net Income | B12: =B10-B11 -> -14.557 | C12: =C10-C11 -> -13.565 | D12: =D10-D11 -> -12.475 | E12: =E10-E11 -> -28.273 | F12: =F10-F11 -> -21.674 | G12: =G10-G11 -> -32.246 | H12: =H10-H11 -> -29.799934 | I12: =I10-I11 -> -27.037121
A13: Earnings per Share | B13: =B12/B14 -> -9.4836039 | C13: =C12/C14 -> -8.8044681 | D13: =D12/D14 -> -8.0743814 | E13: =E12/E14 -> -1.4189089 | F13: =F12/F14 -> -0.64371561 | G13: =G12/G14 -> -0.89235991 | H13: =H12/H14 -> -0.82111324 | I13: =I12/I14 -> -0.74498614
A14: Shares | B14: 1.534965 | C14: 1.540695 | D14: 1.54501 | E14: =6.136636*4-SUM(B14:D14) -> 19.925874 | F14: 33.670148 | G14: 36.135644 | H14: =Main!$C$4 -> 36.292113 | I14: =Main!$C$4 -> 36.292113
A16: Revenue Change | F16: =IFERROR(F2/B2-1,"") -> -1 | G16: =IFERROR(G2/C2-1,"") | H16: =IFERROR(H2/D2-1,"") -> -1 | I16: =IFERROR(I2/E2-1,"")
A17: Gross Margin | B17: =IFERROR(B4/B2,"") -> 1 | C17: =IFERROR(C4/C2,"") | D17: =IFERROR(D4/D2,"") -> 1 | E17: =IFERROR(E4/E2,"") | F17: =IFERROR(F4/F2,"") | G17: =IFERROR(G4/G2,"") | H17: =IFERROR(H4/H2,"") | I17: =IFERROR(I4/I2,"")
A19: Actual / Estimate | B19: A | C19: A | D19: A | E19: A | F19: A | G19: A | H19: E | I19: E
A20: Cash & Investments | D20: =26.818+49.244 -> 76.062 | E20: =44.063+105.137+67.489 -> 216.689 | F20: =48.318+163.146+95.548 -> 307.012 | G20: =60.034+140.759+87.214 -> 288.007 | H20: =G20+H12+H21 -> 262.70707 | I20: =H20+I12+I21 -> 240.16994
A21: Non-cash items (est.) | H21: 4.5 | I21: 4.5

Sheet Assumptions
A1: EVMN — rNPV assumptions ($mm unless noted)
A2: Blue = hard-coded input · Black = formula · Green = link to another sheet · Yellow = key lever. Active column = CHOOSE(scenario) of Bear/Base/Bull.
A4: Scenario (1 = Bear, 2 = Base, 3 = Bull) | B4: 2 | C4: =CHOOSE($B$4,"Bear","Base","Bull") -> Base
A5: Overrides — leave blank to use scenario values (the sensitivity tables drive these)
A6: Discount rate override
A7: EVO301 AD peak sales override ($mm)
A8: EVO301 AD Ph2b success override
A10: Parameter | B10: Active | C10: Bear | D10: Base | E10: Bull | F10: Notes / source
A12: General
A13: Valuation date | B13: =DATE(2026,10,16) -> 46311 | F13: Today. Cash flows are discounted from mid-period dates to this date.
A14: Discount rate | B14: =IF(ISNUMBER($B$6),$B$6,CHOOSE($B$4,C14,D14,E14)) -> 0.12 | C14: 0.14 | D14: 0.12 | E14: 0.1 | F14: Small-cap biotech cost of equity; cash flows are already probability-weighted, so no extra risk premium.
A15: Tax rate | B15: =CHOOSE($B$4,C15,D15,E15) -> 0.21 | C15: 0.21 | D15: 0.21 | E15: 0.21 | F15: US federal statutory rate.
A16: Interest yield on cash | B16: =CHOOSE($B$4,C16,D16,E16) -> 0.0375 | C16: 0.0375 | D16: 0.0375 | E16: 0.0375 | F16: Assumption: approx. short-term Treasury yield. Q2 2026 interest income $2.65mm on ~$298mm avg balance ≈ 3.6%.
A17: Tax-loss pool at 12/31/2025 ($mm) | B17: =CHOOSE($B$4,C17,D17,E17) -> 250 | C17: 250 | D17: 250 | E17: 250 | F17: Approximation: $52.4mm gross deferred tax assets (fully reserved) ÷ 21%. Source: Evommune 10-K FY2025 (filed 2026-03-05, accession 0001193125-26-093932), SEC EDGAR XBRL company facts
A18: Corporate G&A, 2027 ($mm) | B18: =CHOOSE($B$4,C18,D18,E18) -> 34 | C18: 34 | D18: 34 | E18: 34 | F18: Q2 2026 G&A $8.5mm × 4 (includes stock comp). Grows with cost inflation until first launch.
A19: Platform / unallocated R&D, 2027 ($mm) | B19: =CHOOSE($B$4,C19,D19,E19) -> 16 | C19: 16 | D19: 16 | E19: 16 | F19: Personnel + discovery not tied to a program. 2024 unallocated R&D personnel cost was $9.6mm (S-1); headcount has grown since.
A20: Cost inflation | B20: =CHOOSE($B$4,C20,D20,E20) -> 0.03 | C20: 0.03 | D20: 0.03 | E20: 0.03 | F20: Assumption.
A21: Corporate G&A, % of revenue (commercial stage) | B21: =CHOOSE($B$4,C21,D21,E21) -> 0.08 | C21: 0.08 | D21: 0.08 | E21: 0.08 | F21: After first launch: G&A = max(base G&A × P(any approval), % of risk-adjusted revenue).
A22: Lifecycle R&D, % of revenue (commercial stage) | B22: =CHOOSE($B$4,C22,D22,E22) -> 0.05 | C22: 0.05 | D22: 0.05 | E22: 0.05 | F22: Same structure as G&A.
A23: Annual share count growth (EPS display only) | B23: =CHOOSE($B$4,C23,D23,E23) -> 0 | C23: 0 | D23: 0 | E23: 0 | F23: rNPV assumes future funding needs are met at the discount rate; set >0 to see EPS dilution.
A24: Options outstanding (mm) | B24: =CHOOSE($B$4,C24,D24,E24) -> 7.476614 | C24: 7.476614 | D24: 7.476614 | E24: 7.476614 | F24: Source: Evommune 10-Q for Q2 2026 (filed 2026-08-06), https://www.sec.gov/Archives/edgar/data/2044725/000119312526337984/0001193125-26-337984-index.htm
A25: Options weighted-avg exercise price ($) | B25: =CHOOSE($B$4,C25,D25,E25) -> 11.86 | C25: 11.86 | D25: 11.86 | E25: 11.86 | F25: Source: Evommune 10-Q for Q2 2026 (filed 2026-08-06), https://www.sec.gov/Archives/edgar/data/2044725/000119312526337984/0001193125-26-337984-index.htm
A26: RSUs / other dilutive securities (mm) | B26: =CHOOSE($B$4,C26,D26,E26) -> 0.77331 | C26: 0.77331 | D26: 0.77331 | E26: 0.77331 | F26: 8,249,924 anti-dilutive securities less 7,476,614 options. Source: Evommune 10-Q for Q2 2026 (filed 2026-08-06), https://www.sec.gov/Archives/edgar/data/2044725/000119312526337984/0001193125-26-337984-index.htm
A27: Wind-down cost for liquidation value ($mm) | B27: =CHOOSE($B$4,C27,D27,E27) -> 30 | C27: 30 | D27: 30 | E27: 30 | F27: Assumption: severance, contract termination, trial close-out.
A28: Est. cash & investments at 12/31/2026 ($mm) | B28: ='Quarterly Model'!I20 -> 240.16994 | F28: From the Quarterly Model (Q2 actual + 2H 2026 estimates).
A30: Commercial curves (by year since launch)
A31: Year since launch | B31: 1 | C31: 2 | D31: 3 | E31: 4 | F31: 5 | G31: 6 | H31: 7
A32: Sales ramp (% of peak) | B32: 0.08 | C32: 0.2 | D32: 0.38 | E32: 0.58 | F32: 0.76 | G32: 0.9 | H32: 1 | K32: Assumption: typical specialty launch curve, peak in year 7.
A33: Commercial SG&A (% of sales), years 1–5 | B33: 0.9 | C33: 0.55 | D33: 0.4 | E33: 0.32 | F33: 0.28 | K33: Year 6+ uses each program's maturity SG&A %.
A35: EVO301 — Atopic dermatitis (IL-18BP fusion protein; Ph2a positive, Ph2b to start mid-2027)
A36: Launch year | B36: =CHOOSE($B$4,C36,D36,E36) -> 2033 | C36: 2033 | D36: 2033 | E36: 2033 | F36: Ph2b (SC, ≥3 regimens, 16 wks) starts mid-2027 → data ~2H28 → Ph3 2029–31 → BLA 2032 → launch 2033. Source: Q2 2026 release.
A37: Peak WW net sales, unrisked ($mm) | B37: =IF(ISNUMBER($B$7),$B$7,CHOOSE($B$4,C37,D37,E37)) -> 2000 | C37: 1000 | D37: 2000 | E37: 3500 | F37: AD biologics market >$25bn by the 2030s (Dupixent alone >$10bn). Ph2a: 55% vs 22% EASI reduction at wk 12 (placebo-adj. 33 pts), IGA 0/1 23% vs 0%. Base ≈ 5–6% share for a long-acting, Dupixent-like agent in a crowded market.
A38: PoS: Phase 2/2b → Phase 3 | B38: =IF(ISNUMBER($B$8),$B$8,CHOOSE($B$4,C38,D38,E38)) -> 0.5 | C38: 0.35 | D38: 0.5 | E38: 0.6 | F38: Positive randomized Ph2a (n=70, Bayesian primary endpoint met; p<0.01 at wks 4/8/12) but small; IL-18 unvalidated in AD.
A39: PoS: Phase 3 → filing | B39: =CHOOSE($B$4,C39,D39,E39) -> 0.65 | C39: 0.6 | D39: 0.65 | E39: 0.7 | F39: Benchmark: BIO/Informa 2011–2020 Phase III→NDA/BLA ≈ 58%; immunology higher.
A40: PoS: filing → approval | B40: =CHOOSE($B$4,C40,D40,E40) -> 0.9 | C40: 0.9 | D40: 0.9 | E40: 0.92 | F40: Benchmark: BIO/Informa NDA/BLA→approval ≈ 91%.
A41: Cumulative probability of reaching market | B41: =B38*B39*B40 -> 0.2925 | C41: =C38*C39*C40 -> 0.189 | D41: =D38*D39*D40 -> 0.2925 | E41: =E38*E39*E40 -> 0.3864
A42: Cost of goods, % of sales | B42: =CHOOSE($B$4,C42,D42,E42) -> 0.12 | C42: 0.12 | D42: 0.12 | E42: 0.12 | F42: Assumption: biologic manufacturing.
A43: Royalties owed, % of sales | B43: =CHOOSE($B$4,C43,D43,E43) -> 0.1 | C43: 0.1 | D43: 0.1 | E43: 0.1 | F43: AprilBio license: mid-to-high single-digit tiered royalty + up to $377.5mm sales milestones (≈ +1.5 pts). Source: Evommune 10-K/ARS FY2025.
A44: Commercial SG&A at maturity, % of sales | B44: =CHOOSE($B$4,C44,D44,E44) -> 0.25 | C44: 0.25 | D44: 0.25 | E44: 0.25 | F44: Assumption.
A45: Pre-launch commercial spend, year before launch ($mm) | B45: =CHOOSE($B$4,C45,D45,E45) -> 60 | C45: 60 | D45: 60 | E45: 60 | F45: Risked by P(Phase 2b) × P(Phase 3).
A46: Loss of exclusivity (year) | B46: =CHOOSE($B$4,C46,D46,E46) -> 2045 | C46: 2045 | D46: 2045 | E46: 2045 | F46: 12-yr US biologic exclusivity from a 2033 approval; composition patents + PTE assumed similar.
A47: Post-LOE annual sales erosion | B47: =CHOOSE($B$4,C47,D47,E47) -> 0.3 | C47: 0.3 | D47: 0.3 | E47: 0.3 | F47: Assumption: biosimilar erosion.
A49: Development cost schedule (unrisked, $mm) | K49: Ph3 start (−4) includes $15mm AprilBio milestone; filing year (−1) $25mm; approval (0) $40mm ≈ $80mm of the $81mm remaining development milestones.
A50: Years relative to launch | B50: -8 | C50: -7 | D50: -6 | E50: -5 | F50: -4 | G50: -3 | H50: -2 | I50: -1 | J50: 0
A51: Phase | D51: Ph2b | E51: Ph2b | F51: Ph3 | G51: Ph3 | H51: Ph3 | I51: Filing | J51: Approval
A52: Unrisked cost ($mm) | B52: 0 | C52: 0 | D52: 25 | E52: 45 | F52: 105 | G52: 140 | H52: 110 | I52: 65 | J52: 40
A53: Probability the cost is incurred | B53: =IF(B51="",0,IF(B51="Ph3",$B$38,IF(B51="Filing",$B$38*$B$39,IF(B51="Approval",$B$41,1)))) -> 0 | C53: =IF(C51="",0,IF(C51="Ph3",$B$38,IF(C51="Filing",$B$38*$B$39,IF(C51="Approval",$B$41,1)))) -> 0 | D53: =IF(D51="",0,IF(D51="Ph3",$B$38,IF(D51="Filing",$B$38*$B$39,IF(D51="Approval",$B$41,1)))) -> 1 | E53: =IF(E51="",0,IF(E51="Ph3",$B$38,IF(E51="Filing",$B$38*$B$39,IF(E51="Approval",$B$41,1)))) -> 1 | F53: =IF(F51="",0,IF(F51="Ph3",$B$38,IF(F51="Filing",$B$38*$B$39,IF(F51="Approval",$B$41,1)))) -> 0.5 | G53: =IF(G51="",0,IF(G51="Ph3",$B$38,IF(G51="Filing",$B$38*$B$39,IF(G51="Approval",$B$41,1)))) -> 0.5 | H53: =IF(H51="",0,IF(H51="Ph3",$B$38,IF(H51="Filing",$B$38*$B$39,IF(H51="Approval",$B$41,1)))) -> 0.5 | I53: =IF(I51="",0,IF(I51="Ph3",$B$38,IF(I51="Filing",$B$38*$B$39,IF(I51="Approval",$B$41,1)))) -> 0.325 | J53: =IF(J51="",0,IF(J51="Ph3",$B$38,IF(J51="Filing",$B$38*$B$39,IF(J51="Approval",$B$41,1)))) -> 0.2925
A55: EVO756 — Migraine prophylaxis (oral MRGPRX2 antagonist; Ph2b started July 2026)
A56: Launch year | B56: =CHOOSE($B$4,C56,D56,E56) -> 2032 | C56: 2032 | D56: 2032 | E56: 2032 | F56: Ph2b (n≈330, 12 wks, primary = monthly migraine days) top-line in 2027 → Ph3 2028–30 → NDA 2031 → launch 2032.
A57: Peak WW net sales, unrisked ($mm) | B57: =CHOOSE($B$4,C57,D57,E57) -> 1000 | C57: 400 | D57: 1000 | E57: 2000 | F57: Ex-Asia rights (Maruho holds Japan/Greater Asia). Preventive market led by CGRP mAbs and gepants; refractory-patient niche.
A58: PoS: Phase 2/2b → Phase 3 | B58: =CHOOSE($B$4,C58,D58,E58) -> 0.2 | C58: 0.15 | D58: 0.2 | E58: 0.3 | F58: Novel mechanism in migraine; the same drug failed Ph2b in CSU (June 2026) and AD (Sept 2026), so target engagement is in question.
A59: PoS: Phase 3 → filing | B59: =CHOOSE($B$4,C59,D59,E59) -> 0.55 | C59: 0.5 | D59: 0.55 | E59: 0.6 | F59: Benchmark: BIO/Informa 2011–2020 Phase III→NDA/BLA ≈ 58%; immunology higher.
A60: PoS: filing → approval | B60: =CHOOSE($B$4,C60,D60,E60) -> 0.9 | C60: 0.9 | D60: 0.9 | E60: 0.92 | F60: Benchmark: BIO/Informa NDA/BLA→approval ≈ 91%.
A61: Cumulative probability of reaching market | B61: =B58*B59*B60 -> 0.099 | C61: =C58*C59*C60 -> 0.0675 | D61: =D58*D59*D60 -> 0.099 | E61: =E58*E59*E60 -> 0.1656
A62: Cost of goods, % of sales | B62: =CHOOSE($B$4,C62,D62,E62) -> 0.05 | C62: 0.05 | D62: 0.05 | E62: 0.05 | F62: Assumption: oral small molecule.
A63: Royalties owed, % of sales | B63: =CHOOSE($B$4,C63,D63,E63) -> 0.03 | C63: 0.03 | D63: 0.03 | E63: 0.03 | F63: Placeholder assumption for third-party IP; no royalty disclosed for EVO756 ex-Asia.
A64: Commercial SG&A at maturity, % of sales | B64: =CHOOSE($B$4,C64,D64,E64) -> 0.3 | C64: 0.3 | D64: 0.3 | E64: 0.3 | F64: Assumption.
A65: Pre-launch commercial spend, year before launch ($mm) | B65: =CHOOSE($B$4,C65,D65,E65) -> 50 | C65: 50 | D65: 50 | E65: 50 | F65: Risked by P(Phase 2b) × P(Phase 3).
A66: Loss of exclusivity (year) | B66: =CHOOSE($B$4,C66,D66,E66) -> 2044 | C66: 2044 | D66: 2044 | E66: 2044 | F66: Composition-of-matter + patent term extension (assumption).
A67: Post-LOE annual sales erosion | B67: =CHOOSE($B$4,C67,D67,E67) -> 0.6 | C67: 0.6 | D67: 0.6 | E67: 0.6 | F67: Small-molecule generic erosion (assumption).
A69: Development cost schedule (unrisked, $mm) | K69: 2026 Ph2b cost sits in the Quarterly Model, so offset −6 (2026) is 0. Ph2b 2027, Ph3 2028–30, NDA 2031.
A70: Years relative to launch | B70: -8 | C70: -7 | D70: -6 | E70: -5 | F70: -4 | G70: -3 | H70: -2 | I70: -1 | J70: 0
A71: Phase | E71: Ph2b | F71: Ph3 | G71: Ph3 | H71: Ph3 | I71: Filing
A72: Unrisked cost ($mm) | B72: 0 | C72: 0 | D72: 0 | E72: 30 | F72: 45 | G72: 85 | H72: 75 | I72: 25 | J72: 0
A73: Probability the cost is incurred | B73: =IF(B71="",0,IF(B71="Ph3",$B$58,IF(B71="Filing",$B$58*$B$59,IF(B71="Approval",$B$61,1)))) -> 0 | C73: =IF(C71="",0,IF(C71="Ph3",$B$58,IF(C71="Filing",$B$58*$B$59,IF(C71="Approval",$B$61,1)))) -> 0 | D73: =IF(D71="",0,IF(D71="Ph3",$B$58,IF(D71="Filing",$B$58*$B$59,IF(D71="Approval",$B$61,1)))) -> 0 | E73: =IF(E71="",0,IF(E71="Ph3",$B$58,IF(E71="Filing",$B$58*$B$59,IF(E71="Approval",$B$61,1)))) -> 1 | F73: =IF(F71="",0,IF(F71="Ph3",$B$58,IF(F71="Filing",$B$58*$B$59,IF(F71="Approval",$B$61,1)))) -> 0.2 | G73: =IF(G71="",0,IF(G71="Ph3",$B$58,IF(G71="Filing",$B$58*$B$59,IF(G71="Approval",$B$61,1)))) -> 0.2 | H73: =IF(H71="",0,IF(H71="Ph3",$B$58,IF(H71="Filing",$B$58*$B$59,IF(H71="Approval",$B$61,1)))) -> 0.2 | I73: =IF(I71="",0,IF(I71="Ph3",$B$58,IF(I71="Filing",$B$58*$B$59,IF(I71="Approval",$B$61,1)))) -> 0.11 | J73: =IF(J71="",0,IF(J71="Ph3",$B$58,IF(J71="Filing",$B$58*$B$59,IF(J71="Approval",$B$61,1)))) -> 0
A75: EVO301 — Additional indications (UC / CV inflammation; Phase 2 planning)
A76: Include in valuation (1 = yes, 0 = no) | B76: =CHOOSE($B$4,C76,D76,E76) -> 1 | C76: 1 | D76: 1 | E76: 1 | F76: Option value; switch off to value the core programs only.
A77: Launch year | B77: =CHOOSE($B$4,C77,D77,E77) -> 2036 | C77: 2036 | D77: 2036 | E77: 2036 | F77: Company is evaluating UC and CV-related inflammatory conditions for Ph2 (Q2 2026 release). Assumes Ph2 start 2028.
A78: Peak WW net sales, unrisked ($mm) | B78: =CHOOSE($B$4,C78,D78,E78) -> 1000 | C78: 500 | D78: 1000 | E78: 1500 | F78: Assumption: option value on the EVO301 molecule beyond AD.
A79: PoS: Phase 2/2b → Phase 3 | B79: =CHOOSE($B$4,C79,D79,E79) -> 0.25 | C79: 0.2 | D79: 0.25 | E79: 0.3 | F79: Earlier stage than AD; benefits from EVO301 safety data.
A80: PoS: Phase 3 → filing | B80: =CHOOSE($B$4,C80,D80,E80) -> 0.55 | C80: 0.55 | D80: 0.55 | E80: 0.6 | F80: Benchmark: BIO/Informa 2011–2020 Phase III→NDA/BLA ≈ 58%; immunology higher.
A81: PoS: filing → approval | B81: =CHOOSE($B$4,C81,D81,E81) -> 0.9 | C81: 0.9 | D81: 0.9 | E81: 0.92 | F81: Benchmark: BIO/Informa NDA/BLA→approval ≈ 91%.
A82: Cumulative probability of reaching market | B82: =B79*B80*B81 -> 0.12375 | C82: =C79*C80*C81 -> 0.099 | D82: =D79*D80*D81 -> 0.12375 | E82: =E79*E80*E81 -> 0.1656
A83: Cost of goods, % of sales | B83: =CHOOSE($B$4,C83,D83,E83) -> 0.12 | C83: 0.12 | D83: 0.12 | E83: 0.12 | F83: Assumption: biologic manufacturing.
A84: Royalties owed, % of sales | B84: =CHOOSE($B$4,C84,D84,E84) -> 0.1 | C84: 0.1 | D84: 0.1 | E84: 0.1 | F84: Same AprilBio royalty as AD.
A85: Commercial SG&A at maturity, % of sales | B85: =CHOOSE($B$4,C85,D85,E85) -> 0.2 | C85: 0.2 | D85: 0.2 | E85: 0.2 | F85: Assumption.
A86: Pre-launch commercial spend, year before launch ($mm) | B86: =CHOOSE($B$4,C86,D86,E86) -> 25 | C86: 25 | D86: 25 | E86: 25 | F86: Risked by P(Phase 2b) × P(Phase 3).
A87: Loss of exclusivity (year) | B87: =CHOOSE($B$4,C87,D87,E87) -> 2045 | C87: 2045 | D87: 2045 | E87: 2045 | F87: Same molecule as AD.
A88: Post-LOE annual sales erosion | B88: =CHOOSE($B$4,C88,D88,E88) -> 0.3 | C88: 0.3 | D88: 0.3 | E88: 0.3 | F88: Assumption: biosimilar erosion.
A90: Development cost schedule (unrisked, $mm) | K90: Assumption: Ph2 2028–30, Ph3 2031–33, filing 2034–35.
A91: Years relative to launch | B91: -8 | C91: -7 | D91: -6 | E91: -5 | F91: -4 | G91: -3 | H91: -2 | I91: -1 | J91: 0
A92: Phase | B92: Ph2 | C92: Ph2 | D92: Ph2 | E92: Ph3 | F92: Ph3 | G92: Ph3 | H92: Filing | I92: Filing
A93: Unrisked cost ($mm) | B93: 15 | C93: 30 | D93: 15 | E93: 60 | F93: 100 | G93: 90 | H93: 30 | I93: 10 | J93: 0
A94: Probability the cost is incurred | B94: =IF(B92="",0,IF(B92="Ph3",$B$79,IF(B92="Filing",$B$79*$B$80,IF(B92="Approval",$B$82,1))))*$B$76 -> 1 | C94: =IF(C92="",0,IF(C92="Ph3",$B$79,IF(C92="Filing",$B$79*$B$80,IF(C92="Approval",$B$82,1))))*$B$76 -> 1 | D94: =IF(D92="",0,IF(D92="Ph3",$B$79,IF(D92="Filing",$B$79*$B$80,IF(D92="Approval",$B$82,1))))*$B$76 -> 1 | E94: =IF(E92="",0,IF(E92="Ph3",$B$79,IF(E92="Filing",$B$79*$B$80,IF(E92="Approval",$B$82,1))))*$B$76 -> 0.25 | F94: =IF(F92="",0,IF(F92="Ph3",$B$79,IF(F92="Filing",$B$79*$B$80,IF(F92="Approval",$B$82,1))))*$B$76 -> 0.25 | G94: =IF(G92="",0,IF(G92="Ph3",$B$79,IF(G92="Filing",$B$79*$B$80,IF(G92="Approval",$B$82,1))))*$B$76 -> 0.25 | H94: =IF(H92="",0,IF(H92="Ph3",$B$79,IF(H92="Filing",$B$79*$B$80,IF(H92="Approval",$B$82,1))))*$B$76 -> 0.1375 | I94: =IF(I92="",0,IF(I92="Ph3",$B$79,IF(I92="Filing",$B$79*$B$80,IF(I92="Approval",$B$82,1))))*$B$76 -> 0.1375 | J94: =IF(J92="",0,IF(J92="Ph3",$B$79,IF(J92="Filing",$B$79*$B$80,IF(J92="Approval",$B$82,1))))*$B$76 -> 0
A96: Portfolio
A97: Probability at least one program reaches market | B97: =1-(1-$B$41)*(1-$B$61)*(1-$B$82*$B$76) -> 0.44142787 | F97: Scales corporate costs after the first launch.
A98: First launch year | B98: =MIN($B$36,$B$56,IF($B$76=1,$B$77,9999)) -> 2032
A101: Sensitivity tables (Excel data tables; recalculate automatically)
A102: If they show stale values, set Formulas → Calculation Options → Automatic (not 'except data tables').
A104: Scenario summary
A105: Scenario | B105: # | C105: Equity value ($mm) | D105: rNPV / share | E105: Upside vs. price | F105: EVO301 AD PV ($/sh) | G105: EVO756 PV ($/sh) | H105: Discount rate
A106: (live = active scenario) | C106: =NPV!C21 -> 251.32623 | D106: =NPV!C27 -> 6.7806114 | E106: =NPV!C29 -> 0.26740399 | F106: =NPV!C37 -> 12.408086 | G106: =NPV!C38 -> 2.2249878 | H106: =Assumptions!$B$14 -> 0.12
A107: Bear | B107: 1 | C107: -94.4876 | D107: -2.5492114 | E107: -1.4764881 | F107: 0.44568578 | G107: -0.53757534 | H107: 0.14
A108: Base | B108: 2 | C108: 251.32623 | D108: 6.7806114 | E108: 0.26740399 | F108: 12.408086 | G108: 2.2249878 | H108: 0.12
A109: Bull | B109: 3 | C109: 1340.1722 | D109: 31.802274 | E109: 4.9443503 | F109: 41.051452 | G109: 12.426867 | H109: 0.1
A111: rNPV / share (diluted): discount rate × scenario
C112: Bear | D112: Base | E112: Bull
A113: Discount rate ↓ / scenario → | B113: =NPV!C27 -> 6.7806114 | C113: 1 | D113: 2 | E113: 3
B114: 0.1 | C114: -1.2277652 | D114: 10.415567 | E114: 31.802274
B115: 0.11 | C115: -1.6860522 | D115: 8.4489664 | E115: 27.546084
...

Sheet Pipeline
A1: EVMN — risk-adjusted pipeline build ($mm)
A2: Year | C2: 2027 | D2: 2028 | E2: 2029 | F2: 2030 | G2: 2031 | H2: 2032 | I2: 2033 | J2: 2034 | K2: 2035 | L2: 2036 | M2: 2037 | N2: 2038 | O2: 2039 | P2: 2040 | Q2: 2041 | R2: 2042 | S2: 2043 | T2: 2044 | U2: 2045 | V2: 2046 | W2: 2047 | X2: 2048 | Y2: 2049 | Z2: 2050
A4: EVO301 — Atopic dermatitis
A5: Years since launch | C5: =C$2-Assumptions!$B$36+1 -> -5 | D5: =D$2-Assumptions!$B$36+1 -> -4 | E5: =E$2-Assumptions!$B$36+1 -> -3 | F5: =F$2-Assumptions!$B$36+1 -> -2 | G5: =G$2-Assumptions!$B$36+1 -> -1 | H5: =H$2-Assumptions!$B$36+1 -> 0 | I5: =I$2-Assumptions!$B$36+1 -> 1 | J5: =J$2-Assumptions!$B$36+1 -> 2 | ... Z5: =Z$2-Assumptions!$B$36+1 -> 18
A6: Net sales, unrisked | C6: =IF(C$2>Assumptions!$B$46,B6*(1-Assumptions!$B$47),IF(C5>=1,Assumptions!$B$37*INDEX(Assumptions!$B$32:$H$32,MIN(C5,7)),0)) -> 0 | D6: =IF(D$2>Assumptions!$B$46,C6*(1-Assumptions!$B$47),IF(D5>=1,Assumptions!$B$37*INDEX(Assumptions!$B$32:$H$32,MIN(D5,7)),0)) -> 0 | E6: =IF(E$2>Assumptions!$B$46,D6*(1-Assumptions!$B$47),IF(E5>=1,Assumptions!$B$37*INDEX(Assumptions!$B$32:$H$32,MIN(E5,7)),0)) -> 0 | F6: =IF(F$2>Assumptions!$B$46,E6*(1-Assumptions!$B$47),IF(F5>=1,Assumptions!$B$37*INDEX(Assumptions!$B$32:$H$32,MIN(F5,7)),0)) -> 0 | G6: =IF(G$2>Assumptions!$B$46,F6*(1-Assumptions!$B$47),IF(G5>=1,Assumptions!$B$37*INDEX(Assumptions!$B$32:$H$32,MIN(G5,7)),0)) -> 0 | H6: =IF(H$2>Assumptions!$B$46,G6*(1-Assumptions!$B$47),IF(H5>=1,Assumptions!$B$37*INDEX(Assumptions!$B$32:$H$32,MIN(H5,7)),0)) -> 0 | I6: =IF(I$2>Assumptions!$B$46,H6*(1-Assumptions!$B$47),IF(I5>=1,Assumptions!$B$37*INDEX(Assumptions!$B$32:$H$32,MIN(I5,7)),0)) -> 160 | J6: =IF(J$2>Assumptions!$B$46,I6*(1-Assumptions!$B$47),IF(J5>=1,Assumptions!$B$37*INDEX(Assumptions!$B$32:$H$32,MIN(J5,7)),0)) -> 400 | ... Z6: =IF(Z$2>Assumptions!$B$46,Y6*(1-Assumptions!$B$47),IF(Z5>=1,Assumptions!$B$37*INDEX(Assumptions!$B$32:$H$32,MIN(Z5,7)),0)) -> 336.14
A7: Probability of reaching market | C7: =Assumptions!$B$41 -> 0.2925 | D7: =Assumptions!$B$41 -> 0.2925 | E7: =Assumptions!$B$41 -> 0.2925 | F7: =Assumptions!$B$41 -> 0.2925 | G7: =Assumptions!$B$41 -> 0.2925 | H7: =Assumptions!$B$41 -> 0.2925 | I7: =Assumptions!$B$41 -> 0.2925 | J7: =Assumptions!$B$41 -> 0.2925 | ... Z7: =Assumptions!$B$41 -> 0.2925
A8: Net sales, risk-adjusted | C8: =C6*C7 -> 0 | D8: =D6*D7 -> 0 | E8: =E6*E7 -> 0 | F8: =F6*F7 -> 0 | G8: =G6*G7 -> 0 | H8: =H6*H7 -> 0 | I8: =I6*I7 -> 46.8 | J8: =J6*J7 -> 117 | ... Z8: =Z6*Z7 -> 98.32095
A9: COGS + royalties, risk-adjusted | C9: =C8*(Assumptions!$B$42+Assumptions!$B$43) -> 0 | D9: =D8*(Assumptions!$B$42+Assumptions!$B$43) -> 0 | E9: =E8*(Assumptions!$B$42+Assumptions!$B$43) -> 0 | F9: =F8*(Assumptions!$B$42+Assumptions!$B$43) -> 0 | G9: =G8*(Assumptions!$B$42+Assumptions!$B$43) -> 0 | H9: =H8*(Assumptions!$B$42+Assumptions!$B$43) -> 0 | I9: =I8*(Assumptions!$B$42+Assumptions!$B$43) -> 10.296 | J9: =J8*(Assumptions!$B$42+Assumptions!$B$43) -> 25.74 | ... Z9: =Z8*(Assumptions!$B$42+Assumptions!$B$43) -> 21.630609
A10: Commercial SG&A, risk-adjusted | C10: =IF(C5=0,Assumptions!$B$45*Assumptions!$B$38*Assumptions!$B$39,IF(C5>=1,C6*IF(C5<=5,INDEX(Assumptions!$B$33:$F$33,C5),Assumptions!$B$44)*C7,0)) -> 0 | D10: =IF(D5=0,Assumptions!$B$45*Assumptions!$B$38*Assumptions!$B$39,IF(D5>=1,D6*IF(D5<=5,INDEX(Assumptions!$B$33:$F$33,D5),Assumptions!$B$44)*D7,0)) -> 0 | E10: =IF(E5=0,Assumptions!$B$45*Assumptions!$B$38*Assumptions!$B$39,IF(E5>=1,E6*IF(E5<=5,INDEX(Assumptions!$B$33:$F$33,E5),Assumptions!$B$44)*E7,0)) -> 0 | F10: =IF(F5=0,Assumptions!$B$45*Assumptions!$B$38*Assumptions!$B$39,IF(F5>=1,F6*IF(F5<=5,INDEX(Assumptions!$B$33:$F$33,F5),Assumptions!$B$44)*F7,0)) -> 0 | G10: =IF(G5=0,Assumptions!$B$45*Assumptions!$B$38*Assumptions!$B$39,IF(G5>=1,G6*IF(G5<=5,INDEX(Assumptions!$B$33:$F$33,G5),Assumptions!$B$44)*G7,0)) -> 0 | H10: =IF(H5=0,Assumptions!$B$45*Assumptions!$B$38*Assumptions!$B$39,IF(H5>=1,H6*IF(H5<=5,INDEX(Assumptions!$B$33:$F$33,H5),Assumptions!$B$44)*H7,0)) -> 19.5 | I10: =IF(I5=0,Assumptions!$B$45*Assumptions!$B$38*Assumptions!$B$39,IF(I5>=1,I6*IF(I5<=5,INDEX(Assumptions!$B$33:$F$33,I5),Assumptions!$B$44)*I7,0)) -> 42.12 | J10: =IF(J5=0,Assumptions!$B$45*Assumptions!$B$38*Assumptions!$B$39,IF(J5>=1,J6*IF(J5<=5,INDEX(Assumptions!$B$33:$F$33,J5),Assumptions!$B$44)*J7,0)) -> 64.35 | ... Z10: =IF(Z5=0,Assumptions!$B$45*Assumptions!$B$38*Assumptions!$B$39,IF(Z5>=1,Z6*IF(Z5<=5,INDEX(Assumptions!$B$33:$F$33,Z5),Assumptions!$B$44)*Z7,0)) -> 24.580237
A11: Development R&D, risk-adjusted | C11: =IFERROR(INDEX(Assumptions!$B$52:$J$52,MATCH(C$2-Assumptions!$B$36,Assumptions!$B$50:$J$50,0))*INDEX(Assumptions!$B$53:$J$53,MATCH(C$2-Assumptions!$B$36,Assumptions!$B$50:$J$50,0)),0) -> 25 | D11: =IFERROR(INDEX(Assumptions!$B$52:$J$52,MATCH(D$2-Assumptions!$B$36,Assumptions!$B$50:$J$50,0))*INDEX(Assumptions!$B$53:$J$53,MATCH(D$2-Assumptions!$B$36,Assumptions!$B$50:$J$50,0)),0) -> 45 | E11: =IFERROR(INDEX(Assumptions!$B$52:$J$52,MATCH(E$2-Assumptions!$B$36,Assumptions!$B$50:$J$50,0))*INDEX(Assumptions!$B$53:$J$53,MATCH(E$2-Assumptions!$B$36,Assumptions!$B$50:$J$50,0)),0) -> 52.5 | F11: =IFERROR(INDEX(Assumptions!$B$52:$J$52,MATCH(F$2-Assumptions!$B$36,Assumptions!$B$50:$J$50,0))*INDEX(Assumptions!$B$53:$J$53,MATCH(F$2-Assumptions!$B$36,Assumptions!$B$50:$J$50,0)),0) -> 70 | G11: =IFERROR(INDEX(Assumptions!$B$52:$J$52,MATCH(G$2-Assumptions!$B$36,Assumptions!$B$50:$J$50,0))*INDEX(Assumptions!$B$53:$J$53,MATCH(G$2-Assumptions!$B$36,Assumptions!$B$50:$J$50,0)),0) -> 55 | H11: =IFERROR(INDEX(Assumptions!$B$52:$J$52,MATCH(H$2-Assumptions!$B$36,Assumptions!$B$50:$J$50,0))*INDEX(Assumptions!$B$53:$J$53,MATCH(H$2-Assumptions!$B$36,Assumptions!$B$50:$J$50,0)),0) -> 21.125 | I11: =IFERROR(INDEX(Assumptions!$B$52:$J$52,MATCH(I$2-Assumptions!$B$36,Assumptions!$B$50:$J$50,0))*INDEX(Assumptions!$B$53:$J$53,MATCH(I$2-Assumptions!$B$36,Assumptions!$B$50:$J$50,0)),0) -> 11.7 | J11: =IFERROR(INDEX(Assumptions!$B$52:$J$52,MATCH(J$2-Assumptions!$B$36,Assumptions!$B$50:$J$50,0))*INDEX(Assumptions!$B$53:$J$53,MATCH(J$2-Assumptions!$B$36,Assumptions!$B$50:$J$50,0)),0) -> 0 | ... Z11: =IFERROR(INDEX(Assumptions!$B$52:$J$52,MATCH(Z$2-Assumptions!$B$36,Assumptions!$B$50:$J$50,0))*INDEX(Assumptions!$B$53:$J$53,MATCH(Z$2-Assumptions!$B$36,Assumptions!$B$50:$J$50,0)),0) -> 0
A12: Program contribution (pre-tax) | C12: =C8-C9-C10-C11 -> -25 | D12: =D8-D9-D10-D11 -> -45 | E12: =E8-E9-E10-E11 -> -52.5 | F12: =F8-F9-F10-F11 -> -70 | G12: =G8-G9-G10-G11 -> -55 | H12: =H8-H9-H10-H11 -> -40.625 | I12: =I8-I9-I10-I11 -> -17.316 | J12: =J8-J9-J10-J11 -> 26.91 | ... Z12: =Z8-Z9-Z10-Z11 -> 52.110103
A14: EVO756 — Migraine prophylaxis
A15: Years since launch | C15: =C$2-Assumptions!$B$56+1 -> -4 | D15: =D$2-Assumptions!$B$56+1 -> -3 | E15: =E$2-Assumptions!$B$56+1 -> -2 | F15: =F$2-Assumptions!$B$56+1 -> -1 | G15: =G$2-Assumptions!$B$56+1 -> 0 | H15: =H$2-Assumptions!$B$56+1 -> 1 | I15: =I$2-Assumptions!$B$56+1 -> 2 | J15: =J$2-Assumptions!$B$56+1 -> 3 | ... Z15: =Z$2-Assumptions!$B$56+1 -> 19
A16: Net sales, unrisked | C16: =IF(C$2>Assumptions!$B$66,B16*(1-Assumptions!$B$67),IF(C15>=1,Assumptions!$B$57*INDEX(Assumptions!$B$32:$H$32,MIN(C15,7)),0)) -> 0 | D16: =IF(D$2>Assumptions!$B$66,C16*(1-Assumptions!$B$67),IF(D15>=1,Assumptions!$B$57*INDEX(Assumptions!$B$32:$H$32,MIN(D15,7)),0)) -> 0 | E16: =IF(E$2>Assumptions!$B$66,D16*(1-Assumptions!$B$67),IF(E15>=1,Assumptions!$B$57*INDEX(Assumptions!$B$32:$H$32,MIN(E15,7)),0)) -> 0 | F16: =IF(F$2>Assumptions!$B$66,E16*(1-Assumptions!$B$67),IF(F15>=1,Assumptions!$B$57*INDEX(Assumptions!$B$32:$H$32,MIN(F15,7)),0)) -> 0 | G16: =IF(G$2>Assumptions!$B$66,F16*(1-Assumptions!$B$67),IF(G15>=1,Assumptions!$B$57*INDEX(Assumptions!$B$32:$H$32,MIN(G15,7)),0)) -> 0 | H16: =IF(H$2>Assumptions!$B$66,G16*(1-Assumptions!$B$67),IF(H15>=1,Assumptions!$B$57*INDEX(Assumptions!$B$32:$H$32,MIN(H15,7)),0)) -> 80 | I16: =IF(I$2>Assumptions!$B$66,H16*(1-Assumptions!$B$67),IF(I15>=1,Assumptions!$B$57*INDEX(Assumptions!$B$32:$H$32,MIN(I15,7)),0)) -> 200 | J16: =IF(J$2>Assumptions!$B$66,I16*(1-Assumptions!$B$67),IF(J15>=1,Assumptions!$B$57*INDEX(Assumptions!$B$32:$H$32,MIN(J15,7)),0)) -> 380 | ... Z16: =IF(Z$2>Assumptions!$B$66,Y16*(1-Assumptions!$B$67),IF(Z15>=1,Assumptions!$B$57*INDEX(Assumptions!$B$32:$H$32,MIN(Z15,7)),0)) -> 4.096
A17: Probability of reaching market | C17: =Assumptions!$B$61 -> 0.099 | D17: =Assumptions!$B$61 -> 0.099 | E17: =Assumptions!$B$61 -> 0.099 | F17: =Assumptions!$B$61 -> 0.099 | G17: =Assumptions!$B$61 -> 0.099 | H17: =Assumptions!$B$61 -> 0.099 | I17: =Assumptions!$B$61 -> 0.099 | J17: =Assumptions!$B$61 -> 0.099 | ... Z17: =Assumptions!$B$61 -> 0.099
A18: Net sales, risk-adjusted | C18: =C16*C17 -> 0 | D18: =D16*D17 -> 0 | E18: =E16*E17 -> 0 | F18: =F16*F17 -> 0 | G18: =G16*G17 -> 0 | H18: =H16*H17 -> 7.92 | I18: =I16*I17 -> 19.8 | J18: =J16*J17 -> 37.62 | ... Z18: =Z16*Z17 -> 0.405504
A19: COGS + royalties, risk-adjusted | C19: =C18*(Assumptions!$B$62+Assumptions!$B$63) -> 0 | D19: =D18*(Assumptions!$B$62+Assumptions!$B$63) -> 0 | E19: =E18*(Assumptions!$B$62+Assumptions!$B$63) -> 0 | F19: =F18*(Assumptions!$B$62+Assumptions!$B$63) -> 0 | G19: =G18*(Assumptions!$B$62+Assumptions!$B$63) -> 0 | H19: =H18*(Assumptions!$B$62+Assumptions!$B$63) -> 0.6336 | I19: =I18*(Assumptions!$B$62+Assumptions!$B$63) -> 1.584 | J19: =J18*(Assumptions!$B$62+Assumptions!$B$63) -> 3.0096 | ... Z19: =Z18*(Assumptions!$B$62+Assumptions!$B$63) -> 0.03244032
A20: Commercial SG&A, risk-adjusted | C20: =IF(C15=0,Assumptions!$B$65*Assumptions!$B$58*Assumptions!$B$59,IF(C15>=1,C16*IF(C15<=5,INDEX(Assumptions!$B$33:$F$33,C15),Assumptions!$B$64)*C17,0)) -> 0 | D20: =IF(D15=0,Assumptions!$B$65*Assumptions!$B$58*Assumptions!$B$59,IF(D15>=1,D16*IF(D15<=5,INDEX(Assumptions!$B$33:$F$33,D15),Assumptions!$B$64)*D17,0)) -> 0 | E20: =IF(E15=0,Assumptions!$B$65*Assumptions!$B$58*Assumptions!$B$59,IF(E15>=1,E16*IF(E15<=5,INDEX(Assumptions!$B$33:$F$33,E15),Assumptions!$B$64)*E17,0)) -> 0 | F20: =IF(F15=0,Assumptions!$B$65*Assumptions!$B$58*Assumptions!$B$59,IF(F15>=1,F16*IF(F15<=5,INDEX(Assumptions!$B$33:$F$33,F15),Assumptions!$B$64)*F17,0)) -> 0 | G20: =IF(G15=0,Assumptions!$B$65*Assumptions!$B$58*Assumptions!$B$59,IF(G15>=1,G16*IF(G15<=5,INDEX(Assumptions!$B$33:$F$33,G15),Assumptions!$B$64)*G17,0)) -> 5.5 | H20: =IF(H15=0,Assumptions!$B$65*Assumptions!$B$58*Assumptions!$B$59,IF(H15>=1,H16*IF(H15<=5,INDEX(Assumptions!$B$33:$F$33,H15),Assumptions!$B$64)*H17,0)) -> 7.128 | I20: =IF(I15=0,Assumptions!$B$65*Assumptions!$B$58*Assumptions!$B$59,IF(I15>=1,I16*IF(I15<=5,INDEX(Assumptions!$B$33:$F$33,I15),Assumptions!$B$64)*I17,0)) -> 10.89 | J20: =IF(J15=0,Assumptions!$B$65*Assumptions!$B$58*Assumptions!$B$59,IF(J15>=1,J16*IF(J15<=5,INDEX(Assumptions!$B$33:$F$33,J15),Assumptions!$B$64)*J17,0)) -> 15.048 | ... Z20: =IF(Z15=0,Assumptions!$B$65*Assumptions!$B$58*Assumptions!$B$59,IF(Z15>=1,Z16*IF(Z15<=5,INDEX(Assumptions!$B$33:$F$33,Z15),Assumptions!$B$64)*Z17,0)) -> 0.1216512
A21: Development R&D, risk-adjusted | C21: =IFERROR(INDEX(Assumptions!$B$72:$J$72,MATCH(C$2-Assumptions!$B$56,Assumptions!$B$70:$J$70,0))*INDEX(Assumptions!$B$73:$J$73,MATCH(C$2-Assumptions!$B$56,Assumptions!$B$70:$J$70,0)),0) -> 30 | D21: =IFERROR(INDEX(Assumptions!$B$72:$J$72,MATCH(D$2-Assumptions!$B$56,Assumptions!$B$70:$J$70,0))*INDEX(Assumptions!$B$73:$J$73,MATCH(D$2-Assumptions!$B$56,Assumptions!$B$70:$J$70,0)),0) -> 9 | E21: =IFERROR(INDEX(Assumptions!$B$72:$J$72,MATCH(E$2-Assumptions!$B$56,Assumptions!$B$70:$J$70,0))*INDEX(Assumptions!$B$73:$J$73,MATCH(E$2-Assumptions!$B$56,Assumptions!$B$70:$J$70,0)),0) -> 17 | F21: =IFERROR(INDEX(Assumptions!$B$72:$J$72,MATCH(F$2-Assumptions!$B$56,Assumptions!$B$70:$J$70,0))*INDEX(Assumptions!$B$73:$J$73,MATCH(F$2-Assumptions!$B$56,Assumptions!$B$70:$J$70,0)),0) -> 15 | G21: =IFERROR(INDEX(Assumptions!$B$72:$J$72,MATCH(G$2-Assumptions!$B$56,Assumptions!$B$70:$J$70,0))*INDEX(Assumptions!$B$73:$J$73,MATCH(G$2-Assumptions!$B$56,Assumptions!$B$70:$J$70,0)),0) -> 2.75 | H21: =IFERROR(INDEX(Assumptions!$B$72:$J$72,MATCH(H$2-Assumptions!$B$56,Assumptions!$B$70:$J$70,0))*INDEX(Assumptions!$B$73:$J$73,MATCH(H$2-Assumptions!$B$56,Assumptions!$B$70:$J$70,0)),0) -> 0 | I21: =IFERROR(INDEX(Assumptions!$B$72:$J$72,MATCH(I$2-Assumptions!$B$56,Assumptions!$B$70:$J$70,0))*INDEX(Assumptions!$B$73:$J$73,MATCH(I$2-Assumptions!$B$56,Assumptions!$B$70:$J$70,0)),0) -> 0 | J21: =IFERROR(INDEX(Assumptions!$B$72:$J$72,MATCH(J$2-Assumptions!$B$56,Assumptions!$B$70:$J$70,0))*INDEX(Assumptions!$B$73:$J$73,MATCH(J$2-Assumptions!$B$56,Assumptions!$B$70:$J$70,0)),0) -> 0 | ... Z21: =IFERROR(INDEX(Assumptions!$B$72:$J$72,MATCH(Z$2-Assumptions!$B$56,Assumptions!$B$70:$J$70,0))*INDEX(Assumptions!$B$73:$J$73,MATCH(Z$2-Assumptions!$B$56,Assumptions!$B$70:$J$70,0)),0) -> 0
A22: Program contribution (pre-tax) | C22: =C18-C19-C20-C21 -> -30 | D22: =D18-D19-D20-D21 -> -9 | E22: =E18-E19-E20-E21 -> -17 | F22: =F18-F19-F20-F21 -> -15 | G22: =G18-G19-G20-G21 -> -8.25 | H22: =H18-H19-H20-H21 -> 0.1584 | I22: =I18-I19-I20-I21 -> 7.326 | J22: =J18-J19-J20-J21 -> 19.5624 | ... Z22: =Z18-Z19-Z20-Z21 -> 0.25141248
A24: EVO301 — Additional indications
A25: Years since launch | C25: =C$2-Assumptions!$B$77+1 -> -8 | D25: =D$2-Assumptions!$B$77+1 -> -7 | E25: =E$2-Assumptions!$B$77+1 -> -6 | F25: =F$2-Assumptions!$B$77+1 -> -5 | G25: =G$2-Assumptions!$B$77+1 -> -4 | H25: =H$2-Assumptions!$B$77+1 -> -3 | I25: =I$2-Assumptions!$B$77+1 -> -2 | J25: =J$2-Assumptions!$B$77+1 -> -1 | ... Z25: =Z$2-Assumptions!$B$77+1 -> 15
A26: Net sales, unrisked | C26: =IF(C$2>Assumptions!$B$87,B26*(1-Assumptions!$B$88),IF(C25>=1,Assumptions!$B$78*INDEX(Assumptions!$B$32:$H$32,MIN(C25,7)),0)) -> 0 | D26: =IF(D$2>Assumptions!$B$87,C26*(1-Assumptions!$B$88),IF(D25>=1,Assumptions!$B$78*INDEX(Assumptions!$B$32:$H$32,MIN(D25,7)),0)) -> 0 | E26: =IF(E$2>Assumptions!$B$87,D26*(1-Assumptions!$B$88),IF(E25>=1,Assumptions!$B$78*INDEX(Assumptions!$B$32:$H$32,MIN(E25,7)),0)) -> 0 | F26: =IF(F$2>Assumptions!$B$87,E26*(1-Assumptions!$B$88),IF(F25>=1,Assumptions!$B$78*INDEX(Assumptions!$B$32:$H$32,MIN(F25,7)),0)) -> 0 | G26: =IF(G$2>Assumptions!$B$87,F26*(1-Assumptions!$B$88),IF(G25>=1,Assumptions!$B$78*INDEX(Assumptions!$B$32:$H$32,MIN(G25,7)),0)) -> 0 | H26: =IF(H$2>Assumptions!$B$87,G26*(1-Assumptions!$B$88),IF(H25>=1,Assumptions!$B$78*INDEX(Assumptions!$B$32:$H$32,MIN(H25,7)),0)) -> 0 | I26: =IF(I$2>Assumptions!$B$87,H26*(1-Assumptions!$B$88),IF(I25>=1,Assumptions!$B$78*INDEX(Assumptions!$B$32:$H$32,MIN(I25,7)),0)) -> 0 | J26: =IF(J$2>Assumptions!$B$87,I26*(1-Assumptions!$B$88),IF(J25>=1,Assumptions!$B$78*INDEX(Assumptions!$B$32:$H$32,MIN(J25,7)),0)) -> 0 | ... Z26: =IF(Z$2>Assumptions!$B$87,Y26*(1-Assumptions!$B$88),IF(Z25>=1,Assumptions!$B$78*INDEX(Assumptions!$B$32:$H$32,MIN(Z25,7)),0)) -> 168.07
A27: Probability of reaching market | C27: =Assumptions!$B$82*Assumptions!$B$76 -> 0.12375 | D27: =Assumptions!$B$82*Assumptions!$B$76 -> 0.12375 | E27: =Assumptions!$B$82*Assumptions!$B$76 -> 0.12375 | F27: =Assumptions!$B$82*Assumptions!$B$76 -> 0.12375 | G27: =Assumptions!$B$82*Assumptions!$B$76 -> 0.12375 | H27: =Assumptions!$B$82*Assumptions!$B$76 -> 0.12375 | I27: =Assumptions!$B$82*Assumptions!$B$76 -> 0.12375 | J27: =Assumptions!$B$82*Assumptions!$B$76 -> 0.12375 | ... Z27: =Assumptions!$B$82*Assumptions!$B$76 -> 0.12375
A28: Net sales, risk-adjusted | C28: =C26*C27 -> 0 | D28: =D26*D27 -> 0 | E28: =E26*E27 -> 0 | F28: =F26*F27 -> 0 | G28: =G26*G27 -> 0 | H28: =H26*H27 -> 0 | I28: =I26*I27 -> 0 | J28: =J26*J27 -> 0 | ... Z28: =Z26*Z27 -> 20.798662
A29: COGS + royalties, risk-adjusted | C29: =C28*(Assumptions!$B$83+Assumptions!$B$84) -> 0 | D29: =D28*(Assumptions!$B$83+Assumptions!$B$84) -> 0 | E29: =E28*(Assumptions!$B$83+Assumptions!$B$84) -> 0 | F29: =F28*(Assumptions!$B$83+Assumptions!$B$84) -> 0 | G29: =G28*(Assumptions!$B$83+Assumptions!$B$84) -> 0 | H29: =H28*(Assumptions!$B$83+Assumptions!$B$84) -> 0 | I29: =I28*(Assumptions!$B$83+Assumptions!$B$84) -> 0 | J29: =J28*(Assumptions!$B$83+Assumptions!$B$84) -> 0 | ... Z29: =Z28*(Assumptions!$B$83+Assumptions!$B$84) -> 4.5757057
A30: Commercial SG&A, risk-adjusted | C30: =IF(C25=0,Assumptions!$B$86*Assumptions!$B$79*Assumptions!$B$80*Assumptions!$B$76,IF(C25>=1,C26*IF(C25<=5,INDEX(Assumptions!$B$33:$F$33,C25),Assumptions!$B$85)*C27,0)) -> 0 | D30: =IF(D25=0,Assumptions!$B$86*Assumptions!$B$79*Assumptions!$B$80*Assumptions!$B$76,IF(D25>=1,D26*IF(D25<=5,INDEX(Assumptions!$B$33:$F$33,D25),Assumptions!$B$85)*D27,0)) -> 0 | E30: =IF(E25=0,Assumptions!$B$86*Assumptions!$B$79*Assumptions!$B$80*Assumptions!$B$76,IF(E25>=1,E26*IF(E25<=5,INDEX(Assumptions!$B$33:$F$33,E25),Assumptions!$B$85)*E27,0)) -> 0 | F30: =IF(F25=0,Assumptions!$B$86*Assumptions!$B$79*Assumptions!$B$80*Assumptions!$B$76,IF(F25>=1,F26*IF(F25<=5,INDEX(Assumptions!$B$33:$F$33,F25),Assumptions!$B$85)*F27,0)) -> 0 | G30: =IF(G25=0,Assumptions!$B$86*Assumptions!$B$79*Assumptions!$B$80*Assumptions!$B$76,IF(G25>=1,G26*IF(G25<=5,INDEX(Assumptions!$B$33:$F$33,G25),Assumptions!$B$85)*G27,0)) -> 0 | H30: =IF(H25=0,Assumptions!$B$86*Assumptions!$B$79*Assumptions!$B$80*Assumptions!$B$76,IF(H25>=1,H26*IF(H25<=5,INDEX(Assumptions!$B$33:$F$33,H25),Assumptions!$B$85)*H27,0)) -> 0 | I30: =IF(I25=0,Assumptions!$B$86*Assumptions!$B$79*Assumptions!$B$80*Assumptions!$B$76,IF(I25>=1,I26*IF(I25<=5,INDEX(Assumptions!$B$33:$F$33,I25),Assumptions!$B$85)*I27,0)) -> 0 | J30: =IF(J25=0,Assumptions!$B$86*Assumptions!$B$79*Assumptions!$B$80*Assumptions!$B$76,IF(J25>=1,J26*IF(J25<=5,INDEX(Assumptions!$B$33:$F$33,J25),Assumptions!$B$85)*J27,0)) -> 0 | ... Z30: =IF(Z25=0,Assumptions!$B$86*Assumptions!$B$79*Assumptions!$B$80*Assumptions!$B$76,IF(Z25>=1,Z26*IF(Z25<=5,INDEX(Assumptions!$B$33:$F$33,Z25),Assumptions!$B$85)*Z27,0)) -> 4.1597325
A31: Development R&D, risk-adjusted | C31: =IFERROR(INDEX(Assumptions!$B$93:$J$93,MATCH(C$2-Assumptions!$B$77,Assumptions!$B$91:$J$91,0))*INDEX(Assumptions!$B$94:$J$94,MATCH(C$2-Assumptions!$B$77,Assumptions!$B$91:$J$91,0)),0) -> 0 | D31: =IFERROR(INDEX(Assumptions!$B$93:$J$93,MATCH(D$2-Assumptions!$B$77,Assumptions!$B$91:$J$91,0))*INDEX(Assumptions!$B$94:$J$94,MATCH(D$2-Assumptions!$B$77,Assumptions!$B$91:$J$91,0)),0) -> 15 | E31: =IFERROR(INDEX(Assumptions!$B$93:$J$93,MATCH(E$2-Assumptions!$B$77,Assumptions!$B$91:$J$91,0))*INDEX(Assumptions!$B$94:$J$94,MATCH(E$2-Assumptions!$B$77,Assumptions!$B$91:$J$91,0)),0) -> 30 | F31: =IFERROR(INDEX(Assumptions!$B$93:$J$93,MATCH(F$2-Assumptions!$B$77,Assumptions!$B$91:$J$91,0))*INDEX(Assumptions!$B$94:$J$94,MATCH(F$2-Assumptions!$B$77,Assumptions!$B$91:$J$91,0)),0) -> 15 | G31: =IFERROR(INDEX(Assumptions!$B$93:$J$93,MATCH(G$2-Assumptions!$B$77,Assumptions!$B$91:$J$91,0))*INDEX(Assumptions!$B$94:$J$94,MATCH(G$2-Assumptions!$B$77,Assumptions!$B$91:$J$91,0)),0) -> 15 | H31: =IFERROR(INDEX(Assumptions!$B$93:$J$93,MATCH(H$2-Assumptions!$B$77,Assumptions!$B$91:$J$91,0))*INDEX(Assumptions!$B$94:$J$94,MATCH(H$2-Assumptions!$B$77,Assumptions!$B$91:$J$91,0)),0) -> 25 | I31: =IFERROR(INDEX(Assumptions!$B$93:$J$93,MATCH(I$2-Assumptions!$B$77,Assumptions!$B$91:$J$91,0))*INDEX(Assumptions!$B$94:$J$94,MATCH(I$2-Assumptions!$B$77,Assumptions!$B$91:$J$91,0)),0) -> 22.5 | J31: =IFERROR(INDEX(Assumptions!$B$93:$J$93,MATCH(J$2-Assumptions!$B$77,Assumptions!$B$91:$J$91,0))*INDEX(Assumptions!$B$94:$J$94,MATCH(J$2-Assumptions!$B$77,Assumptions!$B$91:$J$91,0)),0) -> 4.125 | ... Z31: =IFERROR(INDEX(Assumptions!$B$93:$J$93,MATCH(Z$2-Assumptions!$B$77,Assumptions!$B$91:$J$91,0))*INDEX(Assumptions!$B$94:$J$94,MATCH(Z$2-Assumptions!$B$77,Assumptions!$B$91:$J$91,0)),0) -> 0
A32: Program contribution (pre-tax) | C32: =C28-C29-C30-C31 -> 0 | D32: =D28-D29-D30-D31 -> -15 | E32: =E28-E29-E30-E31 -> -30 | F32: =F28-F29-F30-F31 -> -15 | G32: =G28-G29-G30-G31 -> -15 | H32: =H28-H29-H30-H31 -> -25 | I32: =I28-I29-I30-I31 -> -22.5 | J32: =J28-J29-J30-J31 -> -4.125 | ... Z32: =Z28-Z29-Z30-Z31 -> 12.063224
A34: Company totals (risk-adjusted)
A35: Revenue | C35: =C8+C18+C28 -> 0 | D35: =D8+D18+D28 -> 0 | E35: =E8+E18+E28 -> 0 | F35: =F8+F18+F28 -> 0 | G35: =G8+G18+G28 -> 0 | H35: =H8+H18+H28 -> 7.92 | I35: =I8+I18+I28 -> 66.6 | J35: =J8+J18+J28 -> 154.62 | ... Z35: =Z8+Z18+Z28 -> 119.52512
A36: Cost of sales (COGS + royalties) | C36: =C9+C19+C29 -> 0 | D36: =D9+D19+D29 -> 0 | E36: =E9+E19+E29 -> 0 | F36: =F9+F19+F29 -> 0 | G36: =G9+G19+G29 -> 0 | H36: =H9+H19+H29 -> 0.6336 | I36: =I9+I19+I29 -> 11.88 | J36: =J9+J19+J29 -> 28.7496 | ... Z36: =Z9+Z19+Z29 -> 26.238755
A37: Program development R&D | C37: =C11+C21+C31 -> 55 | D37: =D11+D21+D31 -> 69 | E37: =E11+E21+E31 -> 99.5 | F37: =F11+F21+F31 -> 100 | G37: =G11+G21+G31 -> 72.75 | H37: =H11+H21+H31 -> 46.125 | I37: =I11+I21+I31 -> 34.2 | J37: =J11+J21+J31 -> 4.125 | ... Z37: =Z11+Z21+Z31 -> 0
A38: Platform / lifecycle R&D | C38: =IF(C$2<Assumptions!$B$98,Assumptions!$B$19*(1+Assumptions!$B$20)^(C$2-$C$2),MAX(Assumptions!$B$19*(1+Assumptions!$B$20)^(C$2-$C$2)*Assumptions!$B$97,Assumptions!$B$22*C35)) -> 16 | D38: =IF(D$2<Assumptions!$B$98,Assumptions!$B$19*(1+Assumptions!$B$20)^(D$2-$C$2),MAX(Assumptions!$B$19*(1+Assumptions!$B$20)^(D$2-$C$2)*Assumptions!$B$97,Assumptions!$B$22*D35)) -> 16.48 | E38: =IF(E$2<Assumptions!$B$98,Assumptions!$B$19*(1+Assumptions!$B$20)^(E$2-$C$2),MAX(Assumptions!$B$19*(1+Assumptions!$B$20)^(E$2-$C$2)*Assumptions!$B$97,Assumptions!$B$22*E35)) -> 16.9744 | F38: =IF(F$2<Assumptions!$B$98,Assumptions!$B$19*(1+Assumptions!$B$20)^(F$2-$C$2),MAX(Assumptions!$B$19*(1+Assumptions!$B$20)^(F$2-$C$2)*Assumptions!$B$97,Assumptions!$B$22*F35)) -> 17.483632 | G38: =IF(G$2<Assumptions!$B$98,Assumptions!$B$19*(1+Assumptions!$B$20)^(G$2-$C$2),MAX(Assumptions!$B$19*(1+Assumptions!$B$20)^(G$2-$C$2)*Assumptions!$B$97,Assumptions!$B$22*G35)) -> 18.008141 | H38: =IF(H$2<Assumptions!$B$98,Assumptions!$B$19*(1+Assumptions!$B$20)^(H$2-$C$2),MAX(Assumptions!$B$19*(1+Assumptions!$B$20)^(H$2-$C$2)*Assumptions!$B$97,Assumptions!$B$22*H35)) -> 8.1877741 | I38: =IF(I$2<Assumptions!$B$98,Assumptions!$B$19*(1+Assumptions!$B$20)^(I$2-$C$2),MAX(Assumptions!$B$19*(1+Assumptions!$B$20)^(I$2-$C$2)*Assumptions!$B$97,Assumptions!$B$22*I35)) -> 8.4334073 | J38: =IF(J$2<Assumptions!$B$98,Assumptions!$B$19*(1+Assumptions!$B$20)^(J$2-$C$2),MAX(Assumptions!$B$19*(1+Assumptions!$B$20)^(J$2-$C$2)*Assumptions!$B$97,Assumptions!$B$22*J35)) -> 8.6864095 | ... Z38: =IF(Z$2<Assumptions!$B$98,Assumptions!$B$19*(1+Assumptions!$B$20)^(Z$2-$C$2),MAX(Assumptions!$B$19*(1+Assumptions!$B$20)^(Z$2-$C$2)*Assumptions!$B$97,Assumptions!$B$22*Z35)) -> 13.939137
A39: Total R&D | C39: =C37+C38 -> 71 | D39: =D37+D38 -> 85.48 | E39: =E37+E38 -> 116.4744 | F39: =F37+F38 -> 117.48363 | G39: =G37+G38 -> 90.758141 | H39: =H37+H38 -> 54.312774 | I39: =I37+I38 -> 42.633407 | J39: =J37+J38 -> 12.81141 | ... Z39: =Z37+Z38 -> 13.939137
A40: Commercial SG&A | C40: =C10+C20+C30 -> 0 | D40: =D10+D20+D30 -> 0 | E40: =E10+E20+E30 -> 0 | F40: =F10+F20+F30 -> 0 | G40: =G10+G20+G30 -> 5.5 | H40: =H10+H20+H30 -> 26.628 | I40: =I10+I20+I30 -> 53.01 | J40: =J10+J20+J30 -> 79.398 | ... Z40: =Z10+Z20+Z30 -> 28.861621
A41: Corporate G&A | C41: =IF(C$2<Assumptions!$B$98,Assumptions!$B$18*(1+Assumptions!$B$20)^(C$2-$C$2),MAX(Assumptions!$B$18*(1+Assumptions!$B$20)^(C$2-$C$2)*Assumptions!$B$97,Assumptions!$B$21*C35)) -> 34 | D41: =IF(D$2<Assumptions!$B$98,Assumptions!$B$18*(1+Assumptions!$B$20)^(D$2-$C$2),MAX(Assumptions!$B$18*(1+Assumptions!$B$20)^(D$2-$C$2)*Assumptions!$B$97,Assumptions!$B$21*D35)) -> 35.02 | E41: =IF(E$2<Assumptions!$B$98,Assumptions!$B$18*(1+Assumptions!$B$20)^(E$2-$C$2),MAX(Assumptions!$B$18*(1+Assumptions!$B$20)^(E$2-$C$2)*Assumptions!$B$97,Assumptions!$B$21*E35)) -> 36.0706 | F41: =IF(F$2<Assumptions!$B$98,Assumptions!$B$18*(1+Assumptions!$B$20)^(F$2-$C$2),MAX(Assumptions!$B$18*(1+Assumptions!$B$20)^(F$2-$C$2)*Assumptions!$B$97,Assumptions!$B$21*F35)) -> 37.152718 | G41: =IF(G$2<Assumptions!$B$98,Assumptions!$B$18*(1+Assumptions!$B$20)^(G$2-$C$2),MAX(Assumptions!$B$18*(1+Assumptions!$B$20)^(G$2-$C$2)*Assumptions!$B$97,Assumptions!$B$21*G35)) -> 38.2673 | H41: =IF(H$2<Assumptions!$B$98,Assumptions!$B$18*(1+Assumptions!$B$20)^(H$2-$C$2),MAX(Assumptions!$B$18*(1+Assumptions!$B$20)^(H$2-$C$2)*Assumptions!$B$97,Assumptions!$B$21*H35)) -> 17.39902 | I41: =IF(I$2<Assumptions!$B$98,Assumptions!$B$18*(1+Assumptions!$B$20)^(I$2-$C$2),MAX(Assumptions!$B$18*(1+Assumptions!$B$20)^(I$2-$C$2)*Assumptions!$B$97,Assumptions!$B$21*I35)) -> 17.920991 | J41: =IF(J$2<Assumptions!$B$98,Assumptions!$B$18*(1+Assumptions!$B$20)^(J$2-$C$2),MAX(Assumptions!$B$18*(1+Assumptions!$B$20)^(J$2-$C$2)*Assumptions!$B$97,Assumptions!$B$21*J35)) -> 18.45862 | ... Z41: =IF(Z$2<Assumptions!$B$98,Assumptions!$B$18*(1+Assumptions!$B$20)^(Z$2-$C$2),MAX(Assumptions!$B$18*(1+Assumptions!$B$20)^(Z$2-$C$2)*Assumptions!$B$97,Assumptions!$B$21*Z35)) -> 29.620667
A42: Total G&A incl. SG&A | C42: =C40+C41 -> 34 | D42: =D40+D41 -> 35.02 | E42: =E40+E41 -> 36.0706 | F42: =F40+F41 -> 37.152718 | G42: =G40+G41 -> 43.7673 | H42: =H40+H41 -> 44.02702 | I42: =I40+I41 -> 70.930991 | J42: =J40+J41 -> 97.85662 | ... Z42: =Z40+Z41 -> 58.482288
A43: Operating income (EBIT) | C43: =C35-C36-C39-C42 -> -105 | D43: =D35-D36-D39-D42 -> -120.5 | E43: =E35-E36-E39-E42 -> -152.545 | F43: =F35-F36-F39-F42 -> -154.63635 | G43: =G35-G36-G39-G42 -> -134.52544 | H43: =H35-H36-H39-H42 -> -91.053394 | I43: =I35-I36-I39-I42 -> -58.844398 | J43: =J35-J36-J39-J42 -> 15.20237 | ... Z43: =Z35-Z36-Z39-Z42 -> 20.864936
A45: All projection rows are probability-weighted (expected values). Unrisked sales show the success case.

Sheet NPV
A1: EVMN — risk-adjusted NPV (rNPV), $mm except per share
A3: Scenario | B3: =Assumptions!$C$4 -> Base
A4: Valuation date | B4: =Assumptions!$B$13 -> 46311
A5: Discount rate | B5: =Assumptions!$B$14 -> 0.12
A7: Period | C7: 2H 2026 | D7: 2027 | E7: 2028 | F7: 2029 | G7: 2030 | H7: 2031 | I7: 2032 | J7: 2033 | K7: 2034 | L7: 2035 | M7: 2036 | N7: 2037 | O7: 2038 | P7: 2039 | Q7: 2040 | R7: 2041 | S7: 2042 | T7: 2043 | U7: 2044 | V7: 2045 | W7: 2046 | X7: 2047 | Y7: 2048 | Z7: 2049 | AA7: 2050
A8: Revenue, risk-adjusted | C8: =SUM('Quarterly Model'!H2:I2) -> 0 | D8: ='Yearly Model'!F2 -> 0 | E8: ='Yearly Model'!G2 -> 0 | F8: ='Yearly Model'!H2 -> 0 | G8: ='Yearly Model'!I2 -> 0 | H8: ='Yearly Model'!J2 -> 0 | I8: ='Yearly Model'!K2 -> 7.92 | J8: ='Yearly Model'!L2 -> 66.6 | K8: ='Yearly Model'!M2 -> 154.62 | ... AA8: ='Yearly Model'!AC2 -> 119.52512
A9: Operating income (EBIT) | C9: =SUM('Quarterly Model'!H8:I8) -> -62 | D9: ='Yearly Model'!F8 -> -105 | E9: ='Yearly Model'!G8 -> -120.5 | F9: ='Yearly Model'!H8 -> -152.545 | G9: ='Yearly Model'!I8 -> -154.63635 | H9: ='Yearly Model'!J8 -> -134.52544 | I9: ='Yearly Model'!K8 -> -91.053394 | J9: ='Yearly Model'!L8 -> -58.844398 | K9: ='Yearly Model'!M8 -> 15.20237 | ... AA9: ='Yearly Model'!AC8 -> 20.864936
A10: Taxes on EBIT (after tax-loss pool) | C10: 0 | D10: =IF(D9>0,MAX(0,D9-'Yearly Model'!E21)*Assumptions!$B$15,0) -> 0 | E10: =IF(E9>0,MAX(0,E9-'Yearly Model'!F21)*Assumptions!$B$15,0) -> 0 | F10: =IF(F9>0,MAX(0,F9-'Yearly Model'!G21)*Assumptions!$B$15,0) -> 0 | G10: =IF(G9>0,MAX(0,G9-'Yearly Model'!H21)*Assumptions!$B$15,0) -> 0 | H10: =IF(H9>0,MAX(0,H9-'Yearly Model'!I21)*Assumptions!$B$15,0) -> 0 | I10: =IF(I9>0,MAX(0,I9-'Yearly Model'!J21)*Assumptions!$B$15,0) -> 0 | J10: =IF(J9>0,MAX(0,J9-'Yearly Model'!K21)*Assumptions!$B$15,0) -> 0 | K10: =IF(K9>0,MAX(0,K9-'Yearly Model'!L21)*Assumptions!$B$15,0) -> 0 | ... AA10: =IF(AA9>0,MAX(0,AA9-'Yearly Model'!AB21)*Assumptions!$B$15,0) -> 4.3816366
A11: Unlevered free cash flow | C11: =C9-C10 -> -62 | D11: =D9-D10 -> -105 | E11: =E9-E10 -> -120.5 | F11: =F9-F10 -> -152.545 | G11: =G9-G10 -> -154.63635 | H11: =H9-H10 -> -134.52544 | I11: =I9-I10 -> -91.053394 | J11: =J9-J10 -> -58.844398 | ... AA11: =AA9-AA10 -> 16.4833
A12: Cash-flow date (mid-period) | C12: =DATE(2026,10,1) -> 46296 | D12: =DATE(D7,7,1) -> 46569 | E12: =DATE(E7,7,1) -> 46935 | F12: =DATE(F7,7,1) -> 47300 | G12: =DATE(G7,7,1) -> 47665 | H12: =DATE(H7,7,1) -> 48030 | I12: =DATE(I7,7,1) -> 48396 | J12: =DATE(J7,7,1) -> 48761 | K12: =DATE(K7,7,1) -> 49126 | ... AA12: =DATE(AA7,7,1) -> 54970
A13: Years from valuation date | C13: =MAX(0,(C12-$B$4)/365.25) -> 0 | D13: =MAX(0,(D12-$B$4)/365.25) -> 0.7063655 | E13: =MAX(0,(E12-$B$4)/365.25) -> 1.7084189 | F13: =MAX(0,(F12-$B$4)/365.25) -> 2.7077344 | G13: =MAX(0,(G12-$B$4)/365.25) -> 3.70705 | H13: =MAX(0,(H12-$B$4)/365.25) -> 4.7063655 | I13: =MAX(0,(I12-$B$4)/365.25) -> 5.7084189 | J13: =MAX(0,(J12-$B$4)/365.25) -> 6.7077344 | ... AA13: =MAX(0,(AA12-$B$4)/365.25) -> 23.70705
A14: Discount factor | C14: =1/(1+$B$5)^C13 -> 1 | D14: =1/(1+$B$5)^D13 -> 0.92306883 | E14: =1/(1+$B$5)^E13 -> 0.82397683 | F14: =1/(1+$B$5)^F13 -> 0.73575067 | G14: =1/(1+$B$5)^G13 -> 0.6569712 | H14: =1/(1+$B$5)^H13 -> 0.58662693 | I14: =1/(1+$B$5)^I13 -> 0.52365217 | J14: =1/(1+$B$5)^J13 -> 0.46758285 | ... AA14: =1/(1+$B$5)^AA13 -> 0.068106079
A15: PV of free cash flow | C15: =C11*C14 -> -62 | D15: =D11*D14 -> -96.922227 | E15: =E11*E14 -> -99.289208 | F15: =F11*F14 -> -112.23509 | G15: =G11*G14 -> -101.59163 | H15: =H11*H14 -> -78.916246 | I15: =I11*I14 -> -47.680308 | J15: =J11*J14 -> -27.514631 | ... AA15: =AA11*AA14 -> 1.1226129
A17: Valuation summary
A18: PV of risk-adjusted free cash flows | C18: =SUM(C15:AA15) -> -36.680772
A19: Cash & investments (6/30/2026) | C19: =Main!C7 -> 288.007
A20: Debt | C20: =Main!C8 -> 0
A21: Equity value (rNPV) | C21: =C18+C19-C20 -> 251.32623
A22: Basic shares (mm) | C22: =Main!C4 -> 36.292113
A23: rNPV / share, basic | C23: =C21/C22 -> 6.9250922
A24: Option dilution, treasury method (mm) | C24: =IF(C23>Assumptions!$B$25,Assumptions!$B$24*(1-Assumptions!$B$25/C23),0) -> 0
A25: RSUs / other (mm) | C25: =Assumptions!$B$26 -> 0.77331
A26: Diluted shares (mm) | C26: =C22+C24+C25 -> 37.065423
A27: rNPV / share, diluted | C27: =C21/C26 -> 6.7806114
A28: Current price (Main) | C28: =Main!C3 -> 5.35
A29: Upside / (downside) to rNPV | C29: =C27/C28-1 -> 0.26740399
A30: Net cash / share (6/30/2026) | C30: =(C19-C20)/C22 -> 7.9358014
A31: Est. cash / share (12/31/2026E) | C31: =Assumptions!$B$28/C22 -> 6.6176898
A32: Liquidation value / share (12/31/2026E cash − wind-down) | C32: =(Assumptions!$B$28-Assumptions!$B$27)/C22 -> 5.7910639
A33: Market-implied value of pipeline (market cap − net cash) | C33: =Main!C5-(C19-C20) -> -93.844195
A34: Negative equity value means expected spending exceeds expected pipeline value plus cash; in practice management would cut spending or wind down first (see liquidation value).
A36: Sum of the parts (PV) | B36: $mm | C36: $/share
A37: EVO301 — Atopic dermatitis | B37: =SUMPRODUCT(Pipeline!C12:Z12,D14:AA14) -> 459.91097 | C37: =B37/$C$26 -> 12.408086
A38: EVO756 — Migraine | B38: =SUMPRODUCT(Pipeline!C22:Z22,D14:AA14) -> 82.470113 | C38: =B38/$C$26 -> 2.2249878
A39: EVO301 — Additional indications | B39: =SUMPRODUCT(Pipeline!C32:Z32,D14:AA14) -> 9.9511395 | C39: =B39/$C$26 -> 0.268475
A40: Corporate G&A + platform R&D (2027+) | B40: =-SUMPRODUCT(Pipeline!C38:Z38,D14:AA14)-SUMPRODUCT(Pipeline!C41:Z41,D14:AA14) -> -455.00536 | C40: =B40/$C$26 -> -12.275736
A41: 2H 2026 operating burn | B41: =C11*C14 -> -62 | C41: =B41/$C$26 -> -1.672718
A42: Taxes | B42: =-SUMPRODUCT(D10:AA10,D14:AA14) -> -72.007631 | C42: =B42/$C$26 -> -1.9427171
A43: Net cash | B43: =C19-C20 -> 288.007 | C43: =B43/$C$26 -> 7.7702337
A44: Equity value | B44: =SUM(B37:B43) -> 251.32623 | C44: =B44/$C$26 -> 6.7806114
A45: Check vs. equity value above (should be 0) | B45: =ROUND(B44-C21,6) -> 0

Sheet Options
A1: EVMN — options strategy analysis (per 1 contract = 100 shares)
A2: Analytical model output, not investment advice. Prices are Black-Scholes values at each strike's market implied volatility; listed quotes are very wide, so real fills may differ.
A4: Inputs
A5: Spot price (last close, 10/15/2026) | B5: 5.93
A6: Pricing date | B6: =DATE(2026,10,16) -> 46311
A7: Risk-free rate | B7: 0.0375
A8: Expiry | B8: =DATE(2027,5,21) -> 46528
A9: Years to expiry (T) | B9: =(B8-B6)/365 -> 0.59452055
A10: Contract multiplier | B10: 100
A12: Model link
A13: Bear floor: % of est. 12/31/2026 cash per share | B13: 0.5
A14: Share of bull-case upside priced in by expiry | B14: 0.25
A15: Scenario price at expiry | B15: $/share | C15: Weight
A16: Bear (rNPV, floored) | B16: =MAX(Assumptions!$D$107,$B$13*NPV!C31) -> 3.3088449 | C16: 0.25
A17: Base (rNPV) | B17: =MAX(0,Assumptions!$D$108) -> 6.7806114 | C17: 0.5
A18: Bull (partly priced in) | B18: =B17+(MAX(0,Assumptions!$D$109)-B17)*$B$14 -> 13.036027 | C18: 0.25
A19: Model-weighted price at expiry | B19: =SUMPRODUCT(B16:B18,C16:C18) -> 7.4765236 | C19: =SUM(C16:C18) -> 1
A20: Liquidation value / share (reference) | B20: =NPV!C32 -> 5.7910639
A22: Market snapshot — May 21, 2027 expiry (Cboe delayed, 10/15/2026 close)
A23: Strike | B23: Call bid | C23: Call ask | D23: Call theo | E23: Call IV | F23: Put bid | G23: Put ask | H23: Put theo | I23: Put IV | J23: Call OI | K23: Put OI
A24: 2.5 | B24: 1 | C24: 5.2 | D24: 4.05 | E24: 1.574 | F24: 0 | G24: 4.9 | H24: 0.4803 | I24: 1.459 | J24: 0 | K24: 0
A25: 5 | B25: 1.05 | C25: 4.9 | D25: 2.2587 | E25: 1.045 | F25: 0 | G25: 4.9 | H25: 1.1287 | I25: 0.985 | J25: 5 | K25: 0
A26: 7.5 | B26: 0 | C26: 4.9 | D26: 1.3482 | E26: 0.994 | F26: 0.1 | G26: 4.9 | H26: 2.6783 | I26: 0.953 | J26: 11 | K26: 0
A27: 10 | B27: 0 | C27: 1.15 | D27: 1.0336 | E27: 1.088 | F27: 2.65 | G27: 7 | H27: 4.8363 | I27: 1.062 | J27: 25 | K27: 0
A28: 12.5 | B28: 0 | C28: 4.9 | D28: 0.886 | E28: 1.181 | F28: 4.5 | G28: 9.3 | H28: 7.1658 | I28: 1.173 | J28: 1 | K28: 0
A29: 15 | B29: 0 | C29: 4.9 | D29: 0.7963 | E29: 1.259 | F29: 6.8 | G29: 11.5 | H29: 9.5562 | I29: 1.272 | J29: 4 | K29: 0
A30: Wide markets (e.g., $0 bid / $4.90 ask) are placeholder quotes from market makers; work limit orders near theo.
A32: Leg pricing (Black-Scholes at strike IV)
A33: Leg | B33: Type | C33: Strike | D33: IV | E33: d1 | F33: d2 | G33: Value | H33: Delta | I33: Mkt bid | J33: Mkt ask
A34: May-27 $5 put | B34: P | C34: =A25 -> 5 | D34: =I25 -> 0.985 | E34: =(LN($B$5/C34)+($B$7+D34^2/2)*$B$9)/(D34*SQRT($B$9)) -> 0.63370528 | F34: =E34-D34*SQRT($B$9) -> -0.12578053 | G34: =IF(B34="C",$B$5*NORMSDIST(E34)-C34*EXP(-$B$7*$B$9)*NORMSDIST(F34),C34*EXP(-$B$7*$B$9)*NORMSDIST(-F34)-$B$5*NORMSDIST(-E34)) -> 1.1291991 | H34: =IF(B34="C",NORMSDIST(E34),NORMSDIST(E34)-1) -> -0.26313659 | I34: =F25 -> 0 | J34: =G25 -> 4.9
A35: May-27 $5 call | B35: C | C35: =A25 -> 5 | D35: =E25 -> 1.045 | E35: =(LN($B$5/C35)+($B$7+D35^2/2)*$B$9)/(D35*SQRT($B$9)) -> 0.64225526 | F35: =E35-D35*SQRT($B$9) -> -0.16349365 | G35: =IF(B35="C",$B$5*NORMSDIST(E35)-C35*EXP(-$B$7*$B$9)*NORMSDIST(F35),C35*EXP(-$B$7*$B$9)*NORMSDIST(-F35)-$B$5*NORMSDIST(-E35)) -> 2.2587391 | H35: =IF(B35="C",NORMSDIST(E35),NORMSDIST(E35)-1) -> 0.73964627 | I35: =B25 -> 1.05 | J35: =C25 -> 4.9
A36: May-27 $7.50 call | B36: C | C36: =A26 -> 7.5 | D36: =E26 -> 0.994 | E36: =(LN($B$5/C36)+($B$7+D36^2/2)*$B$9)/(D36*SQRT($B$9)) -> 0.10584145 | F36: =E36-D36*SQRT($B$9) -> -0.66058382 | G36: =IF(B36="C",$B$5*NORMSDIST(E36)-C36*EXP(-$B$7*$B$9)*NORMSDIST(F36),C36*EXP(-$B$7*$B$9)*NORMSDIST(-F36)-$B$5*NORMSDIST(-E36)) -> 1.348702 | H36: =IF(B36="C",NORMSDIST(E36),NORMSDIST(E36)-1) -> 0.54214593 | I36: =B26 -> 0 | J36: =C26 -> 4.9
A37: May-27 $10 call | B37: C | C37: =A27 -> 10 | D37: =E27 -> 1.088 | E37: =(LN($B$5/C37)+($B$7+D37^2/2)*$B$9)/(D37*SQRT($B$9)) -> -0.17688111 | F37: =E37-D37*SQRT($B$9) -> -1.0157852 | G37: =IF(B37="C",$B$5*NORMSDIST(E37)-C37*EXP(-$B$7*$B$9)*NORMSDIST(F37),C37*EXP(-$B$7*$B$9)*NORMSDIST(-F37)-$B$5*NORMSDIST(-E37)) -> 1.0342055 | H37: =IF(B37="C",NORMSDIST(E37),NORMSDIST(E37)-1) -> 0.42980089 | I37: =B27 -> 0 | J37: =C27 -> 1.15
A38: May-27 $12.50 call | B38: C | C38: =A28 -> 12.5 | D38: =E28 -> 1.181 | E38: =(LN($B$5/C38)+($B$7+D38^2/2)*$B$9)/(D38*SQRT($B$9)) -> -0.33911578 | F38: =E38-D38*SQRT($B$9) -> -1.2497277 | G38: =IF(B38="C",$B$5*NORMSDIST(E38)-C38*EXP(-$B$7*$B$9)*NORMSDIST(F38),C38*EXP(-$B$7*$B$9)*NORMSDIST(-F38)-$B$5*NORMSDIST(-E38)) -> 0.88574585 | H38: =IF(B38="C",NORMSDIST(E38),NORMSDIST(E38)-1) -> 0.36726126 | I38: =B28 -> 0 | J38: =C28 -> 4.9
A40: Strategies (May 21, 2027 expiry; + = credit received, − = debit paid)
A41: Metric | B41: Long call | C41: Bull call spread | D41: Cash-secured put | E41: Bullish seagull
A42: Structure | B42: Buy $7.50 call | C42: Buy $7.50 / sell $12.50 call | D42: Sell $5 put (hold $500 cash) | E42: Sell $5 put, buy $7.50 / sell $12.50 call
A43: Net premium / share | B43: =-$G$36 -> -1.348702 | C43: =-$G$36+$G$38 -> -0.46295614 | D43: =$G$34 -> 1.1291991 | E43: =$G$34-$G$36+$G$38 -> 0.66624301
A44: Net premium / contract | B44: =B43*$B$10 -> -134.8702 | C44: =C43*$B$10 -> -46.295614 | D44: =D43*$B$10 -> 112.91991 | E44: =E43*$B$10 -> 66.624301
A45: Max profit / contract | B45: ="Unlimited" -> Unlimited | C45: =(12.5-7.5+C43)*$B$10 -> 453.70439 | D45: =D43*$B$10 -> 112.91991 | E45: =(12.5-7.5+E43)*$B$10 -> 566.6243
A46: Max loss / contract | B46: =B43*$B$10 -> -134.8702 | C46: =C43*$B$10 -> -46.295614 | D46: =-(5-D43)*$B$10 -> -387.08009 | E46: =-(5-E43)*$B$10 -> -433.3757
A47: Breakeven at expiry | B47: =7.5-B43 -> 8.848702 | C47: =7.5-C43 -> 7.9629561 | D47: =5-D43 -> 3.8708009 | E47: =IF(E43>=0,5-E43,7.5-E43) -> 4.333757
A48: Cash / margin required | B48: =-B43*$B$10 -> 134.8702 | C48: =-C43*$B$10 -> 46.295614 | D48: =5*$B$10 -> 500 | E48: =5*$B$10 -> 500
A49: Prob. of profit (market-implied) | B49: =NORMSDIST((LN($B$5/B47)+($B$7-$D$36^2/2)*$B$9)/($D$36*SQRT($B$9))) -> 0.19042021 | C49: =NORMSDIST((LN($B$5/C47)+($B$7-$D$36^2/2)*$B$9)/($D$36*SQRT($B$9))) -> 0.23003387 | D49: =NORMSDIST((LN($B$5/D47)+($B$7-$D$34^2/2)*$B$9)/($D$34*SQRT($B$9))) -> 0.58365728 | E49: =NORMSDIST((LN($B$5/E47)+($B$7-$D$34^2/2)*$B$9)/($D$34*SQRT($B$9))) -> 0.52492118
A50: P/L at current price | B50: =(MAX($B$5-7.5,0)-$G$36)*$B$10 -> -134.8702 | C50: =(MAX($B$5-7.5,0)-MAX($B$5-12.5,0)-$G$36+$G$38)*$B$10 -> -46.295614 | D50: =($G$34-MAX(5-$B$5,0))*$B$10 -> 112.91991 | E50: =($G$34-MAX(5-$B$5,0)+MAX($B$5-7.5,0)-MAX($B$5-12.5,0)-$G$36+$G$38)*$B$10 -> 66.624301
A51: P/L at bear value | B51: =(MAX($B$16-7.5,0)-$G$36)*$B$10 -> -134.8702 | C51: =(MAX($B$16-7.5,0)-MAX($B$16-12.5,0)-$G$36+$G$38)*$B$10 -> -46.295614 | D51: =($G$34-MAX(5-$B$16,0))*$B$10 -> -56.195597 | E51: =($G$34-MAX(5-$B$16,0)+MAX($B$16-7.5,0)-MAX($B$16-12.5,0)-$G$36+$G$38)*$B$10 -> -102.49121
A52: P/L at base value | B52: =(MAX($B$17-7.5,0)-$G$36)*$B$10 -> -134.8702 | C52: =(MAX($B$17-7.5,0)-MAX($B$17-12.5,0)-$G$36+$G$38)*$B$10 -> -46.295614 | D52: =($G$34-MAX(5-$B$17,0))*$B$10 -> 112.91991 | E52: =($G$34-MAX(5-$B$17,0)+MAX($B$17-7.5,0)-MAX($B$17-12.5,0)-$G$36+$G$38)*$B$10 -> 66.624301
A53: P/L at bull value | B53: =(MAX($B$18-7.5,0)-$G$36)*$B$10 -> 418.7325 | C53: =(MAX($B$18-7.5,0)-MAX($B$18-12.5,0)-$G$36+$G$38)*$B$10 -> 453.70439 | D53: =($G$34-MAX(5-$B$18,0))*$B$10 -> 112.91991 | E53: =($G$34-MAX(5-$B$18,0)+MAX($B$18-7.5,0)-MAX($B$18-12.5,0)-$G$36+$G$38)*$B$10 -> 566.6243
A54: Model-weighted expected P/L | B54: =SUMPRODUCT(B51:B53,$C$16:$C$18) -> 3.5304755 | C54: =SUMPRODUCT(C51:C53,$C$16:$C$18) -> 78.704386 | D54: =SUMPRODUCT(D51:D53,$C$16:$C$18) -> 70.641037 | E54: =SUMPRODUCT(E51:E53,$C$16:$C$18) -> 149.34542
A55: Expected P/L ÷ max loss | B55: =IFERROR(B54/-B46,0) -> 0.026176839 | C55: =IFERROR(C54/-C46,0) -> 1.7000398 | D55: =IFERROR(D54/-D46,0) -> 0.18249721 | E55: =IFERROR(E54/-E46,0) -> 0.34460959
A57: Probability of profit uses a lognormal distribution at the relevant leg's implied volatility (risk-neutral). Scenario P/L uses the scenario prices in rows 16–18 (bear floored near cash, bull only partly priced in before the 2028 Ph2b data).
A58: Sizing: one contract = 100 shares ≈ $593 of stock exposure. The Screener shows a ~7.7-share EVMN position (~$48), so covered calls/collars are not possible without 100 shares.
A60: Payoff at expiry per contract ($)
A61: Price at expiry | B61: Long call | C61: Bull call spread | D61: Cash-secured put | E61: Bullish seagull | F61: Long 100 shares
A62: 0 | B62: =(MAX($A62-7.5,0)-$G$36)*$B$10 -> -134.8702 | C62: =(MAX($A62-7.5,0)-MAX($A62-12.5,0)-$G$36+$G$38)*$B$10 -> -46.295614 | D62: =($G$34-MAX(5-$A62,0))*$B$10 -> -387.08009 | E62: =($G$34-MAX(5-$A62,0)+MAX($A62-7.5,0)-MAX($A62-12.5,0)-$G$36+$G$38)*$B$10 -> -433.3757 | F62: =($A62-$B$5)*$B$10 -> -593
A63: 0.5 | B63: =(MAX($A63-7.5,0)-$G$36)*$B$10 -> -134.8702 | C63: =(MAX($A63-7.5,0)-MAX($A63-12.5,0)-$G$36+$G$38)*$B$10 -> -46.295614 | D63: =($G$34-MAX(5-$A63,0))*$B$10 -> -337.08009 | E63: =($G$34-MAX(5-$A63,0)+MAX($A63-7.5,0)-MAX($A63-12.5,0)-$G$36+$G$38)*$B$10 -> -383.3757 | F63: =($A63-$B$5)*$B$10 -> -543
A64: 1 | B64: =(MAX($A64-7.5,0)-$G$36)*$B$10 -> -134.8702 | C64: =(MAX($A64-7.5,0)-MAX($A64-12.5,0)-$G$36+$G$38)*$B$10 -> -46.295614 | D64: =($G$34-MAX(5-$A64,0))*$B$10 -> -287.08009 | E64: =($G$34-MAX(5-$A64,0)+MAX($A64-7.5,0)-MAX($A64-12.5,0)-$G$36+$G$38)*$B$10 -> -333.3757 | F64: =($A64-$B$5)*$B$10 -> -493
A65: 1.5 | B65: =(MAX($A65-7.5,0)-$G$36)*$B$10 -> -134.8702 | C65: =(MAX($A65-7.5,0)-MAX($A65-12.5,0)-$G$36+$G$38)*$B$10 -> -46.295614 | D65: =($G$34-MAX(5-$A65,0))*$B$10 -> -237.08009 | E65: =($G$34-MAX(5-$A65,0)+MAX($A65-7.5,0)-MAX($A65-12.5,0)-$G$36+$G$38)*$B$10 -> -283.3757 | F65: =($A65-$B$5)*$B$10 -> -443
A66: 2 | B66: =(MAX($A66-7.5,0)-$G$36)*$B$10 -> -134.8702 | C66: =(MAX($A66-7.5,0)-MAX($A66-12.5,0)-$G$36+$G$38)*$B$10 -> -46.295614 | D66: =($G$34-MAX(5-$A66,0))*$B$10 -> -187.08009 | E66: =($G$34-MAX(5-$A66,0)+MAX($A66-7.5,0)-MAX($A66-12.5,0)-$G$36+$G$38)*$B$10 -> -233.3757 | F66: =($A66-$B$5)*$B$10 -> -393
A67: 2.5 | B67: =(MAX($A67-7.5,0)-$G$36)*$B$10 -> -134.8702 | C67: =(MAX($A67-7.5,0)-MAX($A67-12.5,0)-$G$36+$G$38)*$B$10 -> -46.295614 | D67: =($G$34-MAX(5-$A67,0))*$B$10 -> -137.08009 | E67: =($G$34-MAX(5-$A67,0)+MAX($A67-7.5,0)-MAX($A67-12.5,0)-$G$36+$G$38)*$B$10 -> -183.3757 | F67: =($A67-$B$5)*$B$10 -> -343
A68: 3 | B68: =(MAX($A68-7.5,0)-$G$36)*$B$10 -> -134.8702 | C68: =(MAX($A68-7.5,0)-MAX($A68-12.5,0)-$G$36+$G$38)*$B$10 -> -46.295614 | D68: =($G$34-MAX(5-$A68,0))*$B$10 -> -87.080085 | E68: =($G$34-MAX(5-$A68,0)+MAX($A68-7.5,0)-MAX($A68-12.5,0)-$G$36+$G$38)*$B$10 -> -133.3757 | F68: =($A68-$B$5)*$B$10 -> -293
A69: 3.5 | B69: =(MAX($A69-7.5,0)-$G$36)*$B$10 -> -134.8702 | C69: =(MAX($A69-7.5,0)-MAX($A69-12.5,0)-$G$36+$G$38)*$B$10 -> -46.295614 | D69: =($G$34-MAX(5-$A69,0))*$B$10 -> -37.080085 | E69: =($G$34-MAX(5-$A69,0)+MAX($A69-7.5,0)-MAX($A69-12.5,0)-$G$36+$G$38)*$B$10 -> -83.375699 | F69: =($A69-$B$5)*$B$10 -> -243
A70: 4 | B70: =(MAX($A70-7.5,0)-$G$36)*$B$10 -> -134.8702 | C70: =(MAX($A70-7.5,0)-MAX($A70-12.5,0)-$G$36+$G$38)*$B$10 -> -46.295614 | D70: =($G$34-MAX(5-$A70,0))*$B$10 -> 12.919915 | E70: =($G$34-MAX(5-$A70,0)+MAX($A70-7.5,0)-MAX($A70-12.5,0)-$G$36+$G$38)*$B$10 -> -33.375699 | F70: =($A70-$B$5)*$B$10 -> -193
A71: 4.5 | B71: =(MAX($A71-7.5,0)-$G$36)*$B$10 -> -134.8702 | C71: =(MAX($A71-7.5,0)-MAX($A71-12.5,0)-$G$36+$G$38)*$B$10 -> -46.295614 | D71: =($G$34-MAX(5-$A71,0))*$B$10 -> 62.919915 | E71: =($G$34-MAX(5-$A71,0)+MAX($A71-7.5,0)-MAX($A71-12.5,0)-$G$36+$G$38)*$B$10 -> 16.624301 | F71: =($A71-$B$5)*$B$10 -> -143
A72: 5 | B72: =(MAX($A72-7.5,0)-$G$36)*$B$10 -> -134.8702 | C72: =(MAX($A72-7.5,0)-MAX($A72-12.5,0)-$G$36+$G$38)*$B$10 -> -46.295614 | D72: =($G$34-MAX(5-$A72,0))*$B$10 -> 112.91991 | E72: =($G$34-MAX(5-$A72,0)+MAX($A72-7.5,0)-MAX($A72-12.5,0)-$G$36+$G$38)*$B$10 -> 66.624301 | F72: =($A72-$B$5)*$B$10 -> -93
A73: 5.5 | B73: =(MAX($A73-7.5,0)-$G$36)*$B$10 -> -134.8702 | C73: =(MAX($A73-7.5,0)-MAX($A73-12.5,0)-$G$36+$G$38)*$B$10 -> -46.295614 | D73: =($G$34-MAX(5-$A73,0))*$B$10 -> 112.91991 | E73: =($G$34-MAX(5-$A73,0)+MAX($A73-7.5,0)-MAX($A73-12.5,0)-$G$36+$G$38)*$B$10 -> 66.624301 | F73: =($A73-$B$5)*$B$10 -> -43
... A94: 16 | B94: =(MAX($A94-7.5,0)-$G$36)*$B$10 -> 715.1298 | C94: =(MAX($A94-7.5,0)-MAX($A94-12.5,0)-$G$36+$G$38)*$B$10 -> 453.70439 | D94: =($G$34-MAX(5-$A94,0))*$B$10 -> 112.91991 | E94: =($G$34-MAX(5-$A94,0)+MAX($A94-7.5,0)-MAX($A94-12.5,0)-$G$36+$G$38)*$B$10 -> 566.6243 | F94: =($A94-$B$5)*$B$10 -> 1007
