Workbook

Sheet Main
B2: Fennec Pharmaceuticals Inc.
B3: Price | C3: =INDEX([1]Pharma!$F$1:$F$1000,MATCH("FENC",[1]Pharma!$B$1:$B$1000,0)) -> 10.46
B4: Shares | C4: 35.067159
B5: Market Cap. | C5: =C3*C4 -> 366.80248
B7: Cash | C7: 41.249
B8: Debt | C8: 0
B9: Enterprise V. | C9: =C5-C7+C8 -> 325.55348
B11: NPV / Share | C11: =NPV!B28 -> 6.1854105
B12: Upside | C12: =IFERROR(C11/C3-1,"") -> -0.40866056
B13: Cash / Share | C13: =IFERROR((C7-C8)/C4,"") -> 1.1762858
B14: Scenario | C14: =Assumptions!C4 -> Base
B15: Model | C15: DCF

Sheet Yearly Model
B1: 1997 | C1: 1998 | D1: 1999 | E1: 2000 | F1: 2001 | G1: 2002 | H1: 2003 | I1: 2004 | J1: 2005 | K1: 2006 | L1: 2007 | M1: 2008 | N1: 2009 | O1: 2010 | P1: 2011 | Q1: 2012 | R1: 2013 | S1: 2014 | T1: 2015 | U1: 2016 | V1: 2017 | W1: 2018 | X1: 2019 | Y1: 2020 | Z1: 2021 | AA1: 2022 | AB1: 2023 | AC1: 2024 | AD1: 2025 | AE1: 2026 | AF1: 2027 | AG1: 2028 | AH1: 2029 | AI1: 2030 | AJ1: 2031 | AK1: 2032 | AL1: 2033 | AM1: 2034 | AN1: 2035
A2: Revenue | B2: 0 | C2: 0 | D2: 0 | E2: 0 | F2: 0 | G2: 0 | H2: 0 | I2: 0 | J2: 0 | K2: 0 | L2: 0 | M2: 0 | N2: 0 | O2: 0 | P2: 0 | Q2: 0 | R2: 0 | S2: 0 | T2: 0 | U2: 0 | V2: 0 | W2: 0 | X2: 0 | Y2: 0.2 | Z2: 0 | AA2: 1.769 | AB2: 23.782 | AC2: 47.538 | AD2: 44.642 | AE2: =AD2*(1+NPV!C5) -> 60.2667 | AF2: =AE2*(1+NPV!D5) -> 79.183748 | AG2: =AF2*(1+NPV!E5) -> 101.17923 | AH2: =AG2*(1+NPV!F5) -> 125.63088 | AI2: =AH2*(1+NPV!G5) -> 151.45501 | AJ2: =AI2*(1+NPV!H5) -> 177.11822 | AK2: =AJ2*(1+NPV!I5) -> 200.73398 | AL2: =AK2*(1+NPV!J5) -> 220.24978 | ... AN2: =AM2*(1+NPV!L5) -> 239.55223
A3: Cost of Sales | B3: 0 | C3: 0 | D3: 0 | E3: 0 | F3: 0 | G3: 0 | H3: 0 | I3: 0 | J3: 0 | K3: 0 | L3: 0 | M3: 0 | N3: 0 | O3: 0 | P3: 0 | Q3: 0 | R3: 0 | S3: 0 | T3: 0 | U3: 0 | V3: 0 | W3: 0 | X3: 0 | Y3: 0 | Z3: 0 | AA3: 0.086 | AB3: 1.259 | AC3: 0 | AD3: 0 | AE3: =AE2*(1-Assumptions!$B$19) -> 3.1881084 | AF3: =AF2*(1-Assumptions!$B$19) -> 4.1888202 | AG3: =AG2*(1-Assumptions!$B$19) -> 5.3523814 | AH3: =AH2*(1-Assumptions!$B$19) -> 6.6458736 | AI3: =AI2*(1-Assumptions!$B$19) -> 8.0119698 | AJ3: =AJ2*(1-Assumptions!$B$19) -> 9.3695536 | AK3: =AK2*(1-Assumptions!$B$19) -> 10.618827 | AL3: =AL2*(1-Assumptions!$B$19) -> 11.651213 | ... AN3: =AN2*(1-Assumptions!$B$19) -> 12.672313
A4: Gross Margin | B4: =B2-B3 -> 0 | C4: =C2-C3 -> 0 | D4: =D2-D3 -> 0 | E4: =E2-E3 -> 0 | F4: =F2-F3 -> 0 | G4: =G2-G3 -> 0 | H4: =H2-H3 -> 0 | I4: =I2-I3 -> 0 | ... AN4: =AN2-AN3 -> 226.87991
A5: Research & Dev. | B5: 0 | C5: 0 | D5: 0 | E5: 0 | F5: 0 | G5: 0 | H5: 0 | I5: 0 | J5: 0 | K5: 0 | L5: 0 | M5: 0 | N5: 0 | O5: 0.708 | P5: 1.494 | Q5: 2.075 | R5: 0.597 | S5: 0.357 | T5: 0.256 | U5: 0.472 | V5: 1.936 | W5: 5.008 | X5: 5.607 | Y5: 5.105 | Z5: 4.981 | AA5: 3.531 | AB5: 0.056 | AC5: 0.307 | AD5: 0.25 | AE5: =AE7*Assumptions!$B$20 -> 0.27882871 | AF5: =AF7*Assumptions!$B$20 -> 0.35785273 | AG5: =AG7*Assumptions!$B$20 -> 0.44639873 | AH5: =AH7*Assumptions!$B$20 -> 0.54079697 | AI5: =AI7*Assumptions!$B$20 -> 0.63570816 | AJ5: =AJ7*Assumptions!$B$20 -> 0.72441882 | AK5: =AK7*Assumptions!$B$20 -> 0.79946723 | AL5: =AL7*Assumptions!$B$20 -> 0.8535582 | ... AN5: =AN7*Assumptions!$B$20 -> 0.8769504
A6: SG&A & Other | B6: 0.037 | C6: 0.398 | D6: 0.958 | E6: 1.605 | F6: 2.524 | G6: 3.732 | H6: 17.795 | I6: 6.872 | J6: 13.871 | K6: 16.44 | L6: 13.357 | M6: 13.6 | N6: 3.012 | O6: 3.896 | P6: 1.944 | Q6: 1.545 | R6: 1.334 | S6: 2.52 | T6: 1.634 | U6: 2.399 | V6: 5.015 | W6: 5.401 | X6: 7.402 | Y6: 12.98 | Z6: 12.242 | AA6: 20.741 | AB6: 35.238 | AC6: 44.663 | AD6: 50.674 | AE6: =AE7-AE5 -> 56.624989 | AF6: =AF7-AF5 -> 72.673318 | AG6: =AG7-AG5 -> 90.655383 | AH6: =AH7-AH5 -> 109.82593 | AI6: =AI7-AI5 -> 129.10065 | AJ6: =AJ7-AJ5 -> 147.11616 | AK6: =AK7-AK5 -> 162.35711 | AL6: =AL7-AL5 -> 173.34199 | ... AN6: =AN7-AN5 -> 178.09252
A7: Operating Expense | B7: =SUM(B5:B6) -> 0.037 | C7: =SUM(C5:C6) -> 0.398 | D7: =SUM(D5:D6) -> 0.958 | E7: =SUM(E5:E6) -> 1.605 | F7: =SUM(F5:F6) -> 2.524 | G7: =SUM(G5:G6) -> 3.732 | H7: =SUM(H5:H6) -> 17.795 | I7: =SUM(I5:I6) -> 6.872 | ... AD7: =SUM(AD5:AD6) -> 50.924 | AE7: =AE4-AE2*NPV!C6 -> 56.903818 | AF7: =AF4-AF2*NPV!D6 -> 73.03117 | AG7: =AG4-AG2*NPV!E6 -> 91.101781 | AH7: =AH4-AH2*NPV!F6 -> 110.36673 | AI7: =AI4-AI2*NPV!G6 -> 129.73636 | AJ7: =AJ4-AJ2*NPV!H6 -> 147.84057 | AK7: =AK4-AK2*NPV!I6 -> 163.15658 | AL7: =AL4-AL2*NPV!J6 -> 174.19555 | ... AN7: =AN4-AN2*NPV!L6 -> 178.96947
A8: Operating Income | B8: =B4-B7 -> -0.037 | C8: =C4-C7 -> -0.398 | D8: =D4-D7 -> -0.958 | E8: =E4-E7 -> -1.605 | F8: =F4-F7 -> -2.524 | G8: =G4-G7 -> -3.732 | H8: =H4-H7 -> -17.795 | I8: =I4-I7 -> -6.872 | ... AN8: =AN4-AN7 -> 47.910445
A9: Interest & Other | B9: 0 | C9: 0 | D9: 0 | E9: 0 | F9: 0 | G9: 0 | H9: 0 | I9: 0 | J9: 0 | K9: 0 | L9: 0 | M9: 0 | N9: 0 | O9: -3.22 | P9: 8.123 | Q9: -1.543 | R9: 3.776 | S9: 0.701 | T9: 1.231 | U9: 0.082 | V9: -0.095 | W9: 0.521 | X9: 0.234 | Y9: -0.224 | Z9: -0.123 | AA9: -1.125 | AB9: -16032.229 | AC9: -438.203 | AD9: -9734.612 | AE9: 0 | AF9: 0 | AG9: 0 | AH9: 0 | AI9: 0 | AJ9: 0 | AK9: 0 | AL9: 0 | AM9: 0 | AN9: 0
A10: Pretax | B10: =B8+B9 -> -0.037 | C10: =C8+C9 -> -0.398 | D10: =D8+D9 -> -0.958 | E10: =E8+E9 -> -1.605 | F10: =F8+F9 -> -2.524 | G10: =G8+G9 -> -3.732 | H10: =H8+H9 -> -17.795 | I10: =I8+I9 -> -6.872 | ... AN10: =AN8+AN9 -> 47.910445
A11: Taxes | B11: 0 | C11: 0 | D11: 0 | E11: 0 | F11: 0 | G11: 0 | H11: 0 | I11: 0 | J11: 0 | K11: 0 | L11: 0 | M11: 0 | N11: 0 | O11: 0 | P11: 0 | Q11: 0 | R11: 0 | S11: 0 | T11: 0 | U11: 0 | V11: 0 | W11: 0 | X11: 0 | Y11: 0 | Z11: 0 | AA11: 0 | AB11: 0 | AC11: 0.365 | AD11: 0.106 | AE11: =MAX(0,AE10)*Assumptions!$E$14 -> 0.029711483 | AF11: =MAX(0,AF10)*Assumptions!$E$14 -> 0.33383868 | AG11: =MAX(0,AG10)*Assumptions!$E$14 -> 0.80326193 | AH11: =MAX(0,AH10)*Assumptions!$E$14 -> 1.4651073 | AI11: =MAX(0,AI10)*Assumptions!$E$14 -> 2.3301353 | AJ11: =MAX(0,AJ10)*Assumptions!$E$14 -> 3.3843749 | AK11: =MAX(0,AK10)*Assumptions!$E$14 -> 4.5829574 | AL11: =MAX(0,AL10)*Assumptions!$E$14 -> 5.8485127 | ... AN11: =MAX(0,AN10)*Assumptions!$E$14 -> 8.1447757
A12: Net Income | B12: -0.037 | C12: -0.398 | D12: -0.958 | E12: -1.605 | F12: -2.524 | G12: -3.732 | H12: -17.795 | I12: -6.872 | J12: -13.871 | K12: -16.44 | L12: -13.357 | M12: -13.6 | N12: -3.012 | O12: -7.824 | P12: 4.685 | Q12: -5.163 | R12: 1.845 | S12: -2.176 | T12: -0.659 | U12: -2.789 | V12: -7.046 | W12: -9.888 | X12: -12.775 | Y12: -18.109 | Z12: -17.346 | AA12: -23.714 | AB12: -16045 | AC12: -436 | AD12: -9741 | AE12: =AE10-AE11 -> 0.14506195 | AF12: =AF10-AF11 -> 1.6299183 | AG12: =AG10-AG11 -> 3.9218082 | AH12: =AH10-AH11 -> 7.1531711 | AI12: =AI10-AI11 -> 11.376543 | AJ12: =AJ10-AJ11 -> 16.523713 | AK12: =AK10-AK11 -> 22.375616 | AL12: =AL10-AL11 -> 28.554503 | ... AN12: =AN10-AN11 -> 39.76567
A13: Earnings per Share | B13: =IFERROR(B12/B14,0) -> 0 | C13: =IFERROR(C12/C14,0) -> 0 | D13: =IFERROR(D12/D14,0) -> 0 | E13: =IFERROR(E12/E14,0) -> 0 | F13: =IFERROR(F12/F14,0) -> 0 | G13: =IFERROR(G12/G14,0) -> 0 | H13: =IFERROR(H12/H14,0) -> 0 | I13: =IFERROR(I12/I14,0) -> 0 | ... AN13: =IFERROR(AN12/AN14,0) -> 1.1339861
A14: Shares | O14: 16.015 | P14: 24.05 | Q14: 25.158 | R14: 10.571 | S14: 9.871 | T14: 10.827 | U14: 12.765 | V14: 15.014 | W14: 18.942 | X14: 19.896 | Y14: 23.704 | Z14: 26.006 | AA14: 26.275 | AB14: 26.574 | AC14: 27.294 | AD14: 28.577 | AE14: =Main!$C$4 -> 35.067159 | AF14: =Main!$C$4 -> 35.067159 | AG14: =Main!$C$4 -> 35.067159 | AH14: =Main!$C$4 -> 35.067159 | AI14: =Main!$C$4 -> 35.067159 | AJ14: =Main!$C$4 -> 35.067159 | AK14: =Main!$C$4 -> 35.067159 | AL14: =Main!$C$4 -> 35.067159 | ... AN14: =Main!$C$4 -> 35.067159
A16: Revenue Change | C16: =IFERROR(C2/B2-1,"") | D16: =IFERROR(D2/C2-1,"") | E16: =IFERROR(E2/D2-1,"") | F16: =IFERROR(F2/E2-1,"") | G16: =IFERROR(G2/F2-1,"") | H16: =IFERROR(H2/G2-1,"") | I16: =IFERROR(I2/H2-1,"") | J16: =IFERROR(J2/I2-1,"") | ... AN16: =IFERROR(AN2/AM2-1,"") -> 0.025
A17: Gross Margin | B17: =IFERROR(B4/B2,"") | C17: =IFERROR(C4/C2,"") | D17: =IFERROR(D4/D2,"") | E17: =IFERROR(E4/E2,"") | F17: =IFERROR(F4/F2,"") | G17: =IFERROR(G4/G2,"") | H17: =IFERROR(H4/H2,"") | I17: =IFERROR(I4/I2,"") | ... AN17: =IFERROR(AN4/AN2,"") -> 0.9471
A18: Operating Margin | B18: =IFERROR(B8/B2,"") | C18: =IFERROR(C8/C2,"") | D18: =IFERROR(D8/D2,"") | E18: =IFERROR(E8/E2,"") | F18: =IFERROR(F8/F2,"") | G18: =IFERROR(G8/G2,"") | H18: =IFERROR(H8/H2,"") | I18: =IFERROR(I8/I2,"") | ... AN18: =IFERROR(AN8/AN2,"") -> 0.2
A19: Actual / Estimate | B19: A | C19: A | D19: A | E19: A | F19: A | G19: A | H19: A | I19: A | J19: A | K19: A | L19: A | M19: A | N19: A | O19: A | P19: A | Q19: A | R19: A | S19: A | T19: A | U19: A | V19: A | W19: A | X19: A | Y19: A | Z19: A | AA19: A | AB19: A | AC19: A | AD19: A | AE19: E | AF19: E | AG19: E | AH19: E | AI19: E | AJ19: E | AK19: E | AL19: E | AM19: E | AN19: E

Sheet Quarterly Model

Sheet Assumptions
A1: Fennec Pharmaceuticals Inc.: basic DCF assumptions
A2: Blue = input, black = formula, green = link. $mm unless noted.
A4: Scenario (1 Bear, 2 Base, 3 Bull) | B4: 2 | C4: =CHOOSE($B$4,"Bear","Base","Bull") -> Base
A6: Discount rate override (blank = scenario)
A7: Terminal growth override (blank = scenario)
A9: Parameter | B9: Bear | C9: Base | D9: Bull | E9: Live
A10: Discount rate | B10: 0.135 | C10: 0.125 | D10: 0.115 | E10: =IF(ISNUMBER($B$6),$B$6,CHOOSE($B$4,B10,C10,D10)) -> 0.125
A11: Terminal growth | B11: 0.02 | C11: 0.025 | D11: 0.03 | E11: =IF(ISNUMBER($B$7),$B$7,CHOOSE($B$4,B11,C11,D11)) -> 0.025
A12: Revenue growth, first forecast year | B12: 0.3 | C12: 0.35 | D12: 0.4 | E12: =CHOOSE($B$4,B12,C12,D12) -> 0.35
A13: Operating margin, year 10 | B13: 0.15 | C13: 0.2 | D13: 0.25 | E13: =CHOOSE($B$4,B13,C13,D13) -> 0.2
A14: Tax rate on operating income | B14: 0.17 | C14: 0.17 | D14: 0.17 | E14: =CHOOSE($B$4,B14,C14,D14) -> 0.17
A15: Reinvestment, % of revenue increase | B15: 0.25 | C15: 0.25 | D15: 0.25 | E15: =CHOOSE($B$4,B15,C15,D15) -> 0.25
A17: Single inputs
A18: Starting operating margin (TTM) | B18: -0.019
A19: Gross margin (forecast) | B19: 0.9471
A20: R&D share of operating expense (forecast) | B20: 0.0049
A21: Forecast years | B21: 10
A22: First forecast year, fraction after balance sheet date | B22: 0.5041
A23: Balance sheet date | B23: 46203
A24: Reporting currency per USD (USD) | B24: 1
A25: Base revenue, FY2025 | B25: ='Yearly Model'!AD2 -> 44.642
A27: Scenario summary
A28: Scenario | B28: Enterprise value | C28: Equity value | D28: NPV / share | E28: Upside
A29: Live | B29: =NPV!B23 -> 175.65577 | C29: =NPV!B26 -> 216.90477 | D29: =NPV!B28 -> 6.1854105 | E29: =NPV!B30 -> -0.40866056
A30: 1 | B30: 83.092482 | C30: 124.34148 | D30: 3.54581 | E30: -0.66101243
A31: 2 | B31: 175.65577 | C31: 216.90477 | D31: 6.1854105 | E31: -0.40866056
A32: 3 | B32: 342.43761 | C32: 383.68661 | D32: 10.94148 | E32: 0.046030582
A35: NPV / share: discount rate (rows) x terminal growth (columns)
A36: =NPV!B28 -> 6.1854105 | B36: 0.015 | C36: 0.02 | D36: 0.025 | E36: 0.03 | F36: 0.035
A37: 0.105 | B37: 7.342333 | C37: 7.7240823 | D37: 8.1539649 | E37: 8.6416131 | F37: 9.1994114
A38: 0.115 | B38: 6.4327627 | C38: 6.7249798 | D38: 7.0500102 | E38: 7.413649 | F38: 7.8231403
A39: 0.125 | B39: 5.7052005 | C39: 5.9337335 | D39: 6.1854105 | E39: 6.4638896 | F39: 6.7736419
A40: 0.135 | B40: 5.1129389 | C40: 5.2948501 | D40: 5.4935467 | E40: 5.7114299 | F40: 5.951381
A41: 0.145 | B41: 4.623745 | C41: 4.7707026 | D41: 4.9301205 | E41: 5.1036266 | F41: 5.2931448

Sheet NPV
A1: Fennec Pharmaceuticals Inc.: free-cash-flow DCF ($mm)
A3: Fiscal year | B3: ='Yearly Model'!AD1 -> 2025 | C3: ='Yearly Model'!AE1 -> 2026 | D3: ='Yearly Model'!AF1 -> 2027 | E3: ='Yearly Model'!AG1 -> 2028 | F3: ='Yearly Model'!AH1 -> 2029 | G3: ='Yearly Model'!AI1 -> 2030 | H3: ='Yearly Model'!AJ1 -> 2031 | I3: ='Yearly Model'!AK1 -> 2032 | ... L3: ='Yearly Model'!AN1 -> 2035
A4: Period | B4: Actual | C4: 1 | D4: 2 | E4: 3 | F4: 4 | G4: 5 | H4: 6 | I4: 7 | J4: 8 | K4: 9 | L4: 10
A5: Revenue growth | C5: =Assumptions!$E$12+(Assumptions!$E$11-Assumptions!$E$12)*(C4-1)/(Assumptions!$B$21-1) -> 0.35 | D5: =Assumptions!$E$12+(Assumptions!$E$11-Assumptions!$E$12)*(D4-1)/(Assumptions!$B$21-1) -> 0.31388889 | E5: =Assumptions!$E$12+(Assumptions!$E$11-Assumptions!$E$12)*(E4-1)/(Assumptions!$B$21-1) -> 0.27777778 | F5: =Assumptions!$E$12+(Assumptions!$E$11-Assumptions!$E$12)*(F4-1)/(Assumptions!$B$21-1) -> 0.24166667 | G5: =Assumptions!$E$12+(Assumptions!$E$11-Assumptions!$E$12)*(G4-1)/(Assumptions!$B$21-1) -> 0.20555556 | H5: =Assumptions!$E$12+(Assumptions!$E$11-Assumptions!$E$12)*(H4-1)/(Assumptions!$B$21-1) -> 0.16944444 | I5: =Assumptions!$E$12+(Assumptions!$E$11-Assumptions!$E$12)*(I4-1)/(Assumptions!$B$21-1) -> 0.13333333 | J5: =Assumptions!$E$12+(Assumptions!$E$11-Assumptions!$E$12)*(J4-1)/(Assumptions!$B$21-1) -> 0.097222222 | ... L5: =Assumptions!$E$12+(Assumptions!$E$11-Assumptions!$E$12)*(L4-1)/(Assumptions!$B$21-1) -> 0.025
A6: Operating margin | B6: =IFERROR(B8/B7,0) -> -0.1407195 | C6: =Assumptions!$B$18+(Assumptions!$E$13-Assumptions!$B$18)*C4/Assumptions!$B$21 -> 0.0029 | D6: =Assumptions!$B$18+(Assumptions!$E$13-Assumptions!$B$18)*D4/Assumptions!$B$21 -> 0.0248 | E6: =Assumptions!$B$18+(Assumptions!$E$13-Assumptions!$B$18)*E4/Assumptions!$B$21 -> 0.0467 | F6: =Assumptions!$B$18+(Assumptions!$E$13-Assumptions!$B$18)*F4/Assumptions!$B$21 -> 0.0686 | G6: =Assumptions!$B$18+(Assumptions!$E$13-Assumptions!$B$18)*G4/Assumptions!$B$21 -> 0.0905 | H6: =Assumptions!$B$18+(Assumptions!$E$13-Assumptions!$B$18)*H4/Assumptions!$B$21 -> 0.1124 | I6: =Assumptions!$B$18+(Assumptions!$E$13-Assumptions!$B$18)*I4/Assumptions!$B$21 -> 0.1343 | J6: =Assumptions!$B$18+(Assumptions!$E$13-Assumptions!$B$18)*J4/Assumptions!$B$21 -> 0.1562 | ... L6: =Assumptions!$B$18+(Assumptions!$E$13-Assumptions!$B$18)*L4/Assumptions!$B$21 -> 0.2
A7: Revenue | B7: ='Yearly Model'!AD2 -> 44.642 | C7: ='Yearly Model'!AE2 -> 60.2667 | D7: ='Yearly Model'!AF2 -> 79.183748 | E7: ='Yearly Model'!AG2 -> 101.17923 | F7: ='Yearly Model'!AH2 -> 125.63088 | G7: ='Yearly Model'!AI2 -> 151.45501 | H7: ='Yearly Model'!AJ2 -> 177.11822 | I7: ='Yearly Model'!AK2 -> 200.73398 | ... L7: ='Yearly Model'!AN2 -> 239.55223
A8: Operating income | B8: ='Yearly Model'!AD8 -> -6.282 | C8: ='Yearly Model'!AE8 -> 0.17477343 | D8: ='Yearly Model'!AF8 -> 1.9637569 | E8: ='Yearly Model'!AG8 -> 4.7250702 | F8: ='Yearly Model'!AH8 -> 8.6182784 | G8: ='Yearly Model'!AI8 -> 13.706678 | H8: ='Yearly Model'!AJ8 -> 19.908087 | I8: ='Yearly Model'!AK8 -> 26.958573 | ... L8: ='Yearly Model'!AN8 -> 47.910445
A9: Tax on operating income | C9: =MAX(0,C8)*Assumptions!$E$14 -> 0.029711483 | D9: =MAX(0,D8)*Assumptions!$E$14 -> 0.33383868 | E9: =MAX(0,E8)*Assumptions!$E$14 -> 0.80326193 | F9: =MAX(0,F8)*Assumptions!$E$14 -> 1.4651073 | G9: =MAX(0,G8)*Assumptions!$E$14 -> 2.3301353 | H9: =MAX(0,H8)*Assumptions!$E$14 -> 3.3843749 | I9: =MAX(0,I8)*Assumptions!$E$14 -> 4.5829574 | J9: =MAX(0,J8)*Assumptions!$E$14 -> 5.8485127 | ... L9: =MAX(0,L8)*Assumptions!$E$14 -> 8.1447757
A10: NOPAT | C10: =C8-C9 -> 0.14506195 | D10: =D8-D9 -> 1.6299183 | E10: =E8-E9 -> 3.9218082 | F10: =F8-F9 -> 7.1531711 | G10: =G8-G9 -> 11.376543 | H10: =H8-H9 -> 16.523713 | I10: =I8-I9 -> 22.375616 | J10: =J8-J9 -> 28.554503 | ... L10: =L8-L9 -> 39.76567
A11: Reinvestment | C11: =(C7-B7)*Assumptions!$E$15 -> 3.906175 | D11: =(D7-C7)*Assumptions!$E$15 -> 4.7292619 | E11: =(E7-D7)*Assumptions!$E$15 -> 5.4988714 | F11: =(F7-E7)*Assumptions!$E$15 -> 6.112912 | G11: =(G7-F7)*Assumptions!$E$15 -> 6.4560314 | H11: =(H7-G7)*Assumptions!$E$15 -> 6.4158024 | I11: =(I7-H7)*Assumptions!$E$15 -> 5.9039405 | J11: =(J7-I7)*Assumptions!$E$15 -> 4.8789509 | ... L11: =(L7-K7)*Assumptions!$E$15 -> 1.4606843
A12: Free cash flow | C12: =C10-C11 -> -3.7611131 | D12: =D10-D11 -> -3.0993436 | E12: =E10-E11 -> -1.5770631 | F12: =F10-F11 -> 1.0402591 | G12: =G10-G11 -> 4.9205114 | H12: =H10-H11 -> 10.10791 | I12: =I10-I11 -> 16.471675 | J12: =J10-J11 -> 23.675552 | ... L12: =L10-L11 -> 38.304985
A13: Year fraction | C13: =Assumptions!$B$22 -> 0.5041 | D13: 1 | E13: 1 | F13: 1 | G13: 1 | H13: 1 | I13: 1 | J13: 1 | K13: 1 | L13: 1
A14: Discount time (mid-period) | C14: =C13/2 -> 0.25205 | D14: =C14+C13/2+D13/2 -> 1.0041 | E14: =D14+D13/2+E13/2 -> 2.0041 | F14: =E14+E13/2+F13/2 -> 3.0041 | G14: =F14+F13/2+G13/2 -> 4.0041 | H14: =G14+G13/2+H13/2 -> 5.0041 | I14: =H14+H13/2+I13/2 -> 6.0041 | J14: =I14+I13/2+J13/2 -> 7.0041 | K14: =J14+J13/2+K13/2 -> 8.0041 | L14: =K14+K13/2+L13/2 -> 9.0041
A15: Discount factor | C15: =1/(1+Assumptions!$E$10)^C14 -> 0.97074912 | D15: =1/(1+Assumptions!$E$10)^D14 -> 0.88845974 | E15: =1/(1+Assumptions!$E$10)^E14 -> 0.78974199 | F15: =1/(1+Assumptions!$E$10)^F14 -> 0.70199288 | G15: =1/(1+Assumptions!$E$10)^G14 -> 0.62399367 | H15: =1/(1+Assumptions!$E$10)^H14 -> 0.55466104 | I15: =1/(1+Assumptions!$E$10)^I14 -> 0.49303204 | J15: =1/(1+Assumptions!$E$10)^J14 -> 0.4382507 | ... L15: =1/(1+Assumptions!$E$10)^L14 -> 0.34627216
A16: PV of free cash flow | C16: =C12*C13*C15 -> -1.8405181 | D16: =D12*D13*D15 -> -2.753642 | E16: =E12*E13*E15 -> -1.245473 | F16: =F12*F13*F15 -> 0.73025449 | G16: =G12*G13*G15 -> 3.070368 | H16: =H12*H13*H15 -> 5.606464 | I16: =I12*I13*I15 -> 8.1210636 | J16: =J12*J13*J15 -> 10.375827 | ... L16: =L12*L13*L15 -> 13.26395
A19: PV of forecast free cash flow | B19: =SUM(C16:L16) -> 47.475712
A20: Terminal free cash flow (year 11) | B20: =L10*(1+Assumptions!$E$11)-L7*Assumptions!$E$11*Assumptions!$E$15 -> 39.26261
A21: Terminal value | B21: =B20/(Assumptions!$E$10-Assumptions!$E$11) -> 392.6261
A22: PV of terminal value | B22: =B21/(1+Assumptions!$E$10)^(L14+0.5) -> 128.18006
A23: Enterprise value | B23: =B19+B22 -> 175.65577
A24: Cash & investments | B24: =Main!C7 -> 41.249
A25: Debt | B25: =Main!C8 -> 0
A26: Equity value | B26: =B23+B24-B25 -> 216.90477
A27: Shares (mm) | B27: =Main!C4 -> 35.067159
A28: NPV / share | B28: =B26/B27 -> 6.1854105
A29: Price | B29: =Main!C3 -> 10.46
A30: Upside | B30: =B28/B29-1 -> -0.40866056
A31: Terminal value, % of EV | B31: =IFERROR(B22/B23,0) -> 0.72972302
