Workbook

Sheet Main
B2: Gilead Sciences, Inc.
B3: Price | C3: =INDEX([1]Pharma!$F$1:$F$1000,MATCH("GILD",[1]Pharma!$B$1:$B$1000,0)) -> 156.51
B4: Shares | C4: 1239.9552
B5: Market Cap. | C5: =C3*C4 -> 194065.38
B7: Cash | C7: 3179
B8: Debt | C8: =2414+23832 -> 26246
B9: Enterprise V. | C9: =C5-C7+C8 -> 217132.38
B11: NPV / Share | C11: =NPV!B28 -> 71.511969
B12: Upside | C12: =IFERROR(C11/C3-1,"") -> -0.54308371
B13: Cash / Share | C13: =IFERROR((C7-C8)/C4,"") -> -18.603092
B14: Scenario | C14: =Assumptions!C4 -> Base
B15: Model | C15: DCF

Sheet Yearly Model
B1: 2007 | C1: 2008 | D1: 2009 | E1: 2010 | F1: 2011 | G1: 2012 | H1: 2013 | I1: 2014 | J1: 2015 | K1: 2016 | L1: 2017 | M1: 2018 | N1: 2019 | O1: 2020 | P1: 2021 | Q1: 2022 | R1: 2023 | S1: 2024 | T1: 2025 | U1: 2026 | V1: 2027 | W1: 2028 | X1: 2029 | Y1: 2030 | Z1: 2031 | AA1: 2032 | AB1: 2033 | AC1: 2034 | AD1: 2035
A2: Revenue | B2: 4230.045 | C2: 5335.75 | D2: 7011.383 | E2: 7949.42 | F2: 8385.385 | G2: 9702.517 | H2: 11202 | I2: 24890 | J2: 32639 | K2: 30390 | L2: 26107 | M2: 22127 | N2: 22449 | O2: 24689 | P2: 27305 | Q2: 27281 | R2: 27116 | S2: 28754 | T2: 29443 | U2: =T2*(1+NPV!C5) -> 31221.357 | V2: =U2*(1+NPV!D5) -> 32984.323 | W2: =V2*(1+NPV!E5) -> 34717.1 | X2: =W2*(1+NPV!F5) -> 36404.351 | Y2: =X2*(1+NPV!G5) -> 38030.412 | Z2: =Y2*(1+NPV!H5) -> 39579.517 | AA2: =Z2*(1+NPV!I5) -> 41036.043 | AB2: =AA2*(1+NPV!J5) -> 42384.761 | ... AD2: =AC2*(1+NPV!L5) -> 44701.371
A3: Cost of Sales | B3: 768.771 | C3: 1127.246 | D3: 1595.558 | E3: 1869.876 | F3: 2124.41 | G3: 2471 | H3: 2859 | I3: 3788 | J3: 4006 | K3: 4261 | L3: 4371 | M3: 4853 | N3: 4675 | O3: 4572 | P3: 6601 | Q3: 5657 | R3: 6498 | S3: 6251 | T3: 6234 | U3: =U2*(1-Assumptions!$B$19) -> 6609.5613 | V3: =V2*(1-Assumptions!$B$19) -> 6982.7812 | W3: =W2*(1-Assumptions!$B$19) -> 7349.61 | X3: =X2*(1-Assumptions!$B$19) -> 7706.801 | Y3: =Y2*(1-Assumptions!$B$19) -> 8051.0381 | Z3: =Z2*(1-Assumptions!$B$19) -> 8378.9838 | AA3: =AA2*(1-Assumptions!$B$19) -> 8687.3304 | AB3: =AB2*(1-Assumptions!$B$19) -> 8972.854 | ... AD3: =AD2*(1-Assumptions!$B$19) -> 9463.2802
A4: Gross Margin | B4: =B2-B3 -> 3461.274 | C4: =C2-C3 -> 4208.504 | D4: =D2-D3 -> 5415.825 | E4: =E2-E3 -> 6079.544 | F4: =F2-F3 -> 6260.975 | G4: =G2-G3 -> 7231.517 | H4: =H2-H3 -> 8343 | I4: =I2-I3 -> 21102 | ... AD4: =AD2-AD3 -> 35238.091
A5: Research & Dev. | B5: 591.026 | C5: 721.768 | D5: 939.918 | E5: 1072.93 | F5: 1229.151 | G5: 1760 | H5: 2120 | I5: 2854 | J5: 3014 | K5: 5098 | L5: 3734 | M5: 5018 | N5: 9106 | O5: 4927 | P5: 4601 | Q5: 4977 | R5: 5718 | S5: 5907 | T5: 5799 | U5: =U7*Assumptions!$B$20 -> 7083.2152 | V5: =V7*Assumptions!$B$20 -> 7599.9581 | W5: =W7*Assumptions!$B$20 -> 8122.1213 | X5: =X7*Assumptions!$B$20 -> 8645.742 | Y5: =Y7*Assumptions!$B$20 -> 9166.561 | Z5: =Z7*Assumptions!$B$20 -> 9680.0725 | AA5: =AA7*Assumptions!$B$20 -> 10181.583 | AB5: =AB7*Assumptions!$B$20 -> 10666.276 | ... AD5: =AD7*Assumptions!$B$20 -> 11565.78
A6: SG&A & Other | B6: 705.741 | C6: 808.195 | D6: 946.686 | E6: 1044.392 | F6: 1241.983 | G6: 1461.517 | H6: 1699 | I6: 2983 | J6: 3426 | K6: 3398 | L6: 3878 | M6: 4056 | N6: 4381 | O6: 11119 | P6: 6185 | Q6: 9317 | R6: 7295 | S6: 14934 | T6: 7388 | U6: =U7-U5 -> 9022.3219 | V6: =V7-V5 -> 9680.5288 | W6: =W7-W5 -> 10345.64 | X6: =X7-X5 -> 11012.607 | Y6: =Y7-Y5 -> 11676.006 | Z6: =Z7-Z5 -> 12330.097 | AA6: =AA7-AA5 -> 12968.901 | AB6: =AB7-AB5 -> 13586.284 | ... AD6: =AD7-AD5 -> 14732.037
A7: Operating Expense | B7: =SUM(B5:B6) -> 1296.767 | C7: =SUM(C5:C6) -> 1529.963 | D7: =SUM(D5:D6) -> 1886.604 | E7: =SUM(E5:E6) -> 2117.322 | F7: =SUM(F5:F6) -> 2471.134 | G7: =SUM(G5:G6) -> 3221.517 | H7: =SUM(H5:H6) -> 3819 | I7: =SUM(I5:I6) -> 5837 | ... T7: =SUM(T5:T6) -> 13187 | U7: =U4-U2*NPV!C6 -> 16105.537 | V7: =V4-V2*NPV!D6 -> 17280.487 | W7: =W4-W2*NPV!E6 -> 18467.761 | X7: =X4-X2*NPV!F6 -> 19658.349 | Y7: =Y4-Y2*NPV!G6 -> 20842.567 | Z7: =Z4-Z2*NPV!H6 -> 22010.169 | AA7: =AA4-AA2*NPV!I6 -> 23150.484 | AB7: =AB4-AB2*NPV!J6 -> 24252.56 | ... AD7: =AD4-AD2*NPV!L6 -> 26297.817
A8: Operating Income | B8: =B4-B7 -> 2164.507 | C8: =C4-C7 -> 2678.541 | D8: =D4-D7 -> 3529.221 | E8: =E4-E7 -> 3962.222 | F8: =F4-F7 -> 3789.841 | G8: =G4-G7 -> 4010 | H8: =H4-H7 -> 4524 | I8: =I4-I7 -> 15265 | ... AD8: =AD4-AD7 -> 8940.2742
A9: Interest & Other | B9: 55.75 | C9: 2.721 | D9: -17.102 | E9: -37.166 | F9: -124.259 | G9: -380 | H9: -298 | I9: -367 | J9: -532 | K9: -523 | L9: -611 | M9: -406 | N9: 895 | O9: -2368 | P9: -1616 | Q9: -1490 | R9: -693 | S9: -971 | T9: -226 | U9: 0 | V9: 0 | W9: 0 | X9: 0 | Y9: 0 | Z9: 0 | AA9: 0 | AB9: 0 | AC9: 0 | AD9: 0
A10: Pretax | B10: =B8+B9 -> 2220.257 | C10: =C8+C9 -> 2681.262 | D10: =D8+D9 -> 3512.119 | E10: =E8+E9 -> 3925.056 | F10: =F8+F9 -> 3665.582 | G10: =G8+G9 -> 3630 | H10: =H8+H9 -> 4226 | I10: =I8+I9 -> 14898 | ... AD10: =AD8+AD9 -> 8940.2742
A11: Taxes | B11: 635.355 | C11: 702.363 | D11: 876.364 | E11: 1023.799 | F11: 861.945 | G11: 1038 | H11: 1151 | I11: 2797 | J11: 3553 | K11: 3609 | L11: 8885 | M11: 2339 | N11: -204 | O11: 1580 | P11: 2077 | Q11: 1248 | R11: 1247 | S11: 211 | T11: 1286 | U11: =MAX(0,U10)*Assumptions!$E$14 -> 1446.064 | V11: =MAX(0,V10)*Assumptions!$E$14 -> 1482.5794 | W11: =MAX(0,W10)*Assumptions!$E$14 -> 1512.9538 | X11: =MAX(0,X10)*Assumptions!$E$14 -> 1536.664 | Y11: =MAX(0,Y10)*Assumptions!$E$14 -> 1553.2571 | Z11: =MAX(0,Z10)*Assumptions!$E$14 -> 1562.3619 | AA11: =MAX(0,AA10)*Assumptions!$E$14 -> 1563.6989 | AB11: =MAX(0,AB10)*Assumptions!$E$14 -> 1557.089 | ... AD11: =MAX(0,AD10)*Assumptions!$E$14 -> 1519.8466
A12: Net Income | B12: 1584.902 | C12: 1978.899 | D12: 2635.755 | E12: 2901.257 | F12: 2803.637 | G12: 2592 | H12: 3075 | I12: 12101 | J12: 18108 | K12: 13501 | L12: 4628 | M12: 5455 | N12: 5386 | O12: 123 | P12: 6225 | Q12: 4592 | R12: 5665 | S12: 480 | T12: 8510 | U12: =U10-U11 -> 7060.1948 | V12: =V10-V11 -> 7238.4757 | W12: =W10-W11 -> 7386.7746 | X12: =X10-X11 -> 7502.5362 | Y12: =Y10-Y11 -> 7583.5493 | Z12: =Z10-Z11 -> 7628.002 | AA12: =AA10-AA11 -> 7634.5302 | AB12: =AB10-AB11 -> 7602.2579 | ... AD12: =AD10-AD11 -> 7420.4276
A13: Earnings per Share | B13: =IFERROR(B12/B14,0) -> 1.6434823 | C13: =IFERROR(C12/C14,0) -> 2.0638792 | D13: =IFERROR(D12/D14,0) -> 2.8216782 | E13: =IFERROR(E12/E14,0) -> 1.6609058 | F13: =IFERROR(F12/F14,0) -> 1.7741888 | G13: =IFERROR(G12/G14,0) -> 1.6373973 | H13: =IFERROR(H12/H14,0) -> 1.8141593 | I13: =IFERROR(I12/I14,0) -> 7.3472981 | ... AD13: =IFERROR(AD12/AD14,0) -> 5.9844322
A14: Shares | B14: 964.356 | C14: 958.825 | D14: 934.109 | E14: 1746.792 | F14: 1580.236 | G14: 1583 | H14: 1695 | I14: 1647 | J14: 1521 | K14: 1358 | L14: 1319 | M14: 1308 | N14: 1277 | O14: 1263 | P14: 1262 | Q14: 1262 | R14: 1258 | S14: 1255 | T14: 1255 | U14: =Main!$C$4 -> 1239.9552 | V14: =Main!$C$4 -> 1239.9552 | W14: =Main!$C$4 -> 1239.9552 | X14: =Main!$C$4 -> 1239.9552 | Y14: =Main!$C$4 -> 1239.9552 | Z14: =Main!$C$4 -> 1239.9552 | AA14: =Main!$C$4 -> 1239.9552 | AB14: =Main!$C$4 -> 1239.9552 | ... AD14: =Main!$C$4 -> 1239.9552
A16: Revenue Change | C16: =IFERROR(C2/B2-1,"") -> 0.2613932 | D16: =IFERROR(D2/C2-1,"") -> 0.31403889 | E16: =IFERROR(E2/D2-1,"") -> 0.13378773 | F16: =IFERROR(F2/E2-1,"") -> 0.054842366 | G16: =IFERROR(G2/F2-1,"") -> 0.15707472 | H16: =IFERROR(H2/G2-1,"") -> 0.15454577 | I16: =IFERROR(I2/H2-1,"") -> 1.2219247 | J16: =IFERROR(J2/I2-1,"") -> 0.31132985 | ... AD16: =IFERROR(AD2/AC2-1,"") -> 0.025
A17: Gross Margin | B17: =IFERROR(B4/B2,"") -> 0.81825938 | C17: =IFERROR(C4/C2,"") -> 0.7887371 | D17: =IFERROR(D4/D2,"") -> 0.7724332 | E17: =IFERROR(E4/E2,"") -> 0.76477831 | F17: =IFERROR(F4/F2,"") -> 0.74665325 | G17: =IFERROR(G4/G2,"") -> 0.74532382 | H17: =IFERROR(H4/H2,"") -> 0.74477772 | I17: =IFERROR(I4/I2,"") -> 0.84781037 | ... AD17: =IFERROR(AD4/AD2,"") -> 0.7883
A18: Operating Margin | B18: =IFERROR(B8/B2,"") -> 0.51169834 | C18: =IFERROR(C8/C2,"") -> 0.50199897 | D18: =IFERROR(D8/D2,"") -> 0.5033559 | E18: =IFERROR(E8/E2,"") -> 0.49842907 | F18: =IFERROR(F8/F2,"") -> 0.4519579 | G18: =IFERROR(G8/G2,"") -> 0.41329482 | H18: =IFERROR(H8/H2,"") -> 0.40385645 | I18: =IFERROR(I8/I2,"") -> 0.61329851 | ... AD18: =IFERROR(AD8/AD2,"") -> 0.2
A19: Actual / Estimate | B19: A | C19: A | D19: A | E19: A | F19: A | G19: A | H19: A | I19: A | J19: A | K19: A | L19: A | M19: A | N19: A | O19: A | P19: A | Q19: A | R19: A | S19: A | T19: A | U19: E | V19: E | W19: E | X19: E | Y19: E | Z19: E | AA19: E | AB19: E | AC19: E | AD19: E

Sheet Quarterly Model

Sheet Assumptions
A1: Gilead Sciences, Inc.: basic DCF assumptions
A2: Blue = input, black = formula, green = link. $mm unless noted.
A4: Scenario (1 Bear, 2 Base, 3 Bull) | B4: 2 | C4: =CHOOSE($B$4,"Bear","Base","Bull") -> Base
A6: Discount rate override (blank = scenario)
A7: Terminal growth override (blank = scenario)
A9: Parameter | B9: Bear | C9: Base | D9: Bull | E9: Live
A10: Discount rate | B10: 0.09 | C10: 0.08 | D10: 0.07 | E10: =IF(ISNUMBER($B$6),$B$6,CHOOSE($B$4,B10,C10,D10)) -> 0.08
A11: Terminal growth | B11: 0.02 | C11: 0.025 | D11: 0.03 | E11: =IF(ISNUMBER($B$7),$B$7,CHOOSE($B$4,B11,C11,D11)) -> 0.025
A12: Revenue growth, first forecast year | B12: 0.0104 | C12: 0.0604 | D12: 0.1104 | E12: =CHOOSE($B$4,B12,C12,D12) -> 0.0604
A13: Operating margin, year 10 | B13: 0.15 | C13: 0.2 | D13: 0.25 | E13: =CHOOSE($B$4,B13,C13,D13) -> 0.2
A14: Tax rate on operating income | B14: 0.17 | C14: 0.17 | D14: 0.17 | E14: =CHOOSE($B$4,B14,C14,D14) -> 0.17
A15: Reinvestment, % of revenue increase | B15: 0.25 | C15: 0.25 | D15: 0.25 | E15: =CHOOSE($B$4,B15,C15,D15) -> 0.25
A17: Single inputs
A18: Starting operating margin (TTM) | B18: 0.2805
A19: Gross margin (forecast) | B19: 0.7883
A20: R&D share of operating expense (forecast) | B20: 0.4398
A21: Forecast years | B21: 10
A22: First forecast year, fraction after balance sheet date | B22: 0.5041
A23: Balance sheet date | B23: 46203
A24: Reporting currency per USD (USD) | B24: 1
A25: Base revenue, FY2025 | B25: ='Yearly Model'!T2 -> 29443
A27: Scenario summary
A28: Scenario | B28: Enterprise value | C28: Equity value | D28: NPV / share | E28: Upside
A29: Live | B29: =NPV!B23 -> 111738.63 | C29: =NPV!B26 -> 88671.635 | D29: =NPV!B28 -> 71.511969 | E29: =NPV!B30 -> -0.54308371
A30: 1 | B30: 61626.375 | C30: 38559.375 | D30: 31.097395 | E30: -0.8013073
A31: 2 | B31: 111738.63 | C31: 88671.635 | D31: 71.511969 | E31: -0.54308371
A32: 3 | B32: 221805.83 | C32: 198738.83 | D32: 160.27905 | E32: 0.024081842
A35: NPV / share: discount rate (rows) x terminal growth (columns)
A36: =NPV!B28 -> 71.511969 | B36: 0.015 | C36: 0.02 | D36: 0.025 | E36: 0.03 | F36: 0.035
A37: 0.06 | B37: 94.896304 | C37: 105.92074 | D37: 120.07384 | E37: 138.9197 | F37: 165.27369
A38: 0.07 | B38: 75.06911 | C38: 81.975843 | D38: 90.401743 | E38: 100.91633 | F38: 114.41455
A39: 0.08 | B39: 61.34092 | C39: 66.008239 | D39: 71.511969 | E39: 78.102906 | F39: 86.143307
A40: 0.09 | B40: 51.270282 | C40: 54.5972 | D40: 58.426134 | E40: 62.882487 | F40: 68.137262
A41: 0.1 | B41: 43.56499 | C41: 46.032711 | D41: 48.821361 | E41: 51.999631 | F41: 55.657342

Sheet NPV
A1: Gilead Sciences, Inc.: free-cash-flow DCF ($mm)
A3: Fiscal year | B3: ='Yearly Model'!T1 -> 2025 | C3: ='Yearly Model'!U1 -> 2026 | D3: ='Yearly Model'!V1 -> 2027 | E3: ='Yearly Model'!W1 -> 2028 | F3: ='Yearly Model'!X1 -> 2029 | G3: ='Yearly Model'!Y1 -> 2030 | H3: ='Yearly Model'!Z1 -> 2031 | I3: ='Yearly Model'!AA1 -> 2032 | ... L3: ='Yearly Model'!AD1 -> 2035
A4: Period | B4: Actual | C4: 1 | D4: 2 | E4: 3 | F4: 4 | G4: 5 | H4: 6 | I4: 7 | J4: 8 | K4: 9 | L4: 10
A5: Revenue growth | C5: =Assumptions!$E$12+(Assumptions!$E$11-Assumptions!$E$12)*(C4-1)/(Assumptions!$B$21-1) -> 0.0604 | D5: =Assumptions!$E$12+(Assumptions!$E$11-Assumptions!$E$12)*(D4-1)/(Assumptions!$B$21-1) -> 0.056466667 | E5: =Assumptions!$E$12+(Assumptions!$E$11-Assumptions!$E$12)*(E4-1)/(Assumptions!$B$21-1) -> 0.052533333 | F5: =Assumptions!$E$12+(Assumptions!$E$11-Assumptions!$E$12)*(F4-1)/(Assumptions!$B$21-1) -> 0.0486 | G5: =Assumptions!$E$12+(Assumptions!$E$11-Assumptions!$E$12)*(G4-1)/(Assumptions!$B$21-1) -> 0.044666667 | H5: =Assumptions!$E$12+(Assumptions!$E$11-Assumptions!$E$12)*(H4-1)/(Assumptions!$B$21-1) -> 0.040733333 | I5: =Assumptions!$E$12+(Assumptions!$E$11-Assumptions!$E$12)*(I4-1)/(Assumptions!$B$21-1) -> 0.0368 | J5: =Assumptions!$E$12+(Assumptions!$E$11-Assumptions!$E$12)*(J4-1)/(Assumptions!$B$21-1) -> 0.032866667 | ... L5: =Assumptions!$E$12+(Assumptions!$E$11-Assumptions!$E$12)*(L4-1)/(Assumptions!$B$21-1) -> 0.025
A6: Operating margin | B6: =IFERROR(B8/B7,0) -> 0.34038651 | C6: =Assumptions!$B$18+(Assumptions!$E$13-Assumptions!$B$18)*C4/Assumptions!$B$21 -> 0.27245 | D6: =Assumptions!$B$18+(Assumptions!$E$13-Assumptions!$B$18)*D4/Assumptions!$B$21 -> 0.2644 | E6: =Assumptions!$B$18+(Assumptions!$E$13-Assumptions!$B$18)*E4/Assumptions!$B$21 -> 0.25635 | F6: =Assumptions!$B$18+(Assumptions!$E$13-Assumptions!$B$18)*F4/Assumptions!$B$21 -> 0.2483 | G6: =Assumptions!$B$18+(Assumptions!$E$13-Assumptions!$B$18)*G4/Assumptions!$B$21 -> 0.24025 | H6: =Assumptions!$B$18+(Assumptions!$E$13-Assumptions!$B$18)*H4/Assumptions!$B$21 -> 0.2322 | I6: =Assumptions!$B$18+(Assumptions!$E$13-Assumptions!$B$18)*I4/Assumptions!$B$21 -> 0.22415 | J6: =Assumptions!$B$18+(Assumptions!$E$13-Assumptions!$B$18)*J4/Assumptions!$B$21 -> 0.2161 | ... L6: =Assumptions!$B$18+(Assumptions!$E$13-Assumptions!$B$18)*L4/Assumptions!$B$21 -> 0.2
A7: Revenue | B7: ='Yearly Model'!T2 -> 29443 | C7: ='Yearly Model'!U2 -> 31221.357 | D7: ='Yearly Model'!V2 -> 32984.323 | E7: ='Yearly Model'!W2 -> 34717.1 | F7: ='Yearly Model'!X2 -> 36404.351 | G7: ='Yearly Model'!Y2 -> 38030.412 | H7: ='Yearly Model'!Z2 -> 39579.517 | I7: ='Yearly Model'!AA2 -> 41036.043 | ... L7: ='Yearly Model'!AD2 -> 44701.371
A8: Operating income | B8: ='Yearly Model'!T8 -> 10022 | C8: ='Yearly Model'!U8 -> 8506.2588 | D8: ='Yearly Model'!V8 -> 8721.055 | E8: ='Yearly Model'!W8 -> 8899.7285 | F8: ='Yearly Model'!X8 -> 9039.2003 | G8: ='Yearly Model'!Y8 -> 9136.8064 | H8: ='Yearly Model'!Z8 -> 9190.3639 | I8: ='Yearly Model'!AA8 -> 9198.2291 | ... L8: ='Yearly Model'!AD8 -> 8940.2742
A9: Tax on operating income | C9: =MAX(0,C8)*Assumptions!$E$14 -> 1446.064 | D9: =MAX(0,D8)*Assumptions!$E$14 -> 1482.5794 | E9: =MAX(0,E8)*Assumptions!$E$14 -> 1512.9538 | F9: =MAX(0,F8)*Assumptions!$E$14 -> 1536.664 | G9: =MAX(0,G8)*Assumptions!$E$14 -> 1553.2571 | H9: =MAX(0,H8)*Assumptions!$E$14 -> 1562.3619 | I9: =MAX(0,I8)*Assumptions!$E$14 -> 1563.6989 | J9: =MAX(0,J8)*Assumptions!$E$14 -> 1557.089 | ... L9: =MAX(0,L8)*Assumptions!$E$14 -> 1519.8466
A10: NOPAT | C10: =C8-C9 -> 7060.1948 | D10: =D8-D9 -> 7238.4757 | E10: =E8-E9 -> 7386.7746 | F10: =F8-F9 -> 7502.5362 | G10: =G8-G9 -> 7583.5493 | H10: =H8-H9 -> 7628.002 | I10: =I8-I9 -> 7634.5302 | J10: =J8-J9 -> 7602.2579 | ... L10: =L8-L9 -> 7420.4276
A11: Reinvestment | C11: =(C7-B7)*Assumptions!$E$15 -> 444.5893 | D11: =(D7-C7)*Assumptions!$E$15 -> 440.74149 | E11: =(E7-D7)*Assumptions!$E$15 -> 433.19411 | F11: =(F7-E7)*Assumptions!$E$15 -> 421.81276 | G11: =(G7-F7)*Assumptions!$E$15 -> 406.51525 | H11: =(H7-G7)*Assumptions!$E$15 -> 387.27636 | I11: =(I7-H7)*Assumptions!$E$15 -> 364.13156 | J11: =(J7-I7)*Assumptions!$E$15 -> 337.17949 | ... L11: =(L7-K7)*Assumptions!$E$15 -> 272.56934
A12: Free cash flow | C12: =C10-C11 -> 6615.6055 | D12: =D10-D11 -> 6797.7342 | E12: =E10-E11 -> 6953.5805 | F12: =F10-F11 -> 7080.7235 | G12: =G10-G11 -> 7177.0341 | H12: =H10-H11 -> 7240.7257 | I12: =I10-I11 -> 7270.3986 | J12: =J10-J11 -> 7265.0784 | ... L12: =L10-L11 -> 7147.8583
A13: Year fraction | C13: =Assumptions!$B$22 -> 0.5041 | D13: 1 | E13: 1 | F13: 1 | G13: 1 | H13: 1 | I13: 1 | J13: 1 | K13: 1 | L13: 1
A14: Discount time (mid-period) | C14: =C13/2 -> 0.25205 | D14: =C14+C13/2+D13/2 -> 1.0041 | E14: =D14+D13/2+E13/2 -> 2.0041 | F14: =E14+E13/2+F13/2 -> 3.0041 | G14: =F14+F13/2+G13/2 -> 4.0041 | H14: =G14+G13/2+H13/2 -> 5.0041 | I14: =H14+H13/2+I13/2 -> 6.0041 | J14: =I14+I13/2+J13/2 -> 7.0041 | K14: =J14+J13/2+K13/2 -> 8.0041 | L14: =K14+K13/2+L13/2 -> 9.0041
A15: Discount factor | C15: =1/(1+Assumptions!$E$10)^C14 -> 0.9807889 | D15: =1/(1+Assumptions!$E$10)^D14 -> 0.92563381 | E15: =1/(1+Assumptions!$E$10)^E14 -> 0.85706834 | F15: =1/(1+Assumptions!$E$10)^F14 -> 0.79358179 | G15: =1/(1+Assumptions!$E$10)^G14 -> 0.73479796 | H15: =1/(1+Assumptions!$E$10)^H14 -> 0.68036848 | I15: =1/(1+Assumptions!$E$10)^I14 -> 0.62997081 | J15: =1/(1+Assumptions!$E$10)^J14 -> 0.58330631 | ... L15: =1/(1+Assumptions!$E$10)^L14 -> 0.50009114
A16: PV of free cash flow | C16: =C12*C13*C15 -> 3270.8591 | D16: =D12*D13*D15 -> 6292.2126 | E16: =E12*E13*E15 -> 5959.6937 | F16: =F12*F13*F15 -> 5619.1332 | G16: =G12*G13*G15 -> 5273.67 | H16: =H12*H13*H15 -> 4926.3615 | I16: =I12*I13*I15 -> 4580.1389 | J16: =J12*J13*J15 -> 4237.7661 | ... L16: =L12*L13*L15 -> 3574.5806
A19: PV of forecast free cash flow | B19: =SUM(C16:L16) -> 47636.22
A20: Terminal free cash flow (year 11) | B20: =L10*(1+Assumptions!$E$11)-L7*Assumptions!$E$11*Assumptions!$E$15 -> 7326.5547
A21: Terminal value | B21: =B20/(Assumptions!$E$10-Assumptions!$E$11) -> 133210.09
A22: PV of terminal value | B22: =B21/(1+Assumptions!$E$10)^(L14+0.5) -> 64102.415
A23: Enterprise value | B23: =B19+B22 -> 111738.63
A24: Cash & investments | B24: =Main!C7 -> 3179
A25: Debt | B25: =Main!C8 -> 26246
A26: Equity value | B26: =B23+B24-B25 -> 88671.635
A27: Shares (mm) | B27: =Main!C4 -> 1239.9552
A28: NPV / share | B28: =B26/B27 -> 71.511969
A29: Price | B29: =Main!C3 -> 156.51
A30: Upside | B30: =B28/B29-1 -> -0.54308371
A31: Terminal value, % of EV | B31: =IFERROR(B22/B23,0) -> 0.57368175
