Workbook

Sheet Main
B2: Haleon PLC
B3: Price | C3: =INDEX([1]Pharma!$F$1:$F$1000,MATCH("HLN",[1]Pharma!$B$1:$B$1000,0)) -> 10.17
B4: Shares | C4: =8952.353648/2 -> 4476.1768
B5: Market Cap. | C5: =C3*C4 -> 45522.718
B7: Cash | C7: =(1324)/0.74989 -> 1765.5923
B8: Debt | C8: =(836+7773)/0.74989 -> 11480.35
B9: Enterprise V. | C9: =C5-C7+C8 -> 55237.476
B11: NPV / Share | C11: =NPV!B28 -> 5.973576
B12: Upside | C12: =IFERROR(C11/C3-1,"") -> -0.41262772
B13: Cash / Share | C13: =IFERROR((C7-C8)/C4,"") -> -2.1703249
B14: Scenario | C14: =Assumptions!C4 -> Base
B15: Model | C15: DCF

Sheet Yearly Model
B1: 2020 | C1: 2021 | D1: 2022 | E1: 2023 | F1: 2024 | G1: 2025 | H1: 2026 | I1: 2027 | J1: 2028 | K1: 2029 | L1: 2030 | M1: 2031 | N1: 2032 | O1: 2033 | P1: 2034 | Q1: 2035
A2: Revenue | B2: 13191.268 | C2: 12728.534 | D2: 14479.457 | E2: 15071.544 | F2: 14979.53 | G2: 14708.824 | H2: =G2*(1+NPV!C5) -> 14442.594 | I2: =H2*(1+NPV!D5) -> 14250.347 | J2: =I2*(1+NPV!E5) -> 14128.903 | K2: =J2*(1+NPV!F5) -> 14076.155 | L2: =K2*(1+NPV!G5) -> 14091.013 | M2: =L2*(1+NPV!H5) -> 14173.367 | N2: =M2*(1+NPV!I5) -> 14324.077 | O2: =N2*(1+NPV!J5) -> 14544.986 | ... Q2: =P2*(1+NPV!L5) -> 15209.931
A3: Cost of Sales | B3: 5310.112 | C3: 4794.036 | D3: 5708.837 | E3: 6074.224 | F3: 5879.529 | G3: 5267.439 | H3: =H2*(1-Assumptions!$B$19) -> 5171.893 | I3: =I2*(1-Assumptions!$B$19) -> 5103.0494 | J3: =J2*(1-Assumptions!$B$19) -> 5059.5601 | K3: =K2*(1-Assumptions!$B$19) -> 5040.671 | L3: =L2*(1-Assumptions!$B$19) -> 5045.9917 | M3: =M2*(1-Assumptions!$B$19) -> 5075.4828 | N3: =N2*(1-Assumptions!$B$19) -> 5129.4521 | O3: =O2*(1-Assumptions!$B$19) -> 5208.5596 | ... Q3: =Q2*(1-Assumptions!$B$19) -> 5446.6761
A4: Gross Margin | B4: =B2-B3 -> 7881.156 | C4: =C2-C3 -> 7934.498 | D4: =D2-D3 -> 8770.62 | E4: =E2-E3 -> 8997.32 | F4: =F2-F3 -> 9100.001 | G4: =G2-G3 -> 9441.385 | H4: =H2-H3 -> 9270.7013 | I4: =I2-I3 -> 9147.2979 | ... Q4: =Q2-Q3 -> 9763.2544
A5: Research & Dev. | B5: 405.393 | C5: 342.717 | D5: 400.059 | E5: 414.727 | F5: 397.392 | G5: 421.395 | H5: =H7*Assumptions!$B$20 -> 414.88466 | I5: =I7*Assumptions!$B$20 -> 410.44261 | J5: =J7*Assumptions!$B$20 -> 408.01603 | K5: =K7*Assumptions!$B$20 -> 407.56008 | L5: =L7*Assumptions!$B$20 -> 409.05872 | M5: =M7*Assumptions!$B$20 -> 412.52413 | N5: =N7*Assumptions!$B$20 -> 417.99674 | O5: =O7*Assumptions!$B$20 -> 425.54604 | ... Q5: =Q7*Assumptions!$B$20 -> 447.30702
A6: SG&A & Other | B6: 5344.784 | C6: 5407.46 | D6: 5936.871 | E6: 5920.868 | F6: 5760.845 | G6: 5803.518 | H6: =H7-H5 -> 5713.3969 | I6: =I7-I5 -> 5652.2252 | J6: =J7-J5 -> 5618.8087 | K6: =K7-K5 -> 5612.5298 | L6: =L7-L5 -> 5633.1676 | M6: =M7-M5 -> 5680.8899 | N6: =N7-N5 -> 5756.2535 | O6: =O7-O5 -> 5860.2152 | ... Q6: =Q7-Q5 -> 6159.8868
A7: Operating Expense | B7: =SUM(B5:B6) -> 5750.177 | C7: =SUM(C5:C6) -> 5750.177 | D7: =SUM(D5:D6) -> 6336.93 | E7: =SUM(E5:E6) -> 6335.595 | F7: =SUM(F5:F6) -> 6158.237 | G7: =SUM(G5:G6) -> 6224.913 | H7: =H4-H2*NPV!C6 -> 6128.2816 | I7: =I4-I2*NPV!D6 -> 6062.6678 | J7: =J4-J2*NPV!E6 -> 6026.8247 | K7: =K4-K2*NPV!F6 -> 6020.0899 | L7: =L4-L2*NPV!G6 -> 6042.2263 | M7: =M4-M2*NPV!H6 -> 6093.414 | N7: =N4-N2*NPV!I6 -> 6174.2502 | O7: =O4-O2*NPV!J6 -> 6285.7613 | ... Q7: =Q4-Q2*NPV!L6 -> 6607.1938
A8: Operating Income | B8: =B4-B7 -> 2130.979 | C8: =C4-C7 -> 2184.321 | D8: =D4-D7 -> 2433.69 | E8: =E4-E7 -> 2661.725 | F8: =F4-F7 -> 2941.764 | G8: =G4-G7 -> 3216.472 | H8: =H4-H7 -> 3142.4197 | I8: =I4-I7 -> 3084.6302 | ... Q8: =Q4-Q7 -> 3156.0606
A9: Interest & Other | B9: -57.342 | C9: -68.01 | D9: -354.719 | E9: -573.417 | F9: -438.731 | G9: -364.053 | H9: 0 | I9: 0 | J9: 0 | K9: 0 | L9: 0 | M9: 0 | N9: 0 | O9: 0 | P9: 0 | Q9: 0
A10: Pretax | B10: =B8+B9 -> 2073.637 | C10: =C8+C9 -> 2116.311 | D10: =D8+D9 -> 2078.971 | E10: =E8+E9 -> 2088.308 | F10: =F8+F9 -> 2503.033 | G10: =G8+G9 -> 2852.419 | H10: =H8+H9 -> 3142.4197 | I10: =I8+I9 -> 3084.6302 | ... Q10: =Q8+Q9 -> 3156.0606
A11: Taxes | B11: 546.747 | C11: 262.705 | D11: 665.431 | E11: 689.434 | F11: 580.085 | G11: 629.426 | H11: =MAX(0,H10)*Assumptions!$E$14 -> 534.21134 | I11: =MAX(0,I10)*Assumptions!$E$14 -> 524.38713 | J11: =MAX(0,J10)*Assumptions!$E$14 -> 517.22804 | K11: =MAX(0,K10)*Assumptions!$E$14 -> 512.61696 | L11: =MAX(0,L10)*Assumptions!$E$14 -> 510.47513 | M11: =MAX(0,M10)*Assumptions!$E$14 -> 510.75996 | N11: =MAX(0,N10)*Assumptions!$E$14 -> 513.46374 | O11: =MAX(0,O10)*Assumptions!$E$14 -> 518.61312 | ... Q11: =MAX(0,Q10)*Assumptions!$E$14 -> 536.5303
A12: Net Income | B12: 1526.891 | C12: 1853.605 | D12: 1413.541 | E12: 1398.872 | F12: 1922.949 | G12: 2222.993 | H12: =H10-H11 -> 2608.2083 | I12: =I10-I11 -> 2560.243 | J12: =J10-J11 -> 2525.2899 | K12: =K10-K11 -> 2502.7769 | L12: =L10-L11 -> 2492.3197 | M12: =M10-M11 -> 2493.7104 | N12: =N10-N11 -> 2506.9112 | O12: =O10-O11 -> 2532.0523 | ... Q12: =Q10-Q11 -> 2619.5303
A13: Earnings per Share | B13: =IFERROR(B12/B14,0) -> 0.16533741 | C13: =IFERROR(C12/C14,0) -> 0.20071521 | D13: =IFERROR(D12/D14,0) -> 0.15299719 | E13: =IFERROR(E12/E14,0) -> 0.15101717 | F13: =IFERROR(F12/F14,0) -> 0.20958572 | G13: =IFERROR(G12/G14,0) -> 0.24628772 | H13: =IFERROR(H12/H14,0) -> 0.58268661 | I13: =IFERROR(I12/I14,0) -> 0.57197094 | ... Q13: =IFERROR(Q12/Q14,0) -> 0.585216
A14: Shares | B14: 9235 | C14: 9235 | D14: 9239 | E14: 9263 | F14: 9175 | G14: 9026 | H14: =Main!$C$4 -> 4476.1768 | I14: =Main!$C$4 -> 4476.1768 | J14: =Main!$C$4 -> 4476.1768 | K14: =Main!$C$4 -> 4476.1768 | L14: =Main!$C$4 -> 4476.1768 | M14: =Main!$C$4 -> 4476.1768 | N14: =Main!$C$4 -> 4476.1768 | O14: =Main!$C$4 -> 4476.1768 | ... Q14: =Main!$C$4 -> 4476.1768
A16: Revenue Change | C16: =IFERROR(C2/B2-1,"") -> -0.035078811 | D16: =IFERROR(D2/C2-1,"") -> 0.13755889 | E16: =IFERROR(E2/D2-1,"") -> 0.04089152 | F16: =IFERROR(F2/E2-1,"") -> -0.0061051476 | G16: =IFERROR(G2/F2-1,"") -> -0.018071729 | H16: =IFERROR(H2/G2-1,"") -> -0.0181 | I16: =IFERROR(I2/H2-1,"") -> -0.013311111 | J16: =IFERROR(J2/I2-1,"") -> -0.0085222222 | ... Q16: =IFERROR(Q2/P2-1,"") -> 0.025
A17: Gross Margin | B17: =IFERROR(B4/B2,"") -> 0.5974525 | C17: =IFERROR(C4/C2,"") -> 0.62336307 | D17: =IFERROR(D4/D2,"") -> 0.60572852 | E17: =IFERROR(E4/E2,"") -> 0.59697401 | F17: =IFERROR(F4/F2,"") -> 0.60749576 | G17: =IFERROR(G4/G2,"") -> 0.64188578 | H17: =IFERROR(H4/H2,"") -> 0.6419 | I17: =IFERROR(I4/I2,"") -> 0.6419 | ... Q17: =IFERROR(Q4/Q2,"") -> 0.6419
A18: Operating Margin | B18: =IFERROR(B8/B2,"") -> 0.16154467 | C18: =IFERROR(C8/C2,"") -> 0.17160822 | D18: =IFERROR(D8/D2,"") -> 0.16807882 | E18: =IFERROR(E8/E2,"") -> 0.17660599 | F18: =IFERROR(F8/F2,"") -> 0.1963856 | G18: =IFERROR(G8/G2,"") -> 0.21867635 | H18: =IFERROR(H8/H2,"") -> 0.21758 | I18: =IFERROR(I8/I2,"") -> 0.21646 | ... Q18: =IFERROR(Q8/Q2,"") -> 0.2075
A19: Actual / Estimate | B19: A | C19: A | D19: A | E19: A | F19: A | G19: A | H19: E | I19: E | J19: E | K19: E | L19: E | M19: E | N19: E | O19: E | P19: E | Q19: E

Sheet Quarterly Model

Sheet Assumptions
A1: Haleon PLC: basic DCF assumptions
A2: Blue = input, black = formula, green = link. $mm unless noted.
A4: Scenario (1 Bear, 2 Base, 3 Bull) | B4: 2 | C4: =CHOOSE($B$4,"Bear","Base","Bull") -> Base
A6: Discount rate override (blank = scenario)
A7: Terminal growth override (blank = scenario)
A9: Parameter | B9: Bear | C9: Base | D9: Bull | E9: Live
A10: Discount rate | B10: 0.095 | C10: 0.085 | D10: 0.075 | E10: =IF(ISNUMBER($B$6),$B$6,CHOOSE($B$4,B10,C10,D10)) -> 0.085
A11: Terminal growth | B11: 0.02 | C11: 0.025 | D11: 0.03 | E11: =IF(ISNUMBER($B$7),$B$7,CHOOSE($B$4,B11,C11,D11)) -> 0.025
A12: Revenue growth, first forecast year | B12: -0.0681 | C12: -0.0181 | D12: 0.0319 | E12: =CHOOSE($B$4,B12,C12,D12) -> -0.0181
A13: Operating margin, year 10 | B13: 0.1575 | C13: 0.2075 | D13: 0.2575 | E13: =CHOOSE($B$4,B13,C13,D13) -> 0.2075
A14: Tax rate on operating income | B14: 0.17 | C14: 0.17 | D14: 0.17 | E14: =CHOOSE($B$4,B14,C14,D14) -> 0.17
A15: Reinvestment, % of revenue increase | B15: 0.25 | C15: 0.25 | D15: 0.25 | E15: =CHOOSE($B$4,B15,C15,D15) -> 0.25
A17: Single inputs
A18: Starting operating margin (TTM) | B18: 0.2187
A19: Gross margin (forecast) | B19: 0.6419
A20: R&D share of operating expense (forecast) | B20: 0.0677
A21: Forecast years | B21: 10
A22: First forecast year, fraction after balance sheet date | B22: 1
A23: Balance sheet date | B23: 46022
A24: Reporting currency per USD (GBP) | B24: 0.74989
A25: Base revenue, FY2025 | B25: ='Yearly Model'!G2 -> 14708.824
A27: Scenario summary
A28: Scenario | B28: Enterprise value | C28: Equity value | D28: NPV / share | E28: Upside
A29: Live | B29: =NPV!B23 -> 36453.541 | C29: =NPV!B26 -> 26738.783 | D29: =NPV!B28 -> 5.973576 | E29: =NPV!B30 -> -0.41262772
A30: 1 | B30: 21133.252 | C30: 11418.494 | D30: 2.5509479 | E30: -0.74916933
A31: 2 | B31: 36453.541 | C31: 26738.783 | D31: 5.973576 | E31: -0.41262772
A32: 3 | B32: 69039.225 | C32: 59324.467 | D32: 13.253379 | E32: 0.30318375
A35: NPV / share: discount rate (rows) x terminal growth (columns)
A36: =NPV!B28 -> 5.973576 | B36: 0.015 | C36: 0.02 | D36: 0.025 | E36: 0.03 | F36: 0.035
A37: 0.065 | B37: 7.8911696 | C37: 8.714066 | D37: 9.7412957 | E37: 11.060416 | F37: 12.817354
A38: 0.075 | B38: 6.304423 | C38: 6.8397644 | D38: 7.4811176 | E38: 8.2638093 | F38: 9.2408297
A39: 0.085 | B39: 5.1708057 | C39: 5.5417009 | D39: 5.973576 | E39: 6.483054 | F39: 7.0934065
A40: 0.095 | B40: 4.3202027 | C40: 4.5891843 | D40: 4.8959115 | E40: 5.2490884 | F40: 5.6603203
A41: 0.105 | B41: 3.65814 | C41: 3.8601201 | D41: 4.0867824 | E41: 4.3430581 | F41: 4.6352871

Sheet NPV
A1: Haleon PLC: free-cash-flow DCF ($mm)
A3: Fiscal year | B3: ='Yearly Model'!G1 -> 2025 | C3: ='Yearly Model'!H1 -> 2026 | D3: ='Yearly Model'!I1 -> 2027 | E3: ='Yearly Model'!J1 -> 2028 | F3: ='Yearly Model'!K1 -> 2029 | G3: ='Yearly Model'!L1 -> 2030 | H3: ='Yearly Model'!M1 -> 2031 | I3: ='Yearly Model'!N1 -> 2032 | ... L3: ='Yearly Model'!Q1 -> 2035
A4: Period | B4: Actual | C4: 1 | D4: 2 | E4: 3 | F4: 4 | G4: 5 | H4: 6 | I4: 7 | J4: 8 | K4: 9 | L4: 10
A5: Revenue growth | C5: =Assumptions!$E$12+(Assumptions!$E$11-Assumptions!$E$12)*(C4-1)/(Assumptions!$B$21-1) -> -0.0181 | D5: =Assumptions!$E$12+(Assumptions!$E$11-Assumptions!$E$12)*(D4-1)/(Assumptions!$B$21-1) -> -0.013311111 | E5: =Assumptions!$E$12+(Assumptions!$E$11-Assumptions!$E$12)*(E4-1)/(Assumptions!$B$21-1) -> -0.0085222222 | F5: =Assumptions!$E$12+(Assumptions!$E$11-Assumptions!$E$12)*(F4-1)/(Assumptions!$B$21-1) -> -0.0037333333 | G5: =Assumptions!$E$12+(Assumptions!$E$11-Assumptions!$E$12)*(G4-1)/(Assumptions!$B$21-1) -> 0.0010555556 | H5: =Assumptions!$E$12+(Assumptions!$E$11-Assumptions!$E$12)*(H4-1)/(Assumptions!$B$21-1) -> 0.0058444444 | I5: =Assumptions!$E$12+(Assumptions!$E$11-Assumptions!$E$12)*(I4-1)/(Assumptions!$B$21-1) -> 0.010633333 | J5: =Assumptions!$E$12+(Assumptions!$E$11-Assumptions!$E$12)*(J4-1)/(Assumptions!$B$21-1) -> 0.015422222 | ... L5: =Assumptions!$E$12+(Assumptions!$E$11-Assumptions!$E$12)*(L4-1)/(Assumptions!$B$21-1) -> 0.025
A6: Operating margin | B6: =IFERROR(B8/B7,0) -> 0.21867635 | C6: =Assumptions!$B$18+(Assumptions!$E$13-Assumptions!$B$18)*C4/Assumptions!$B$21 -> 0.21758 | D6: =Assumptions!$B$18+(Assumptions!$E$13-Assumptions!$B$18)*D4/Assumptions!$B$21 -> 0.21646 | E6: =Assumptions!$B$18+(Assumptions!$E$13-Assumptions!$B$18)*E4/Assumptions!$B$21 -> 0.21534 | F6: =Assumptions!$B$18+(Assumptions!$E$13-Assumptions!$B$18)*F4/Assumptions!$B$21 -> 0.21422 | G6: =Assumptions!$B$18+(Assumptions!$E$13-Assumptions!$B$18)*G4/Assumptions!$B$21 -> 0.2131 | H6: =Assumptions!$B$18+(Assumptions!$E$13-Assumptions!$B$18)*H4/Assumptions!$B$21 -> 0.21198 | I6: =Assumptions!$B$18+(Assumptions!$E$13-Assumptions!$B$18)*I4/Assumptions!$B$21 -> 0.21086 | J6: =Assumptions!$B$18+(Assumptions!$E$13-Assumptions!$B$18)*J4/Assumptions!$B$21 -> 0.20974 | ... L6: =Assumptions!$B$18+(Assumptions!$E$13-Assumptions!$B$18)*L4/Assumptions!$B$21 -> 0.2075
A7: Revenue | B7: ='Yearly Model'!G2 -> 14708.824 | C7: ='Yearly Model'!H2 -> 14442.594 | D7: ='Yearly Model'!I2 -> 14250.347 | E7: ='Yearly Model'!J2 -> 14128.903 | F7: ='Yearly Model'!K2 -> 14076.155 | G7: ='Yearly Model'!L2 -> 14091.013 | H7: ='Yearly Model'!M2 -> 14173.367 | I7: ='Yearly Model'!N2 -> 14324.077 | ... L7: ='Yearly Model'!Q2 -> 15209.931
A8: Operating income | B8: ='Yearly Model'!G8 -> 3216.472 | C8: ='Yearly Model'!H8 -> 3142.4197 | D8: ='Yearly Model'!I8 -> 3084.6302 | E8: ='Yearly Model'!J8 -> 3042.5179 | F8: ='Yearly Model'!K8 -> 3015.3939 | G8: ='Yearly Model'!L8 -> 3002.7949 | H8: ='Yearly Model'!M8 -> 3004.4704 | I8: ='Yearly Model'!N8 -> 3020.3749 | ... L8: ='Yearly Model'!Q8 -> 3156.0606
A9: Tax on operating income | C9: =MAX(0,C8)*Assumptions!$E$14 -> 534.21134 | D9: =MAX(0,D8)*Assumptions!$E$14 -> 524.38713 | E9: =MAX(0,E8)*Assumptions!$E$14 -> 517.22804 | F9: =MAX(0,F8)*Assumptions!$E$14 -> 512.61696 | G9: =MAX(0,G8)*Assumptions!$E$14 -> 510.47513 | H9: =MAX(0,H8)*Assumptions!$E$14 -> 510.75996 | I9: =MAX(0,I8)*Assumptions!$E$14 -> 513.46374 | J9: =MAX(0,J8)*Assumptions!$E$14 -> 518.61312 | ... L9: =MAX(0,L8)*Assumptions!$E$14 -> 536.5303
A10: NOPAT | C10: =C8-C9 -> 2608.2083 | D10: =D8-D9 -> 2560.243 | E10: =E8-E9 -> 2525.2899 | F10: =F8-F9 -> 2502.7769 | G10: =G8-G9 -> 2492.3197 | H10: =H8-H9 -> 2493.7104 | I10: =I8-I9 -> 2506.9112 | J10: =J8-J9 -> 2532.0523 | ... L10: =L8-L9 -> 2619.5303
A11: Reinvestment | C11: =(C7-B7)*Assumptions!$E$15 -> -66.557429 | D11: =(D7-C7)*Assumptions!$E$15 -> -48.061744 | E11: =(E7-D7)*Assumptions!$E$15 -> -30.361157 | F11: =(F7-E7)*Assumptions!$E$15 -> -13.186976 | G11: =(G7-F7)*Assumptions!$E$15 -> 3.7145408 | H11: =(H7-G7)*Assumptions!$E$15 -> 20.588536 | I11: =(I7-H7)*Assumptions!$E$15 -> 37.677534 | J11: =(J7-I7)*Assumptions!$E$15 -> 55.227276 | ... L11: =(L7-K7)*Assumptions!$E$15 -> 92.743479
A12: Free cash flow | C12: =C10-C11 -> 2674.7658 | D12: =D10-D11 -> 2608.3048 | E12: =E10-E11 -> 2555.651 | F12: =F10-F11 -> 2515.9639 | G12: =G10-G11 -> 2488.6052 | H12: =H10-H11 -> 2473.1219 | I12: =I10-I11 -> 2469.2337 | J12: =J10-J11 -> 2476.825 | ... L12: =L10-L11 -> 2526.7868
A13: Year fraction | C13: =Assumptions!$B$22 -> 1 | D13: 1 | E13: 1 | F13: 1 | G13: 1 | H13: 1 | I13: 1 | J13: 1 | K13: 1 | L13: 1
A14: Discount time (mid-period) | C14: =C13/2 -> 0.5 | D14: =C14+C13/2+D13/2 -> 1.5 | E14: =D14+D13/2+E13/2 -> 2.5 | F14: =E14+E13/2+F13/2 -> 3.5 | G14: =F14+F13/2+G13/2 -> 4.5 | H14: =G14+G13/2+H13/2 -> 5.5 | I14: =H14+H13/2+I13/2 -> 6.5 | J14: =I14+I13/2+J13/2 -> 7.5 | K14: =J14+J13/2+K13/2 -> 8.5 | L14: =K14+K13/2+L13/2 -> 9.5
A15: Discount factor | C15: =1/(1+Assumptions!$E$10)^C14 -> 0.96003072 | D15: =1/(1+Assumptions!$E$10)^D14 -> 0.88482094 | E15: =1/(1+Assumptions!$E$10)^E14 -> 0.81550317 | F15: =1/(1+Assumptions!$E$10)^F14 -> 0.75161583 | G15: =1/(1+Assumptions!$E$10)^G14 -> 0.69273348 | H15: =1/(1+Assumptions!$E$10)^H14 -> 0.63846404 | I15: =1/(1+Assumptions!$E$10)^I14 -> 0.58844612 | J15: =1/(1+Assumptions!$E$10)^J14 -> 0.54234665 | ... L15: =1/(1+Assumptions!$E$10)^L14 -> 0.46069923
A16: PV of free cash flow | C16: =C12*C13*C15 -> 2567.8573 | D16: =D12*D13*D15 -> 2307.8827 | E16: =E12*E13*E15 -> 2084.1415 | F16: =F12*F13*F15 -> 1891.0383 | G16: =G12*G13*G15 -> 1723.9401 | H16: =H12*H13*H15 -> 1578.9994 | I16: =I12*I13*I15 -> 1453.011 | J16: =J12*J13*J15 -> 1343.2978 | ... L16: =L12*L13*L15 -> 1164.0887
A19: PV of forecast free cash flow | B19: =SUM(C16:L16) -> 17361.874
A20: Terminal free cash flow (year 11) | B20: =L10*(1+Assumptions!$E$11)-L7*Assumptions!$E$11*Assumptions!$E$15 -> 2589.9565
A21: Terminal value | B21: =B20/(Assumptions!$E$10-Assumptions!$E$11) -> 43165.941
A22: PV of terminal value | B22: =B21/(1+Assumptions!$E$10)^(L14+0.5) -> 19091.666
A23: Enterprise value | B23: =B19+B22 -> 36453.541
A24: Cash & investments | B24: =Main!C7 -> 1765.5923
A25: Debt | B25: =Main!C8 -> 11480.35
A26: Equity value | B26: =B23+B24-B25 -> 26738.783
A27: Shares (mm) | B27: =Main!C4 -> 4476.1768
A28: NPV / share | B28: =B26/B27 -> 5.973576
A29: Price | B29: =Main!C3 -> 10.17
A30: Upside | B30: =B28/B29-1 -> -0.41262772
A31: Terminal value, % of EV | B31: =IFERROR(B22/B23,0) -> 0.52372598
