Workbook

Sheet Main
B2: Harrow, Inc.
B3: Price | C3: =INDEX([1]Pharma!$F$1:$F$1000,MATCH("HROW",[1]Pharma!$B$1:$B$1000,0)) -> 28.07
B4: Shares | C4: 37.48785
B5: Market Cap. | C5: =C3*C4 -> 1052.2839
B7: Cash | C7: 83.889
B8: Debt | C8: 292.379
B9: Enterprise V. | C9: =C5-C7+C8 -> 1260.7739
B11: NPV / Share | C11: =NPV!B28 -> 5.009593
B12: Upside | C12: =IFERROR(C11/C3-1,"") -> -0.82153213
B13: Cash / Share | C13: =IFERROR((C7-C8)/C4,"") -> -5.5615353
B14: Scenario | C14: =Assumptions!C4 -> Base
B15: Model | C15: DCF

Sheet Yearly Model
B1: 1999 | C1: 2000 | D1: 2001 | E1: 2002 | F1: 2003 | G1: 2004 | H1: 2005 | I1: 2006 | J1: 2007 | K1: 2008 | L1: 2009 | M1: 2010 | N1: 2011 | O1: 2012 | P1: 2013 | Q1: 2014 | R1: 2015 | S1: 2016 | T1: 2017 | U1: 2018 | V1: 2019 | W1: 2020 | X1: 2021 | Y1: 2022 | Z1: 2023 | AA1: 2024 | AB1: 2025 | AC1: 2026 | AD1: 2027 | AE1: 2028 | AF1: 2029 | AG1: 2030 | AH1: 2031 | AI1: 2032 | AJ1: 2033 | AK1: 2034 | AL1: 2035
A2: Revenue | B2: 0 | C2: 0 | D2: 0 | E2: 0 | F2: 0 | G2: 0 | H2: 0 | I2: 0 | J2: 0 | K2: 0 | L2: 0 | M2: 0 | N2: 0 | O2: 0 | P2: 0.01 | Q2: 1.66 | R2: 9.716 | S2: 19.942 | T2: 26.774 | U2: 41.372 | V2: 51.165 | W2: 48.871 | X2: 72.476 | Y2: 88.595 | Z2: 130.193 | AA2: 199.614 | AB2: 272.303 | AC2: =AB2*(1+NPV!C5) -> 280.33594 | AD2: =AC2*(1+NPV!D5) -> 288.46568 | AE2: =AD2*(1+NPV!E5) -> 296.68695 | AF2: =AE2*(1+NPV!F5) -> 304.99419 | AG2: =AF2*(1+NPV!G5) -> 313.38153 | AH2: =AG2*(1+NPV!H5) -> 321.84283 | AI2: =AH2*(1+NPV!I5) -> 330.37166 | AJ2: =AI2*(1+NPV!J5) -> 338.96133 | ... AL2: =AK2*(1+NPV!L5) -> 356.29496
A3: Cost of Sales | B3: 0 | C3: 0 | D3: 0 | E3: 0 | F3: 0 | G3: 0 | H3: 0 | I3: 0 | J3: 0 | K3: 0 | L3: 0 | M3: 0 | N3: 0 | O3: 0 | P3: 0 | Q3: 0 | R3: 0 | S3: 0 | T3: 13.505 | U3: 16.521 | V3: 16.749 | W3: 14.463 | X3: 18.214 | Y3: 25.383 | Z3: 39.64 | AA3: 49.245 | AB3: 67.934 | AC3: =AC2*(1-Assumptions!$B$19) -> 69.943817 | AD3: =AD2*(1-Assumptions!$B$19) -> 71.972187 | AE3: =AE2*(1-Assumptions!$B$19) -> 74.023395 | AF3: =AF2*(1-Assumptions!$B$19) -> 76.09605 | AG3: =AG2*(1-Assumptions!$B$19) -> 78.188691 | AH3: =AH2*(1-Assumptions!$B$19) -> 80.299786 | AI3: =AI2*(1-Assumptions!$B$19) -> 82.42773 | AJ3: =AJ2*(1-Assumptions!$B$19) -> 84.570851 | ... AL3: =AL2*(1-Assumptions!$B$19) -> 88.895593
A4: Gross Margin | B4: =B2-B3 -> 0 | C4: =C2-C3 -> 0 | D4: =D2-D3 -> 0 | E4: =E2-E3 -> 0 | F4: =F2-F3 -> 0 | G4: =G2-G3 -> 0 | H4: =H2-H3 -> 0 | I4: =I2-I3 -> 0 | ... AL4: =AL2-AL3 -> 267.39937
A5: Research & Dev. | B5: 0 | C5: 0 | D5: 0 | E5: 0 | F5: 0 | G5: 0 | H5: 0 | I5: 0 | J5: 0 | K5: 0 | L5: 0 | M5: 0.195 | N5: 0.112 | O5: 1.299 | P5: 1.616 | Q5: 0.237 | R5: 0.332 | S5: 0.739 | T5: 0.413 | U5: 0.825 | V5: 2.083 | W5: 2.413 | X5: 11.084 | Y5: 3.05 | Z5: 6.652 | AA5: 12.23 | AB5: 20.94 | AC5: =AC7*Assumptions!$B$20 -> 24.959935 | AD5: =AD7*Assumptions!$B$20 -> 24.954416 | AE5: =AE7*Assumptions!$B$20 -> 24.915474 | AF5: =AF7*Assumptions!$B$20 -> 24.84196 | AG5: =AG7*Assumptions!$B$20 -> 24.73276 | AH5: =AH7*Assumptions!$B$20 -> 24.586797 | AI5: =AI7*Assumptions!$B$20 -> 24.403035 | AJ5: =AJ7*Assumptions!$B$20 -> 24.180484 | ... AL5: =AL7*Assumptions!$B$20 -> 23.615301
A6: SG&A & Other | B6: 0.204 | C6: 0.213 | D6: 0.208 | E6: 0.228 | F6: 0.207 | G6: 0.508 | H6: 0.54 | I6: 0.584 | J6: 4.285 | K6: 3.304 | L6: 4.554 | M6: 2.308 | N6: 0.828 | O6: 2.88 | P6: 6.081 | Q6: 11.57 | R6: 24.206 | S6: 35.085 | T6: 25.019 | U6: 29.243 | V6: 37.128 | W6: 31.61 | X6: 41.564 | Y6: 58.243 | Z6: 83.47 | AA6: 129.317 | AB6: 152.914 | AC6: =AC7-AC5 -> 182.34849 | AD6: =AD7-AD5 -> 182.30818 | AE6: =AE7-AE5 -> 182.02368 | AF6: =AF7-AF5 -> 181.48661 | AG6: =AG7-AG5 -> 180.68883 | AH6: =AH7-AH5 -> 179.62248 | AI6: =AI7-AI5 -> 178.27998 | AJ6: =AJ7-AJ5 -> 176.6541 | ... AL6: =AL7-AL5 -> 172.52508
A7: Operating Expense | B7: =SUM(B5:B6) -> 0.204 | C7: =SUM(C5:C6) -> 0.213 | D7: =SUM(D5:D6) -> 0.208 | E7: =SUM(E5:E6) -> 0.228 | F7: =SUM(F5:F6) -> 0.207 | G7: =SUM(G5:G6) -> 0.508 | H7: =SUM(H5:H6) -> 0.54 | I7: =SUM(I5:I6) -> 0.584 | ... AB7: =SUM(AB5:AB6) -> 173.854 | AC7: =AC4-AC2*NPV!C6 -> 207.30843 | AD7: =AD4-AD2*NPV!D6 -> 207.26259 | AE7: =AE4-AE2*NPV!E6 -> 206.93915 | AF7: =AF4-AF2*NPV!F6 -> 206.32857 | AG7: =AG4-AG2*NPV!G6 -> 205.42159 | AH7: =AH4-AH2*NPV!H6 -> 204.20927 | AI7: =AI4-AI2*NPV!I6 -> 202.68302 | AJ7: =AJ4-AJ2*NPV!J6 -> 200.83459 | ... AL7: =AL4-AL2*NPV!L6 -> 196.14038
A8: Operating Income | B8: =B4-B7 -> -0.204 | C8: =C4-C7 -> -0.213 | D8: =D4-D7 -> -0.208 | E8: =E4-E7 -> -0.228 | F8: =F4-F7 -> -0.207 | G8: =G4-G7 -> -0.508 | H8: =H4-H7 -> -0.54 | I8: =I4-I7 -> -0.584 | ... AL8: =AL4-AL7 -> 71.258992
A9: Interest & Other | B9: 0 | C9: 0 | D9: 0 | E9: 0 | F9: 0 | G9: 0 | H9: 0 | I9: 0 | J9: 0 | K9: 0 | L9: 0 | M9: -0.029 | N9: -0.015 | O9: -1.203 | P9: 0.044 | Q9: 0.032 | R9: -1.072 | S9: -3.316 | T9: -0.757 | U9: 19.842 | V9: 4.971 | W9: -3.738 | X9: -19.488 | Y9: -15.93 | Z9: -24.141 | AA9: -26.142 | AB9: -31.883 | AC9: 0 | AD9: 0 | AE9: 0 | AF9: 0 | AG9: 0 | AH9: 0 | AI9: 0 | AJ9: 0 | AK9: 0 | AL9: 0
A10: Pretax | B10: =B8+B9 -> -0.204 | C10: =C8+C9 -> -0.213 | D10: =D8+D9 -> -0.208 | E10: =E8+E9 -> -0.228 | F10: =F8+F9 -> -0.207 | G10: =G8+G9 -> -0.508 | H10: =H8+H9 -> -0.54 | I10: =I8+I9 -> -0.584 | ... AL10: =AL8+AL9 -> 71.258992
A11: Taxes | B11: 0 | C11: 0 | D11: 0 | E11: 0 | F11: 0 | G11: 0 | H11: 0 | I11: 0 | J11: 0 | K11: 0 | L11: 0 | M11: 0 | N11: 0 | O11: 0.002 | P11: 0 | Q11: 0.003 | R11: 0.005 | S11: -0.111 | T11: -0.935 | U11: 0 | V11: 0.008 | W11: 0.004 | X11: 0.133 | Y11: 0.075 | Z11: 0.701 | AA11: 0.161 | AB11: 3.771 | AC11: =MAX(0,AC10)*Assumptions!$E$14 -> 0.5242282 | AD11: =MAX(0,AD10)*Assumptions!$E$14 -> 1.5692533 | AE11: =MAX(0,AE10)*Assumptions!$E$14 -> 2.6731494 | AF11: =MAX(0,AF10)*Assumptions!$E$14 -> 3.8368269 | AG11: =MAX(0,AG10)*Assumptions!$E$14 -> 5.0611117 | AH11: =MAX(0,AH10)*Assumptions!$E$14 -> 6.3467406 | AI11: =MAX(0,AI10)*Assumptions!$E$14 -> 7.694356 | AJ11: =MAX(0,AJ10)*Assumptions!$E$14 -> 9.1045012 | ... AL11: =MAX(0,AL10)*Assumptions!$E$14 -> 12.114029
A12: Net Income | B12: -0.204 | C12: -0.213 | D12: -0.208 | E12: -0.228 | F12: -0.207 | G12: -0.508 | H12: -0.54 | I12: -0.584 | J12: -4.285 | K12: -3.304 | L12: -4.554 | M12: -2.531 | N12: -0.954 | O12: -5.384 | P12: -7.643 | Q12: -10.118 | R12: -15.899 | S12: -19.087 | T12: -11.985 | U12: 14.625 | V12: 0.168 | W12: -3.357 | X12: -18.007 | Y12: -14.086 | Z12: -24.411 | AA12: -17.481 | AB12: -5.139 | AC12: =AC10-AC11 -> 2.5594671 | AD12: =AD10-AD11 -> 7.6616485 | AE12: =AE10-AE11 -> 13.051259 | AF12: =AF10-AF11 -> 18.732743 | AG12: =AG10-AG11 -> 24.710133 | AH12: =AH10-AH11 -> 30.987028 | AI12: =AI10-AI11 -> 37.566562 | AJ12: =AJ10-AJ11 -> 44.451388 | ... AL12: =AL10-AL11 -> 59.144964
A13: Earnings per Share | B13: =IFERROR(B12/B14,0) -> 0 | C13: =IFERROR(C12/C14,0) -> 0 | D13: =IFERROR(D12/D14,0) -> 0 | E13: =IFERROR(E12/E14,0) -> 0 | F13: =IFERROR(F12/F14,0) -> 0 | G13: =IFERROR(G12/G14,0) -> 0 | H13: =IFERROR(H12/H14,0) -> 0 | I13: =IFERROR(I12/I14,0) -> 0 | ... AL13: =IFERROR(AL12/AL14,0) -> 1.5777102
A14: Shares | N14: 0.398 | O14: 4.494 | P14: 8.657 | Q14: 9.133 | R14: 9.576 | S14: 12.743 | T14: 20.028 | U14: 23.812 | V14: 26.466 | W14: 25.895 | X14: 26.757 | Y14: 27.461 | Z14: 32.617 | AA14: 35.651 | AB14: 36.76 | AC14: =Main!$C$4 -> 37.48785 | AD14: =Main!$C$4 -> 37.48785 | AE14: =Main!$C$4 -> 37.48785 | AF14: =Main!$C$4 -> 37.48785 | AG14: =Main!$C$4 -> 37.48785 | AH14: =Main!$C$4 -> 37.48785 | AI14: =Main!$C$4 -> 37.48785 | AJ14: =Main!$C$4 -> 37.48785 | ... AL14: =Main!$C$4 -> 37.48785
A16: Revenue Change | C16: =IFERROR(C2/B2-1,"") | D16: =IFERROR(D2/C2-1,"") | E16: =IFERROR(E2/D2-1,"") | F16: =IFERROR(F2/E2-1,"") | G16: =IFERROR(G2/F2-1,"") | H16: =IFERROR(H2/G2-1,"") | I16: =IFERROR(I2/H2-1,"") | J16: =IFERROR(J2/I2-1,"") | ... AL16: =IFERROR(AL2/AK2-1,"") -> 0.025
A17: Gross Margin | B17: =IFERROR(B4/B2,"") | C17: =IFERROR(C4/C2,"") | D17: =IFERROR(D4/D2,"") | E17: =IFERROR(E4/E2,"") | F17: =IFERROR(F4/F2,"") | G17: =IFERROR(G4/G2,"") | H17: =IFERROR(H4/H2,"") | I17: =IFERROR(I4/I2,"") | ... AL17: =IFERROR(AL4/AL2,"") -> 0.7505
A18: Operating Margin | B18: =IFERROR(B8/B2,"") | C18: =IFERROR(C8/C2,"") | D18: =IFERROR(D8/D2,"") | E18: =IFERROR(E8/E2,"") | F18: =IFERROR(F8/F2,"") | G18: =IFERROR(G8/G2,"") | H18: =IFERROR(H8/H2,"") | I18: =IFERROR(I8/I2,"") | ... AL18: =IFERROR(AL8/AL2,"") -> 0.2
A19: Actual / Estimate | B19: A | C19: A | D19: A | E19: A | F19: A | G19: A | H19: A | I19: A | J19: A | K19: A | L19: A | M19: A | N19: A | O19: A | P19: A | Q19: A | R19: A | S19: A | T19: A | U19: A | V19: A | W19: A | X19: A | Y19: A | Z19: A | AA19: A | AB19: A | AC19: E | AD19: E | AE19: E | AF19: E | AG19: E | AH19: E | AI19: E | AJ19: E | AK19: E | AL19: E

Sheet Quarterly Model

Sheet Assumptions
A1: Harrow, Inc.: basic DCF assumptions
A2: Blue = input, black = formula, green = link. $mm unless noted.
A4: Scenario (1 Bear, 2 Base, 3 Bull) | B4: 2 | C4: =CHOOSE($B$4,"Bear","Base","Bull") -> Base
A6: Discount rate override (blank = scenario)
A7: Terminal growth override (blank = scenario)
A9: Parameter | B9: Bear | C9: Base | D9: Bull | E9: Live
A10: Discount rate | B10: 0.12 | C10: 0.11 | D10: 0.1 | E10: =IF(ISNUMBER($B$6),$B$6,CHOOSE($B$4,B10,C10,D10)) -> 0.11
A11: Terminal growth | B11: 0.02 | C11: 0.025 | D11: 0.03 | E11: =IF(ISNUMBER($B$7),$B$7,CHOOSE($B$4,B11,C11,D11)) -> 0.025
A12: Revenue growth, first forecast year | B12: -0.0205 | C12: 0.0295 | D12: 0.0795 | E12: =CHOOSE($B$4,B12,C12,D12) -> 0.0295
A13: Operating margin, year 10 | B13: 0.15 | C13: 0.2 | D13: 0.25 | E13: =CHOOSE($B$4,B13,C13,D13) -> 0.2
A14: Tax rate on operating income | B14: 0.17 | C14: 0.17 | D14: 0.17 | E14: =CHOOSE($B$4,B14,C14,D14) -> 0.17
A15: Reinvestment, % of revenue increase | B15: 0.25 | C15: 0.25 | D15: 0.25 | E15: =CHOOSE($B$4,B15,C15,D15) -> 0.25
A17: Single inputs
A18: Starting operating margin (TTM) | B18: -0.01
A19: Gross margin (forecast) | B19: 0.7505
A20: R&D share of operating expense (forecast) | B20: 0.1204
A21: Forecast years | B21: 10
A22: First forecast year, fraction after balance sheet date | B22: 0.5041
A23: Balance sheet date | B23: 46203
A24: Reporting currency per USD (USD) | B24: 1
A25: Base revenue, FY2025 | B25: ='Yearly Model'!AB2 -> 272.303
A27: Scenario summary
A28: Scenario | B28: Enterprise value | C28: Equity value | D28: NPV / share | E28: Upside
A29: Live | B29: =NPV!B23 -> 396.28887 | C29: =NPV!B26 -> 187.79887 | D29: =NPV!B28 -> 5.009593 | E29: =NPV!B30 -> -0.82153213
A30: 1 | B30: 200.3353 | C30: -8.1547019 | D30: -0.2175292 | E30: -1.0077495
A31: 2 | B31: 396.28887 | C31: 187.79887 | D31: 5.009593 | E31: -0.82153213
A32: 3 | B32: 775.77709 | C32: 567.28709 | D32: 15.132559 | E32: -0.46089923
A35: NPV / share: discount rate (rows) x terminal growth (columns)
A36: =NPV!B28 -> 5.009593 | B36: 0.015 | C36: 0.02 | D36: 0.025 | E36: 0.03 | F36: 0.035
A37: 0.09 | B37: 7.3619872 | C37: 8.2188192 | D37: 9.2081963 | E37: 10.363267 | F37: 11.729234
A38: 0.1 | B38: 5.4686872 | C38: 6.0996558 | D38: 6.8153427 | E38: 7.6339118 | F38: 8.5791159
A39: 0.11 | B39: 3.9952586 | C39: 4.4740189 | D39: 5.009593 | E39: 5.6126416 | F39: 6.296668
A40: 0.12 | B40: 2.820137 | C40: 3.1921525 | D40: 3.6037402 | E40: 4.0615021 | F40: 4.5735936
A41: 0.13 | B41: 1.8641859 | C41: 2.1589101 | D41: 2.4820564 | E41: 2.8378935 | F41: 3.2315891

Sheet NPV
A1: Harrow, Inc.: free-cash-flow DCF ($mm)
A3: Fiscal year | B3: ='Yearly Model'!AB1 -> 2025 | C3: ='Yearly Model'!AC1 -> 2026 | D3: ='Yearly Model'!AD1 -> 2027 | E3: ='Yearly Model'!AE1 -> 2028 | F3: ='Yearly Model'!AF1 -> 2029 | G3: ='Yearly Model'!AG1 -> 2030 | H3: ='Yearly Model'!AH1 -> 2031 | I3: ='Yearly Model'!AI1 -> 2032 | ... L3: ='Yearly Model'!AL1 -> 2035
A4: Period | B4: Actual | C4: 1 | D4: 2 | E4: 3 | F4: 4 | G4: 5 | H4: 6 | I4: 7 | J4: 8 | K4: 9 | L4: 10
A5: Revenue growth | C5: =Assumptions!$E$12+(Assumptions!$E$11-Assumptions!$E$12)*(C4-1)/(Assumptions!$B$21-1) -> 0.0295 | D5: =Assumptions!$E$12+(Assumptions!$E$11-Assumptions!$E$12)*(D4-1)/(Assumptions!$B$21-1) -> 0.029 | E5: =Assumptions!$E$12+(Assumptions!$E$11-Assumptions!$E$12)*(E4-1)/(Assumptions!$B$21-1) -> 0.0285 | F5: =Assumptions!$E$12+(Assumptions!$E$11-Assumptions!$E$12)*(F4-1)/(Assumptions!$B$21-1) -> 0.028 | G5: =Assumptions!$E$12+(Assumptions!$E$11-Assumptions!$E$12)*(G4-1)/(Assumptions!$B$21-1) -> 0.0275 | H5: =Assumptions!$E$12+(Assumptions!$E$11-Assumptions!$E$12)*(H4-1)/(Assumptions!$B$21-1) -> 0.027 | I5: =Assumptions!$E$12+(Assumptions!$E$11-Assumptions!$E$12)*(I4-1)/(Assumptions!$B$21-1) -> 0.0265 | J5: =Assumptions!$E$12+(Assumptions!$E$11-Assumptions!$E$12)*(J4-1)/(Assumptions!$B$21-1) -> 0.026 | ... L5: =Assumptions!$E$12+(Assumptions!$E$11-Assumptions!$E$12)*(L4-1)/(Assumptions!$B$21-1) -> 0.025
A6: Operating margin | B6: =IFERROR(B8/B7,0) -> 0.11206267 | C6: =Assumptions!$B$18+(Assumptions!$E$13-Assumptions!$B$18)*C4/Assumptions!$B$21 -> 0.011 | D6: =Assumptions!$B$18+(Assumptions!$E$13-Assumptions!$B$18)*D4/Assumptions!$B$21 -> 0.032 | E6: =Assumptions!$B$18+(Assumptions!$E$13-Assumptions!$B$18)*E4/Assumptions!$B$21 -> 0.053 | F6: =Assumptions!$B$18+(Assumptions!$E$13-Assumptions!$B$18)*F4/Assumptions!$B$21 -> 0.074 | G6: =Assumptions!$B$18+(Assumptions!$E$13-Assumptions!$B$18)*G4/Assumptions!$B$21 -> 0.095 | H6: =Assumptions!$B$18+(Assumptions!$E$13-Assumptions!$B$18)*H4/Assumptions!$B$21 -> 0.116 | I6: =Assumptions!$B$18+(Assumptions!$E$13-Assumptions!$B$18)*I4/Assumptions!$B$21 -> 0.137 | J6: =Assumptions!$B$18+(Assumptions!$E$13-Assumptions!$B$18)*J4/Assumptions!$B$21 -> 0.158 | ... L6: =Assumptions!$B$18+(Assumptions!$E$13-Assumptions!$B$18)*L4/Assumptions!$B$21 -> 0.2
A7: Revenue | B7: ='Yearly Model'!AB2 -> 272.303 | C7: ='Yearly Model'!AC2 -> 280.33594 | D7: ='Yearly Model'!AD2 -> 288.46568 | E7: ='Yearly Model'!AE2 -> 296.68695 | F7: ='Yearly Model'!AF2 -> 304.99419 | G7: ='Yearly Model'!AG2 -> 313.38153 | H7: ='Yearly Model'!AH2 -> 321.84283 | I7: ='Yearly Model'!AI2 -> 330.37166 | ... L7: ='Yearly Model'!AL2 -> 356.29496
A8: Operating income | B8: ='Yearly Model'!AB8 -> 30.515 | C8: ='Yearly Model'!AC8 -> 3.0836953 | D8: ='Yearly Model'!AD8 -> 9.2309018 | E8: ='Yearly Model'!AE8 -> 15.724408 | F8: ='Yearly Model'!AF8 -> 22.56957 | G8: ='Yearly Model'!AG8 -> 29.771245 | H8: ='Yearly Model'!AH8 -> 37.333768 | I8: ='Yearly Model'!AI8 -> 45.260918 | ... L8: ='Yearly Model'!AL8 -> 71.258992
A9: Tax on operating income | C9: =MAX(0,C8)*Assumptions!$E$14 -> 0.5242282 | D9: =MAX(0,D8)*Assumptions!$E$14 -> 1.5692533 | E9: =MAX(0,E8)*Assumptions!$E$14 -> 2.6731494 | F9: =MAX(0,F8)*Assumptions!$E$14 -> 3.8368269 | G9: =MAX(0,G8)*Assumptions!$E$14 -> 5.0611117 | H9: =MAX(0,H8)*Assumptions!$E$14 -> 6.3467406 | I9: =MAX(0,I8)*Assumptions!$E$14 -> 7.694356 | J9: =MAX(0,J8)*Assumptions!$E$14 -> 9.1045012 | ... L9: =MAX(0,L8)*Assumptions!$E$14 -> 12.114029
A10: NOPAT | C10: =C8-C9 -> 2.5594671 | D10: =D8-D9 -> 7.6616485 | E10: =E8-E9 -> 13.051259 | F10: =F8-F9 -> 18.732743 | G10: =G8-G9 -> 24.710133 | H10: =H8-H9 -> 30.987028 | I10: =I8-I9 -> 37.566562 | J10: =J8-J9 -> 44.451388 | ... L10: =L8-L9 -> 59.144964
A11: Reinvestment | C11: =(C7-B7)*Assumptions!$E$15 -> 2.0082346 | D11: =(D7-C7)*Assumptions!$E$15 -> 2.0324356 | E11: =(E7-D7)*Assumptions!$E$15 -> 2.055318 | F11: =(F7-E7)*Assumptions!$E$15 -> 2.0768087 | G11: =(G7-F7)*Assumptions!$E$15 -> 2.096835 | H11: =(H7-G7)*Assumptions!$E$15 -> 2.1153253 | I11: =(I7-H7)*Assumptions!$E$15 -> 2.1322087 | J11: =(J7-I7)*Assumptions!$E$15 -> 2.1474158 | ... L11: =(L7-K7)*Assumptions!$E$15 -> 2.1725303
A12: Free cash flow | C12: =C10-C11 -> 0.55123249 | D12: =D10-D11 -> 5.6292129 | E12: =E10-E11 -> 10.995941 | F12: =F10-F11 -> 16.655934 | G12: =G10-G11 -> 22.613298 | H12: =H10-H11 -> 28.871702 | I12: =I10-I11 -> 35.434353 | J12: =J10-J11 -> 42.303973 | ... L12: =L10-L11 -> 56.972433
A13: Year fraction | C13: =Assumptions!$B$22 -> 0.5041 | D13: 1 | E13: 1 | F13: 1 | G13: 1 | H13: 1 | I13: 1 | J13: 1 | K13: 1 | L13: 1
A14: Discount time (mid-period) | C14: =C13/2 -> 0.25205 | D14: =C14+C13/2+D13/2 -> 1.0041 | E14: =D14+D13/2+E13/2 -> 2.0041 | F14: =E14+E13/2+F13/2 -> 3.0041 | G14: =F14+F13/2+G13/2 -> 4.0041 | H14: =G14+G13/2+H13/2 -> 5.0041 | I14: =H14+H13/2+I13/2 -> 6.0041 | J14: =I14+I13/2+J13/2 -> 7.0041 | K14: =J14+J13/2+K13/2 -> 8.0041 | L14: =K14+K13/2+L13/2 -> 9.0041
A15: Discount factor | C15: =1/(1+Assumptions!$E$10)^C14 -> 0.97403899 | D15: =1/(1+Assumptions!$E$10)^D14 -> 0.90051551 | E15: =1/(1+Assumptions!$E$10)^E14 -> 0.81127523 | F15: =1/(1+Assumptions!$E$10)^F14 -> 0.73087859 | G15: =1/(1+Assumptions!$E$10)^G14 -> 0.65844918 | H15: =1/(1+Assumptions!$E$10)^H14 -> 0.59319746 | I15: =1/(1+Assumptions!$E$10)^I14 -> 0.53441213 | J15: =1/(1+Assumptions!$E$10)^J14 -> 0.48145236 | ... L15: =1/(1+Assumptions!$E$10)^L14 -> 0.39075754
A16: PV of free cash flow | C16: =C12*C13*C15 -> 0.27066235 | D16: =D12*D13*D15 -> 5.0691935 | E16: =E12*E13*E15 -> 8.9207347 | F16: =F12*F13*F15 -> 12.173466 | G16: =G12*G13*G15 -> 14.889708 | H16: =H12*H13*H15 -> 17.12662 | I16: =I12*I13*I15 -> 18.936548 | J16: =J12*J13*J15 -> 20.367348 | ... L16: =L12*L13*L15 -> 22.262408
A19: PV of forecast free cash flow | B19: =SUM(C16:L16) -> 141.47939
A20: Terminal free cash flow (year 11) | B20: =L10*(1+Assumptions!$E$11)-L7*Assumptions!$E$11*Assumptions!$E$15 -> 58.396744
A21: Terminal value | B21: =B20/(Assumptions!$E$10-Assumptions!$E$11) -> 687.02052
A22: PV of terminal value | B22: =B21/(1+Assumptions!$E$10)^(L14+0.5) -> 254.80948
A23: Enterprise value | B23: =B19+B22 -> 396.28887
A24: Cash & investments | B24: =Main!C7 -> 83.889
A25: Debt | B25: =Main!C8 -> 292.379
A26: Equity value | B26: =B23+B24-B25 -> 187.79887
A27: Shares (mm) | B27: =Main!C4 -> 37.48785
A28: NPV / share | B28: =B26/B27 -> 5.009593
A29: Price | B29: =Main!C3 -> 28.07
A30: Upside | B30: =B28/B29-1 -> -0.82153213
A31: Terminal value, % of EV | B31: =IFERROR(B22/B23,0) -> 0.64298925
