Workbook

Sheet Main
B2: Innoviva, Inc.
B3: Price | C3: =INDEX([1]Pharma!$F$1:$F$1000,MATCH("INVA",[1]Pharma!$B$1:$B$1000,0)) -> 21.28
B4: Shares | C4: 72.245485
B5: Market Cap. | C5: =C3*C4 -> 1537.3839
B7: Cash | C7: 570.388
B8: Debt | C8: 258.454
B9: Enterprise V. | C9: =C5-C7+C8 -> 1225.4499
B11: NPV / Share | C11: =NPV!B28 -> 40.280657
B12: Upside | C12: =IFERROR(C11/C3-1,"") -> 0.89288802
B13: Cash / Share | C13: =IFERROR((C7-C8)/C4,"") -> 4.3176954
B14: Scenario | C14: =Assumptions!C4 -> Base
B15: Model | C15: DCF

Sheet Yearly Model
B1: 2009 | C1: 2010 | D1: 2011 | E1: 2012 | F1: 2013 | G1: 2014 | H1: 2015 | I1: 2016 | J1: 2017 | K1: 2018 | L1: 2019 | M1: 2020 | N1: 2021 | O1: 2022 | P1: 2023 | Q1: 2024 | R1: 2025 | S1: 2026 | T1: 2027 | U1: 2028 | V1: 2029 | W1: 2030 | X1: 2031 | Y1: 2032 | Z1: 2033 | AA1: 2034 | AB1: 2035
A2: Revenue | B2: 24.374 | C2: 24.223 | D2: 24.512 | E2: 5.613 | F2: 4.532 | G2: 8.433 | H2: 53.949 | I2: 133.569 | J2: 217.217 | K2: 261.004 | L2: 261.016 | M2: 336.794 | N2: 391.866 | O2: 331.339 | P2: 310.463 | Q2: 358.711 | R2: 411.328 | S2: =R2*(1+NPV!C5) -> 473.76759 | T2: =S2*(1+NPV!D5) -> 539.01065 | U2: =T2*(1+NPV!E5) -> 605.64435 | V2: =U2*(1+NPV!F5) -> 671.98259 | W2: =V2*(1+NPV!G5) -> 736.1196 | X2: =W2*(1+NPV!H5) -> 796.00701 | Y2: =X2*(1+NPV!I5) -> 849.55175 | Z2: =Y2*(1+NPV!J5) -> 894.72903 | ... AB2: =AA2*(1+NPV!L5) -> 952.94556
A3: Cost of Sales | B3: 0 | C3: 0 | D3: 0 | E3: 0 | F3: 0 | G3: 0 | H3: 0 | I3: 0 | J3: 0 | K3: 0 | L3: 0 | M3: 0 | N3: 0 | O3: 0 | P3: 0 | Q3: 0 | R3: 0 | S3: =S2*(1-Assumptions!$B$19) -> 0 | T3: =T2*(1-Assumptions!$B$19) -> 0 | U3: =U2*(1-Assumptions!$B$19) -> 0 | V3: =V2*(1-Assumptions!$B$19) -> 0 | W3: =W2*(1-Assumptions!$B$19) -> 0 | X3: =X2*(1-Assumptions!$B$19) -> 0 | Y3: =Y2*(1-Assumptions!$B$19) -> 0 | Z3: =Z2*(1-Assumptions!$B$19) -> 0 | ... AB3: =AB2*(1-Assumptions!$B$19) -> 0
A4: Gross Margin | B4: =B2-B3 -> 24.374 | C4: =C2-C3 -> 24.223 | D4: =D2-D3 -> 24.512 | E4: =E2-E3 -> 5.613 | F4: =F2-F3 -> 4.532 | G4: =G2-G3 -> 8.433 | H4: =H2-H3 -> 53.949 | I4: =I2-I3 -> 133.569 | ... AB4: =AB2-AB3 -> 952.94556
A5: Research & Dev. | B5: 77.524 | C5: 75.07 | D5: 103.568 | E5: 8.153 | F5: 9.038 | G5: 7.498 | H5: 2.619 | I5: 1.393 | J5: 1.355 | K5: 0 | L5: 0 | M5: 1.788 | N5: 0.576 | O5: 41.432 | P5: 33.922 | Q5: 13.654 | R5: 30.604 | S5: =S7*Assumptions!$B$20 -> 36.836876 | T5: =T7*Assumptions!$B$20 -> 41.814454 | U5: =U7*Assumptions!$B$20 -> 46.876603 | V5: =V7*Assumptions!$B$20 -> 51.892383 | W5: =W7*Assumptions!$B$20 -> 56.715115 | X5: =X7*Assumptions!$B$20 -> 61.188512 | Y5: =Y7*Assumptions!$B$20 -> 65.154302 | Z5: =Z7*Assumptions!$B$20 -> 68.460922 | ... AB5: =AB7*Assumptions!$B$20 -> 72.578545
A6: SG&A & Other | B6: 28.211 | C6: 27.476 | D6: 30.681 | E6: 22.606 | F6: 24.289 | G6: 34.864 | H6: 19.75 | I6: 23.188 | J6: 32.258 | K6: 22.753 | L6: 14.656 | M6: 13.883 | N6: 16.187 | O6: 2.958 | P6: 162.656 | Q6: 178.19 | R6: 216.979 | S6: =S7-S5 -> 261.1961 | T6: =T7-T5 -> 296.49019 | U6: =U7-U5 -> 332.38394 | V6: =V7-V5 -> 367.9489 | W6: =W7-W5 -> 402.14504 | X6: =X7-X5 -> 433.86417 | Y6: =Y7-Y5 -> 461.98406 | Z6: =Z7-Z5 -> 485.43003 | ... AB6: =AB7-AB5 -> 514.62651
A7: Operating Expense | B7: =SUM(B5:B6) -> 105.735 | C7: =SUM(C5:C6) -> 102.546 | D7: =SUM(D5:D6) -> 134.249 | E7: =SUM(E5:E6) -> 30.759 | F7: =SUM(F5:F6) -> 33.327 | G7: =SUM(G5:G6) -> 42.362 | H7: =SUM(H5:H6) -> 22.369 | I7: =SUM(I5:I6) -> 24.581 | ... R7: =SUM(R5:R6) -> 247.583 | S7: =S4-S2*NPV!C6 -> 298.03298 | T7: =T4-T2*NPV!D6 -> 338.30465 | U7: =U4-U2*NPV!E6 -> 379.26055 | V7: =V4-V2*NPV!F6 -> 419.84128 | W7: =W4-W2*NPV!G6 -> 458.86015 | X7: =X4-X2*NPV!H6 -> 495.05268 | Y7: =Y4-Y2*NPV!I6 -> 527.13837 | Z7: =Z4-Z2*NPV!J6 -> 553.89095 | ... AB7: =AB4-AB2*NPV!L6 -> 587.20506
A8: Operating Income | B8: =B4-B7 -> -81.361 | C8: =C4-C7 -> -78.323 | D8: =D4-D7 -> -109.737 | E8: =E4-E7 -> -25.146 | F8: =F4-F7 -> -28.795 | G8: =G4-G7 -> -33.929 | H8: =H4-H7 -> 31.58 | I8: =I4-I7 -> 108.988 | ... AB8: =AB4-AB7 -> 365.74051
A9: Interest & Other | B9: -3.941 | C9: -5.539 | D9: -5.607 | E9: 6.604 | F9: -141.906 | G9: -134.535 | H9: -50.34 | I9: -49.357 | J9: -49.457 | K9: -39.268 | L9: -47.17 | M9: -36.29 | N9: -32.81 | O9: -6.341 | P9: 80.213 | Q9: -129.479 | R9: 163.117 | S9: 0 | T9: 0 | U9: 0 | V9: 0 | W9: 0 | X9: 0 | Y9: 0 | Z9: 0 | AA9: 0 | AB9: 0
A10: Pretax | B10: =B8+B9 -> -85.302 | C10: =C8+C9 -> -83.862 | D10: =D8+D9 -> -115.344 | E10: =E8+E9 -> -18.542 | F10: =F8+F9 -> -170.701 | G10: =G8+G9 -> -168.464 | H10: =H8+H9 -> -18.76 | I10: =I8+I9 -> 59.631 | ... AB10: =AB8+AB9 -> 365.74051
A11: Taxes | B11: 0 | C11: 0 | D11: 0 | E11: 0 | F11: 0 | G11: 0 | H11: 0 | I11: 0.095 | J11: 0.004 | K11: -196.073 | L11: 41.902 | M11: 60.431 | N11: 76.439 | O11: 66.687 | P11: 14.376 | Q11: 13.996 | R11: 55.697 | S11: =MAX(0,S10)*Assumptions!$E$14 -> 29.874884 | T11: =MAX(0,T10)*Assumptions!$E$14 -> 34.120021 | U11: =MAX(0,U10)*Assumptions!$E$14 -> 38.485246 | V11: =MAX(0,V10)*Assumptions!$E$14 -> 42.864022 | W11: =MAX(0,W10)*Assumptions!$E$14 -> 47.134106 | X11: =MAX(0,X10)*Assumptions!$E$14 -> 51.162236 | Y11: =MAX(0,Y10)*Assumptions!$E$14 -> 54.810276 | Z11: =MAX(0,Z10)*Assumptions!$E$14 -> 57.942473 | ... AB11: =MAX(0,AB10)*Assumptions!$E$14 -> 62.175886
A12: Net Income | B12: -85.302 | C12: -83.862 | D12: -115.344 | E12: -18.542 | F12: -170.701 | G12: -168.464 | H12: -18.76 | I12: 59.536 | J12: 134.143 | K12: 395.056 | L12: 157.288 | M12: 224.402 | N12: 265.854 | O12: 213.921 | P12: 179.722 | Q12: 23.392 | R12: 271.165 | S12: =S10-S11 -> 145.85973 | T12: =T10-T11 -> 166.58599 | U12: =U10-U11 -> 187.89855 | V12: =V10-V11 -> 209.27729 | W12: =W10-W11 -> 230.12534 | X12: =X10-X11 -> 249.7921 | Y12: =Y10-Y11 -> 267.60311 | Z12: =Z10-Z11 -> 282.8956 | ... AB12: =AB10-AB11 -> 303.56462
A13: Earnings per Share | B13: =IFERROR(B12/B14,0) -> -1.35342 | C13: =IFERROR(C12/C14,0) -> -1.1636187 | D13: =IFERROR(D12/D14,0) -> -1.4057598 | E13: =IFERROR(E12/E14,0) -> -0.2039622 | F13: =IFERROR(F12/F14,0) -> -1.6665951 | G13: =IFERROR(G12/G14,0) -> -1.5033509 | H13: =IFERROR(H12/H14,0) -> -0.16260444 | I13: =IFERROR(I12/I14,0) -> 0.48311735 | ... AB13: =IFERROR(AB12/AB14,0) -> 4.201849
A14: Shares | B14: 63.027 | C14: 72.07 | D14: 82.051 | E14: 90.909 | F14: 102.425 | G14: 112.059 | H14: 115.372 | I14: 123.233 | J14: 119.866 | K14: 113.408 | L14: 113.409 | M14: 113.554 | N14: 94.31 | O14: 95.248 | P14: 86.876 | Q14: 74.187 | R14: 84.76 | S14: =Main!$C$4 -> 72.245485 | T14: =Main!$C$4 -> 72.245485 | U14: =Main!$C$4 -> 72.245485 | V14: =Main!$C$4 -> 72.245485 | W14: =Main!$C$4 -> 72.245485 | X14: =Main!$C$4 -> 72.245485 | Y14: =Main!$C$4 -> 72.245485 | Z14: =Main!$C$4 -> 72.245485 | ... AB14: =Main!$C$4 -> 72.245485
A16: Revenue Change | C16: =IFERROR(C2/B2-1,"") -> -0.006195126 | D16: =IFERROR(D2/C2-1,"") -> 0.01193081 | E16: =IFERROR(E2/D2-1,"") -> -0.77101012 | F16: =IFERROR(F2/E2-1,"") -> -0.19258863 | G16: =IFERROR(G2/F2-1,"") -> 0.86076787 | H16: =IFERROR(H2/G2-1,"") -> 5.3973675 | I16: =IFERROR(I2/H2-1,"") -> 1.4758383 | J16: =IFERROR(J2/I2-1,"") -> 0.6262531 | ... AB16: =IFERROR(AB2/AA2-1,"") -> 0.025
A17: Gross Margin | B17: =IFERROR(B4/B2,"") -> 1 | C17: =IFERROR(C4/C2,"") -> 1 | D17: =IFERROR(D4/D2,"") -> 1 | E17: =IFERROR(E4/E2,"") -> 1 | F17: =IFERROR(F4/F2,"") -> 1 | G17: =IFERROR(G4/G2,"") -> 1 | H17: =IFERROR(H4/H2,"") -> 1 | I17: =IFERROR(I4/I2,"") -> 1 | ... AB17: =IFERROR(AB4/AB2,"") -> 1
A18: Operating Margin | B18: =IFERROR(B8/B2,"") -> -3.3380241 | C18: =IFERROR(C8/C2,"") -> -3.2334145 | D18: =IFERROR(D8/D2,"") -> -4.4768685 | E18: =IFERROR(E8/E2,"") -> -4.4799572 | F18: =IFERROR(F8/F2,"") -> -6.353707 | G18: =IFERROR(G8/G2,"") -> -4.0233606 | H18: =IFERROR(H8/H2,"") -> 0.58536766 | I18: =IFERROR(I8/I2,"") -> 0.81596778 | ... AB18: =IFERROR(AB8/AB2,"") -> 0.3838
A19: Actual / Estimate | B19: A | C19: A | D19: A | E19: A | F19: A | G19: A | H19: A | I19: A | J19: A | K19: A | L19: A | M19: A | N19: A | O19: A | P19: A | Q19: A | R19: A | S19: E | T19: E | U19: E | V19: E | W19: E | X19: E | Y19: E | Z19: E | AA19: E | AB19: E

Sheet Quarterly Model

Sheet Assumptions
A1: Innoviva, Inc.: basic DCF assumptions
A2: Blue = input, black = formula, green = link. $mm unless noted.
A4: Scenario (1 Bear, 2 Base, 3 Bull) | B4: 2 | C4: =CHOOSE($B$4,"Bear","Base","Bull") -> Base
A6: Discount rate override (blank = scenario)
A7: Terminal growth override (blank = scenario)
A9: Parameter | B9: Bear | C9: Base | D9: Bull | E9: Live
A10: Discount rate | B10: 0.12 | C10: 0.11 | D10: 0.1 | E10: =IF(ISNUMBER($B$6),$B$6,CHOOSE($B$4,B10,C10,D10)) -> 0.11
A11: Terminal growth | B11: 0.02 | C11: 0.025 | D11: 0.03 | E11: =IF(ISNUMBER($B$7),$B$7,CHOOSE($B$4,B11,C11,D11)) -> 0.025
A12: Revenue growth, first forecast year | B12: 0.1018 | C12: 0.1518 | D12: 0.2018 | E12: =CHOOSE($B$4,B12,C12,D12) -> 0.1518
A13: Operating margin, year 10 | B13: 0.3338 | C13: 0.3838 | D13: 0.4338 | E13: =CHOOSE($B$4,B13,C13,D13) -> 0.3838
A14: Tax rate on operating income | B14: 0.17 | C14: 0.17 | D14: 0.17 | E14: =CHOOSE($B$4,B14,C14,D14) -> 0.17
A15: Reinvestment, % of revenue increase | B15: 0.25 | C15: 0.25 | D15: 0.25 | E15: =CHOOSE($B$4,B15,C15,D15) -> 0.25
A17: Single inputs
A18: Starting operating margin (TTM) | B18: 0.3695
A19: Gross margin (forecast) | B19: 1
A20: R&D share of operating expense (forecast) | B20: 0.1236
A21: Forecast years | B21: 10
A22: First forecast year, fraction after balance sheet date | B22: 0.5041
A23: Balance sheet date | B23: 46203
A24: Reporting currency per USD (USD) | B24: 1
A25: Base revenue, FY2025 | B25: ='Yearly Model'!R2 -> 411.328
A27: Scenario summary
A28: Scenario | B28: Enterprise value | C28: Equity value | D28: NPV / share | E28: Upside
A29: Live | B29: =NPV!B23 -> 2598.1616 | C29: =NPV!B26 -> 2910.0956 | D29: =NPV!B28 -> 40.280657 | E29: =NPV!B30 -> 0.89288802
A30: 1 | B30: 1662.9219 | C30: 1974.8559 | D30: 27.335354 | E30: 0.2845561
A31: 2 | B31: 2598.1616 | C31: 2910.0956 | D31: 40.280657 | E31: 0.89288802
A32: 3 | B32: 4229.9266 | C32: 4541.8606 | D32: 62.86705 | E32: 1.9542787
A35: NPV / share: discount rate (rows) x terminal growth (columns)
A36: =NPV!B28 -> 40.280657 | B36: 0.015 | C36: 0.02 | D36: 0.025 | E36: 0.03 | F36: 0.035
A37: 0.09 | B37: 46.787838 | C37: 49.241316 | D37: 52.06829 | E37: 55.362089 | F37: 59.249983
A38: 0.1 | B38: 41.479942 | C38: 43.306569 | D38: 45.373437 | E38: 47.731989 | F38: 50.4495
A39: 0.11 | B39: 37.314014 | C39: 38.716257 | D39: 40.280657 | E39: 42.037589 | F39: 44.025527
A40: 0.12 | B40: 33.961627 | C40: 35.064786 | D40: 36.281644 | E40: 37.631126 | F40: 39.136609
A41: 0.13 | B41: 31.208812 | C41: 32.094286 | D41: 33.061981 | E41: 34.124209 | F41: 35.295873

Sheet NPV
A1: Innoviva, Inc.: free-cash-flow DCF ($mm)
A3: Fiscal year | B3: ='Yearly Model'!R1 -> 2025 | C3: ='Yearly Model'!S1 -> 2026 | D3: ='Yearly Model'!T1 -> 2027 | E3: ='Yearly Model'!U1 -> 2028 | F3: ='Yearly Model'!V1 -> 2029 | G3: ='Yearly Model'!W1 -> 2030 | H3: ='Yearly Model'!X1 -> 2031 | I3: ='Yearly Model'!Y1 -> 2032 | ... L3: ='Yearly Model'!AB1 -> 2035
A4: Period | B4: Actual | C4: 1 | D4: 2 | E4: 3 | F4: 4 | G4: 5 | H4: 6 | I4: 7 | J4: 8 | K4: 9 | L4: 10
A5: Revenue growth | C5: =Assumptions!$E$12+(Assumptions!$E$11-Assumptions!$E$12)*(C4-1)/(Assumptions!$B$21-1) -> 0.1518 | D5: =Assumptions!$E$12+(Assumptions!$E$11-Assumptions!$E$12)*(D4-1)/(Assumptions!$B$21-1) -> 0.13771111 | E5: =Assumptions!$E$12+(Assumptions!$E$11-Assumptions!$E$12)*(E4-1)/(Assumptions!$B$21-1) -> 0.12362222 | F5: =Assumptions!$E$12+(Assumptions!$E$11-Assumptions!$E$12)*(F4-1)/(Assumptions!$B$21-1) -> 0.10953333 | G5: =Assumptions!$E$12+(Assumptions!$E$11-Assumptions!$E$12)*(G4-1)/(Assumptions!$B$21-1) -> 0.095444444 | H5: =Assumptions!$E$12+(Assumptions!$E$11-Assumptions!$E$12)*(H4-1)/(Assumptions!$B$21-1) -> 0.081355556 | I5: =Assumptions!$E$12+(Assumptions!$E$11-Assumptions!$E$12)*(I4-1)/(Assumptions!$B$21-1) -> 0.067266667 | J5: =Assumptions!$E$12+(Assumptions!$E$11-Assumptions!$E$12)*(J4-1)/(Assumptions!$B$21-1) -> 0.053177778 | ... L5: =Assumptions!$E$12+(Assumptions!$E$11-Assumptions!$E$12)*(L4-1)/(Assumptions!$B$21-1) -> 0.025
A6: Operating margin | B6: =IFERROR(B8/B7,0) -> 0.39808863 | C6: =Assumptions!$B$18+(Assumptions!$E$13-Assumptions!$B$18)*C4/Assumptions!$B$21 -> 0.37093 | D6: =Assumptions!$B$18+(Assumptions!$E$13-Assumptions!$B$18)*D4/Assumptions!$B$21 -> 0.37236 | E6: =Assumptions!$B$18+(Assumptions!$E$13-Assumptions!$B$18)*E4/Assumptions!$B$21 -> 0.37379 | F6: =Assumptions!$B$18+(Assumptions!$E$13-Assumptions!$B$18)*F4/Assumptions!$B$21 -> 0.37522 | G6: =Assumptions!$B$18+(Assumptions!$E$13-Assumptions!$B$18)*G4/Assumptions!$B$21 -> 0.37665 | H6: =Assumptions!$B$18+(Assumptions!$E$13-Assumptions!$B$18)*H4/Assumptions!$B$21 -> 0.37808 | I6: =Assumptions!$B$18+(Assumptions!$E$13-Assumptions!$B$18)*I4/Assumptions!$B$21 -> 0.37951 | J6: =Assumptions!$B$18+(Assumptions!$E$13-Assumptions!$B$18)*J4/Assumptions!$B$21 -> 0.38094 | ... L6: =Assumptions!$B$18+(Assumptions!$E$13-Assumptions!$B$18)*L4/Assumptions!$B$21 -> 0.3838
A7: Revenue | B7: ='Yearly Model'!R2 -> 411.328 | C7: ='Yearly Model'!S2 -> 473.76759 | D7: ='Yearly Model'!T2 -> 539.01065 | E7: ='Yearly Model'!U2 -> 605.64435 | F7: ='Yearly Model'!V2 -> 671.98259 | G7: ='Yearly Model'!W2 -> 736.1196 | H7: ='Yearly Model'!X2 -> 796.00701 | I7: ='Yearly Model'!Y2 -> 849.55175 | ... L7: ='Yearly Model'!AB2 -> 952.94556
A8: Operating income | B8: ='Yearly Model'!R8 -> 163.745 | C8: ='Yearly Model'!S8 -> 175.73461 | D8: ='Yearly Model'!T8 -> 200.70601 | E8: ='Yearly Model'!U8 -> 226.3838 | F8: ='Yearly Model'!V8 -> 252.14131 | G8: ='Yearly Model'!W8 -> 277.25945 | H8: ='Yearly Model'!X8 -> 300.95433 | I8: ='Yearly Model'!Y8 -> 322.41339 | ... L8: ='Yearly Model'!AB8 -> 365.74051
A9: Tax on operating income | C9: =MAX(0,C8)*Assumptions!$E$14 -> 29.874884 | D9: =MAX(0,D8)*Assumptions!$E$14 -> 34.120021 | E9: =MAX(0,E8)*Assumptions!$E$14 -> 38.485246 | F9: =MAX(0,F8)*Assumptions!$E$14 -> 42.864022 | G9: =MAX(0,G8)*Assumptions!$E$14 -> 47.134106 | H9: =MAX(0,H8)*Assumptions!$E$14 -> 51.162236 | I9: =MAX(0,I8)*Assumptions!$E$14 -> 54.810276 | J9: =MAX(0,J8)*Assumptions!$E$14 -> 57.942473 | ... L9: =MAX(0,L8)*Assumptions!$E$14 -> 62.175886
A10: NOPAT | C10: =C8-C9 -> 145.85973 | D10: =D8-D9 -> 166.58599 | E10: =E8-E9 -> 187.89855 | F10: =F8-F9 -> 209.27729 | G10: =G8-G9 -> 230.12534 | H10: =H8-H9 -> 249.7921 | I10: =I8-I9 -> 267.60311 | J10: =J8-J9 -> 282.8956 | ... L10: =L8-L9 -> 303.56462
A11: Reinvestment | C11: =(C7-B7)*Assumptions!$E$15 -> 15.609898 | D11: =(D7-C7)*Assumptions!$E$15 -> 16.310765 | E11: =(E7-D7)*Assumptions!$E$15 -> 16.658424 | F11: =(F7-E7)*Assumptions!$E$15 -> 16.584561 | G11: =(G7-F7)*Assumptions!$E$15 -> 16.034251 | H11: =(H7-G7)*Assumptions!$E$15 -> 14.971855 | I11: =(I7-H7)*Assumptions!$E$15 -> 13.386185 | J11: =(J7-I7)*Assumptions!$E$15 -> 11.294319 | ... L11: =(L7-K7)*Assumptions!$E$15 -> 5.8106437
A12: Free cash flow | C12: =C10-C11 -> 130.24983 | D12: =D10-D11 -> 150.27522 | E12: =E10-E11 -> 171.24013 | F12: =F10-F11 -> 192.69272 | G12: =G10-G11 -> 214.09109 | H12: =H10-H11 -> 234.82024 | I12: =I10-I11 -> 254.21693 | J12: =J10-J11 -> 271.60128 | ... L12: =L10-L11 -> 297.75398
A13: Year fraction | C13: =Assumptions!$B$22 -> 0.5041 | D13: 1 | E13: 1 | F13: 1 | G13: 1 | H13: 1 | I13: 1 | J13: 1 | K13: 1 | L13: 1
A14: Discount time (mid-period) | C14: =C13/2 -> 0.25205 | D14: =C14+C13/2+D13/2 -> 1.0041 | E14: =D14+D13/2+E13/2 -> 2.0041 | F14: =E14+E13/2+F13/2 -> 3.0041 | G14: =F14+F13/2+G13/2 -> 4.0041 | H14: =G14+G13/2+H13/2 -> 5.0041 | I14: =H14+H13/2+I13/2 -> 6.0041 | J14: =I14+I13/2+J13/2 -> 7.0041 | K14: =J14+J13/2+K13/2 -> 8.0041 | L14: =K14+K13/2+L13/2 -> 9.0041
A15: Discount factor | C15: =1/(1+Assumptions!$E$10)^C14 -> 0.97403899 | D15: =1/(1+Assumptions!$E$10)^D14 -> 0.90051551 | E15: =1/(1+Assumptions!$E$10)^E14 -> 0.81127523 | F15: =1/(1+Assumptions!$E$10)^F14 -> 0.73087859 | G15: =1/(1+Assumptions!$E$10)^G14 -> 0.65844918 | H15: =1/(1+Assumptions!$E$10)^H14 -> 0.59319746 | I15: =1/(1+Assumptions!$E$10)^I14 -> 0.53441213 | J15: =1/(1+Assumptions!$E$10)^J14 -> 0.48145236 | ... L15: =1/(1+Assumptions!$E$10)^L14 -> 0.39075754
A16: PV of free cash flow | C16: =C12*C13*C15 -> 63.954367 | D16: =D12*D13*D15 -> 135.32517 | E16: =E12*E13*E15 -> 138.92288 | F16: =F12*F13*F15 -> 140.83499 | G16: =G12*G13*G15 -> 140.9681 | H16: =H12*H13*H15 -> 139.29477 | I16: =I12*I13*I15 -> 135.85661 | J16: =J12*J13*J15 -> 130.76308 | ... L16: =L12*L13*L15 -> 116.34961
A19: PV of forecast free cash flow | B19: =SUM(C16:L16) -> 1266.4555
A20: Terminal free cash flow (year 11) | B20: =L10*(1+Assumptions!$E$11)-L7*Assumptions!$E$11*Assumptions!$E$15 -> 305.19783
A21: Terminal value | B21: =B20/(Assumptions!$E$10-Assumptions!$E$11) -> 3590.5627
A22: PV of terminal value | B22: =B21/(1+Assumptions!$E$10)^(L14+0.5) -> 1331.7061
A23: Enterprise value | B23: =B19+B22 -> 2598.1616
A24: Cash & investments | B24: =Main!C7 -> 570.388
A25: Debt | B25: =Main!C8 -> 258.454
A26: Equity value | B26: =B23+B24-B25 -> 2910.0956
A27: Shares (mm) | B27: =Main!C4 -> 72.245485
A28: NPV / share | B28: =B26/B27 -> 40.280657
A29: Price | B29: =Main!C3 -> 21.28
A30: Upside | B30: =B28/B29-1 -> 0.89288802
A31: Terminal value, % of EV | B31: =IFERROR(B22/B23,0) -> 0.51255707
