Workbook

Sheet Main
B2: Iovance Biotherapeutics Inc
B3: Price | C3: =INDEX([1]Pharma!$F$1:$F$1000,MATCH("IOVA",[1]Pharma!$B$1:$B$1000,0)) -> 14.86
B4: Shares | C4: 452.97143
B5: Market Cap. | C5: =C3*C4 -> 6731.1555
B7: Cash | C7: =110.768+186.906 -> 297.674
B8: Debt | C8: 0
B9: Enterprise V. | C9: =C5-C7+C8 -> 6433.4815
B11: NPV / Share | C11: =NPV!B28 -> 0.15760837
B12: Upside | C12: =IFERROR(C11/C3-1,"") -> -0.98939378
B13: Cash / Share | C13: =IFERROR((C7-C8)/C4,"") -> 0.65715844
B14: Scenario | C14: =Assumptions!C4 -> Base
B15: Model | C15: DCF

Sheet Yearly Model
B1: 2008 | C1: 2009 | D1: 2010 | E1: 2011 | F1: 2012 | G1: 2013 | H1: 2014 | I1: 2015 | J1: 2016 | K1: 2017 | L1: 2018 | M1: 2019 | N1: 2020 | O1: 2021 | P1: 2022 | Q1: 2023 | R1: 2024 | S1: 2025 | T1: 2026 | U1: 2027 | V1: 2028 | W1: 2029 | X1: 2030 | Y1: 2031 | Z1: 2032 | AA1: 2033 | AB1: 2034 | AC1: 2035
A2: Revenue | B2: 0 | C2: 0 | D2: 0 | E2: 0 | F2: 0 | G2: 0 | H2: 0 | I2: 0 | J2: 0 | K2: 0 | L2: 0 | M2: 0 | N2: 0 | O2: 0 | P2: 0 | Q2: 1.189 | R2: 164.07 | S2: 263.502 | T2: =S2*(1+NPV!C5) -> 355.7277 | U2: =T2*(1+NPV!D5) -> 467.38667 | V2: =U2*(1+NPV!E5) -> 597.2163 | W2: =V2*(1+NPV!F5) -> 741.54358 | X2: =W2*(1+NPV!G5) -> 893.97198 | Y2: =X2*(1+NPV!H5) -> 1045.4506 | Z2: =Y2*(1+NPV!I5) -> 1184.844 | AA2: =Z2*(1+NPV!J5) -> 1300.0371 | ... AC2: =AB2*(1+NPV!L5) -> 1413.9709
A3: Cost of Sales | B3: 0 | C3: 0 | D3: 0 | E3: 0 | F3: 0 | G3: 0 | H3: 0 | I3: 0 | J3: 0 | K3: 0 | L3: 0 | M3: 0 | N3: 0 | O3: 0 | P3: 0 | Q3: 1.033 | R3: 93.248 | S3: 173.184 | T3: =T2*(1-Assumptions!$B$19) -> 233.78424 | U3: =U2*(1-Assumptions!$B$19) -> 307.16652 | V3: =V2*(1-Assumptions!$B$19) -> 392.49055 | W3: =W2*(1-Assumptions!$B$19) -> 487.34244 | X3: =X2*(1-Assumptions!$B$19) -> 587.51838 | Y3: =Y2*(1-Assumptions!$B$19) -> 687.07011 | Z3: =Z2*(1-Assumptions!$B$19) -> 778.67946 | AA3: =AA2*(1-Assumptions!$B$19) -> 854.38441 | ... AC3: =AC2*(1-Assumptions!$B$19) -> 929.26171
A4: Gross Margin | B4: =B2-B3 -> 0 | C4: =C2-C3 -> 0 | D4: =D2-D3 -> 0 | E4: =E2-E3 -> 0 | F4: =F2-F3 -> 0 | G4: =G2-G3 -> 0 | H4: =H2-H3 -> 0 | I4: =I2-I3 -> 0 | ... AC4: =AC2-AC3 -> 484.70924
A5: Research & Dev. | B5: 0 | C5: 0 | D5: 0.171 | E5: 1.756 | F5: 1.656 | G5: 2.154 | H5: 3.849 | I5: 15.47 | J5: 26.941 | K5: 71.615 | L5: 99.828 | M5: 166.023 | N5: 201.727 | O5: 259.039 | P5: 294.781 | Q5: 333.194 | R5: 276.228 | S5: 300.27 | T5: =T7*Assumptions!$B$20 -> 250.53745 | U5: =U7*Assumptions!$B$20 -> 297.34074 | V5: =V7*Assumptions!$B$20 -> 339.25398 | W5: =W7*Assumptions!$B$20 -> 370.72759 | X5: =X7*Assumptions!$B$20 -> 386.03677 | Y5: =Y7*Assumptions!$B$20 -> 380.23413 | Z5: =Z7*Assumptions!$B$20 -> 350.22234 | AA5: =AA7*Assumptions!$B$20 -> 295.71529 | ... AC5: =AC7*Assumptions!$B$20 -> 128.99657
A6: SG&A & Other | B6: 0.059 | C6: 0.016 | D6: 0.644 | E6: 19.463 | F6: 6.477 | G6: 20.487 | H6: 8.192 | I6: 12.39 | J6: 26.698 | K6: 21.262 | L6: 28.43 | M6: 40.849 | N6: 60.21 | O6: 83.664 | P6: 104.097 | Q6: 127.521 | R6: 189.872 | S6: 193.404 | T6: =T7-T5 -> 161.39522 | U6: =U7-U5 -> 191.54571 | V6: =V7-V5 -> 218.54605 | W6: =W7-W5 -> 238.82123 | X6: =X7-X5 -> 248.68334 | Y6: =Y7-Y5 -> 244.9453 | Z6: =Z7-Z5 -> 225.61183 | AA6: =AA7-AA5 -> 190.4986 | ... AC6: =AC7-AC5 -> 83.099073
A7: Operating Expense | B7: =SUM(B5:B6) -> 0.059 | C7: =SUM(C5:C6) -> 0.016 | D7: =SUM(D5:D6) -> 0.815 | E7: =SUM(E5:E6) -> 21.219 | F7: =SUM(F5:F6) -> 8.133 | G7: =SUM(G5:G6) -> 22.641 | H7: =SUM(H5:H6) -> 12.041 | I7: =SUM(I5:I6) -> 27.86 | ... S7: =SUM(S5:S6) -> 493.674 | T7: =T4-T2*NPV!C6 -> 411.93268 | U7: =U4-U2*NPV!D6 -> 488.88646 | V7: =V4-V2*NPV!E6 -> 557.80003 | W7: =W4-W2*NPV!F6 -> 609.54882 | X7: =X4-X2*NPV!G6 -> 634.72011 | Y7: =Y4-Y2*NPV!H6 -> 625.17944 | Z7: =Z4-Z2*NPV!I6 -> 575.83417 | AA7: =AA4-AA2*NPV!J6 -> 486.21389 | ... AC7: =AC4-AC2*NPV!L6 -> 212.09564
A8: Operating Income | B8: =B4-B7 -> -0.059 | C8: =C4-C7 -> -0.016 | D8: =D4-D7 -> -0.815 | E8: =E4-E7 -> -21.219 | F8: =F4-F7 -> -8.133 | G8: =G4-G7 -> -22.641 | H8: =H4-H7 -> -12.041 | I8: =I4-I7 -> -27.86 | ... AC8: =AC4-AC7 -> 272.6136
A9: Interest & Other | B9: 0 | C9: 0 | D9: -0.793 | E9: -4.476 | F9: 4.825 | G9: -2.741 | H9: 0.006 | I9: 0.2 | J9: 0.745 | K9: 0.813 | L9: 4.678 | M9: 9.316 | N9: 2.356 | O9: 0.403 | P9: 2.978 | Q9: 13.08 | R9: 20.25 | S9: 10.285 | T9: 0 | U9: 0 | V9: 0 | W9: 0 | X9: 0 | Y9: 0 | Z9: 0 | AA9: 0 | AB9: 0 | AC9: 0
A10: Pretax | B10: =B8+B9 -> -0.059 | C10: =C8+C9 -> -0.016 | D10: =D8+D9 -> -1.608 | E10: =E8+E9 -> -25.695 | F10: =F8+F9 -> -3.308 | G10: =G8+G9 -> -25.382 | H10: =H8+H9 -> -12.035 | I10: =I8+I9 -> -27.66 | ... AC10: =AC8+AC9 -> 272.6136
A11: Taxes | B11: 0 | C11: 0 | D11: 0 | E11: 0 | F11: 0 | G11: 0 | H11: 0 | I11: 0 | J11: 0 | K11: 0 | L11: 0 | M11: 0 | N11: 0 | O11: 0 | P11: 0 | Q11: -3.479 | R11: -2.828 | S11: -2.071 | T11: =MAX(0,T10)*Assumptions!$E$14 -> 0 | U11: =MAX(0,U10)*Assumptions!$E$14 -> 0 | V11: =MAX(0,V10)*Assumptions!$E$14 -> 0 | W11: =MAX(0,W10)*Assumptions!$E$14 -> 0 | X11: =MAX(0,X10)*Assumptions!$E$14 -> 0 | Y11: =MAX(0,Y10)*Assumptions!$E$14 -> 0 | Z11: =MAX(0,Z10)*Assumptions!$E$14 -> 0 | AA11: =MAX(0,AA10)*Assumptions!$E$14 -> 0 | ... AC11: =MAX(0,AC10)*Assumptions!$E$14 -> 46.344312
A12: Net Income | B12: -0.059 | C12: -0.016 | D12: -1.608 | E12: -25.694 | F12: -3.308 | G12: -25.382 | H12: -12.035 | I12: -27.66 | J12: -52.894 | K12: -92.064 | L12: -123.58 | M12: -197.556 | N12: -259.581 | O12: -342.3 | P12: -395.9 | Q12: -444 | R12: -372.2 | S12: -391 | T12: =T10-T11 -> -289.98922 | U12: =U10-U11 -> -328.66631 | V12: =V10-V11 -> -353.07428 | W12: =W10-W11 -> -355.34768 | X12: =X10-X11 -> -328.26651 | Y12: =Y10-Y11 -> -266.79898 | Z12: =Z10-Z11 -> -169.66966 | AA12: =AA10-AA11 -> -40.561159 | ... AC12: =AC10-AC11 -> 226.26929
A13: Earnings per Share | B13: =IFERROR(B12/B14,0) -> 0 | C13: =IFERROR(C12/C14,0) -> 0 | D13: =IFERROR(D12/D14,0) -> 0 | E13: =IFERROR(E12/E14,0) -> -7.3516452 | F13: =IFERROR(F12/F14,0) -> -0.089986671 | G13: =IFERROR(G12/G14,0) -> -0.68873633 | H13: =IFERROR(H12/H14,0) -> -0.32633748 | I13: =IFERROR(I12/I14,0) -> -0.4219744 | ... AC13: =IFERROR(AC12/AC14,0) -> 0.4995222
A14: Shares | E14: 3.495 | F14: 36.761 | G14: 36.853 | H14: 36.879 | I14: 65.549 | J14: 81.576 | K14: 96.297 | L14: 143.581 | M14: 183.52 | N14: 204.132 | O14: 226.427 | P14: 235.066 | Q14: 235.131 | R14: 289.877 | S14: 357.345 | T14: =Main!$C$4 -> 452.97143 | U14: =Main!$C$4 -> 452.97143 | V14: =Main!$C$4 -> 452.97143 | W14: =Main!$C$4 -> 452.97143 | X14: =Main!$C$4 -> 452.97143 | Y14: =Main!$C$4 -> 452.97143 | Z14: =Main!$C$4 -> 452.97143 | AA14: =Main!$C$4 -> 452.97143 | ... AC14: =Main!$C$4 -> 452.97143
A16: Revenue Change | C16: =IFERROR(C2/B2-1,"") | D16: =IFERROR(D2/C2-1,"") | E16: =IFERROR(E2/D2-1,"") | F16: =IFERROR(F2/E2-1,"") | G16: =IFERROR(G2/F2-1,"") | H16: =IFERROR(H2/G2-1,"") | I16: =IFERROR(I2/H2-1,"") | J16: =IFERROR(J2/I2-1,"") | ... AC16: =IFERROR(AC2/AB2-1,"") -> 0.025
A17: Gross Margin | B17: =IFERROR(B4/B2,"") | C17: =IFERROR(C4/C2,"") | D17: =IFERROR(D4/D2,"") | E17: =IFERROR(E4/E2,"") | F17: =IFERROR(F4/F2,"") | G17: =IFERROR(G4/G2,"") | H17: =IFERROR(H4/H2,"") | I17: =IFERROR(I4/I2,"") | ... AC17: =IFERROR(AC4/AC2,"") -> 0.3428
A18: Operating Margin | B18: =IFERROR(B8/B2,"") | C18: =IFERROR(C8/C2,"") | D18: =IFERROR(D8/D2,"") | E18: =IFERROR(E8/E2,"") | F18: =IFERROR(F8/F2,"") | G18: =IFERROR(G8/G2,"") | H18: =IFERROR(H8/H2,"") | I18: =IFERROR(I8/I2,"") | ... AC18: =IFERROR(AC8/AC2,"") -> 0.1928
A19: Actual / Estimate | B19: A | C19: A | D19: A | E19: A | F19: A | G19: A | H19: A | I19: A | J19: A | K19: A | L19: A | M19: A | N19: A | O19: A | P19: A | Q19: A | R19: A | S19: A | T19: E | U19: E | V19: E | W19: E | X19: E | Y19: E | Z19: E | AA19: E | AB19: E | AC19: E

Sheet Quarterly Model

Sheet Assumptions
A1: Iovance Biotherapeutics Inc: basic DCF assumptions
A2: Blue = input, black = formula, green = link. $mm unless noted.
A4: Scenario (1 Bear, 2 Base, 3 Bull) | B4: 2 | C4: =CHOOSE($B$4,"Bear","Base","Bull") -> Base
A6: Discount rate override (blank = scenario)
A7: Terminal growth override (blank = scenario)
A9: Parameter | B9: Bear | C9: Base | D9: Bull | E9: Live
A10: Discount rate | B10: 0.105 | C10: 0.095 | D10: 0.085 | E10: =IF(ISNUMBER($B$6),$B$6,CHOOSE($B$4,B10,C10,D10)) -> 0.095
A11: Terminal growth | B11: 0.02 | C11: 0.025 | D11: 0.03 | E11: =IF(ISNUMBER($B$7),$B$7,CHOOSE($B$4,B11,C11,D11)) -> 0.025
A12: Revenue growth, first forecast year | B12: 0.3 | C12: 0.35 | D12: 0.4 | E12: =CHOOSE($B$4,B12,C12,D12) -> 0.35
A13: Operating margin, year 10 | B13: 0.1428 | C13: 0.1928 | D13: 0.2428 | E13: =CHOOSE($B$4,B13,C13,D13) -> 0.1928
A14: Tax rate on operating income | B14: 0.17 | C14: 0.17 | D14: 0.17 | E14: =CHOOSE($B$4,B14,C14,D14) -> 0.17
A15: Reinvestment, % of revenue increase | B15: 0.25 | C15: 0.25 | D15: 0.25 | E15: =CHOOSE($B$4,B15,C15,D15) -> 0.25
A17: Single inputs
A18: Starting operating margin (TTM) | B18: -0.9272
A19: Gross margin (forecast) | B19: 0.3428
A20: R&D share of operating expense (forecast) | B20: 0.6082
A21: Forecast years | B21: 10
A22: First forecast year, fraction after balance sheet date | B22: 0.5041
A23: Balance sheet date | B23: 46203
A24: Reporting currency per USD (USD) | B24: 1
A25: Base revenue, FY2025 | B25: ='Yearly Model'!S2 -> 263.502
A27: Scenario summary
A28: Scenario | B28: Enterprise value | C28: Equity value | D28: NPV / share | E28: Upside
A29: Live | B29: =NPV!B23 -> -226.28191 | C29: =NPV!B26 -> 71.39209 | D29: =NPV!B28 -> 0.15760837 | E29: =NPV!B30 -> -0.98939378
A30: 1 | B30: -885.00029 | C30: -587.32629 | D30: -1.2966078 | E30: -1.0872549
A31: 2 | B31: -226.28191 | C31: 71.39209 | D31: 0.15760837 | E31: -0.98939378
A32: 3 | B32: 1332.3824 | C32: 1630.0564 | D32: 3.5985854 | E32: -0.75783409
A35: NPV / share: discount rate (rows) x terminal growth (columns)
A36: =NPV!B28 -> 0.15760837 | B36: 0.015 | C36: 0.02 | D36: 0.025 | E36: 0.03 | F36: 0.035
A37: 0.075 | B37: 1.0301823 | C37: 1.4631601 | D37: 1.9868836 | E37: 2.6316506 | F37: 3.4429087
A38: 0.085 | B38: 0.25420432 | C38: 0.5471092 | D38: 0.89209602 | E38: 1.3034068 | F38: 1.8009809
A39: 0.095 | B39: -0.28764921 | C39: -0.08109604 | D39: 0.15760837 | E39: 0.43591356 | F39: 0.76375256
A40: 0.105 | B40: -0.67622688 | C40: -0.52607297 | D40: -0.35496239 | E40: -0.1586794 | F40: 0.068196492
A41: 0.115 | B41: -0.95981098 | C41: -0.84814653 | D41: -0.72223464 | E41: -0.57954084 | F41: -0.41689681

Sheet NPV
A1: Iovance Biotherapeutics Inc: free-cash-flow DCF ($mm)
A3: Fiscal year | B3: ='Yearly Model'!S1 -> 2025 | C3: ='Yearly Model'!T1 -> 2026 | D3: ='Yearly Model'!U1 -> 2027 | E3: ='Yearly Model'!V1 -> 2028 | F3: ='Yearly Model'!W1 -> 2029 | G3: ='Yearly Model'!X1 -> 2030 | H3: ='Yearly Model'!Y1 -> 2031 | I3: ='Yearly Model'!Z1 -> 2032 | ... L3: ='Yearly Model'!AC1 -> 2035
A4: Period | B4: Actual | C4: 1 | D4: 2 | E4: 3 | F4: 4 | G4: 5 | H4: 6 | I4: 7 | J4: 8 | K4: 9 | L4: 10
A5: Revenue growth | C5: =Assumptions!$E$12+(Assumptions!$E$11-Assumptions!$E$12)*(C4-1)/(Assumptions!$B$21-1) -> 0.35 | D5: =Assumptions!$E$12+(Assumptions!$E$11-Assumptions!$E$12)*(D4-1)/(Assumptions!$B$21-1) -> 0.31388889 | E5: =Assumptions!$E$12+(Assumptions!$E$11-Assumptions!$E$12)*(E4-1)/(Assumptions!$B$21-1) -> 0.27777778 | F5: =Assumptions!$E$12+(Assumptions!$E$11-Assumptions!$E$12)*(F4-1)/(Assumptions!$B$21-1) -> 0.24166667 | G5: =Assumptions!$E$12+(Assumptions!$E$11-Assumptions!$E$12)*(G4-1)/(Assumptions!$B$21-1) -> 0.20555556 | H5: =Assumptions!$E$12+(Assumptions!$E$11-Assumptions!$E$12)*(H4-1)/(Assumptions!$B$21-1) -> 0.16944444 | I5: =Assumptions!$E$12+(Assumptions!$E$11-Assumptions!$E$12)*(I4-1)/(Assumptions!$B$21-1) -> 0.13333333 | J5: =Assumptions!$E$12+(Assumptions!$E$11-Assumptions!$E$12)*(J4-1)/(Assumptions!$B$21-1) -> 0.097222222 | ... L5: =Assumptions!$E$12+(Assumptions!$E$11-Assumptions!$E$12)*(L4-1)/(Assumptions!$B$21-1) -> 0.025
A6: Operating margin | B6: =IFERROR(B8/B7,0) -> -1.5307512 | C6: =Assumptions!$B$18+(Assumptions!$E$13-Assumptions!$B$18)*C4/Assumptions!$B$21 -> -0.8152 | D6: =Assumptions!$B$18+(Assumptions!$E$13-Assumptions!$B$18)*D4/Assumptions!$B$21 -> -0.7032 | E6: =Assumptions!$B$18+(Assumptions!$E$13-Assumptions!$B$18)*E4/Assumptions!$B$21 -> -0.5912 | F6: =Assumptions!$B$18+(Assumptions!$E$13-Assumptions!$B$18)*F4/Assumptions!$B$21 -> -0.4792 | G6: =Assumptions!$B$18+(Assumptions!$E$13-Assumptions!$B$18)*G4/Assumptions!$B$21 -> -0.3672 | H6: =Assumptions!$B$18+(Assumptions!$E$13-Assumptions!$B$18)*H4/Assumptions!$B$21 -> -0.2552 | I6: =Assumptions!$B$18+(Assumptions!$E$13-Assumptions!$B$18)*I4/Assumptions!$B$21 -> -0.1432 | J6: =Assumptions!$B$18+(Assumptions!$E$13-Assumptions!$B$18)*J4/Assumptions!$B$21 -> -0.0312 | ... L6: =Assumptions!$B$18+(Assumptions!$E$13-Assumptions!$B$18)*L4/Assumptions!$B$21 -> 0.1928
A7: Revenue | B7: ='Yearly Model'!S2 -> 263.502 | C7: ='Yearly Model'!T2 -> 355.7277 | D7: ='Yearly Model'!U2 -> 467.38667 | E7: ='Yearly Model'!V2 -> 597.2163 | F7: ='Yearly Model'!W2 -> 741.54358 | G7: ='Yearly Model'!X2 -> 893.97198 | H7: ='Yearly Model'!Y2 -> 1045.4506 | I7: ='Yearly Model'!Z2 -> 1184.844 | ... L7: ='Yearly Model'!AC2 -> 1413.9709
A8: Operating income | B8: ='Yearly Model'!S8 -> -403.356 | C8: ='Yearly Model'!T8 -> -289.98922 | D8: ='Yearly Model'!U8 -> -328.66631 | E8: ='Yearly Model'!V8 -> -353.07428 | F8: ='Yearly Model'!W8 -> -355.34768 | G8: ='Yearly Model'!X8 -> -328.26651 | H8: ='Yearly Model'!Y8 -> -266.79898 | I8: ='Yearly Model'!Z8 -> -169.66966 | ... L8: ='Yearly Model'!AC8 -> 272.6136
A9: Tax on operating income | C9: =MAX(0,C8)*Assumptions!$E$14 -> 0 | D9: =MAX(0,D8)*Assumptions!$E$14 -> 0 | E9: =MAX(0,E8)*Assumptions!$E$14 -> 0 | F9: =MAX(0,F8)*Assumptions!$E$14 -> 0 | G9: =MAX(0,G8)*Assumptions!$E$14 -> 0 | H9: =MAX(0,H8)*Assumptions!$E$14 -> 0 | I9: =MAX(0,I8)*Assumptions!$E$14 -> 0 | J9: =MAX(0,J8)*Assumptions!$E$14 -> 0 | ... L9: =MAX(0,L8)*Assumptions!$E$14 -> 46.344312
A10: NOPAT | C10: =C8-C9 -> -289.98922 | D10: =D8-D9 -> -328.66631 | E10: =E8-E9 -> -353.07428 | F10: =F8-F9 -> -355.34768 | G10: =G8-G9 -> -328.26651 | H10: =H8-H9 -> -266.79898 | I10: =I8-I9 -> -169.66966 | J10: =J8-J9 -> -40.561159 | ... L10: =L8-L9 -> 226.26929
A11: Reinvestment | C11: =(C7-B7)*Assumptions!$E$15 -> 23.056425 | D11: =(D7-C7)*Assumptions!$E$15 -> 27.914743 | E11: =(E7-D7)*Assumptions!$E$15 -> 32.457408 | F11: =(F7-E7)*Assumptions!$E$15 -> 36.081818 | G11: =(G7-F7)*Assumptions!$E$15 -> 38.1071 | H11: =(H7-G7)*Assumptions!$E$15 -> 37.869646 | I11: =(I7-H7)*Assumptions!$E$15 -> 34.848352 | J11: =(J7-I7)*Assumptions!$E$15 -> 28.798291 | ... L11: =(L7-K7)*Assumptions!$E$15 -> 8.6217741
A12: Free cash flow | C12: =C10-C11 -> -313.04565 | D12: =D10-D11 -> -356.58105 | E12: =E10-E11 -> -385.53169 | F12: =F10-F11 -> -391.4295 | G12: =G10-G11 -> -366.37361 | H12: =H10-H11 -> -304.66863 | I12: =I10-I11 -> -204.51801 | J12: =J10-J11 -> -69.35945 | ... L12: =L10-L11 -> 217.64751
A13: Year fraction | C13: =Assumptions!$B$22 -> 0.5041 | D13: 1 | E13: 1 | F13: 1 | G13: 1 | H13: 1 | I13: 1 | J13: 1 | K13: 1 | L13: 1
A14: Discount time (mid-period) | C14: =C13/2 -> 0.25205 | D14: =C14+C13/2+D13/2 -> 1.0041 | E14: =D14+D13/2+E13/2 -> 2.0041 | F14: =E14+E13/2+F13/2 -> 3.0041 | G14: =F14+F13/2+G13/2 -> 4.0041 | H14: =G14+G13/2+H13/2 -> 5.0041 | I14: =H14+H13/2+I13/2 -> 6.0041 | J14: =I14+I13/2+J13/2 -> 7.0041 | K14: =J14+J13/2+K13/2 -> 8.0041 | L14: =K14+K13/2+L13/2 -> 9.0041
A15: Discount factor | C15: =1/(1+Assumptions!$E$10)^C14 -> 0.977385 | D15: =1/(1+Assumptions!$E$10)^D14 -> 0.91290226 | E15: =1/(1+Assumptions!$E$10)^E14 -> 0.8337007 | F15: =1/(1+Assumptions!$E$10)^F14 -> 0.7613705 | G15: =1/(1+Assumptions!$E$10)^G14 -> 0.69531552 | H15: =1/(1+Assumptions!$E$10)^H14 -> 0.63499135 | I15: =1/(1+Assumptions!$E$10)^I14 -> 0.57990077 | J15: =1/(1+Assumptions!$E$10)^J14 -> 0.52958975 | ... L15: =1/(1+Assumptions!$E$10)^L14 -> 0.44168366
A16: PV of free cash flow | C16: =C12*C13*C15 -> -154.23752 | D16: =D12*D13*D15 -> -325.52365 | E16: =E12*E13*E15 -> -321.41804 | F16: =F12*F13*F15 -> -298.02287 | G16: =G12*G13*G15 -> -254.74526 | H16: =H12*H13*H15 -> -193.46194 | I16: =I12*I13*I15 -> -118.60015 | J16: =J12*J13*J15 -> -36.732053 | ... L16: =L12*L13*L15 -> 96.131349
A19: PV of forecast free cash flow | B19: =SUM(C16:L16) -> -1571.4724
A20: Terminal free cash flow (year 11) | B20: =L10*(1+Assumptions!$E$11)-L7*Assumptions!$E$11*Assumptions!$E$15 -> 223.0887
A21: Terminal value | B21: =B20/(Assumptions!$E$10-Assumptions!$E$11) -> 3186.9814
A22: PV of terminal value | B22: =B21/(1+Assumptions!$E$10)^(L14+0.5) -> 1345.1905
A23: Enterprise value | B23: =B19+B22 -> -226.28191
A24: Cash & investments | B24: =Main!C7 -> 297.674
A25: Debt | B25: =Main!C8 -> 0
A26: Equity value | B26: =B23+B24-B25 -> 71.39209
A27: Shares (mm) | B27: =Main!C4 -> 452.97143
A28: NPV / share | B28: =B26/B27 -> 0.15760837
A29: Price | B29: =Main!C3 -> 14.86
A30: Upside | B30: =B28/B29-1 -> -0.98939378
A31: Terminal value, % of EV | B31: =IFERROR(B22/B23,0) -> -5.9447551
