Workbook

Sheet Main
B2: Invivyd, Inc.
B3: Price | C3: =INDEX([1]Pharma!$F$1:$F$1000,MATCH("IVVD",[1]Pharma!$B$1:$B$1000,0)) -> 0.6366
B4: Shares | C4: 294.75875
B5: Market Cap. | C5: =C3*C4 -> 187.64342
B7: Cash | C7: 160.08
B8: Debt | C8: 0
B9: Enterprise V. | C9: =C5-C7+C8 -> 27.563418
B11: NPV / Share | C11: =NPV!B28 -> -0.42449278
B12: Upside | C12: =IFERROR(C11/C3-1,"") -> -1.6668124
B13: Cash / Share | C13: =IFERROR((C7-C8)/C4,"") -> 0.54308821
B14: Scenario | C14: =Assumptions!C4 -> Base
B15: Model | C15: DCF

Sheet Yearly Model
B1: 2021 | C1: 2022 | D1: 2023 | E1: 2024 | F1: 2025 | G1: 2026 | H1: 2027 | I1: 2028 | J1: 2029 | K1: 2030 | L1: 2031 | M1: 2032 | N1: 2033 | O1: 2034 | P1: 2035
A2: Revenue | B2: 0 | C2: 0 | D2: 0 | E2: 25.384 | F2: 53.426 | G2: =F2*(1+NPV!C5) -> 64.853821 | H2: =G2*(1+NPV!D5) -> 77.364844 | I2: =H2*(1+NPV!E5) -> 90.66558 | J2: =I2*(1+NPV!F5) -> 104.35004 | K2: =J2*(1+NPV!G5) -> 117.90975 | L2: =K2*(1+NPV!H5) -> 130.75667 | M2: =L2*(1+NPV!I5) -> 142.2589 | N2: =M2*(1+NPV!J5) -> 151.78708 | ... P2: =O2*(1+NPV!L5) -> 162.73679
A3: Cost of Sales | B3: 0 | C3: 0 | D3: 0 | E3: 0 | F3: 0 | G3: =G2*(1-Assumptions!$B$19) -> 0 | H3: =H2*(1-Assumptions!$B$19) -> 0 | I3: =I2*(1-Assumptions!$B$19) -> 0 | J3: =J2*(1-Assumptions!$B$19) -> 0 | K3: =K2*(1-Assumptions!$B$19) -> 0 | L3: =L2*(1-Assumptions!$B$19) -> 0 | M3: =M2*(1-Assumptions!$B$19) -> 0 | N3: =N2*(1-Assumptions!$B$19) -> 0 | ... P3: =P2*(1-Assumptions!$B$19) -> 0
A4: Gross Margin | B4: =B2-B3 -> 0 | C4: =C2-C3 -> 0 | D4: =D2-D3 -> 0 | E4: =E2-E3 -> 25.384 | F4: =F2-F3 -> 53.426 | G4: =G2-G3 -> 64.853821 | H4: =H2-H3 -> 77.364844 | I4: =I2-I3 -> 90.66558 | ... P4: =P2-P3 -> 162.73679
A5: Research & Dev. | B5: 182.891 | C5: 179.214 | D5: 158.658 | E5: 137.254 | F5: 38.308 | G5: =G7*Assumptions!$B$20 -> 53.114955 | H5: =H7*Assumptions!$B$20 -> 58.738484 | I5: =I7*Assumptions!$B$20 -> 63.419213 | J5: =J7*Assumptions!$B$20 -> 66.75585 | K5: =K7*Assumptions!$B$20 -> 68.384705 | L5: =L7*Assumptions!$B$20 -> 68.022234 | M5: =M7*Assumptions!$B$20 -> 65.505243 | N5: =N7*Assumptions!$B$20 -> 60.822601 | ... P5: =P7*Assumptions!$B$20 -> 45.761585
A6: SG&A & Other | B6: 44.017 | C6: 68.817 | D6: 54.1 | E6: 65.006 | F6: 70.678 | G6: =G7-G5 -> 97.994448 | H6: =H7-H5 -> 108.36958 | I6: =I7-I5 -> 117.00529 | J6: =J7-J5 -> 123.16122 | K6: =K7-K5 -> 126.16638 | L6: =L7-L5 -> 125.49763 | M6: =M7-M5 -> 120.85391 | N6: =N7-N5 -> 112.21467 | ... P6: =P7-P5 -> 84.427847
A7: Operating Expense | B7: =SUM(B5:B6) -> 226.908 | C7: =SUM(C5:C6) -> 248.031 | D7: =SUM(D5:D6) -> 212.758 | E7: =SUM(E5:E6) -> 202.26 | F7: =SUM(F5:F6) -> 108.986 | G7: =G4-G2*NPV!C6 -> 151.1094 | H7: =H4-H2*NPV!D6 -> 167.10806 | I7: =I4-I2*NPV!E6 -> 180.4245 | J7: =J4-J2*NPV!F6 -> 189.91707 | K7: =K4-K2*NPV!G6 -> 194.55108 | L7: =L4-L2*NPV!H6 -> 193.51987 | M7: =M4-M2*NPV!I6 -> 186.35915 | N7: =N4-N2*NPV!J6 -> 173.03727 | ... P7: =P4-P2*NPV!L6 -> 130.18943
A8: Operating Income | B8: =B4-B7 -> -226.908 | C8: =C4-C7 -> -248.031 | D8: =D4-D7 -> -212.758 | E8: =E4-E7 -> -176.876 | F8: =F4-F7 -> -55.56 | G8: =G4-G7 -> -86.255582 | H8: =H4-H7 -> -89.743219 | I8: =I4-I7 -> -89.758924 | ... P8: =P4-P7 -> 32.547358
A9: Interest & Other | B9: 0.118 | C9: 6.714 | D9: 14.115 | E9: 6.951 | F9: 3.071 | G9: 0 | H9: 0 | I9: 0 | J9: 0 | K9: 0 | L9: 0 | M9: 0 | N9: 0 | O9: 0 | P9: 0
A10: Pretax | B10: =B8+B9 -> -226.79 | C10: =C8+C9 -> -241.317 | D10: =D8+D9 -> -198.643 | E10: =E8+E9 -> -169.925 | F10: =F8+F9 -> -52.489 | G10: =G8+G9 -> -86.255582 | H10: =H8+H9 -> -89.743219 | I10: =I8+I9 -> -89.758924 | ... P10: =P8+P9 -> 32.547358
A11: Taxes | B11: 0 | C11: 0 | D11: 0 | E11: 0 | F11: 0 | G11: =MAX(0,G10)*Assumptions!$E$14 -> 0 | H11: =MAX(0,H10)*Assumptions!$E$14 -> 0 | I11: =MAX(0,I10)*Assumptions!$E$14 -> 0 | J11: =MAX(0,J10)*Assumptions!$E$14 -> 0 | K11: =MAX(0,K10)*Assumptions!$E$14 -> 0 | L11: =MAX(0,L10)*Assumptions!$E$14 -> 0 | M11: =MAX(0,M10)*Assumptions!$E$14 -> 0 | N11: =MAX(0,N10)*Assumptions!$E$14 -> 0 | ... P11: =MAX(0,P10)*Assumptions!$E$14 -> 5.5330509
A12: Net Income | B12: -226.79 | C12: -241.317 | D12: -198.643 | E12: -169.925 | F12: -52.489 | G12: =G10-G11 -> -86.255582 | H12: =H10-H11 -> -89.743219 | I12: =I10-I11 -> -89.758924 | J12: =J10-J11 -> -85.567031 | K12: =K10-K11 -> -76.641335 | L12: =L10-L11 -> -62.763201 | M12: =M10-M11 -> -44.100258 | N12: =N10-N11 -> -21.250191 | ... P12: =P10-P11 -> 27.014307
A13: Earnings per Share | B13: =IFERROR(B12/B14,0) -> -5.3210858 | C13: =IFERROR(C12/C14,0) -> -2.2288857 | D13: =IFERROR(D12/D14,0) -> -1.8136607 | E13: =IFERROR(E12/E14,0) -> -1.433301 | F13: =IFERROR(F12/F14,0) -> -0.30479116 | G13: =IFERROR(G12/G14,0) -> -0.29263112 | H13: =IFERROR(H12/H14,0) -> -0.3044633 | I13: =IFERROR(I12/I14,0) -> -0.30451658 | ... P13: =IFERROR(P12/P14,0) -> 0.091648874
A14: Shares | B14: 42.621 | C14: 108.268 | D14: 109.526 | E14: 118.555 | F14: 172.213 | G14: =Main!$C$4 -> 294.75875 | H14: =Main!$C$4 -> 294.75875 | I14: =Main!$C$4 -> 294.75875 | J14: =Main!$C$4 -> 294.75875 | K14: =Main!$C$4 -> 294.75875 | L14: =Main!$C$4 -> 294.75875 | M14: =Main!$C$4 -> 294.75875 | N14: =Main!$C$4 -> 294.75875 | ... P14: =Main!$C$4 -> 294.75875
A16: Revenue Change | C16: =IFERROR(C2/B2-1,"") | D16: =IFERROR(D2/C2-1,"") | E16: =IFERROR(E2/D2-1,"") | F16: =IFERROR(F2/E2-1,"") -> 1.1047116 | G16: =IFERROR(G2/F2-1,"") -> 0.2139 | H16: =IFERROR(H2/G2-1,"") -> 0.19291111 | I16: =IFERROR(I2/H2-1,"") -> 0.17192222 | J16: =IFERROR(J2/I2-1,"") -> 0.15093333 | ... P16: =IFERROR(P2/O2-1,"") -> 0.025
A17: Gross Margin | B17: =IFERROR(B4/B2,"") | C17: =IFERROR(C4/C2,"") | D17: =IFERROR(D4/D2,"") | E17: =IFERROR(E4/E2,"") -> 1 | F17: =IFERROR(F4/F2,"") -> 1 | G17: =IFERROR(G4/G2,"") -> 1 | H17: =IFERROR(H4/H2,"") -> 1 | I17: =IFERROR(I4/I2,"") -> 1 | ... P17: =IFERROR(P4/P2,"") -> 1
A18: Operating Margin | B18: =IFERROR(B8/B2,"") | C18: =IFERROR(C8/C2,"") | D18: =IFERROR(D8/D2,"") | E18: =IFERROR(E8/E2,"") -> -6.9680113 | F18: =IFERROR(F8/F2,"") -> -1.0399431 | G18: =IFERROR(G8/G2,"") -> -1.33 | H18: =IFERROR(H8/H2,"") -> -1.16 | I18: =IFERROR(I8/I2,"") -> -0.99 | ... P18: =IFERROR(P8/P2,"") -> 0.2
A19: Actual / Estimate | B19: A | C19: A | D19: A | E19: A | F19: A | G19: E | H19: E | I19: E | J19: E | K19: E | L19: E | M19: E | N19: E | O19: E | P19: E

Sheet Quarterly Model

Sheet Assumptions
A1: Invivyd, Inc.: basic DCF assumptions
A2: Blue = input, black = formula, green = link. $mm unless noted.
A4: Scenario (1 Bear, 2 Base, 3 Bull) | B4: 2 | C4: =CHOOSE($B$4,"Bear","Base","Bull") -> Base
A6: Discount rate override (blank = scenario)
A7: Terminal growth override (blank = scenario)
A9: Parameter | B9: Bear | C9: Base | D9: Bull | E9: Live
A10: Discount rate | B10: 0.135 | C10: 0.125 | D10: 0.115 | E10: =IF(ISNUMBER($B$6),$B$6,CHOOSE($B$4,B10,C10,D10)) -> 0.125
A11: Terminal growth | B11: 0.02 | C11: 0.025 | D11: 0.03 | E11: =IF(ISNUMBER($B$7),$B$7,CHOOSE($B$4,B11,C11,D11)) -> 0.025
A12: Revenue growth, first forecast year | B12: 0.1639 | C12: 0.2139 | D12: 0.2639 | E12: =CHOOSE($B$4,B12,C12,D12) -> 0.2139
A13: Operating margin, year 10 | B13: 0.15 | C13: 0.2 | D13: 0.25 | E13: =CHOOSE($B$4,B13,C13,D13) -> 0.2
A14: Tax rate on operating income | B14: 0.17 | C14: 0.17 | D14: 0.17 | E14: =CHOOSE($B$4,B14,C14,D14) -> 0.17
A15: Reinvestment, % of revenue increase | B15: 0.25 | C15: 0.25 | D15: 0.25 | E15: =CHOOSE($B$4,B15,C15,D15) -> 0.25
A17: Single inputs
A18: Starting operating margin (TTM) | B18: -1.5
A19: Gross margin (forecast) | B19: 1
A20: R&D share of operating expense (forecast) | B20: 0.3515
A21: Forecast years | B21: 10
A22: First forecast year, fraction after balance sheet date | B22: 0.5041
A23: Balance sheet date | B23: 46203
A24: Reporting currency per USD (USD) | B24: 1
A25: Base revenue, FY2025 | B25: ='Yearly Model'!F2 -> 53.426
A27: Scenario summary
A28: Scenario | B28: Enterprise value | C28: Equity value | D28: NPV / share | E28: Upside
A29: Live | B29: =NPV!B23 -> -285.20296 | C29: =NPV!B26 -> -125.12296 | D29: =NPV!B28 -> -0.42449278 | E29: =NPV!B30 -> -1.6668124
A30: 1 | B30: -291.74415 | C30: -131.66415 | D30: -0.44668445 | E30: -1.7016721
A31: 2 | B31: -285.20296 | C31: -125.12296 | D31: -0.42449278 | E31: -1.6668124
A32: 3 | B32: -234.98248 | C32: -74.902484 | D32: -0.25411454 | E32: -1.3991746
A35: NPV / share: discount rate (rows) x terminal growth (columns)
A36: =NPV!B28 -> -0.42449278 | B36: 0.015 | C36: 0.02 | D36: 0.025 | E36: 0.03 | F36: 0.035
A37: 0.105 | B37: -0.39536151 | C37: -0.36999119 | D37: -0.3407243 | E37: -0.3067734 | F37: -0.26712603
A38: 0.115 | B38: -0.43071674 | C38: -0.41237093 | D38: -0.39137542 | E38: -0.36725587 | F38: -0.33941934
A39: 0.125 | B39: -0.45316472 | C39: -0.43976003 | D39: -0.42449278 | E39: -0.40706324 | F39: -0.38710501
A40: 0.135 | B40: -0.46636631 | C40: -0.45653067 | D40: -0.44535013 | E40: -0.43262773 | F40: -0.41812709
A41: 0.145 | B41: -0.47282213 | C41: -0.46562015 | D41: -0.45742525 | E41: -0.4481038 | F41: -0.43749781

Sheet NPV
A1: Invivyd, Inc.: free-cash-flow DCF ($mm)
A3: Fiscal year | B3: ='Yearly Model'!F1 -> 2025 | C3: ='Yearly Model'!G1 -> 2026 | D3: ='Yearly Model'!H1 -> 2027 | E3: ='Yearly Model'!I1 -> 2028 | F3: ='Yearly Model'!J1 -> 2029 | G3: ='Yearly Model'!K1 -> 2030 | H3: ='Yearly Model'!L1 -> 2031 | I3: ='Yearly Model'!M1 -> 2032 | ... L3: ='Yearly Model'!P1 -> 2035
A4: Period | B4: Actual | C4: 1 | D4: 2 | E4: 3 | F4: 4 | G4: 5 | H4: 6 | I4: 7 | J4: 8 | K4: 9 | L4: 10
A5: Revenue growth | C5: =Assumptions!$E$12+(Assumptions!$E$11-Assumptions!$E$12)*(C4-1)/(Assumptions!$B$21-1) -> 0.2139 | D5: =Assumptions!$E$12+(Assumptions!$E$11-Assumptions!$E$12)*(D4-1)/(Assumptions!$B$21-1) -> 0.19291111 | E5: =Assumptions!$E$12+(Assumptions!$E$11-Assumptions!$E$12)*(E4-1)/(Assumptions!$B$21-1) -> 0.17192222 | F5: =Assumptions!$E$12+(Assumptions!$E$11-Assumptions!$E$12)*(F4-1)/(Assumptions!$B$21-1) -> 0.15093333 | G5: =Assumptions!$E$12+(Assumptions!$E$11-Assumptions!$E$12)*(G4-1)/(Assumptions!$B$21-1) -> 0.12994444 | H5: =Assumptions!$E$12+(Assumptions!$E$11-Assumptions!$E$12)*(H4-1)/(Assumptions!$B$21-1) -> 0.10895556 | I5: =Assumptions!$E$12+(Assumptions!$E$11-Assumptions!$E$12)*(I4-1)/(Assumptions!$B$21-1) -> 0.087966667 | J5: =Assumptions!$E$12+(Assumptions!$E$11-Assumptions!$E$12)*(J4-1)/(Assumptions!$B$21-1) -> 0.066977778 | ... L5: =Assumptions!$E$12+(Assumptions!$E$11-Assumptions!$E$12)*(L4-1)/(Assumptions!$B$21-1) -> 0.025
A6: Operating margin | B6: =IFERROR(B8/B7,0) -> -1.0399431 | C6: =Assumptions!$B$18+(Assumptions!$E$13-Assumptions!$B$18)*C4/Assumptions!$B$21 -> -1.33 | D6: =Assumptions!$B$18+(Assumptions!$E$13-Assumptions!$B$18)*D4/Assumptions!$B$21 -> -1.16 | E6: =Assumptions!$B$18+(Assumptions!$E$13-Assumptions!$B$18)*E4/Assumptions!$B$21 -> -0.99 | F6: =Assumptions!$B$18+(Assumptions!$E$13-Assumptions!$B$18)*F4/Assumptions!$B$21 -> -0.82 | G6: =Assumptions!$B$18+(Assumptions!$E$13-Assumptions!$B$18)*G4/Assumptions!$B$21 -> -0.65 | H6: =Assumptions!$B$18+(Assumptions!$E$13-Assumptions!$B$18)*H4/Assumptions!$B$21 -> -0.48 | I6: =Assumptions!$B$18+(Assumptions!$E$13-Assumptions!$B$18)*I4/Assumptions!$B$21 -> -0.31 | J6: =Assumptions!$B$18+(Assumptions!$E$13-Assumptions!$B$18)*J4/Assumptions!$B$21 -> -0.14 | ... L6: =Assumptions!$B$18+(Assumptions!$E$13-Assumptions!$B$18)*L4/Assumptions!$B$21 -> 0.2
A7: Revenue | B7: ='Yearly Model'!F2 -> 53.426 | C7: ='Yearly Model'!G2 -> 64.853821 | D7: ='Yearly Model'!H2 -> 77.364844 | E7: ='Yearly Model'!I2 -> 90.66558 | F7: ='Yearly Model'!J2 -> 104.35004 | G7: ='Yearly Model'!K2 -> 117.90975 | H7: ='Yearly Model'!L2 -> 130.75667 | I7: ='Yearly Model'!M2 -> 142.2589 | ... L7: ='Yearly Model'!P2 -> 162.73679
A8: Operating income | B8: ='Yearly Model'!F8 -> -55.56 | C8: ='Yearly Model'!G8 -> -86.255582 | D8: ='Yearly Model'!H8 -> -89.743219 | E8: ='Yearly Model'!I8 -> -89.758924 | F8: ='Yearly Model'!J8 -> -85.567031 | G8: ='Yearly Model'!K8 -> -76.641335 | H8: ='Yearly Model'!L8 -> -62.763201 | I8: ='Yearly Model'!M8 -> -44.100258 | ... L8: ='Yearly Model'!P8 -> 32.547358
A9: Tax on operating income | C9: =MAX(0,C8)*Assumptions!$E$14 -> 0 | D9: =MAX(0,D8)*Assumptions!$E$14 -> 0 | E9: =MAX(0,E8)*Assumptions!$E$14 -> 0 | F9: =MAX(0,F8)*Assumptions!$E$14 -> 0 | G9: =MAX(0,G8)*Assumptions!$E$14 -> 0 | H9: =MAX(0,H8)*Assumptions!$E$14 -> 0 | I9: =MAX(0,I8)*Assumptions!$E$14 -> 0 | J9: =MAX(0,J8)*Assumptions!$E$14 -> 0 | ... L9: =MAX(0,L8)*Assumptions!$E$14 -> 5.5330509
A10: NOPAT | C10: =C8-C9 -> -86.255582 | D10: =D8-D9 -> -89.743219 | E10: =E8-E9 -> -89.758924 | F10: =F8-F9 -> -85.567031 | G10: =G8-G9 -> -76.641335 | H10: =H8-H9 -> -62.763201 | I10: =I8-I9 -> -44.100258 | J10: =J8-J9 -> -21.250191 | ... L10: =L8-L9 -> 27.014307
A11: Reinvestment | C11: =(C7-B7)*Assumptions!$E$15 -> 2.8569553 | D11: =(D7-C7)*Assumptions!$E$15 -> 3.1277557 | E11: =(E7-D7)*Assumptions!$E$15 -> 3.325184 | F11: =(F7-E7)*Assumptions!$E$15 -> 3.4211146 | G11: =(G7-F7)*Assumptions!$E$15 -> 3.3899269 | H11: =(H7-G7)*Assumptions!$E$15 -> 3.2117305 | I11: =(I7-H7)*Assumptions!$E$15 -> 2.8755571 | J11: =(J7-I7)*Assumptions!$E$15 -> 2.3820462 | ... L11: =(L7-K7)*Assumptions!$E$15 -> 0.9922975
A12: Free cash flow | C12: =C10-C11 -> -89.112538 | D12: =D10-D11 -> -92.870975 | E12: =E10-E11 -> -93.084108 | F12: =F10-F11 -> -88.988146 | G12: =G10-G11 -> -80.031262 | H12: =H10-H11 -> -65.974931 | I12: =I10-I11 -> -46.975815 | J12: =J10-J11 -> -23.632238 | ... L12: =L10-L11 -> 26.02201
A13: Year fraction | C13: =Assumptions!$B$22 -> 0.5041 | D13: 1 | E13: 1 | F13: 1 | G13: 1 | H13: 1 | I13: 1 | J13: 1 | K13: 1 | L13: 1
A14: Discount time (mid-period) | C14: =C13/2 -> 0.25205 | D14: =C14+C13/2+D13/2 -> 1.0041 | E14: =D14+D13/2+E13/2 -> 2.0041 | F14: =E14+E13/2+F13/2 -> 3.0041 | G14: =F14+F13/2+G13/2 -> 4.0041 | H14: =G14+G13/2+H13/2 -> 5.0041 | I14: =H14+H13/2+I13/2 -> 6.0041 | J14: =I14+I13/2+J13/2 -> 7.0041 | K14: =J14+J13/2+K13/2 -> 8.0041 | L14: =K14+K13/2+L13/2 -> 9.0041
A15: Discount factor | C15: =1/(1+Assumptions!$E$10)^C14 -> 0.97074912 | D15: =1/(1+Assumptions!$E$10)^D14 -> 0.88845974 | E15: =1/(1+Assumptions!$E$10)^E14 -> 0.78974199 | F15: =1/(1+Assumptions!$E$10)^F14 -> 0.70199288 | G15: =1/(1+Assumptions!$E$10)^G14 -> 0.62399367 | H15: =1/(1+Assumptions!$E$10)^H14 -> 0.55466104 | I15: =1/(1+Assumptions!$E$10)^I14 -> 0.49303204 | J15: =1/(1+Assumptions!$E$10)^J14 -> 0.4382507 | ... L15: =1/(1+Assumptions!$E$10)^L14 -> 0.34627216
A16: PV of free cash flow | C16: =C12*C13*C15 -> -43.607633 | D16: =D12*D13*D15 -> -82.512122 | E16: =E12*E13*E15 -> -73.512429 | F16: =F12*F13*F15 -> -62.469045 | G16: =G12*G13*G15 -> -49.939001 | H16: =H12*H13*H15 -> -36.593724 | I16: =I12*I13*I15 -> -23.160582 | J16: =J12*J13*J15 -> -10.356845 | ... L16: =L12*L13*L15 -> 9.0106974
A19: PV of forecast free cash flow | B19: =SUM(C16:L16) -> -372.28047
A20: Terminal free cash flow (year 11) | B20: =L10*(1+Assumptions!$E$11)-L7*Assumptions!$E$11*Assumptions!$E$15 -> 26.67256
A21: Terminal value | B21: =B20/(Assumptions!$E$10-Assumptions!$E$11) -> 266.7256
A22: PV of terminal value | B22: =B21/(1+Assumptions!$E$10)^(L14+0.5) -> 87.077512
A23: Enterprise value | B23: =B19+B22 -> -285.20296
A24: Cash & investments | B24: =Main!C7 -> 160.08
A25: Debt | B25: =Main!C8 -> 0
A26: Equity value | B26: =B23+B24-B25 -> -125.12296
A27: Shares (mm) | B27: =Main!C4 -> 294.75875
A28: NPV / share | B28: =B26/B27 -> -0.42449278
A29: Price | B29: =Main!C3 -> 0.6366
A30: Upside | B30: =B28/B29-1 -> -1.6668124
A31: Terminal value, % of EV | B31: =IFERROR(B22/B23,0) -> -0.3053177
