Workbook

Sheet Main
B2: MannKind Corporation
B3: Price | C3: =INDEX([1]Pharma!$F$1:$F$1000,MATCH("MNKD",[1]Pharma!$B$1:$B$1000,0)) -> 3.1
B4: Shares | C4: 321.54064
B5: Market Cap. | C5: =C3*C4 -> 996.77597
B7: Cash | C7: =52.929+58.201 -> 111.13
B8: Debt | C8: 319.085
B9: Enterprise V. | C9: =C5-C7+C8 -> 1204.731
B11: NPV / Share | C11: =NPV!B28 -> 2.9962755
B12: Upside | C12: =IFERROR(C11/C3-1,"") -> -0.033459508
B13: Cash / Share | C13: =IFERROR((C7-C8)/C4,"") -> -0.64674562
B14: Scenario | C14: =Assumptions!C4 -> Base
B15: Model | C15: DCF

Sheet Yearly Model
B1: 1992 | C1: 1993 | D1: 1994 | E1: 1995 | F1: 1996 | G1: 1997 | H1: 1998 | I1: 1999 | J1: 2000 | K1: 2001 | L1: 2002 | M1: 2003 | N1: 2004 | O1: 2005 | P1: 2006 | Q1: 2007 | R1: 2008 | S1: 2009 | T1: 2010 | U1: 2011 | V1: 2012 | W1: 2013 | X1: 2014 | Y1: 2015 | Z1: 2016 | AA1: 2017 | AB1: 2018 | AC1: 2019 | AD1: 2020 | AE1: 2021 | AF1: 2022 | AG1: 2023 | AH1: 2024 | AI1: 2025 | AJ1: 2026 | AK1: 2027 | AL1: 2028 | AM1: 2029 | AN1: 2030 | AO1: 2031 | AP1: 2032 | AQ1: 2033 | AR1: 2034 | AS1: 2035
A2: Revenue | B2: 0 | C2: 0 | D2: 0 | E2: 0 | F2: 0 | G2: 0 | H2: 0 | I2: 0 | J2: 0 | K2: 0 | L2: 0 | M2: 0 | N2: 0 | O2: 0 | P2: 0 | Q2: 0 | R2: 0 | S2: 0 | T2: 0.093 | U2: 0.05 | V2: 0.035 | W2: 0 | X2: 0 | Y2: 0 | Z2: 174.758 | AA2: 11.745 | AB2: 27.859 | AC2: 63.038 | AD2: 65.144 | AE2: 75.442 | AF2: 99.77 | AG2: 198.962 | AH2: 285.504 | AI2: 348.966 | AJ2: =AI2*(1+NPV!C5) -> 449.60779 | AK2: =AJ2*(1+NPV!D5) -> 566.11616 | AL2: =AK2*(1+NPV!E5) -> 696.2474 | AM2: =AL2*(1+NPV!F5) -> 835.91462 | AN2: =AM2*(1+NPV!G5) -> 979.13466 | AO2: =AN2*(1+NPV!H5) -> 1118.2371 | AP2: =AO2*(1+NPV!I5) -> 1244.3742 | AQ2: =AP2*(1+NPV!J5) -> 1348.3209 | ... AS2: =AR2*(1+NPV!L5) -> 1457.0271
A3: Cost of Sales | B3: 0 | C3: 0 | D3: 0 | E3: 0 | F3: 0 | G3: 0 | H3: 0 | I3: 0 | J3: 0 | K3: 0 | L3: 0 | M3: 0 | N3: 0 | O3: 0 | P3: 0 | Q3: 0 | R3: 0 | S3: 0 | T3: 0 | U3: 0 | V3: 0 | W3: 0 | X3: 0 | Y3: 64.745 | Z3: 17.121 | AA3: 17.228 | AB3: 19.392 | AC3: 20.078 | AD3: 15.084 | AE3: 16.833 | AF3: 16.003 | AG3: 20.863 | AH3: 17.429 | AI3: 26.8 | AJ3: =AJ2*(1-Assumptions!$B$19) -> 34.529879 | AK3: =AK2*(1-Assumptions!$B$19) -> 43.477721 | AL3: =AL2*(1-Assumptions!$B$19) -> 53.4718 | AM3: =AM2*(1-Assumptions!$B$19) -> 64.198243 | AN3: =AN2*(1-Assumptions!$B$19) -> 75.197542 | AO3: =AO2*(1-Assumptions!$B$19) -> 85.880606 | AP3: =AP2*(1-Assumptions!$B$19) -> 95.567939 | AQ3: =AQ2*(1-Assumptions!$B$19) -> 103.55105 | ... AS3: =AS2*(1-Assumptions!$B$19) -> 111.89968
A4: Gross Margin | B4: =B2-B3 -> 0 | C4: =C2-C3 -> 0 | D4: =D2-D3 -> 0 | E4: =E2-E3 -> 0 | F4: =F2-F3 -> 0 | G4: =G2-G3 -> 0 | H4: =H2-H3 -> 0 | I4: =I2-I3 -> 0 | ... AS4: =AS2-AS3 -> 1345.1274
A5: Research & Dev. | B5: 0 | C5: 0 | D5: 0 | E5: 0 | F5: 0 | G5: 0 | H5: 0 | I5: 0 | J5: 0 | K5: 0 | L5: 0 | M5: 0 | N5: 0 | O5: 0 | P5: 0 | Q5: 0 | R5: 0 | S5: 156.331 | T5: 112.279 | U5: 99.959 | V5: 101.522 | W5: 109.719 | X5: 100.244 | Y5: 29.674 | Z5: 14.917 | AA5: 14.118 | AB5: 8.737 | AC5: 6.9 | AD5: 6.248 | AE5: 12.312 | AF5: 19.721 | AG5: 31.283 | AH5: 45.893 | AI5: 66.348 | AJ5: =AJ7*Assumptions!$B$20 -> 92.857517 | AK5: =AK7*Assumptions!$B$20 -> 114.57823 | AL5: =AL7*Assumptions!$B$20 -> 138.03588 | AM5: =AM7*Assumptions!$B$20 -> 162.26808 | AN5: =AN7*Assumptions!$B$20 -> 186.01978 | AO5: =AO7*Assumptions!$B$20 -> 207.82135 | AP5: =AP7*Assumptions!$B$20 -> 226.11618 | AQ5: =AQ7*Assumptions!$B$20 -> 239.42703 | ... AS5: =AS7*Assumptions!$B$20 -> 246.67631
A6: SG&A & Other | B6: 0.911 | C6: 1.175 | D6: 1.156 | E6: 2.815 | F6: 2.57 | G6: 2.28 | H6: 3.331 | I6: 5.679 | J6: 24.661 | K6: 48.245 | L6: 206.265 | M6: 65.879 | N6: 75.992 | O6: 114.338 | P6: 230.548 | Q6: 293.19 | R6: 303.039 | S6: 53.447 | T6: 40.312 | U6: 40.63 | V6: 45.473 | W6: 59.682 | X6: 79.383 | Y6: 250.236 | Z6: 75.46 | AA6: 88.588 | AB6: 76.325 | AC6: 80.657 | AD6: 91.725 | AE6: 93.319 | AF6: 128.156 | AG6: 138.138 | AH6: 149.595 | AI6: 217.017 | AJ6: =AJ7-AJ5 -> 303.79997 | AK6: =AK7-AK5 -> 374.86316 | AL6: =AL7-AL5 -> 451.60907 | AM6: =AM7-AM5 -> 530.88904 | AN6: =AN7-AN5 -> 608.59696 | AO6: =AO7-AO5 -> 679.92469 | AP6: =AP7-AP5 -> 739.77951 | AQ6: =AQ7-AQ5 -> 783.32833 | ... AS6: =AS7-AS5 -> 807.04565
A7: Operating Expense | B7: =SUM(B5:B6) -> 0.911 | C7: =SUM(C5:C6) -> 1.175 | D7: =SUM(D5:D6) -> 1.156 | E7: =SUM(E5:E6) -> 2.815 | F7: =SUM(F5:F6) -> 2.57 | G7: =SUM(G5:G6) -> 2.28 | H7: =SUM(H5:H6) -> 3.331 | I7: =SUM(I5:I6) -> 5.679 | ... AI7: =SUM(AI5:AI6) -> 283.365 | AJ7: =AJ4-AJ2*NPV!C6 -> 396.65748 | AK7: =AK4-AK2*NPV!D6 -> 489.44139 | AL7: =AL4-AL2*NPV!E6 -> 589.64496 | AM7: =AM4-AM2*NPV!F6 -> 693.15712 | AN7: =AN4-AN2*NPV!G6 -> 794.61673 | AO7: =AO4-AO2*NPV!H6 -> 887.74604 | AP7: =AP4-AP2*NPV!I6 -> 965.8957 | AQ7: =AQ4-AQ2*NPV!J6 -> 1022.7554 | ... AS7: =AS4-AS2*NPV!L6 -> 1053.722
A8: Operating Income | B8: =B4-B7 -> -0.911 | C8: =C4-C7 -> -1.175 | D8: =D4-D7 -> -1.156 | E8: =E4-E7 -> -2.815 | F8: =F4-F7 -> -2.57 | G8: =G4-G7 -> -2.28 | H8: =H4-H7 -> -3.331 | I8: =I4-I7 -> -5.679 | ... AS8: =AS4-AS7 -> 291.40541
A9: Interest & Other | B9: 0 | C9: 0 | D9: 0 | E9: 0 | F9: 0 | G9: 0 | H9: 0 | I9: 0 | J9: 0 | K9: 0 | L9: 0 | M9: 0 | N9: 0 | O9: 0 | P9: 0 | Q9: 0 | R9: 0 | S9: -10.326 | T9: -18.062 | U9: -20.265 | V9: -22.814 | W9: -22.089 | X9: -18.755 | Y9: -23.79 | Z9: 58.404 | AA9: -9.093 | AB9: -10.14 | AC9: -7.306 | AD9: -9.545 | AE9: -33.904 | AF9: -23.29 | AG9: -19.055 | AH9: -42.069 | AI9: -37.394 | AJ9: 0 | AK9: 0 | AL9: 0 | AM9: 0 | AN9: 0 | AO9: 0 | AP9: 0 | AQ9: 0 | AR9: 0 | AS9: 0
A10: Pretax | B10: =B8+B9 -> -0.911 | C10: =C8+C9 -> -1.175 | D10: =D8+D9 -> -1.156 | E10: =E8+E9 -> -2.815 | F10: =F8+F9 -> -2.57 | G10: =G8+G9 -> -2.28 | H10: =H8+H9 -> -3.331 | I10: =I8+I9 -> -5.679 | ... AS10: =AS8+AS9 -> 291.40541
A11: Taxes | B11: 0 | C11: 0 | D11: 0 | E11: 0 | F11: 0 | G11: 0 | H11: 0 | I11: 0 | J11: 0 | K11: 0 | L11: 0 | M11: 0 | N11: 0 | O11: 0 | P11: 0 | Q11: 0 | R11: 0 | S11: 0 | T11: 0 | U11: 0 | V11: -0.408 | W11: 0 | X11: 0 | Y11: 0 | Z11: 0 | AA11: 0.051 | AB11: 0.24 | AC11: 0 | AD11: -0.218 | AE11: 0 | AF11: 0 | AG11: 1.561 | AH11: 2.93 | AI11: -4.456 | AJ11: =MAX(0,AJ10)*Assumptions!$E$14 -> 3.1314733 | AK11: =MAX(0,AK10)*Assumptions!$E$14 -> 5.6434988 | AL11: =MAX(0,AL10)*Assumptions!$E$14 -> 9.0322086 | AM11: =MAX(0,AM10)*Assumptions!$E$14 -> 13.355074 | AN11: =MAX(0,AN10)*Assumptions!$E$14 -> 18.584465 | AO11: =MAX(0,AO10)*Assumptions!$E$14 -> 24.583771 | AP11: =MAX(0,AP10)*Assumptions!$E$14 -> 31.094796 | AQ11: =MAX(0,AQ10)*Assumptions!$E$14 -> 37.742469 | ... AS11: =MAX(0,AS10)*Assumptions!$E$14 -> 49.53892
A12: Net Income | B12: -0.911 | C12: -1.175 | D12: -1.156 | E12: -2.815 | F12: -2.57 | G12: -2.28 | H12: -3.331 | I12: -5.679 | J12: -24.661 | K12: -48.245 | L12: -206.265 | M12: -65.879 | N12: -75.992 | O12: -114.338 | P12: -230.548 | Q12: -293.19 | R12: -303.039 | S12: -220.104 | T12: -170.56 | U12: -160.804 | V12: -169.366 | W12: -191.49 | X12: -198.382 | Y12: -368.445 | Z12: 125.664 | AA12: -117.333 | AB12: -86.975 | AC12: -51.903 | AD12: -57.24 | AE12: -80.926 | AF12: -87.4 | AG12: -11.938 | AH12: 27.588 | AI12: 5.863 | AJ12: =AJ10-AJ11 -> 15.288958 | AK12: =AK10-AK11 -> 27.553553 | AL12: =AL10-AL11 -> 44.09843 | AM12: =AM10-AM11 -> 65.204183 | AN12: =AN10-AN11 -> 90.73592 | AO12: =AO10-AO11 -> 120.02665 | AP12: =AP10-AP11 -> 151.81577 | AQ12: =AQ10-AQ11 -> 184.27205 | ... AS12: =AS10-AS11 -> 241.86649
A13: Earnings per Share | B13: =IFERROR(B12/B14,0) -> 0 | C13: =IFERROR(C12/C14,0) -> 0 | D13: =IFERROR(D12/D14,0) -> 0 | E13: =IFERROR(E12/E14,0) -> 0 | F13: =IFERROR(F12/F14,0) -> 0 | G13: =IFERROR(G12/G14,0) -> 0 | H13: =IFERROR(H12/H14,0) -> 0 | I13: =IFERROR(I12/I14,0) -> 0 | ... AS13: =IFERROR(AS12/AS14,0) -> 0.75221127
A14: Shares | V14: 180.855 | W14: 299.591 | X14: 77.045 | Y14: 81.233 | Z14: 92.085 | AA14: 104.245 | AB14: 144.136 | AC14: 195.584 | AD14: 222.585 | AE14: 249.244 | AF14: 257.092 | AG14: 267.014 | AH14: 283.844 | AI14: 314.112 | AJ14: =Main!$C$4 -> 321.54064 | AK14: =Main!$C$4 -> 321.54064 | AL14: =Main!$C$4 -> 321.54064 | AM14: =Main!$C$4 -> 321.54064 | AN14: =Main!$C$4 -> 321.54064 | AO14: =Main!$C$4 -> 321.54064 | AP14: =Main!$C$4 -> 321.54064 | AQ14: =Main!$C$4 -> 321.54064 | ... AS14: =Main!$C$4 -> 321.54064
A16: Revenue Change | C16: =IFERROR(C2/B2-1,"") | D16: =IFERROR(D2/C2-1,"") | E16: =IFERROR(E2/D2-1,"") | F16: =IFERROR(F2/E2-1,"") | G16: =IFERROR(G2/F2-1,"") | H16: =IFERROR(H2/G2-1,"") | I16: =IFERROR(I2/H2-1,"") | J16: =IFERROR(J2/I2-1,"") | ... AS16: =IFERROR(AS2/AR2-1,"") -> 0.025
A17: Gross Margin | B17: =IFERROR(B4/B2,"") | C17: =IFERROR(C4/C2,"") | D17: =IFERROR(D4/D2,"") | E17: =IFERROR(E4/E2,"") | F17: =IFERROR(F4/F2,"") | G17: =IFERROR(G4/G2,"") | H17: =IFERROR(H4/H2,"") | I17: =IFERROR(I4/I2,"") | ... AS17: =IFERROR(AS4/AS2,"") -> 0.9232
A18: Operating Margin | B18: =IFERROR(B8/B2,"") | C18: =IFERROR(C8/C2,"") | D18: =IFERROR(D8/D2,"") | E18: =IFERROR(E8/E2,"") | F18: =IFERROR(F8/F2,"") | G18: =IFERROR(G8/G2,"") | H18: =IFERROR(H8/H2,"") | I18: =IFERROR(I8/I2,"") | ... AS18: =IFERROR(AS8/AS2,"") -> 0.2
A19: Actual / Estimate | B19: A | C19: A | D19: A | E19: A | F19: A | G19: A | H19: A | I19: A | J19: A | K19: A | L19: A | M19: A | N19: A | O19: A | P19: A | Q19: A | R19: A | S19: A | T19: A | U19: A | V19: A | W19: A | X19: A | Y19: A | Z19: A | AA19: A | AB19: A | AC19: A | AD19: A | AE19: A | AF19: A | AG19: A | AH19: A | AI19: A | AJ19: E | AK19: E | AL19: E | AM19: E | AN19: E | AO19: E | AP19: E | AQ19: E | AR19: E | AS19: E

Sheet Quarterly Model

Sheet Assumptions
A1: MannKind Corporation: basic DCF assumptions
A2: Blue = input, black = formula, green = link. $mm unless noted.
A4: Scenario (1 Bear, 2 Base, 3 Bull) | B4: 2 | C4: =CHOOSE($B$4,"Bear","Base","Bull") -> Base
A6: Discount rate override (blank = scenario)
A7: Terminal growth override (blank = scenario)
A9: Parameter | B9: Bear | C9: Base | D9: Bull | E9: Live
A10: Discount rate | B10: 0.135 | C10: 0.125 | D10: 0.115 | E10: =IF(ISNUMBER($B$6),$B$6,CHOOSE($B$4,B10,C10,D10)) -> 0.125
A11: Terminal growth | B11: 0.02 | C11: 0.025 | D11: 0.03 | E11: =IF(ISNUMBER($B$7),$B$7,CHOOSE($B$4,B11,C11,D11)) -> 0.025
A12: Revenue growth, first forecast year | B12: 0.2384 | C12: 0.2884 | D12: 0.3384 | E12: =CHOOSE($B$4,B12,C12,D12) -> 0.2884
A13: Operating margin, year 10 | B13: 0.15 | C13: 0.2 | D13: 0.25 | E13: =CHOOSE($B$4,B13,C13,D13) -> 0.2
A14: Tax rate on operating income | B14: 0.17 | C14: 0.17 | D14: 0.17 | E14: =CHOOSE($B$4,B14,C14,D14) -> 0.17
A15: Reinvestment, % of revenue increase | B15: 0.25 | C15: 0.25 | D15: 0.25 | E15: =CHOOSE($B$4,B15,C15,D15) -> 0.25
A17: Single inputs
A18: Starting operating margin (TTM) | B18: 0.0233
A19: Gross margin (forecast) | B19: 0.9232
A20: R&D share of operating expense (forecast) | B20: 0.2341
A21: Forecast years | B21: 10
A22: First forecast year, fraction after balance sheet date | B22: 0.5041
A23: Balance sheet date | B23: 46203
A24: Reporting currency per USD (USD) | B24: 1
A25: Base revenue, FY2025 | B25: ='Yearly Model'!AI2 -> 348.966
A27: Scenario summary
A28: Scenario | B28: Enterprise value | C28: Equity value | D28: NPV / share | E28: Upside
A29: Live | B29: =NPV!B23 -> 1171.3793 | C29: =NPV!B26 -> 963.42434 | D29: =NPV!B28 -> 2.9962755 | E29: =NPV!B30 -> -0.033459508
A30: 1 | B30: 587.78822 | C30: 379.83322 | D30: 1.1812915 | E30: -0.61893823
A31: 2 | B31: 1171.3793 | C31: 963.42434 | D31: 2.9962755 | E31: -0.033459508
A32: 3 | B32: 2221.089 | C32: 2013.134 | D32: 6.2609006 | E32: 1.0196454
A35: NPV / share: discount rate (rows) x terminal growth (columns)
A36: =NPV!B28 -> 2.9962755 | B36: 0.015 | C36: 0.02 | D36: 0.025 | E36: 0.03 | F36: 0.035
A37: 0.105 | B37: 3.779424 | C37: 4.0350387 | D37: 4.3227545 | E37: 4.6489939 | F37: 5.0220147
A38: 0.115 | B38: 3.1659918 | C38: 3.3619786 | D38: 3.5798647 | E38: 3.8235165 | F38: 4.0977673
A39: 0.125 | B39: 2.673732 | C39: 2.8272752 | D39: 2.9962755 | E39: 3.1831752 | F39: 3.3909591
A40: 0.135 | B40: 2.2716498 | C40: 2.394097 | D40: 2.5277628 | E40: 2.6742513 | F40: 2.8354874
A41: 0.145 | B41: 1.9383481 | C41: 2.0374626 | D41: 2.1449112 | E41: 2.2617821 | F41: 2.3893615

Sheet NPV
A1: MannKind Corporation: free-cash-flow DCF ($mm)
A3: Fiscal year | B3: ='Yearly Model'!AI1 -> 2025 | C3: ='Yearly Model'!AJ1 -> 2026 | D3: ='Yearly Model'!AK1 -> 2027 | E3: ='Yearly Model'!AL1 -> 2028 | F3: ='Yearly Model'!AM1 -> 2029 | G3: ='Yearly Model'!AN1 -> 2030 | H3: ='Yearly Model'!AO1 -> 2031 | I3: ='Yearly Model'!AP1 -> 2032 | ... L3: ='Yearly Model'!AS1 -> 2035
A4: Period | B4: Actual | C4: 1 | D4: 2 | E4: 3 | F4: 4 | G4: 5 | H4: 6 | I4: 7 | J4: 8 | K4: 9 | L4: 10
A5: Revenue growth | C5: =Assumptions!$E$12+(Assumptions!$E$11-Assumptions!$E$12)*(C4-1)/(Assumptions!$B$21-1) -> 0.2884 | D5: =Assumptions!$E$12+(Assumptions!$E$11-Assumptions!$E$12)*(D4-1)/(Assumptions!$B$21-1) -> 0.25913333 | E5: =Assumptions!$E$12+(Assumptions!$E$11-Assumptions!$E$12)*(E4-1)/(Assumptions!$B$21-1) -> 0.22986667 | F5: =Assumptions!$E$12+(Assumptions!$E$11-Assumptions!$E$12)*(F4-1)/(Assumptions!$B$21-1) -> 0.2006 | G5: =Assumptions!$E$12+(Assumptions!$E$11-Assumptions!$E$12)*(G4-1)/(Assumptions!$B$21-1) -> 0.17133333 | H5: =Assumptions!$E$12+(Assumptions!$E$11-Assumptions!$E$12)*(H4-1)/(Assumptions!$B$21-1) -> 0.14206667 | I5: =Assumptions!$E$12+(Assumptions!$E$11-Assumptions!$E$12)*(I4-1)/(Assumptions!$B$21-1) -> 0.1128 | J5: =Assumptions!$E$12+(Assumptions!$E$11-Assumptions!$E$12)*(J4-1)/(Assumptions!$B$21-1) -> 0.083533333 | ... L5: =Assumptions!$E$12+(Assumptions!$E$11-Assumptions!$E$12)*(L4-1)/(Assumptions!$B$21-1) -> 0.025
A6: Operating margin | B6: =IFERROR(B8/B7,0) -> 0.11118848 | C6: =Assumptions!$B$18+(Assumptions!$E$13-Assumptions!$B$18)*C4/Assumptions!$B$21 -> 0.04097 | D6: =Assumptions!$B$18+(Assumptions!$E$13-Assumptions!$B$18)*D4/Assumptions!$B$21 -> 0.05864 | E6: =Assumptions!$B$18+(Assumptions!$E$13-Assumptions!$B$18)*E4/Assumptions!$B$21 -> 0.07631 | F6: =Assumptions!$B$18+(Assumptions!$E$13-Assumptions!$B$18)*F4/Assumptions!$B$21 -> 0.09398 | G6: =Assumptions!$B$18+(Assumptions!$E$13-Assumptions!$B$18)*G4/Assumptions!$B$21 -> 0.11165 | H6: =Assumptions!$B$18+(Assumptions!$E$13-Assumptions!$B$18)*H4/Assumptions!$B$21 -> 0.12932 | I6: =Assumptions!$B$18+(Assumptions!$E$13-Assumptions!$B$18)*I4/Assumptions!$B$21 -> 0.14699 | J6: =Assumptions!$B$18+(Assumptions!$E$13-Assumptions!$B$18)*J4/Assumptions!$B$21 -> 0.16466 | ... L6: =Assumptions!$B$18+(Assumptions!$E$13-Assumptions!$B$18)*L4/Assumptions!$B$21 -> 0.2
A7: Revenue | B7: ='Yearly Model'!AI2 -> 348.966 | C7: ='Yearly Model'!AJ2 -> 449.60779 | D7: ='Yearly Model'!AK2 -> 566.11616 | E7: ='Yearly Model'!AL2 -> 696.2474 | F7: ='Yearly Model'!AM2 -> 835.91462 | G7: ='Yearly Model'!AN2 -> 979.13466 | H7: ='Yearly Model'!AO2 -> 1118.2371 | I7: ='Yearly Model'!AP2 -> 1244.3742 | ... L7: ='Yearly Model'!AS2 -> 1457.0271
A8: Operating income | B8: ='Yearly Model'!AI8 -> 38.801 | C8: ='Yearly Model'!AJ8 -> 18.420431 | D8: ='Yearly Model'!AK8 -> 33.197052 | E8: ='Yearly Model'!AL8 -> 53.130639 | F8: ='Yearly Model'!AM8 -> 78.559256 | G8: ='Yearly Model'!AN8 -> 109.32039 | H8: ='Yearly Model'!AO8 -> 144.61042 | I8: ='Yearly Model'!AP8 -> 182.91056 | ... L8: ='Yearly Model'!AS8 -> 291.40541
A9: Tax on operating income | C9: =MAX(0,C8)*Assumptions!$E$14 -> 3.1314733 | D9: =MAX(0,D8)*Assumptions!$E$14 -> 5.6434988 | E9: =MAX(0,E8)*Assumptions!$E$14 -> 9.0322086 | F9: =MAX(0,F8)*Assumptions!$E$14 -> 13.355074 | G9: =MAX(0,G8)*Assumptions!$E$14 -> 18.584465 | H9: =MAX(0,H8)*Assumptions!$E$14 -> 24.583771 | I9: =MAX(0,I8)*Assumptions!$E$14 -> 31.094796 | J9: =MAX(0,J8)*Assumptions!$E$14 -> 37.742469 | ... L9: =MAX(0,L8)*Assumptions!$E$14 -> 49.53892
A10: NOPAT | C10: =C8-C9 -> 15.288958 | D10: =D8-D9 -> 27.553553 | E10: =E8-E9 -> 44.09843 | F10: =F8-F9 -> 65.204183 | G10: =G8-G9 -> 90.73592 | H10: =H8-H9 -> 120.02665 | I10: =I8-I9 -> 151.81577 | J10: =J8-J9 -> 184.27205 | ... L10: =L8-L9 -> 241.86649
A11: Reinvestment | C11: =(C7-B7)*Assumptions!$E$15 -> 25.160449 | D11: =(D7-C7)*Assumptions!$E$15 -> 29.127092 | E11: =(E7-D7)*Assumptions!$E$15 -> 32.532809 | F11: =(F7-E7)*Assumptions!$E$15 -> 34.916807 | G11: =(G7-F7)*Assumptions!$E$15 -> 35.80501 | H11: =(H7-G7)*Assumptions!$E$15 -> 34.775599 | I11: =(I7-H7)*Assumptions!$E$15 -> 31.534285 | J11: =(J7-I7)*Assumptions!$E$15 -> 25.986681 | ... L11: =(L7-K7)*Assumptions!$E$15 -> 8.8843113
A12: Free cash flow | C12: =C10-C11 -> -9.8714906 | D12: =D10-D11 -> -1.5735387 | E12: =E10-E11 -> 11.565621 | F12: =F10-F11 -> 30.287376 | G12: =G10-G11 -> 54.93091 | H12: =H10-H11 -> 85.251046 | I12: =I10-I11 -> 120.28148 | J12: =J10-J11 -> 158.28537 | ... L12: =L10-L11 -> 232.98218
A13: Year fraction | C13: =Assumptions!$B$22 -> 0.5041 | D13: 1 | E13: 1 | F13: 1 | G13: 1 | H13: 1 | I13: 1 | J13: 1 | K13: 1 | L13: 1
A14: Discount time (mid-period) | C14: =C13/2 -> 0.25205 | D14: =C14+C13/2+D13/2 -> 1.0041 | E14: =D14+D13/2+E13/2 -> 2.0041 | F14: =E14+E13/2+F13/2 -> 3.0041 | G14: =F14+F13/2+G13/2 -> 4.0041 | H14: =G14+G13/2+H13/2 -> 5.0041 | I14: =H14+H13/2+I13/2 -> 6.0041 | J14: =I14+I13/2+J13/2 -> 7.0041 | K14: =J14+J13/2+K13/2 -> 8.0041 | L14: =K14+K13/2+L13/2 -> 9.0041
A15: Discount factor | C15: =1/(1+Assumptions!$E$10)^C14 -> 0.97074912 | D15: =1/(1+Assumptions!$E$10)^D14 -> 0.88845974 | E15: =1/(1+Assumptions!$E$10)^E14 -> 0.78974199 | F15: =1/(1+Assumptions!$E$10)^F14 -> 0.70199288 | G15: =1/(1+Assumptions!$E$10)^G14 -> 0.62399367 | H15: =1/(1+Assumptions!$E$10)^H14 -> 0.55466104 | I15: =1/(1+Assumptions!$E$10)^I14 -> 0.49303204 | J15: =1/(1+Assumptions!$E$10)^J14 -> 0.4382507 | ... L15: =1/(1+Assumptions!$E$10)^L14 -> 0.34627216
A16: PV of free cash flow | C16: =C12*C13*C15 -> -4.8306597 | D16: =D12*D13*D15 -> -1.3980258 | E16: =E12*E13*E15 -> 9.1338569 | F16: =F12*F13*F15 -> 21.261522 | G16: =G12*G13*G15 -> 34.27654 | H16: =H12*H13*H15 -> 47.285434 | I16: =I12*I13*I15 -> 59.302624 | J16: =J12*J13*J15 -> 69.368675 | ... L16: =L12*L13*L15 -> 80.675242
A19: PV of forecast free cash flow | B19: =SUM(C16:L16) -> 391.75053
A20: Terminal free cash flow (year 11) | B20: =L10*(1+Assumptions!$E$11)-L7*Assumptions!$E$11*Assumptions!$E$15 -> 238.80673
A21: Terminal value | B21: =B20/(Assumptions!$E$10-Assumptions!$E$11) -> 2388.0673
A22: PV of terminal value | B22: =B21/(1+Assumptions!$E$10)^(L14+0.5) -> 779.62881
A23: Enterprise value | B23: =B19+B22 -> 1171.3793
A24: Cash & investments | B24: =Main!C7 -> 111.13
A25: Debt | B25: =Main!C8 -> 319.085
A26: Equity value | B26: =B23+B24-B25 -> 963.42434
A27: Shares (mm) | B27: =Main!C4 -> 321.54064
A28: NPV / share | B28: =B26/B27 -> 2.9962755
A29: Price | B29: =Main!C3 -> 3.1
A30: Upside | B30: =B28/B29-1 -> -0.033459508
A31: Terminal value, % of EV | B31: =IFERROR(B22/B23,0) -> 0.66556476
