Workbook

Sheet Main
B2: BeOne Medicines AG
B3: Price | C3: =INDEX([1]Pharma!$F$1:$F$1000,MATCH("ONC",[1]Pharma!$B$1:$B$1000,0)) -> 384.5
B4: Shares | C4: =1478.124405/13 -> 113.70188
B5: Market Cap. | C5: =C3*C4 -> 43718.372
B7: Cash | C7: 5098.041
B8: Debt | C8: =190.896+71.182+882.163 -> 1144.241
B9: Enterprise V. | C9: =C5-C7+C8 -> 39764.572
B11: NPV / Share | C11: =NPV!B28 -> 433.27763
B12: Upside | C12: =IFERROR(C11/C3-1,"") -> 0.1268599
B13: Cash / Share | C13: =IFERROR((C7-C8)/C4,"") -> 34.773392
B14: Scenario | C14: =Assumptions!C4 -> Base
B15: Model | C15: DCF

Sheet Yearly Model
B1: 2014 | C1: 2015 | D1: 2016 | E1: 2017 | F1: 2018 | G1: 2019 | H1: 2020 | I1: 2021 | J1: 2022 | K1: 2023 | L1: 2024 | M1: 2025 | N1: 2026 | O1: 2027 | P1: 2028 | Q1: 2029 | R1: 2030 | S1: 2031 | T1: 2032 | U1: 2033 | V1: 2034 | W1: 2035
A2: Revenue | B2: 13.035 | C2: 8.816 | D2: 1.07 | E2: 238.387 | F2: 198.22 | G2: 428.212 | H2: 308.874 | I2: 1176.283 | J2: 1415.921 | K2: 2458.779 | L2: 3810.241 | M2: 5343.033 | N2: =M2*(1+NPV!C5) -> 7069.367 | O2: =N2*(1+NPV!D5) -> 9119.3263 | P2: =O2*(1+NPV!E5) -> 11461.676 | Q2: =P2*(1+NPV!F5) -> 14026.035 | R2: =Q2*(1+NPV!G5) -> 16699.553 | S2: =R2*(1+NPV!H5) -> 19329.547 | T2: =S2*(1+NPV!I5) -> 21733.498 | U2: =T2*(1+NPV!J5) -> 23716.559 | ... W2: =V2*(1+NPV!L5) -> 25722.394
A3: Cost of Sales | B3: 0 | C3: 0 | D3: 0 | E3: 4.974 | F3: 28.705 | G3: 71.19 | H3: 70.657 | I3: 164.906 | J3: 286.475 | K3: 0 | L3: 0 | M3: 0 | N3: =N2*(1-Assumptions!$B$19) -> 1430.1329 | O3: =O2*(1-Assumptions!$B$19) -> 1844.8397 | P3: =P2*(1-Assumptions!$B$19) -> 2318.697 | Q3: =Q2*(1-Assumptions!$B$19) -> 2837.4669 | R3: =R2*(1-Assumptions!$B$19) -> 3378.3196 | S3: =S2*(1-Assumptions!$B$19) -> 3910.3674 | T3: =T2*(1-Assumptions!$B$19) -> 4396.6867 | U3: =U2*(1-Assumptions!$B$19) -> 4797.8599 | ... W3: =W2*(1-Assumptions!$B$19) -> 5203.6403
A4: Gross Margin | B4: =B2-B3 -> 13.035 | C4: =C2-C3 -> 8.816 | D4: =D2-D3 -> 1.07 | E4: =E2-E3 -> 233.413 | F4: =F2-F3 -> 169.515 | G4: =G2-G3 -> 357.022 | H4: =H2-H3 -> 238.217 | I4: =I2-I3 -> 1011.377 | ... W4: =W2-W3 -> 20518.754
A5: Research & Dev. | B5: 21.862 | C5: 58.25 | D5: 98.033 | E5: 269.018 | F5: 679.005 | G5: 927.338 | H5: 1294.877 | I5: 1459.239 | J5: 1640.508 | K5: 1778.594 | L5: 1953.295 | M5: 2145.868 | N5: =N7*Assumptions!$B$20 -> 1989.735 | O5: =O7*Assumptions!$B$20 -> 2546.9688 | P5: =P7*Assumptions!$B$20 -> 3176.355 | Q5: =Q7*Assumptions!$B$20 -> 3856.6423 | R5: =R7*Assumptions!$B$20 -> 4555.6033 | S5: =S7*Assumptions!$B$20 -> 5231.2078 | T5: =T7*Assumptions!$B$20 -> 5834.7383 | U5: =U7*Assumptions!$B$20 -> 6315.7746 | ... W5: =W7*Assumptions!$B$20 -> 6738.5447
A6: SG&A & Other | B6: 6.93 | C6: 7.311 | D6: 20.097 | E6: 62.852 | F6: 196.279 | G6: 389.575 | H6: 601.022 | I6: 990.873 | J6: 1278.603 | K6: 1887.921 | L6: 2425.145 | M6: 2750.029 | N6: =N7-N5 -> 2549.9297 | O6: =O7-O5 -> 3264.0483 | P6: =P7-P5 -> 4070.6334 | Q6: =Q7-Q5 -> 4942.4504 | R6: =R7-R5 -> 5838.1984 | S6: =S7-S5 -> 6704.0142 | T6: =T7-T5 -> 7477.4641 | U6: =U7-U5 -> 8093.9325 | ... W6: =W7-W5 -> 8635.7302
A7: Operating Expense | B7: =SUM(B5:B6) -> 28.792 | C7: =SUM(C5:C6) -> 65.561 | D7: =SUM(D5:D6) -> 118.13 | E7: =SUM(E5:E6) -> 331.87 | F7: =SUM(F5:F6) -> 875.284 | G7: =SUM(G5:G6) -> 1316.913 | H7: =SUM(H5:H6) -> 1895.899 | I7: =SUM(I5:I6) -> 2450.112 | ... M7: =SUM(M5:M6) -> 4895.897 | N7: =N4-N2*NPV!C6 -> 4539.6647 | O7: =O4-O2*NPV!D6 -> 5811.0171 | P7: =P4-P2*NPV!E6 -> 7246.9884 | Q7: =Q4-Q2*NPV!F6 -> 8799.0927 | R7: =R4-R2*NPV!G6 -> 10393.802 | S7: =S4-S2*NPV!H6 -> 11935.222 | T7: =T4-T2*NPV!I6 -> 13312.202 | U7: =U4-U2*NPV!J6 -> 14409.707 | ... W7: =W4-W2*NPV!L6 -> 15374.275
A8: Operating Income | B8: =B4-B7 -> -15.757 | C8: =C4-C7 -> -56.745 | D8: =D4-D7 -> -117.06 | E8: =E4-E7 -> -98.457 | F8: =F4-F7 -> -705.769 | G8: =G4-G7 -> -959.891 | H8: =H4-H7 -> -1657.682 | I8: =I4-I7 -> -1438.735 | ... W8: =W4-W7 -> 5144.4788
A9: Interest & Other | B9: -2.521 | C9: -0.357 | D9: -2.103 | E9: 7.587 | F9: 16.204 | G9: 18.255 | H9: 43.105 | I9: 0.147 | J9: -171.372 | K9: 381.9 | L9: 35.198 | M9: -30.282 | N9: 0 | O9: 0 | P9: 0 | Q9: 0 | R9: 0 | S9: 0 | T9: 0 | U9: 0 | V9: 0 | W9: 0
A10: Pretax | B10: =B8+B9 -> -18.278 | C10: =C8+C9 -> -57.102 | D10: =D8+D9 -> -119.163 | E10: =E8+E9 -> -90.87 | F10: =F8+F9 -> -689.565 | G10: =G8+G9 -> -941.636 | H10: =H8+H9 -> -1614.577 | I10: =I8+I9 -> -1438.588 | ... W10: =W8+W9 -> 5144.4788
A11: Taxes | B11: 0 | C11: 0 | D11: 0.054 | E11: 2.235 | F11: -15.796 | G11: 6.992 | H11: 10.397 | I11: 19.228 | J11: 42.778 | K11: 55.872 | L11: 111.785 | M11: 129.921 | N11: =MAX(0,N10)*Assumptions!$E$14 -> 186.92679 | O11: =MAX(0,O10)*Assumptions!$E$14 -> 248.78981 | P11: =MAX(0,P10)*Assumptions!$E$14 -> 322.31837 | Q11: =MAX(0,Q10)*Assumptions!$E$14 -> 406.2108 | R11: =MAX(0,R10)*Assumptions!$E$14 -> 497.66338 | S11: =MAX(0,S10)*Assumptions!$E$14 -> 592.27278 | T11: =MAX(0,T10)*Assumptions!$E$14 -> 684.18357 | U11: =MAX(0,U10)*Assumptions!$E$14 -> 766.52868 | ... W11: =MAX(0,W10)*Assumptions!$E$14 -> 874.56139
A12: Net Income | B12: -18.278 | C12: -57.102 | D12: -119.217 | E12: -93.105 | F12: -673.769 | G12: -948.628 | H12: -1624.974 | I12: -1457.816 | J12: -2003.815 | K12: -881.708 | L12: -644.786 | M12: 286.933 | N12: =N10-N11 -> 912.64255 | O12: =O10-O11 -> 1214.6797 | P12: =P10-P11 -> 1573.6721 | Q12: =Q10-Q11 -> 1983.2645 | R12: =R10-R11 -> 2429.7683 | S12: =S10-S11 -> 2891.6848 | T12: =T10-T11 -> 3340.4257 | U12: =U10-U11 -> 3742.4636 | ... W12: =W10-W11 -> 4269.9174
A13: Earnings per Share | B13: =IFERROR(B12/B14,0) -> -0.18303992 | C13: =IFERROR(C12/C14,0) -> -0.51630695 | D13: =IFERROR(D12/D14,0) -> -0.29537014 | E13: =IFERROR(E12/E14,0) -> -0.17140569 | F13: =IFERROR(F12/F14,0) -> -0.93481132 | G13: =IFERROR(G12/G14,0) -> -1.2150977 | H13: =IFERROR(H12/H14,0) -> -1.4974897 | I13: =IFERROR(I12/I14,0) -> -1.2085922 | ... W13: =IFERROR(W12/W14,0) -> 37.553623
A14: Shares | B14: 99.858 | C14: 110.597 | D14: 403.619 | E14: 543.185 | F14: 720.754 | G14: 780.701 | H14: 1085.132 | I14: 1206.21 | J14: 1340.73 | K14: 1357.035 | L14: 1368.747 | M14: 1474.83 | N14: =Main!$C$4 -> 113.70188 | O14: =Main!$C$4 -> 113.70188 | P14: =Main!$C$4 -> 113.70188 | Q14: =Main!$C$4 -> 113.70188 | R14: =Main!$C$4 -> 113.70188 | S14: =Main!$C$4 -> 113.70188 | T14: =Main!$C$4 -> 113.70188 | U14: =Main!$C$4 -> 113.70188 | ... W14: =Main!$C$4 -> 113.70188
A16: Revenue Change | C16: =IFERROR(C2/B2-1,"") -> -0.32366705 | D16: =IFERROR(D2/C2-1,"") -> -0.87862976 | E16: =IFERROR(E2/D2-1,"") -> 221.79159 | F16: =IFERROR(F2/E2-1,"") -> -0.16849493 | G16: =IFERROR(G2/F2-1,"") -> 1.1602866 | H16: =IFERROR(H2/G2-1,"") -> -0.27868906 | I16: =IFERROR(I2/H2-1,"") -> 2.808294 | J16: =IFERROR(J2/I2-1,"") -> 0.20372478 | ... W16: =IFERROR(W2/V2-1,"") -> 0.025
A17: Gross Margin | B17: =IFERROR(B4/B2,"") -> 1 | C17: =IFERROR(C4/C2,"") -> 1 | D17: =IFERROR(D4/D2,"") -> 1 | E17: =IFERROR(E4/E2,"") -> 0.97913477 | F17: =IFERROR(F4/F2,"") -> 0.85518616 | G17: =IFERROR(G4/G2,"") -> 0.83375057 | H17: =IFERROR(H4/H2,"") -> 0.77124329 | I17: =IFERROR(I4/I2,"") -> 0.85980755 | ... W17: =IFERROR(W4/W2,"") -> 0.7977
A18: Operating Margin | B18: =IFERROR(B8/B2,"") -> -1.2088224 | C18: =IFERROR(C8/C2,"") -> -6.4365926 | D18: =IFERROR(D8/D2,"") -> -109.40187 | E18: =IFERROR(E8/E2,"") -> -0.41301329 | F18: =IFERROR(F8/F2,"") -> -3.5605338 | G18: =IFERROR(G8/G2,"") -> -2.2416256 | H18: =IFERROR(H8/H2,"") -> -5.3668551 | I18: =IFERROR(I8/I2,"") -> -1.2231198 | ... W18: =IFERROR(W8/W2,"") -> 0.2
A19: Actual / Estimate | B19: A | C19: A | D19: A | E19: A | F19: A | G19: A | H19: A | I19: A | J19: A | K19: A | L19: A | M19: A | N19: E | O19: E | P19: E | Q19: E | R19: E | S19: E | T19: E | U19: E | V19: E | W19: E

Sheet Quarterly Model

Sheet Assumptions
A1: BeOne Medicines AG: basic DCF assumptions
A2: Blue = input, black = formula, green = link. $mm unless noted.
A4: Scenario (1 Bear, 2 Base, 3 Bull) | B4: 2 | C4: =CHOOSE($B$4,"Bear","Base","Bull") -> Base
A6: Discount rate override (blank = scenario)
A7: Terminal growth override (blank = scenario)
A9: Parameter | B9: Bear | C9: Base | D9: Bull | E9: Live
A10: Discount rate | B10: 0.095 | C10: 0.085 | D10: 0.075 | E10: =IF(ISNUMBER($B$6),$B$6,CHOOSE($B$4,B10,C10,D10)) -> 0.085
A11: Terminal growth | B11: 0.02 | C11: 0.025 | D11: 0.03 | E11: =IF(ISNUMBER($B$7),$B$7,CHOOSE($B$4,B11,C11,D11)) -> 0.025
A12: Revenue growth, first forecast year | B12: 0.2731 | C12: 0.3231 | D12: 0.3731 | E12: =CHOOSE($B$4,B12,C12,D12) -> 0.3231
A13: Operating margin, year 10 | B13: 0.15 | C13: 0.2 | D13: 0.25 | E13: =CHOOSE($B$4,B13,C13,D13) -> 0.2
A14: Tax rate on operating income | B14: 0.17 | C14: 0.17 | D14: 0.17 | E14: =CHOOSE($B$4,B14,C14,D14) -> 0.17
A15: Reinvestment, % of revenue increase | B15: 0.25 | C15: 0.25 | D15: 0.25 | E15: =CHOOSE($B$4,B15,C15,D15) -> 0.25
A17: Single inputs
A18: Starting operating margin (TTM) | B18: 0.1506
A19: Gross margin (forecast) | B19: 0.7977
A20: R&D share of operating expense (forecast) | B20: 0.4383
A21: Forecast years | B21: 10
A22: First forecast year, fraction after balance sheet date | B22: 0.5041
A23: Balance sheet date | B23: 46203
A24: Reporting currency per USD (USD) | B24: 1
A25: Base revenue, FY2025 | B25: ='Yearly Model'!M2 -> 5343.033
A27: Scenario summary
A28: Scenario | B28: Enterprise value | C28: Equity value | D28: NPV / share | E28: Upside
A29: Live | B29: =NPV!B23 -> 45310.68 | C29: =NPV!B26 -> 49264.48 | D29: =NPV!B28 -> 433.27763 | E29: =NPV!B30 -> 0.1268599
A30: 1 | B30: 22523.956 | C30: 26477.756 | D30: 232.87 | E30: -0.3943563
A31: 2 | B31: 45310.68 | C31: 49264.48 | D31: 433.27763 | E31: 0.1268599
A32: 3 | B32: 93455.806 | C32: 97409.606 | D32: 856.71062 | E32: 1.228116
A35: NPV / share: discount rate (rows) x terminal growth (columns)
A36: =NPV!B28 -> 433.27763 | B36: 0.015 | C36: 0.02 | D36: 0.025 | E36: 0.03 | F36: 0.035
A37: 0.065 | B37: 551.63679 | C37: 604.74721 | D37: 671.10907 | E37: 756.40134 | F37: 870.08893
A38: 0.075 | B38: 452.04207 | C38: 486.51252 | D38: 527.85687 | E38: 578.36624 | F38: 641.47731
A39: 0.085 | B39: 381.69286 | C39: 405.5087 | D39: 433.27763 | E39: 466.07764 | F39: 505.41788
A40: 0.095 | B40: 329.562 | C40: 346.77897 | D40: 366.44215 | E40: 389.11591 | F40: 415.55278
A41: 0.105 | B41: 289.52877 | C41: 302.41092 | D41: 316.89208 | E41: 333.29199 | F41: 352.02168

Sheet NPV
A1: BeOne Medicines AG: free-cash-flow DCF ($mm)
A3: Fiscal year | B3: ='Yearly Model'!M1 -> 2025 | C3: ='Yearly Model'!N1 -> 2026 | D3: ='Yearly Model'!O1 -> 2027 | E3: ='Yearly Model'!P1 -> 2028 | F3: ='Yearly Model'!Q1 -> 2029 | G3: ='Yearly Model'!R1 -> 2030 | H3: ='Yearly Model'!S1 -> 2031 | I3: ='Yearly Model'!T1 -> 2032 | ... L3: ='Yearly Model'!W1 -> 2035
A4: Period | B4: Actual | C4: 1 | D4: 2 | E4: 3 | F4: 4 | G4: 5 | H4: 6 | I4: 7 | J4: 8 | K4: 9 | L4: 10
A5: Revenue growth | C5: =Assumptions!$E$12+(Assumptions!$E$11-Assumptions!$E$12)*(C4-1)/(Assumptions!$B$21-1) -> 0.3231 | D5: =Assumptions!$E$12+(Assumptions!$E$11-Assumptions!$E$12)*(D4-1)/(Assumptions!$B$21-1) -> 0.28997778 | E5: =Assumptions!$E$12+(Assumptions!$E$11-Assumptions!$E$12)*(E4-1)/(Assumptions!$B$21-1) -> 0.25685556 | F5: =Assumptions!$E$12+(Assumptions!$E$11-Assumptions!$E$12)*(F4-1)/(Assumptions!$B$21-1) -> 0.22373333 | G5: =Assumptions!$E$12+(Assumptions!$E$11-Assumptions!$E$12)*(G4-1)/(Assumptions!$B$21-1) -> 0.19061111 | H5: =Assumptions!$E$12+(Assumptions!$E$11-Assumptions!$E$12)*(H4-1)/(Assumptions!$B$21-1) -> 0.15748889 | I5: =Assumptions!$E$12+(Assumptions!$E$11-Assumptions!$E$12)*(I4-1)/(Assumptions!$B$21-1) -> 0.12436667 | J5: =Assumptions!$E$12+(Assumptions!$E$11-Assumptions!$E$12)*(J4-1)/(Assumptions!$B$21-1) -> 0.091244444 | ... L5: =Assumptions!$E$12+(Assumptions!$E$11-Assumptions!$E$12)*(L4-1)/(Assumptions!$B$21-1) -> 0.025
A6: Operating margin | B6: =IFERROR(B8/B7,0) -> 0.083685802 | C6: =Assumptions!$B$18+(Assumptions!$E$13-Assumptions!$B$18)*C4/Assumptions!$B$21 -> 0.15554 | D6: =Assumptions!$B$18+(Assumptions!$E$13-Assumptions!$B$18)*D4/Assumptions!$B$21 -> 0.16048 | E6: =Assumptions!$B$18+(Assumptions!$E$13-Assumptions!$B$18)*E4/Assumptions!$B$21 -> 0.16542 | F6: =Assumptions!$B$18+(Assumptions!$E$13-Assumptions!$B$18)*F4/Assumptions!$B$21 -> 0.17036 | G6: =Assumptions!$B$18+(Assumptions!$E$13-Assumptions!$B$18)*G4/Assumptions!$B$21 -> 0.1753 | H6: =Assumptions!$B$18+(Assumptions!$E$13-Assumptions!$B$18)*H4/Assumptions!$B$21 -> 0.18024 | I6: =Assumptions!$B$18+(Assumptions!$E$13-Assumptions!$B$18)*I4/Assumptions!$B$21 -> 0.18518 | J6: =Assumptions!$B$18+(Assumptions!$E$13-Assumptions!$B$18)*J4/Assumptions!$B$21 -> 0.19012 | ... L6: =Assumptions!$B$18+(Assumptions!$E$13-Assumptions!$B$18)*L4/Assumptions!$B$21 -> 0.2
A7: Revenue | B7: ='Yearly Model'!M2 -> 5343.033 | C7: ='Yearly Model'!N2 -> 7069.367 | D7: ='Yearly Model'!O2 -> 9119.3263 | E7: ='Yearly Model'!P2 -> 11461.676 | F7: ='Yearly Model'!Q2 -> 14026.035 | G7: ='Yearly Model'!R2 -> 16699.553 | H7: ='Yearly Model'!S2 -> 19329.547 | I7: ='Yearly Model'!T2 -> 21733.498 | ... L7: ='Yearly Model'!W2 -> 25722.394
A8: Operating income | B8: ='Yearly Model'!M8 -> 447.136 | C8: ='Yearly Model'!N8 -> 1099.5693 | D8: ='Yearly Model'!O8 -> 1463.4695 | E8: ='Yearly Model'!P8 -> 1895.9904 | F8: ='Yearly Model'!Q8 -> 2389.4753 | G8: ='Yearly Model'!R8 -> 2927.4316 | H8: ='Yearly Model'!S8 -> 3483.9575 | I8: ='Yearly Model'!T8 -> 4024.6092 | ... L8: ='Yearly Model'!W8 -> 5144.4788
A9: Tax on operating income | C9: =MAX(0,C8)*Assumptions!$E$14 -> 186.92679 | D9: =MAX(0,D8)*Assumptions!$E$14 -> 248.78981 | E9: =MAX(0,E8)*Assumptions!$E$14 -> 322.31837 | F9: =MAX(0,F8)*Assumptions!$E$14 -> 406.2108 | G9: =MAX(0,G8)*Assumptions!$E$14 -> 497.66338 | H9: =MAX(0,H8)*Assumptions!$E$14 -> 592.27278 | I9: =MAX(0,I8)*Assumptions!$E$14 -> 684.18357 | J9: =MAX(0,J8)*Assumptions!$E$14 -> 766.52868 | ... L9: =MAX(0,L8)*Assumptions!$E$14 -> 874.56139
A10: NOPAT | C10: =C8-C9 -> 912.64255 | D10: =D8-D9 -> 1214.6797 | E10: =E8-E9 -> 1573.6721 | F10: =F8-F9 -> 1983.2645 | G10: =G8-G9 -> 2429.7683 | H10: =H8-H9 -> 2891.6848 | I10: =I8-I9 -> 3340.4257 | J10: =J8-J9 -> 3742.4636 | ... L10: =L8-L9 -> 4269.9174
A11: Reinvestment | C11: =(C7-B7)*Assumptions!$E$15 -> 431.58349 | D11: =(D7-C7)*Assumptions!$E$15 -> 512.48983 | E11: =(E7-D7)*Assumptions!$E$15 -> 585.5874 | F11: =(F7-E7)*Assumptions!$E$15 -> 641.08974 | G11: =(G7-F7)*Assumptions!$E$15 -> 668.37952 | H11: =(H7-G7)*Assumptions!$E$15 -> 657.49851 | I11: =(I7-H7)*Assumptions!$E$15 -> 600.98783 | J11: =(J7-I7)*Assumptions!$E$15 -> 495.76524 | ... L11: =(L7-K7)*Assumptions!$E$15 -> 156.84387
A12: Free cash flow | C12: =C10-C11 -> 481.05906 | D12: =D10-D11 -> 702.18984 | E12: =E10-E11 -> 988.08465 | F12: =F10-F11 -> 1342.1748 | G12: =G10-G11 -> 1761.3887 | H12: =H10-H11 -> 2234.1863 | I12: =I10-I11 -> 2739.4378 | J12: =J10-J11 -> 3246.6983 | ... L12: =L10-L11 -> 4113.0735
A13: Year fraction | C13: =Assumptions!$B$22 -> 0.5041 | D13: 1 | E13: 1 | F13: 1 | G13: 1 | H13: 1 | I13: 1 | J13: 1 | K13: 1 | L13: 1
A14: Discount time (mid-period) | C14: =C13/2 -> 0.25205 | D14: =C14+C13/2+D13/2 -> 1.0041 | E14: =D14+D13/2+E13/2 -> 2.0041 | F14: =E14+E13/2+F13/2 -> 3.0041 | G14: =F14+F13/2+G13/2 -> 4.0041 | H14: =G14+G13/2+H13/2 -> 5.0041 | I14: =H14+H13/2+I13/2 -> 6.0041 | J14: =I14+I13/2+J13/2 -> 7.0041 | K14: =J14+J13/2+K13/2 -> 8.0041 | L14: =K14+K13/2+L13/2 -> 9.0041
A15: Discount factor | C15: =1/(1+Assumptions!$E$10)^C14 -> 0.97964773 | D15: =1/(1+Assumptions!$E$10)^D14 -> 0.92135076 | E15: =1/(1+Assumptions!$E$10)^E14 -> 0.84917121 | F15: =1/(1+Assumptions!$E$10)^F14 -> 0.78264628 | G15: =1/(1+Assumptions!$E$10)^G14 -> 0.72133297 | H15: =1/(1+Assumptions!$E$10)^H14 -> 0.66482302 | I15: =1/(1+Assumptions!$E$10)^I14 -> 0.61274011 | J15: =1/(1+Assumptions!$E$10)^J14 -> 0.56473743 | ... L15: =1/(1+Assumptions!$E$10)^L14 -> 0.47971919
A16: PV of free cash flow | C16: =C12*C13*C15 -> 237.56641 | D16: =D12*D13*D15 -> 646.96314 | E16: =E12*E13*E15 -> 839.05304 | F16: =F12*F13*F15 -> 1050.4481 | G16: =G12*G13*G15 -> 1270.5478 | H16: =H12*H13*H15 -> 1485.3384 | I16: =I12*I13*I15 -> 1678.5634 | J16: =J12*J13*J15 -> 1833.5321 | ... L16: =L12*L13*L15 -> 1973.1203
A19: PV of forecast free cash flow | B19: =SUM(C16:L16) -> 12950.472
A20: Terminal free cash flow (year 11) | B20: =L10*(1+Assumptions!$E$11)-L7*Assumptions!$E$11*Assumptions!$E$15 -> 4215.9004
A21: Terminal value | B21: =B20/(Assumptions!$E$10-Assumptions!$E$11) -> 70265.006
A22: PV of terminal value | B22: =B21/(1+Assumptions!$E$10)^(L14+0.5) -> 32360.209
A23: Enterprise value | B23: =B19+B22 -> 45310.68
A24: Cash & investments | B24: =Main!C7 -> 5098.041
A25: Debt | B25: =Main!C8 -> 1144.241
A26: Equity value | B26: =B23+B24-B25 -> 49264.48
A27: Shares (mm) | B27: =Main!C4 -> 113.70188
A28: NPV / share | B28: =B26/B27 -> 433.27763
A29: Price | B29: =Main!C3 -> 384.5
A30: Upside | B30: =B28/B29-1 -> 0.1268599
A31: Terminal value, % of EV | B31: =IFERROR(B22/B23,0) -> 0.71418501
