Workbook

Sheet Main
B2: Pharming Group N.V.
B3: Price | C3: =INDEX([1]Pharma!$F$1:$F$1000,MATCH("PHAR",[1]Pharma!$B$1:$B$1000,0)) -> 9.75
B4: Shares | C4: =701.68044/10 -> 70.168044
B5: Market Cap. | C5: =C3*C4 -> 684.13843
B7: Cash | C7: 145.305
B8: Debt | C8: 0
B9: Enterprise V. | C9: =C5-C7+C8 -> 538.83343
B11: NPV / Share | C11: =NPV!B28 -> 17.332363
B12: Upside | C12: =IFERROR(C11/C3-1,"") -> 0.77767824
B13: Cash / Share | C13: =IFERROR((C7-C8)/C4,"") -> 2.0708145
B14: Scenario | C14: =Assumptions!C4 -> Base
B15: Model | C15: DCF

Sheet Yearly Model
B1: 2018 | C1: 2019 | D1: 2020 | E1: 2021 | F1: 2022 | G1: 2023 | H1: 2024 | I1: 2025 | J1: 2026 | K1: 2027 | L1: 2028 | M1: 2029 | N1: 2030 | O1: 2031 | P1: 2032 | Q1: 2033 | R1: 2034 | S1: 2035
A2: Revenue | B2: 152.062 | C2: 189.389 | D2: 212.174 | E2: 198.871 | F2: 205.622 | G2: 245.316 | H2: 297.2 | I2: 376.134 | J2: =I2*(1+NPV!C5) -> 465.84196 | K2: =J2*(1+NPV!D5) -> 565.89446 | L2: =K2*(1+NPV!E5) -> 674.01174 | M2: =L2*(1+NPV!F5) -> 786.79637 | N2: =M2*(1+NPV!G5) -> 899.78907 | O2: =N2*(1+NPV!H5) -> 1007.6638 | P2: =O2*(1+NPV!I5) -> 1104.5675 | Q2: =P2*(1+NPV!J5) -> 1184.5872 | ... S2: =R2*(1+NPV!L5) -> 1273.3605
A3: Cost of Sales | B3: 24.959 | C3: 23.928 | D3: 23.539 | E3: 21.142 | F3: 17.562 | G3: 25.212 | H3: 35.399 | I3: 45.5 | J3: =J2*(1-Assumptions!$B$19) -> 56.366877 | K3: =K2*(1-Assumptions!$B$19) -> 68.47323 | L3: =L2*(1-Assumptions!$B$19) -> 81.555421 | M3: =M2*(1-Assumptions!$B$19) -> 95.202361 | N3: =N2*(1-Assumptions!$B$19) -> 108.87448 | O3: =O2*(1-Assumptions!$B$19) -> 121.92732 | P3: =P2*(1-Assumptions!$B$19) -> 133.65266 | Q3: =Q2*(1-Assumptions!$B$19) -> 143.33505 | ... S3: =S2*(1-Assumptions!$B$19) -> 154.07662
A4: Gross Margin | B4: =B2-B3 -> 127.103 | C4: =C2-C3 -> 165.461 | D4: =D2-D3 -> 188.635 | E4: =E2-E3 -> 177.729 | F4: =F2-F3 -> 188.06 | G4: =G2-G3 -> 220.104 | H4: =H2-H3 -> 261.801 | I4: =I2-I3 -> 330.634 | ... S4: =S2-S3 -> 1119.2839
A5: Research & Dev. | B5: 32.501 | C5: 31.786 | D5: 38.519 | E5: 70.369 | F5: 52.531 | G5: 68.914 | H5: 83.147 | I5: 100.367 | J5: =J7*Assumptions!$B$20 -> 122.28728 | K5: =K7*Assumptions!$B$20 -> 146.10511 | L5: =L7*Assumptions!$B$20 -> 171.10507 | M5: =M7*Assumptions!$B$20 -> 196.33477 | N5: =N7*Assumptions!$B$20 -> 220.6402 | O5: =O7*Assumptions!$B$20 -> 242.73566 | P5: =P7*Assumptions!$B$20 -> 261.30291 | Q5: =Q7*Assumptions!$B$20 -> 275.11105 | ... S5: =S7*Assumptions!$B$20 -> 284.71666
A6: SG&A & Other | B6: 51.849 | C6: 65.429 | D6: 73.86 | E6: 93.799 | F6: 117.296 | G6: 156.577 | H6: 187.275 | I6: 204.425 | J6: =J7-J5 -> 249.06796 | K6: =K7-K5 -> 297.57879 | L6: =L7-L5 -> 348.49732 | M6: =M7-M5 -> 399.88378 | N6: =N7-N5 -> 449.38773 | O6: =O7-O5 -> 494.39055 | P6: =P7-P5 -> 532.2073 | Q6: =Q7-Q5 -> 560.33094 | ... S6: =S7-S5 -> 579.89513
A7: Operating Expense | B7: =SUM(B5:B6) -> 84.35 | C7: =SUM(C5:C6) -> 97.215 | D7: =SUM(D5:D6) -> 112.379 | E7: =SUM(E5:E6) -> 164.168 | F7: =SUM(F5:F6) -> 169.827 | G7: =SUM(G5:G6) -> 225.491 | H7: =SUM(H5:H6) -> 270.422 | I7: =SUM(I5:I6) -> 304.792 | J7: =J4-J2*NPV!C6 -> 371.35523 | K7: =K4-K2*NPV!D6 -> 443.68389 | L7: =L4-L2*NPV!E6 -> 519.60239 | M7: =M4-M2*NPV!F6 -> 596.21855 | N7: =N4-N2*NPV!G6 -> 670.02793 | O7: =O4-O2*NPV!H6 -> 737.12621 | P7: =P4-P2*NPV!I6 -> 793.51021 | Q7: =Q4-Q2*NPV!J6 -> 835.44199 | ... S7: =S4-S2*NPV!L6 -> 864.6118
A8: Operating Income | B8: =B4-B7 -> 42.753 | C8: =C4-C7 -> 68.246 | D8: =D4-D7 -> 76.256 | E8: =E4-E7 -> 13.561 | F8: =F4-F7 -> 18.233 | G8: =G4-G7 -> -5.387 | H8: =H4-H7 -> -8.621 | I8: =I4-I7 -> 25.842 | ... S8: =S4-S7 -> 254.6721
A9: Interest & Other | B9: -41.788 | C9: -15.942 | D9: -32.162 | E9: 9.517 | F9: -3.246 | G9: -6.625 | H9: 0.129 | I9: -12.681 | J9: 0 | K9: 0 | L9: 0 | M9: 0 | N9: 0 | O9: 0 | P9: 0 | Q9: 0 | R9: 0 | S9: 0
A10: Pretax | B10: =B8+B9 -> 0.965 | C10: =C8+C9 -> 52.304 | D10: =D8+D9 -> 44.094 | E10: =E8+E9 -> 23.078 | F10: =F8+F9 -> 14.987 | G10: =G8+G9 -> -12.012 | H10: =H8+H9 -> -8.492 | I10: =I8+I9 -> 13.161 | ... S10: =S8+S9 -> 254.6721
A11: Taxes | B11: -27.16 | C11: 11.747 | D11: 6.348 | E11: 7.082 | F11: 1.313 | G11: -1.464 | H11: 3.349 | I11: 10.31 | J11: =MAX(0,J10)*Assumptions!$E$14 -> 6.4803741 | K11: =MAX(0,K10)*Assumptions!$E$14 -> 9.1353474 | L11: =MAX(0,L10)*Assumptions!$E$14 -> 12.385168 | M11: =MAX(0,M10)*Assumptions!$E$14 -> 16.213828 | N11: =MAX(0,N10)*Assumptions!$E$14 -> 20.550733 | O11: =MAX(0,O10)*Assumptions!$E$14 -> 25.263743 | P11: =MAX(0,P10)*Assumptions!$E$14 -> 30.158778 | Q11: =MAX(0,Q10)*Assumptions!$E$14 -> 34.987731 | ... S11: =MAX(0,S10)*Assumptions!$E$14 -> 43.294258
A12: Net Income | B12: 28.125 | C12: 40.557 | D12: 37.746 | E12: 15.996 | F12: 13.674 | G12: -10.548 | H12: -11.841 | I12: 2.851 | J12: =J10-J11 -> 31.639473 | K12: =K10-K11 -> 44.60199 | L12: =L10-L11 -> 60.468761 | M12: =M10-M11 -> 79.161629 | N12: =N10-N11 -> 100.33593 | O12: =O10-O11 -> 123.34651 | P12: =P10-P11 -> 147.2458 | Q12: =Q10-Q11 -> 170.82245 | ... S12: =S10-S11 -> 211.37785
A13: Earnings per Share | B13: =IFERROR(B12/B14,0) -> 0.043035647 | C13: =IFERROR(C12/C14,0) -> 0.060216475 | D13: =IFERROR(D12/D14,0) -> 0.055286296 | E13: =IFERROR(E12/E14,0) -> 0.022813883 | F13: =IFERROR(F12/F14,0) -> 0.01933702 | G13: =IFERROR(G12/G14,0) -> -0.01453966 | H13: =IFERROR(H12/H14,0) -> -0.015076164 | I13: =IFERROR(I12/I14,0) -> 0.0038172845 | ... S13: =IFERROR(S12/S14,0) -> 3.0124517
A14: Shares | B14: 653.528 | C14: 673.52 | D14: 682.737 | E14: 701.152 | F14: 707.141 | G14: 725.464 | H14: 785.412 | I14: 746.866 | J14: =Main!$C$4 -> 70.168044 | K14: =Main!$C$4 -> 70.168044 | L14: =Main!$C$4 -> 70.168044 | M14: =Main!$C$4 -> 70.168044 | N14: =Main!$C$4 -> 70.168044 | O14: =Main!$C$4 -> 70.168044 | P14: =Main!$C$4 -> 70.168044 | Q14: =Main!$C$4 -> 70.168044 | ... S14: =Main!$C$4 -> 70.168044
A16: Revenue Change | C16: =IFERROR(C2/B2-1,"") -> 0.24547224 | D16: =IFERROR(D2/C2-1,"") -> 0.12030794 | E16: =IFERROR(E2/D2-1,"") -> -0.06269854 | F16: =IFERROR(F2/E2-1,"") -> 0.033946629 | G16: =IFERROR(G2/F2-1,"") -> 0.19304355 | H16: =IFERROR(H2/G2-1,"") -> 0.21149864 | I16: =IFERROR(I2/H2-1,"") -> 0.26559219 | J16: =IFERROR(J2/I2-1,"") -> 0.2385 | ... S16: =IFERROR(S2/R2-1,"") -> 0.025
A17: Gross Margin | B17: =IFERROR(B4/B2,"") -> 0.835863 | C17: =IFERROR(C4/C2,"") -> 0.87365686 | D17: =IFERROR(D4/D2,"") -> 0.88905804 | E17: =IFERROR(E4/E2,"") -> 0.89368988 | F17: =IFERROR(F4/F2,"") -> 0.91459085 | G17: =IFERROR(G4/G2,"") -> 0.89722643 | H17: =IFERROR(H4/H2,"") -> 0.88089166 | I17: =IFERROR(I4/I2,"") -> 0.87903247 | ... S17: =IFERROR(S4/S2,"") -> 0.879
A18: Operating Margin | B18: =IFERROR(B8/B2,"") -> 0.28115506 | C18: =IFERROR(C8/C2,"") -> 0.36034828 | D18: =IFERROR(D8/D2,"") -> 0.35940313 | E18: =IFERROR(E8/E2,"") -> 0.068189932 | F18: =IFERROR(F8/F2,"") -> 0.088672418 | G18: =IFERROR(G8/G2,"") -> -0.021959432 | H18: =IFERROR(H8/H2,"") -> -0.029007402 | I18: =IFERROR(I8/I2,"") -> 0.068704238 | ... S18: =IFERROR(S8/S2,"") -> 0.2
A19: Actual / Estimate | B19: A | C19: A | D19: A | E19: A | F19: A | G19: A | H19: A | I19: A | J19: E | K19: E | L19: E | M19: E | N19: E | O19: E | P19: E | Q19: E | R19: E | S19: E

Sheet Quarterly Model

Sheet Assumptions
A1: Pharming Group N.V.: basic DCF assumptions
A2: Blue = input, black = formula, green = link. $mm unless noted.
A4: Scenario (1 Bear, 2 Base, 3 Bull) | B4: 2 | C4: =CHOOSE($B$4,"Bear","Base","Bull") -> Base
A6: Discount rate override (blank = scenario)
A7: Terminal growth override (blank = scenario)
A9: Parameter | B9: Bear | C9: Base | D9: Bull | E9: Live
A10: Discount rate | B10: 0.135 | C10: 0.125 | D10: 0.115 | E10: =IF(ISNUMBER($B$6),$B$6,CHOOSE($B$4,B10,C10,D10)) -> 0.125
A11: Terminal growth | B11: 0.02 | C11: 0.025 | D11: 0.03 | E11: =IF(ISNUMBER($B$7),$B$7,CHOOSE($B$4,B11,C11,D11)) -> 0.025
A12: Revenue growth, first forecast year | B12: 0.1885 | C12: 0.2385 | D12: 0.2885 | E12: =CHOOSE($B$4,B12,C12,D12) -> 0.2385
A13: Operating margin, year 10 | B13: 0.15 | C13: 0.2 | D13: 0.25 | E13: =CHOOSE($B$4,B13,C13,D13) -> 0.2
A14: Tax rate on operating income | B14: 0.17 | C14: 0.17 | D14: 0.17 | E14: =CHOOSE($B$4,B14,C14,D14) -> 0.17
A15: Reinvestment, % of revenue increase | B15: 0.25 | C15: 0.25 | D15: 0.25 | E15: =CHOOSE($B$4,B15,C15,D15) -> 0.25
A17: Single inputs
A18: Starting operating margin (TTM) | B18: 0.0687
A19: Gross margin (forecast) | B19: 0.879
A20: R&D share of operating expense (forecast) | B20: 0.3293
A21: Forecast years | B21: 10
A22: First forecast year, fraction after balance sheet date | B22: 1
A23: Balance sheet date | B23: 46022
A24: Reporting currency per USD (USD) | B24: 1
A25: Base revenue, FY2025 | B25: ='Yearly Model'!I2 -> 376.134
A27: Scenario summary
A28: Scenario | B28: Enterprise value | C28: Equity value | D28: NPV / share | E28: Upside
A29: Live | B29: =NPV!B23 -> 1070.873 | C29: =NPV!B26 -> 1216.178 | D29: =NPV!B28 -> 17.332363 | E29: =NPV!B30 -> 0.77767824
A30: 1 | B30: 569.32924 | C30: 714.63424 | D30: 10.184611 | E30: 0.044575502
A31: 2 | B31: 1070.873 | C31: 1216.178 | D31: 17.332363 | E31: 0.77767824
A32: 3 | B32: 1974.2954 | C32: 2119.6004 | D32: 30.207489 | E32: 2.098204
A35: NPV / share: discount rate (rows) x terminal growth (columns)
A36: =NPV!B28 -> 17.332363 | B36: 0.015 | C36: 0.02 | D36: 0.025 | E36: 0.03 | F36: 0.035
A37: 0.105 | B37: 20.520779 | C37: 21.504212 | D37: 22.610564 | E37: 23.86442 | F37: 25.297391
A38: 0.115 | B38: 18.068785 | C38: 18.820755 | D38: 19.656258 | E38: 20.590037 | F38: 21.640522
A39: 0.125 | B39: 16.0984 | C39: 16.686013 | D39: 17.332363 | E39: 18.046727 | F39: 18.840441
A40: 0.135 | B40: 14.486511 | C40: 14.953997 | D40: 15.463957 | E40: 16.022458 | F40: 16.636783
A41: 0.145 | B41: 13.148132 | C41: 13.525696 | D41: 13.934696 | E41: 14.379234 | F41: 14.864158

Sheet NPV
A1: Pharming Group N.V.: free-cash-flow DCF ($mm)
A3: Fiscal year | B3: ='Yearly Model'!I1 -> 2025 | C3: ='Yearly Model'!J1 -> 2026 | D3: ='Yearly Model'!K1 -> 2027 | E3: ='Yearly Model'!L1 -> 2028 | F3: ='Yearly Model'!M1 -> 2029 | G3: ='Yearly Model'!N1 -> 2030 | H3: ='Yearly Model'!O1 -> 2031 | I3: ='Yearly Model'!P1 -> 2032 | ... L3: ='Yearly Model'!S1 -> 2035
A4: Period | B4: Actual | C4: 1 | D4: 2 | E4: 3 | F4: 4 | G4: 5 | H4: 6 | I4: 7 | J4: 8 | K4: 9 | L4: 10
A5: Revenue growth | C5: =Assumptions!$E$12+(Assumptions!$E$11-Assumptions!$E$12)*(C4-1)/(Assumptions!$B$21-1) -> 0.2385 | D5: =Assumptions!$E$12+(Assumptions!$E$11-Assumptions!$E$12)*(D4-1)/(Assumptions!$B$21-1) -> 0.21477778 | E5: =Assumptions!$E$12+(Assumptions!$E$11-Assumptions!$E$12)*(E4-1)/(Assumptions!$B$21-1) -> 0.19105556 | F5: =Assumptions!$E$12+(Assumptions!$E$11-Assumptions!$E$12)*(F4-1)/(Assumptions!$B$21-1) -> 0.16733333 | G5: =Assumptions!$E$12+(Assumptions!$E$11-Assumptions!$E$12)*(G4-1)/(Assumptions!$B$21-1) -> 0.14361111 | H5: =Assumptions!$E$12+(Assumptions!$E$11-Assumptions!$E$12)*(H4-1)/(Assumptions!$B$21-1) -> 0.11988889 | I5: =Assumptions!$E$12+(Assumptions!$E$11-Assumptions!$E$12)*(I4-1)/(Assumptions!$B$21-1) -> 0.096166667 | J5: =Assumptions!$E$12+(Assumptions!$E$11-Assumptions!$E$12)*(J4-1)/(Assumptions!$B$21-1) -> 0.072444444 | ... L5: =Assumptions!$E$12+(Assumptions!$E$11-Assumptions!$E$12)*(L4-1)/(Assumptions!$B$21-1) -> 0.025
A6: Operating margin | B6: =IFERROR(B8/B7,0) -> 0.068704238 | C6: =Assumptions!$B$18+(Assumptions!$E$13-Assumptions!$B$18)*C4/Assumptions!$B$21 -> 0.08183 | D6: =Assumptions!$B$18+(Assumptions!$E$13-Assumptions!$B$18)*D4/Assumptions!$B$21 -> 0.09496 | E6: =Assumptions!$B$18+(Assumptions!$E$13-Assumptions!$B$18)*E4/Assumptions!$B$21 -> 0.10809 | F6: =Assumptions!$B$18+(Assumptions!$E$13-Assumptions!$B$18)*F4/Assumptions!$B$21 -> 0.12122 | G6: =Assumptions!$B$18+(Assumptions!$E$13-Assumptions!$B$18)*G4/Assumptions!$B$21 -> 0.13435 | H6: =Assumptions!$B$18+(Assumptions!$E$13-Assumptions!$B$18)*H4/Assumptions!$B$21 -> 0.14748 | I6: =Assumptions!$B$18+(Assumptions!$E$13-Assumptions!$B$18)*I4/Assumptions!$B$21 -> 0.16061 | J6: =Assumptions!$B$18+(Assumptions!$E$13-Assumptions!$B$18)*J4/Assumptions!$B$21 -> 0.17374 | ... L6: =Assumptions!$B$18+(Assumptions!$E$13-Assumptions!$B$18)*L4/Assumptions!$B$21 -> 0.2
A7: Revenue | B7: ='Yearly Model'!I2 -> 376.134 | C7: ='Yearly Model'!J2 -> 465.84196 | D7: ='Yearly Model'!K2 -> 565.89446 | E7: ='Yearly Model'!L2 -> 674.01174 | F7: ='Yearly Model'!M2 -> 786.79637 | G7: ='Yearly Model'!N2 -> 899.78907 | H7: ='Yearly Model'!O2 -> 1007.6638 | I7: ='Yearly Model'!P2 -> 1104.5675 | ... L7: ='Yearly Model'!S2 -> 1273.3605
A8: Operating income | B8: ='Yearly Model'!I8 -> 25.842 | C8: ='Yearly Model'!J8 -> 38.119848 | D8: ='Yearly Model'!K8 -> 53.737338 | E8: ='Yearly Model'!L8 -> 72.853929 | F8: ='Yearly Model'!M8 -> 95.375456 | G8: ='Yearly Model'!N8 -> 120.88666 | H8: ='Yearly Model'!O8 -> 148.61025 | I8: ='Yearly Model'!P8 -> 177.40458 | ... L8: ='Yearly Model'!S8 -> 254.6721
A9: Tax on operating income | C9: =MAX(0,C8)*Assumptions!$E$14 -> 6.4803741 | D9: =MAX(0,D8)*Assumptions!$E$14 -> 9.1353474 | E9: =MAX(0,E8)*Assumptions!$E$14 -> 12.385168 | F9: =MAX(0,F8)*Assumptions!$E$14 -> 16.213828 | G9: =MAX(0,G8)*Assumptions!$E$14 -> 20.550733 | H9: =MAX(0,H8)*Assumptions!$E$14 -> 25.263743 | I9: =MAX(0,I8)*Assumptions!$E$14 -> 30.158778 | J9: =MAX(0,J8)*Assumptions!$E$14 -> 34.987731 | ... L9: =MAX(0,L8)*Assumptions!$E$14 -> 43.294258
A10: NOPAT | C10: =C8-C9 -> 31.639473 | D10: =D8-D9 -> 44.60199 | E10: =E8-E9 -> 60.468761 | F10: =F8-F9 -> 79.161629 | G10: =G8-G9 -> 100.33593 | H10: =H8-H9 -> 123.34651 | I10: =I8-I9 -> 147.2458 | J10: =J8-J9 -> 170.82245 | ... L10: =L8-L9 -> 211.37785
A11: Reinvestment | C11: =(C7-B7)*Assumptions!$E$15 -> 22.42699 | D11: =(D7-C7)*Assumptions!$E$15 -> 25.013125 | E11: =(E7-D7)*Assumptions!$E$15 -> 27.02932 | F11: =(F7-E7)*Assumptions!$E$15 -> 28.196158 | G11: =(G7-F7)*Assumptions!$E$15 -> 28.248175 | H11: =(H7-G7)*Assumptions!$E$15 -> 26.968678 | I11: =(I7-H7)*Assumptions!$E$15 -> 24.225917 | J11: =(J7-I7)*Assumptions!$E$15 -> 20.004944 | ... L11: =(L7-K7)*Assumptions!$E$15 -> 7.7643934
A12: Free cash flow | C12: =C10-C11 -> 9.2124837 | D12: =D10-D11 -> 19.588865 | E12: =E10-E11 -> 33.439441 | F12: =F10-F11 -> 50.965471 | G12: =G10-G11 -> 72.087754 | H12: =H10-H11 -> 96.377834 | I12: =I10-I11 -> 123.01988 | J12: =J10-J11 -> 150.81751 | ... L12: =L10-L11 -> 203.61345
A13: Year fraction | C13: =Assumptions!$B$22 -> 1 | D13: 1 | E13: 1 | F13: 1 | G13: 1 | H13: 1 | I13: 1 | J13: 1 | K13: 1 | L13: 1
A14: Discount time (mid-period) | C14: =C13/2 -> 0.5 | D14: =C14+C13/2+D13/2 -> 1.5 | E14: =D14+D13/2+E13/2 -> 2.5 | F14: =E14+E13/2+F13/2 -> 3.5 | G14: =F14+F13/2+G13/2 -> 4.5 | H14: =G14+G13/2+H13/2 -> 5.5 | I14: =H14+H13/2+I13/2 -> 6.5 | J14: =I14+I13/2+J13/2 -> 7.5 | K14: =J14+J13/2+K13/2 -> 8.5 | L14: =K14+K13/2+L13/2 -> 9.5
A15: Discount factor | C15: =1/(1+Assumptions!$E$10)^C14 -> 0.94280904 | D15: =1/(1+Assumptions!$E$10)^D14 -> 0.83805248 | E15: =1/(1+Assumptions!$E$10)^E14 -> 0.74493554 | F15: =1/(1+Assumptions!$E$10)^F14 -> 0.66216492 | G15: =1/(1+Assumptions!$E$10)^G14 -> 0.58859104 | H15: =1/(1+Assumptions!$E$10)^H14 -> 0.52319204 | I15: =1/(1+Assumptions!$E$10)^I14 -> 0.46505959 | J15: =1/(1+Assumptions!$E$10)^J14 -> 0.4133863 | ... L15: =1/(1+Assumptions!$E$10)^L14 -> 0.32662621
A16: PV of free cash flow | C16: =C12*C13*C15 -> 8.6856129 | D16: =D12*D13*D15 -> 16.416497 | E16: =E12*E13*E15 -> 24.910228 | F16: =F12*F13*F15 -> 33.747547 | G16: =G12*G13*G15 -> 42.430206 | H16: =H12*H13*H15 -> 50.424115 | I16: =I12*I13*I15 -> 57.211576 | J16: =J12*J13*J15 -> 62.345893 | ... L16: =L12*L13*L15 -> 66.505491
A19: PV of forecast free cash flow | B19: =SUM(C16:L16) -> 428.17772
A20: Terminal free cash flow (year 11) | B20: =L10*(1+Assumptions!$E$11)-L7*Assumptions!$E$11*Assumptions!$E$15 -> 208.70379
A21: Terminal value | B21: =B20/(Assumptions!$E$10-Assumptions!$E$11) -> 2087.0379
A22: PV of terminal value | B22: =B21/(1+Assumptions!$E$10)^(L14+0.5) -> 642.69528
A23: Enterprise value | B23: =B19+B22 -> 1070.873
A24: Cash & investments | B24: =Main!C7 -> 145.305
A25: Debt | B25: =Main!C8 -> 0
A26: Equity value | B26: =B23+B24-B25 -> 1216.178
A27: Shares (mm) | B27: =Main!C4 -> 70.168044
A28: NPV / share | B28: =B26/B27 -> 17.332363
A29: Price | B29: =Main!C3 -> 9.75
A30: Upside | B30: =B28/B29-1 -> 0.77767824
A31: Terminal value, % of EV | B31: =IFERROR(B22/B23,0) -> 0.60016013
