Workbook

Sheet Main
B2: Praxis Precision Medicines, Inc.
B3: Price | C3: =INDEX([1]Pharma!$F$1:$F$1000,MATCH("PRAX",[1]Pharma!$B$1:$B$1000,0)) -> 264.49
B4: Shares | C4: =27.919988+0.704225+0.221238+0.31847 -> 29.163921
B5: Market Cap. | C5: =C3*C4 -> 7713.5655
B7: Cash | C7: =474.76+283.79+615.29 -> 1373.84
B8: Debt | C8: 0
B9: Enterprise V. | C9: =C5-C7+C8 -> 6339.7255
B11: rNPV / Share | C11: =NPV!C43 -> 272.58649
B12: Upside | C12: =C11/C3-1 -> 0.030611696
B13: Cash / Share | C13: =(C7-C8)/C4 -> 47.10752
B14: Scenario | C14: =Assumptions!$C$4 -> Base
B16: PDUFA Date | C16: =Assumptions!$B$30 -> 46383
B17: P(Approval) | C17: =Assumptions!$B$32 -> 0.9
B18: If Approved | C18: =Assumptions!$D$142 -> 275.37473
B19: If CRL | C19: =Assumptions!$D$141 -> 247.23121

Sheet Yearly Model
B1: 2021 | C1: 2022 | D1: 2023 | E1: 2024 | F1: 2025 | G1: 2026 | H1: 2027 | I1: 2028 | J1: 2029 | K1: 2030 | L1: 2031 | M1: 2032 | N1: 2033 | O1: 2034 | P1: 2035 | Q1: 2036 | R1: 2037 | S1: 2038 | T1: 2039 | U1: 2040 | V1: 2041 | W1: 2042 | X1: 2043 | Y1: 2044 | Z1: 2045 | AA1: 2046 | AB1: 2047 | AC1: 2048 | AD1: 2049 | AE1: 2050
A2: Revenue | B2: 0 | C2: 0 | D2: 2.447 | E2: 8.553 | F2: 0 | G2: =SUM('Quarterly Model'!F2:I2) -> 0 | H2: =Pipeline!C57 -> 471 | I2: =Pipeline!D57 -> 925.5 | J2: =Pipeline!E57 -> 1683 | K2: =Pipeline!F57 -> 2493 | L2: =Pipeline!G57 -> 3214.5 | M2: =Pipeline!H57 -> 3741.75 | N2: =Pipeline!I57 -> 4072.5 | O2: =Pipeline!J57 -> 4146 | ... AE2: =Pipeline!Z57 -> 2.3338055
A3: Cost of Sales | B3: 0 | C3: 0 | D3: 0 | E3: 0 | F3: 0 | G3: =SUM('Quarterly Model'!F3:I3) -> 0 | H3: =Pipeline!C58 -> 13.44 | I3: =Pipeline!D58 -> 36.57 | J3: =Pipeline!E58 -> 68.67 | K3: =Pipeline!F58 -> 102.87 | L3: =Pipeline!G58 -> 133.53 | M3: =Pipeline!H58 -> 156.42 | N3: =Pipeline!I58 -> 171 | O3: =Pipeline!J58 -> 174.84 | ... AE3: =Pipeline!Z58 -> 0.12850847
A4: Gross Margin | B4: =B2-B3 -> 0 | C4: =C2-C3 -> 0 | D4: =D2-D3 -> 2.447 | E4: =E2-E3 -> 8.553 | F4: =F2-F3 -> 0 | G4: =G2-G3 -> 0 | H4: =H2-H3 -> 457.56 | I4: =I2-I3 -> 888.93 | ... AE4: =AE2-AE3 -> 2.205297
A5: Research & Dev. | B5: 120.257 | C5: 155.04 | D5: 86.766 | E5: 152.413 | F5: 267.115 | G5: =SUM('Quarterly Model'!F5:I5) -> 294.403 | H5: =Pipeline!C61 -> 305 | I5: =Pipeline!D61 -> 254.5 | J5: =Pipeline!E61 -> 221.96 | K5: =Pipeline!F61 -> 299.16 | L5: =Pipeline!G61 -> 385.74 | M5: =Pipeline!H61 -> 449.01 | N5: =Pipeline!I61 -> 488.7 | O5: =Pipeline!J61 -> 497.52 | ... AE5: =Pipeline!Z61 -> 0.28005665
A6: General & Admin | B6: 47.075 | C6: 59.946 | D6: 42.054 | E6: 56.305 | F6: 59.083 | G6: =SUM('Quarterly Model'!F6:I6) -> 125.361 | H6: =Pipeline!C64 -> 433.275 | I6: =Pipeline!D64 -> 663.9 | J6: =Pipeline!E64 -> 863.4275 | K6: =Pipeline!F64 -> 1058.4525 | L6: =Pipeline!G64 -> 1251.69 | M6: =Pipeline!H64 -> 1401.21 | N6: =Pipeline!I64 -> 1464.15 | O6: =Pipeline!J64 -> 1469.73 | ... AE6: =Pipeline!Z64 -> 0.77713196
A7: Operating Expense | B7: =SUM(B5:B6) -> 167.332 | C7: =SUM(C5:C6) -> 214.986 | D7: =SUM(D5:D6) -> 128.82 | E7: =SUM(E5:E6) -> 208.718 | F7: =SUM(F5:F6) -> 326.198 | G7: =SUM(G5:G6) -> 419.764 | H7: =SUM(H5:H6) -> 738.275 | I7: =SUM(I5:I6) -> 918.4 | ... AE7: =SUM(AE5:AE6) -> 1.0571886
A8: Operating Income | B8: =B4-B7 -> -167.332 | C8: =C4-C7 -> -214.986 | D8: =D4-D7 -> -126.373 | E8: =E4-E7 -> -200.165 | F8: =F4-F7 -> -326.198 | G8: =G4-G7 -> -419.764 | H8: =H4-H7 -> -280.715 | I8: =I4-I7 -> -29.47 | ... AE8: =AE4-AE7 -> 1.1481084
A9: Interest & Other | B9: 0.332 | C9: 0.986 | D9: 3.373 | E9: 17.165 | F9: 23.669 | G9: =SUM('Quarterly Model'!F9:I9) -> 51.983 | H9: =Assumptions!$B$16*MAX(0,G20)-Assumptions!$B$17*Main!$C$8 -> 44.33775 | I9: =Assumptions!$B$16*MAX(0,H20)-Assumptions!$B$17*Main!$C$8 -> 35.473603 | J9: =Assumptions!$B$16*MAX(0,I20)-Assumptions!$B$17*Main!$C$8 -> 35.698738 | K9: =Assumptions!$B$16*MAX(0,J20)-Assumptions!$B$17*Main!$C$8 -> 56.872785 | L9: =Assumptions!$B$16*MAX(0,K20)-Assumptions!$B$17*Main!$C$8 -> 97.72492 | M9: =Assumptions!$B$16*MAX(0,L20)-Assumptions!$B$17*Main!$C$8 -> 144.51986 | N9: =Assumptions!$B$16*MAX(0,M20)-Assumptions!$B$17*Main!$C$8 -> 200.2039 | O9: =Assumptions!$B$16*MAX(0,N20)-Assumptions!$B$17*Main!$C$8 -> 263.86369 | ... AE9: =Assumptions!$B$16*MAX(0,AD20)-Assumptions!$B$17*Main!$C$8 -> 1155.9051
A10: Pretax | B10: =B8+B9 -> -167 | C10: =C8+C9 -> -214 | D10: =D8+D9 -> -123 | E10: =E8+E9 -> -183 | F10: =F8+F9 -> -302.529 | G10: =G8+G9 -> -367.781 | H10: =H8+H9 -> -236.37725 | I10: =I8+I9 -> 6.0036031 | ... AE10: =AE8+AE9 -> 1157.0532
A11: Taxes | B11: 0 | C11: 0 | D11: 0 | E11: 0 | F11: 0.471 | G11: =SUM('Quarterly Model'!F11:I11) -> 0 | H11: =MAX(0,H10-G21)*Assumptions!$B$15 -> 0 | I11: =MAX(0,I10-H21)*Assumptions!$B$15 -> 0 | J11: =MAX(0,J10-I21)*Assumptions!$B$15 -> 0 | K11: =MAX(0,K10-J21)*Assumptions!$B$15 -> 0 | L11: =MAX(0,L10-K21)*Assumptions!$B$15 -> 293.39978 | M11: =MAX(0,M10-L21)*Assumptions!$B$15 -> 394.72227 | N11: =MAX(0,N10-M21)*Assumptions!$B$15 -> 451.25932 | O11: =MAX(0,O10-N21)*Assumptions!$B$15 -> 476.23248 | ... AE11: =MAX(0,AE10-AD21)*Assumptions!$B$15 -> 242.98117
A12: Net Income | B12: -167 | C12: -214 | D12: -123 | E12: -183 | F12: -303 | G12: =G10-G11 -> -367.781 | H12: =H10-H11 -> -236.37725 | I12: =I10-I11 -> 6.0036031 | J12: =J10-J11 -> 564.64124 | K12: =K10-K11 -> 1089.3903 | L12: =L10-L11 -> 1247.8651 | M12: =M10-M11 -> 1484.9076 | N12: =N10-N11 -> 1697.5946 | ... AE12: =AE10-AE11 -> 914.07203
A13: Earnings per Share | B13: =IFERROR(B12/B14,0) -> -59.010601 | C13: =IFERROR(C12/C14,0) -> -69.638789 | D13: =IFERROR(D12/D14,0) -> -18.653321 | E13: =IFERROR(E12/E14,0) -> -10.219467 | F13: =IFERROR(F12/F14,0) -> -13.463675 | G13: =IFERROR(G12/G14,0) -> -12.626048 | H13: =IFERROR(H12/H14,0) -> -8.1051259 | I13: =IFERROR(I12/I14,0) -> 0.2058572 | ... AE13: =IFERROR(AE12/AE14,0) -> 31.342563
A14: Shares | B14: 2.83 | C14: 3.073 | D14: 6.594 | E14: 17.907 | F14: 22.505 | G14: =AVERAGE('Quarterly Model'!F14:I14) -> 29.12875 | H14: =Main!$C$4*(1+Assumptions!$B$26)^(H1-2026) -> 29.163921 | I14: =Main!$C$4*(1+Assumptions!$B$26)^(I1-2026) -> 29.163921 | J14: =Main!$C$4*(1+Assumptions!$B$26)^(J1-2026) -> 29.163921 | K14: =Main!$C$4*(1+Assumptions!$B$26)^(K1-2026) -> 29.163921 | L14: =Main!$C$4*(1+Assumptions!$B$26)^(L1-2026) -> 29.163921 | M14: =Main!$C$4*(1+Assumptions!$B$26)^(M1-2026) -> 29.163921 | N14: =Main!$C$4*(1+Assumptions!$B$26)^(N1-2026) -> 29.163921 | O14: =Main!$C$4*(1+Assumptions!$B$26)^(O1-2026) -> 29.163921 | ... AE14: =Main!$C$4*(1+Assumptions!$B$26)^(AE1-2026) -> 29.163921
A16: Revenue Change | C16: =IFERROR(C2/B2-1,"") | D16: =IFERROR(D2/C2-1,"") | E16: =IFERROR(E2/D2-1,"") -> 2.4953004 | F16: =IFERROR(F2/E2-1,"") -> -1 | G16: =IFERROR(G2/F2-1,"") | H16: =IFERROR(H2/G2-1,"") | I16: =IFERROR(I2/H2-1,"") -> 0.96496815 | J16: =IFERROR(J2/I2-1,"") -> 0.8184765 | ... AE16: =IFERROR(AE2/AD2-1,"") -> -0.56741811
A17: Gross Margin | B17: =IFERROR(B4/B2,"") | C17: =IFERROR(C4/C2,"") | D17: =IFERROR(D4/D2,"") -> 1 | E17: =IFERROR(E4/E2,"") -> 1 | F17: =IFERROR(F4/F2,"") | G17: =IFERROR(G4/G2,"") | H17: =IFERROR(H4/H2,"") -> 0.97146497 | I17: =IFERROR(I4/I2,"") -> 0.96048622 | ... AE17: =IFERROR(AE4/AE2,"") -> 0.94493608
A19: Actual / Estimate | B19: A | C19: A | D19: A | E19: A | F19: A | G19: A+E | H19: E | I19: E | J19: E | K19: E | L19: E | M19: E | N19: E | O19: E | P19: E | Q19: E | R19: E | S19: E | T19: E | U19: E | V19: E | W19: E | X19: E | Y19: E | Z19: E | AA19: E | AB19: E | AC19: E | AD19: E | AE19: E
A20: Cash & Investments | G20: ='Quarterly Model'!I20 -> 1182.34 | H20: =G20+H12 -> 945.96275 | I20: =H20+I12 -> 951.96635 | J20: =I20+J12 -> 1516.6076 | K20: =J20+K12 -> 2605.9979 | L20: =K20+L12 -> 3853.863 | M20: =L20+M12 -> 5338.7706 | N20: =M20+N12 -> 7036.3652 | O20: =N20+O12 -> 8827.9064 | ... AE20: =AD20+AE12 -> 31738.208
A21: Tax-Loss Pool | F21: =Assumptions!$B$18 -> 1200 | G21: =F21-MIN(F21,MAX(0,G10))+MAX(0,-G10) -> 1567.781 | H21: =G21-MIN(G21,MAX(0,H10))+MAX(0,-H10) -> 1804.1582 | I21: =H21-MIN(H21,MAX(0,I10))+MAX(0,-I10) -> 1798.1546 | J21: =I21-MIN(I21,MAX(0,J10))+MAX(0,-J10) -> 1233.5134 | K21: =J21-MIN(J21,MAX(0,K10))+MAX(0,-K10) -> 144.12312 | L21: =K21-MIN(K21,MAX(0,L10))+MAX(0,-L10) -> 0 | M21: =L21-MIN(L21,MAX(0,M10))+MAX(0,-M10) -> 0 | N21: =M21-MIN(M21,MAX(0,N10))+MAX(0,-N10) -> 0 | ... AE21: =AD21-MIN(AD21,MAX(0,AE10))+MAX(0,-AE10) -> 0

Sheet Quarterly Model
B1: Q1 2025 | C1: Q2 2025 | D1: Q3 2025 | E1: Q4 2025 | F1: Q1 2026 | G1: Q2 2026 | H1: Q3 2026 | I1: Q4 2026
A2: Revenue | B2: 0 | C2: 0 | D2: 0 | E2: 0 | F2: 0 | G2: 0 | H2: 0 | I2: 0
A3: Cost of Sales | B3: 0 | C3: 0 | D3: 0 | E3: 0 | F3: 0 | G3: 0 | H3: =H2*0.0 -> 0 | I3: =I2*0.0 -> 0
A4: Gross Margin | B4: =B2-B3 -> 0 | C4: =C2-C3 -> 0 | D4: =D2-D3 -> 0 | E4: =E2-E3 -> 0 | F4: =F2-F3 -> 0 | G4: =G2-G3 -> 0 | H4: =H2-H3 -> 0 | I4: =I2-I3 -> 0
A5: Research & Dev. | B5: 60.806 | C5: 63.006 | D5: 65.797 | E5: 77.506 | F5: 77.987 | G5: 69.416 | H5: 72 | I5: 75
A6: General & Admin | B6: 13.922 | C6: 13.061 | D6: 12.562 | E6: 19.538 | F6: 27.873 | G6: 27.488 | H6: 32 | I6: 38
A7: Operating Expense | B7: =SUM(B5:B6) -> 74.728 | C7: =SUM(C5:C6) -> 76.067 | D7: =SUM(D5:D6) -> 78.359 | E7: =SUM(E5:E6) -> 97.044 | F7: =SUM(F5:F6) -> 105.86 | G7: =SUM(G5:G6) -> 96.904 | H7: =SUM(H5:H6) -> 104 | I7: =SUM(I5:I6) -> 113
A8: Operating Income | B8: =B4-B7 -> -74.728 | C8: =C4-C7 -> -76.067 | D8: =D4-D7 -> -78.359 | E8: =E4-E7 -> -97.044 | F8: =F4-F7 -> -105.86 | G8: =G4-G7 -> -96.904 | H8: =H4-H7 -> -104 | I8: =I4-I7 -> -113
A9: Interest & Other | B9: 5.432 | C9: 4.94 | D9: 4.425 | E9: 8.401 | F9: 13.299 | G9: 13.184 | H9: 13 | I9: 12.5
A10: Pretax | B10: =B8+B9 -> -69.296 | C10: =C8+C9 -> -71.127 | D10: =D8+D9 -> -73.934 | E10: =E8+E9 -> -88.643 | F10: =F8+F9 -> -92.561 | G10: =G8+G9 -> -83.72 | H10: =H8+H9 -> -91 | I10: =I8+I9 -> -100.5
A11: Taxes | B11: 0 | C11: 0 | D11: 0 | E11: 0 | F11: 0 | G11: 0 | H11: 0 | I11: 0
A12: Net Income | B12: =B10-B11 -> -69.296 | C12: =C10-C11 -> -71.127 | D12: =D10-D11 -> -73.934 | E12: =E10-E11 -> -88.643 | F12: =F10-F11 -> -92.561 | G12: =G10-G11 -> -83.72 | H12: =H10-H11 -> -91 | I12: =I10-I11 -> -100.5
A13: Earnings per Share | B13: =IFERROR(B12/B14,0) -> -3.2910334 | C13: =IFERROR(C12/C14,0) -> -3.3120838 | D13: =IFERROR(D12/D14,0) -> -3.3641534 | E13: =IFERROR(E12/E14,0) -> -3.4746972 | F13: =IFERROR(F12/F14,0) -> -3.2045769 | G13: =IFERROR(G12/G14,0) -> -2.8739144 | H13: =IFERROR(H12/H14,0) -> -3.1164384 | I13: =IFERROR(I12/I14,0) -> -3.4300341
A14: Shares | B14: 21.056 | C14: 21.475 | D14: 21.977 | E14: 25.511 | F14: 28.884 | G14: 29.131 | H14: 29.2 | I14: 29.3
A16: Revenue Change (YoY) | F16: =IFERROR(F2/B2-1,"") | G16: =IFERROR(G2/C2-1,"") | H16: =IFERROR(H2/D2-1,"") | I16: =IFERROR(I2/E2-1,"")
A17: Gross Margin | B17: =IFERROR(B4/B2,"") | C17: =IFERROR(C4/C2,"") | D17: =IFERROR(D4/D2,"") | E17: =IFERROR(E4/E2,"") | F17: =IFERROR(F4/F2,"") | G17: =IFERROR(G4/G2,"") | H17: =IFERROR(H4/H2,"") | I17: =IFERROR(I4/I2,"")
A19: Actual / Estimate | B19: A | C19: A | D19: A | E19: A | F19: A | G19: A | H19: E | I19: E
A20: Cash & Investments | G20: 1373.84 | H20: =G20+H12+H21 -> 1282.84 | I20: =H20+I12+I21 -> 1182.34
A21: Other Cash Flows (est.) | H21: 0 | I21: 0

Sheet Assumptions
A1: PRAX — rNPV assumptions ($mm unless noted)
A4: Scenario (1 = Bear, 2 = Base, 3 = Bull) | B4: 2 | C4: =CHOOSE($B$4,"Bear","Base","Bull") -> Base
A5: Overrides (blank = scenario value; the sensitivity tables drive these)
A6: Discount rate override
A7: PDUFA approval probability override
A8: PDUFA program peak sales override ($mm)
A10: Parameter | B10: Active | C10: Bear | D10: Base | E10: Bull
A12: Valuation & corporate
A13: Valuation date | B13: =DATE(2026,10,16) -> 46311
A14: Discount rate (cost of equity) | B14: =IF(ISNUMBER($B$6),$B$6,CHOOSE($B$4,C14,D14,E14)) -> 0.11 | C14: 0.125 | D14: 0.11 | E14: 0.095
A15: Tax rate | B15: =CHOOSE($B$4,C15,D15,E15) -> 0.21 | C15: 0.21 | D15: 0.21 | E15: 0.21
A16: Interest yield on cash | B16: =CHOOSE($B$4,C16,D16,E16) -> 0.0375 | C16: 0.0375 | D16: 0.0375 | E16: 0.0375
A17: Average cash cost of debt (P&L display only) | B17: =CHOOSE($B$4,C17,D17,E17) -> 0.025 | C17: 0.025 | D17: 0.025 | E17: 0.025
A18: Tax-loss pool at 12/31/2025 | B18: =CHOOSE($B$4,C18,D18,E18) -> 1200 | C18: 1200 | D18: 1200 | E18: 1200
A19: Corporate G&A, 2027 | B19: =CHOOSE($B$4,C19,D19,E19) -> 120 | C19: 120 | D19: 120 | E19: 120
A20: Platform / unallocated R&D, 2027 | B20: =CHOOSE($B$4,C20,D20,E20) -> 150 | C20: 150 | D20: 150 | E20: 150
A21: Cost inflation | B21: =CHOOSE($B$4,C21,D21,E21) -> 0.03 | C21: 0.03 | D21: 0.03 | E21: 0.03
A22: Corporate G&A floor, % of revenue | B22: =CHOOSE($B$4,C22,D22,E22) -> 0.08 | C22: 0.08 | D22: 0.08 | E22: 0.08
A23: Platform R&D floor, % of revenue | B23: =CHOOSE($B$4,C23,D23,E23) -> 0.12 | C23: 0.12 | D23: 0.12 | E23: 0.12
A24: Corporate cost cut after a CRL (2027+) | B24: =CHOOSE($B$4,C24,D24,E24) -> 0 | C24: 0 | D24: 0 | E24: 0
A25: Last year of base-level corporate costs (then % of revenue only) | B25: =CHOOSE($B$4,C25,D25,E25) -> 2042 | C25: 2042 | D25: 2042 | E25: 2042
A26: Annual share count growth (EPS display only) | B26: =CHOOSE($B$4,C26,D26,E26) -> 0 | C26: 0 | D26: 0 | E26: 0
A27: Wind-down cost for liquidation value | B27: =CHOOSE($B$4,C27,D27,E27) -> 60 | C27: 60 | D27: 60 | E27: 60
A29: PDUFA event
A30: PDUFA target action date | B30: =DATE(2026,12,27) -> 46383
A31: Application | B31: Relutrigine NDA, SCN2A/SCN8A developmental & epileptic encephalopathies
A32: Probability of approval at this PDUFA | B32: =IF(ISNUMBER($B$7),$B$7,CHOOSE($B$4,C32,D32,E32)) -> 0.9 | C32: 0.82 | D32: 0.9 | E32: 0.95
A33: Probability of approval later, after a CRL | B33: =CHOOSE($B$4,C33,D33,E33) -> 0.75 | C33: 0.7 | D33: 0.75 | E33: 0.8
A34: Launch delay after a CRL (years) | B34: =CHOOSE($B$4,C34,D34,E34) -> 1 | C34: 1 | D34: 1 | E34: 1
A35: Probability of approval, scenario value (before override) | B35: =CHOOSE($B$4,C32,D32,E32) -> 0.9
A36: Read-through: relative cut to other programs' PoS after a CRL | B36: =CHOOSE($B$4,C36,D36,E36) -> 0.05 | C36: 0.05 | D36: 0.05 | E36: 0.05
A37: Read-through multiplier on other programs' PoS (1 = none) | B37: =1+$B$36*($B$32-$B$35)/$B$35 -> 1
A38: Expected corporate cost multiplier (2027+) | B38: =$B$32+(1-$B$32)*(1-$B$24) -> 1
A40: Commercial curves (by year since launch)
A41: Year since launch | B41: 1 | C41: 2 | D41: 3 | E41: 4 | F41: 5 | G41: 6 | H41: 7
A42: Ramp 1 — standard launch, % of peak | B42: 0.1 | C42: 0.25 | D42: 0.45 | E42: 0.65 | F42: 0.82 | G42: 0.93 | H42: 1
A43: Ramp 2 — orphan-disease launch, % of peak | B43: 0.15 | C43: 0.35 | D43: 0.55 | E43: 0.75 | F43: 0.9 | G43: 1 | H43: 1
A44: Commercial SG&A, % of sales (years 1–5; floor = program maturity %) | B44: 0.9 | C44: 0.55 | D44: 0.4 | E44: 0.32 | F44: 0.28
A46: Relutrigine — SCN2A / SCN8A DEE (PDUFA)
A47: Launch year (first full year of sales) | B47: =CHOOSE($B$4,C47,D47,E47) -> 2027 | C47: 2027 | D47: 2027 | E47: 2027
A48: Peak net sales, unrisked | B48: =IF(ISNUMBER($B$8),$B$8,CHOOSE($B$4,C48,D48,E48)) -> 600 | C48: 300 | D48: 600 | E48: 1000
A49: Probability of approval (PDUFA event above) | B49: =$B$32 -> 0.9
A50: Company revenue, % of product net sales | B50: 1
A51: Cost of goods, % of product sales | B51: 0.04
A52: Royalties owed, % of product sales | B52: 0
A53: Commercial SG&A at maturity, % of sales | B53: 0.25
A54: Pre-launch commercial spend, year before launch | B54: 25
A55: Launch ramp (1 = standard, 2 = orphan) | B55: 2
A56: Loss of exclusivity (year) | B56: =CHOOSE($B$4,C56,D56,E56) -> 2041 | C56: 2041 | D56: 2041 | E56: 2041
A57: Post-LOE annual sales erosion | B57: 0.6
A58: Development spend, unrisked ($mm) by year | B58: 2027 | C58: 2028 | D58: 2029 | E58: 2030 | F58: 2031 | G58: 2032 | H58: 2033 | I58: 2034
A59: Cost | B59: 10 | C59: 0 | D59: 0 | E59: 0 | F59: 0 | G59: 0 | H59: 0 | I59: 0
A60: Probability the cost is incurred | B60: 1 | C60: 1 | D60: 1 | E60: 1 | F60: 1 | G60: 1 | H60: 1 | I60: 1
A61: Milestones / PRV received, by year relative to launch (on-time path) | B61: 0 | C61: 1 | D61: 2 | E61: 3 | F61: 4 | G61: 5 | H61: 6 | I61: 7 | J61: 8 | K61: 9
A62: Amount ($mm, unrisked) | B62: 150 | C62: 0 | D62: 0 | E62: 0 | F62: 0 | G62: 0 | H62: 0 | I62: 0 | J62: 0 | K62: 0
A64: Ulixacaltamide — essential tremor (PDUFA Jan 29, 2027) (pipeline)
A65: Launch year (first full year of sales) | B65: =CHOOSE($B$4,C65,D65,E65) -> 2027 | C65: 2027 | D65: 2027 | E65: 2027
A66: Peak net sales, unrisked | B66: =CHOOSE($B$4,C66,D66,E66) -> 3000 | C66: 1500 | D66: 3000 | E66: 5000
A67: Probability of reaching market | B67: =CHOOSE($B$4,C67,D67,E67) -> 0.85 | C67: 0.75 | D67: 0.85 | E67: 0.92
A68: Company revenue, % of product net sales | B68: 1
A69: Cost of goods, % of product sales | B69: 0.04
A70: Royalties owed, % of product sales | B70: 0
A71: Commercial SG&A at maturity, % of sales | B71: 0.3
A72: Pre-launch commercial spend, year before launch | B72: 80
A73: Launch ramp (1 = standard, 2 = orphan) | B73: 1
A74: Loss of exclusivity (year) | B74: =CHOOSE($B$4,C74,D74,E74) -> 2041 | C74: 2041 | D74: 2041 | E74: 2041
A75: Post-LOE annual sales erosion | B75: 0.6
A76: Development spend, unrisked ($mm) by year | B76: 2027 | C76: 2028 | D76: 2029 | E76: 2030 | F76: 2031 | G76: 2032 | H76: 2033 | I76: 2034
A77: Cost | B77: 20 | C77: 0 | D77: 0 | E77: 0 | F77: 0 | G77: 0 | H77: 0 | I77: 0
A78: Probability the cost is incurred | B78: 1 | C78: 1 | D78: 1 | E78: 1 | F78: 1 | G78: 1 | H78: 1 | I78: 1
A80: Relutrigine — broad DEEs (EMERALD, data Q4 2026) (pipeline)
A81: Launch year (first full year of sales) | B81: =CHOOSE($B$4,C81,D81,E81) -> 2028 | C81: 2028 | D81: 2028 | E81: 2028
A82: Peak net sales, unrisked | B82: =CHOOSE($B$4,C82,D82,E82) -> 1200 | C82: 500 | D82: 1200 | E82: 2500
A83: Probability of reaching market | B83: =CHOOSE($B$4,C83,D83,E83) -> 0.45 | C83: 0.3 | D83: 0.45 | E83: 0.6
A84: Company revenue, % of product net sales | B84: 1
A85: Cost of goods, % of product sales | B85: 0.04
A86: Royalties owed, % of product sales | B86: 0
A87: Commercial SG&A at maturity, % of sales | B87: 0.2
A88: Pre-launch commercial spend, year before launch | B88: 20
A89: Launch ramp (1 = standard, 2 = orphan) | B89: 2
A90: Loss of exclusivity (year) | B90: =CHOOSE($B$4,C90,D90,E90) -> 2041 | C90: 2041 | D90: 2041 | E90: 2041
A91: Post-LOE annual sales erosion | B91: 0.6
A92: Development spend, unrisked ($mm) by year | B92: 2027 | C92: 2028 | D92: 2029 | E92: 2030 | F92: 2031 | G92: 2032 | H92: 2033 | I92: 2034
A93: Cost | B93: 15 | C93: 0 | D93: 0 | E93: 0 | F93: 0 | G93: 0 | H93: 0 | I93: 0
A94: Probability the cost is incurred | B94: 1 | C94: 1 | D94: 1 | E94: 1 | F94: 1 | G94: 1 | H94: 1 | I94: 1
A96: Vormatrigine — focal / generalized epilepsy (POWER2/3) (pipeline)
A97: Launch year (first full year of sales) | B97: =CHOOSE($B$4,C97,D97,E97) -> 2030 | C97: 2030 | D97: 2030 | E97: 2030
A98: Peak net sales, unrisked | B98: =CHOOSE($B$4,C98,D98,E98) -> 1500 | C98: 800 | D98: 1500 | E98: 2500
A99: Probability of reaching market | B99: =CHOOSE($B$4,C99,D99,E99) -> 0.2 | C99: 0.15 | D99: 0.2 | E99: 0.3
A100: Company revenue, % of product net sales | B100: 1
A101: Cost of goods, % of product sales | B101: 0.04
A102: Royalties owed, % of product sales | B102: 0
A103: Commercial SG&A at maturity, % of sales | B103: 0.3
A104: Pre-launch commercial spend, year before launch | B104: 40
A105: Launch ramp (1 = standard, 2 = orphan) | B105: 1
A106: Loss of exclusivity (year) | B106: =CHOOSE($B$4,C106,D106,E106) -> 2043 | C106: 2043 | D106: 2043 | E106: 2043
A107: Post-LOE annual sales erosion | B107: 0.6
A108: Development spend, unrisked ($mm) by year | B108: 2027 | C108: 2028 | D108: 2029 | E108: 2030 | F108: 2031 | G108: 2032 | H108: 2033 | I108: 2034
A109: Cost | B109: 80 | C109: 80 | D109: 40 | E109: 0 | F109: 0 | G109: 0 | H109: 0 | I109: 0
A110: Probability the cost is incurred | B110: 1 | C110: 1 | D110: 0.5 | E110: 1 | F110: 1 | G110: 1 | H110: 1 | I110: 1
...

Sheet Pipeline
A1: PRAX — risk-adjusted program build ($mm)
A2: Year | C2: 2027 | D2: 2028 | E2: 2029 | F2: 2030 | G2: 2031 | H2: 2032 | I2: 2033 | J2: 2034 | K2: 2035 | L2: 2036 | M2: 2037 | N2: 2038 | O2: 2039 | P2: 2040 | Q2: 2041 | R2: 2042 | S2: 2043 | T2: 2044 | U2: 2045 | V2: 2046 | W2: 2047 | X2: 2048 | Y2: 2049 | Z2: 2050
A4: Relutrigine — SCN2A / SCN8A DEE
A5: Years since launch (approved on time) | C5: =C$2-Assumptions!$B$47+1 -> 1 | D5: =D$2-Assumptions!$B$47+1 -> 2 | E5: =E$2-Assumptions!$B$47+1 -> 3 | F5: =F$2-Assumptions!$B$47+1 -> 4 | G5: =G$2-Assumptions!$B$47+1 -> 5 | H5: =H$2-Assumptions!$B$47+1 -> 6 | I5: =I$2-Assumptions!$B$47+1 -> 7 | J5: =J$2-Assumptions!$B$47+1 -> 8 | ... Z5: =Z$2-Assumptions!$B$47+1 -> 24
A6: Net sales, unrisked (approved on time) | C6: =IF(C$2>Assumptions!$B$56,0*(1-Assumptions!$B$57),IF(C5>=1,Assumptions!$B$48*CHOOSE(Assumptions!$B$55,INDEX(Assumptions!$B$42:$H$42,MIN(C5,7)),INDEX(Assumptions!$B$43:$H$43,MIN(C5,7))),0)) -> 90 | D6: =IF(D$2>Assumptions!$B$56,C6*(1-Assumptions!$B$57),IF(D5>=1,Assumptions!$B$48*CHOOSE(Assumptions!$B$55,INDEX(Assumptions!$B$42:$H$42,MIN(D5,7)),INDEX(Assumptions!$B$43:$H$43,MIN(D5,7))),0)) -> 210 | E6: =IF(E$2>Assumptions!$B$56,D6*(1-Assumptions!$B$57),IF(E5>=1,Assumptions!$B$48*CHOOSE(Assumptions!$B$55,INDEX(Assumptions!$B$42:$H$42,MIN(E5,7)),INDEX(Assumptions!$B$43:$H$43,MIN(E5,7))),0)) -> 330 | F6: =IF(F$2>Assumptions!$B$56,E6*(1-Assumptions!$B$57),IF(F5>=1,Assumptions!$B$48*CHOOSE(Assumptions!$B$55,INDEX(Assumptions!$B$42:$H$42,MIN(F5,7)),INDEX(Assumptions!$B$43:$H$43,MIN(F5,7))),0)) -> 450 | G6: =IF(G$2>Assumptions!$B$56,F6*(1-Assumptions!$B$57),IF(G5>=1,Assumptions!$B$48*CHOOSE(Assumptions!$B$55,INDEX(Assumptions!$B$42:$H$42,MIN(G5,7)),INDEX(Assumptions!$B$43:$H$43,MIN(G5,7))),0)) -> 540 | H6: =IF(H$2>Assumptions!$B$56,G6*(1-Assumptions!$B$57),IF(H5>=1,Assumptions!$B$48*CHOOSE(Assumptions!$B$55,INDEX(Assumptions!$B$42:$H$42,MIN(H5,7)),INDEX(Assumptions!$B$43:$H$43,MIN(H5,7))),0)) -> 600 | I6: =IF(I$2>Assumptions!$B$56,H6*(1-Assumptions!$B$57),IF(I5>=1,Assumptions!$B$48*CHOOSE(Assumptions!$B$55,INDEX(Assumptions!$B$42:$H$42,MIN(I5,7)),INDEX(Assumptions!$B$43:$H$43,MIN(I5,7))),0)) -> 600 | J6: =IF(J$2>Assumptions!$B$56,I6*(1-Assumptions!$B$57),IF(J5>=1,Assumptions!$B$48*CHOOSE(Assumptions!$B$55,INDEX(Assumptions!$B$42:$H$42,MIN(J5,7)),INDEX(Assumptions!$B$43:$H$43,MIN(J5,7))),0)) -> 600 | K6: =IF(K$2>Assumptions!$B$56,J6*(1-Assumptions!$B$57),IF(K5>=1,Assumptions!$B$48*CHOOSE(Assumptions!$B$55,INDEX(Assumptions!$B$42:$H$42,MIN(K5,7)),INDEX(Assumptions!$B$43:$H$43,MIN(K5,7))),0)) -> 600 | ... Z6: =IF(Z$2>Assumptions!$B$56,Y6*(1-Assumptions!$B$57),IF(Z5>=1,Assumptions!$B$48*CHOOSE(Assumptions!$B$55,INDEX(Assumptions!$B$42:$H$42,MIN(Z5,7)),INDEX(Assumptions!$B$43:$H$43,MIN(Z5,7))),0)) -> 0.1572864
A7: Years since launch (approved after a CRL) | C7: =C$2-(Assumptions!$B$47+Assumptions!$B$34)+1 -> 0 | D7: =D$2-(Assumptions!$B$47+Assumptions!$B$34)+1 -> 1 | E7: =E$2-(Assumptions!$B$47+Assumptions!$B$34)+1 -> 2 | F7: =F$2-(Assumptions!$B$47+Assumptions!$B$34)+1 -> 3 | G7: =G$2-(Assumptions!$B$47+Assumptions!$B$34)+1 -> 4 | H7: =H$2-(Assumptions!$B$47+Assumptions!$B$34)+1 -> 5 | I7: =I$2-(Assumptions!$B$47+Assumptions!$B$34)+1 -> 6 | J7: =J$2-(Assumptions!$B$47+Assumptions!$B$34)+1 -> 7 | ... Z7: =Z$2-(Assumptions!$B$47+Assumptions!$B$34)+1 -> 23
A8: Net sales, unrisked (approved after a CRL) | C8: =IF(C$2>Assumptions!$B$56,0*(1-Assumptions!$B$57),IF(C7>=1,Assumptions!$B$48*CHOOSE(Assumptions!$B$55,INDEX(Assumptions!$B$42:$H$42,MIN(C7,7)),INDEX(Assumptions!$B$43:$H$43,MIN(C7,7))),0)) -> 0 | D8: =IF(D$2>Assumptions!$B$56,C8*(1-Assumptions!$B$57),IF(D7>=1,Assumptions!$B$48*CHOOSE(Assumptions!$B$55,INDEX(Assumptions!$B$42:$H$42,MIN(D7,7)),INDEX(Assumptions!$B$43:$H$43,MIN(D7,7))),0)) -> 90 | E8: =IF(E$2>Assumptions!$B$56,D8*(1-Assumptions!$B$57),IF(E7>=1,Assumptions!$B$48*CHOOSE(Assumptions!$B$55,INDEX(Assumptions!$B$42:$H$42,MIN(E7,7)),INDEX(Assumptions!$B$43:$H$43,MIN(E7,7))),0)) -> 210 | F8: =IF(F$2>Assumptions!$B$56,E8*(1-Assumptions!$B$57),IF(F7>=1,Assumptions!$B$48*CHOOSE(Assumptions!$B$55,INDEX(Assumptions!$B$42:$H$42,MIN(F7,7)),INDEX(Assumptions!$B$43:$H$43,MIN(F7,7))),0)) -> 330 | G8: =IF(G$2>Assumptions!$B$56,F8*(1-Assumptions!$B$57),IF(G7>=1,Assumptions!$B$48*CHOOSE(Assumptions!$B$55,INDEX(Assumptions!$B$42:$H$42,MIN(G7,7)),INDEX(Assumptions!$B$43:$H$43,MIN(G7,7))),0)) -> 450 | H8: =IF(H$2>Assumptions!$B$56,G8*(1-Assumptions!$B$57),IF(H7>=1,Assumptions!$B$48*CHOOSE(Assumptions!$B$55,INDEX(Assumptions!$B$42:$H$42,MIN(H7,7)),INDEX(Assumptions!$B$43:$H$43,MIN(H7,7))),0)) -> 540 | I8: =IF(I$2>Assumptions!$B$56,H8*(1-Assumptions!$B$57),IF(I7>=1,Assumptions!$B$48*CHOOSE(Assumptions!$B$55,INDEX(Assumptions!$B$42:$H$42,MIN(I7,7)),INDEX(Assumptions!$B$43:$H$43,MIN(I7,7))),0)) -> 600 | J8: =IF(J$2>Assumptions!$B$56,I8*(1-Assumptions!$B$57),IF(J7>=1,Assumptions!$B$48*CHOOSE(Assumptions!$B$55,INDEX(Assumptions!$B$42:$H$42,MIN(J7,7)),INDEX(Assumptions!$B$43:$H$43,MIN(J7,7))),0)) -> 600 | K8: =IF(K$2>Assumptions!$B$56,J8*(1-Assumptions!$B$57),IF(K7>=1,Assumptions!$B$48*CHOOSE(Assumptions!$B$55,INDEX(Assumptions!$B$42:$H$42,MIN(K7,7)),INDEX(Assumptions!$B$43:$H$43,MIN(K7,7))),0)) -> 600 | ... Z8: =IF(Z$2>Assumptions!$B$56,Y8*(1-Assumptions!$B$57),IF(Z7>=1,Assumptions!$B$48*CHOOSE(Assumptions!$B$55,INDEX(Assumptions!$B$42:$H$42,MIN(Z7,7)),INDEX(Assumptions!$B$43:$H$43,MIN(Z7,7))),0)) -> 0.1572864
A9: Product net sales, risk-adjusted | C9: =Assumptions!$B$32*C6+(1-Assumptions!$B$32)*Assumptions!$B$33*C8 -> 81 | D9: =Assumptions!$B$32*D6+(1-Assumptions!$B$32)*Assumptions!$B$33*D8 -> 195.75 | E9: =Assumptions!$B$32*E6+(1-Assumptions!$B$32)*Assumptions!$B$33*E8 -> 312.75 | F9: =Assumptions!$B$32*F6+(1-Assumptions!$B$32)*Assumptions!$B$33*F8 -> 429.75 | G9: =Assumptions!$B$32*G6+(1-Assumptions!$B$32)*Assumptions!$B$33*G8 -> 519.75 | H9: =Assumptions!$B$32*H6+(1-Assumptions!$B$32)*Assumptions!$B$33*H8 -> 580.5 | I9: =Assumptions!$B$32*I6+(1-Assumptions!$B$32)*Assumptions!$B$33*I8 -> 585 | J9: =Assumptions!$B$32*J6+(1-Assumptions!$B$32)*Assumptions!$B$33*J8 -> 585 | ... Z9: =Assumptions!$B$32*Z6+(1-Assumptions!$B$32)*Assumptions!$B$33*Z8 -> 0.15335424
A10: Company revenue, risk-adjusted (incl. milestones) | C10: =C9*Assumptions!$B$50+Assumptions!$B$32*IFERROR(INDEX(Assumptions!$B$62:$K$62,MATCH(C$2-Assumptions!$B$47,Assumptions!$B$61:$K$61,0)),0)+(1-Assumptions!$B$32)*Assumptions!$B$33*IFERROR(INDEX(Assumptions!$B$62:$K$62,MATCH(C$2-Assumptions!$B$47-Assumptions!$B$34,Assumptions!$B$61:$K$61,0)),0) -> 216 | D10: =D9*Assumptions!$B$50+Assumptions!$B$32*IFERROR(INDEX(Assumptions!$B$62:$K$62,MATCH(D$2-Assumptions!$B$47,Assumptions!$B$61:$K$61,0)),0)+(1-Assumptions!$B$32)*Assumptions!$B$33*IFERROR(INDEX(Assumptions!$B$62:$K$62,MATCH(D$2-Assumptions!$B$47-Assumptions!$B$34,Assumptions!$B$61:$K$61,0)),0) -> 207 | E10: =E9*Assumptions!$B$50+Assumptions!$B$32*IFERROR(INDEX(Assumptions!$B$62:$K$62,MATCH(E$2-Assumptions!$B$47,Assumptions!$B$61:$K$61,0)),0)+(1-Assumptions!$B$32)*Assumptions!$B$33*IFERROR(INDEX(Assumptions!$B$62:$K$62,MATCH(E$2-Assumptions!$B$47-Assumptions!$B$34,Assumptions!$B$61:$K$61,0)),0) -> 312.75 | F10: =F9*Assumptions!$B$50+Assumptions!$B$32*IFERROR(INDEX(Assumptions!$B$62:$K$62,MATCH(F$2-Assumptions!$B$47,Assumptions!$B$61:$K$61,0)),0)+(1-Assumptions!$B$32)*Assumptions!$B$33*IFERROR(INDEX(Assumptions!$B$62:$K$62,MATCH(F$2-Assumptions!$B$47-Assumptions!$B$34,Assumptions!$B$61:$K$61,0)),0) -> 429.75 | G10: =G9*Assumptions!$B$50+Assumptions!$B$32*IFERROR(INDEX(Assumptions!$B$62:$K$62,MATCH(G$2-Assumptions!$B$47,Assumptions!$B$61:$K$61,0)),0)+(1-Assumptions!$B$32)*Assumptions!$B$33*IFERROR(INDEX(Assumptions!$B$62:$K$62,MATCH(G$2-Assumptions!$B$47-Assumptions!$B$34,Assumptions!$B$61:$K$61,0)),0) -> 519.75 | H10: =H9*Assumptions!$B$50+Assumptions!$B$32*IFERROR(INDEX(Assumptions!$B$62:$K$62,MATCH(H$2-Assumptions!$B$47,Assumptions!$B$61:$K$61,0)),0)+(1-Assumptions!$B$32)*Assumptions!$B$33*IFERROR(INDEX(Assumptions!$B$62:$K$62,MATCH(H$2-Assumptions!$B$47-Assumptions!$B$34,Assumptions!$B$61:$K$61,0)),0) -> 580.5 | I10: =I9*Assumptions!$B$50+Assumptions!$B$32*IFERROR(INDEX(Assumptions!$B$62:$K$62,MATCH(I$2-Assumptions!$B$47,Assumptions!$B$61:$K$61,0)),0)+(1-Assumptions!$B$32)*Assumptions!$B$33*IFERROR(INDEX(Assumptions!$B$62:$K$62,MATCH(I$2-Assumptions!$B$47-Assumptions!$B$34,Assumptions!$B$61:$K$61,0)),0) -> 585 | J10: =J9*Assumptions!$B$50+Assumptions!$B$32*IFERROR(INDEX(Assumptions!$B$62:$K$62,MATCH(J$2-Assumptions!$B$47,Assumptions!$B$61:$K$61,0)),0)+(1-Assumptions!$B$32)*Assumptions!$B$33*IFERROR(INDEX(Assumptions!$B$62:$K$62,MATCH(J$2-Assumptions!$B$47-Assumptions!$B$34,Assumptions!$B$61:$K$61,0)),0) -> 585 | ... Z10: =Z9*Assumptions!$B$50+Assumptions!$B$32*IFERROR(INDEX(Assumptions!$B$62:$K$62,MATCH(Z$2-Assumptions!$B$47,Assumptions!$B$61:$K$61,0)),0)+(1-Assumptions!$B$32)*Assumptions!$B$33*IFERROR(INDEX(Assumptions!$B$62:$K$62,MATCH(Z$2-Assumptions!$B$47-Assumptions!$B$34,Assumptions!$B$61:$K$61,0)),0) -> 0.15335424
A11: COGS + royalties, risk-adjusted | C11: =C9*(Assumptions!$B$51+Assumptions!$B$52) -> 3.24 | D11: =D9*(Assumptions!$B$51+Assumptions!$B$52) -> 7.83 | E11: =E9*(Assumptions!$B$51+Assumptions!$B$52) -> 12.51 | F11: =F9*(Assumptions!$B$51+Assumptions!$B$52) -> 17.19 | G11: =G9*(Assumptions!$B$51+Assumptions!$B$52) -> 20.79 | H11: =H9*(Assumptions!$B$51+Assumptions!$B$52) -> 23.22 | I11: =I9*(Assumptions!$B$51+Assumptions!$B$52) -> 23.4 | J11: =J9*(Assumptions!$B$51+Assumptions!$B$52) -> 23.4 | ... Z11: =Z9*(Assumptions!$B$51+Assumptions!$B$52) -> 0.0061341696
A12: Commercial SG&A, risk-adjusted | C12: =Assumptions!$B$32*IF(Assumptions!$B$53=0,0,IF(C5=0,Assumptions!$B$54,IF(C5>=1,C6*IF(OR(Assumptions!$B$50<1,C5>5),Assumptions!$B$53,MAX(Assumptions!$B$53,INDEX(Assumptions!$B$44:$F$44,C5))),0)))+(1-Assumptions!$B$32)*Assumptions!$B$33*IF(Assumptions!$B$53=0,0,IF(C7=0,Assumptions!$B$54,IF(C7>=1,C8*IF(OR(Assumptions!$B$50<1,C7>5),Assumptions!$B$53,MAX(Assumptions!$B$53,INDEX(Assumptions!$B$44:$F$44,C7))),0))) -> 74.775 | D12: =Assumptions!$B$32*IF(Assumptions!$B$53=0,0,IF(D5=0,Assumptions!$B$54,IF(D5>=1,D6*IF(OR(Assumptions!$B$50<1,D5>5),Assumptions!$B$53,MAX(Assumptions!$B$53,INDEX(Assumptions!$B$44:$F$44,D5))),0)))+(1-Assumptions!$B$32)*Assumptions!$B$33*IF(Assumptions!$B$53=0,0,IF(D7=0,Assumptions!$B$54,IF(D7>=1,D8*IF(OR(Assumptions!$B$50<1,D7>5),Assumptions!$B$53,MAX(Assumptions!$B$53,INDEX(Assumptions!$B$44:$F$44,D7))),0))) -> 110.025 | E12: =Assumptions!$B$32*IF(Assumptions!$B$53=0,0,IF(E5=0,Assumptions!$B$54,IF(E5>=1,E6*IF(OR(Assumptions!$B$50<1,E5>5),Assumptions!$B$53,MAX(Assumptions!$B$53,INDEX(Assumptions!$B$44:$F$44,E5))),0)))+(1-Assumptions!$B$32)*Assumptions!$B$33*IF(Assumptions!$B$53=0,0,IF(E7=0,Assumptions!$B$54,IF(E7>=1,E8*IF(OR(Assumptions!$B$50<1,E7>5),Assumptions!$B$53,MAX(Assumptions!$B$53,INDEX(Assumptions!$B$44:$F$44,E7))),0))) -> 127.4625 | F12: =Assumptions!$B$32*IF(Assumptions!$B$53=0,0,IF(F5=0,Assumptions!$B$54,IF(F5>=1,F6*IF(OR(Assumptions!$B$50<1,F5>5),Assumptions!$B$53,MAX(Assumptions!$B$53,INDEX(Assumptions!$B$44:$F$44,F5))),0)))+(1-Assumptions!$B$32)*Assumptions!$B$33*IF(Assumptions!$B$53=0,0,IF(F7=0,Assumptions!$B$54,IF(F7>=1,F8*IF(OR(Assumptions!$B$50<1,F7>5),Assumptions!$B$53,MAX(Assumptions!$B$53,INDEX(Assumptions!$B$44:$F$44,F7))),0))) -> 139.5 | G12: =Assumptions!$B$32*IF(Assumptions!$B$53=0,0,IF(G5=0,Assumptions!$B$54,IF(G5>=1,G6*IF(OR(Assumptions!$B$50<1,G5>5),Assumptions!$B$53,MAX(Assumptions!$B$53,INDEX(Assumptions!$B$44:$F$44,G5))),0)))+(1-Assumptions!$B$32)*Assumptions!$B$33*IF(Assumptions!$B$53=0,0,IF(G7=0,Assumptions!$B$54,IF(G7>=1,G8*IF(OR(Assumptions!$B$50<1,G7>5),Assumptions!$B$53,MAX(Assumptions!$B$53,INDEX(Assumptions!$B$44:$F$44,G7))),0))) -> 146.88 | H12: =Assumptions!$B$32*IF(Assumptions!$B$53=0,0,IF(H5=0,Assumptions!$B$54,IF(H5>=1,H6*IF(OR(Assumptions!$B$50<1,H5>5),Assumptions!$B$53,MAX(Assumptions!$B$53,INDEX(Assumptions!$B$44:$F$44,H5))),0)))+(1-Assumptions!$B$32)*Assumptions!$B$33*IF(Assumptions!$B$53=0,0,IF(H7=0,Assumptions!$B$54,IF(H7>=1,H8*IF(OR(Assumptions!$B$50<1,H7>5),Assumptions!$B$53,MAX(Assumptions!$B$53,INDEX(Assumptions!$B$44:$F$44,H7))),0))) -> 146.34 | I12: =Assumptions!$B$32*IF(Assumptions!$B$53=0,0,IF(I5=0,Assumptions!$B$54,IF(I5>=1,I6*IF(OR(Assumptions!$B$50<1,I5>5),Assumptions!$B$53,MAX(Assumptions!$B$53,INDEX(Assumptions!$B$44:$F$44,I5))),0)))+(1-Assumptions!$B$32)*Assumptions!$B$33*IF(Assumptions!$B$53=0,0,IF(I7=0,Assumptions!$B$54,IF(I7>=1,I8*IF(OR(Assumptions!$B$50<1,I7>5),Assumptions!$B$53,MAX(Assumptions!$B$53,INDEX(Assumptions!$B$44:$F$44,I7))),0))) -> 146.25 | J12: =Assumptions!$B$32*IF(Assumptions!$B$53=0,0,IF(J5=0,Assumptions!$B$54,IF(J5>=1,J6*IF(OR(Assumptions!$B$50<1,J5>5),Assumptions!$B$53,MAX(Assumptions!$B$53,INDEX(Assumptions!$B$44:$F$44,J5))),0)))+(1-Assumptions!$B$32)*Assumptions!$B$33*IF(Assumptions!$B$53=0,0,IF(J7=0,Assumptions!$B$54,IF(J7>=1,J8*IF(OR(Assumptions!$B$50<1,J7>5),Assumptions!$B$53,MAX(Assumptions!$B$53,INDEX(Assumptions!$B$44:$F$44,J7))),0))) -> 146.25 | ... Z12: =Assumptions!$B$32*IF(Assumptions!$B$53=0,0,IF(Z5=0,Assumptions!$B$54,IF(Z5>=1,Z6*IF(OR(Assumptions!$B$50<1,Z5>5),Assumptions!$B$53,MAX(Assumptions!$B$53,INDEX(Assumptions!$B$44:$F$44,Z5))),0)))+(1-Assumptions!$B$32)*Assumptions!$B$33*IF(Assumptions!$B$53=0,0,IF(Z7=0,Assumptions!$B$54,IF(Z7>=1,Z8*IF(OR(Assumptions!$B$50<1,Z7>5),Assumptions!$B$53,MAX(Assumptions!$B$53,INDEX(Assumptions!$B$44:$F$44,Z7))),0))) -> 0.03833856
A13: Development R&D, risk-adjusted | C13: =IFERROR(INDEX(Assumptions!$B$59:$I$59,MATCH(C$2,Assumptions!$B$58:$I$58,0))*INDEX(Assumptions!$B$60:$I$60,MATCH(C$2,Assumptions!$B$58:$I$58,0)),0) -> 10 | D13: =IFERROR(INDEX(Assumptions!$B$59:$I$59,MATCH(D$2,Assumptions!$B$58:$I$58,0))*INDEX(Assumptions!$B$60:$I$60,MATCH(D$2,Assumptions!$B$58:$I$58,0)),0) -> 0 | E13: =IFERROR(INDEX(Assumptions!$B$59:$I$59,MATCH(E$2,Assumptions!$B$58:$I$58,0))*INDEX(Assumptions!$B$60:$I$60,MATCH(E$2,Assumptions!$B$58:$I$58,0)),0) -> 0 | F13: =IFERROR(INDEX(Assumptions!$B$59:$I$59,MATCH(F$2,Assumptions!$B$58:$I$58,0))*INDEX(Assumptions!$B$60:$I$60,MATCH(F$2,Assumptions!$B$58:$I$58,0)),0) -> 0 | G13: =IFERROR(INDEX(Assumptions!$B$59:$I$59,MATCH(G$2,Assumptions!$B$58:$I$58,0))*INDEX(Assumptions!$B$60:$I$60,MATCH(G$2,Assumptions!$B$58:$I$58,0)),0) -> 0 | H13: =IFERROR(INDEX(Assumptions!$B$59:$I$59,MATCH(H$2,Assumptions!$B$58:$I$58,0))*INDEX(Assumptions!$B$60:$I$60,MATCH(H$2,Assumptions!$B$58:$I$58,0)),0) -> 0 | I13: =IFERROR(INDEX(Assumptions!$B$59:$I$59,MATCH(I$2,Assumptions!$B$58:$I$58,0))*INDEX(Assumptions!$B$60:$I$60,MATCH(I$2,Assumptions!$B$58:$I$58,0)),0) -> 0 | J13: =IFERROR(INDEX(Assumptions!$B$59:$I$59,MATCH(J$2,Assumptions!$B$58:$I$58,0))*INDEX(Assumptions!$B$60:$I$60,MATCH(J$2,Assumptions!$B$58:$I$58,0)),0) -> 0 | ... Z13: =IFERROR(INDEX(Assumptions!$B$59:$I$59,MATCH(Z$2,Assumptions!$B$58:$I$58,0))*INDEX(Assumptions!$B$60:$I$60,MATCH(Z$2,Assumptions!$B$58:$I$58,0)),0) -> 0
A14: Program contribution (pre-tax) | C14: =C10-C11-C12-C13 -> 127.985 | D14: =D10-D11-D12-D13 -> 89.145 | E14: =E10-E11-E12-E13 -> 172.7775 | F14: =F10-F11-F12-F13 -> 273.06 | G14: =G10-G11-G12-G13 -> 352.08 | H14: =H10-H11-H12-H13 -> 410.94 | I14: =I10-I11-I12-I13 -> 415.35 | J14: =J10-J11-J12-J13 -> 415.35 | ... Z14: =Z10-Z11-Z12-Z13 -> 0.10888151
A16: Ulixacaltamide — essential tremor (PDUFA Jan 29, 2027)
A17: Years since launch | C17: =C$2-Assumptions!$B$65+1 -> 1 | D17: =D$2-Assumptions!$B$65+1 -> 2 | E17: =E$2-Assumptions!$B$65+1 -> 3 | F17: =F$2-Assumptions!$B$65+1 -> 4 | G17: =G$2-Assumptions!$B$65+1 -> 5 | H17: =H$2-Assumptions!$B$65+1 -> 6 | I17: =I$2-Assumptions!$B$65+1 -> 7 | J17: =J$2-Assumptions!$B$65+1 -> 8 | ... Z17: =Z$2-Assumptions!$B$65+1 -> 24
A18: Net sales, unrisked | C18: =IF(C$2>Assumptions!$B$74,0*(1-Assumptions!$B$75),IF(C17>=1,Assumptions!$B$66*CHOOSE(Assumptions!$B$73,INDEX(Assumptions!$B$42:$H$42,MIN(C17,7)),INDEX(Assumptions!$B$43:$H$43,MIN(C17,7))),0)) -> 300 | D18: =IF(D$2>Assumptions!$B$74,C18*(1-Assumptions!$B$75),IF(D17>=1,Assumptions!$B$66*CHOOSE(Assumptions!$B$73,INDEX(Assumptions!$B$42:$H$42,MIN(D17,7)),INDEX(Assumptions!$B$43:$H$43,MIN(D17,7))),0)) -> 750 | E18: =IF(E$2>Assumptions!$B$74,D18*(1-Assumptions!$B$75),IF(E17>=1,Assumptions!$B$66*CHOOSE(Assumptions!$B$73,INDEX(Assumptions!$B$42:$H$42,MIN(E17,7)),INDEX(Assumptions!$B$43:$H$43,MIN(E17,7))),0)) -> 1350 | F18: =IF(F$2>Assumptions!$B$74,E18*(1-Assumptions!$B$75),IF(F17>=1,Assumptions!$B$66*CHOOSE(Assumptions!$B$73,INDEX(Assumptions!$B$42:$H$42,MIN(F17,7)),INDEX(Assumptions!$B$43:$H$43,MIN(F17,7))),0)) -> 1950 | G18: =IF(G$2>Assumptions!$B$74,F18*(1-Assumptions!$B$75),IF(G17>=1,Assumptions!$B$66*CHOOSE(Assumptions!$B$73,INDEX(Assumptions!$B$42:$H$42,MIN(G17,7)),INDEX(Assumptions!$B$43:$H$43,MIN(G17,7))),0)) -> 2460 | H18: =IF(H$2>Assumptions!$B$74,G18*(1-Assumptions!$B$75),IF(H17>=1,Assumptions!$B$66*CHOOSE(Assumptions!$B$73,INDEX(Assumptions!$B$42:$H$42,MIN(H17,7)),INDEX(Assumptions!$B$43:$H$43,MIN(H17,7))),0)) -> 2790 | I18: =IF(I$2>Assumptions!$B$74,H18*(1-Assumptions!$B$75),IF(I17>=1,Assumptions!$B$66*CHOOSE(Assumptions!$B$73,INDEX(Assumptions!$B$42:$H$42,MIN(I17,7)),INDEX(Assumptions!$B$43:$H$43,MIN(I17,7))),0)) -> 3000 | J18: =IF(J$2>Assumptions!$B$74,I18*(1-Assumptions!$B$75),IF(J17>=1,Assumptions!$B$66*CHOOSE(Assumptions!$B$73,INDEX(Assumptions!$B$42:$H$42,MIN(J17,7)),INDEX(Assumptions!$B$43:$H$43,MIN(J17,7))),0)) -> 3000 | K18: =IF(K$2>Assumptions!$B$74,J18*(1-Assumptions!$B$75),IF(K17>=1,Assumptions!$B$66*CHOOSE(Assumptions!$B$73,INDEX(Assumptions!$B$42:$H$42,MIN(K17,7)),INDEX(Assumptions!$B$43:$H$43,MIN(K17,7))),0)) -> 3000 | ... Z18: =IF(Z$2>Assumptions!$B$74,Y18*(1-Assumptions!$B$75),IF(Z17>=1,Assumptions!$B$66*CHOOSE(Assumptions!$B$73,INDEX(Assumptions!$B$42:$H$42,MIN(Z17,7)),INDEX(Assumptions!$B$43:$H$43,MIN(Z17,7))),0)) -> 0.786432
A19: Product net sales, risk-adjusted | C19: =C18*MIN(1,Assumptions!$B$67*Assumptions!$B$37) -> 255 | D19: =D18*MIN(1,Assumptions!$B$67*Assumptions!$B$37) -> 637.5 | E19: =E18*MIN(1,Assumptions!$B$67*Assumptions!$B$37) -> 1147.5 | F19: =F18*MIN(1,Assumptions!$B$67*Assumptions!$B$37) -> 1657.5 | G19: =G18*MIN(1,Assumptions!$B$67*Assumptions!$B$37) -> 2091 | H19: =H18*MIN(1,Assumptions!$B$67*Assumptions!$B$37) -> 2371.5 | I19: =I18*MIN(1,Assumptions!$B$67*Assumptions!$B$37) -> 2550 | J19: =J18*MIN(1,Assumptions!$B$67*Assumptions!$B$37) -> 2550 | ... Z19: =Z18*MIN(1,Assumptions!$B$67*Assumptions!$B$37) -> 0.6684672
A20: Company revenue, risk-adjusted (incl. milestones) | C20: =C19*Assumptions!$B$68 -> 255 | D20: =D19*Assumptions!$B$68 -> 637.5 | E20: =E19*Assumptions!$B$68 -> 1147.5 | F20: =F19*Assumptions!$B$68 -> 1657.5 | G20: =G19*Assumptions!$B$68 -> 2091 | H20: =H19*Assumptions!$B$68 -> 2371.5 | I20: =I19*Assumptions!$B$68 -> 2550 | J20: =J19*Assumptions!$B$68 -> 2550 | ... Z20: =Z19*Assumptions!$B$68 -> 0.6684672
A21: COGS + royalties, risk-adjusted | C21: =C19*(Assumptions!$B$69+Assumptions!$B$70) -> 10.2 | D21: =D19*(Assumptions!$B$69+Assumptions!$B$70) -> 25.5 | E21: =E19*(Assumptions!$B$69+Assumptions!$B$70) -> 45.9 | F21: =F19*(Assumptions!$B$69+Assumptions!$B$70) -> 66.3 | G21: =G19*(Assumptions!$B$69+Assumptions!$B$70) -> 83.64 | H21: =H19*(Assumptions!$B$69+Assumptions!$B$70) -> 94.86 | I21: =I19*(Assumptions!$B$69+Assumptions!$B$70) -> 102 | J21: =J19*(Assumptions!$B$69+Assumptions!$B$70) -> 102 | ... Z21: =Z19*(Assumptions!$B$69+Assumptions!$B$70) -> 0.026738688
A22: Commercial SG&A, risk-adjusted | C22: =MIN(1,Assumptions!$B$67*Assumptions!$B$37)*IF(Assumptions!$B$71=0,0,IF(C17=0,Assumptions!$B$72,IF(C17>=1,C18*IF(OR(Assumptions!$B$68<1,C17>5),Assumptions!$B$71,MAX(Assumptions!$B$71,INDEX(Assumptions!$B$44:$F$44,C17))),0))) -> 229.5 | D22: =MIN(1,Assumptions!$B$67*Assumptions!$B$37)*IF(Assumptions!$B$71=0,0,IF(D17=0,Assumptions!$B$72,IF(D17>=1,D18*IF(OR(Assumptions!$B$68<1,D17>5),Assumptions!$B$71,MAX(Assumptions!$B$71,INDEX(Assumptions!$B$44:$F$44,D17))),0))) -> 350.625 | E22: =MIN(1,Assumptions!$B$67*Assumptions!$B$37)*IF(Assumptions!$B$71=0,0,IF(E17=0,Assumptions!$B$72,IF(E17>=1,E18*IF(OR(Assumptions!$B$68<1,E17>5),Assumptions!$B$71,MAX(Assumptions!$B$71,INDEX(Assumptions!$B$44:$F$44,E17))),0))) -> 459 | F22: =MIN(1,Assumptions!$B$67*Assumptions!$B$37)*IF(Assumptions!$B$71=0,0,IF(F17=0,Assumptions!$B$72,IF(F17>=1,F18*IF(OR(Assumptions!$B$68<1,F17>5),Assumptions!$B$71,MAX(Assumptions!$B$71,INDEX(Assumptions!$B$44:$F$44,F17))),0))) -> 530.4 | G22: =MIN(1,Assumptions!$B$67*Assumptions!$B$37)*IF(Assumptions!$B$71=0,0,IF(G17=0,Assumptions!$B$72,IF(G17>=1,G18*IF(OR(Assumptions!$B$68<1,G17>5),Assumptions!$B$71,MAX(Assumptions!$B$71,INDEX(Assumptions!$B$44:$F$44,G17))),0))) -> 627.3 | H22: =MIN(1,Assumptions!$B$67*Assumptions!$B$37)*IF(Assumptions!$B$71=0,0,IF(H17=0,Assumptions!$B$72,IF(H17>=1,H18*IF(OR(Assumptions!$B$68<1,H17>5),Assumptions!$B$71,MAX(Assumptions!$B$71,INDEX(Assumptions!$B$44:$F$44,H17))),0))) -> 711.45 | I22: =MIN(1,Assumptions!$B$67*Assumptions!$B$37)*IF(Assumptions!$B$71=0,0,IF(I17=0,Assumptions!$B$72,IF(I17>=1,I18*IF(OR(Assumptions!$B$68<1,I17>5),Assumptions!$B$71,MAX(Assumptions!$B$71,INDEX(Assumptions!$B$44:$F$44,I17))),0))) -> 765 | J22: =MIN(1,Assumptions!$B$67*Assumptions!$B$37)*IF(Assumptions!$B$71=0,0,IF(J17=0,Assumptions!$B$72,IF(J17>=1,J18*IF(OR(Assumptions!$B$68<1,J17>5),Assumptions!$B$71,MAX(Assumptions!$B$71,INDEX(Assumptions!$B$44:$F$44,J17))),0))) -> 765 | ... Z22: =MIN(1,Assumptions!$B$67*Assumptions!$B$37)*IF(Assumptions!$B$71=0,0,IF(Z17=0,Assumptions!$B$72,IF(Z17>=1,Z18*IF(OR(Assumptions!$B$68<1,Z17>5),Assumptions!$B$71,MAX(Assumptions!$B$71,INDEX(Assumptions!$B$44:$F$44,Z17))),0))) -> 0.20054016
A23: Development R&D, risk-adjusted | C23: =IFERROR(INDEX(Assumptions!$B$77:$I$77,MATCH(C$2,Assumptions!$B$76:$I$76,0))*INDEX(Assumptions!$B$78:$I$78,MATCH(C$2,Assumptions!$B$76:$I$76,0)),0) -> 20 | D23: =IFERROR(INDEX(Assumptions!$B$77:$I$77,MATCH(D$2,Assumptions!$B$76:$I$76,0))*INDEX(Assumptions!$B$78:$I$78,MATCH(D$2,Assumptions!$B$76:$I$76,0)),0) -> 0 | E23: =IFERROR(INDEX(Assumptions!$B$77:$I$77,MATCH(E$2,Assumptions!$B$76:$I$76,0))*INDEX(Assumptions!$B$78:$I$78,MATCH(E$2,Assumptions!$B$76:$I$76,0)),0) -> 0 | F23: =IFERROR(INDEX(Assumptions!$B$77:$I$77,MATCH(F$2,Assumptions!$B$76:$I$76,0))*INDEX(Assumptions!$B$78:$I$78,MATCH(F$2,Assumptions!$B$76:$I$76,0)),0) -> 0 | G23: =IFERROR(INDEX(Assumptions!$B$77:$I$77,MATCH(G$2,Assumptions!$B$76:$I$76,0))*INDEX(Assumptions!$B$78:$I$78,MATCH(G$2,Assumptions!$B$76:$I$76,0)),0) -> 0 | H23: =IFERROR(INDEX(Assumptions!$B$77:$I$77,MATCH(H$2,Assumptions!$B$76:$I$76,0))*INDEX(Assumptions!$B$78:$I$78,MATCH(H$2,Assumptions!$B$76:$I$76,0)),0) -> 0 | I23: =IFERROR(INDEX(Assumptions!$B$77:$I$77,MATCH(I$2,Assumptions!$B$76:$I$76,0))*INDEX(Assumptions!$B$78:$I$78,MATCH(I$2,Assumptions!$B$76:$I$76,0)),0) -> 0 | J23: =IFERROR(INDEX(Assumptions!$B$77:$I$77,MATCH(J$2,Assumptions!$B$76:$I$76,0))*INDEX(Assumptions!$B$78:$I$78,MATCH(J$2,Assumptions!$B$76:$I$76,0)),0) -> 0 | ... Z23: =IFERROR(INDEX(Assumptions!$B$77:$I$77,MATCH(Z$2,Assumptions!$B$76:$I$76,0))*INDEX(Assumptions!$B$78:$I$78,MATCH(Z$2,Assumptions!$B$76:$I$76,0)),0) -> 0
A24: Program contribution (pre-tax) | C24: =C20-C21-C22-C23 -> -4.7 | D24: =D20-D21-D22-D23 -> 261.375 | E24: =E20-E21-E22-E23 -> 642.6 | F24: =F20-F21-F22-F23 -> 1060.8 | G24: =G20-G21-G22-G23 -> 1380.06 | H24: =H20-H21-H22-H23 -> 1565.19 | I24: =I20-I21-I22-I23 -> 1683 | J24: =J20-J21-J22-J23 -> 1683 | ... Z24: =Z20-Z21-Z22-Z23 -> 0.44118835
A26: Relutrigine — broad DEEs (EMERALD, data Q4 2026)
A27: Years since launch | C27: =C$2-Assumptions!$B$81+1 -> 0 | D27: =D$2-Assumptions!$B$81+1 -> 1 | E27: =E$2-Assumptions!$B$81+1 -> 2 | F27: =F$2-Assumptions!$B$81+1 -> 3 | G27: =G$2-Assumptions!$B$81+1 -> 4 | H27: =H$2-Assumptions!$B$81+1 -> 5 | I27: =I$2-Assumptions!$B$81+1 -> 6 | J27: =J$2-Assumptions!$B$81+1 -> 7 | ... Z27: =Z$2-Assumptions!$B$81+1 -> 23
A28: Net sales, unrisked | C28: =IF(C$2>Assumptions!$B$90,0*(1-Assumptions!$B$91),IF(C27>=1,Assumptions!$B$82*CHOOSE(Assumptions!$B$89,INDEX(Assumptions!$B$42:$H$42,MIN(C27,7)),INDEX(Assumptions!$B$43:$H$43,MIN(C27,7))),0)) -> 0 | D28: =IF(D$2>Assumptions!$B$90,C28*(1-Assumptions!$B$91),IF(D27>=1,Assumptions!$B$82*CHOOSE(Assumptions!$B$89,INDEX(Assumptions!$B$42:$H$42,MIN(D27,7)),INDEX(Assumptions!$B$43:$H$43,MIN(D27,7))),0)) -> 180 | E28: =IF(E$2>Assumptions!$B$90,D28*(1-Assumptions!$B$91),IF(E27>=1,Assumptions!$B$82*CHOOSE(Assumptions!$B$89,INDEX(Assumptions!$B$42:$H$42,MIN(E27,7)),INDEX(Assumptions!$B$43:$H$43,MIN(E27,7))),0)) -> 420 | F28: =IF(F$2>Assumptions!$B$90,E28*(1-Assumptions!$B$91),IF(F27>=1,Assumptions!$B$82*CHOOSE(Assumptions!$B$89,INDEX(Assumptions!$B$42:$H$42,MIN(F27,7)),INDEX(Assumptions!$B$43:$H$43,MIN(F27,7))),0)) -> 660 | G28: =IF(G$2>Assumptions!$B$90,F28*(1-Assumptions!$B$91),IF(G27>=1,Assumptions!$B$82*CHOOSE(Assumptions!$B$89,INDEX(Assumptions!$B$42:$H$42,MIN(G27,7)),INDEX(Assumptions!$B$43:$H$43,MIN(G27,7))),0)) -> 900 | H28: =IF(H$2>Assumptions!$B$90,G28*(1-Assumptions!$B$91),IF(H27>=1,Assumptions!$B$82*CHOOSE(Assumptions!$B$89,INDEX(Assumptions!$B$42:$H$42,MIN(H27,7)),INDEX(Assumptions!$B$43:$H$43,MIN(H27,7))),0)) -> 1080 | I28: =IF(I$2>Assumptions!$B$90,H28*(1-Assumptions!$B$91),IF(I27>=1,Assumptions!$B$82*CHOOSE(Assumptions!$B$89,INDEX(Assumptions!$B$42:$H$42,MIN(I27,7)),INDEX(Assumptions!$B$43:$H$43,MIN(I27,7))),0)) -> 1200 | J28: =IF(J$2>Assumptions!$B$90,I28*(1-Assumptions!$B$91),IF(J27>=1,Assumptions!$B$82*CHOOSE(Assumptions!$B$89,INDEX(Assumptions!$B$42:$H$42,MIN(J27,7)),INDEX(Assumptions!$B$43:$H$43,MIN(J27,7))),0)) -> 1200 | K28: =IF(K$2>Assumptions!$B$90,J28*(1-Assumptions!$B$91),IF(K27>=1,Assumptions!$B$82*CHOOSE(Assumptions!$B$89,INDEX(Assumptions!$B$42:$H$42,MIN(K27,7)),INDEX(Assumptions!$B$43:$H$43,MIN(K27,7))),0)) -> 1200 | ... Z28: =IF(Z$2>Assumptions!$B$90,Y28*(1-Assumptions!$B$91),IF(Z27>=1,Assumptions!$B$82*CHOOSE(Assumptions!$B$89,INDEX(Assumptions!$B$42:$H$42,MIN(Z27,7)),INDEX(Assumptions!$B$43:$H$43,MIN(Z27,7))),0)) -> 0.3145728
A29: Product net sales, risk-adjusted | C29: =C28*MIN(1,Assumptions!$B$83*Assumptions!$B$37) -> 0 | D29: =D28*MIN(1,Assumptions!$B$83*Assumptions!$B$37) -> 81 | E29: =E28*MIN(1,Assumptions!$B$83*Assumptions!$B$37) -> 189 | F29: =F28*MIN(1,Assumptions!$B$83*Assumptions!$B$37) -> 297 | G29: =G28*MIN(1,Assumptions!$B$83*Assumptions!$B$37) -> 405 | H29: =H28*MIN(1,Assumptions!$B$83*Assumptions!$B$37) -> 486 | I29: =I28*MIN(1,Assumptions!$B$83*Assumptions!$B$37) -> 540 | J29: =J28*MIN(1,Assumptions!$B$83*Assumptions!$B$37) -> 540 | ... Z29: =Z28*MIN(1,Assumptions!$B$83*Assumptions!$B$37) -> 0.14155776
A30: Company revenue, risk-adjusted (incl. milestones) | C30: =C29*Assumptions!$B$84 -> 0 | D30: =D29*Assumptions!$B$84 -> 81 | E30: =E29*Assumptions!$B$84 -> 189 | F30: =F29*Assumptions!$B$84 -> 297 | G30: =G29*Assumptions!$B$84 -> 405 | H30: =H29*Assumptions!$B$84 -> 486 | I30: =I29*Assumptions!$B$84 -> 540 | J30: =J29*Assumptions!$B$84 -> 540 | ... Z30: =Z29*Assumptions!$B$84 -> 0.14155776
A31: COGS + royalties, risk-adjusted | C31: =C29*(Assumptions!$B$85+Assumptions!$B$86) -> 0 | D31: =D29*(Assumptions!$B$85+Assumptions!$B$86) -> 3.24 | E31: =E29*(Assumptions!$B$85+Assumptions!$B$86) -> 7.56 | F31: =F29*(Assumptions!$B$85+Assumptions!$B$86) -> 11.88 | G31: =G29*(Assumptions!$B$85+Assumptions!$B$86) -> 16.2 | H31: =H29*(Assumptions!$B$85+Assumptions!$B$86) -> 19.44 | I31: =I29*(Assumptions!$B$85+Assumptions!$B$86) -> 21.6 | J31: =J29*(Assumptions!$B$85+Assumptions!$B$86) -> 21.6 | ... Z31: =Z29*(Assumptions!$B$85+Assumptions!$B$86) -> 0.0056623104
A32: Commercial SG&A, risk-adjusted | C32: =MIN(1,Assumptions!$B$83*Assumptions!$B$37)*IF(Assumptions!$B$87=0,0,IF(C27=0,Assumptions!$B$88,IF(C27>=1,C28*IF(OR(Assumptions!$B$84<1,C27>5),Assumptions!$B$87,MAX(Assumptions!$B$87,INDEX(Assumptions!$B$44:$F$44,C27))),0))) -> 9 | D32: =MIN(1,Assumptions!$B$83*Assumptions!$B$37)*IF(Assumptions!$B$87=0,0,IF(D27=0,Assumptions!$B$88,IF(D27>=1,D28*IF(OR(Assumptions!$B$84<1,D27>5),Assumptions!$B$87,MAX(Assumptions!$B$87,INDEX(Assumptions!$B$44:$F$44,D27))),0))) -> 72.9 | E32: =MIN(1,Assumptions!$B$83*Assumptions!$B$37)*IF(Assumptions!$B$87=0,0,IF(E27=0,Assumptions!$B$88,IF(E27>=1,E28*IF(OR(Assumptions!$B$84<1,E27>5),Assumptions!$B$87,MAX(Assumptions!$B$87,INDEX(Assumptions!$B$44:$F$44,E27))),0))) -> 103.95 | F32: =MIN(1,Assumptions!$B$83*Assumptions!$B$37)*IF(Assumptions!$B$87=0,0,IF(F27=0,Assumptions!$B$88,IF(F27>=1,F28*IF(OR(Assumptions!$B$84<1,F27>5),Assumptions!$B$87,MAX(Assumptions!$B$87,INDEX(Assumptions!$B$44:$F$44,F27))),0))) -> 118.8 | G32: =MIN(1,Assumptions!$B$83*Assumptions!$B$37)*IF(Assumptions!$B$87=0,0,IF(G27=0,Assumptions!$B$88,IF(G27>=1,G28*IF(OR(Assumptions!$B$84<1,G27>5),Assumptions!$B$87,MAX(Assumptions!$B$87,INDEX(Assumptions!$B$44:$F$44,G27))),0))) -> 129.6 | H32: =MIN(1,Assumptions!$B$83*Assumptions!$B$37)*IF(Assumptions!$B$87=0,0,IF(H27=0,Assumptions!$B$88,IF(H27>=1,H28*IF(OR(Assumptions!$B$84<1,H27>5),Assumptions!$B$87,MAX(Assumptions!$B$87,INDEX(Assumptions!$B$44:$F$44,H27))),0))) -> 136.08 | I32: =MIN(1,Assumptions!$B$83*Assumptions!$B$37)*IF(Assumptions!$B$87=0,0,IF(I27=0,Assumptions!$B$88,IF(I27>=1,I28*IF(OR(Assumptions!$B$84<1,I27>5),Assumptions!$B$87,MAX(Assumptions!$B$87,INDEX(Assumptions!$B$44:$F$44,I27))),0))) -> 108 | J32: =MIN(1,Assumptions!$B$83*Assumptions!$B$37)*IF(Assumptions!$B$87=0,0,IF(J27=0,Assumptions!$B$88,IF(J27>=1,J28*IF(OR(Assumptions!$B$84<1,J27>5),Assumptions!$B$87,MAX(Assumptions!$B$87,INDEX(Assumptions!$B$44:$F$44,J27))),0))) -> 108 | ... Z32: =MIN(1,Assumptions!$B$83*Assumptions!$B$37)*IF(Assumptions!$B$87=0,0,IF(Z27=0,Assumptions!$B$88,IF(Z27>=1,Z28*IF(OR(Assumptions!$B$84<1,Z27>5),Assumptions!$B$87,MAX(Assumptions!$B$87,INDEX(Assumptions!$B$44:$F$44,Z27))),0))) -> 0.028311552
A33: Development R&D, risk-adjusted | C33: =IFERROR(INDEX(Assumptions!$B$93:$I$93,MATCH(C$2,Assumptions!$B$92:$I$92,0))*INDEX(Assumptions!$B$94:$I$94,MATCH(C$2,Assumptions!$B$92:$I$92,0)),0) -> 15 | D33: =IFERROR(INDEX(Assumptions!$B$93:$I$93,MATCH(D$2,Assumptions!$B$92:$I$92,0))*INDEX(Assumptions!$B$94:$I$94,MATCH(D$2,Assumptions!$B$92:$I$92,0)),0) -> 0 | E33: =IFERROR(INDEX(Assumptions!$B$93:$I$93,MATCH(E$2,Assumptions!$B$92:$I$92,0))*INDEX(Assumptions!$B$94:$I$94,MATCH(E$2,Assumptions!$B$92:$I$92,0)),0) -> 0 | F33: =IFERROR(INDEX(Assumptions!$B$93:$I$93,MATCH(F$2,Assumptions!$B$92:$I$92,0))*INDEX(Assumptions!$B$94:$I$94,MATCH(F$2,Assumptions!$B$92:$I$92,0)),0) -> 0 | G33: =IFERROR(INDEX(Assumptions!$B$93:$I$93,MATCH(G$2,Assumptions!$B$92:$I$92,0))*INDEX(Assumptions!$B$94:$I$94,MATCH(G$2,Assumptions!$B$92:$I$92,0)),0) -> 0 | H33: =IFERROR(INDEX(Assumptions!$B$93:$I$93,MATCH(H$2,Assumptions!$B$92:$I$92,0))*INDEX(Assumptions!$B$94:$I$94,MATCH(H$2,Assumptions!$B$92:$I$92,0)),0) -> 0 | I33: =IFERROR(INDEX(Assumptions!$B$93:$I$93,MATCH(I$2,Assumptions!$B$92:$I$92,0))*INDEX(Assumptions!$B$94:$I$94,MATCH(I$2,Assumptions!$B$92:$I$92,0)),0) -> 0 | J33: =IFERROR(INDEX(Assumptions!$B$93:$I$93,MATCH(J$2,Assumptions!$B$92:$I$92,0))*INDEX(Assumptions!$B$94:$I$94,MATCH(J$2,Assumptions!$B$92:$I$92,0)),0) -> 0 | ... Z33: =IFERROR(INDEX(Assumptions!$B$93:$I$93,MATCH(Z$2,Assumptions!$B$92:$I$92,0))*INDEX(Assumptions!$B$94:$I$94,MATCH(Z$2,Assumptions!$B$92:$I$92,0)),0) -> 0
A34: Program contribution (pre-tax) | C34: =C30-C31-C32-C33 -> -24 | D34: =D30-D31-D32-D33 -> 4.86 | E34: =E30-E31-E32-E33 -> 77.49 | F34: =F30-F31-F32-F33 -> 166.32 | G34: =G30-G31-G32-G33 -> 259.2 | H34: =H30-H31-H32-H33 -> 330.48 | I34: =I30-I31-I32-I33 -> 410.4 | J34: =J30-J31-J32-J33 -> 410.4 | ... Z34: =Z30-Z31-Z32-Z33 -> 0.1075839
A36: Vormatrigine — focal / generalized epilepsy (POWER2/3)
A37: Years since launch | C37: =C$2-Assumptions!$B$97+1 -> -2 | D37: =D$2-Assumptions!$B$97+1 -> -1 | E37: =E$2-Assumptions!$B$97+1 -> 0 | F37: =F$2-Assumptions!$B$97+1 -> 1 | G37: =G$2-Assumptions!$B$97+1 -> 2 | H37: =H$2-Assumptions!$B$97+1 -> 3 | I37: =I$2-Assumptions!$B$97+1 -> 4 | J37: =J$2-Assumptions!$B$97+1 -> 5 | ... Z37: =Z$2-Assumptions!$B$97+1 -> 21
A38: Net sales, unrisked | C38: =IF(C$2>Assumptions!$B$106,0*(1-Assumptions!$B$107),IF(C37>=1,Assumptions!$B$98*CHOOSE(Assumptions!$B$105,INDEX(Assumptions!$B$42:$H$42,MIN(C37,7)),INDEX(Assumptions!$B$43:$H$43,MIN(C37,7))),0)) -> 0 | D38: =IF(D$2>Assumptions!$B$106,C38*(1-Assumptions!$B$107),IF(D37>=1,Assumptions!$B$98*CHOOSE(Assumptions!$B$105,INDEX(Assumptions!$B$42:$H$42,MIN(D37,7)),INDEX(Assumptions!$B$43:$H$43,MIN(D37,7))),0)) -> 0 | E38: =IF(E$2>Assumptions!$B$106,D38*(1-Assumptions!$B$107),IF(E37>=1,Assumptions!$B$98*CHOOSE(Assumptions!$B$105,INDEX(Assumptions!$B$42:$H$42,MIN(E37,7)),INDEX(Assumptions!$B$43:$H$43,MIN(E37,7))),0)) -> 0 | F38: =IF(F$2>Assumptions!$B$106,E38*(1-Assumptions!$B$107),IF(F37>=1,Assumptions!$B$98*CHOOSE(Assumptions!$B$105,INDEX(Assumptions!$B$42:$H$42,MIN(F37,7)),INDEX(Assumptions!$B$43:$H$43,MIN(F37,7))),0)) -> 150 | G38: =IF(G$2>Assumptions!$B$106,F38*(1-Assumptions!$B$107),IF(G37>=1,Assumptions!$B$98*CHOOSE(Assumptions!$B$105,INDEX(Assumptions!$B$42:$H$42,MIN(G37,7)),INDEX(Assumptions!$B$43:$H$43,MIN(G37,7))),0)) -> 375 | H38: =IF(H$2>Assumptions!$B$106,G38*(1-Assumptions!$B$107),IF(H37>=1,Assumptions!$B$98*CHOOSE(Assumptions!$B$105,INDEX(Assumptions!$B$42:$H$42,MIN(H37,7)),INDEX(Assumptions!$B$43:$H$43,MIN(H37,7))),0)) -> 675 | I38: =IF(I$2>Assumptions!$B$106,H38*(1-Assumptions!$B$107),IF(I37>=1,Assumptions!$B$98*CHOOSE(Assumptions!$B$105,INDEX(Assumptions!$B$42:$H$42,MIN(I37,7)),INDEX(Assumptions!$B$43:$H$43,MIN(I37,7))),0)) -> 975 | J38: =IF(J$2>Assumptions!$B$106,I38*(1-Assumptions!$B$107),IF(J37>=1,Assumptions!$B$98*CHOOSE(Assumptions!$B$105,INDEX(Assumptions!$B$42:$H$42,MIN(J37,7)),INDEX(Assumptions!$B$43:$H$43,MIN(J37,7))),0)) -> 1230 | K38: =IF(K$2>Assumptions!$B$106,J38*(1-Assumptions!$B$107),IF(K37>=1,Assumptions!$B$98*CHOOSE(Assumptions!$B$105,INDEX(Assumptions!$B$42:$H$42,MIN(K37,7)),INDEX(Assumptions!$B$43:$H$43,MIN(K37,7))),0)) -> 1395 | ... Z38: =IF(Z$2>Assumptions!$B$106,Y38*(1-Assumptions!$B$107),IF(Z37>=1,Assumptions!$B$98*CHOOSE(Assumptions!$B$105,INDEX(Assumptions!$B$42:$H$42,MIN(Z37,7)),INDEX(Assumptions!$B$43:$H$43,MIN(Z37,7))),0)) -> 2.4576
A39: Product net sales, risk-adjusted | C39: =C38*MIN(1,Assumptions!$B$99*Assumptions!$B$37) -> 0 | D39: =D38*MIN(1,Assumptions!$B$99*Assumptions!$B$37) -> 0 | E39: =E38*MIN(1,Assumptions!$B$99*Assumptions!$B$37) -> 0 | F39: =F38*MIN(1,Assumptions!$B$99*Assumptions!$B$37) -> 30 | G39: =G38*MIN(1,Assumptions!$B$99*Assumptions!$B$37) -> 75 | H39: =H38*MIN(1,Assumptions!$B$99*Assumptions!$B$37) -> 135 | I39: =I38*MIN(1,Assumptions!$B$99*Assumptions!$B$37) -> 195 | J39: =J38*MIN(1,Assumptions!$B$99*Assumptions!$B$37) -> 246 | ... Z39: =Z38*MIN(1,Assumptions!$B$99*Assumptions!$B$37) -> 0.49152
A40: Company revenue, risk-adjusted (incl. milestones) | C40: =C39*Assumptions!$B$100 -> 0 | D40: =D39*Assumptions!$B$100 -> 0 | E40: =E39*Assumptions!$B$100 -> 0 | F40: =F39*Assumptions!$B$100 -> 30 | G40: =G39*Assumptions!$B$100 -> 75 | H40: =H39*Assumptions!$B$100 -> 135 | I40: =I39*Assumptions!$B$100 -> 195 | J40: =J39*Assumptions!$B$100 -> 246 | ... Z40: =Z39*Assumptions!$B$100 -> 0.49152
A41: COGS + royalties, risk-adjusted | C41: =C39*(Assumptions!$B$101+Assumptions!$B$102) -> 0 | D41: =D39*(Assumptions!$B$101+Assumptions!$B$102) -> 0 | E41: =E39*(Assumptions!$B$101+Assumptions!$B$102) -> 0 | F41: =F39*(Assumptions!$B$101+Assumptions!$B$102) -> 1.2 | G41: =G39*(Assumptions!$B$101+Assumptions!$B$102) -> 3 | H41: =H39*(Assumptions!$B$101+Assumptions!$B$102) -> 5.4 | I41: =I39*(Assumptions!$B$101+Assumptions!$B$102) -> 7.8 | J41: =J39*(Assumptions!$B$101+Assumptions!$B$102) -> 9.84 | ... Z41: =Z39*(Assumptions!$B$101+Assumptions!$B$102) -> 0.0196608
A42: Commercial SG&A, risk-adjusted | C42: =MIN(1,Assumptions!$B$99*Assumptions!$B$37)*IF(Assumptions!$B$103=0,0,IF(C37=0,Assumptions!$B$104,IF(C37>=1,C38*IF(OR(Assumptions!$B$100<1,C37>5),Assumptions!$B$103,MAX(Assumptions!$B$103,INDEX(Assumptions!$B$44:$F$44,C37))),0))) -> 0 | D42: =MIN(1,Assumptions!$B$99*Assumptions!$B$37)*IF(Assumptions!$B$103=0,0,IF(D37=0,Assumptions!$B$104,IF(D37>=1,D38*IF(OR(Assumptions!$B$100<1,D37>5),Assumptions!$B$103,MAX(Assumptions!$B$103,INDEX(Assumptions!$B$44:$F$44,D37))),0))) -> 0 | E42: =MIN(1,Assumptions!$B$99*Assumptions!$B$37)*IF(Assumptions!$B$103=0,0,IF(E37=0,Assumptions!$B$104,IF(E37>=1,E38*IF(OR(Assumptions!$B$100<1,E37>5),Assumptions!$B$103,MAX(Assumptions!$B$103,INDEX(Assumptions!$B$44:$F$44,E37))),0))) -> 8 | F42: =MIN(1,Assumptions!$B$99*Assumptions!$B$37)*IF(Assumptions!$B$103=0,0,IF(F37=0,Assumptions!$B$104,IF(F37>=1,F38*IF(OR(Assumptions!$B$100<1,F37>5),Assumptions!$B$103,MAX(Assumptions!$B$103,INDEX(Assumptions!$B$44:$F$44,F37))),0))) -> 27 | G42: =MIN(1,Assumptions!$B$99*Assumptions!$B$37)*IF(Assumptions!$B$103=0,0,IF(G37=0,Assumptions!$B$104,IF(G37>=1,G38*IF(OR(Assumptions!$B$100<1,G37>5),Assumptions!$B$103,MAX(Assumptions!$B$103,INDEX(Assumptions!$B$44:$F$44,G37))),0))) -> 41.25 | H42: =MIN(1,Assumptions!$B$99*Assumptions!$B$37)*IF(Assumptions!$B$103=0,0,IF(H37=0,Assumptions!$B$104,IF(H37>=1,H38*IF(OR(Assumptions!$B$100<1,H37>5),Assumptions!$B$103,MAX(Assumptions!$B$103,INDEX(Assumptions!$B$44:$F$44,H37))),0))) -> 54 | I42: =MIN(1,Assumptions!$B$99*Assumptions!$B$37)*IF(Assumptions!$B$103=0,0,IF(I37=0,Assumptions!$B$104,IF(I37>=1,I38*IF(OR(Assumptions!$B$100<1,I37>5),Assumptions!$B$103,MAX(Assumptions!$B$103,INDEX(Assumptions!$B$44:$F$44,I37))),0))) -> 62.4 | J42: =MIN(1,Assumptions!$B$99*Assumptions!$B$37)*IF(Assumptions!$B$103=0,0,IF(J37=0,Assumptions!$B$104,IF(J37>=1,J38*IF(OR(Assumptions!$B$100<1,J37>5),Assumptions!$B$103,MAX(Assumptions!$B$103,INDEX(Assumptions!$B$44:$F$44,J37))),0))) -> 73.8 | ... Z42: =MIN(1,Assumptions!$B$99*Assumptions!$B$37)*IF(Assumptions!$B$103=0,0,IF(Z37=0,Assumptions!$B$104,IF(Z37>=1,Z38*IF(OR(Assumptions!$B$100<1,Z37>5),Assumptions!$B$103,MAX(Assumptions!$B$103,INDEX(Assumptions!$B$44:$F$44,Z37))),0))) -> 0.147456
A43: Development R&D, risk-adjusted | C43: =IFERROR(INDEX(Assumptions!$B$109:$I$109,MATCH(C$2,Assumptions!$B$108:$I$108,0))*INDEX(Assumptions!$B$110:$I$110,MATCH(C$2,Assumptions!$B$108:$I$108,0)),0) -> 80 | D43: =IFERROR(INDEX(Assumptions!$B$109:$I$109,MATCH(D$2,Assumptions!$B$108:$I$108,0))*INDEX(Assumptions!$B$110:$I$110,MATCH(D$2,Assumptions!$B$108:$I$108,0)),0) -> 80 | E43: =IFERROR(INDEX(Assumptions!$B$109:$I$109,MATCH(E$2,Assumptions!$B$108:$I$108,0))*INDEX(Assumptions!$B$110:$I$110,MATCH(E$2,Assumptions!$B$108:$I$108,0)),0) -> 20 | F43: =IFERROR(INDEX(Assumptions!$B$109:$I$109,MATCH(F$2,Assumptions!$B$108:$I$108,0))*INDEX(Assumptions!$B$110:$I$110,MATCH(F$2,Assumptions!$B$108:$I$108,0)),0) -> 0 | G43: =IFERROR(INDEX(Assumptions!$B$109:$I$109,MATCH(G$2,Assumptions!$B$108:$I$108,0))*INDEX(Assumptions!$B$110:$I$110,MATCH(G$2,Assumptions!$B$108:$I$108,0)),0) -> 0 | H43: =IFERROR(INDEX(Assumptions!$B$109:$I$109,MATCH(H$2,Assumptions!$B$108:$I$108,0))*INDEX(Assumptions!$B$110:$I$110,MATCH(H$2,Assumptions!$B$108:$I$108,0)),0) -> 0 | I43: =IFERROR(INDEX(Assumptions!$B$109:$I$109,MATCH(I$2,Assumptions!$B$108:$I$108,0))*INDEX(Assumptions!$B$110:$I$110,MATCH(I$2,Assumptions!$B$108:$I$108,0)),0) -> 0 | J43: =IFERROR(INDEX(Assumptions!$B$109:$I$109,MATCH(J$2,Assumptions!$B$108:$I$108,0))*INDEX(Assumptions!$B$110:$I$110,MATCH(J$2,Assumptions!$B$108:$I$108,0)),0) -> 0 | ... Z43: =IFERROR(INDEX(Assumptions!$B$109:$I$109,MATCH(Z$2,Assumptions!$B$108:$I$108,0))*INDEX(Assumptions!$B$110:$I$110,MATCH(Z$2,Assumptions!$B$108:$I$108,0)),0) -> 0
A44: Program contribution (pre-tax) | C44: =C40-C41-C42-C43 -> -80 | D44: =D40-D41-D42-D43 -> -80 | E44: =E40-E41-E42-E43 -> -28 | F44: =F40-F41-F42-F43 -> 1.8 | G44: =G40-G41-G42-G43 -> 30.75 | H44: =H40-H41-H42-H43 -> 75.6 | I44: =I40-I41-I42-I43 -> 124.8 | J44: =J40-J41-J42-J43 -> 162.36 | ... Z44: =Z40-Z41-Z42-Z43 -> 0.3244032
A46: Elsunersen — early-onset SCN2A DEE (ASO)
A47: Years since launch | C47: =C$2-Assumptions!$B$113+1 -> -1 | D47: =D$2-Assumptions!$B$113+1 -> 0 | E47: =E$2-Assumptions!$B$113+1 -> 1 | F47: =F$2-Assumptions!$B$113+1 -> 2 | G47: =G$2-Assumptions!$B$113+1 -> 3 | H47: =H$2-Assumptions!$B$113+1 -> 4 | I47: =I$2-Assumptions!$B$113+1 -> 5 | J47: =J$2-Assumptions!$B$113+1 -> 6 | ... Z47: =Z$2-Assumptions!$B$113+1 -> 22
A48: Net sales, unrisked | C48: =IF(C$2>Assumptions!$B$122,0*(1-Assumptions!$B$123),IF(C47>=1,Assumptions!$B$114*CHOOSE(Assumptions!$B$121,INDEX(Assumptions!$B$42:$H$42,MIN(C47,7)),INDEX(Assumptions!$B$43:$H$43,MIN(C47,7))),0)) -> 0 | D48: =IF(D$2>Assumptions!$B$122,C48*(1-Assumptions!$B$123),IF(D47>=1,Assumptions!$B$114*CHOOSE(Assumptions!$B$121,INDEX(Assumptions!$B$42:$H$42,MIN(D47,7)),INDEX(Assumptions!$B$43:$H$43,MIN(D47,7))),0)) -> 0 | E48: =IF(E$2>Assumptions!$B$122,D48*(1-Assumptions!$B$123),IF(E47>=1,Assumptions!$B$114*CHOOSE(Assumptions!$B$121,INDEX(Assumptions!$B$42:$H$42,MIN(E47,7)),INDEX(Assumptions!$B$43:$H$43,MIN(E47,7))),0)) -> 75 | F48: =IF(F$2>Assumptions!$B$122,E48*(1-Assumptions!$B$123),IF(F47>=1,Assumptions!$B$114*CHOOSE(Assumptions!$B$121,INDEX(Assumptions!$B$42:$H$42,MIN(F47,7)),INDEX(Assumptions!$B$43:$H$43,MIN(F47,7))),0)) -> 175 | G48: =IF(G$2>Assumptions!$B$122,F48*(1-Assumptions!$B$123),IF(G47>=1,Assumptions!$B$114*CHOOSE(Assumptions!$B$121,INDEX(Assumptions!$B$42:$H$42,MIN(G47,7)),INDEX(Assumptions!$B$43:$H$43,MIN(G47,7))),0)) -> 275 | H48: =IF(H$2>Assumptions!$B$122,G48*(1-Assumptions!$B$123),IF(H47>=1,Assumptions!$B$114*CHOOSE(Assumptions!$B$121,INDEX(Assumptions!$B$42:$H$42,MIN(H47,7)),INDEX(Assumptions!$B$43:$H$43,MIN(H47,7))),0)) -> 375 | I48: =IF(I$2>Assumptions!$B$122,H48*(1-Assumptions!$B$123),IF(I47>=1,Assumptions!$B$114*CHOOSE(Assumptions!$B$121,INDEX(Assumptions!$B$42:$H$42,MIN(I47,7)),INDEX(Assumptions!$B$43:$H$43,MIN(I47,7))),0)) -> 450 | J48: =IF(J$2>Assumptions!$B$122,I48*(1-Assumptions!$B$123),IF(J47>=1,Assumptions!$B$114*CHOOSE(Assumptions!$B$121,INDEX(Assumptions!$B$42:$H$42,MIN(J47,7)),INDEX(Assumptions!$B$43:$H$43,MIN(J47,7))),0)) -> 500 | K48: =IF(K$2>Assumptions!$B$122,J48*(1-Assumptions!$B$123),IF(K47>=1,Assumptions!$B$114*CHOOSE(Assumptions!$B$121,INDEX(Assumptions!$B$42:$H$42,MIN(K47,7)),INDEX(Assumptions!$B$43:$H$43,MIN(K47,7))),0)) -> 500 | ... Z48: =IF(Z$2>Assumptions!$B$122,Y48*(1-Assumptions!$B$123),IF(Z47>=1,Assumptions!$B$114*CHOOSE(Assumptions!$B$121,INDEX(Assumptions!$B$42:$H$42,MIN(Z47,7)),INDEX(Assumptions!$B$43:$H$43,MIN(Z47,7))),0)) -> 1.953125
A49: Product net sales, risk-adjusted | C49: =C48*MIN(1,Assumptions!$B$115*Assumptions!$B$37) -> 0 | D49: =D48*MIN(1,Assumptions!$B$115*Assumptions!$B$37) -> 0 | E49: =E48*MIN(1,Assumptions!$B$115*Assumptions!$B$37) -> 33.75 | F49: =F48*MIN(1,Assumptions!$B$115*Assumptions!$B$37) -> 78.75 | G49: =G48*MIN(1,Assumptions!$B$115*Assumptions!$B$37) -> 123.75 | H49: =H48*MIN(1,Assumptions!$B$115*Assumptions!$B$37) -> 168.75 | I49: =I48*MIN(1,Assumptions!$B$115*Assumptions!$B$37) -> 202.5 | J49: =J48*MIN(1,Assumptions!$B$115*Assumptions!$B$37) -> 225 | ... Z49: =Z48*MIN(1,Assumptions!$B$115*Assumptions!$B$37) -> 0.87890625
A50: Company revenue, risk-adjusted (incl. milestones) | C50: =C49*Assumptions!$B$116 -> 0 | D50: =D49*Assumptions!$B$116 -> 0 | E50: =E49*Assumptions!$B$116 -> 33.75 | F50: =F49*Assumptions!$B$116 -> 78.75 | G50: =G49*Assumptions!$B$116 -> 123.75 | H50: =H49*Assumptions!$B$116 -> 168.75 | I50: =I49*Assumptions!$B$116 -> 202.5 | J50: =J49*Assumptions!$B$116 -> 225 | ... Z50: =Z49*Assumptions!$B$116 -> 0.87890625
A51: COGS + royalties, risk-adjusted | C51: =C49*(Assumptions!$B$117+Assumptions!$B$118) -> 0 | D51: =D49*(Assumptions!$B$117+Assumptions!$B$118) -> 0 | E51: =E49*(Assumptions!$B$117+Assumptions!$B$118) -> 2.7 | F51: =F49*(Assumptions!$B$117+Assumptions!$B$118) -> 6.3 | G51: =G49*(Assumptions!$B$117+Assumptions!$B$118) -> 9.9 | H51: =H49*(Assumptions!$B$117+Assumptions!$B$118) -> 13.5 | I51: =I49*(Assumptions!$B$117+Assumptions!$B$118) -> 16.2 | J51: =J49*(Assumptions!$B$117+Assumptions!$B$118) -> 18 | ... Z51: =Z49*(Assumptions!$B$117+Assumptions!$B$118) -> 0.0703125
A52: Commercial SG&A, risk-adjusted | C52: =MIN(1,Assumptions!$B$115*Assumptions!$B$37)*IF(Assumptions!$B$119=0,0,IF(C47=0,Assumptions!$B$120,IF(C47>=1,C48*IF(OR(Assumptions!$B$116<1,C47>5),Assumptions!$B$119,MAX(Assumptions!$B$119,INDEX(Assumptions!$B$44:$F$44,C47))),0))) -> 0 | D52: =MIN(1,Assumptions!$B$115*Assumptions!$B$37)*IF(Assumptions!$B$119=0,0,IF(D47=0,Assumptions!$B$120,IF(D47>=1,D48*IF(OR(Assumptions!$B$116<1,D47>5),Assumptions!$B$119,MAX(Assumptions!$B$119,INDEX(Assumptions!$B$44:$F$44,D47))),0))) -> 6.75 | E52: =MIN(1,Assumptions!$B$115*Assumptions!$B$37)*IF(Assumptions!$B$119=0,0,IF(E47=0,Assumptions!$B$120,IF(E47>=1,E48*IF(OR(Assumptions!$B$116<1,E47>5),Assumptions!$B$119,MAX(Assumptions!$B$119,INDEX(Assumptions!$B$44:$F$44,E47))),0))) -> 30.375 | F52: =MIN(1,Assumptions!$B$115*Assumptions!$B$37)*IF(Assumptions!$B$119=0,0,IF(F47=0,Assumptions!$B$120,IF(F47>=1,F48*IF(OR(Assumptions!$B$116<1,F47>5),Assumptions!$B$119,MAX(Assumptions!$B$119,INDEX(Assumptions!$B$44:$F$44,F47))),0))) -> 43.3125 | G52: =MIN(1,Assumptions!$B$115*Assumptions!$B$37)*IF(Assumptions!$B$119=0,0,IF(G47=0,Assumptions!$B$120,IF(G47>=1,G48*IF(OR(Assumptions!$B$116<1,G47>5),Assumptions!$B$119,MAX(Assumptions!$B$119,INDEX(Assumptions!$B$44:$F$44,G47))),0))) -> 49.5 | H52: =MIN(1,Assumptions!$B$115*Assumptions!$B$37)*IF(Assumptions!$B$119=0,0,IF(H47=0,Assumptions!$B$120,IF(H47>=1,H48*IF(OR(Assumptions!$B$116<1,H47>5),Assumptions!$B$119,MAX(Assumptions!$B$119,INDEX(Assumptions!$B$44:$F$44,H47))),0))) -> 54 | I52: =MIN(1,Assumptions!$B$115*Assumptions!$B$37)*IF(Assumptions!$B$119=0,0,IF(I47=0,Assumptions!$B$120,IF(I47>=1,I48*IF(OR(Assumptions!$B$116<1,I47>5),Assumptions!$B$119,MAX(Assumptions!$B$119,INDEX(Assumptions!$B$44:$F$44,I47))),0))) -> 56.7 | J52: =MIN(1,Assumptions!$B$115*Assumptions!$B$37)*IF(Assumptions!$B$119=0,0,IF(J47=0,Assumptions!$B$120,IF(J47>=1,J48*IF(OR(Assumptions!$B$116<1,J47>5),Assumptions!$B$119,MAX(Assumptions!$B$119,INDEX(Assumptions!$B$44:$F$44,J47))),0))) -> 45 | ... Z52: =MIN(1,Assumptions!$B$115*Assumptions!$B$37)*IF(Assumptions!$B$119=0,0,IF(Z47=0,Assumptions!$B$120,IF(Z47>=1,Z48*IF(OR(Assumptions!$B$116<1,Z47>5),Assumptions!$B$119,MAX(Assumptions!$B$119,INDEX(Assumptions!$B$44:$F$44,Z47))),0))) -> 0.17578125
A53: Development R&D, risk-adjusted | C53: =IFERROR(INDEX(Assumptions!$B$125:$I$125,MATCH(C$2,Assumptions!$B$124:$I$124,0))*INDEX(Assumptions!$B$126:$I$126,MATCH(C$2,Assumptions!$B$124:$I$124,0)),0) -> 30 | D53: =IFERROR(INDEX(Assumptions!$B$125:$I$125,MATCH(D$2,Assumptions!$B$124:$I$124,0))*INDEX(Assumptions!$B$126:$I$126,MATCH(D$2,Assumptions!$B$124:$I$124,0)),0) -> 20 | E53: =IFERROR(INDEX(Assumptions!$B$125:$I$125,MATCH(E$2,Assumptions!$B$124:$I$124,0))*INDEX(Assumptions!$B$126:$I$126,MATCH(E$2,Assumptions!$B$124:$I$124,0)),0) -> 0 | F53: =IFERROR(INDEX(Assumptions!$B$125:$I$125,MATCH(F$2,Assumptions!$B$124:$I$124,0))*INDEX(Assumptions!$B$126:$I$126,MATCH(F$2,Assumptions!$B$124:$I$124,0)),0) -> 0 | G53: =IFERROR(INDEX(Assumptions!$B$125:$I$125,MATCH(G$2,Assumptions!$B$124:$I$124,0))*INDEX(Assumptions!$B$126:$I$126,MATCH(G$2,Assumptions!$B$124:$I$124,0)),0) -> 0 | H53: =IFERROR(INDEX(Assumptions!$B$125:$I$125,MATCH(H$2,Assumptions!$B$124:$I$124,0))*INDEX(Assumptions!$B$126:$I$126,MATCH(H$2,Assumptions!$B$124:$I$124,0)),0) -> 0 | I53: =IFERROR(INDEX(Assumptions!$B$125:$I$125,MATCH(I$2,Assumptions!$B$124:$I$124,0))*INDEX(Assumptions!$B$126:$I$126,MATCH(I$2,Assumptions!$B$124:$I$124,0)),0) -> 0 | J53: =IFERROR(INDEX(Assumptions!$B$125:$I$125,MATCH(J$2,Assumptions!$B$124:$I$124,0))*INDEX(Assumptions!$B$126:$I$126,MATCH(J$2,Assumptions!$B$124:$I$124,0)),0) -> 0 | ... Z53: =IFERROR(INDEX(Assumptions!$B$125:$I$125,MATCH(Z$2,Assumptions!$B$124:$I$124,0))*INDEX(Assumptions!$B$126:$I$126,MATCH(Z$2,Assumptions!$B$124:$I$124,0)),0) -> 0
A54: Program contribution (pre-tax) | C54: =C50-C51-C52-C53 -> -30 | D54: =D50-D51-D52-D53 -> -26.75 | E54: =E50-E51-E52-E53 -> 0.675 | F54: =F50-F51-F52-F53 -> 29.1375 | G54: =G50-G51-G52-G53 -> 64.35 | H54: =H50-H51-H52-H53 -> 101.25 | I54: =I50-I51-I52-I53 -> 129.6 | J54: =J50-J51-J52-J53 -> 162 | ... Z54: =Z50-Z51-Z52-Z53 -> 0.6328125
A56: Company totals (risk-adjusted)
A57: Revenue | C57: =C10+C20+C30+C40+C50 -> 471 | D57: =D10+D20+D30+D40+D50 -> 925.5 | E57: =E10+E20+E30+E40+E50 -> 1683 | F57: =F10+F20+F30+F40+F50 -> 2493 | G57: =G10+G20+G30+G40+G50 -> 3214.5 | H57: =H10+H20+H30+H40+H50 -> 3741.75 | I57: =I10+I20+I30+I40+I50 -> 4072.5 | J57: =J10+J20+J30+J40+J50 -> 4146 | ... Z57: =Z10+Z20+Z30+Z40+Z50 -> 2.3338055
A58: Cost of sales (COGS + royalties) | C58: =C11+C21+C31+C41+C51 -> 13.44 | D58: =D11+D21+D31+D41+D51 -> 36.57 | E58: =E11+E21+E31+E41+E51 -> 68.67 | F58: =F11+F21+F31+F41+F51 -> 102.87 | G58: =G11+G21+G31+G41+G51 -> 133.53 | H58: =H11+H21+H31+H41+H51 -> 156.42 | I58: =I11+I21+I31+I41+I51 -> 171 | J58: =J11+J21+J31+J41+J51 -> 174.84 | ... Z58: =Z11+Z21+Z31+Z41+Z51 -> 0.12850847
A59: Program development R&D | C59: =C13+C23+C33+C43+C53 -> 155 | D59: =D13+D23+D33+D43+D53 -> 100 | E59: =E13+E23+E33+E43+E53 -> 20 | F59: =F13+F23+F33+F43+F53 -> 0 | G59: =G13+G23+G33+G43+G53 -> 0 | H59: =H13+H23+H33+H43+H53 -> 0 | I59: =I13+I23+I33+I43+I53 -> 0 | J59: =J13+J23+J33+J43+J53 -> 0 | ... Z59: =Z13+Z23+Z33+Z43+Z53 -> 0
A60: Platform / unallocated R&D | C60: =IF(C$2>Assumptions!$B$25,Assumptions!$B$23*C57,MAX(Assumptions!$B$20*(1+Assumptions!$B$21)^(C$2-2027)*Assumptions!$B$38,Assumptions!$B$23*C57)) -> 150 | D60: =IF(D$2>Assumptions!$B$25,Assumptions!$B$23*D57,MAX(Assumptions!$B$20*(1+Assumptions!$B$21)^(D$2-2027)*Assumptions!$B$38,Assumptions!$B$23*D57)) -> 154.5 | E60: =IF(E$2>Assumptions!$B$25,Assumptions!$B$23*E57,MAX(Assumptions!$B$20*(1+Assumptions!$B$21)^(E$2-2027)*Assumptions!$B$38,Assumptions!$B$23*E57)) -> 201.96 | F60: =IF(F$2>Assumptions!$B$25,Assumptions!$B$23*F57,MAX(Assumptions!$B$20*(1+Assumptions!$B$21)^(F$2-2027)*Assumptions!$B$38,Assumptions!$B$23*F57)) -> 299.16 | G60: =IF(G$2>Assumptions!$B$25,Assumptions!$B$23*G57,MAX(Assumptions!$B$20*(1+Assumptions!$B$21)^(G$2-2027)*Assumptions!$B$38,Assumptions!$B$23*G57)) -> 385.74 | H60: =IF(H$2>Assumptions!$B$25,Assumptions!$B$23*H57,MAX(Assumptions!$B$20*(1+Assumptions!$B$21)^(H$2-2027)*Assumptions!$B$38,Assumptions!$B$23*H57)) -> 449.01 | I60: =IF(I$2>Assumptions!$B$25,Assumptions!$B$23*I57,MAX(Assumptions!$B$20*(1+Assumptions!$B$21)^(I$2-2027)*Assumptions!$B$38,Assumptions!$B$23*I57)) -> 488.7 | J60: =IF(J$2>Assumptions!$B$25,Assumptions!$B$23*J57,MAX(Assumptions!$B$20*(1+Assumptions!$B$21)^(J$2-2027)*Assumptions!$B$38,Assumptions!$B$23*J57)) -> 497.52 | ... Z60: =IF(Z$2>Assumptions!$B$25,Assumptions!$B$23*Z57,MAX(Assumptions!$B$20*(1+Assumptions!$B$21)^(Z$2-2027)*Assumptions!$B$38,Assumptions!$B$23*Z57)) -> 0.28005665
A61: Total R&D | C61: =C59+C60 -> 305 | D61: =D59+D60 -> 254.5 | E61: =E59+E60 -> 221.96 | F61: =F59+F60 -> 299.16 | G61: =G59+G60 -> 385.74 | H61: =H59+H60 -> 449.01 | I61: =I59+I60 -> 488.7 | J61: =J59+J60 -> 497.52 | ... Z61: =Z59+Z60 -> 0.28005665
A62: Commercial SG&A | C62: =C12+C22+C32+C42+C52 -> 313.275 | D62: =D12+D22+D32+D42+D52 -> 540.3 | E62: =E12+E22+E32+E42+E52 -> 728.7875 | F62: =F12+F22+F32+F42+F52 -> 859.0125 | G62: =G12+G22+G32+G42+G52 -> 994.53 | H62: =H12+H22+H32+H42+H52 -> 1101.87 | I62: =I12+I22+I32+I42+I52 -> 1138.35 | J62: =J12+J22+J32+J42+J52 -> 1138.05 | ... Z62: =Z12+Z22+Z32+Z42+Z52 -> 0.59042752
A63: Corporate G&A | C63: =IF(C$2>Assumptions!$B$25,Assumptions!$B$22*C57,MAX(Assumptions!$B$19*(1+Assumptions!$B$21)^(C$2-2027)*Assumptions!$B$38,Assumptions!$B$22*C57)) -> 120 | D63: =IF(D$2>Assumptions!$B$25,Assumptions!$B$22*D57,MAX(Assumptions!$B$19*(1+Assumptions!$B$21)^(D$2-2027)*Assumptions!$B$38,Assumptions!$B$22*D57)) -> 123.6 | E63: =IF(E$2>Assumptions!$B$25,Assumptions!$B$22*E57,MAX(Assumptions!$B$19*(1+Assumptions!$B$21)^(E$2-2027)*Assumptions!$B$38,Assumptions!$B$22*E57)) -> 134.64 | F63: =IF(F$2>Assumptions!$B$25,Assumptions!$B$22*F57,MAX(Assumptions!$B$19*(1+Assumptions!$B$21)^(F$2-2027)*Assumptions!$B$38,Assumptions!$B$22*F57)) -> 199.44 | G63: =IF(G$2>Assumptions!$B$25,Assumptions!$B$22*G57,MAX(Assumptions!$B$19*(1+Assumptions!$B$21)^(G$2-2027)*Assumptions!$B$38,Assumptions!$B$22*G57)) -> 257.16 | H63: =IF(H$2>Assumptions!$B$25,Assumptions!$B$22*H57,MAX(Assumptions!$B$19*(1+Assumptions!$B$21)^(H$2-2027)*Assumptions!$B$38,Assumptions!$B$22*H57)) -> 299.34 | I63: =IF(I$2>Assumptions!$B$25,Assumptions!$B$22*I57,MAX(Assumptions!$B$19*(1+Assumptions!$B$21)^(I$2-2027)*Assumptions!$B$38,Assumptions!$B$22*I57)) -> 325.8 | J63: =IF(J$2>Assumptions!$B$25,Assumptions!$B$22*J57,MAX(Assumptions!$B$19*(1+Assumptions!$B$21)^(J$2-2027)*Assumptions!$B$38,Assumptions!$B$22*J57)) -> 331.68 | ... Z63: =IF(Z$2>Assumptions!$B$25,Assumptions!$B$22*Z57,MAX(Assumptions!$B$19*(1+Assumptions!$B$21)^(Z$2-2027)*Assumptions!$B$38,Assumptions!$B$22*Z57)) -> 0.18670444
A64: Total G&A incl. SG&A | C64: =C62+C63 -> 433.275 | D64: =D62+D63 -> 663.9 | E64: =E62+E63 -> 863.4275 | F64: =F62+F63 -> 1058.4525 | G64: =G62+G63 -> 1251.69 | H64: =H62+H63 -> 1401.21 | I64: =I62+I63 -> 1464.15 | J64: =J62+J63 -> 1469.73 | ... Z64: =Z62+Z63 -> 0.77713196
A65: Operating income (EBIT) | C65: =C57-C58-C61-C64 -> -280.715 | D65: =D57-D58-D61-D64 -> -29.47 | E65: =E57-E58-E61-E64 -> 528.9425 | F65: =F57-F58-F61-F64 -> 1032.5175 | G65: =G57-G58-G61-G64 -> 1443.54 | H65: =H57-H58-H61-H64 -> 1735.11 | I65: =I57-I58-I61-I64 -> 1948.65 | J65: =J57-J58-J61-J64 -> 2003.91 | ... Z65: =Z57-Z58-Z61-Z64 -> 1.1481084

Sheet NPV
A1: PRAX — risk-adjusted NPV (rNPV), $mm except per share
A3: Scenario | B3: =Assumptions!$C$4 -> Base
A4: Valuation date | B4: =Assumptions!$B$13 -> 46311
A5: Discount rate | B5: =Assumptions!$B$14 -> 0.11
A7: Period | C7: 2H 2026 | D7: 2027 | E7: 2028 | F7: 2029 | G7: 2030 | H7: 2031 | I7: 2032 | J7: 2033 | K7: 2034 | L7: 2035 | M7: 2036 | N7: 2037 | O7: 2038 | P7: 2039 | Q7: 2040 | R7: 2041 | S7: 2042 | T7: 2043 | U7: 2044 | V7: 2045 | W7: 2046 | X7: 2047 | Y7: 2048 | Z7: 2049 | AA7: 2050
A8: Revenue, risk-adjusted | C8: =SUM('Quarterly Model'!H2:I2) -> 0 | D8: ='Yearly Model'!H2 -> 471 | E8: ='Yearly Model'!I2 -> 925.5 | F8: ='Yearly Model'!J2 -> 1683 | G8: ='Yearly Model'!K2 -> 2493 | H8: ='Yearly Model'!L2 -> 3214.5 | I8: ='Yearly Model'!M2 -> 3741.75 | J8: ='Yearly Model'!N2 -> 4072.5 | K8: ='Yearly Model'!O2 -> 4146 | ... AA8: ='Yearly Model'!AE2 -> 2.3338055
A9: Operating income (EBIT) | C9: =SUM('Quarterly Model'!H8:I8) -> -217 | D9: ='Yearly Model'!H8 -> -280.715 | E9: ='Yearly Model'!I8 -> -29.47 | F9: ='Yearly Model'!J8 -> 528.9425 | G9: ='Yearly Model'!K8 -> 1032.5175 | H9: ='Yearly Model'!L8 -> 1443.54 | I9: ='Yearly Model'!M8 -> 1735.11 | J9: ='Yearly Model'!N8 -> 1948.65 | K9: ='Yearly Model'!O8 -> 2003.91 | ... AA9: ='Yearly Model'!AE8 -> 1.1481084
A10: Taxes on EBIT (after tax-loss pool) | C10: 0 | D10: =IF(D9>0,MAX(0,D9-'Yearly Model'!G21)*Assumptions!$B$15,0) -> 0 | E10: =IF(E9>0,MAX(0,E9-'Yearly Model'!H21)*Assumptions!$B$15,0) -> 0 | F10: =IF(F9>0,MAX(0,F9-'Yearly Model'!I21)*Assumptions!$B$15,0) -> 0 | G10: =IF(G9>0,MAX(0,G9-'Yearly Model'!J21)*Assumptions!$B$15,0) -> 0 | H10: =IF(H9>0,MAX(0,H9-'Yearly Model'!K21)*Assumptions!$B$15,0) -> 272.87754 | I10: =IF(I9>0,MAX(0,I9-'Yearly Model'!L21)*Assumptions!$B$15,0) -> 364.3731 | J10: =IF(J9>0,MAX(0,J9-'Yearly Model'!M21)*Assumptions!$B$15,0) -> 409.2165 | K10: =IF(K9>0,MAX(0,K9-'Yearly Model'!N21)*Assumptions!$B$15,0) -> 420.8211 | ... AA10: =IF(AA9>0,MAX(0,AA9-'Yearly Model'!AD21)*Assumptions!$B$15,0) -> 0.24110276
A11: Unlevered free cash flow | C11: =C9-C10 -> -217 | D11: =D9-D10 -> -280.715 | E11: =E9-E10 -> -29.47 | F11: =F9-F10 -> 528.9425 | G11: =G9-G10 -> 1032.5175 | H11: =H9-H10 -> 1170.6625 | I11: =I9-I10 -> 1370.7369 | J11: =J9-J10 -> 1539.4335 | ... AA11: =AA9-AA10 -> 0.90700561
A12: Cash-flow date (mid-period) | C12: =DATE(2026,10,1) -> 46296 | D12: =DATE(D7,7,1) -> 46569 | E12: =DATE(E7,7,1) -> 46935 | F12: =DATE(F7,7,1) -> 47300 | G12: =DATE(G7,7,1) -> 47665 | H12: =DATE(H7,7,1) -> 48030 | I12: =DATE(I7,7,1) -> 48396 | J12: =DATE(J7,7,1) -> 48761 | K12: =DATE(K7,7,1) -> 49126 | ... AA12: =DATE(AA7,7,1) -> 54970
A13: Years from valuation date | C13: =MAX(0,(C12-$B$4)/365.25) -> 0 | D13: =MAX(0,(D12-$B$4)/365.25) -> 0.7063655 | E13: =MAX(0,(E12-$B$4)/365.25) -> 1.7084189 | F13: =MAX(0,(F12-$B$4)/365.25) -> 2.7077344 | G13: =MAX(0,(G12-$B$4)/365.25) -> 3.70705 | H13: =MAX(0,(H12-$B$4)/365.25) -> 4.7063655 | I13: =MAX(0,(I12-$B$4)/365.25) -> 5.7084189 | J13: =MAX(0,(J12-$B$4)/365.25) -> 6.7077344 | ... AA13: =MAX(0,(AA12-$B$4)/365.25) -> 23.70705
A14: Discount factor | C14: =1/(1+$B$5)^C13 -> 1 | D14: =1/(1+$B$5)^D13 -> 0.92893518 | E14: =1/(1+$B$5)^E13 -> 0.83669923 | F14: =1/(1+$B$5)^F13 -> 0.75383693 | G14: =1/(1+$B$5)^G13 -> 0.67918088 | H14: =1/(1+$B$5)^H13 -> 0.61191838 | I14: =1/(1+$B$5)^I13 -> 0.5511597 | J14: =1/(1+$B$5)^J13 -> 0.49657574 | ... AA14: =1/(1+$B$5)^AA13 -> 0.084241458
A15: PV of free cash flow | C15: =C11*C14 -> -217 | D15: =D11*D14 -> -260.76604 | E15: =E11*E14 -> -24.657526 | F15: =F11*F14 -> 398.73639 | G15: =G11*G14 -> 701.26615 | H15: =H11*H14 -> 716.34987 | I15: =I11*I14 -> 755.49493 | J15: =J11*J14 -> 764.44532 | ... AA15: =AA11*AA14 -> 0.076407476
A17: Valuation summary
A18: PV of risk-adjusted free cash flows | C18: =SUM(C15:AA15) -> 7167.3182
A19: Cash & investments (Main; incl. post-quarter financing) | C19: =Main!C7 -> 1373.84
A20: Debt, convertibles & preferred at face (Main) | C20: =Main!C8 -> 0
A21: Equity value, all claims treated as debt | C21: =C18+C19-C20 -> 8541.1582
A22: Basic shares incl. pre-funded / as-converted (Main) | C22: =Main!C4 -> 29.163921
A23: Value / share before conversions | C23: =C21/C22 -> 292.86728
A25: Convertible instruments (converted if value / share before conversions > conversion price) | B25: Face ($mm) | C25: Shares (mm) | D25: Conv. price | E25: Converted?
A26: — | B26: 0 | C26: 0 | D26: 0 | E26: =IF(AND(C26>0,$C$23>D26),1,0) -> 0
A27: — | B27: 0 | C27: 0 | D27: 0 | E27: =IF(AND(C27>0,$C$23>D27),1,0) -> 0
A28: — | B28: 0 | C28: 0 | D28: 0 | E28: =IF(AND(C28>0,$C$23>D28),1,0) -> 0
A29: — | B29: 0 | C29: 0 | D29: 0 | E29: =IF(AND(C29>0,$C$23>D29),1,0) -> 0
A30: — | B30: 0 | C30: 0 | D30: 0 | E30: =IF(AND(C30>0,$C$23>D30),1,0) -> 0
A31: Equity value (rNPV) after conversions | C31: =C21+SUMPRODUCT(B26:B30,E26:E30) -> 8541.1582
A32: Shares after conversions (mm) | C32: =C22+SUMPRODUCT(C26:C30,E26:E30) -> 29.163921
A33: Value / share before options & warrants | C33: =C31/C32 -> 292.86728
A35: Options, warrants & RSUs (treasury-stock method) | B35: Count (mm) | C35: Strike | D35: Dilution (mm)
A36: Options (strike assumed) | B36: 1.905404 | C36: 60 | D36: =IF(AND(B36>0,$C$33>C36),B36*(1-C36/$C$33),0) -> 1.5150421
A37: RSUs / PSUs | B37: 0.654792 | C37: 0 | D37: =IF(AND(B37>0,$C$33>C37),B37*(1-C37/$C$33),0) -> 0.654792
A38: — | B38: 0 | C38: 0 | D38: =IF(AND(B38>0,$C$33>C38),B38*(1-C38/$C$33),0) -> 0
A39: — | B39: 0 | C39: 0 | D39: =IF(AND(B39>0,$C$33>C39),B39*(1-C39/$C$33),0) -> 0
A40: — | B40: 0 | C40: 0 | D40: =IF(AND(B40>0,$C$33>C40),B40*(1-C40/$C$33),0) -> 0
A41: — | B41: 0 | C41: 0 | D41: =IF(AND(B41>0,$C$33>C41),B41*(1-C41/$C$33),0) -> 0
A42: Diluted shares (mm) | C42: =C32+SUM(D36:D41) -> 31.333755
A43: rNPV / share, diluted | C43: =C31/C42 -> 272.58649
A44: Current price (Main) | C44: =Main!C3 -> 264.49
A45: Upside / (downside) to rNPV | C45: =C43/C44-1 -> 0.030611696
A46: Net cash / share | C46: =(C19-C20)/C22 -> 47.10752
A47: Est. cash & investments at 12/31/2026 | C47: ='Quarterly Model'!I20 -> 1182.34
A48: Liquidation value / share (12/31/2026E cash − debt − wind-down) | C48: =MAX(0,C47-C20-Assumptions!$B$27)/C22 -> 38.483851
A49: Market-implied value of pipeline (market cap − net cash) | C49: =Main!C5-(C19-C20) -> 6339.7255
A51: Sum of the parts (PV) | B51: $mm | C51: $ / share
A52: Relutrigine — SCN2A / SCN8A DEE | B52: =SUMPRODUCT(Pipeline!C14:Z14,$D$14:$AA$14) -> 2269.237 | C52: =B52/$C$42 -> 72.421483
A53: Ulixacaltamide — essential tremor (PDUFA Jan 29, 2027) | B53: =SUMPRODUCT(Pipeline!C24:Z24,$D$14:$AA$14) -> 8467.3933 | C53: =B53/$C$42 -> 270.23232
A54: Relutrigine — broad DEEs (EMERALD, data Q4 2026) | B54: =SUMPRODUCT(Pipeline!C34:Z34,$D$14:$AA$14) -> 1796.3144 | C54: =B54/$C$42 -> 57.328412
A55: Vormatrigine — focal / generalized epilepsy (POWER2/3) | B55: =SUMPRODUCT(Pipeline!C44:Z44,$D$14:$AA$14) -> 538.35105 | C55: =B55/$C$42 -> 17.181185
A56: Elsunersen — early-onset SCN2A DEE (ASO) | B56: =SUMPRODUCT(Pipeline!C54:Z54,$D$14:$AA$14) -> 600.77054 | C56: =B56/$C$42 -> 19.17327
A57: Corporate G&A + platform R&D (2027+) | B57: =-SUMPRODUCT(Pipeline!C60:Z60,$D$14:$AA$14)-SUMPRODUCT(Pipeline!C63:Z63,$D$14:$AA$14) -> -4564.805 | C57: =B57/$C$42 -> -145.68331
A58: 2H 2026 operating result | B58: =C11*C14 -> -217 | C58: =B58/$C$42 -> -6.9254387
A59: Taxes | B59: =-SUMPRODUCT(D10:AA10,D14:AA14) -> -1722.9431 | C59: =B59/$C$42 -> -54.986804
A60: Net cash (cash − all claims at face) | B60: =C19-C20 -> 1373.84 | C60: =B60/$C$42 -> 43.845367
A61: Add back converted claims | B61: =SUMPRODUCT(B26:B30,E26:E30) -> 0 | C61: =B61/$C$42 -> 0
A62: Equity value | B62: =SUM(B52:B61) -> 8541.1582 | C62: =B62/$C$42 -> 272.58649
A63: Check vs. equity value above (should be 0) | B63: =ROUND(B62-C31,6) -> 0

Sheet Options
A1: PRAX — PDUFA options analysis (per contract = 100 shares)
A3: Inputs
A4: Spot price (close 10/16/2026) | B4: 241.76
A5: Pricing date | B5: =DATE(2026,10,16) -> 46311
A6: PDUFA date | B6: =Assumptions!$B$30 -> 46383
A7: Expiry (first monthly after the PDUFA date) | B7: =DATE(2027,1,15) -> 46402
A8: Years to expiry (T) | B8: =(B7-B5)/365 -> 0.24931507
A9: Risk-free rate | B9: 0.04
A10: Reference IV for wide quotes (theo prices) | B10: 0.8404
A11: Contract multiplier | B11: 100
A13: Event model (two outcomes at the PDUFA)
A14: Model value / share, probability-weighted | B14: =NPV!C43 -> 272.58649
A15: Model value / share if approved | B15: =Assumptions!$D$142 -> 275.37473
A16: Model value / share if CRL | B16: =Assumptions!$D$141 -> 247.23121
A17: Model probability of approval | B17: =Assumptions!$B$32 -> 0.9
A18: Event-move scale (share of model jump priced at expiry) | B18: 1
A19: Floor after a CRL, % of est. 12/31/2026 net cash / share | B19: 0.5
A20: Floor price after a CRL | B20: =MAX(0,B19*(NPV!C47-NPV!C20)/NPV!C22) -> 20.270594
A21: Price if approved (center of outcome) | B21: =IF(B14>0,B4*(1+B18*(B15/B14-1)),B4+B18*(B15-B14)) -> 244.23293
A22: Price if CRL (center of outcome) | B22: =MAX(B20,IF(B14>0,B4*(1+B18*(B16/B14-1)),B4+B18*(B16-B14))) -> 219.27212
A23: Model expected price after the decision | B23: =B17*B21+(1-B17)*B22 -> 241.73685
A24: Non-event volatility (6-month realized, 3 largest days removed) | B24: 0.492
A25: Model fair ATM straddle, % of spot (jump + non-event volatility) | B25: =(B17*((B21*NORMSDIST(((LN(B21/240.0)+$B$24^2*$B$8/2)/($B$24*SQRT($B$8))))-240.0*NORMSDIST((((LN(B21/240.0)+$B$24^2*$B$8/2)/($B$24*SQRT($B$8)))-$B$24*SQRT($B$8))))+(240.0*NORMSDIST(-(((LN(B21/240.0)+$B$24^2*$B$8/2)/($B$24*SQRT($B$8)))-$B$24*SQRT($B$8)))-B21*NORMSDIST(-((LN(B21/240.0)+$B$24^2*$B$8/2)/($B$24*SQRT($B$8))))))+(1-B17)*((B22*NORMSDIST(((LN(B22/240.0)+$B$24^2*$B$8/2)/($B$24*SQRT($B$8))))-240.0*NORMSDIST((((LN(B22/240.0)+$B$24^2*$B$8/2)/($B$24*SQRT($B$8)))-$B$24*SQRT($B$8))))+(240.0*NORMSDIST(-(((LN(B22/240.0)+$B$24^2*$B$8/2)/($B$24*SQRT($B$8)))-$B$24*SQRT($B$8)))-B22*NORMSDIST(-((LN(B22/240.0)+$B$24^2*$B$8/2)/($B$24*SQRT($B$8)))))))/B4 -> 0.19647566
A26: Market ATM straddle, % of spot | B26: =($G$43+$G$44)/B4 -> 0.33152713
A27: Options richness (market straddle ÷ model straddle) | B27: =B26/B25 -> 1.68737
A28: Market snapshot — 1/15/2027 expiry (Cboe delayed quotes, 10/16/2026 close)
A29: Strike | B29: Call bid | C29: Call ask | D29: Call mid | E29: Call IV | F29: Put bid | G29: Put ask | H29: Put mid | I29: Put IV | J29: Call OI | K29: Put OI
A30: 160 | B30: 88 | C30: 97 | D30: =(B30+C30)/2 -> 92.5 | E30: 0.9104 | F30: 3 | G30: 12.9 | H30: =(F30+G30)/2 -> 7.95 | I30: 0.8994 | J30: 0 | K30: 20
A31: 210 | B31: 54.4 | C31: 63 | D31: =(B31+C31)/2 -> 58.7 | E31: 0.873 | F31: 18 | G31: 25 | H31: =(F31+G31)/2 -> 21.5 | I31: 0.813 | J31: 0 | K31: 0
A32: 220 | B32: 48.3 | C32: 57 | D32: =(B32+C32)/2 -> 52.65 | E32: 0.8551 | F32: 23 | G32: 32 | H32: =(F32+G32)/2 -> 27.5 | I32: 0.8475 | J32: 1 | K32: 0
A33: 230 | B33: 43.1 | C33: 52 | D33: =(B33+C33)/2 -> 47.55 | E33: 0.8506 | F33: 27 | G33: 36.7 | H33: =(F33+G33)/2 -> 31.85 | I33: 0.8332 | J33: 0 | K33: 10
A34: 240 | B34: 38.6 | C34: 47 | D34: =(B34+C34)/2 -> 42.8 | E34: 0.8454 | F34: 33 | G34: 41.7 | H34: =(F34+G34)/2 -> 37.35 | I34: 0.8353 | J34: 2 | K34: 1
A35: 250 | B35: 34 | C35: 43 | D35: =(B35+C35)/2 -> 38.5 | E35: 0.8418 | F35: 38 | G35: 47.7 | H35: =(F35+G35)/2 -> 42.85 | I35: 0.829 | J35: 4 | K35: 1
A36: 260 | B36: 30.2 | C36: 39 | D36: =(B36+C36)/2 -> 34.6 | E36: 0.839 | F36: 45 | G36: 53.4 | H36: =(F36+G36)/2 -> 49.2 | I36: 0.8328 | J36: 1 | K36: 8
A37: 270 | B37: 26.1 | C37: 36 | D37: =(B37+C37)/2 -> 31.05 | E37: 0.8376 | F37: 51 | G37: 60.7 | H37: =(F37+G37)/2 -> 55.85 | I37: 0.8354 | J37: 6 | K37: 4
A38: 280 | B38: 23.1 | C38: 33 | D38: =(B38+C38)/2 -> 28.05 | E38: 0.8389 | F38: 58 | G38: 66.9 | H38: =(F38+G38)/2 -> 62.45 | I38: 0.8303 | J38: 17 | K38: 5
A39: 320 | B39: 17 | C39: 22 | D39: =(B39+C39)/2 -> 19.5 | E39: 0.8662 | F39: 88 | G39: 96.9 | H39: =(F39+G39)/2 -> 92.45 | I39: 0.8259 | J39: 5 | K39: 6
A41: Legs (premium = mid when the market is tight, else Black-Scholes at the reference IV)
A42: Leg | B42: Type | C42: Strike | D42: Mid | E42: Spread % of mid | F42: BS value | G42: Premium used | H42: Source | I42: d1 | J42: Delta | K42: E[payoff] if approved | L42: E[payoff] if CRL
A43: Jan-27 $240 call | B43: C | C43: =A34 -> 240 | D43: =(B34+C34)/2 -> 42.8 | E43: =IF(B34>0,(C34-B34)/D43,9.99) -> 0.19626168 | F43: =IF(B43="C",$B$4*NORMSDIST((LN($B$4/C43)+($B$9+$B$10^2/2)*$B$8)/($B$10*SQRT($B$8)))-C43*EXP(-$B$9*$B$8)*NORMSDIST((LN($B$4/C43)+($B$9+$B$10^2/2)*$B$8)/($B$10*SQRT($B$8))-$B$10*SQRT($B$8)),C43*EXP(-$B$9*$B$8)*NORMSDIST(-((LN($B$4/C43)+($B$9+$B$10^2/2)*$B$8)/($B$10*SQRT($B$8))-$B$10*SQRT($B$8)))-$B$4*NORMSDIST(-(LN($B$4/C43)+($B$9+$B$10^2/2)*$B$8)/($B$10*SQRT($B$8)))) -> 41.936934 | G43: =IF(AND(B34>0,E43<=0.6),D43,F43) -> 42.8 | H43: =IF(AND(B34>0,E43<=0.6),"market","theo") -> market | I43: =(LN($B$4/C43)+($B$9+$B$10^2/2)*$B$8)/($B$10*SQRT($B$8)) -> 0.25098976 | J43: =IF(B43="C",NORMSDIST(I43),NORMSDIST(I43)-1) -> 0.59908899 | K43: =IF(B43="C",($B$21*NORMSDIST(((LN($B$21/C43)+$B$24^2*$B$8/2)/($B$24*SQRT($B$8))))-C43*NORMSDIST((((LN($B$21/C43)+$B$24^2*$B$8/2)/($B$24*SQRT($B$8)))-$B$24*SQRT($B$8)))),(C43*NORMSDIST(-(((LN($B$21/C43)+$B$24^2*$B$8/2)/($B$24*SQRT($B$8)))-$B$24*SQRT($B$8)))-$B$21*NORMSDIST(-((LN($B$21/C43)+$B$24^2*$B$8/2)/($B$24*SQRT($B$8)))))) -> 25.845234 | L43: =IF(B43="C",($B$22*NORMSDIST(((LN($B$22/C43)+$B$24^2*$B$8/2)/($B$24*SQRT($B$8))))-C43*NORMSDIST((((LN($B$22/C43)+$B$24^2*$B$8/2)/($B$24*SQRT($B$8)))-$B$24*SQRT($B$8)))),(C43*NORMSDIST(-(((LN($B$22/C43)+$B$24^2*$B$8/2)/($B$24*SQRT($B$8)))-$B$24*SQRT($B$8)))-$B$22*NORMSDIST(-((LN($B$22/C43)+$B$24^2*$B$8/2)/($B$24*SQRT($B$8)))))) -> 13.57691
A44: Jan-27 $240 put | B44: P | C44: =A34 -> 240 | D44: =(F34+G34)/2 -> 37.35 | E44: =IF(F34>0,(G34-F34)/D44,9.99) -> 0.23293173 | F44: =IF(B44="C",$B$4*NORMSDIST((LN($B$4/C44)+($B$9+$B$10^2/2)*$B$8)/($B$10*SQRT($B$8)))-C44*EXP(-$B$9*$B$8)*NORMSDIST((LN($B$4/C44)+($B$9+$B$10^2/2)*$B$8)/($B$10*SQRT($B$8))-$B$10*SQRT($B$8)),C44*EXP(-$B$9*$B$8)*NORMSDIST(-((LN($B$4/C44)+($B$9+$B$10^2/2)*$B$8)/($B$10*SQRT($B$8))-$B$10*SQRT($B$8)))-$B$4*NORMSDIST(-(LN($B$4/C44)+($B$9+$B$10^2/2)*$B$8)/($B$10*SQRT($B$8)))) -> 37.795404 | G44: =IF(AND(F34>0,E44<=0.6),D44,F44) -> 37.35 | H44: =IF(AND(F34>0,E44<=0.6),"market","theo") -> market | I44: =(LN($B$4/C44)+($B$9+$B$10^2/2)*$B$8)/($B$10*SQRT($B$8)) -> 0.25098976 | J44: =IF(B44="C",NORMSDIST(I44),NORMSDIST(I44)-1) -> -0.40091101 | K44: =IF(B44="C",($B$21*NORMSDIST(((LN($B$21/C44)+$B$24^2*$B$8/2)/($B$24*SQRT($B$8))))-C44*NORMSDIST((((LN($B$21/C44)+$B$24^2*$B$8/2)/($B$24*SQRT($B$8)))-$B$24*SQRT($B$8)))),(C44*NORMSDIST(-(((LN($B$21/C44)+$B$24^2*$B$8/2)/($B$24*SQRT($B$8)))-$B$24*SQRT($B$8)))-$B$21*NORMSDIST(-((LN($B$21/C44)+$B$24^2*$B$8/2)/($B$24*SQRT($B$8)))))) -> 21.612307 | L44: =IF(B44="C",($B$22*NORMSDIST(((LN($B$22/C44)+$B$24^2*$B$8/2)/($B$24*SQRT($B$8))))-C44*NORMSDIST((((LN($B$22/C44)+$B$24^2*$B$8/2)/($B$24*SQRT($B$8)))-$B$24*SQRT($B$8)))),(C44*NORMSDIST(-(((LN($B$22/C44)+$B$24^2*$B$8/2)/($B$24*SQRT($B$8)))-$B$24*SQRT($B$8)))-$B$22*NORMSDIST(-((LN($B$22/C44)+$B$24^2*$B$8/2)/($B$24*SQRT($B$8)))))) -> 34.304788
A45: Jan-27 $320 call | B45: C | C45: =A39 -> 320 | D45: =(B39+C39)/2 -> 19.5 | E45: =IF(B39>0,(C39-B39)/D45,9.99) -> 0.25641026 | F45: =IF(B45="C",$B$4*NORMSDIST((LN($B$4/C45)+($B$9+$B$10^2/2)*$B$8)/($B$10*SQRT($B$8)))-C45*EXP(-$B$9*$B$8)*NORMSDIST((LN($B$4/C45)+($B$9+$B$10^2/2)*$B$8)/($B$10*SQRT($B$8))-$B$10*SQRT($B$8)),C45*EXP(-$B$9*$B$8)*NORMSDIST(-((LN($B$4/C45)+($B$9+$B$10^2/2)*$B$8)/($B$10*SQRT($B$8))-$B$10*SQRT($B$8)))-$B$4*NORMSDIST(-(LN($B$4/C45)+($B$9+$B$10^2/2)*$B$8)/($B$10*SQRT($B$8)))) -> 17.993513 | G45: =IF(AND(B39>0,E45<=0.6),D45,F45) -> 19.5 | H45: =IF(AND(B39>0,E45<=0.6),"market","theo") -> market | I45: =(LN($B$4/C45)+($B$9+$B$10^2/2)*$B$8)/($B$10*SQRT($B$8)) -> -0.43458132 | J45: =IF(B45="C",NORMSDIST(I45),NORMSDIST(I45)-1) -> 0.33193318 | K45: =IF(B45="C",($B$21*NORMSDIST(((LN($B$21/C45)+$B$24^2*$B$8/2)/($B$24*SQRT($B$8))))-C45*NORMSDIST((((LN($B$21/C45)+$B$24^2*$B$8/2)/($B$24*SQRT($B$8)))-$B$24*SQRT($B$8)))),(C45*NORMSDIST(-(((LN($B$21/C45)+$B$24^2*$B$8/2)/($B$24*SQRT($B$8)))-$B$24*SQRT($B$8)))-$B$21*NORMSDIST(-((LN($B$21/C45)+$B$24^2*$B$8/2)/($B$24*SQRT($B$8)))))) -> 4.6905686 | L45: =IF(B45="C",($B$22*NORMSDIST(((LN($B$22/C45)+$B$24^2*$B$8/2)/($B$24*SQRT($B$8))))-C45*NORMSDIST((((LN($B$22/C45)+$B$24^2*$B$8/2)/($B$24*SQRT($B$8)))-$B$24*SQRT($B$8)))),(C45*NORMSDIST(-(((LN($B$22/C45)+$B$24^2*$B$8/2)/($B$24*SQRT($B$8)))-$B$24*SQRT($B$8)))-$B$22*NORMSDIST(-((LN($B$22/C45)+$B$24^2*$B$8/2)/($B$24*SQRT($B$8)))))) -> 1.7353836
A46: Jan-27 $160 put | B46: P | C46: =A30 -> 160 | D46: =(F30+G30)/2 -> 7.95 | E46: =IF(F30>0,(G30-F30)/D46,9.99) -> 1.245283 | F46: =IF(B46="C",$B$4*NORMSDIST((LN($B$4/C46)+($B$9+$B$10^2/2)*$B$8)/($B$10*SQRT($B$8)))-C46*EXP(-$B$9*$B$8)*NORMSDIST((LN($B$4/C46)+($B$9+$B$10^2/2)*$B$8)/($B$10*SQRT($B$8))-$B$10*SQRT($B$8)),C46*EXP(-$B$9*$B$8)*NORMSDIST(-((LN($B$4/C46)+($B$9+$B$10^2/2)*$B$8)/($B$10*SQRT($B$8))-$B$10*SQRT($B$8)))-$B$4*NORMSDIST(-(LN($B$4/C46)+($B$9+$B$10^2/2)*$B$8)/($B$10*SQRT($B$8)))) -> 6.6517698 | G46: =IF(AND(F30>0,E46<=0.6),D46,F46) -> 6.6517698 | H46: =IF(AND(F30>0,E46<=0.6),"market","theo") -> theo | I46: =(LN($B$4/C46)+($B$9+$B$10^2/2)*$B$8)/($B$10*SQRT($B$8)) -> 1.2172479 | J46: =IF(B46="C",NORMSDIST(I46),NORMSDIST(I46)-1) -> -0.11175495 | K46: =IF(B46="C",($B$21*NORMSDIST(((LN($B$21/C46)+$B$24^2*$B$8/2)/($B$24*SQRT($B$8))))-C46*NORMSDIST((((LN($B$21/C46)+$B$24^2*$B$8/2)/($B$24*SQRT($B$8)))-$B$24*SQRT($B$8)))),(C46*NORMSDIST(-(((LN($B$21/C46)+$B$24^2*$B$8/2)/($B$24*SQRT($B$8)))-$B$24*SQRT($B$8)))-$B$21*NORMSDIST(-((LN($B$21/C46)+$B$24^2*$B$8/2)/($B$24*SQRT($B$8)))))) -> 0.83750188 | L46: =IF(B46="C",($B$22*NORMSDIST(((LN($B$22/C46)+$B$24^2*$B$8/2)/($B$24*SQRT($B$8))))-C46*NORMSDIST((((LN($B$22/C46)+$B$24^2*$B$8/2)/($B$24*SQRT($B$8)))-$B$24*SQRT($B$8)))),(C46*NORMSDIST(-(((LN($B$22/C46)+$B$24^2*$B$8/2)/($B$24*SQRT($B$8)))-$B$24*SQRT($B$8)))-$B$22*NORMSDIST(-((LN($B$22/C46)+$B$24^2*$B$8/2)/($B$24*SQRT($B$8)))))) -> 2.1613996
A48: Strategies (+ = credit received, − = debit paid; per share unless noted)
A49: Metric | B49: Long straddle | C49: Bull call spread | D49: Bear put spread | E49: Iron butterfly
A50: Structure | B50: Buy $240 call + $240 put | C50: Buy $240 / sell $320 call | D50: Buy $240 / sell $160 put | E50: Sell $240 straddle, buy $160 put + $320 call
A51: Net premium | B51: =-$G$43-$G$44 -> -80.15 | C51: =-$G$43+$G$45 -> -23.3 | D51: =-$G$44+$G$46 -> -30.69823 | E51: =$G$43+$G$44-$G$45-$G$46 -> 53.99823
A52: Net premium / contract | B52: =B51*$B$11 -> -8015 | C52: =C51*$B$11 -> -2330 | D52: =D51*$B$11 -> -3069.823 | E52: =E51*$B$11 -> 5399.823
A53: Max profit / contract | B53: ="Unlimited" -> Unlimited | C53: =(320.0-240.0+C51)*$B$11 -> 5670 | D53: =(240.0-160.0+D51)*$B$11 -> 4930.177 | E53: =E51*$B$11 -> 5399.823
A54: Max loss / contract | B54: =B51*$B$11 -> -8015 | C54: =C51*$B$11 -> -2330 | D54: =D51*$B$11 -> -3069.823 | E54: =-(MAX(320.0-240.0,240.0-160.0)-E51)*$B$11 -> -2600.177
A55: Breakeven (low) | B55: =240.0+B51 -> 159.85 | C55: ="—" -> — | D55: =240.0+D51 -> 209.30177 | E55: =240.0-E51 -> 186.00177
A56: Breakeven (high) | B56: =240.0-B51 -> 320.15 | C56: =240.0-C51 -> 263.3 | D56: ="—" -> — | E56: =240.0+E51 -> 293.99823
A57: Prob. of profit (market-implied, lognormal) | B57: =(1-NORMSDIST((LN($B$4/B55)+($B$9-IF((($E$34+$I$34)/2)>0,(($E$34+$I$34)/2),$B$10)^2/2)*$B$8)/(IF((($E$34+$I$34)/2)>0,(($E$34+$I$34)/2),$B$10)*SQRT($B$8))))+NORMSDIST((LN($B$4/B56)+($B$9-IF((($E$34+$I$34)/2)>0,(($E$34+$I$34)/2),$B$10)^2/2)*$B$8)/(IF((($E$34+$I$34)/2)>0,(($E$34+$I$34)/2),$B$10)*SQRT($B$8))) -> 0.40805444 | C57: =NORMSDIST((LN($B$4/C56)+($B$9-IF((($E$34+$I$34)/2)>0,(($E$34+$I$34)/2),$B$10)^2/2)*$B$8)/(IF((($E$34+$I$34)/2)>0,(($E$34+$I$34)/2),$B$10)*SQRT($B$8))) -> 0.34847623 | D57: =1-NORMSDIST((LN($B$4/D55)+($B$9-IF((($E$34+$I$34)/2)>0,(($E$34+$I$34)/2),$B$10)^2/2)*$B$8)/(IF((($E$34+$I$34)/2)>0,(($E$34+$I$34)/2),$B$10)*SQRT($B$8))) -> 0.43740428 | E57: =MAX(0,NORMSDIST((LN($B$4/E55)+($B$9-IF((($E$34+$I$34)/2)>0,(($E$34+$I$34)/2),$B$10)^2/2)*$B$8)/(IF((($E$34+$I$34)/2)>0,(($E$34+$I$34)/2),$B$10)*SQRT($B$8)))-NORMSDIST((LN($B$4/E56)+($B$9-IF((($E$34+$I$34)/2)>0,(($E$34+$I$34)/2),$B$10)^2/2)*$B$8)/(IF((($E$34+$I$34)/2)>0,(($E$34+$I$34)/2),$B$10)*SQRT($B$8)))) -> 0.41248858
A58: Expected P/L if approved | B58: =((1)*$K$43+(1)*$K$44+B51)*$B$11 -> -3269.246 | C58: =((1)*$K$43+(-1)*$K$45+C51)*$B$11 -> -214.5335 | D58: =((1)*$K$44+(-1)*$K$46+D51)*$B$11 -> -992.34254 | E58: =((-1)*$K$43+(-1)*$K$44+(1)*$K$45+(1)*$K$46+E51)*$B$11 -> 1206.876
A59: Expected P/L if CRL | B59: =((1)*$L$43+(1)*$L$44+B51)*$B$11 -> -3226.8302 | C59: =((1)*$L$43+(-1)*$L$45+C51)*$B$11 -> -1145.8474 | D59: =((1)*$L$44+(-1)*$L$46+D51)*$B$11 -> 144.51582 | E59: =((-1)*$L$43+(-1)*$L$44+(1)*$L$45+(1)*$L$46+E51)*$B$11 -> 1001.3316
A60: Model expected P/L | B60: =$B$17*B58+(1-$B$17)*B59 -> -3265.0044 | C60: =$B$17*C58+(1-$B$17)*C59 -> -307.66489 | D60: =$B$17*D58+(1-$B$17)*D59 -> -878.6567 | E60: =$B$17*E58+(1-$B$17)*E59 -> 1186.3216
A61: Expected P/L ÷ max loss | B61: =B60/-B54 -> -0.40736175 | C61: =C60/-C54 -> -0.13204502 | D61: =D60/-D54 -> -0.28622389 | E61: =E60/-E54 -> 0.45624648
A63: Payoff at expiry per contract ($)
A64: Price at expiry | B64: Long straddle | C64: Bull call spread | D64: Bear put spread | E64: Iron butterfly
A65: 1.3 | B65: =(MAX($A65-240.0,0)+MAX(240.0-$A65,0)-$G$43-$G$44)*$B$11 -> 15855 | C65: =(MAX($A65-240.0,0)-MAX($A65-320.0,0)-$G$43+$G$45)*$B$11 -> -2330 | D65: =(MAX(240.0-$A65,0)-MAX(160.0-$A65,0)-$G$44+$G$46)*$B$11 -> 4930.177 | E65: =($G$43+$G$44-$G$45-$G$46-MAX($A65-240.0,0)-MAX(240.0-$A65,0)+MAX($A65-320.0,0)+MAX(160.0-$A65,0))*$B$11 -> -2600.177
A66: 17.3 | B66: =(MAX($A66-240.0,0)+MAX(240.0-$A66,0)-$G$43-$G$44)*$B$11 -> 14255 | C66: =(MAX($A66-240.0,0)-MAX($A66-320.0,0)-$G$43+$G$45)*$B$11 -> -2330 | D66: =(MAX(240.0-$A66,0)-MAX(160.0-$A66,0)-$G$44+$G$46)*$B$11 -> 4930.177 | E66: =($G$43+$G$44-$G$45-$G$46-MAX($A66-240.0,0)-MAX(240.0-$A66,0)+MAX($A66-320.0,0)+MAX(160.0-$A66,0))*$B$11 -> -2600.177
A67: 33.4 | B67: =(MAX($A67-240.0,0)+MAX(240.0-$A67,0)-$G$43-$G$44)*$B$11 -> 12645 | C67: =(MAX($A67-240.0,0)-MAX($A67-320.0,0)-$G$43+$G$45)*$B$11 -> -2330 | D67: =(MAX(240.0-$A67,0)-MAX(160.0-$A67,0)-$G$44+$G$46)*$B$11 -> 4930.177 | E67: =($G$43+$G$44-$G$45-$G$46-MAX($A67-240.0,0)-MAX(240.0-$A67,0)+MAX($A67-320.0,0)+MAX(160.0-$A67,0))*$B$11 -> -2600.177
A68: 49.4 | B68: =(MAX($A68-240.0,0)+MAX(240.0-$A68,0)-$G$43-$G$44)*$B$11 -> 11045 | C68: =(MAX($A68-240.0,0)-MAX($A68-320.0,0)-$G$43+$G$45)*$B$11 -> -2330 | D68: =(MAX(240.0-$A68,0)-MAX(160.0-$A68,0)-$G$44+$G$46)*$B$11 -> 4930.177 | E68: =($G$43+$G$44-$G$45-$G$46-MAX($A68-240.0,0)-MAX(240.0-$A68,0)+MAX($A68-320.0,0)+MAX(160.0-$A68,0))*$B$11 -> -2600.177
A69: 65.4 | B69: =(MAX($A69-240.0,0)+MAX(240.0-$A69,0)-$G$43-$G$44)*$B$11 -> 9445 | C69: =(MAX($A69-240.0,0)-MAX($A69-320.0,0)-$G$43+$G$45)*$B$11 -> -2330 | D69: =(MAX(240.0-$A69,0)-MAX(160.0-$A69,0)-$G$44+$G$46)*$B$11 -> 4930.177 | E69: =($G$43+$G$44-$G$45-$G$46-MAX($A69-240.0,0)-MAX(240.0-$A69,0)+MAX($A69-320.0,0)+MAX(160.0-$A69,0))*$B$11 -> -2600.177
A70: 81.5 | B70: =(MAX($A70-240.0,0)+MAX(240.0-$A70,0)-$G$43-$G$44)*$B$11 -> 7835 | C70: =(MAX($A70-240.0,0)-MAX($A70-320.0,0)-$G$43+$G$45)*$B$11 -> -2330 | D70: =(MAX(240.0-$A70,0)-MAX(160.0-$A70,0)-$G$44+$G$46)*$B$11 -> 4930.177 | E70: =($G$43+$G$44-$G$45-$G$46-MAX($A70-240.0,0)-MAX(240.0-$A70,0)+MAX($A70-320.0,0)+MAX(160.0-$A70,0))*$B$11 -> -2600.177
A71: 97.5 | B71: =(MAX($A71-240.0,0)+MAX(240.0-$A71,0)-$G$43-$G$44)*$B$11 -> 6235 | C71: =(MAX($A71-240.0,0)-MAX($A71-320.0,0)-$G$43+$G$45)*$B$11 -> -2330 | D71: =(MAX(240.0-$A71,0)-MAX(160.0-$A71,0)-$G$44+$G$46)*$B$11 -> 4930.177 | E71: =($G$43+$G$44-$G$45-$G$46-MAX($A71-240.0,0)-MAX(240.0-$A71,0)+MAX($A71-320.0,0)+MAX(160.0-$A71,0))*$B$11 -> -2600.177
A72: 113.5 | B72: =(MAX($A72-240.0,0)+MAX(240.0-$A72,0)-$G$43-$G$44)*$B$11 -> 4635 | C72: =(MAX($A72-240.0,0)-MAX($A72-320.0,0)-$G$43+$G$45)*$B$11 -> -2330 | D72: =(MAX(240.0-$A72,0)-MAX(160.0-$A72,0)-$G$44+$G$46)*$B$11 -> 4930.177 | E72: =($G$43+$G$44-$G$45-$G$46-MAX($A72-240.0,0)-MAX(240.0-$A72,0)+MAX($A72-320.0,0)+MAX(160.0-$A72,0))*$B$11 -> -2600.177
A73: 129.6 | B73: =(MAX($A73-240.0,0)+MAX(240.0-$A73,0)-$G$43-$G$44)*$B$11 -> 3025 | C73: =(MAX($A73-240.0,0)-MAX($A73-320.0,0)-$G$43+$G$45)*$B$11 -> -2330 | D73: =(MAX(240.0-$A73,0)-MAX(160.0-$A73,0)-$G$44+$G$46)*$B$11 -> 4930.177 | E73: =($G$43+$G$44-$G$45-$G$46-MAX($A73-240.0,0)-MAX(240.0-$A73,0)+MAX($A73-320.0,0)+MAX(160.0-$A73,0))*$B$11 -> -2600.177
A74: 145.6 | B74: =(MAX($A74-240.0,0)+MAX(240.0-$A74,0)-$G$43-$G$44)*$B$11 -> 1425 | C74: =(MAX($A74-240.0,0)-MAX($A74-320.0,0)-$G$43+$G$45)*$B$11 -> -2330 | D74: =(MAX(240.0-$A74,0)-MAX(160.0-$A74,0)-$G$44+$G$46)*$B$11 -> 4930.177 | E74: =($G$43+$G$44-$G$45-$G$46-MAX($A74-240.0,0)-MAX(240.0-$A74,0)+MAX($A74-320.0,0)+MAX(160.0-$A74,0))*$B$11 -> -2600.177
A75: 161.6 | B75: =(MAX($A75-240.0,0)+MAX(240.0-$A75,0)-$G$43-$G$44)*$B$11 -> -175 | C75: =(MAX($A75-240.0,0)-MAX($A75-320.0,0)-$G$43+$G$45)*$B$11 -> -2330 | D75: =(MAX(240.0-$A75,0)-MAX(160.0-$A75,0)-$G$44+$G$46)*$B$11 -> 4770.177 | E75: =($G$43+$G$44-$G$45-$G$46-MAX($A75-240.0,0)-MAX(240.0-$A75,0)+MAX($A75-320.0,0)+MAX(160.0-$A75,0))*$B$11 -> -2440.177
A76: 177.6 | B76: =(MAX($A76-240.0,0)+MAX(240.0-$A76,0)-$G$43-$G$44)*$B$11 -> -1775 | C76: =(MAX($A76-240.0,0)-MAX($A76-320.0,0)-$G$43+$G$45)*$B$11 -> -2330 | D76: =(MAX(240.0-$A76,0)-MAX(160.0-$A76,0)-$G$44+$G$46)*$B$11 -> 3170.177 | E76: =($G$43+$G$44-$G$45-$G$46-MAX($A76-240.0,0)-MAX(240.0-$A76,0)+MAX($A76-320.0,0)+MAX(160.0-$A76,0))*$B$11 -> -840.17698
... A95: 482.2 | B95: =(MAX($A95-240.0,0)+MAX(240.0-$A95,0)-$G$43-$G$44)*$B$11 -> 16205 | C95: =(MAX($A95-240.0,0)-MAX($A95-320.0,0)-$G$43+$G$45)*$B$11 -> 5670 | D95: =(MAX(240.0-$A95,0)-MAX(160.0-$A95,0)-$G$44+$G$46)*$B$11 -> -3069.823 | E95: =($G$43+$G$44-$G$45-$G$46-MAX($A95-240.0,0)-MAX(240.0-$A95,0)+MAX($A95-320.0,0)+MAX(160.0-$A95,0))*$B$11 -> -2600.177
