Workbook

Sheet Main
B2: PTC Therapeutics, Inc.
B3: Price | C3: =INDEX([1]Pharma!$F$1:$F$1000,MATCH("PTCT",[1]Pharma!$B$1:$B$1000,0)) -> 62.92
B4: Shares | C4: 83.460802
B5: Market Cap. | C5: =C3*C4 -> 5251.3537
B7: Cash | C7: =1049.887+1179.195 -> 2229.082
B8: Debt | C8: =55.451+535.519 -> 590.97
B9: Enterprise V. | C9: =C5-C7+C8 -> 3613.2417
B11: NPV / Share | C11: =NPV!B28 -> 47.505232
B12: Upside | C12: =IFERROR(C11/C3-1,"") -> -0.24498995
B13: Cash / Share | C13: =IFERROR((C7-C8)/C4,"") -> 19.627322
B14: Scenario | C14: =Assumptions!C4 -> Base
B15: Model | C15: DCF

Sheet Yearly Model
B1: 2011 | C1: 2012 | D1: 2013 | E1: 2014 | F1: 2015 | G1: 2016 | H1: 2017 | I1: 2018 | J1: 2019 | K1: 2020 | L1: 2021 | M1: 2022 | N1: 2023 | O1: 2024 | P1: 2025 | Q1: 2026 | R1: 2027 | S1: 2028 | T1: 2029 | U1: 2030 | V1: 2031 | W1: 2032 | X1: 2033 | Y1: 2034 | Z1: 2035
A2: Revenue | B2: 105.412 | C2: 33.946 | D2: 34.696 | E2: 25.245 | F2: 36.766 | G2: 82.705 | H2: 194.392 | I2: 264.734 | J2: 306.98 | K2: 380.766 | L2: 538.593 | M2: 698.801 | N2: 937.822 | O2: 806.78 | P2: 1730.655 | Q2: =P2*(1+NPV!C5) -> 1557.5895 | R2: =Q2*(1+NPV!D5) -> 1423.4637 | S2: =R2*(1+NPV!E5) -> 1320.658 | T2: =S2*(1+NPV!F5) -> 1243.6196 | U2: =T2*(1+NPV!G5) -> 1188.3477 | V2: =U2*(1+NPV!H5) -> 1152.037 | W2: =V2*(1+NPV!I5) -> 1132.8364 | X2: =W2*(1+NPV!J5) -> 1129.6896 | ... Z2: =Y2*(1+NPV!L5) -> 1170.7978
A3: Cost of Sales | B3: 0 | C3: 0 | D3: 0 | E3: 0 | F3: 0 | G3: 0 | H3: 4.577 | I3: 12.67 | J3: 12.135 | K3: 0 | L3: 0 | M3: 0 | N3: 0 | O3: 0 | P3: 0 | Q3: =Q2*(1-Assumptions!$B$19) -> 61.524785 | R3: =R2*(1-Assumptions!$B$19) -> 56.226818 | S3: =S2*(1-Assumptions!$B$19) -> 52.165992 | T3: =T2*(1-Assumptions!$B$19) -> 49.122976 | U3: =U2*(1-Assumptions!$B$19) -> 46.939732 | V3: =V2*(1-Assumptions!$B$19) -> 45.505463 | W3: =W2*(1-Assumptions!$B$19) -> 44.747038 | X3: =X2*(1-Assumptions!$B$19) -> 44.622741 | ... Z3: =Z2*(1-Assumptions!$B$19) -> 46.246513
A4: Gross Margin | B4: =B2-B3 -> 105.412 | C4: =C2-C3 -> 33.946 | D4: =D2-D3 -> 34.696 | E4: =E2-E3 -> 25.245 | F4: =F2-F3 -> 36.766 | G4: =G2-G3 -> 82.705 | H4: =H2-H3 -> 189.815 | I4: =I2-I3 -> 252.064 | ... Z4: =Z2-Z3 -> 1124.5513
A5: Research & Dev. | B5: 58.677 | C5: 46.139 | D5: 54.875 | E5: 79.838 | F5: 121.816 | G5: 117.633 | H5: 117.456 | I5: 171.984 | J5: 257.452 | K5: 477.643 | L5: 540.684 | M5: 651.496 | N5: 666.563 | O5: 534.48 | P5: 455.249 | Q5: =Q7*Assumptions!$B$20 -> 680.16194 | R5: =R7*Assumptions!$B$20 -> 615.92762 | S5: =S7*Assumptions!$B$20 -> 566.18826 | T5: =T7*Assumptions!$B$20 -> 528.2115 | U5: =U7*Assumptions!$B$20 -> 500.00628 | V5: =V7*Assumptions!$B$20 -> 480.14366 | W5: =W7*Assumptions!$B$20 -> 467.63302 | X5: =X7*Assumptions!$B$20 -> 461.83832 | ... Z5: =Z7*Assumptions!$B$20 -> 469.32548
A6: SG&A & Other | B6: 16.153 | C6: 14.615 | D6: 25.219 | E6: 44.82 | F6: 82.08 | G6: 97.13 | H6: 136.651 | I6: 195.765 | J6: 278.551 | K6: 334.891 | L6: 372.352 | M6: 494.714 | N6: 710.761 | O6: 574.87 | P6: 408.471 | Q6: =Q7-Q5 -> 610.22308 | R6: =R7-R5 -> 552.59376 | S6: =S7-S5 -> 507.96894 | T6: =T7-T5 -> 473.89721 | U6: =U7-U5 -> 448.59224 | V6: =V7-V5 -> 430.77203 | W6: =W7-W5 -> 419.54782 | X6: =X7-X5 -> 414.34897 | ... Z6: =Z7-Z5 -> 421.06625
A7: Operating Expense | B7: =SUM(B5:B6) -> 74.83 | C7: =SUM(C5:C6) -> 60.754 | D7: =SUM(D5:D6) -> 80.094 | E7: =SUM(E5:E6) -> 124.658 | F7: =SUM(F5:F6) -> 203.896 | G7: =SUM(G5:G6) -> 214.763 | H7: =SUM(H5:H6) -> 254.107 | I7: =SUM(I5:I6) -> 367.749 | ... P7: =SUM(P5:P6) -> 863.72 | Q7: =Q4-Q2*NPV!C6 -> 1290.385 | R7: =R4-R2*NPV!D6 -> 1168.5214 | S7: =S4-S2*NPV!E6 -> 1074.1572 | T7: =T4-T2*NPV!F6 -> 1002.1087 | U7: =U4-U2*NPV!G6 -> 948.59852 | V7: =V4-V2*NPV!H6 -> 910.91568 | W7: =W4-W2*NPV!I6 -> 887.18084 | X7: =X4-X2*NPV!J6 -> 876.18729 | ... Z7: =Z4-Z2*NPV!L6 -> 890.39173
A8: Operating Income | B8: =B4-B7 -> 30.582 | C8: =C4-C7 -> -26.808 | D8: =D4-D7 -> -45.398 | E8: =E4-E7 -> -99.413 | F8: =F4-F7 -> -167.13 | G8: =G4-G7 -> -132.058 | H8: =H4-H7 -> -64.292 | I8: =I4-I7 -> -115.685 | ... Z8: =Z4-Z7 -> 234.15956
A9: Interest & Other | B9: -1.983 | C9: 0.573 | D9: -6.176 | E9: 0.967 | F9: -2.832 | G9: -9.483 | H9: -13.373 | I9: -12.425 | J9: 1.232 | K9: 28.836 | L9: -143.896 | M9: -140.061 | N9: -256.604 | O9: -60.554 | P9: -169.96 | Q9: 0 | R9: 0 | S9: 0 | T9: 0 | U9: 0 | V9: 0 | W9: 0 | X9: 0 | Y9: 0 | Z9: 0
A10: Pretax | B10: =B8+B9 -> 28.599 | C10: =C8+C9 -> -26.235 | D10: =D8+D9 -> -51.574 | E10: =E8+E9 -> -98.446 | F10: =F8+F9 -> -169.962 | G10: =G8+G9 -> -141.541 | H10: =H8+H9 -> -77.665 | I10: =I8+I9 -> -128.11 | ... Z10: =Z8+Z9 -> 234.15956
A11: Taxes | B11: -2.306 | C11: 0 | D11: 0 | E11: -4.693 | F11: 0.485 | G11: 0.569 | H11: 1.335 | I11: -0.029 | J11: 11.65 | K11: 35.228 | L11: 5.561 | M11: -28.47 | N11: -69.506 | O11: 0.176 | P11: 13.975 | Q11: =MAX(0,Q10)*Assumptions!$E$14 -> 34.965548 | R11: =MAX(0,R10)*Assumptions!$E$14 -> 33.781641 | S11: =MAX(0,S10)*Assumptions!$E$14 -> 33.036921 | T11: =MAX(0,T10)*Assumptions!$E$14 -> 32.705953 | U11: =MAX(0,U10)*Assumptions!$E$14 -> 32.777599 | V11: =MAX(0,V10)*Assumptions!$E$14 -> 33.254701 | W11: =MAX(0,W10)*Assumptions!$E$14 -> 34.154451 | X11: =MAX(0,X10)*Assumptions!$E$14 -> 35.509535 | ... Z11: =MAX(0,Z10)*Assumptions!$E$14 -> 39.807125
A12: Net Income | B12: 30.905 | C12: -26.235 | D12: -51.574 | E12: -93.753 | F12: -170.447 | G12: -142.11 | H12: -79 | I12: -128.081 | J12: -251.576 | K12: -438.16 | L12: -523.9 | M12: -559 | N12: -626.6 | O12: -363.3 | P12: 683 | Q12: =Q10-Q11 -> 170.71415 | R12: =R10-R11 -> 164.9339 | S12: =S10-S11 -> 161.29791 | T12: =T10-T11 -> 159.68201 | U12: =U10-U11 -> 160.03181 | V12: =V10-V11 -> 162.36119 | W12: =W10-W11 -> 166.75409 | X12: =X10-X11 -> 173.37008 | ... Z12: =Z10-Z11 -> 194.35243
A13: Earnings per Share | B13: =IFERROR(B12/B14,0) -> 2.4103104 | C13: =IFERROR(C12/C14,0) -> -2.0440203 | D13: =IFERROR(D12/D14,0) -> -4.0201107 | E13: =IFERROR(E12/E14,0) -> -2.9701568 | F13: =IFERROR(F12/F14,0) -> -5.068905 | G13: =IFERROR(G12/G14,0) -> -4.1741812 | H13: =IFERROR(H12/H14,0) -> -2.0161805 | I13: =IFERROR(I12/I14,0) -> -2.7499356 | ... Z13: =IFERROR(Z12/Z14,0) -> 2.3286672
A14: Shares | B14: 12.822 | C14: 12.835 | D14: 12.829 | E14: 31.565 | F14: 33.626 | G14: 34.045 | H14: 39.183 | I14: 46.576 | J14: 58.863 | K14: 66.028 | L14: 70.466 | M14: 71.729 | N14: 74.838 | O14: 76.845 | P14: 88.311 | Q14: =Main!$C$4 -> 83.460802 | R14: =Main!$C$4 -> 83.460802 | S14: =Main!$C$4 -> 83.460802 | T14: =Main!$C$4 -> 83.460802 | U14: =Main!$C$4 -> 83.460802 | V14: =Main!$C$4 -> 83.460802 | W14: =Main!$C$4 -> 83.460802 | X14: =Main!$C$4 -> 83.460802 | ... Z14: =Main!$C$4 -> 83.460802
A16: Revenue Change | C16: =IFERROR(C2/B2-1,"") -> -0.67796835 | D16: =IFERROR(D2/C2-1,"") -> 0.022093914 | E16: =IFERROR(E2/D2-1,"") -> -0.27239451 | F16: =IFERROR(F2/E2-1,"") -> 0.4563676 | G16: =IFERROR(G2/F2-1,"") -> 1.2494968 | H16: =IFERROR(H2/G2-1,"") -> 1.3504262 | I16: =IFERROR(I2/H2-1,"") -> 0.36185645 | J16: =IFERROR(J2/I2-1,"") -> 0.15957905 | ... Z16: =IFERROR(Z2/Y2-1,"") -> 0.025
A17: Gross Margin | B17: =IFERROR(B4/B2,"") -> 1 | C17: =IFERROR(C4/C2,"") -> 1 | D17: =IFERROR(D4/D2,"") -> 1 | E17: =IFERROR(E4/E2,"") -> 1 | F17: =IFERROR(F4/F2,"") -> 1 | G17: =IFERROR(G4/G2,"") -> 1 | H17: =IFERROR(H4/H2,"") -> 0.97645479 | I17: =IFERROR(I4/I2,"") -> 0.95214064 | ... Z17: =IFERROR(Z4/Z2,"") -> 0.9605
A18: Operating Margin | B18: =IFERROR(B8/B2,"") -> 0.29011877 | C18: =IFERROR(C8/C2,"") -> -0.78972486 | D18: =IFERROR(D8/D2,"") -> -1.3084505 | E18: =IFERROR(E8/E2,"") -> -3.9379283 | F18: =IFERROR(F8/F2,"") -> -4.545776 | G18: =IFERROR(G8/G2,"") -> -1.5967354 | H18: =IFERROR(H8/H2,"") -> -0.33073378 | I18: =IFERROR(I8/I2,"") -> -0.4369858 | ... Z18: =IFERROR(Z8/Z2,"") -> 0.2
A19: Actual / Estimate | B19: A | C19: A | D19: A | E19: A | F19: A | G19: A | H19: A | I19: A | J19: A | K19: A | L19: A | M19: A | N19: A | O19: A | P19: A | Q19: E | R19: E | S19: E | T19: E | U19: E | V19: E | W19: E | X19: E | Y19: E | Z19: E

Sheet Quarterly Model

Sheet Assumptions
A1: PTC Therapeutics, Inc.: basic DCF assumptions
A2: Blue = input, black = formula, green = link. $mm unless noted.
A4: Scenario (1 Bear, 2 Base, 3 Bull) | B4: 2 | C4: =CHOOSE($B$4,"Bear","Base","Bull") -> Base
A6: Discount rate override (blank = scenario)
A7: Terminal growth override (blank = scenario)
A9: Parameter | B9: Bear | C9: Base | D9: Bull | E9: Live
A10: Discount rate | B10: 0.105 | C10: 0.095 | D10: 0.085 | E10: =IF(ISNUMBER($B$6),$B$6,CHOOSE($B$4,B10,C10,D10)) -> 0.095
A11: Terminal growth | B11: 0.02 | C11: 0.025 | D11: 0.03 | E11: =IF(ISNUMBER($B$7),$B$7,CHOOSE($B$4,B11,C11,D11)) -> 0.025
A12: Revenue growth, first forecast year | B12: -0.15 | C12: -0.1 | D12: -0.05 | E12: =CHOOSE($B$4,B12,C12,D12) -> -0.1
A13: Operating margin, year 10 | B13: 0.15 | C13: 0.2 | D13: 0.25 | E13: =CHOOSE($B$4,B13,C13,D13) -> 0.2
A14: Tax rate on operating income | B14: 0.17 | C14: 0.17 | D14: 0.17 | E14: =CHOOSE($B$4,B14,C14,D14) -> 0.17
A15: Reinvestment, % of revenue increase | B15: 0.25 | C15: 0.25 | D15: 0.25 | E15: =CHOOSE($B$4,B15,C15,D15) -> 0.25
A17: Single inputs
A18: Starting operating margin (TTM) | B18: 0.1245
A19: Gross margin (forecast) | B19: 0.9605
A20: R&D share of operating expense (forecast) | B20: 0.5271
A21: Forecast years | B21: 10
A22: First forecast year, fraction after balance sheet date | B22: 0.5041
A23: Balance sheet date | B23: 46203
A24: Reporting currency per USD (USD) | B24: 1
A25: Base revenue, FY2025 | B25: ='Yearly Model'!P2 -> 1730.655
A27: Scenario summary
A28: Scenario | B28: Enterprise value | C28: Equity value | D28: NPV / share | E28: Upside
A29: Live | B29: =NPV!B23 -> 2326.7128 | C29: =NPV!B26 -> 3964.8248 | D29: =NPV!B28 -> 47.505232 | E29: =NPV!B30 -> -0.24498995
A30: 1 | B30: 1354.5329 | C30: 2992.6449 | D30: 35.856891 | E30: -0.43011933
A31: 2 | B31: 2326.7128 | C31: 3964.8248 | D31: 47.505232 | E31: -0.24498995
A32: 3 | B32: 4297.3612 | C32: 5935.4732 | D32: 71.116896 | E32: 0.13027489
A35: NPV / share: discount rate (rows) x terminal growth (columns)
A36: =NPV!B28 -> 47.505232 | B36: 0.015 | C36: 0.02 | D36: 0.025 | E36: 0.03 | F36: 0.035
A37: 0.075 | B37: 53.0062 | C37: 55.209023 | D37: 57.849845 | E37: 61.074647 | F37: 65.102398
A38: 0.085 | B38: 48.497095 | C38: 50.028742 | D38: 51.813618 | E38: 53.920773 | F38: 56.446871
A39: 0.095 | B39: 45.118847 | C39: 46.233275 | D39: 47.505232 | E39: 48.97106 | F39: 50.679211
A40: 0.105 | B40: 42.493596 | C40: 43.33291 | D40: 44.275738 | E40: 45.342775 | F40: 46.560624
A41: 0.115 | B41: 40.394751 | C41: 41.044262 | D41: 41.764753 | E41: 42.568743 | F41: 43.471877

Sheet NPV
A1: PTC Therapeutics, Inc.: free-cash-flow DCF ($mm)
A3: Fiscal year | B3: ='Yearly Model'!P1 -> 2025 | C3: ='Yearly Model'!Q1 -> 2026 | D3: ='Yearly Model'!R1 -> 2027 | E3: ='Yearly Model'!S1 -> 2028 | F3: ='Yearly Model'!T1 -> 2029 | G3: ='Yearly Model'!U1 -> 2030 | H3: ='Yearly Model'!V1 -> 2031 | I3: ='Yearly Model'!W1 -> 2032 | ... L3: ='Yearly Model'!Z1 -> 2035
A4: Period | B4: Actual | C4: 1 | D4: 2 | E4: 3 | F4: 4 | G4: 5 | H4: 6 | I4: 7 | J4: 8 | K4: 9 | L4: 10
A5: Revenue growth | C5: =Assumptions!$E$12+(Assumptions!$E$11-Assumptions!$E$12)*(C4-1)/(Assumptions!$B$21-1) -> -0.1 | D5: =Assumptions!$E$12+(Assumptions!$E$11-Assumptions!$E$12)*(D4-1)/(Assumptions!$B$21-1) -> -0.086111111 | E5: =Assumptions!$E$12+(Assumptions!$E$11-Assumptions!$E$12)*(E4-1)/(Assumptions!$B$21-1) -> -0.072222222 | F5: =Assumptions!$E$12+(Assumptions!$E$11-Assumptions!$E$12)*(F4-1)/(Assumptions!$B$21-1) -> -0.058333333 | G5: =Assumptions!$E$12+(Assumptions!$E$11-Assumptions!$E$12)*(G4-1)/(Assumptions!$B$21-1) -> -0.044444444 | H5: =Assumptions!$E$12+(Assumptions!$E$11-Assumptions!$E$12)*(H4-1)/(Assumptions!$B$21-1) -> -0.030555556 | I5: =Assumptions!$E$12+(Assumptions!$E$11-Assumptions!$E$12)*(I4-1)/(Assumptions!$B$21-1) -> -0.016666667 | J5: =Assumptions!$E$12+(Assumptions!$E$11-Assumptions!$E$12)*(J4-1)/(Assumptions!$B$21-1) -> -0.0027777778 | ... L5: =Assumptions!$E$12+(Assumptions!$E$11-Assumptions!$E$12)*(L4-1)/(Assumptions!$B$21-1) -> 0.025
A6: Operating margin | B6: =IFERROR(B8/B7,0) -> 0.50092884 | C6: =Assumptions!$B$18+(Assumptions!$E$13-Assumptions!$B$18)*C4/Assumptions!$B$21 -> 0.13205 | D6: =Assumptions!$B$18+(Assumptions!$E$13-Assumptions!$B$18)*D4/Assumptions!$B$21 -> 0.1396 | E6: =Assumptions!$B$18+(Assumptions!$E$13-Assumptions!$B$18)*E4/Assumptions!$B$21 -> 0.14715 | F6: =Assumptions!$B$18+(Assumptions!$E$13-Assumptions!$B$18)*F4/Assumptions!$B$21 -> 0.1547 | G6: =Assumptions!$B$18+(Assumptions!$E$13-Assumptions!$B$18)*G4/Assumptions!$B$21 -> 0.16225 | H6: =Assumptions!$B$18+(Assumptions!$E$13-Assumptions!$B$18)*H4/Assumptions!$B$21 -> 0.1698 | I6: =Assumptions!$B$18+(Assumptions!$E$13-Assumptions!$B$18)*I4/Assumptions!$B$21 -> 0.17735 | J6: =Assumptions!$B$18+(Assumptions!$E$13-Assumptions!$B$18)*J4/Assumptions!$B$21 -> 0.1849 | ... L6: =Assumptions!$B$18+(Assumptions!$E$13-Assumptions!$B$18)*L4/Assumptions!$B$21 -> 0.2
A7: Revenue | B7: ='Yearly Model'!P2 -> 1730.655 | C7: ='Yearly Model'!Q2 -> 1557.5895 | D7: ='Yearly Model'!R2 -> 1423.4637 | E7: ='Yearly Model'!S2 -> 1320.658 | F7: ='Yearly Model'!T2 -> 1243.6196 | G7: ='Yearly Model'!U2 -> 1188.3477 | H7: ='Yearly Model'!V2 -> 1152.037 | I7: ='Yearly Model'!W2 -> 1132.8364 | ... L7: ='Yearly Model'!Z2 -> 1170.7978
A8: Operating income | B8: ='Yearly Model'!P8 -> 866.935 | C8: ='Yearly Model'!Q8 -> 205.67969 | D8: ='Yearly Model'!R8 -> 198.71554 | E8: ='Yearly Model'!S8 -> 194.33483 | F8: ='Yearly Model'!T8 -> 192.38796 | G8: ='Yearly Model'!U8 -> 192.80941 | H8: ='Yearly Model'!V8 -> 195.61589 | I8: ='Yearly Model'!W8 -> 200.90854 | ... L8: ='Yearly Model'!Z8 -> 234.15956
A9: Tax on operating income | C9: =MAX(0,C8)*Assumptions!$E$14 -> 34.965548 | D9: =MAX(0,D8)*Assumptions!$E$14 -> 33.781641 | E9: =MAX(0,E8)*Assumptions!$E$14 -> 33.036921 | F9: =MAX(0,F8)*Assumptions!$E$14 -> 32.705953 | G9: =MAX(0,G8)*Assumptions!$E$14 -> 32.777599 | H9: =MAX(0,H8)*Assumptions!$E$14 -> 33.254701 | I9: =MAX(0,I8)*Assumptions!$E$14 -> 34.154451 | J9: =MAX(0,J8)*Assumptions!$E$14 -> 35.509535 | ... L9: =MAX(0,L8)*Assumptions!$E$14 -> 39.807125
A10: NOPAT | C10: =C8-C9 -> 170.71415 | D10: =D8-D9 -> 164.9339 | E10: =E8-E9 -> 161.29791 | F10: =F8-F9 -> 159.68201 | G10: =G8-G9 -> 160.03181 | H10: =H8-H9 -> 162.36119 | I10: =I8-I9 -> 166.75409 | J10: =J8-J9 -> 173.37008 | ... L10: =L8-L9 -> 194.35243
A11: Reinvestment | C11: =(C7-B7)*Assumptions!$E$15 -> -43.266375 | D11: =(D7-C7)*Assumptions!$E$15 -> -33.531441 | E11: =(E7-D7)*Assumptions!$E$15 -> -25.701429 | F11: =(F7-E7)*Assumptions!$E$15 -> -19.259596 | G11: =(G7-F7)*Assumptions!$E$15 -> -13.817996 | H11: =(H7-G7)*Assumptions!$E$15 -> -9.0776557 | I11: =(I7-H7)*Assumptions!$E$15 -> -4.8001543 | J11: =(J7-I7)*Assumptions!$E$15 -> -0.78669195 | ... L11: =(L7-K7)*Assumptions!$E$15 -> 7.139011
A12: Free cash flow | C12: =C10-C11 -> 213.98052 | D12: =D10-D11 -> 198.46534 | E12: =E10-E11 -> 186.99934 | F12: =F10-F11 -> 178.9416 | G12: =G10-G11 -> 173.8498 | H12: =H10-H11 -> 171.43884 | I12: =I10-I11 -> 171.55424 | J12: =J10-J11 -> 174.15677 | ... L12: =L10-L11 -> 187.21342
A13: Year fraction | C13: =Assumptions!$B$22 -> 0.5041 | D13: 1 | E13: 1 | F13: 1 | G13: 1 | H13: 1 | I13: 1 | J13: 1 | K13: 1 | L13: 1
A14: Discount time (mid-period) | C14: =C13/2 -> 0.25205 | D14: =C14+C13/2+D13/2 -> 1.0041 | E14: =D14+D13/2+E13/2 -> 2.0041 | F14: =E14+E13/2+F13/2 -> 3.0041 | G14: =F14+F13/2+G13/2 -> 4.0041 | H14: =G14+G13/2+H13/2 -> 5.0041 | I14: =H14+H13/2+I13/2 -> 6.0041 | J14: =I14+I13/2+J13/2 -> 7.0041 | K14: =J14+J13/2+K13/2 -> 8.0041 | L14: =K14+K13/2+L13/2 -> 9.0041
A15: Discount factor | C15: =1/(1+Assumptions!$E$10)^C14 -> 0.977385 | D15: =1/(1+Assumptions!$E$10)^D14 -> 0.91290226 | E15: =1/(1+Assumptions!$E$10)^E14 -> 0.8337007 | F15: =1/(1+Assumptions!$E$10)^F14 -> 0.7613705 | G15: =1/(1+Assumptions!$E$10)^G14 -> 0.69531552 | H15: =1/(1+Assumptions!$E$10)^H14 -> 0.63499135 | I15: =1/(1+Assumptions!$E$10)^I14 -> 0.57990077 | J15: =1/(1+Assumptions!$E$10)^J14 -> 0.52958975 | ... L15: =1/(1+Assumptions!$E$10)^L14 -> 0.44168366
A16: PV of free cash flow | C16: =C12*C13*C15 -> 105.42816 | D16: =D12*D13*D15 -> 181.17945 | E16: =E12*E13*E15 -> 155.90148 | F16: =F12*F13*F15 -> 136.24086 | G16: =G12*G13*G15 -> 120.88047 | H16: =H12*H13*H15 -> 108.86218 | I16: =I12*I13*I15 -> 99.484437 | J16: =J12*J13*J15 -> 92.231641 | ... L16: =L12*L13*L15 -> 82.689109
A19: PV of forecast free cash flow | B19: =SUM(C16:L16) -> 1169.6229
A20: Terminal free cash flow (year 11) | B20: =L10*(1+Assumptions!$E$11)-L7*Assumptions!$E$11*Assumptions!$E$15 -> 191.89376
A21: Terminal value | B21: =B20/(Assumptions!$E$10-Assumptions!$E$11) -> 2741.3394
A22: PV of terminal value | B22: =B21/(1+Assumptions!$E$10)^(L14+0.5) -> 1157.0898
A23: Enterprise value | B23: =B19+B22 -> 2326.7128
A24: Cash & investments | B24: =Main!C7 -> 2229.082
A25: Debt | B25: =Main!C8 -> 590.97
A26: Equity value | B26: =B23+B24-B25 -> 3964.8248
A27: Shares (mm) | B27: =Main!C4 -> 83.460802
A28: NPV / share | B28: =B26/B27 -> 47.505232
A29: Price | B29: =Main!C3 -> 62.92
A30: Upside | B30: =B28/B29-1 -> -0.24498995
A31: Terminal value, % of EV | B31: =IFERROR(B22/B23,0) -> 0.49730669
