Workbook

Sheet Main
B2: Supernus Pharmaceuticals, Inc.
B3: Price | C3: =INDEX([1]Pharma!$F$1:$F$1000,MATCH("SUPN",[1]Pharma!$B$1:$B$1000,0)) -> 41.23
B4: Shares | C4: 58.127013
B5: Market Cap. | C5: =C3*C4 -> 2396.5767
B7: Cash | C7: =179.953+192.114 -> 372.067
B8: Debt | C8: 0
B9: Enterprise V. | C9: =C5-C7+C8 -> 2024.5097
B11: NPV / Share | C11: =NPV!B28 -> 22.845624
B12: Upside | C12: =IFERROR(C11/C3-1,"") -> -0.44589804
B13: Cash / Share | C13: =IFERROR((C7-C8)/C4,"") -> 6.400931
B14: Scenario | C14: =Assumptions!C4 -> Base
B15: Model | C15: DCF

Sheet Yearly Model
B1: 2010 | C1: 2011 | D1: 2012 | E1: 2013 | F1: 2014 | G1: 2015 | H1: 2016 | I1: 2017 | J1: 2018 | K1: 2019 | L1: 2020 | M1: 2021 | N1: 2022 | O1: 2023 | P1: 2024 | Q1: 2025 | R1: 2026 | S1: 2027 | T1: 2028 | U1: 2029 | V1: 2030 | W1: 2031 | X1: 2032 | Y1: 2033 | Z1: 2034 | AA1: 2035
A2: Revenue | B2: 0.106 | C2: 0.803 | D2: 1.48 | E2: 12.019 | F2: 92.678 | G2: 147.465 | H2: 215.003 | I2: 302.238 | J2: 408.897 | K2: 392.755 | L2: 520.397 | M2: 579.775 | N2: 667.238 | O2: 607.521 | P2: 661.817 | Q2: 718.952 | R2: =Q2*(1+NPV!C5) -> 783.22631 | S2: =R2*(1+NPV!D5) -> 847.64232 | T2: =S2*(1+NPV!E5) -> 911.29084 | U2: =T2*(1+NPV!F5) -> 973.19787 | V2: =U2*(1+NPV!G5) -> 1032.3467 | W2: =V2*(1+NPV!H5) -> 1087.7034 | X2: =W2*(1+NPV!I5) -> 1138.2453 | Y2: =X2*(1+NPV!J5) -> 1182.991 | ... AA2: =Z2*(1+NPV!L5) -> 1251.5565
A3: Cost of Sales | B3: 0 | C3: 0 | D3: 0 | E3: 1.104 | F3: 5.758 | G3: 8.423 | H3: 11.986 | I3: 15.215 | J3: 15.356 | K3: 16.66 | L3: 52.459 | M3: 75.061 | N3: 87.221 | O3: 83.779 | P3: 77.906 | Q3: 74.562 | R3: =R2*(1-Assumptions!$B$19) -> 81.220568 | S3: =S2*(1-Assumptions!$B$19) -> 87.900509 | T3: =T2*(1-Assumptions!$B$19) -> 94.50086 | U3: =U2*(1-Assumptions!$B$19) -> 100.92062 | V3: =V2*(1-Assumptions!$B$19) -> 107.05435 | W3: =W2*(1-Assumptions!$B$19) -> 112.79484 | X3: =X2*(1-Assumptions!$B$19) -> 118.03604 | Y3: =Y2*(1-Assumptions!$B$19) -> 122.67617 | ... AA3: =AA2*(1-Assumptions!$B$19) -> 129.78641
A4: Gross Margin | B4: =B2-B3 -> 0.106 | C4: =C2-C3 -> 0.803 | D4: =D2-D3 -> 1.48 | E4: =E2-E3 -> 10.915 | F4: =F2-F3 -> 86.92 | G4: =G2-G3 -> 139.042 | H4: =H2-H3 -> 203.017 | I4: =I2-I3 -> 287.023 | ... AA4: =AA2-AA3 -> 1121.7701
A5: Research & Dev. | B5: 35.149 | C5: 30.627 | D5: 23.517 | E5: 17.245 | F5: 19.586 | G5: 29.135 | H5: 42.791 | I5: 49.577 | J5: 89.209 | K5: 69.099 | L5: 75.961 | M5: 90.467 | N5: 74.552 | O5: 91.593 | P5: 108.796 | Q5: 106.235 | R5: =R7*Assumptions!$B$20 -> 119.80136 | S5: =S7*Assumptions!$B$20 -> 125.10488 | T5: =T7*Assumptions!$B$20 -> 129.60778 | U5: =U7*Assumptions!$B$20 -> 133.1891 | V5: =V7*Assumptions!$B$20 -> 135.74322 | W5: =W7*Assumptions!$B$20 -> 137.18413 | X5: =X7*Assumptions!$B$20 -> 137.44942 | Y5: =Y7*Assumptions!$B$20 -> 136.50334 | ... AA5: =AA7*Assumptions!$B$20 -> 130.98026
A6: SG&A & Other | B6: 5.08 | C6: 7.928 | D6: 20.132 | E6: 55.59 | F6: 72.612 | G6: 89.063 | H6: 106.01 | I6: 137.905 | J6: 159.888 | K6: 158.425 | L6: 218.279 | M6: 328.218 | N6: 459.341 | O6: 437.418 | P6: 393.449 | Q6: 600.438 | R6: =R7-R5 -> 677.28022 | S6: =S7-S5 -> 707.26293 | T6: =T7-T5 -> 732.71941 | U6: =U7-U5 -> 752.96595 | V6: =V7-V5 -> 767.40527 | W6: =W7-W5 -> 775.55129 | X6: =X7-X5 -> 777.05104 | Y6: =Y7-Y5 -> 771.70253 | ... AA6: =AA7-AA5 -> 740.47856
A7: Operating Expense | B7: =SUM(B5:B6) -> 40.229 | C7: =SUM(C5:C6) -> 38.555 | D7: =SUM(D5:D6) -> 43.649 | E7: =SUM(E5:E6) -> 72.835 | F7: =SUM(F5:F6) -> 92.198 | G7: =SUM(G5:G6) -> 118.198 | H7: =SUM(H5:H6) -> 148.801 | I7: =SUM(I5:I6) -> 187.482 | ... Q7: =SUM(Q5:Q6) -> 706.673 | R7: =R4-R2*NPV!C6 -> 797.08158 | S7: =S4-S2*NPV!D6 -> 832.36781 | T7: =T4-T2*NPV!E6 -> 862.32718 | U7: =U4-U2*NPV!F6 -> 886.15505 | V7: =V4-V2*NPV!G6 -> 903.14848 | W7: =W4-W2*NPV!H6 -> 912.73542 | X7: =X4-X2*NPV!I6 -> 914.50046 | Y7: =Y4-Y2*NPV!J6 -> 908.20588 | ... AA7: =AA4-AA2*NPV!L6 -> 871.45882
A8: Operating Income | B8: =B4-B7 -> -40.123 | C8: =C4-C7 -> -37.752 | D8: =D4-D7 -> -42.169 | E8: =E4-E7 -> -61.92 | F8: =F4-F7 -> -5.278 | G8: =G4-G7 -> 20.844 | H8: =H4-H7 -> 54.216 | I8: =I4-I7 -> 99.541 | ... AA8: =AA4-AA7 -> 250.31131
A9: Interest & Other | B9: 1.261 | C9: 75.322 | D9: -4.115 | E9: -30.353 | F9: -5.017 | G9: -6.234 | H9: -3.847 | I9: 1.077 | J9: -4.268 | K9: -1.084 | L9: -5.05 | M9: -12.878 | N9: 14.608 | O9: 8.022 | P9: 16.239 | Q9: 13.203 | R9: 0 | S9: 0 | T9: 0 | U9: 0 | V9: 0 | W9: 0 | X9: 0 | Y9: 0 | Z9: 0 | AA9: 0
A10: Pretax | B10: =B8+B9 -> -38.862 | C10: =C8+C9 -> 37.57 | D10: =D8+D9 -> -46.284 | E10: =E8+E9 -> -92.273 | F10: =F8+F9 -> -10.295 | G10: =G8+G9 -> 14.61 | H10: =H8+H9 -> 50.369 | I10: =I8+I9 -> 100.618 | ... AA10: =AA8+AA9 -> 250.31131
A11: Taxes | B11: -0.399 | C11: -16.245 | D11: 0 | E11: 0 | F11: 0.63 | G11: 0.666 | H11: -40.852 | I11: 43.334 | J11: 29.183 | K11: 34.431 | L11: 41.698 | M11: 19.751 | N11: 0.032 | O11: 1.453 | P11: 24.005 | Q11: -10.48 | R11: =MAX(0,R10)*Assumptions!$E$14 -> 0 | S11: =MAX(0,S10)*Assumptions!$E$14 -> 0 | T11: =MAX(0,T10)*Assumptions!$E$14 -> 0 | U11: =MAX(0,U10)*Assumptions!$E$14 -> 0 | V11: =MAX(0,V10)*Assumptions!$E$14 -> 3.7644521 | W11: =MAX(0,W10)*Assumptions!$E$14 -> 10.569431 | X11: =MAX(0,X10)*Assumptions!$E$14 -> 17.970504 | Y11: =MAX(0,Y10)*Assumptions!$E$14 -> 25.858528 | ... AA11: =MAX(0,AA10)*Assumptions!$E$14 -> 42.552922
A12: Net Income | B12: -38.463 | C12: 53.815 | D12: -46.284 | E12: -92.273 | F12: -10.925 | G12: 13.944 | H12: 91.221 | I12: 57.284 | J12: 110.993 | K12: 113.056 | L12: 126.95 | M12: 53.4 | N12: 60.7 | O12: 1.3 | P12: 73.9 | Q12: -38.6 | R12: =R10-R11 -> -95.075842 | S12: =S10-S11 -> -72.625994 | T12: =T10-T11 -> -45.537203 | U12: =U10-U11 -> -13.877802 | V12: =V10-V11 -> 18.379384 | W12: =W10-W11 -> 51.603694 | X12: =X10-X11 -> 87.738341 | Y12: =Y10-Y11 -> 126.25046 | ... AA12: =AA10-AA11 -> 207.75838
A13: Earnings per Share | B13: =IFERROR(B12/B14,0) -> -2.2019121 | C13: =IFERROR(C12/C14,0) -> 3.0474546 | D13: =IFERROR(D12/D14,0) -> -2.6537469 | E13: =IFERROR(E12/E14,0) -> -2.8972934 | F13: =IFERROR(F12/F14,0) -> -0.25851258 | G13: =IFERROR(G12/G14,0) -> 0.27255668 | H13: =IFERROR(H12/H14,0) -> 1.7641223 | I13: =IFERROR(I12/I14,0) -> 1.0747266 | ... AA13: =IFERROR(AA12/AA14,0) -> 3.574214
A14: Shares | B14: 17.468 | C14: 17.659 | D14: 17.441 | E14: 31.848 | F14: 42.261 | G14: 51.16 | H14: 51.709 | I14: 53.301 | J14: 54.099 | K14: 53.817 | L14: 53.69 | M14: 54.357 | N14: 61.68 | O14: 55.507 | P14: 55.959 | Q14: 56.451 | R14: =Main!$C$4 -> 58.127013 | S14: =Main!$C$4 -> 58.127013 | T14: =Main!$C$4 -> 58.127013 | U14: =Main!$C$4 -> 58.127013 | V14: =Main!$C$4 -> 58.127013 | W14: =Main!$C$4 -> 58.127013 | X14: =Main!$C$4 -> 58.127013 | Y14: =Main!$C$4 -> 58.127013 | ... AA14: =Main!$C$4 -> 58.127013
A16: Revenue Change | C16: =IFERROR(C2/B2-1,"") -> 6.5754717 | D16: =IFERROR(D2/C2-1,"") -> 0.84308842 | E16: =IFERROR(E2/D2-1,"") -> 7.1209459 | F16: =IFERROR(F2/E2-1,"") -> 6.7109577 | G16: =IFERROR(G2/F2-1,"") -> 0.59115432 | H16: =IFERROR(H2/G2-1,"") -> 0.45799342 | I16: =IFERROR(I2/H2-1,"") -> 0.40573852 | J16: =IFERROR(J2/I2-1,"") -> 0.35289739 | ... AA16: =IFERROR(AA2/Z2-1,"") -> 0.025
A17: Gross Margin | B17: =IFERROR(B4/B2,"") -> 1 | C17: =IFERROR(C4/C2,"") -> 1 | D17: =IFERROR(D4/D2,"") -> 1 | E17: =IFERROR(E4/E2,"") -> 0.90814544 | F17: =IFERROR(F4/F2,"") -> 0.93787091 | G17: =IFERROR(G4/G2,"") -> 0.94288136 | H17: =IFERROR(H4/H2,"") -> 0.94425194 | I17: =IFERROR(I4/I2,"") -> 0.94965888 | ... AA17: =IFERROR(AA4/AA2,"") -> 0.8963
A18: Operating Margin | B18: =IFERROR(B8/B2,"") -> -378.51887 | C18: =IFERROR(C8/C2,"") -> -47.013699 | D18: =IFERROR(D8/D2,"") -> -28.492568 | E18: =IFERROR(E8/E2,"") -> -5.1518429 | F18: =IFERROR(F8/F2,"") -> -0.056949869 | G18: =IFERROR(G8/G2,"") -> 0.14134879 | H18: =IFERROR(H8/H2,"") -> 0.25216392 | I18: =IFERROR(I8/I2,"") -> 0.32934641 | ... AA18: =IFERROR(AA8/AA2,"") -> 0.2
A19: Actual / Estimate | B19: A | C19: A | D19: A | E19: A | F19: A | G19: A | H19: A | I19: A | J19: A | K19: A | L19: A | M19: A | N19: A | O19: A | P19: A | Q19: A | R19: E | S19: E | T19: E | U19: E | V19: E | W19: E | X19: E | Y19: E | Z19: E | AA19: E

Sheet Quarterly Model

Sheet Assumptions
A1: Supernus Pharmaceuticals, Inc.: basic DCF assumptions
A2: Blue = input, black = formula, green = link. $mm unless noted.
A4: Scenario (1 Bear, 2 Base, 3 Bull) | B4: 2 | C4: =CHOOSE($B$4,"Bear","Base","Bull") -> Base
A6: Discount rate override (blank = scenario)
A7: Terminal growth override (blank = scenario)
A9: Parameter | B9: Bear | C9: Base | D9: Bull | E9: Live
A10: Discount rate | B10: 0.12 | C10: 0.11 | D10: 0.1 | E10: =IF(ISNUMBER($B$6),$B$6,CHOOSE($B$4,B10,C10,D10)) -> 0.11
A11: Terminal growth | B11: 0.02 | C11: 0.025 | D11: 0.03 | E11: =IF(ISNUMBER($B$7),$B$7,CHOOSE($B$4,B11,C11,D11)) -> 0.025
A12: Revenue growth, first forecast year | B12: 0.0394 | C12: 0.0894 | D12: 0.1394 | E12: =CHOOSE($B$4,B12,C12,D12) -> 0.0894
A13: Operating margin, year 10 | B13: 0.15 | C13: 0.2 | D13: 0.25 | E13: =CHOOSE($B$4,B13,C13,D13) -> 0.2
A14: Tax rate on operating income | B14: 0.17 | C14: 0.17 | D14: 0.17 | E14: =CHOOSE($B$4,B14,C14,D14) -> 0.17
A15: Reinvestment, % of revenue increase | B15: 0.25 | C15: 0.25 | D15: 0.25 | E15: =CHOOSE($B$4,B15,C15,D15) -> 0.25
A17: Single inputs
A18: Starting operating margin (TTM) | B18: -0.1571
A19: Gross margin (forecast) | B19: 0.8963
A20: R&D share of operating expense (forecast) | B20: 0.1503
A21: Forecast years | B21: 10
A22: First forecast year, fraction after balance sheet date | B22: 0.5041
A23: Balance sheet date | B23: 46203
A24: Reporting currency per USD (USD) | B24: 1
A25: Base revenue, FY2025 | B25: ='Yearly Model'!Q2 -> 718.952
A27: Scenario summary
A28: Scenario | B28: Enterprise value | C28: Equity value | D28: NPV / share | E28: Upside
A29: Live | B29: =NPV!B23 -> 955.88087 | C29: =NPV!B26 -> 1327.9479 | D29: =NPV!B28 -> 22.845624 | E29: =NPV!B30 -> -0.44589804
A30: 1 | B30: 332.43444 | C30: 704.50144 | D30: 12.120035 | E30: -0.70603844
A31: 2 | B31: 955.88087 | C31: 1327.9479 | D31: 22.845624 | E31: -0.44589804
A32: 3 | B32: 2193.3444 | C32: 2565.4114 | D32: 44.134582 | E32: 0.070448275
A35: NPV / share: discount rate (rows) x terminal growth (columns)
A36: =NPV!B28 -> 22.845624 | B36: 0.015 | C36: 0.02 | D36: 0.025 | E36: 0.03 | F36: 0.035
A37: 0.09 | B37: 27.861524 | C37: 29.767283 | D37: 31.971601 | E37: 34.549185 | F37: 37.601913
A38: 0.1 | B38: 23.763984 | C38: 25.160759 | D38: 26.748162 | E38: 28.5671 | F38: 30.671064
A39: 0.11 | B39: 20.609409 | C39: 21.663667 | D39: 22.845624 | E39: 24.179267 | F39: 25.694984
A40: 0.12 | B40: 18.122723 | C40: 18.93716 | D40: 19.840437 | E40: 20.847398 | F40: 21.976381
A41: 0.13 | B41: 16.125007 | C41: 16.766113 | D41: 17.470945 | E41: 18.249094 | F41: 19.112171

Sheet NPV
A1: Supernus Pharmaceuticals, Inc.: free-cash-flow DCF ($mm)
A3: Fiscal year | B3: ='Yearly Model'!Q1 -> 2025 | C3: ='Yearly Model'!R1 -> 2026 | D3: ='Yearly Model'!S1 -> 2027 | E3: ='Yearly Model'!T1 -> 2028 | F3: ='Yearly Model'!U1 -> 2029 | G3: ='Yearly Model'!V1 -> 2030 | H3: ='Yearly Model'!W1 -> 2031 | I3: ='Yearly Model'!X1 -> 2032 | ... L3: ='Yearly Model'!AA1 -> 2035
A4: Period | B4: Actual | C4: 1 | D4: 2 | E4: 3 | F4: 4 | G4: 5 | H4: 6 | I4: 7 | J4: 8 | K4: 9 | L4: 10
A5: Revenue growth | C5: =Assumptions!$E$12+(Assumptions!$E$11-Assumptions!$E$12)*(C4-1)/(Assumptions!$B$21-1) -> 0.0894 | D5: =Assumptions!$E$12+(Assumptions!$E$11-Assumptions!$E$12)*(D4-1)/(Assumptions!$B$21-1) -> 0.082244444 | E5: =Assumptions!$E$12+(Assumptions!$E$11-Assumptions!$E$12)*(E4-1)/(Assumptions!$B$21-1) -> 0.075088889 | F5: =Assumptions!$E$12+(Assumptions!$E$11-Assumptions!$E$12)*(F4-1)/(Assumptions!$B$21-1) -> 0.067933333 | G5: =Assumptions!$E$12+(Assumptions!$E$11-Assumptions!$E$12)*(G4-1)/(Assumptions!$B$21-1) -> 0.060777778 | H5: =Assumptions!$E$12+(Assumptions!$E$11-Assumptions!$E$12)*(H4-1)/(Assumptions!$B$21-1) -> 0.053622222 | I5: =Assumptions!$E$12+(Assumptions!$E$11-Assumptions!$E$12)*(I4-1)/(Assumptions!$B$21-1) -> 0.046466667 | J5: =Assumptions!$E$12+(Assumptions!$E$11-Assumptions!$E$12)*(J4-1)/(Assumptions!$B$21-1) -> 0.039311111 | ... L5: =Assumptions!$E$12+(Assumptions!$E$11-Assumptions!$E$12)*(L4-1)/(Assumptions!$B$21-1) -> 0.025
A6: Operating margin | B6: =IFERROR(B8/B7,0) -> -0.086630262 | C6: =Assumptions!$B$18+(Assumptions!$E$13-Assumptions!$B$18)*C4/Assumptions!$B$21 -> -0.12139 | D6: =Assumptions!$B$18+(Assumptions!$E$13-Assumptions!$B$18)*D4/Assumptions!$B$21 -> -0.08568 | E6: =Assumptions!$B$18+(Assumptions!$E$13-Assumptions!$B$18)*E4/Assumptions!$B$21 -> -0.04997 | F6: =Assumptions!$B$18+(Assumptions!$E$13-Assumptions!$B$18)*F4/Assumptions!$B$21 -> -0.01426 | G6: =Assumptions!$B$18+(Assumptions!$E$13-Assumptions!$B$18)*G4/Assumptions!$B$21 -> 0.02145 | H6: =Assumptions!$B$18+(Assumptions!$E$13-Assumptions!$B$18)*H4/Assumptions!$B$21 -> 0.05716 | I6: =Assumptions!$B$18+(Assumptions!$E$13-Assumptions!$B$18)*I4/Assumptions!$B$21 -> 0.09287 | J6: =Assumptions!$B$18+(Assumptions!$E$13-Assumptions!$B$18)*J4/Assumptions!$B$21 -> 0.12858 | ... L6: =Assumptions!$B$18+(Assumptions!$E$13-Assumptions!$B$18)*L4/Assumptions!$B$21 -> 0.2
A7: Revenue | B7: ='Yearly Model'!Q2 -> 718.952 | C7: ='Yearly Model'!R2 -> 783.22631 | D7: ='Yearly Model'!S2 -> 847.64232 | E7: ='Yearly Model'!T2 -> 911.29084 | F7: ='Yearly Model'!U2 -> 973.19787 | G7: ='Yearly Model'!V2 -> 1032.3467 | H7: ='Yearly Model'!W2 -> 1087.7034 | I7: ='Yearly Model'!X2 -> 1138.2453 | ... L7: ='Yearly Model'!AA2 -> 1251.5565
A8: Operating income | B8: ='Yearly Model'!Q8 -> -62.283 | C8: ='Yearly Model'!R8 -> -95.075842 | D8: ='Yearly Model'!S8 -> -72.625994 | E8: ='Yearly Model'!T8 -> -45.537203 | F8: ='Yearly Model'!U8 -> -13.877802 | G8: ='Yearly Model'!V8 -> 22.143836 | H8: ='Yearly Model'!W8 -> 62.173126 | I8: ='Yearly Model'!X8 -> 105.70885 | ... L8: ='Yearly Model'!AA8 -> 250.31131
A9: Tax on operating income | C9: =MAX(0,C8)*Assumptions!$E$14 -> 0 | D9: =MAX(0,D8)*Assumptions!$E$14 -> 0 | E9: =MAX(0,E8)*Assumptions!$E$14 -> 0 | F9: =MAX(0,F8)*Assumptions!$E$14 -> 0 | G9: =MAX(0,G8)*Assumptions!$E$14 -> 3.7644521 | H9: =MAX(0,H8)*Assumptions!$E$14 -> 10.569431 | I9: =MAX(0,I8)*Assumptions!$E$14 -> 17.970504 | J9: =MAX(0,J8)*Assumptions!$E$14 -> 25.858528 | ... L9: =MAX(0,L8)*Assumptions!$E$14 -> 42.552922
A10: NOPAT | C10: =C8-C9 -> -95.075842 | D10: =D8-D9 -> -72.625994 | E10: =E8-E9 -> -45.537203 | F10: =F8-F9 -> -13.877802 | G10: =G8-G9 -> 18.379384 | H10: =H8-H9 -> 51.603694 | I10: =I8-I9 -> 87.738341 | J10: =J8-J9 -> 126.25046 | ... L10: =L8-L9 -> 207.75838
A11: Reinvestment | C11: =(C7-B7)*Assumptions!$E$15 -> 16.068577 | D11: =(D7-C7)*Assumptions!$E$15 -> 16.104003 | E11: =(E7-D7)*Assumptions!$E$15 -> 15.91213 | F11: =(F7-E7)*Assumptions!$E$15 -> 15.476756 | G11: =(G7-F7)*Assumptions!$E$15 -> 14.787201 | H11: =(H7-G7)*Assumptions!$E$15 -> 13.839181 | I11: =(I7-H7)*Assumptions!$E$15 -> 12.635488 | J11: =(J7-I7)*Assumptions!$E$15 -> 11.186422 | ... L11: =(L7-K7)*Assumptions!$E$15 -> 7.6314423
A12: Free cash flow | C12: =C10-C11 -> -111.14442 | D12: =D10-D11 -> -88.729997 | E12: =E10-E11 -> -61.449333 | F12: =F10-F11 -> -29.354558 | G12: =G10-G11 -> 3.592183 | H12: =H10-H11 -> 37.764514 | I12: =I10-I11 -> 75.102854 | J12: =J10-J11 -> 115.06404 | ... L12: =L10-L11 -> 200.12694
A13: Year fraction | C13: =Assumptions!$B$22 -> 0.5041 | D13: 1 | E13: 1 | F13: 1 | G13: 1 | H13: 1 | I13: 1 | J13: 1 | K13: 1 | L13: 1
A14: Discount time (mid-period) | C14: =C13/2 -> 0.25205 | D14: =C14+C13/2+D13/2 -> 1.0041 | E14: =D14+D13/2+E13/2 -> 2.0041 | F14: =E14+E13/2+F13/2 -> 3.0041 | G14: =F14+F13/2+G13/2 -> 4.0041 | H14: =G14+G13/2+H13/2 -> 5.0041 | I14: =H14+H13/2+I13/2 -> 6.0041 | J14: =I14+I13/2+J13/2 -> 7.0041 | K14: =J14+J13/2+K13/2 -> 8.0041 | L14: =K14+K13/2+L13/2 -> 9.0041
A15: Discount factor | C15: =1/(1+Assumptions!$E$10)^C14 -> 0.97403899 | D15: =1/(1+Assumptions!$E$10)^D14 -> 0.90051551 | E15: =1/(1+Assumptions!$E$10)^E14 -> 0.81127523 | F15: =1/(1+Assumptions!$E$10)^F14 -> 0.73087859 | G15: =1/(1+Assumptions!$E$10)^G14 -> 0.65844918 | H15: =1/(1+Assumptions!$E$10)^H14 -> 0.59319746 | I15: =1/(1+Assumptions!$E$10)^I14 -> 0.53441213 | J15: =1/(1+Assumptions!$E$10)^J14 -> 0.48145236 | ... L15: =1/(1+Assumptions!$E$10)^L14 -> 0.39075754
A16: PV of free cash flow | C16: =C12*C13*C15 -> -54.573361 | D16: =D12*D13*D15 -> -79.902739 | E16: =E12*E13*E15 -> -49.852322 | F16: =F12*F13*F15 -> -21.454618 | G16: =G12*G13*G15 -> 2.36527 | H16: =H12*H13*H15 -> 22.401814 | I16: =I12*I13*I15 -> 40.135876 | J16: =J12*J13*J15 -> 55.397853 | ... L16: =L12*L13*L15 -> 78.201112
A19: PV of forecast free cash flow | B19: =SUM(C16:L16) -> 60.812157
A20: Terminal free cash flow (year 11) | B20: =L10*(1+Assumptions!$E$11)-L7*Assumptions!$E$11*Assumptions!$E$15 -> 205.13012
A21: Terminal value | B21: =B20/(Assumptions!$E$10-Assumptions!$E$11) -> 2413.2955
A22: PV of terminal value | B22: =B21/(1+Assumptions!$E$10)^(L14+0.5) -> 895.06871
A23: Enterprise value | B23: =B19+B22 -> 955.88087
A24: Cash & investments | B24: =Main!C7 -> 372.067
A25: Debt | B25: =Main!C8 -> 0
A26: Equity value | B26: =B23+B24-B25 -> 1327.9479
A27: Shares (mm) | B27: =Main!C4 -> 58.127013
A28: NPV / share | B28: =B26/B27 -> 22.845624
A29: Price | B29: =Main!C3 -> 41.23
A30: Upside | B30: =B28/B29-1 -> -0.44589804
A31: Terminal value, % of EV | B31: =IFERROR(B22/B23,0) -> 0.93638103
