Workbook

Sheet Main
B2: TG Therapeutics, Inc.
B3: Price | C3: =INDEX([1]Pharma!$F$1:$F$1000,MATCH("TGTX",[1]Pharma!$B$1:$B$1000,0)) -> 54.53
B4: Shares | C4: 153.06905
B5: Market Cap. | C5: =C3*C4 -> 8346.8555
B7: Cash | C7: 612.3
B8: Debt | C8: 745.387
B9: Enterprise V. | C9: =C5-C7+C8 -> 8479.9425
B11: NPV / Share | C11: =NPV!B28 -> 31.001645
B12: Upside | C12: =IFERROR(C11/C3-1,"") -> -0.43147543
B13: Cash / Share | C13: =IFERROR((C7-C8)/C4,"") -> -0.86945726
B14: Scenario | C14: =Assumptions!C4 -> Base
B15: Model | C15: DCF

Sheet Yearly Model
B1: 2001 | C1: 2002 | D1: 2003 | E1: 2004 | F1: 2005 | G1: 2006 | H1: 2007 | I1: 2008 | J1: 2009 | K1: 2010 | L1: 2011 | M1: 2012 | N1: 2013 | O1: 2014 | P1: 2015 | Q1: 2016 | R1: 2017 | S1: 2018 | T1: 2019 | U1: 2020 | V1: 2021 | W1: 2022 | X1: 2023 | Y1: 2024 | Z1: 2025 | AA1: 2026 | AB1: 2027 | AC1: 2028 | AD1: 2029 | AE1: 2030 | AF1: 2031 | AG1: 2032 | AH1: 2033 | AI1: 2034 | AJ1: 2035
A2: Revenue | B2: 0 | C2: 0 | D2: 0 | E2: 0 | F2: 0 | G2: 0 | H2: 0 | I2: 0 | J2: 0 | K2: 0 | L2: 0 | M2: 0 | N2: 0 | O2: 0 | P2: 0 | Q2: 0.152 | R2: 0.152 | S2: 0.152 | T2: 0.152 | U2: 0.152 | V2: 6.689 | W2: 2.785 | X2: 233.662 | Y2: 329.004 | Z2: 616.287 | AA2: =Z2*(1+NPV!C5) -> 831.98745 | AB2: =AA2*(1+NPV!D5) -> 1093.1391 | AC2: =AB2*(1+NPV!E5) -> 1396.7888 | AD2: =AC2*(1+NPV!F5) -> 1734.3461 | AE2: =AD2*(1+NPV!G5) -> 2090.8506 | AF2: =AE2*(1+NPV!H5) -> 2445.1336 | AG2: =AF2*(1+NPV!I5) -> 2771.1514 | AH2: =AG2*(1+NPV!J5) -> 3040.5689 | ... AJ2: =AI2*(1+NPV!L5) -> 3307.041
A3: Cost of Sales | B3: 0 | C3: 0 | D3: 0 | E3: 0 | F3: 0 | G3: 0 | H3: 0 | I3: 0 | J3: 0 | K3: 0 | L3: 0 | M3: 0 | N3: 0 | O3: 0 | P3: 0 | Q3: 0 | R3: 0 | S3: 0 | T3: 0 | U3: 0 | V3: 0.79 | W3: 0.265 | X3: 14.131 | Y3: 38.486 | Z3: 100.714 | AA3: =AA2*(1-Assumptions!$B$19) -> 135.94675 | AB3: =AB2*(1-Assumptions!$B$19) -> 178.61892 | AC3: =AC2*(1-Assumptions!$B$19) -> 228.23529 | AD3: =AD2*(1-Assumptions!$B$19) -> 283.39215 | AE3: =AE2*(1-Assumptions!$B$19) -> 341.64498 | AF3: =AF2*(1-Assumptions!$B$19) -> 399.53483 | AG3: =AG2*(1-Assumptions!$B$19) -> 452.80614 | AH3: =AH2*(1-Assumptions!$B$19) -> 496.82896 | ... AJ3: =AJ2*(1-Assumptions!$B$19) -> 540.3705
A4: Gross Margin | B4: =B2-B3 -> 0 | C4: =C2-C3 -> 0 | D4: =D2-D3 -> 0 | E4: =E2-E3 -> 0 | F4: =F2-F3 -> 0 | G4: =G2-G3 -> 0 | H4: =H2-H3 -> 0 | I4: =I2-I3 -> 0 | ... AJ4: =AJ2-AJ3 -> 2766.6705
A5: Research & Dev. | B5: 0 | C5: 0 | D5: 0 | E5: 0 | F5: 0 | G5: 0 | H5: 0 | I5: 0 | J5: 0 | K5: 0 | L5: 0.327 | M5: 21.028 | N5: 13.663 | O5: 40.086 | P5: 47.707 | Q5: 69.232 | R5: 102.533 | S5: 159.391 | T5: 154.18 | U5: 165.896 | V5: 222.579 | W5: 125.352 | X5: 76.192 | Y5: 94.291 | Z5: 160.215 | AA5: =AA7*Assumptions!$B$20 -> 225.38272 | AB5: =AB7*Assumptions!$B$20 -> 294.81053 | AC5: =AC7*Assumptions!$B$20 -> 375.01911 | AD5: =AD7*Assumptions!$B$20 -> 463.55871 | AE5: =AE7*Assumptions!$B$20 -> 556.32615 | AF5: =AF7*Assumptions!$B$20 -> 647.64596 | AG5: =AG7*Assumptions!$B$20 -> 730.65931 | AH5: =AH7*Assumptions!$B$20 -> 798.03152 | ... AJ5: =AJ7*Assumptions!$B$20 -> 859.99965
A6: SG&A & Other | B6: 0.057 | C6: 1.037 | D6: 5.961 | E6: 5.896 | F6: 19.141 | G6: 9.695 | H6: 12.032 | I6: 4.269 | J6: 2.793 | K6: -0.624 | L6: 0.555 | M6: 5.867 | N6: 9.303 | O6: 15.635 | P6: 15.473 | Q6: 9.889 | R6: 16.331 | S6: 15.161 | T6: 15.027 | U6: 107.85 | V6: 128.09 | W6: 95.484 | X6: 122.706 | Y6: 154.298 | Z6: 232.034 | AA6: =AA7-AA5 -> 326.34976 | AB6: =AB7-AB5 -> 426.87988 | AC6: =AC7-AC5 -> 543.02033 | AD6: =AD7-AD5 -> 671.22394 | AE6: =AE7-AE5 -> 805.54937 | AF6: =AF7-AF5 -> 937.77866 | AG6: =AG7-AG5 -> 1057.9804 | AH6: =AH7-AH5 -> 1155.534 | ... AJ6: =AJ7-AJ5 -> 1245.2626
A7: Operating Expense | B7: =SUM(B5:B6) -> 0.057 | C7: =SUM(C5:C6) -> 1.037 | D7: =SUM(D5:D6) -> 5.961 | E7: =SUM(E5:E6) -> 5.896 | F7: =SUM(F5:F6) -> 19.141 | G7: =SUM(G5:G6) -> 9.695 | H7: =SUM(H5:H6) -> 12.032 | I7: =SUM(I5:I6) -> 4.269 | ... Z7: =SUM(Z5:Z6) -> 392.249 | AA7: =AA4-AA2*NPV!C6 -> 551.73248 | AB7: =AB4-AB2*NPV!D6 -> 721.69041 | AC7: =AC4-AC2*NPV!E6 -> 918.03944 | AD7: =AD4-AD2*NPV!F6 -> 1134.7827 | AE7: =AE4-AE2*NPV!G6 -> 1361.8755 | AF7: =AF4-AF2*NPV!H6 -> 1585.4246 | AG7: =AG4-AG2*NPV!I6 -> 1788.6397 | AH7: =AH4-AH2*NPV!J6 -> 1953.5655 | ... AJ7: =AJ4-AJ2*NPV!L6 -> 2105.2623
A8: Operating Income | B8: =B4-B7 -> -0.057 | C8: =C4-C7 -> -1.037 | D8: =D4-D7 -> -5.961 | E8: =E4-E7 -> -5.896 | F8: =F4-F7 -> -19.141 | G8: =G4-G7 -> -9.695 | H8: =H4-H7 -> -12.032 | I8: =I4-I7 -> -4.269 | ... AJ8: =AJ4-AJ7 -> 661.4082
A9: Interest & Other | B9: 0 | C9: 0 | D9: 0 | E9: 0 | F9: 0 | G9: 0 | H9: 0 | I9: 0 | J9: 0 | K9: 0 | L9: 0.029 | M9: 9.122 | N9: 2.488 | O9: -0.06 | P9: 0.231 | Q9: 0.716 | R9: 0.236 | S9: 0.918 | T9: -3.816 | U9: -5.787 | V9: -3.33 | W9: 20.016 | X9: -7.543 | Y9: -16.318 | Z9: -15.913 | AA9: 0 | AB9: 0 | AC9: 0 | AD9: 0 | AE9: 0 | AF9: 0 | AG9: 0 | AH9: 0 | AI9: 0 | AJ9: 0
A10: Pretax | B10: =B8+B9 -> -0.057 | C10: =C8+C9 -> -1.037 | D10: =D8+D9 -> -5.961 | E10: =E8+E9 -> -5.896 | F10: =F8+F9 -> -19.141 | G10: =G8+G9 -> -9.695 | H10: =H8+H9 -> -12.032 | I10: =I8+I9 -> -4.269 | ... AJ10: =AJ8+AJ9 -> 661.4082
A11: Taxes | B11: 0 | C11: 0 | D11: 0 | E11: 0 | F11: 0 | G11: 0 | H11: 0 | I11: 0 | J11: 0 | K11: 0 | L11: 0 | M11: 0.3 | N11: 0 | O11: 0 | P11: 0 | Q11: 0 | R11: 0 | S11: 0 | T11: 0 | U11: 0 | V11: 0 | W11: 0 | X11: 0.39 | Y11: 2.211 | Z11: -339.789 | AA11: =MAX(0,AA10)*Assumptions!$E$14 -> 24.532398 | AB11: =MAX(0,AB10)*Assumptions!$E$14 -> 32.781054 | AC11: =MAX(0,AC10)*Assumptions!$E$14 -> 42.587392 | AD11: =MAX(0,AD10)*Assumptions!$E$14 -> 53.74912 | AE11: =MAX(0,AE10)*Assumptions!$E$14 -> 65.846112 | AF11: =MAX(0,AF10)*Assumptions!$E$14 -> 78.229604 | AG11: =MAX(0,AG10)*Assumptions!$E$14 -> 90.04995 | AH11: =MAX(0,AH10)*Assumptions!$E$14 -> 100.32965 | ... AJ11: =MAX(0,AJ10)*Assumptions!$E$14 -> 112.43939
A12: Net Income | B12: -0.057 | C12: -1.037 | D12: -5.961 | E12: -5.896 | F12: -19.141 | G12: -9.695 | H12: -12.032 | I12: -4.269 | J12: -2.793 | K12: 0.624 | L12: -0.853 | M12: -18.073 | N12: -20.478 | O12: -55.781 | P12: -62.949 | Q12: -78.253 | R12: -118.476 | S12: -173.482 | T12: -172.871 | U12: -279.381 | V12: -348.1 | W12: -198.3 | X12: 12.7 | Y12: 23.4 | Z12: 447.2 | AA12: =AA10-AA11 -> 119.77583 | AB12: =AB10-AB11 -> 160.04868 | AC12: =AC10-AC11 -> 207.92668 | AD12: =AD10-AD11 -> 262.42217 | AE12: =AE10-AE11 -> 321.48396 | AF12: =AF10-AF11 -> 381.94454 | AG12: =AG10-AG11 -> 439.65564 | AH12: =AH10-AH11 -> 489.84477 | ... AJ12: =AJ10-AJ11 -> 548.9688
A13: Earnings per Share | B13: =IFERROR(B12/B14,0) -> 0 | C13: =IFERROR(C12/C14,0) -> 0 | D13: =IFERROR(D12/D14,0) -> 0 | E13: =IFERROR(E12/E14,0) -> 0 | F13: =IFERROR(F12/F14,0) -> 0 | G13: =IFERROR(G12/G14,0) -> 0 | H13: =IFERROR(H12/H14,0) -> 0 | I13: =IFERROR(I12/I14,0) -> 0 | ... AJ13: =IFERROR(AJ12/AJ14,0) -> 3.5864127
A14: Shares | L14: 1.926 | M14: 13.114 | N14: 25.414 | O14: 34.069 | P14: 45.646 | Q14: 49.041 | R14: 62.07 | S14: 75.467 | T14: 88.369 | U14: 115.334 | V14: 132.223 | W14: 135.411 | X14: 148.508 | Y14: 160.336 | Z14: 161.413 | AA14: =Main!$C$4 -> 153.06905 | AB14: =Main!$C$4 -> 153.06905 | AC14: =Main!$C$4 -> 153.06905 | AD14: =Main!$C$4 -> 153.06905 | AE14: =Main!$C$4 -> 153.06905 | AF14: =Main!$C$4 -> 153.06905 | AG14: =Main!$C$4 -> 153.06905 | AH14: =Main!$C$4 -> 153.06905 | ... AJ14: =Main!$C$4 -> 153.06905
A16: Revenue Change | C16: =IFERROR(C2/B2-1,"") | D16: =IFERROR(D2/C2-1,"") | E16: =IFERROR(E2/D2-1,"") | F16: =IFERROR(F2/E2-1,"") | G16: =IFERROR(G2/F2-1,"") | H16: =IFERROR(H2/G2-1,"") | I16: =IFERROR(I2/H2-1,"") | J16: =IFERROR(J2/I2-1,"") | ... AJ16: =IFERROR(AJ2/AI2-1,"") -> 0.025
A17: Gross Margin | B17: =IFERROR(B4/B2,"") | C17: =IFERROR(C4/C2,"") | D17: =IFERROR(D4/D2,"") | E17: =IFERROR(E4/E2,"") | F17: =IFERROR(F4/F2,"") | G17: =IFERROR(G4/G2,"") | H17: =IFERROR(H4/H2,"") | I17: =IFERROR(I4/I2,"") | ... AJ17: =IFERROR(AJ4/AJ2,"") -> 0.8366
A18: Operating Margin | B18: =IFERROR(B8/B2,"") | C18: =IFERROR(C8/C2,"") | D18: =IFERROR(D8/D2,"") | E18: =IFERROR(E8/E2,"") | F18: =IFERROR(F8/F2,"") | G18: =IFERROR(G8/G2,"") | H18: =IFERROR(H8/H2,"") | I18: =IFERROR(I8/I2,"") | ... AJ18: =IFERROR(AJ8/AJ2,"") -> 0.2
A19: Actual / Estimate | B19: A | C19: A | D19: A | E19: A | F19: A | G19: A | H19: A | I19: A | J19: A | K19: A | L19: A | M19: A | N19: A | O19: A | P19: A | Q19: A | R19: A | S19: A | T19: A | U19: A | V19: A | W19: A | X19: A | Y19: A | Z19: A | AA19: E | AB19: E | AC19: E | AD19: E | AE19: E | AF19: E | AG19: E | AH19: E | AI19: E | AJ19: E

Sheet Quarterly Model

Sheet Assumptions
A1: TG Therapeutics, Inc.: basic DCF assumptions
A2: Blue = input, black = formula, green = link. $mm unless noted.
A4: Scenario (1 Bear, 2 Base, 3 Bull) | B4: 2 | C4: =CHOOSE($B$4,"Bear","Base","Bull") -> Base
A6: Discount rate override (blank = scenario)
A7: Terminal growth override (blank = scenario)
A9: Parameter | B9: Bear | C9: Base | D9: Bull | E9: Live
A10: Discount rate | B10: 0.105 | C10: 0.095 | D10: 0.085 | E10: =IF(ISNUMBER($B$6),$B$6,CHOOSE($B$4,B10,C10,D10)) -> 0.095
A11: Terminal growth | B11: 0.02 | C11: 0.025 | D11: 0.03 | E11: =IF(ISNUMBER($B$7),$B$7,CHOOSE($B$4,B11,C11,D11)) -> 0.025
A12: Revenue growth, first forecast year | B12: 0.3 | C12: 0.35 | D12: 0.4 | E12: =CHOOSE($B$4,B12,C12,D12) -> 0.35
A13: Operating margin, year 10 | B13: 0.15 | C13: 0.2 | D13: 0.25 | E13: =CHOOSE($B$4,B13,C13,D13) -> 0.2
A14: Tax rate on operating income | B14: 0.17 | C14: 0.17 | D14: 0.17 | E14: =CHOOSE($B$4,B14,C14,D14) -> 0.17
A15: Reinvestment, % of revenue increase | B15: 0.25 | C15: 0.25 | D15: 0.25 | E15: =CHOOSE($B$4,B15,C15,D15) -> 0.25
A17: Single inputs
A18: Starting operating margin (TTM) | B18: 0.1705
A19: Gross margin (forecast) | B19: 0.8366
A20: R&D share of operating expense (forecast) | B20: 0.4085
A21: Forecast years | B21: 10
A22: First forecast year, fraction after balance sheet date | B22: 0.5041
A23: Balance sheet date | B23: 46203
A24: Reporting currency per USD (USD) | B24: 1
A25: Base revenue, FY2025 | B25: ='Yearly Model'!Z2 -> 616.287
A27: Scenario summary
A28: Scenario | B28: Enterprise value | C28: Equity value | D28: NPV / share | E28: Upside
A29: Live | B29: =NPV!B23 -> 4878.4794 | C29: =NPV!B26 -> 4745.3924 | D29: =NPV!B28 -> 31.001645 | E29: =NPV!B30 -> -0.43147543
A30: 1 | B30: 2533.7769 | C30: 2400.6899 | D30: 15.683705 | E30: -0.71238392
A31: 2 | B31: 4878.4794 | C31: 4745.3924 | D31: 31.001645 | E31: -0.43147543
A32: 3 | B32: 9498.9802 | C32: 9365.8932 | D32: 61.187373 | E32: 0.12208643
A35: NPV / share: discount rate (rows) x terminal growth (columns)
A36: =NPV!B28 -> 31.001645 | B36: 0.015 | C36: 0.02 | D36: 0.025 | E36: 0.03 | F36: 0.035
A37: 0.075 | B37: 39.196762 | C37: 42.486218 | D37: 46.431228 | E37: 51.250291 | F37: 57.27115
A38: 0.085 | B38: 32.469281 | C38: 34.741916 | D38: 37.391455 | E38: 40.520674 | F38: 44.273456
A39: 0.095 | B39: 27.482565 | C39: 29.125519 | D39: 31.001645 | E39: 33.164737 | F39: 35.686523
A40: 0.105 | B40: 23.651884 | C40: 24.881244 | D40: 26.262987 | E40: 27.827577 | F40: 29.614183
A41: 0.115 | B41: 20.626809 | C41: 21.571969 | D41: 22.621051 | E41: 23.792384 | F41: 25.108879

Sheet NPV
A1: TG Therapeutics, Inc.: free-cash-flow DCF ($mm)
A3: Fiscal year | B3: ='Yearly Model'!Z1 -> 2025 | C3: ='Yearly Model'!AA1 -> 2026 | D3: ='Yearly Model'!AB1 -> 2027 | E3: ='Yearly Model'!AC1 -> 2028 | F3: ='Yearly Model'!AD1 -> 2029 | G3: ='Yearly Model'!AE1 -> 2030 | H3: ='Yearly Model'!AF1 -> 2031 | I3: ='Yearly Model'!AG1 -> 2032 | ... L3: ='Yearly Model'!AJ1 -> 2035
A4: Period | B4: Actual | C4: 1 | D4: 2 | E4: 3 | F4: 4 | G4: 5 | H4: 6 | I4: 7 | J4: 8 | K4: 9 | L4: 10
A5: Revenue growth | C5: =Assumptions!$E$12+(Assumptions!$E$11-Assumptions!$E$12)*(C4-1)/(Assumptions!$B$21-1) -> 0.35 | D5: =Assumptions!$E$12+(Assumptions!$E$11-Assumptions!$E$12)*(D4-1)/(Assumptions!$B$21-1) -> 0.31388889 | E5: =Assumptions!$E$12+(Assumptions!$E$11-Assumptions!$E$12)*(E4-1)/(Assumptions!$B$21-1) -> 0.27777778 | F5: =Assumptions!$E$12+(Assumptions!$E$11-Assumptions!$E$12)*(F4-1)/(Assumptions!$B$21-1) -> 0.24166667 | G5: =Assumptions!$E$12+(Assumptions!$E$11-Assumptions!$E$12)*(G4-1)/(Assumptions!$B$21-1) -> 0.20555556 | H5: =Assumptions!$E$12+(Assumptions!$E$11-Assumptions!$E$12)*(H4-1)/(Assumptions!$B$21-1) -> 0.16944444 | I5: =Assumptions!$E$12+(Assumptions!$E$11-Assumptions!$E$12)*(I4-1)/(Assumptions!$B$21-1) -> 0.13333333 | J5: =Assumptions!$E$12+(Assumptions!$E$11-Assumptions!$E$12)*(J4-1)/(Assumptions!$B$21-1) -> 0.097222222 | ... L5: =Assumptions!$E$12+(Assumptions!$E$11-Assumptions!$E$12)*(L4-1)/(Assumptions!$B$21-1) -> 0.025
A6: Operating margin | B6: =IFERROR(B8/B7,0) -> 0.20010807 | C6: =Assumptions!$B$18+(Assumptions!$E$13-Assumptions!$B$18)*C4/Assumptions!$B$21 -> 0.17345 | D6: =Assumptions!$B$18+(Assumptions!$E$13-Assumptions!$B$18)*D4/Assumptions!$B$21 -> 0.1764 | E6: =Assumptions!$B$18+(Assumptions!$E$13-Assumptions!$B$18)*E4/Assumptions!$B$21 -> 0.17935 | F6: =Assumptions!$B$18+(Assumptions!$E$13-Assumptions!$B$18)*F4/Assumptions!$B$21 -> 0.1823 | G6: =Assumptions!$B$18+(Assumptions!$E$13-Assumptions!$B$18)*G4/Assumptions!$B$21 -> 0.18525 | H6: =Assumptions!$B$18+(Assumptions!$E$13-Assumptions!$B$18)*H4/Assumptions!$B$21 -> 0.1882 | I6: =Assumptions!$B$18+(Assumptions!$E$13-Assumptions!$B$18)*I4/Assumptions!$B$21 -> 0.19115 | J6: =Assumptions!$B$18+(Assumptions!$E$13-Assumptions!$B$18)*J4/Assumptions!$B$21 -> 0.1941 | ... L6: =Assumptions!$B$18+(Assumptions!$E$13-Assumptions!$B$18)*L4/Assumptions!$B$21 -> 0.2
A7: Revenue | B7: ='Yearly Model'!Z2 -> 616.287 | C7: ='Yearly Model'!AA2 -> 831.98745 | D7: ='Yearly Model'!AB2 -> 1093.1391 | E7: ='Yearly Model'!AC2 -> 1396.7888 | F7: ='Yearly Model'!AD2 -> 1734.3461 | G7: ='Yearly Model'!AE2 -> 2090.8506 | H7: ='Yearly Model'!AF2 -> 2445.1336 | I7: ='Yearly Model'!AG2 -> 2771.1514 | ... L7: ='Yearly Model'!AJ2 -> 3307.041
A8: Operating income | B8: ='Yearly Model'!Z8 -> 123.324 | C8: ='Yearly Model'!AA8 -> 144.30822 | D8: ='Yearly Model'!AB8 -> 192.82973 | E8: ='Yearly Model'!AC8 -> 250.51407 | F8: ='Yearly Model'!AD8 -> 316.17129 | G8: ='Yearly Model'!AE8 -> 387.33007 | H8: ='Yearly Model'!AF8 -> 460.17414 | I8: ='Yearly Model'!AG8 -> 529.70559 | ... L8: ='Yearly Model'!AJ8 -> 661.4082
A9: Tax on operating income | C9: =MAX(0,C8)*Assumptions!$E$14 -> 24.532398 | D9: =MAX(0,D8)*Assumptions!$E$14 -> 32.781054 | E9: =MAX(0,E8)*Assumptions!$E$14 -> 42.587392 | F9: =MAX(0,F8)*Assumptions!$E$14 -> 53.74912 | G9: =MAX(0,G8)*Assumptions!$E$14 -> 65.846112 | H9: =MAX(0,H8)*Assumptions!$E$14 -> 78.229604 | I9: =MAX(0,I8)*Assumptions!$E$14 -> 90.04995 | J9: =MAX(0,J8)*Assumptions!$E$14 -> 100.32965 | ... L9: =MAX(0,L8)*Assumptions!$E$14 -> 112.43939
A10: NOPAT | C10: =C8-C9 -> 119.77583 | D10: =D8-D9 -> 160.04868 | E10: =E8-E9 -> 207.92668 | F10: =F8-F9 -> 262.42217 | G10: =G8-G9 -> 321.48396 | H10: =H8-H9 -> 381.94454 | I10: =I8-I9 -> 439.65564 | J10: =J8-J9 -> 489.84477 | ... L10: =L8-L9 -> 548.9688
A11: Reinvestment | C11: =(C7-B7)*Assumptions!$E$15 -> 53.925113 | D11: =(D7-C7)*Assumptions!$E$15 -> 65.287904 | E11: =(E7-D7)*Assumptions!$E$15 -> 75.912435 | F11: =(F7-E7)*Assumptions!$E$15 -> 84.389324 | G11: =(G7-F7)*Assumptions!$E$15 -> 89.126119 | H11: =(H7-G7)*Assumptions!$E$15 -> 88.570754 | I11: =(I7-H7)*Assumptions!$E$15 -> 81.504453 | J11: =(J7-I7)*Assumptions!$E$15 -> 67.354374 | ... L11: =(L7-K7)*Assumptions!$E$15 -> 20.164884
A12: Free cash flow | C12: =C10-C11 -> 65.850713 | D12: =D10-D11 -> 94.760773 | E12: =E10-E11 -> 132.01425 | F12: =F10-F11 -> 178.03285 | G12: =G10-G11 -> 232.35784 | H12: =H10-H11 -> 293.37378 | I12: =I10-I11 -> 358.15119 | J12: =J10-J11 -> 422.4904 | ... L12: =L10-L11 -> 528.80392
A13: Year fraction | C13: =Assumptions!$B$22 -> 0.5041 | D13: 1 | E13: 1 | F13: 1 | G13: 1 | H13: 1 | I13: 1 | J13: 1 | K13: 1 | L13: 1
A14: Discount time (mid-period) | C14: =C13/2 -> 0.25205 | D14: =C14+C13/2+D13/2 -> 1.0041 | E14: =D14+D13/2+E13/2 -> 2.0041 | F14: =E14+E13/2+F13/2 -> 3.0041 | G14: =F14+F13/2+G13/2 -> 4.0041 | H14: =G14+G13/2+H13/2 -> 5.0041 | I14: =H14+H13/2+I13/2 -> 6.0041 | J14: =I14+I13/2+J13/2 -> 7.0041 | K14: =J14+J13/2+K13/2 -> 8.0041 | L14: =K14+K13/2+L13/2 -> 9.0041
A15: Discount factor | C15: =1/(1+Assumptions!$E$10)^C14 -> 0.977385 | D15: =1/(1+Assumptions!$E$10)^D14 -> 0.91290226 | E15: =1/(1+Assumptions!$E$10)^E14 -> 0.8337007 | F15: =1/(1+Assumptions!$E$10)^F14 -> 0.7613705 | G15: =1/(1+Assumptions!$E$10)^G14 -> 0.69531552 | H15: =1/(1+Assumptions!$E$10)^H14 -> 0.63499135 | I15: =1/(1+Assumptions!$E$10)^I14 -> 0.57990077 | J15: =1/(1+Assumptions!$E$10)^J14 -> 0.52958975 | ... L15: =1/(1+Assumptions!$E$10)^L14 -> 0.44168366
A16: PV of free cash flow | C16: =C12*C13*C15 -> 32.444632 | D16: =D12*D13*D15 -> 86.507324 | E16: =E12*E13*E15 -> 110.06037 | F16: =F12*F13*F15 -> 135.54896 | G16: =G12*G13*G15 -> 161.56201 | H16: =H12*H13*H15 -> 186.28981 | I16: =I12*I13*I15 -> 207.69215 | J16: =J12*J13*J15 -> 223.74658 | ... L16: =L12*L13*L15 -> 233.56405
A19: PV of forecast free cash flow | B19: =SUM(C16:L16) -> 1610.158
A20: Terminal free cash flow (year 11) | B20: =L10*(1+Assumptions!$E$11)-L7*Assumptions!$E$11*Assumptions!$E$15 -> 542.02402
A21: Terminal value | B21: =B20/(Assumptions!$E$10-Assumptions!$E$11) -> 7743.2002
A22: PV of terminal value | B22: =B21/(1+Assumptions!$E$10)^(L14+0.5) -> 3268.3214
A23: Enterprise value | B23: =B19+B22 -> 4878.4794
A24: Cash & investments | B24: =Main!C7 -> 612.3
A25: Debt | B25: =Main!C8 -> 745.387
A26: Equity value | B26: =B23+B24-B25 -> 4745.3924
A27: Shares (mm) | B27: =Main!C4 -> 153.06905
A28: NPV / share | B28: =B26/B27 -> 31.001645
A29: Price | B29: =Main!C3 -> 54.53
A30: Upside | B30: =B28/B29-1 -> -0.43147543
A31: Terminal value, % of EV | B31: =IFERROR(B22/B23,0) -> 0.66994675
