Workbook

Sheet Main
B2: Telix Pharmaceuticals Limited
B3: Price | C3: =INDEX([1]Pharma!$F$1:$F$1000,MATCH("TLX",[1]Pharma!$B$1:$B$1000,0)) -> 11.16
B4: Shares | C4: 338.77705
B5: Market Cap. | C5: =C3*C4 -> 3780.7519
B7: Cash | C7: 141.866
B8: Debt | C8: =13.11+391.914 -> 405.024
B9: Enterprise V. | C9: =C5-C7+C8 -> 4043.9099
B11: NPV / Share | C11: =NPV!B28 -> 11.325641
B12: Upside | C12: =IFERROR(C11/C3-1,"") -> 0.014842398
B13: Cash / Share | C13: =IFERROR((C7-C8)/C4,"") -> -0.77678816
B14: Scenario | C14: =Assumptions!C4 -> Base
B15: Model | C15: DCF

Sheet Yearly Model
B1: 2022 | C1: 2023 | D1: 2024 | E1: 2025 | F1: 2026 | G1: 2027 | H1: 2028 | I1: 2029 | J1: 2030 | K1: 2031 | L1: 2032 | M1: 2033 | N1: 2034 | O1: 2035
A2: Revenue | B2: 111.41 | C2: 332.978 | D2: 516.551 | E2: 803.794 | F2: =E2*(1+NPV!C5) -> 1085.1219 | G2: =F2*(1+NPV!D5) -> 1425.7296 | H2: =G2*(1+NPV!E5) -> 1821.7656 | I2: =H2*(1+NPV!F5) -> 2262.0256 | J2: =I2*(1+NPV!G5) -> 2726.9976 | K2: =J2*(1+NPV!H5) -> 3189.0722 | L2: =K2*(1+NPV!I5) -> 3614.2818 | M2: =L2*(1+NPV!J5) -> 3965.6703 | ... O2: =N2*(1+NPV!L5) -> 4313.2172
A3: Cost of Sales | B3: 45.351 | C3: 123.445 | D3: 180.388 | E3: 377.356 | F3: =F2*(1-Assumptions!$B$19) -> 509.46473 | G3: =G2*(1-Assumptions!$B$19) -> 669.38005 | H3: =H2*(1-Assumptions!$B$19) -> 855.31895 | I3: =I2*(1-Assumptions!$B$19) -> 1062.021 | J3: =J2*(1-Assumptions!$B$19) -> 1280.3254 | K3: =K2*(1-Assumptions!$B$19) -> 1497.2694 | L3: =L2*(1-Assumptions!$B$19) -> 1696.9053 | M3: =M2*(1-Assumptions!$B$19) -> 1861.8822 | ... O3: =O2*(1-Assumptions!$B$19) -> 2025.0555
A4: Gross Margin | B4: =B2-B3 -> 66.059 | C4: =C2-C3 -> 209.533 | D4: =D2-D3 -> 336.163 | E4: =E2-E3 -> 426.438 | F4: =F2-F3 -> 575.65717 | G4: =G2-G3 -> 756.34956 | H4: =H2-H3 -> 966.44666 | I4: =I2-I3 -> 1200.0046 | ... O4: =O2-O3 -> 2288.1617
A5: Research & Dev. | B5: 56.15 | C5: 85.315 | D5: 127.93 | E5: 171.249 | F5: =F7*Assumptions!$B$20 -> 223.54297 | G5: =G7*Assumptions!$B$20 -> 283.67818 | H5: =H7*Assumptions!$B$20 -> 349.65843 | I5: =I7*Assumptions!$B$20 -> 418.242 | J5: =J7*Assumptions!$B$20 -> 485.02488 | K5: =K7*Assumptions!$B$20 -> 544.76907 | L5: =L7*Assumptions!$B$20 -> 591.9723 | M5: =M7*Assumptions!$B$20 -> 621.61989 | ... O5: =O7*Assumptions!$B$20 -> 615.39625
A6: SG&A & Other | B6: 73.882 | C6: 113.21 | D6: 153.056 | E6: 225.413 | F6: =F7-F5 -> 294.2772 | G6: =G7-G5 -> 373.4406 | H6: =H7-H5 -> 460.29856 | I6: =I7-I5 -> 550.58358 | J6: =J7-J5 -> 638.49812 | K6: =K7-K5 -> 717.14678 | L6: =L7-L5 -> 779.28621 | M6: =M7-M5 -> 818.31499 | ... O6: =O7-O5 -> 810.12204
A7: Operating Expense | B7: =SUM(B5:B6) -> 130.032 | C7: =SUM(C5:C6) -> 198.525 | D7: =SUM(D5:D6) -> 280.986 | E7: =SUM(E5:E6) -> 396.662 | F7: =F4-F2*NPV!C6 -> 517.82017 | G7: =G4-G2*NPV!D6 -> 657.11878 | H7: =H4-H2*NPV!E6 -> 809.95699 | I7: =I4-I2*NPV!F6 -> 968.82558 | J7: =J4-J2*NPV!G6 -> 1123.523 | K7: =K4-K2*NPV!H6 -> 1261.9159 | L7: =L4-L2*NPV!I6 -> 1371.2585 | M7: =M4-M2*NPV!J6 -> 1439.9349 | ... O7: =O4-O2*NPV!L6 -> 1425.5183
A8: Operating Income | B8: =B4-B7 -> -63.973 | C8: =C4-C7 -> 11.008 | D8: =D4-D7 -> 55.177 | E8: =E4-E7 -> 29.776 | F8: =F4-F7 -> 57.836997 | G8: =G4-G7 -> 99.230781 | H8: =H4-H7 -> 156.48967 | I8: =I4-I7 -> 231.17902 | ... O8: =O4-O7 -> 862.64344
A9: Interest & Other | B9: -4.657 | C9: -8.414 | D9: -17.262 | E9: -35.042 | F9: 0 | G9: 0 | H9: 0 | I9: 0 | J9: 0 | K9: 0 | L9: 0 | M9: 0 | N9: 0 | O9: 0
A10: Pretax | B10: =B8+B9 -> -68.63 | C10: =C8+C9 -> 2.594 | D10: =D8+D9 -> 37.915 | E10: =E8+E9 -> -5.266 | F10: =F8+F9 -> 57.836997 | G10: =G8+G9 -> 99.230781 | H10: =H8+H9 -> 156.48967 | I10: =I8+I9 -> 231.17902 | ... O10: =O8+O9 -> 862.64344
A11: Taxes | B11: 3.797 | C11: -1.614 | D11: 4.23 | E11: 1.859 | F11: =MAX(0,F10)*Assumptions!$E$14 -> 9.8322895 | G11: =MAX(0,G10)*Assumptions!$E$14 -> 16.869233 | H11: =MAX(0,H10)*Assumptions!$E$14 -> 26.603243 | I11: =MAX(0,I10)*Assumptions!$E$14 -> 39.300433 | J11: =MAX(0,J10)*Assumptions!$E$14 -> 54.935366 | K11: =MAX(0,K10)*Assumptions!$E$14 -> 73.080778 | L11: =MAX(0,L10)*Assumptions!$E$14 -> 92.840056 | M11: =MAX(0,M10)*Assumptions!$E$14 -> 112.85504 | ... O11: =MAX(0,O10)*Assumptions!$E$14 -> 146.64939
A12: Net Income | B12: -72.428 | C12: 4.208 | D12: 33.685 | E12: -7.125 | F12: =F10-F11 -> 48.004708 | G12: =G10-G11 -> 82.361548 | H12: =H10-H11 -> 129.88642 | I12: =I10-I11 -> 191.87859 | J12: =J10-J11 -> 268.21385 | K12: =K10-K11 -> 356.80615 | L12: =L10-L11 -> 453.27792 | M12: =M10-M11 -> 550.99816 | ... O12: =O10-O11 -> 715.99406
A13: Earnings per Share | B13: =IFERROR(B12/B14,0) -> -0.23315435 | C13: =IFERROR(C12/C14,0) -> 0.012999289 | D13: =IFERROR(D12/D14,0) -> 0.097584505 | E13: =IFERROR(E12/E14,0) -> -0.021087368 | F13: =IFERROR(F12/F14,0) -> 0.1417 | G13: =IFERROR(G12/G14,0) -> 0.24311431 | H13: =IFERROR(H12/H14,0) -> 0.38339794 | I13: =IFERROR(I12/I14,0) -> 0.56638603 | ... O13: =IFERROR(O12/O14,0) -> 2.1134668
A14: Shares | B14: 310.644 | C14: 323.71 | D14: 345.188 | E14: 337.88 | F14: =Main!$C$4 -> 338.77705 | G14: =Main!$C$4 -> 338.77705 | H14: =Main!$C$4 -> 338.77705 | I14: =Main!$C$4 -> 338.77705 | J14: =Main!$C$4 -> 338.77705 | K14: =Main!$C$4 -> 338.77705 | L14: =Main!$C$4 -> 338.77705 | M14: =Main!$C$4 -> 338.77705 | ... O14: =Main!$C$4 -> 338.77705
A16: Revenue Change | C16: =IFERROR(C2/B2-1,"") -> 1.9887622 | D16: =IFERROR(D2/C2-1,"") -> 0.55130669 | E16: =IFERROR(E2/D2-1,"") -> 0.55607868 | F16: =IFERROR(F2/E2-1,"") -> 0.35 | G16: =IFERROR(G2/F2-1,"") -> 0.31388889 | H16: =IFERROR(H2/G2-1,"") -> 0.27777778 | I16: =IFERROR(I2/H2-1,"") -> 0.24166667 | J16: =IFERROR(J2/I2-1,"") -> 0.20555556 | ... O16: =IFERROR(O2/N2-1,"") -> 0.025
A17: Gross Margin | B17: =IFERROR(B4/B2,"") -> 0.592936 | C17: =IFERROR(C4/C2,"") -> 0.6292698 | D17: =IFERROR(D4/D2,"") -> 0.65078376 | E17: =IFERROR(E4/E2,"") -> 0.53053145 | F17: =IFERROR(F4/F2,"") -> 0.5305 | G17: =IFERROR(G4/G2,"") -> 0.5305 | H17: =IFERROR(H4/H2,"") -> 0.5305 | I17: =IFERROR(I4/I2,"") -> 0.5305 | ... O17: =IFERROR(O4/O2,"") -> 0.5305
A18: Operating Margin | B18: =IFERROR(B8/B2,"") -> -0.57421237 | C18: =IFERROR(C8/C2,"") -> 0.033059241 | D18: =IFERROR(D8/D2,"") -> 0.10681811 | E18: =IFERROR(E8/E2,"") -> 0.037044317 | F18: =IFERROR(F8/F2,"") -> 0.0533 | G18: =IFERROR(G8/G2,"") -> 0.0696 | H18: =IFERROR(H8/H2,"") -> 0.0859 | I18: =IFERROR(I8/I2,"") -> 0.1022 | ... O18: =IFERROR(O8/O2,"") -> 0.2
A19: Actual / Estimate | B19: A | C19: A | D19: A | E19: A | F19: E | G19: E | H19: E | I19: E | J19: E | K19: E | L19: E | M19: E | N19: E | O19: E

Sheet Quarterly Model

Sheet Assumptions
A1: Telix Pharmaceuticals Limited: basic DCF assumptions
A2: Blue = input, black = formula, green = link. $mm unless noted.
A4: Scenario (1 Bear, 2 Base, 3 Bull) | B4: 2 | C4: =CHOOSE($B$4,"Bear","Base","Bull") -> Base
A6: Discount rate override (blank = scenario)
A7: Terminal growth override (blank = scenario)
A9: Parameter | B9: Bear | C9: Base | D9: Bull | E9: Live
A10: Discount rate | B10: 0.12 | C10: 0.11 | D10: 0.1 | E10: =IF(ISNUMBER($B$6),$B$6,CHOOSE($B$4,B10,C10,D10)) -> 0.11
A11: Terminal growth | B11: 0.02 | C11: 0.025 | D11: 0.03 | E11: =IF(ISNUMBER($B$7),$B$7,CHOOSE($B$4,B11,C11,D11)) -> 0.025
A12: Revenue growth, first forecast year | B12: 0.3 | C12: 0.35 | D12: 0.4 | E12: =CHOOSE($B$4,B12,C12,D12) -> 0.35
A13: Operating margin, year 10 | B13: 0.15 | C13: 0.2 | D13: 0.25 | E13: =CHOOSE($B$4,B13,C13,D13) -> 0.2
A14: Tax rate on operating income | B14: 0.17 | C14: 0.17 | D14: 0.17 | E14: =CHOOSE($B$4,B14,C14,D14) -> 0.17
A15: Reinvestment, % of revenue increase | B15: 0.25 | C15: 0.25 | D15: 0.25 | E15: =CHOOSE($B$4,B15,C15,D15) -> 0.25
A17: Single inputs
A18: Starting operating margin (TTM) | B18: 0.037
A19: Gross margin (forecast) | B19: 0.5305
A20: R&D share of operating expense (forecast) | B20: 0.4317
A21: Forecast years | B21: 10
A22: First forecast year, fraction after balance sheet date | B22: 1
A23: Balance sheet date | B23: 46022
A24: Reporting currency per USD (USD) | B24: 1
A25: Base revenue, FY2025 | B25: ='Yearly Model'!E2 -> 803.794
A27: Scenario summary
A28: Scenario | B28: Enterprise value | C28: Equity value | D28: NPV / share | E28: Upside
A29: Live | B29: =NPV!B23 -> 4100.0253 | C29: =NPV!B26 -> 3836.8673 | D29: =NPV!B28 -> 11.325641 | E29: =NPV!B30 -> 0.014842398
A30: 1 | B30: 2005.7686 | C30: 1742.6106 | D30: 5.1438272 | E30: -0.53908359
A31: 2 | B31: 4100.0253 | C31: 3836.8673 | D31: 11.325641 | E31: 0.014842398
A32: 3 | B32: 8039.1934 | C32: 7776.0354 | D32: 22.953253 | E32: 1.0567431
A35: NPV / share: discount rate (rows) x terminal growth (columns)
A36: =NPV!B28 -> 11.325641 | B36: 0.015 | C36: 0.02 | D36: 0.025 | E36: 0.03 | F36: 0.035
A37: 0.09 | B37: 14.41842 | C37: 15.494749 | D37: 16.737099 | E37: 18.18698 | F37: 19.901001
A38: 0.1 | B38: 11.965987 | C38: 12.752877 | D38: 13.645027 | E38: 14.664996 | F38: 15.842288
A39: 0.11 | B39: 10.069828 | C39: 10.662721 | D39: 11.325641 | E39: 12.071722 | F39: 12.917601
A40: 0.12 | B40: 8.5679665 | C40: 9.0255492 | D40: 9.5315235 | E40: 10.093958 | F40: 10.722821
A41: 0.13 | B41: 7.3550412 | C41: 7.7151846 | D41: 8.1098145 | E41: 8.5441069 | F41: 9.0243276

Sheet NPV
A1: Telix Pharmaceuticals Limited: free-cash-flow DCF ($mm)
A3: Fiscal year | B3: ='Yearly Model'!E1 -> 2025 | C3: ='Yearly Model'!F1 -> 2026 | D3: ='Yearly Model'!G1 -> 2027 | E3: ='Yearly Model'!H1 -> 2028 | F3: ='Yearly Model'!I1 -> 2029 | G3: ='Yearly Model'!J1 -> 2030 | H3: ='Yearly Model'!K1 -> 2031 | I3: ='Yearly Model'!L1 -> 2032 | ... L3: ='Yearly Model'!O1 -> 2035
A4: Period | B4: Actual | C4: 1 | D4: 2 | E4: 3 | F4: 4 | G4: 5 | H4: 6 | I4: 7 | J4: 8 | K4: 9 | L4: 10
A5: Revenue growth | C5: =Assumptions!$E$12+(Assumptions!$E$11-Assumptions!$E$12)*(C4-1)/(Assumptions!$B$21-1) -> 0.35 | D5: =Assumptions!$E$12+(Assumptions!$E$11-Assumptions!$E$12)*(D4-1)/(Assumptions!$B$21-1) -> 0.31388889 | E5: =Assumptions!$E$12+(Assumptions!$E$11-Assumptions!$E$12)*(E4-1)/(Assumptions!$B$21-1) -> 0.27777778 | F5: =Assumptions!$E$12+(Assumptions!$E$11-Assumptions!$E$12)*(F4-1)/(Assumptions!$B$21-1) -> 0.24166667 | G5: =Assumptions!$E$12+(Assumptions!$E$11-Assumptions!$E$12)*(G4-1)/(Assumptions!$B$21-1) -> 0.20555556 | H5: =Assumptions!$E$12+(Assumptions!$E$11-Assumptions!$E$12)*(H4-1)/(Assumptions!$B$21-1) -> 0.16944444 | I5: =Assumptions!$E$12+(Assumptions!$E$11-Assumptions!$E$12)*(I4-1)/(Assumptions!$B$21-1) -> 0.13333333 | J5: =Assumptions!$E$12+(Assumptions!$E$11-Assumptions!$E$12)*(J4-1)/(Assumptions!$B$21-1) -> 0.097222222 | ... L5: =Assumptions!$E$12+(Assumptions!$E$11-Assumptions!$E$12)*(L4-1)/(Assumptions!$B$21-1) -> 0.025
A6: Operating margin | B6: =IFERROR(B8/B7,0) -> 0.037044317 | C6: =Assumptions!$B$18+(Assumptions!$E$13-Assumptions!$B$18)*C4/Assumptions!$B$21 -> 0.0533 | D6: =Assumptions!$B$18+(Assumptions!$E$13-Assumptions!$B$18)*D4/Assumptions!$B$21 -> 0.0696 | E6: =Assumptions!$B$18+(Assumptions!$E$13-Assumptions!$B$18)*E4/Assumptions!$B$21 -> 0.0859 | F6: =Assumptions!$B$18+(Assumptions!$E$13-Assumptions!$B$18)*F4/Assumptions!$B$21 -> 0.1022 | G6: =Assumptions!$B$18+(Assumptions!$E$13-Assumptions!$B$18)*G4/Assumptions!$B$21 -> 0.1185 | H6: =Assumptions!$B$18+(Assumptions!$E$13-Assumptions!$B$18)*H4/Assumptions!$B$21 -> 0.1348 | I6: =Assumptions!$B$18+(Assumptions!$E$13-Assumptions!$B$18)*I4/Assumptions!$B$21 -> 0.1511 | J6: =Assumptions!$B$18+(Assumptions!$E$13-Assumptions!$B$18)*J4/Assumptions!$B$21 -> 0.1674 | ... L6: =Assumptions!$B$18+(Assumptions!$E$13-Assumptions!$B$18)*L4/Assumptions!$B$21 -> 0.2
A7: Revenue | B7: ='Yearly Model'!E2 -> 803.794 | C7: ='Yearly Model'!F2 -> 1085.1219 | D7: ='Yearly Model'!G2 -> 1425.7296 | E7: ='Yearly Model'!H2 -> 1821.7656 | F7: ='Yearly Model'!I2 -> 2262.0256 | G7: ='Yearly Model'!J2 -> 2726.9976 | H7: ='Yearly Model'!K2 -> 3189.0722 | I7: ='Yearly Model'!L2 -> 3614.2818 | ... L7: ='Yearly Model'!O2 -> 4313.2172
A8: Operating income | B8: ='Yearly Model'!E8 -> 29.776 | C8: ='Yearly Model'!F8 -> 57.836997 | D8: ='Yearly Model'!G8 -> 99.230781 | E8: ='Yearly Model'!H8 -> 156.48967 | F8: ='Yearly Model'!I8 -> 231.17902 | G8: ='Yearly Model'!J8 -> 323.14921 | H8: ='Yearly Model'!K8 -> 429.88693 | I8: ='Yearly Model'!L8 -> 546.11798 | ... L8: ='Yearly Model'!O8 -> 862.64344
A9: Tax on operating income | C9: =MAX(0,C8)*Assumptions!$E$14 -> 9.8322895 | D9: =MAX(0,D8)*Assumptions!$E$14 -> 16.869233 | E9: =MAX(0,E8)*Assumptions!$E$14 -> 26.603243 | F9: =MAX(0,F8)*Assumptions!$E$14 -> 39.300433 | G9: =MAX(0,G8)*Assumptions!$E$14 -> 54.935366 | H9: =MAX(0,H8)*Assumptions!$E$14 -> 73.080778 | I9: =MAX(0,I8)*Assumptions!$E$14 -> 92.840056 | J9: =MAX(0,J8)*Assumptions!$E$14 -> 112.85504 | ... L9: =MAX(0,L8)*Assumptions!$E$14 -> 146.64939
A10: NOPAT | C10: =C8-C9 -> 48.004708 | D10: =D8-D9 -> 82.361548 | E10: =E8-E9 -> 129.88642 | F10: =F8-F9 -> 191.87859 | G10: =G8-G9 -> 268.21385 | H10: =H8-H9 -> 356.80615 | I10: =I8-I9 -> 453.27792 | J10: =J8-J9 -> 550.99816 | ... L10: =L8-L9 -> 715.99406
A11: Reinvestment | C11: =(C7-B7)*Assumptions!$E$15 -> 70.331975 | D11: =(D7-C7)*Assumptions!$E$15 -> 85.151927 | E11: =(E7-D7)*Assumptions!$E$15 -> 99.009001 | F11: =(F7-E7)*Assumptions!$E$15 -> 110.06501 | G11: =(G7-F7)*Assumptions!$E$15 -> 116.24298 | H11: =(H7-G7)*Assumptions!$E$15 -> 115.51865 | I11: =(I7-H7)*Assumptions!$E$15 -> 106.30241 | J11: =(J7-I7)*Assumptions!$E$15 -> 87.847126 | ... L11: =(L7-K7)*Assumptions!$E$15 -> 26.300105
A12: Free cash flow | C12: =C10-C11 -> -22.327267 | D12: =D10-D11 -> -2.7903789 | E12: =E10-E11 -> 30.877422 | F12: =F10-F11 -> 81.813581 | G12: =G10-G11 -> 151.97086 | H12: =H10-H11 -> 241.2875 | I12: =I10-I11 -> 346.97552 | J12: =J10-J11 -> 463.15103 | ... L12: =L10-L11 -> 689.69395
A13: Year fraction | C13: =Assumptions!$B$22 -> 1 | D13: 1 | E13: 1 | F13: 1 | G13: 1 | H13: 1 | I13: 1 | J13: 1 | K13: 1 | L13: 1
A14: Discount time (mid-period) | C14: =C13/2 -> 0.5 | D14: =C14+C13/2+D13/2 -> 1.5 | E14: =D14+D13/2+E13/2 -> 2.5 | F14: =E14+E13/2+F13/2 -> 3.5 | G14: =F14+F13/2+G13/2 -> 4.5 | H14: =G14+G13/2+H13/2 -> 5.5 | I14: =H14+H13/2+I13/2 -> 6.5 | J14: =I14+I13/2+J13/2 -> 7.5 | K14: =J14+J13/2+K13/2 -> 8.5 | L14: =K14+K13/2+L13/2 -> 9.5
A15: Discount factor | C15: =1/(1+Assumptions!$E$10)^C14 -> 0.949158 | D15: =1/(1+Assumptions!$E$10)^D14 -> 0.85509729 | E15: =1/(1+Assumptions!$E$10)^E14 -> 0.77035792 | F15: =1/(1+Assumptions!$E$10)^F14 -> 0.69401615 | G15: =1/(1+Assumptions!$E$10)^G14 -> 0.62523977 | H15: =1/(1+Assumptions!$E$10)^H14 -> 0.56327907 | I15: =1/(1+Assumptions!$E$10)^I14 -> 0.50745862 | J15: =1/(1+Assumptions!$E$10)^J14 -> 0.45716993 | ... L15: =1/(1+Assumptions!$E$10)^L14 -> 0.37104937
A16: PV of free cash flow | C16: =C12*C13*C15 -> -21.192104 | D16: =D12*D13*D15 -> -2.3860455 | E16: =E12*E13*E15 -> 23.786667 | F16: =F12*F13*F15 -> 56.779946 | G16: =G12*G13*G15 -> 95.018227 | H16: =H12*H13*H15 -> 135.9122 | I16: =I12*I13*I15 -> 176.07572 | J16: =J12*J13*J15 -> 211.73873 | ... L16: =L12*L13*L15 -> 255.91051
A19: PV of forecast free cash flow | B19: =SUM(C16:L16) -> 1170.943
A20: Terminal free cash flow (year 11) | B20: =L10*(1+Assumptions!$E$11)-L7*Assumptions!$E$11*Assumptions!$E$15 -> 706.9363
A21: Terminal value | B21: =B20/(Assumptions!$E$10-Assumptions!$E$11) -> 8316.8977
A22: PV of terminal value | B22: =B21/(1+Assumptions!$E$10)^(L14+0.5) -> 2929.0823
A23: Enterprise value | B23: =B19+B22 -> 4100.0253
A24: Cash & investments | B24: =Main!C7 -> 141.866
A25: Debt | B25: =Main!C8 -> 405.024
A26: Equity value | B26: =B23+B24-B25 -> 3836.8673
A27: Shares (mm) | B27: =Main!C4 -> 338.77705
A28: NPV / share | B28: =B26/B27 -> 11.325641
A29: Price | B29: =Main!C3 -> 11.16
A30: Upside | B30: =B28/B29-1 -> 0.014842398
A31: Terminal value, % of EV | B31: =IFERROR(B22/B23,0) -> 0.7144059
