Workbook

Sheet Main
B2: Wave Life Sciences Ltd.
B3: Price | C3: =INDEX([1]Pharma!$F$1:$F$1000,MATCH("WVE",[1]Pharma!$B$1:$B$1000,0)) -> 3.385
B4: Shares | C4: 197.04817
B5: Market Cap. | C5: =C3*C4 -> 667.00807
B7: Cash | C7: 490.6
B8: Debt | C8: 0
B9: Enterprise V. | C9: =C5-C7+C8 -> 176.40807
B11: NPV / Share | C11: =NPV!B28 -> 2.1192275
B12: Upside | C12: =IFERROR(C11/C3-1,"") -> -0.37393575
B13: Cash / Share | C13: =IFERROR((C7-C8)/C4,"") -> 2.4897465
B14: Scenario | C14: =Assumptions!C4 -> Base
B15: Model | C15: DCF

Sheet Yearly Model
B1: 2013 | C1: 2014 | D1: 2015 | E1: 2016 | F1: 2017 | G1: 2018 | H1: 2019 | I1: 2020 | J1: 2021 | K1: 2022 | L1: 2023 | M1: 2024 | N1: 2025 | O1: 2026 | P1: 2027 | Q1: 2028 | R1: 2029 | S1: 2030 | T1: 2031 | U1: 2032 | V1: 2033 | W1: 2034 | X1: 2035
A2: Revenue | B2: 0 | C2: 0 | D2: 0.152 | E2: 1.485 | F2: 3.893 | G2: 14.414 | H2: 15.983 | I2: 20.077 | J2: 40.964 | K2: 3.649 | L2: 113.305 | M2: 108.302 | N2: 42.727 | O2: =N2*(1+NPV!C5) -> 40.838467 | P2: =O2*(1+NPV!D5) -> 39.347409 | Q2: =P2*(1+NPV!E5) -> 38.213329 | R2: =Q2*(1+NPV!F5) -> 37.405754 | S2: =R2*(1+NPV!G5) -> 36.902854 | T2: =S2*(1+NPV!H5) -> 36.690458 | U2: =T2*(1+NPV!I5) -> 36.761393 | V2: =U2*(1+NPV!J5) -> 37.115119 | ... X2: =W2*(1+NPV!L5) -> 38.701564
A3: Cost of Sales | B3: 0 | C3: 0 | D3: 0 | E3: 0 | F3: 0 | G3: 0 | H3: 0 | I3: 0 | J3: 0 | K3: 0 | L3: 0 | M3: 0 | N3: 0 | O3: =O2*(1-Assumptions!$B$19) -> 0 | P3: =P2*(1-Assumptions!$B$19) -> 0 | Q3: =Q2*(1-Assumptions!$B$19) -> 0 | R3: =R2*(1-Assumptions!$B$19) -> 0 | S3: =S2*(1-Assumptions!$B$19) -> 0 | T3: =T2*(1-Assumptions!$B$19) -> 0 | U3: =U2*(1-Assumptions!$B$19) -> 0 | V3: =V2*(1-Assumptions!$B$19) -> 0 | ... X3: =X2*(1-Assumptions!$B$19) -> 0
A4: Gross Margin | B4: =B2-B3 -> 0 | C4: =C2-C3 -> 0 | D4: =D2-D3 -> 0.152 | E4: =E2-E3 -> 1.485 | F4: =F2-F3 -> 3.893 | G4: =G2-G3 -> 14.414 | H4: =H2-H3 -> 15.983 | I4: =I2-I3 -> 20.077 | ... X4: =X2-X3 -> 38.701564
A5: Research & Dev. | B5: 1.92 | C5: 2.395 | D5: 9.057 | E5: 40.818 | F5: 79.309 | G5: 134.428 | H5: 175.431 | I5: 130.944 | J5: 121.875 | K5: 115.856 | L5: 130.009 | M5: 159.682 | N5: 182.779 | O5: =O7*Assumptions!$B$20 -> 54.870214 | P5: =P7*Assumptions!$B$20 -> 49.469361 | Q5: =Q7*Assumptions!$B$20 -> 44.743987 | R5: =R7*Assumptions!$B$20 -> 40.568571 | S5: =S7*Assumptions!$B$20 -> 36.836746 | T5: =T7*Assumptions!$B$20 -> 33.456666 | U5: =U7*Assumptions!$B$20 -> 30.34716 | V5: =V7*Assumptions!$B$20 -> 27.434436 | ... X5: =X7*Assumptions!$B$20 -> 21.923662
A6: SG&A & Other | B6: 1.654 | C6: 2.999 | D6: 10.393 | E6: 16.387 | F6: 26.975 | G6: 39.509 | H6: 48.869 | I6: 42.51 | J6: 46.105 | K6: 50.513 | L6: 51.292 | M6: 59.023 | N6: 75.331 | O6: =O7-O5 -> 22.619143 | P6: =P7-P5 -> 20.39275 | Q6: =Q7-Q5 -> 18.44481 | R6: =R7-R5 -> 16.723578 | S6: =S7-S5 -> 15.185208 | T6: =T7-T5 -> 13.791838 | U6: =U7-U5 -> 12.510007 | V6: =V7-V5 -> 11.309295 | ... X6: =X7-X5 -> 9.0375892
A7: Operating Expense | B7: =SUM(B5:B6) -> 3.574 | C7: =SUM(C5:C6) -> 5.394 | D7: =SUM(D5:D6) -> 19.45 | E7: =SUM(E5:E6) -> 57.205 | F7: =SUM(F5:F6) -> 106.284 | G7: =SUM(G5:G6) -> 173.937 | H7: =SUM(H5:H6) -> 224.3 | I7: =SUM(I5:I6) -> 173.454 | ... N7: =SUM(N5:N6) -> 258.11 | O7: =O4-O2*NPV!C6 -> 77.489357 | P7: =P4-P2*NPV!D6 -> 69.862111 | Q7: =Q4-Q2*NPV!E6 -> 63.188797 | R7: =R4-R2*NPV!F6 -> 57.292149 | S7: =S4-S2*NPV!G6 -> 52.021954 | T7: =T4-T2*NPV!H6 -> 47.248504 | U7: =U4-U2*NPV!I6 -> 42.857167 | V7: =V4-V2*NPV!J6 -> 38.743731 | ... X7: =X4-X2*NPV!L6 -> 30.961251
A8: Operating Income | B8: =B4-B7 -> -3.574 | C8: =C4-C7 -> -5.394 | D8: =D4-D7 -> -19.298 | E8: =E4-E7 -> -55.72 | F8: =F4-F7 -> -102.391 | G8: =G4-G7 -> -159.523 | H8: =H4-H7 -> -208.317 | I8: =I4-I7 -> -153.377 | ... X8: =X4-X7 -> 7.7403127
A9: Interest & Other | B9: -0.074 | C9: 0.249 | D9: 0.142 | E9: 0.542 | F9: 1.253 | G9: 12.939 | H9: 14.679 | I9: 2.626 | J9: 4.612 | K9: 1.601 | L9: 9.819 | M9: 13.403 | N9: 10.983 | O9: 0 | P9: 0 | Q9: 0 | R9: 0 | S9: 0 | T9: 0 | U9: 0 | V9: 0 | W9: 0 | X9: 0
A10: Pretax | B10: =B8+B9 -> -3.648 | C10: =C8+C9 -> -5.145 | D10: =D8+D9 -> -19.156 | E10: =E8+E9 -> -55.178 | F10: =F8+F9 -> -101.138 | G10: =G8+G9 -> -146.584 | H10: =H8+H9 -> -193.638 | I10: =I8+I9 -> -150.751 | ... X10: =X8+X9 -> 7.7403127
A11: Taxes | B11: -0.33 | C11: 0.084 | D11: 0.044 | E11: 0.482 | F11: 0.842 | G11: 0.069 | H11: 0 | I11: -0.841 | J11: -0.204 | K11: 0.681 | L11: -0.677 | M11: 0 | N11: 0 | O11: =MAX(0,O10)*Assumptions!$E$14 -> 0 | P11: =MAX(0,P10)*Assumptions!$E$14 -> 0 | Q11: =MAX(0,Q10)*Assumptions!$E$14 -> 0 | R11: =MAX(0,R10)*Assumptions!$E$14 -> 0 | S11: =MAX(0,S10)*Assumptions!$E$14 -> 0 | T11: =MAX(0,T10)*Assumptions!$E$14 -> 0 | U11: =MAX(0,U10)*Assumptions!$E$14 -> 0 | V11: =MAX(0,V10)*Assumptions!$E$14 -> 0 | ... X11: =MAX(0,X10)*Assumptions!$E$14 -> 1.3158532
A12: Net Income | B12: -3.318 | C12: -5.229 | D12: -19.2 | E12: -55.66 | F12: -101.98 | G12: -146.653 | H12: -193.638 | I12: -149.91 | J12: -122.2 | K12: -161.8 | L12: -57.5 | M12: -97 | N12: -204.4 | O12: =O10-O11 -> -36.65089 | P12: =P10-P11 -> -30.514702 | Q12: =Q10-Q11 -> -24.975468 | R12: =R10-R11 -> -19.886395 | S12: =S10-S11 -> -15.119099 | T12: =T10-T11 -> -10.558046 | U12: =U10-U11 -> -6.0957742 | V12: =V10-V11 -> -1.6286114 | ... X12: =X10-X11 -> 6.4244596
A13: Earnings per Share | B13: =IFERROR(B12/B14,0) -> -1.9036145 | C13: =IFERROR(C12/C14,0) -> -1.3366564 | D13: =IFERROR(D12/D14,0) -> -1.8283973 | E13: =IFERROR(E12/E14,0) -> -2.441121 | F13: =IFERROR(F12/F14,0) -> -3.846415 | G13: =IFERROR(G12/G14,0) -> -5.0622368 | H13: =IFERROR(H12/H14,0) -> -5.71777 | I13: =IFERROR(I12/I14,0) -> -3.821505 | ... X13: =IFERROR(X12/X14,0) -> 0.032603497
A14: Shares | B14: 1.743 | C14: 3.912 | D14: 10.501 | E14: 22.801 | F14: 26.513 | G14: 28.97 | H14: 33.866 | I14: 39.228 | J14: 51.826 | K14: 78.856 | L14: 106.097 | M14: 138.277 | N14: 168.65 | O14: =Main!$C$4 -> 197.04817 | P14: =Main!$C$4 -> 197.04817 | Q14: =Main!$C$4 -> 197.04817 | R14: =Main!$C$4 -> 197.04817 | S14: =Main!$C$4 -> 197.04817 | T14: =Main!$C$4 -> 197.04817 | U14: =Main!$C$4 -> 197.04817 | V14: =Main!$C$4 -> 197.04817 | ... X14: =Main!$C$4 -> 197.04817
A16: Revenue Change | C16: =IFERROR(C2/B2-1,"") | D16: =IFERROR(D2/C2-1,"") | E16: =IFERROR(E2/D2-1,"") -> 8.7697368 | F16: =IFERROR(F2/E2-1,"") -> 1.6215488 | G16: =IFERROR(G2/F2-1,"") -> 2.702543 | H16: =IFERROR(H2/G2-1,"") -> 0.1088525 | I16: =IFERROR(I2/H2-1,"") -> 0.25614716 | J16: =IFERROR(J2/I2-1,"") -> 1.0403447 | ... X16: =IFERROR(X2/W2-1,"") -> 0.025
A17: Gross Margin | B17: =IFERROR(B4/B2,"") | C17: =IFERROR(C4/C2,"") | D17: =IFERROR(D4/D2,"") -> 1 | E17: =IFERROR(E4/E2,"") -> 1 | F17: =IFERROR(F4/F2,"") -> 1 | G17: =IFERROR(G4/G2,"") -> 1 | H17: =IFERROR(H4/H2,"") -> 1 | I17: =IFERROR(I4/I2,"") -> 1 | ... X17: =IFERROR(X4/X2,"") -> 1
A18: Operating Margin | B18: =IFERROR(B8/B2,"") | C18: =IFERROR(C8/C2,"") | D18: =IFERROR(D8/D2,"") -> -126.96053 | E18: =IFERROR(E8/E2,"") -> -37.521886 | F18: =IFERROR(F8/F2,"") -> -26.30131 | G18: =IFERROR(G8/G2,"") -> -11.067226 | H18: =IFERROR(H8/H2,"") -> -13.033661 | I18: =IFERROR(I8/I2,"") -> -7.6394382 | ... X18: =IFERROR(X8/X2,"") -> 0.2
A19: Actual / Estimate | B19: A | C19: A | D19: A | E19: A | F19: A | G19: A | H19: A | I19: A | J19: A | K19: A | L19: A | M19: A | N19: A | O19: E | P19: E | Q19: E | R19: E | S19: E | T19: E | U19: E | V19: E | W19: E | X19: E

Sheet Quarterly Model

Sheet Assumptions
A1: Wave Life Sciences Ltd.: basic DCF assumptions
A2: Blue = input, black = formula, green = link. $mm unless noted.
A4: Scenario (1 Bear, 2 Base, 3 Bull) | B4: 2 | C4: =CHOOSE($B$4,"Bear","Base","Bull") -> Base
A6: Discount rate override (blank = scenario)
A7: Terminal growth override (blank = scenario)
A9: Parameter | B9: Bear | C9: Base | D9: Bull | E9: Live
A10: Discount rate | B10: 0.135 | C10: 0.125 | D10: 0.115 | E10: =IF(ISNUMBER($B$6),$B$6,CHOOSE($B$4,B10,C10,D10)) -> 0.125
A11: Terminal growth | B11: 0.02 | C11: 0.025 | D11: 0.03 | E11: =IF(ISNUMBER($B$7),$B$7,CHOOSE($B$4,B11,C11,D11)) -> 0.025
A12: Revenue growth, first forecast year | B12: -0.0942 | C12: -0.0442 | D12: 0.0058 | E12: =CHOOSE($B$4,B12,C12,D12) -> -0.0442
A13: Operating margin, year 10 | B13: 0.15 | C13: 0.2 | D13: 0.25 | E13: =CHOOSE($B$4,B13,C13,D13) -> 0.2
A14: Tax rate on operating income | B14: 0.17 | C14: 0.17 | D14: 0.17 | E14: =CHOOSE($B$4,B14,C14,D14) -> 0.17
A15: Reinvestment, % of revenue increase | B15: 0.25 | C15: 0.25 | D15: 0.25 | E15: =CHOOSE($B$4,B15,C15,D15) -> 0.25
A17: Single inputs
A18: Starting operating margin (TTM) | B18: -1.0194
A19: Gross margin (forecast) | B19: 1
A20: R&D share of operating expense (forecast) | B20: 0.7081
A21: Forecast years | B21: 10
A22: First forecast year, fraction after balance sheet date | B22: 0.5041
A23: Balance sheet date | B23: 46203
A24: Reporting currency per USD (USD) | B24: 1
A25: Base revenue, FY2025 | B25: ='Yearly Model'!N2 -> 42.727
A27: Scenario summary
A28: Scenario | B28: Enterprise value | C28: Equity value | D28: NPV / share | E28: Upside
A29: Live | B29: =NPV!B23 -> -73.01009 | C29: =NPV!B26 -> 417.58991 | D29: =NPV!B28 -> 2.1192275 | E29: =NPV!B30 -> -0.37393575
A30: 1 | B30: -73.938923 | C30: 416.66108 | D30: 2.1145138 | E30: -0.37532828
A31: 2 | B31: -73.01009 | C31: 417.58991 | D31: 2.1192275 | E31: -0.37393575
A32: 3 | B32: -59.894045 | C32: 430.70595 | D32: 2.1857901 | E32: -0.35427175
A35: NPV / share: discount rate (rows) x terminal growth (columns)
A36: =NPV!B28 -> 2.1192275 | B36: 0.015 | C36: 0.02 | D36: 0.025 | E36: 0.03 | F36: 0.035
A37: 0.105 | B37: 2.1333096 | C37: 2.1427312 | D37: 2.1535775 | E37: 2.166136 | F37: 2.1807768
A38: 0.115 | B38: 2.1184943 | C38: 2.1253629 | D38: 2.1332036 | E38: 2.1421904 | F38: 2.1525404
A39: 0.125 | B39: 2.1084108 | C39: 2.1134762 | D39: 2.1192275 | E39: 2.1257747 | F39: 2.1332527
A40: 0.135 | B40: 2.1017499 | C40: 2.1055072 | D40: 2.1097615 | E40: 2.1145854 | F40: 2.1200661
A41: 0.145 | B41: 2.0976151 | C41: 2.1004024 | D41: 2.1035579 | E41: 2.1071312 | F41: 2.1111806

Sheet NPV
A1: Wave Life Sciences Ltd.: free-cash-flow DCF ($mm)
A3: Fiscal year | B3: ='Yearly Model'!N1 -> 2025 | C3: ='Yearly Model'!O1 -> 2026 | D3: ='Yearly Model'!P1 -> 2027 | E3: ='Yearly Model'!Q1 -> 2028 | F3: ='Yearly Model'!R1 -> 2029 | G3: ='Yearly Model'!S1 -> 2030 | H3: ='Yearly Model'!T1 -> 2031 | I3: ='Yearly Model'!U1 -> 2032 | ... L3: ='Yearly Model'!X1 -> 2035
A4: Period | B4: Actual | C4: 1 | D4: 2 | E4: 3 | F4: 4 | G4: 5 | H4: 6 | I4: 7 | J4: 8 | K4: 9 | L4: 10
A5: Revenue growth | C5: =Assumptions!$E$12+(Assumptions!$E$11-Assumptions!$E$12)*(C4-1)/(Assumptions!$B$21-1) -> -0.0442 | D5: =Assumptions!$E$12+(Assumptions!$E$11-Assumptions!$E$12)*(D4-1)/(Assumptions!$B$21-1) -> -0.036511111 | E5: =Assumptions!$E$12+(Assumptions!$E$11-Assumptions!$E$12)*(E4-1)/(Assumptions!$B$21-1) -> -0.028822222 | F5: =Assumptions!$E$12+(Assumptions!$E$11-Assumptions!$E$12)*(F4-1)/(Assumptions!$B$21-1) -> -0.021133333 | G5: =Assumptions!$E$12+(Assumptions!$E$11-Assumptions!$E$12)*(G4-1)/(Assumptions!$B$21-1) -> -0.013444444 | H5: =Assumptions!$E$12+(Assumptions!$E$11-Assumptions!$E$12)*(H4-1)/(Assumptions!$B$21-1) -> -0.0057555556 | I5: =Assumptions!$E$12+(Assumptions!$E$11-Assumptions!$E$12)*(I4-1)/(Assumptions!$B$21-1) -> 0.0019333333 | J5: =Assumptions!$E$12+(Assumptions!$E$11-Assumptions!$E$12)*(J4-1)/(Assumptions!$B$21-1) -> 0.0096222222 | ... L5: =Assumptions!$E$12+(Assumptions!$E$11-Assumptions!$E$12)*(L4-1)/(Assumptions!$B$21-1) -> 0.025
A6: Operating margin | B6: =IFERROR(B8/B7,0) -> -5.0409109 | C6: =Assumptions!$B$18+(Assumptions!$E$13-Assumptions!$B$18)*C4/Assumptions!$B$21 -> -0.89746 | D6: =Assumptions!$B$18+(Assumptions!$E$13-Assumptions!$B$18)*D4/Assumptions!$B$21 -> -0.77552 | E6: =Assumptions!$B$18+(Assumptions!$E$13-Assumptions!$B$18)*E4/Assumptions!$B$21 -> -0.65358 | F6: =Assumptions!$B$18+(Assumptions!$E$13-Assumptions!$B$18)*F4/Assumptions!$B$21 -> -0.53164 | G6: =Assumptions!$B$18+(Assumptions!$E$13-Assumptions!$B$18)*G4/Assumptions!$B$21 -> -0.4097 | H6: =Assumptions!$B$18+(Assumptions!$E$13-Assumptions!$B$18)*H4/Assumptions!$B$21 -> -0.28776 | I6: =Assumptions!$B$18+(Assumptions!$E$13-Assumptions!$B$18)*I4/Assumptions!$B$21 -> -0.16582 | J6: =Assumptions!$B$18+(Assumptions!$E$13-Assumptions!$B$18)*J4/Assumptions!$B$21 -> -0.04388 | ... L6: =Assumptions!$B$18+(Assumptions!$E$13-Assumptions!$B$18)*L4/Assumptions!$B$21 -> 0.2
A7: Revenue | B7: ='Yearly Model'!N2 -> 42.727 | C7: ='Yearly Model'!O2 -> 40.838467 | D7: ='Yearly Model'!P2 -> 39.347409 | E7: ='Yearly Model'!Q2 -> 38.213329 | F7: ='Yearly Model'!R2 -> 37.405754 | G7: ='Yearly Model'!S2 -> 36.902854 | H7: ='Yearly Model'!T2 -> 36.690458 | I7: ='Yearly Model'!U2 -> 36.761393 | ... L7: ='Yearly Model'!X2 -> 38.701564
A8: Operating income | B8: ='Yearly Model'!N8 -> -215.383 | C8: ='Yearly Model'!O8 -> -36.65089 | D8: ='Yearly Model'!P8 -> -30.514702 | E8: ='Yearly Model'!Q8 -> -24.975468 | F8: ='Yearly Model'!R8 -> -19.886395 | G8: ='Yearly Model'!S8 -> -15.119099 | H8: ='Yearly Model'!T8 -> -10.558046 | I8: ='Yearly Model'!U8 -> -6.0957742 | ... L8: ='Yearly Model'!X8 -> 7.7403127
A9: Tax on operating income | C9: =MAX(0,C8)*Assumptions!$E$14 -> 0 | D9: =MAX(0,D8)*Assumptions!$E$14 -> 0 | E9: =MAX(0,E8)*Assumptions!$E$14 -> 0 | F9: =MAX(0,F8)*Assumptions!$E$14 -> 0 | G9: =MAX(0,G8)*Assumptions!$E$14 -> 0 | H9: =MAX(0,H8)*Assumptions!$E$14 -> 0 | I9: =MAX(0,I8)*Assumptions!$E$14 -> 0 | J9: =MAX(0,J8)*Assumptions!$E$14 -> 0 | ... L9: =MAX(0,L8)*Assumptions!$E$14 -> 1.3158532
A10: NOPAT | C10: =C8-C9 -> -36.65089 | D10: =D8-D9 -> -30.514702 | E10: =E8-E9 -> -24.975468 | F10: =F8-F9 -> -19.886395 | G10: =G8-G9 -> -15.119099 | H10: =H8-H9 -> -10.558046 | I10: =I8-I9 -> -6.0957742 | J10: =J8-J9 -> -1.6286114 | ... L10: =L8-L9 -> 6.4244596
A11: Reinvestment | C11: =(C7-B7)*Assumptions!$E$15 -> -0.47213335 | D11: =(D7-C7)*Assumptions!$E$15 -> -0.37276445 | E11: =(E7-D7)*Assumptions!$E$15 -> -0.28351994 | F11: =(F7-E7)*Assumptions!$E$15 -> -0.20189376 | G11: =(G7-F7)*Assumptions!$E$15 -> -0.1257249 | H11: =(H7-G7)*Assumptions!$E$15 -> -0.053099107 | I11: =(I7-H7)*Assumptions!$E$15 -> 0.017733721 | J11: =(J7-I7)*Assumptions!$E$15 -> 0.088431573 | ... L11: =(L7-K7)*Assumptions!$E$15 -> 0.23598514
A12: Free cash flow | C12: =C10-C11 -> -36.178757 | D12: =D10-D11 -> -30.141938 | E12: =E10-E11 -> -24.691948 | F12: =F10-F11 -> -19.684501 | G12: =G10-G11 -> -14.993375 | H12: =H10-H11 -> -10.504947 | I12: =I10-I11 -> -6.1135079 | J12: =J10-J11 -> -1.717043 | ... L12: =L10-L11 -> 6.1884744
A13: Year fraction | C13: =Assumptions!$B$22 -> 0.5041 | D13: 1 | E13: 1 | F13: 1 | G13: 1 | H13: 1 | I13: 1 | J13: 1 | K13: 1 | L13: 1
A14: Discount time (mid-period) | C14: =C13/2 -> 0.25205 | D14: =C14+C13/2+D13/2 -> 1.0041 | E14: =D14+D13/2+E13/2 -> 2.0041 | F14: =E14+E13/2+F13/2 -> 3.0041 | G14: =F14+F13/2+G13/2 -> 4.0041 | H14: =G14+G13/2+H13/2 -> 5.0041 | I14: =H14+H13/2+I13/2 -> 6.0041 | J14: =I14+I13/2+J13/2 -> 7.0041 | K14: =J14+J13/2+K13/2 -> 8.0041 | L14: =K14+K13/2+L13/2 -> 9.0041
A15: Discount factor | C15: =1/(1+Assumptions!$E$10)^C14 -> 0.97074912 | D15: =1/(1+Assumptions!$E$10)^D14 -> 0.88845974 | E15: =1/(1+Assumptions!$E$10)^E14 -> 0.78974199 | F15: =1/(1+Assumptions!$E$10)^F14 -> 0.70199288 | G15: =1/(1+Assumptions!$E$10)^G14 -> 0.62399367 | H15: =1/(1+Assumptions!$E$10)^H14 -> 0.55466104 | I15: =1/(1+Assumptions!$E$10)^I14 -> 0.49303204 | J15: =1/(1+Assumptions!$E$10)^J14 -> 0.4382507 | ... L15: =1/(1+Assumptions!$E$10)^L14 -> 0.34627216
A16: PV of free cash flow | C16: =C12*C13*C15 -> -17.704242 | D16: =D12*D13*D15 -> -26.779898 | E16: =E12*E13*E15 -> -19.500268 | F16: =F12*F13*F15 -> -13.81838 | G16: =G12*G13*G15 -> -9.3557708 | H16: =H12*H13*H15 -> -5.8266849 | I16: =I12*I13*I15 -> -3.0141552 | J16: =J12*J13*J15 -> -0.7524953 | ... L16: =L12*L13*L15 -> 2.1428964
A19: PV of forecast free cash flow | B19: =SUM(C16:L16) -> -93.718596
A20: Terminal free cash flow (year 11) | B20: =L10*(1+Assumptions!$E$11)-L7*Assumptions!$E$11*Assumptions!$E$15 -> 6.3431863
A21: Terminal value | B21: =B20/(Assumptions!$E$10-Assumptions!$E$11) -> 63.431863
A22: PV of terminal value | B22: =B21/(1+Assumptions!$E$10)^(L14+0.5) -> 20.708506
A23: Enterprise value | B23: =B19+B22 -> -73.01009
A24: Cash & investments | B24: =Main!C7 -> 490.6
A25: Debt | B25: =Main!C8 -> 0
A26: Equity value | B26: =B23+B24-B25 -> 417.58991
A27: Shares (mm) | B27: =Main!C4 -> 197.04817
A28: NPV / share | B28: =B26/B27 -> 2.1192275
A29: Price | B29: =Main!C3 -> 3.385
A30: Upside | B30: =B28/B29-1 -> -0.37393575
A31: Terminal value, % of EV | B31: =IFERROR(B22/B23,0) -> -0.28363897
