Workbook

Sheet Main
B2: Zai Lab Ltd
B3: Price | C3: =INDEX([1]Pharma!$F$1:$F$1000,MATCH("ZLAB",[1]Pharma!$B$1:$B$1000,0)) -> 25.08
B4: Shares | C4: =1122.44539/10 -> 112.24454
B5: Market Cap. | C5: =C3*C4 -> 2815.093
B7: Cash | C7: =607.522+10 -> 617.522
B8: Debt | C8: 238.104
B9: Enterprise V. | C9: =C5-C7+C8 -> 2435.675
B11: NPV / Share | C11: =NPV!B28 -> 1.6158726
B12: Upside | C12: =IFERROR(C11/C3-1,"") -> -0.93557127
B13: Cash / Share | C13: =IFERROR((C7-C8)/C4,"") -> 3.3802803
B14: Scenario | C14: =Assumptions!C4 -> Base
B15: Model | C15: DCF

Sheet Yearly Model
B1: 2015 | C1: 2016 | D1: 2017 | E1: 2018 | F1: 2019 | G1: 2020 | H1: 2021 | I1: 2022 | J1: 2023 | K1: 2024 | L1: 2025 | M1: 2026 | N1: 2027 | O1: 2028 | P1: 2029 | Q1: 2030 | R1: 2031 | S1: 2032 | T1: 2033 | U1: 2034 | V1: 2035
A2: Revenue | B2: 0 | C2: 0 | D2: 0 | E2: 0.129 | F2: 12.985 | G2: 48.958 | H2: 144.312 | I2: 215.04 | J2: 266.719 | K2: 398.988 | L2: 460.156 | M2: =L2*(1+NPV!C5) -> 437.7464 | N2: =M2*(1+NPV!D5) -> 420.01281 | O2: =N2*(1+NPV!E5) -> 406.43706 | P2: =O2*(1+NPV!F5) -> 396.62838 | Q2: =P2*(1+NPV!G5) -> 390.30436 | R2: =Q2*(1+NPV!H5) -> 387.27733 | S2: =R2*(1+NPV!I5) -> 387.44515 | T2: =S2*(1+NPV!J5) -> 390.78579 | ... V2: =U2*(1+NPV!L5) -> 407.28922
A3: Cost of Sales | B3: 0 | C3: 0 | D3: 0 | E3: 0.043 | F3: 3.749 | G3: 16.736 | H3: 52.239 | I3: 74.018 | J3: 95.816 | K3: 147.118 | L3: 190.52 | M3: =M2*(1-Assumptions!$B$19) -> 181.22701 | N3: =N2*(1-Assumptions!$B$19) -> 173.8853 | O3: =O2*(1-Assumptions!$B$19) -> 168.26494 | P3: =P2*(1-Assumptions!$B$19) -> 164.20415 | Q3: =Q2*(1-Assumptions!$B$19) -> 161.58601 | R3: =R2*(1-Assumptions!$B$19) -> 160.33282 | S3: =S2*(1-Assumptions!$B$19) -> 160.40229 | T3: =T2*(1-Assumptions!$B$19) -> 161.78532 | ... V3: =V2*(1-Assumptions!$B$19) -> 168.61774
A4: Gross Margin | B4: =B2-B3 -> 0 | C4: =C2-C3 -> 0 | D4: =D2-D3 -> 0 | E4: =E2-E3 -> 0.086 | F4: =F2-F3 -> 9.236 | G4: =G2-G3 -> 32.222 | H4: =H2-H3 -> 92.073 | I4: =I2-I3 -> 141.022 | ... V4: =V2-V3 -> 238.67148
A5: Research & Dev. | B5: 13.587 | C5: 32.149 | D5: 39.342 | E5: 120.278 | F5: 142.221 | G5: 222.711 | H5: 573.306 | I5: 286.408 | J5: 265.868 | K5: 234.504 | L5: 220.904 | M5: =M7*Assumptions!$B$20 -> 212.08661 | N5: =N7*Assumptions!$B$20 -> 188.85716 | O5: =O7*Assumptions!$B$20 -> 168.58841 | P5: =P7*Assumptions!$B$20 -> 150.69719 | Q5: =Q7*Assumptions!$B$20 -> 134.69217 | R5: =R7*Assumptions!$B$20 -> 120.15082 | S5: =S7*Assumptions!$B$20 -> 106.70029 | T5: =T7*Assumptions!$B$20 -> 94.001275 | ... V5: =V7*Assumptions!$B$20 -> 69.582757
A6: SG&A & Other | B6: 2.762 | C6: 6.38 | D6: 12.049 | E6: 21.576 | F6: 70.211 | G6: 111.312 | H6: 218.831 | I6: 258.971 | J6: 271.608 | K6: 299.483 | L6: 278.166 | M6: =M7-M5 -> 267.09687 | N6: =N7-N5 -> 237.84225 | O6: =O7-O5 -> 212.31627 | P6: =P7-P5 -> 189.78448 | Q6: =Q7-Q5 -> 169.62814 | R6: =R7-R5 -> 151.3151 | S6: =S7-S5 -> 134.37583 | T6: =T7-T5 -> 118.38299 | ... V6: =V7-V5 -> 87.630882
A7: Operating Expense | B7: =SUM(B5:B6) -> 16.349 | C7: =SUM(C5:C6) -> 38.529 | D7: =SUM(D5:D6) -> 51.391 | E7: =SUM(E5:E6) -> 141.854 | F7: =SUM(F5:F6) -> 212.432 | G7: =SUM(G5:G6) -> 334.023 | H7: =SUM(H5:H6) -> 792.137 | I7: =SUM(I5:I6) -> 545.379 | ... L7: =SUM(L5:L6) -> 499.07 | M7: =M4-M2*NPV!C6 -> 479.18348 | N7: =N4-N2*NPV!D6 -> 426.69941 | O7: =O4-O2*NPV!E6 -> 380.90469 | P7: =P4-P2*NPV!F6 -> 340.48167 | Q7: =Q4-Q2*NPV!G6 -> 304.32031 | R7: =R4-R2*NPV!H6 -> 271.46592 | S7: =S4-S2*NPV!I6 -> 241.07612 | T7: =T4-T2*NPV!J6 -> 212.38426 | ... V7: =V4-V2*NPV!L6 -> 157.21364
A8: Operating Income | B8: =B4-B7 -> -16.349 | C8: =C4-C7 -> -38.529 | D8: =D4-D7 -> -51.391 | E8: =E4-E7 -> -141.768 | F8: =F4-F7 -> -203.196 | G8: =G4-G7 -> -301.801 | H8: =H4-H7 -> -700.064 | I8: =I4-I7 -> -404.357 | ... V8: =V4-V7 -> 81.457844
A9: Interest & Other | B9: -1.672 | C9: 1.017 | D9: 1.007 | E9: 2.693 | F9: 8.125 | G9: 32.896 | H9: -4.436 | I9: -38.943 | J9: 31.973 | K9: 25.017 | L9: 51.007 | M9: 0 | N9: 0 | O9: 0 | P9: 0 | Q9: 0 | R9: 0 | S9: 0 | T9: 0 | U9: 0 | V9: 0
A10: Pretax | B10: =B8+B9 -> -18.021 | C10: =C8+C9 -> -37.512 | D10: =D8+D9 -> -50.384 | E10: =E8+E9 -> -139.075 | F10: =F8+F9 -> -195.071 | G10: =G8+G9 -> -268.905 | H10: =H8+H9 -> -704.5 | I10: =I8+I9 -> -443.3 | ... V10: =V8+V9 -> 81.457844
A11: Taxes | B11: 0 | C11: 0 | D11: 0 | E11: 0 | F11: 0 | G11: 0 | H11: 0 | I11: 0 | J11: 0 | K11: 0 | L11: -2.927 | M11: =MAX(0,M10)*Assumptions!$E$14 -> 0 | N11: =MAX(0,N10)*Assumptions!$E$14 -> 0 | O11: =MAX(0,O10)*Assumptions!$E$14 -> 0 | P11: =MAX(0,P10)*Assumptions!$E$14 -> 0 | Q11: =MAX(0,Q10)*Assumptions!$E$14 -> 0 | R11: =MAX(0,R10)*Assumptions!$E$14 -> 0 | S11: =MAX(0,S10)*Assumptions!$E$14 -> 0 | T11: =MAX(0,T10)*Assumptions!$E$14 -> 2.824756 | ... V11: =MAX(0,V10)*Assumptions!$E$14 -> 13.847833
A12: Net Income | B12: -18.022 | C12: -37.512 | D12: -50.384 | E12: -139.075 | F12: -195.071 | G12: -268.905 | H12: -704.5 | I12: -443.3 | J12: -334.6 | K12: -257.1 | L12: -175.5 | M12: =M10-M11 -> -222.66409 | N12: =N10-N11 -> -180.57191 | O12: =O10-O11 -> -142.73257 | P12: =P10-P11 -> -108.05744 | Q12: =Q10-Q11 -> -75.601955 | R12: =R10-R11 -> -44.521402 | S12: =S10-S11 -> -14.033264 | T12: =T10-T11 -> 13.791456 | ... V12: =V10-V11 -> 67.610011
A13: Earnings per Share | B13: =IFERROR(B12/B14,0) -> -0.17275028 | C13: =IFERROR(C12/C14,0) -> -0.33117915 | D13: =IFERROR(D12/D14,0) -> -0.19301774 | E13: =IFERROR(E12/E14,0) -> -0.2202931 | F13: =IFERROR(F12/F14,0) -> -0.25254067 | G13: =IFERROR(G12/G14,0) -> -0.34622501 | H13: =IFERROR(H12/H14,0) -> -0.75759124 | I13: =IFERROR(I12/I14,0) -> -0.4627025 | ... V13: =IFERROR(V12/V14,0) -> 0.60234566
A14: Shares | B14: 104.324 | C14: 113.268 | D14: 261.033 | E14: 631.318 | F14: 772.434 | G14: 776.677 | H14: 929.921 | I14: 958.067 | J14: 966.394 | K14: 989.478 | L14: 1095.311 | M14: =Main!$C$4 -> 112.24454 | N14: =Main!$C$4 -> 112.24454 | O14: =Main!$C$4 -> 112.24454 | P14: =Main!$C$4 -> 112.24454 | Q14: =Main!$C$4 -> 112.24454 | R14: =Main!$C$4 -> 112.24454 | S14: =Main!$C$4 -> 112.24454 | T14: =Main!$C$4 -> 112.24454 | ... V14: =Main!$C$4 -> 112.24454
A16: Revenue Change | C16: =IFERROR(C2/B2-1,"") | D16: =IFERROR(D2/C2-1,"") | E16: =IFERROR(E2/D2-1,"") | F16: =IFERROR(F2/E2-1,"") -> 99.658915 | G16: =IFERROR(G2/F2-1,"") -> 2.7703504 | H16: =IFERROR(H2/G2-1,"") -> 1.9476694 | I16: =IFERROR(I2/H2-1,"") -> 0.49010477 | J16: =IFERROR(J2/I2-1,"") -> 0.24032273 | ... V16: =IFERROR(V2/U2-1,"") -> 0.025
A17: Gross Margin | B17: =IFERROR(B4/B2,"") | C17: =IFERROR(C4/C2,"") | D17: =IFERROR(D4/D2,"") | E17: =IFERROR(E4/E2,"") -> 0.66666667 | F17: =IFERROR(F4/F2,"") -> 0.71128225 | G17: =IFERROR(G4/G2,"") -> 0.65815597 | H17: =IFERROR(H4/H2,"") -> 0.63801347 | I17: =IFERROR(I4/I2,"") -> 0.65579427 | ... V17: =IFERROR(V4/V2,"") -> 0.586
A18: Operating Margin | B18: =IFERROR(B8/B2,"") | C18: =IFERROR(C8/C2,"") | D18: =IFERROR(D8/D2,"") | E18: =IFERROR(E8/E2,"") -> -1098.9767 | F18: =IFERROR(F8/F2,"") -> -15.648518 | G18: =IFERROR(G8/G2,"") -> -6.1644879 | H18: =IFERROR(H8/H2,"") -> -4.851045 | I18: =IFERROR(I8/I2,"") -> -1.8803804 | ... V18: =IFERROR(V8/V2,"") -> 0.2
A19: Actual / Estimate | B19: A | C19: A | D19: A | E19: A | F19: A | G19: A | H19: A | I19: A | J19: A | K19: A | L19: A | M19: E | N19: E | O19: E | P19: E | Q19: E | R19: E | S19: E | T19: E | U19: E | V19: E

Sheet Quarterly Model

Sheet Assumptions
A1: Zai Lab Ltd: basic DCF assumptions
A2: Blue = input, black = formula, green = link. $mm unless noted.
A4: Scenario (1 Bear, 2 Base, 3 Bull) | B4: 2 | C4: =CHOOSE($B$4,"Bear","Base","Bull") -> Base
A6: Discount rate override (blank = scenario)
A7: Terminal growth override (blank = scenario)
A9: Parameter | B9: Bear | C9: Base | D9: Bull | E9: Live
A10: Discount rate | B10: 0.12 | C10: 0.11 | D10: 0.1 | E10: =IF(ISNUMBER($B$6),$B$6,CHOOSE($B$4,B10,C10,D10)) -> 0.11
A11: Terminal growth | B11: 0.02 | C11: 0.025 | D11: 0.03 | E11: =IF(ISNUMBER($B$7),$B$7,CHOOSE($B$4,B11,C11,D11)) -> 0.025
A12: Revenue growth, first forecast year | B12: -0.0987 | C12: -0.0487 | D12: 0.0013 | E12: =CHOOSE($B$4,B12,C12,D12) -> -0.0487
A13: Operating margin, year 10 | B13: 0.15 | C13: 0.2 | D13: 0.25 | E13: =CHOOSE($B$4,B13,C13,D13) -> 0.2
A14: Tax rate on operating income | B14: 0.17 | C14: 0.17 | D14: 0.17 | E14: =CHOOSE($B$4,B14,C14,D14) -> 0.17
A15: Reinvestment, % of revenue increase | B15: 0.25 | C15: 0.25 | D15: 0.25 | E15: =CHOOSE($B$4,B15,C15,D15) -> 0.25
A17: Single inputs
A18: Starting operating margin (TTM) | B18: -0.5874
A19: Gross margin (forecast) | B19: 0.586
A20: R&D share of operating expense (forecast) | B20: 0.4426
A21: Forecast years | B21: 10
A22: First forecast year, fraction after balance sheet date | B22: 0.5041
A23: Balance sheet date | B23: 46203
A24: Reporting currency per USD (USD) | B24: 1
A25: Base revenue, FY2025 | B25: ='Yearly Model'!L2 -> 460.156
A27: Scenario summary
A28: Scenario | B28: Enterprise value | C28: Equity value | D28: NPV / share | E28: Upside
A29: Live | B29: =NPV!B23 -> -198.04512 | C29: =NPV!B26 -> 181.37288 | D29: =NPV!B28 -> 1.6158726 | E29: =NPV!B30 -> -0.93557127
A30: 1 | B30: -329.22046 | C30: 50.197539 | D30: 0.44721586 | E30: -0.98216843
A31: 2 | B31: -198.04512 | C31: 181.37288 | D31: 1.6158726 | E31: -0.93557127
A32: 3 | B32: 136.86044 | C32: 516.27844 | D32: 4.5995863 | E32: -0.81660342
A35: NPV / share: discount rate (rows) x terminal growth (columns)
A36: =NPV!B28 -> 1.6158726 | B36: 0.015 | C36: 0.02 | D36: 0.025 | E36: 0.03 | F36: 0.035
A37: 0.09 | B37: 2.2906857 | C37: 2.5982559 | D37: 2.956646 | E37: 3.3786016 | F37: 3.8815038
A38: 0.1 | B38: 1.7008566 | C38: 1.9227535 | D38: 2.1771218 | E38: 2.4709525 | F38: 2.8133881
A39: 0.11 | B39: 1.2653771 | C39: 1.4297448 | D39: 1.6158726 | E39: 1.8278677 | F39: 2.0709326
A40: 0.12 | B40: 0.9382279 | C40: 1.0624303 | D40: 1.2017717 | E40: 1.3587979 | F40: 1.5366539
A41: 0.13 | B41: 0.68954504 | C41: 0.78482329 | D41: 0.89095718 | E41: 1.0095942 | F41: 1.142729

Sheet NPV
A1: Zai Lab Ltd: free-cash-flow DCF ($mm)
A3: Fiscal year | B3: ='Yearly Model'!L1 -> 2025 | C3: ='Yearly Model'!M1 -> 2026 | D3: ='Yearly Model'!N1 -> 2027 | E3: ='Yearly Model'!O1 -> 2028 | F3: ='Yearly Model'!P1 -> 2029 | G3: ='Yearly Model'!Q1 -> 2030 | H3: ='Yearly Model'!R1 -> 2031 | I3: ='Yearly Model'!S1 -> 2032 | ... L3: ='Yearly Model'!V1 -> 2035
A4: Period | B4: Actual | C4: 1 | D4: 2 | E4: 3 | F4: 4 | G4: 5 | H4: 6 | I4: 7 | J4: 8 | K4: 9 | L4: 10
A5: Revenue growth | C5: =Assumptions!$E$12+(Assumptions!$E$11-Assumptions!$E$12)*(C4-1)/(Assumptions!$B$21-1) -> -0.0487 | D5: =Assumptions!$E$12+(Assumptions!$E$11-Assumptions!$E$12)*(D4-1)/(Assumptions!$B$21-1) -> -0.040511111 | E5: =Assumptions!$E$12+(Assumptions!$E$11-Assumptions!$E$12)*(E4-1)/(Assumptions!$B$21-1) -> -0.032322222 | F5: =Assumptions!$E$12+(Assumptions!$E$11-Assumptions!$E$12)*(F4-1)/(Assumptions!$B$21-1) -> -0.024133333 | G5: =Assumptions!$E$12+(Assumptions!$E$11-Assumptions!$E$12)*(G4-1)/(Assumptions!$B$21-1) -> -0.015944444 | H5: =Assumptions!$E$12+(Assumptions!$E$11-Assumptions!$E$12)*(H4-1)/(Assumptions!$B$21-1) -> -0.0077555556 | I5: =Assumptions!$E$12+(Assumptions!$E$11-Assumptions!$E$12)*(I4-1)/(Assumptions!$B$21-1) -> 0.00043333333 | J5: =Assumptions!$E$12+(Assumptions!$E$11-Assumptions!$E$12)*(J4-1)/(Assumptions!$B$21-1) -> 0.0086222222 | ... L5: =Assumptions!$E$12+(Assumptions!$E$11-Assumptions!$E$12)*(L4-1)/(Assumptions!$B$21-1) -> 0.025
A6: Operating margin | B6: =IFERROR(B8/B7,0) -> -0.49860047 | C6: =Assumptions!$B$18+(Assumptions!$E$13-Assumptions!$B$18)*C4/Assumptions!$B$21 -> -0.50866 | D6: =Assumptions!$B$18+(Assumptions!$E$13-Assumptions!$B$18)*D4/Assumptions!$B$21 -> -0.42992 | E6: =Assumptions!$B$18+(Assumptions!$E$13-Assumptions!$B$18)*E4/Assumptions!$B$21 -> -0.35118 | F6: =Assumptions!$B$18+(Assumptions!$E$13-Assumptions!$B$18)*F4/Assumptions!$B$21 -> -0.27244 | G6: =Assumptions!$B$18+(Assumptions!$E$13-Assumptions!$B$18)*G4/Assumptions!$B$21 -> -0.1937 | H6: =Assumptions!$B$18+(Assumptions!$E$13-Assumptions!$B$18)*H4/Assumptions!$B$21 -> -0.11496 | I6: =Assumptions!$B$18+(Assumptions!$E$13-Assumptions!$B$18)*I4/Assumptions!$B$21 -> -0.03622 | J6: =Assumptions!$B$18+(Assumptions!$E$13-Assumptions!$B$18)*J4/Assumptions!$B$21 -> 0.04252 | ... L6: =Assumptions!$B$18+(Assumptions!$E$13-Assumptions!$B$18)*L4/Assumptions!$B$21 -> 0.2
A7: Revenue | B7: ='Yearly Model'!L2 -> 460.156 | C7: ='Yearly Model'!M2 -> 437.7464 | D7: ='Yearly Model'!N2 -> 420.01281 | E7: ='Yearly Model'!O2 -> 406.43706 | F7: ='Yearly Model'!P2 -> 396.62838 | G7: ='Yearly Model'!Q2 -> 390.30436 | H7: ='Yearly Model'!R2 -> 387.27733 | I7: ='Yearly Model'!S2 -> 387.44515 | ... L7: ='Yearly Model'!V2 -> 407.28922
A8: Operating income | B8: ='Yearly Model'!L8 -> -229.434 | C8: ='Yearly Model'!M8 -> -222.66409 | D8: ='Yearly Model'!N8 -> -180.57191 | E8: ='Yearly Model'!O8 -> -142.73257 | F8: ='Yearly Model'!P8 -> -108.05744 | G8: ='Yearly Model'!Q8 -> -75.601955 | H8: ='Yearly Model'!R8 -> -44.521402 | I8: ='Yearly Model'!S8 -> -14.033264 | ... L8: ='Yearly Model'!V8 -> 81.457844
A9: Tax on operating income | C9: =MAX(0,C8)*Assumptions!$E$14 -> 0 | D9: =MAX(0,D8)*Assumptions!$E$14 -> 0 | E9: =MAX(0,E8)*Assumptions!$E$14 -> 0 | F9: =MAX(0,F8)*Assumptions!$E$14 -> 0 | G9: =MAX(0,G8)*Assumptions!$E$14 -> 0 | H9: =MAX(0,H8)*Assumptions!$E$14 -> 0 | I9: =MAX(0,I8)*Assumptions!$E$14 -> 0 | J9: =MAX(0,J8)*Assumptions!$E$14 -> 2.824756 | ... L9: =MAX(0,L8)*Assumptions!$E$14 -> 13.847833
A10: NOPAT | C10: =C8-C9 -> -222.66409 | D10: =D8-D9 -> -180.57191 | E10: =E8-E9 -> -142.73257 | F10: =F8-F9 -> -108.05744 | G10: =G8-G9 -> -75.601955 | H10: =H8-H9 -> -44.521402 | I10: =I8-I9 -> -14.033264 | J10: =J8-J9 -> 13.791456 | ... L10: =L8-L9 -> 67.610011
A11: Reinvestment | C11: =(C7-B7)*Assumptions!$E$15 -> -5.6023993 | D11: =(D7-C7)*Assumptions!$E$15 -> -4.4333983 | E11: =(E7-D7)*Assumptions!$E$15 -> -3.3939368 | F11: =(F7-E7)*Assumptions!$E$15 -> -2.4521703 | G11: =(G7-F7)*Assumptions!$E$15 -> -1.5810048 | H11: =(H7-G7)*Assumptions!$E$15 -> -0.75675679 | I11: =(I7-H7)*Assumptions!$E$15 -> 0.041955045 | J11: =(J7-I7)*Assumptions!$E$15 -> 0.83515956 | ... L11: =(L7-K7)*Assumptions!$E$15 -> 2.4834709
A12: Free cash flow | C12: =C10-C11 -> -217.06169 | D12: =D10-D11 -> -176.13851 | E12: =E10-E11 -> -139.33863 | F12: =F10-F11 -> -105.60527 | G12: =G10-G11 -> -74.02095 | H12: =H10-H11 -> -43.764646 | I12: =I10-I11 -> -14.075219 | J12: =J10-J11 -> 12.956296 | ... L12: =L10-L11 -> 65.12654
A13: Year fraction | C13: =Assumptions!$B$22 -> 0.5041 | D13: 1 | E13: 1 | F13: 1 | G13: 1 | H13: 1 | I13: 1 | J13: 1 | K13: 1 | L13: 1
A14: Discount time (mid-period) | C14: =C13/2 -> 0.25205 | D14: =C14+C13/2+D13/2 -> 1.0041 | E14: =D14+D13/2+E13/2 -> 2.0041 | F14: =E14+E13/2+F13/2 -> 3.0041 | G14: =F14+F13/2+G13/2 -> 4.0041 | H14: =G14+G13/2+H13/2 -> 5.0041 | I14: =H14+H13/2+I13/2 -> 6.0041 | J14: =I14+I13/2+J13/2 -> 7.0041 | K14: =J14+J13/2+K13/2 -> 8.0041 | L14: =K14+K13/2+L13/2 -> 9.0041
A15: Discount factor | C15: =1/(1+Assumptions!$E$10)^C14 -> 0.97403899 | D15: =1/(1+Assumptions!$E$10)^D14 -> 0.90051551 | E15: =1/(1+Assumptions!$E$10)^E14 -> 0.81127523 | F15: =1/(1+Assumptions!$E$10)^F14 -> 0.73087859 | G15: =1/(1+Assumptions!$E$10)^G14 -> 0.65844918 | H15: =1/(1+Assumptions!$E$10)^H14 -> 0.59319746 | I15: =1/(1+Assumptions!$E$10)^I14 -> 0.53441213 | J15: =1/(1+Assumptions!$E$10)^J14 -> 0.48145236 | ... L15: =1/(1+Assumptions!$E$10)^L14 -> 0.39075754
A16: PV of free cash flow | C16: =C12*C13*C15 -> -106.58012 | D16: =D12*D13*D15 -> -158.61546 | E16: =E12*E13*E15 -> -113.04198 | F16: =F12*F13*F15 -> -77.184628 | G16: =G12*G13*G15 -> -48.739034 | H16: =H12*H13*H15 -> -25.961077 | I16: =I12*I13*I15 -> -7.5219675 | J16: =J12*J13*J15 -> 6.2378395 | ... L16: =L12*L13*L15 -> 25.448686
A19: PV of forecast free cash flow | B19: =SUM(C16:L16) -> -489.32388
A20: Terminal free cash flow (year 11) | B20: =L10*(1+Assumptions!$E$11)-L7*Assumptions!$E$11*Assumptions!$E$15 -> 66.754703
A21: Terminal value | B21: =B20/(Assumptions!$E$10-Assumptions!$E$11) -> 785.34945
A22: PV of terminal value | B22: =B21/(1+Assumptions!$E$10)^(L14+0.5) -> 291.27876
A23: Enterprise value | B23: =B19+B22 -> -198.04512
A24: Cash & investments | B24: =Main!C7 -> 617.522
A25: Debt | B25: =Main!C8 -> 238.104
A26: Equity value | B26: =B23+B24-B25 -> 181.37288
A27: Shares (mm) | B27: =Main!C4 -> 112.24454
A28: NPV / share | B28: =B26/B27 -> 1.6158726
A29: Price | B29: =Main!C3 -> 25.08
A30: Upside | B30: =B28/B29-1 -> -0.93557127
A31: Terminal value, % of EV | B31: =IFERROR(B22/B23,0) -> -1.4707697
